Workbook
Name Veh_Type: 'WesternSP-Data'!$G$2:$G$239
Name zones: #REF!
Name Zones_Ndeke: #REF!

Sheet Age
A4: Count of Gender (M/F) | B4: Column Labels | G4: Row Labels | H4: F | I4: M | L4: Age | M4: Female | N4: Male | O4: Grand Total
A5: Row Labels | B5: F | C5: M | D5: (blank) | E5: Grand Total | G5: 20-29 | H5: 151 | I5: 266 | J5: 417 | L5: 20-29 | M5: =H5/$O$11 -> 0.097356544 | N5: =I5/$O$11 -> 0.17150226 | O5: 417
A6: 20-29 | B6: 151 | C6: 266 | E6: 417 | G6: 30-39 | H6: 228 | I6: 475 | J6: 703 | L6: 30-39 | M6: =H6/$O$11 -> 0.14700193 | N6: =I6/$O$11 -> 0.30625403 | O6: 703
A7: 30-39 | B7: 228 | C7: 475 | E7: 703 | G7: 40-49 | H7: 52 | I7: 277 | J7: 329 | L7: 40-49 | M7: =H7/$O$11 -> 0.033526757 | N7: =I7/$O$11 -> 0.17859446 | O7: 329
A8: 40-49 | B8: 52 | C8: 277 | E8: 329 | G8: 50-59 | H8: 14 | I8: 77 | J8: 91 | L8: 50-59 | M8: =H8/$O$11 -> 0.0090264346 | N8: =I8/$O$11 -> 0.04964539 | O8: 91
A9: 50-59 | B9: 14 | C9: 77 | E9: 91 | G9: 60-69 | H9: 3 | I9: 5 | J9: 8 | L9: 60-69 | M9: =H9/$O$11 -> 0.001934236 | N9: =I9/$O$11 -> 0.0032237266 | O9: 8
A10: 60-69 | B10: 3 | C10: 5 | E10: 8 | G10: 70- | H10: 2 | I10: 1 | J10: 3 | L10: 70- | M10: =H10/$O$11 -> 0.0012894907 | N10: =I10/$O$11 -> 0.00064474533 | O10: 3
A11: 70- | B11: 2 | C11: 1 | E11: 3 | L11: Grand Total | M11: =SUM(M5:M10) -> 0.2901354 | N11: =SUM(N5:N10) -> 0.7098646 | O11: =SUM(O5:O10) -> 1551
A12: (blank)
A13: Grand Total | B13: 450 | C13: 1101 | E13: 1551

Sheet Journey P
A3: Count of Gender (M/F) | B3: Column Labels
A4: Row Labels | B4: F | C4: M | D4: (blank) | E4: Grand Total | G4: Journey Purpose | H4: Female | I4: Male | J4: Grand Total | L4: Journey Purpose | M4: Female | N4: Male | O4: Grand Total | R4: Female | S4: Male
A5: Commercial-Commercial | B5: 28 | C5: 99 | E5: 127 | G5: Commercial-Commercial | H5: 28 | I5: 99 | J5: 127 | L5: Commercial | M5: =SUM(H5:H9) -> 37 | N5: =SUM(I5:I9) -> 134 | O5: =SUM(M5:N5) -> 171 | Q5: Commercial | R5: =M5/$O$13 -> 0.024088542 | S5: =N5/$O$13 -> 0.087239583
A6: Commercial-Home | B6: 6 | C6: 24 | E6: 30 | G6: Commercial-Home | H6: 6 | I6: 24 | J6: 30 | L6: Work | M6: =SUM(H37:H43) -> 100 | N6: =SUM(I37:I43) -> 360 | O6: =SUM(M6:N6) -> 460 | Q6: Work | R6: =M6/$O$13 -> 0.065104167 | S6: =N6/$O$13 -> 0.234375
A7: Commercial-Leisure/Social | B7: 2 | E7: 2 | G7: Commercial-Leisure/Social | H7: 2 | J7: 2 | L7: Home | M7: =SUM(H10:H17) -> 247 | N7: =SUM(I10:I17) -> 516 | O7: =SUM(M7:N7) -> 763 | Q7: Home | R7: =M7/$O$13 -> 0.16080729 | S7: =N7/$O$13 -> 0.3359375
A8: Commercial-Study | B8: 1 | C8: 1 | E8: 2 | G8: Commercial-Study | H8: 1 | I8: 1 | J8: 2 | L8: Hospital | M8: =SUM(H18) -> 1 | N8: =SUM(I18) -> 4 | O8: =SUM(M8:N8) -> 5 | Q8: Hospital | R8: =M8/$O$13 -> 0.00065104167 | S8: =N8/$O$13 -> 0.0026041667
A9: Commercial-Work | C9: 10 | E9: 10 | G9: Commercial-Work | I9: 10 | J9: 10 | L9: Leisure | M9: =SUM(H19:H23) -> 18 | N9: =SUM(I19:I23) -> 33 | O9: =SUM(M9:N9) -> 51 | Q9: Leisure | R9: =M9/$O$13 -> 0.01171875 | S9: =N9/$O$13 -> 0.021484375
A10: Home-Commercial | B10: 53 | C10: 88 | E10: 141 | G10: Home-Commercial | H10: 53 | I10: 88 | J10: 141 | L10: Study | M10: =SUM(H30:H33) -> 19 | N10: =SUM(I30:I33) -> 22 | O10: =SUM(M10:N10) -> 41 | Q10: Study | R10: =M10/$O$13 -> 0.012369792 | S10: =N10/$O$13 -> 0.014322917
A11: Home-Home | B11: 8 | C11: 14 | E11: 22 | G11: Home-Home | H11: 8 | I11: 14 | J11: 22 | L11: Tourism | M11: =SUM(H34:H36) -> 4 | N11: =SUM(I34:I36) -> 6 | O11: =SUM(M11:N11) -> 10 | Q11: Tourism | R11: =M11/$O$13 -> 0.0026041667 | S11: =N11/$O$13 -> 0.00390625
A12: Home-Hospital | B12: 9 | C12: 8 | E12: 17 | G12: Home-Hospital | H12: 9 | I12: 8 | J12: 17 | L12: Others | M12: =SUM(H24:H28) -> 21 | N12: =SUM(I24:I28) -> 14 | O12: =SUM(M12:N12) -> 35 | Q12: Others | R12: =M12/$O$13 -> 0.013671875 | S12: =N12/$O$13 -> 0.0091145833
A13: Home-Leisure/Social | B13: 39 | C13: 49 | E13: 88 | G13: Home-Leisure/Social | H13: 39 | I13: 49 | J13: 88 | O13: =SUM(O5:O12) -> 1536
A14: Home-Others | B14: 29 | C14: 23 | E14: 52 | G14: Home-Others | H14: 29 | I14: 23 | J14: 52
A15: Home-Study | B15: 22 | C15: 14 | E15: 36 | G15: Home-Study | H15: 22 | I15: 14 | J15: 36
A16: Home-Tourism | B16: 3 | C16: 15 | E16: 18 | G16: Home-Tourism | H16: 3 | I16: 15 | J16: 18
A17: Home-Work | B17: 84 | C17: 305 | E17: 389 | G17: Home-Work | H17: 84 | I17: 305 | J17: 389
A18: Hospital-Home | B18: 1 | C18: 4 | E18: 5 | G18: Hospital-Home | H18: 1 | I18: 4 | J18: 5
A19: Leisure/Social-Commercial | B19: 1 | C19: 1 | E19: 2 | G19: Leisure/Social-Commercial | H19: 1 | I19: 1 | J19: 2
A20: Leisure/Social-Home | B20: 14 | C20: 28 | E20: 42 | G20: Leisure/Social-Home | H20: 14 | I20: 28 | J20: 42
A21: Leisure/Social-Leisure/Social | B21: 3 | C21: 2 | E21: 5 | G21: Leisure/Social-Leisure/Social | H21: 3 | I21: 2 | J21: 5
A22: Leisure/Social-Others | C22: 1 | E22: 1 | G22: Leisure/Social-Others | I22: 1 | J22: 1
A23: Leisure/Social-Work | C23: 1 | E23: 1 | G23: Leisure/Social-Work | I23: 1 | J23: 1
A24: Others-Home | B24: 16 | C24: 7 | E24: 23 | G24: Others-Home | H24: 16 | I24: 7 | J24: 23
A25: Others-Hospital | C25: 1 | E25: 1 | G25: Others-Hospital | I25: 1 | J25: 1
A26: Others-Leisure/Social | B26: 1 | E26: 1 | G26: Others-Leisure/Social | H26: 1 | J26: 1
A27: Others-Others | B27: 3 | C27: 6 | E27: 9 | G27: Others-Others | H27: 3 | I27: 6 | J27: 9
A28: Others-Study | B28: 1 | E28: 1 | G28: Others-Study | H28: 1 | J28: 1
A29: Others-Work | B29: 3 | C29: 11 | E29: 14 | G29: Others-Work | H29: 3 | I29: 11 | J29: 14
A30: Study-Home | B30: 19 | C30: 16 | E30: 35 | G30: Study-Home | H30: 19 | I30: 16 | J30: 35
A31: Study-Study | C31: 1 | E31: 1 | G31: Study-Study | I31: 1 | J31: 1
A32: Study-Tourism | C32: 2 | E32: 2 | G32: Study-Tourism | I32: 2 | J32: 2
A33: Study-Work | C33: 3 | E33: 3 | G33: Study-Work | I33: 3 | J33: 3
A34: Tourism-Home | B34: 2 | C34: 4 | E34: 6 | G34: Tourism-Home | H34: 2 | I34: 4 | J34: 6
A35: Tourism-Tourism | B35: 1 | C35: 1 | E35: 2 | G35: Tourism-Tourism | H35: 1 | I35: 1 | J35: 2
A36: Tourism-Work | B36: 1 | C36: 1 | E36: 2 | G36: Tourism-Work | H36: 1 | I36: 1 | J36: 2
A37: Work-Commercial | B37: 12 | C37: 30 | E37: 42 | G37: Work-Commercial | H37: 12 | I37: 30 | J37: 42
A38: Work-Home | B38: 58 | C38: 186 | E38: 244 | G38: Work-Home | H38: 58 | I38: 186 | J38: 244
A39: Work-Hospital | B39: 2 | C39: 1 | E39: 3 | G39: Work-Hospital | H39: 2 | I39: 1 | J39: 3
A40: Work-Leisure/Social | B40: 8 | C40: 4 | E40: 12 | G40: Work-Leisure/Social | H40: 8 | I40: 4 | J40: 12
A41: Work-Others | B41: 7 | C41: 38 | E41: 45 | G41: Work-Others | H41: 7 | I41: 38 | J41: 45
A42: Work-Study | B42: 4 | C42: 1 | E42: 5 | G42: Work-Study | H42: 4 | I42: 1 | J42: 5
A43: Work-Work | B43: 9 | C43: 100 | E43: 109 | G43: Work-Work | H43: 9 | I43: 100 | J43: 109
A44: #N/A | C44: 1 | E44: 1 | G44: #N/A | I44: 1 | J44: 1
A45: (blank) | G45: (blank)
A46: Grand Total | B46: 450 | C46: 1101 | E46: 1551

Sheet Dist-Time
A3: Row Labels | B3: Count of Dist Range | F3: Distance (Km) | G3: No. Responses | H3: %ge Responses
A4: 0-10 | B4: 540 | F4: 0-10 | G4: 540 | H4: =G4/$G$12 -> 0.34816248
A5: 100-200 | B5: 229 | F5: 10-20 | G5: 62 | H5: =G5/$G$12 -> 0.03997421
A6: 10-20 | B6: 62 | F6: 20-40 | G6: 92 | H6: =G6/$G$12 -> 0.05931657
A7: 20-40 | B7: 92 | F7: 40-70 | G7: 141 | H7: =G7/$G$12 -> 0.090909091
A8: 40-70 | B8: 141 | F8: 70-100 | G8: 123 | H8: =G8/$G$12 -> 0.079303675
A9: 70-100 | B9: 123 | F9: 100-200 | G9: 229 | H9: =G9/$G$12 -> 0.14764668
A10: Over 200 | B10: 364 | F10: Over 200 | G10: 364 | H10: =G10/$G$12 -> 0.2346873
A11: (blank)
A12: Grand Total | B12: 1551 | F12: Grand Total | G12: =SUM(G4:G10) -> 1551
A15: Row Labels | B15: Count of Time Range
A16: 0.5-1.0 | B16: 123
A17: 0-0.5 | B17: 183
A18: 1.0-2.0 | B18: 223
A19: 2.0-3.5 | B19: 458
A20: Over 3.5 | B20: 564
A21: (blank) | F21: Journey Time (Hours) | G21: No. Responses | H21: %ge Responses
A22: Grand Total | B22: 1551 | F22: 0-0.5 | G22: 183 | H22: =G22/$G$27 -> 0.11798839
F23: 0.5-1.0 | G23: 123 | H23: =G23/$G$27 -> 0.079303675
F24: 1.0-2.0 | G24: 223 | H24: =G24/$G$27 -> 0.14377821
F25: 2.0-3.5 | G25: 458 | H25: =G25/$G$27 -> 0.29529336
F26: Over 3.5 | G26: 564 | H26: =G26/$G$27 -> 0.36363636
F27: Grand Total | G27: =SUM(G22:G26) -> 1551

Sheet Dist-Time Toll
A3: Count of Toll Charge | B3: Column Labels | V3: Potential Expressway Toll Charge (UGX)
A4: Row Labels | B4: 0-1000 | C4: 1000-2000 | D4: 2000-3000 | E4: 3000-5000 | F4: 5000-10000 | G4: Over 10000 | H4: (blank) | I4: Grand Total | K4: Distance (Km) | L4: 0-1000 | M4: 1000-2000 | N4: 2000-3000 | O4: 3000-5000 | P4: 5000-10000 | Q4: Over 10000 | R4: Grand Total | U4: Journey Distance (Km) | V4: 0-1,000 | W4: 1,000-2,000 | X4: 2,000-3,000 | Y4: 3,000-5,000 | Z4: 5,000-10,000 | AA4: Over 10,000
A5: 0-10 | B5: 231 | C5: 118 | D5: 61 | E5: 37 | F5: 49 | G5: 44 | I5: 540 | K5: 0-10 | L5: 231 | M5: 118 | N5: 61 | O5: 37 | P5: 49 | Q5: 44 | R5: 540 | U5: 0-10 | V5: =L5/$R$13 -> 0.14893617 | W5: =M5/$R$13 -> 0.076079948 | X5: =N5/$R$13 -> 0.039329465 | Y5: =O5/$R$13 -> 0.023855577 | Z5: =P5/$R$13 -> 0.031592521 | AA5: =Q5/$R$13 -> 0.028368794
A6: 100-200 | B6: 79 | C6: 54 | D6: 30 | E6: 28 | F6: 32 | G6: 6 | I6: 229 | K6: 10-20 | L6: 25 | M6: 20 | N6: 9 | O6: 3 | P6: 5 | R6: 62 | U6: 10-20 | V6: =L10/$R$13 -> 0.050934881 | W6: =M10/$R$13 -> 0.034816248 | X6: =N10/$R$13 -> 0.01934236 | Y6: =O10/$R$13 -> 0.018052869 | Z6: =P10/$R$13 -> 0.02063185 | AA6: =Q10/$R$13 -> 0.003868472
A7: 10-20 | B7: 25 | C7: 20 | D7: 9 | E7: 3 | F7: 5 | I7: 62 | K7: 20-40 | L7: 33 | M7: 22 | N7: 15 | O7: 7 | P7: 12 | Q7: 3 | R7: 92 | U7: 20-40 | V7: =L6/$R$13 -> 0.016118633 | W7: =M6/$R$13 -> 0.012894907 | X7: =N6/$R$13 -> 0.0058027079 | Y7: =O6/$R$13 -> 0.001934236 | Z7: =P6/$R$13 -> 0.0032237266 | AA7: =Q6/$R$13 -> 0
A8: 20-40 | B8: 33 | C8: 22 | D8: 15 | E8: 7 | F8: 12 | G8: 3 | I8: 92 | K8: 40-70 | L8: 55 | M8: 36 | N8: 19 | O8: 9 | P8: 20 | Q8: 2 | R8: 141 | U8: 40-70 | V8: =L7/$R$13 -> 0.021276596 | W8: =M7/$R$13 -> 0.014184397 | X8: =N7/$R$13 -> 0.0096711799 | Y8: =O7/$R$13 -> 0.0045132173 | Z8: =P7/$R$13 -> 0.0077369439 | AA8: =Q7/$R$13 -> 0.001934236
A9: 40-70 | B9: 55 | C9: 36 | D9: 19 | E9: 9 | F9: 20 | G9: 2 | I9: 141 | K9: 70-100 | L9: 42 | M9: 31 | N9: 18 | O9: 11 | P9: 19 | Q9: 2 | R9: 123 | U9: 70-100 | V9: =L8/$R$13 -> 0.035460993 | W9: =M8/$R$13 -> 0.023210832 | X9: =N8/$R$13 -> 0.012250161 | Y9: =O8/$R$13 -> 0.0058027079 | Z9: =P8/$R$13 -> 0.012894907 | AA9: =Q8/$R$13 -> 0.0012894907
A10: 70-100 | B10: 42 | C10: 31 | D10: 18 | E10: 11 | F10: 19 | G10: 2 | I10: 123 | K10: 100-200 | L10: 79 | M10: 54 | N10: 30 | O10: 28 | P10: 32 | Q10: 6 | R10: 229 | U10: 100-150 | V10: =L9/$R$13 -> 0.027079304 | W10: =M9/$R$13 -> 0.019987105 | X10: =N9/$R$13 -> 0.011605416 | Y10: =O9/$R$13 -> 0.0070921986 | Z10: =P9/$R$13 -> 0.012250161 | AA10: =Q9/$R$13 -> 0.0012894907
A11: Over 200 | B11: 140 | C11: 60 | D11: 58 | E11: 47 | F11: 48 | G11: 11 | I11: 364 | K11: Over 200 | L11: 140 | M11: 60 | N11: 58 | O11: 47 | P11: 48 | Q11: 11 | R11: 364 | U11: Over 150 | V11: =L11/$R$13 -> 0.090264346 | W11: =M11/$R$13 -> 0.03868472 | X11: =N11/$R$13 -> 0.037395229 | Y11: =O11/$R$13 -> 0.03030303 | Z11: =P11/$R$13 -> 0.030947776 | AA11: =Q11/$R$13 -> 0.0070921986
A12: (blank)
A13: Grand Total | B13: 605 | C13: 341 | D13: 210 | E13: 142 | F13: 185 | G13: 68 | I13: 1551 | K13: Grand Total | L13: =SUM(L5:L11) -> 605 | M13: =SUM(M5:M11) -> 341 | N13: =SUM(N5:N11) -> 210 | O13: =SUM(O5:O11) -> 142 | P13: =SUM(P5:P11) -> 185 | Q13: =SUM(Q5:Q11) -> 68 | R13: =SUM(R5:R11) -> 1551
A16: Count of Toll Charge | B16: Column Labels
A17: Row Labels | B17: 0-1000 | C17: 1000-2000 | D17: 2000-3000 | E17: 3000-5000 | F17: 5000-10000 | G17: Over 10000 | H17: (blank) | I17: Grand Total
A18: 0.5-1.0 | B18: 53 | C18: 38 | D18: 19 | E18: 2 | F18: 10 | G18: 1 | I18: 123
A19: 0-0.5 | B19: 88 | C19: 55 | D19: 22 | E19: 6 | F19: 9 | G19: 3 | I19: 183
A20: 1.0-2.0 | B20: 86 | C20: 60 | D20: 27 | E20: 19 | F20: 26 | G20: 5 | I20: 223
A21: 2.0-3.5 | B21: 167 | C21: 100 | D21: 64 | E21: 48 | F21: 58 | G21: 21 | I21: 458
A22: Over 3.5 | B22: 211 | C22: 88 | D22: 78 | E22: 67 | F22: 82 | G22: 38 | I22: 564
A23: (blank)
A24: Grand Total | B24: 605 | C24: 341 | D24: 210 | E24: 142 | F24: 185 | G24: 68 | I24: 1551

Sheet Income-Toll
A3: Count of Toll Charge | B3: Column Labels | U3: Potential Expressway Toll Charge (UGX)
A4: Row Labels | B4: 0-1000 | C4: 1000-2000 | D4: 2000-3000 | E4: 3000-5000 | F4: 5000-10000 | G4: Over 10000 | H4: (blank) | I4: Grand Total | K4: Income (UGX) | L4: 0-1000 | M4: 1000-2000 | N4: 2000-3000 | O4: 3000-5000 | P4: 5000-10000 | Q4: Over 10000 | R4: Grand Total | T4: Income (UGX) | U4: 0-1,000 | V4: 1,000-2,000 | W4: 2,000-3,000 | X4: 3,000-5,000 | Y4: 5,000-10,000 | Z4: Over 10,000
A5: <300,000 | B5: 294 | C5: 121 | D5: 35 | E5: 26 | F5: 39 | G5: 13 | I5: 528 | K5: <300,000 | L5: 294 | M5: 121 | N5: 35 | O5: 26 | P5: 39 | Q5: 13 | R5: 528 | T5: <300,000 | U5: =L5/$R$12 -> 0.200409 | V5: =M5/$R$12 -> 0.082481254 | W5: =N5/$R$12 -> 0.023858214 | X5: =O5/$R$12 -> 0.017723245 | Y5: =P5/$R$12 -> 0.026584867 | Z5: =Q5/$R$12 -> 0.0088616224
A6: >1,000,000 | B6: 23 | C6: 10 | D6: 9 | E6: 11 | F6: 17 | G6: 14 | I6: 84 | K6: 300,000-500,000 | L6: 154 | M6: 118 | N6: 91 | O6: 39 | P6: 41 | Q6: 10 | R6: 453 | T6: 300,000-500,000 | U6: =L9/$R$12 -> 0.015678255 | V6: =M9/$R$12 -> 0.0068166326 | W6: =N9/$R$12 -> 0.0061349693 | X6: =O9/$R$12 -> 0.0074982958 | Y6: =P9/$R$12 -> 0.011588275 | Z6: =Q9/$R$12 -> 0.0095432856
A7: 300,000-500,000 | B7: 154 | C7: 118 | D7: 91 | E7: 39 | F7: 41 | G7: 10 | I7: 453 | K7: 500,000-750,000 | L7: 75 | M7: 59 | N7: 51 | O7: 32 | P7: 49 | Q7: 14 | R7: 280 | T7: 500,000-750,000 | U7: =L6/$R$12 -> 0.10497614 | V7: =M6/$R$12 -> 0.080436264 | W7: =N6/$R$12 -> 0.062031357 | X7: =O6/$R$12 -> 0.026584867 | Y7: =P6/$R$12 -> 0.027948194 | Z7: =Q6/$R$12 -> 0.0068166326
A8: 500,000-750,000 | B8: 75 | C8: 59 | D8: 51 | E8: 32 | F8: 49 | G8: 14 | I8: 280 | K8: 750,000-1,000,000 | L8: 59 | M8: 33 | N8: 24 | O8: 34 | P8: 39 | Q8: 17 | R8: 206 | T8: 750,000-1,000,000 | U8: =L7/$R$12 -> 0.051124744 | V8: =M7/$R$12 -> 0.040218132 | W8: =N7/$R$12 -> 0.034764826 | X8: =O7/$R$12 -> 0.021813224 | Y8: =P7/$R$12 -> 0.0334015 | Z8: =Q7/$R$12 -> 0.0095432856
A9: 750,000-1,000,000 | B9: 59 | C9: 33 | D9: 24 | E9: 34 | F9: 39 | G9: 17 | I9: 206 | K9: >1,000,000 | L9: 23 | M9: 10 | N9: 9 | O9: 11 | P9: 17 | Q9: 14 | R9: 84 | T9: >1,000,000 | U9: =L8/$R$12 -> 0.040218132 | V9: =M8/$R$12 -> 0.022494888 | W9: =N8/$R$12 -> 0.016359918 | X9: =O8/$R$12 -> 0.023176551 | Y9: =P8/$R$12 -> 0.026584867 | Z9: =Q8/$R$12 -> 0.011588275
A10: (blank) | T10: Totals | U10: =SUM(U5:U9) -> 0.41240627 | V10: =SUM(V5:V9) -> 0.23244717 | W10: =SUM(W5:W9) -> 0.14314928 | X10: =SUM(X5:X9) -> 0.096796183 | Y10: =SUM(Y5:Y9) -> 0.1261077 | Z10: =SUM(Z5:Z9) -> 0.046353102
A11: Grand Total | B11: 605 | C11: 341 | D11: 210 | E11: 142 | F11: 185 | G11: 68 | I11: 1551
K12: Grand Total | L12: 387 | M12: 256 | N12: 175 | O12: 66 | P12: 55 | Q12: 29 | R12: =SUM(R5:R8) -> 1467

Sheet Veh-Toll
A3: Count of Toll Charge | B3: Column Labels | U3: Potential Expressway Toll Charge (UGX)
A4: Row Labels | B4: 0-1000 | C4: 1000-2000 | D4: 2000-3000 | E4: 3000-5000 | F4: 5000-10000 | G4: Over 10000 | H4: (blank) | I4: Grand Total | K4: Vehicle Type | L4: 0-1000 | M4: 1000-2000 | N4: 2000-3000 | O4: 3000-5000 | P4: 5000-10000 | Q4: Over 10000 | R4: Grand Total | T4: Vehicle Type | U4: 0-1,000 | V4: 1,000-2,000 | W4: 2,000-3,00 | X4: 3,000-5,000 | Y4: 5,000-10,000 | Z4: Over 10,000
A5: Bicycle | E5: 1 | I5: 1 | K5: Car | L5: 75 | M5: 54 | N5: 24 | O5: 8 | P5: 17 | Q5: 7 | R5: 185 | S5: 185 | T5: Car | U5: =L5/$R$15 -> 0.051020408 | V5: =M5/$R$15 -> 0.036734694 | W5: =N5/$R$15 -> 0.016326531 | X5: =O5/$R$15 -> 0.0054421769 | Y5: =P5/$R$15 -> 0.011564626 | Z5: =Q5/$R$15 -> 0.0047619048
A6: Bicycles | B6: 44 | C6: 24 | D6: 7 | F6: 3 | G6: 1 | I6: 79 | K6: Heavy truck | L6: 1 | N6: 1 | P6: 3 | Q6: 1 | R6: 6 | S6: 6 | T6: Heavy truck | U6: =L6/$R$15 -> 0.00068027211 | V6: =M6/$R$15 -> 0 | W6: =N6/$R$15 -> 0.00068027211 | X6: =O6/$R$15 -> 0 | Y6: =P6/$R$15 -> 0.0020408163 | Z6: =Q6/$R$15 -> 0.00068027211
A7: Bicylces | G7: 1 | I7: 1 | K7: Large Bus | L7: 144 | M7: 68 | N7: 66 | O7: 43 | P7: 59 | Q7: 17 | R7: 397 | S7: 397 | T7: Large Bus | U7: =L7/$R$15 -> 0.097959184 | V7: =M7/$R$15 -> 0.046258503 | W7: =N7/$R$15 -> 0.044897959 | X7: =O7/$R$15 -> 0.029251701 | Y7: =P7/$R$15 -> 0.040136054 | Z7: =Q7/$R$15 -> 0.011564626
A8: Car | B8: 75 | C8: 54 | D8: 24 | E8: 8 | F8: 17 | G8: 7 | I8: 185 | K8: Light Truck | L8: 1 | M8: 4 | N8: 2 | O8: 1 | P8: 2 | R8: 10 | S8: 10 | T8: Light Truck | U8: =L8/$R$15 -> 0.00068027211 | V8: =M8/$R$15 -> 0.0027210884 | W8: =N8/$R$15 -> 0.0013605442 | X8: =O8/$R$15 -> 0.00068027211 | Y8: =P8/$R$15 -> 0.0013605442 | Z8: =Q8/$R$15 -> 0
A9: Heavy truck | B9: 1 | D9: 1 | F9: 3 | G9: 1 | I9: 6 | K9: Medium bus | L9: 9 | M9: 4 | N9: 5 | O9: 6 | P9: 3 | Q9: 3 | R9: 30 | S9: 30 | T9: Medium bus | U9: =L9/$R$15 -> 0.006122449 | V9: =M9/$R$15 -> 0.0027210884 | W9: =N9/$R$15 -> 0.0034013605 | X9: =O9/$R$15 -> 0.0040816327 | Y9: =P9/$R$15 -> 0.0020408163 | Z9: =Q9/$R$15 -> 0.0020408163
A10: Large Bus | B10: 144 | C10: 68 | D10: 66 | E10: 43 | F10: 59 | G10: 17 | I10: 397 | K10: Medium Truck | L10: 1 | P10: 2 | R10: 3 | S10: 3 | T10: Medium Truck | U10: =L10/$R$15 -> 0.00068027211 | V10: =M10/$R$15 -> 0 | W10: =N10/$R$15 -> 0 | X10: =O10/$R$15 -> 0 | Y10: =P10/$R$15 -> 0.0013605442 | Z10: =Q10/$R$15 -> 0
A11: Light Truck | B11: 1 | C11: 4 | D11: 2 | E11: 1 | F11: 2 | I11: 10 | K11: Minibus | L11: 302 | M11: 164 | N11: 94 | O11: 81 | P11: 86 | Q11: 32 | R11: 759 | S11: 759 | T11: Minibus | U11: =L11/$R$15 -> 0.20544218 | V11: =M11/$R$15 -> 0.11156463 | W11: =N11/$R$15 -> 0.063945578 | X11: =O11/$R$15 -> 0.055102041 | Y11: =P11/$R$15 -> 0.058503401 | Z11: =Q11/$R$15 -> 0.021768707
A12: Medium bus | B12: 9 | C12: 4 | D12: 5 | E12: 6 | F12: 3 | G12: 3 | I12: 30 | K12: Pickups | L12: 5 | M12: 5 | N12: 1 | P12: 3 | R12: 14 | S12: 14 | T12: Pickups | U12: =L12/$R$15 -> 0.0034013605 | V12: =M12/$R$15 -> 0.0034013605 | W12: =N12/$R$15 -> 0.00068027211 | X12: =O12/$R$15 -> 0 | Y12: =P12/$R$15 -> 0.0020408163 | Z12: =Q12/$R$15 -> 0
A13: Medium Truck | B13: 1 | F13: 2 | I13: 3 | K13: Station Wagon | L13: 23 | M13: 18 | N13: 10 | O13: 2 | P13: 7 | Q13: 6 | R13: 66 | S13: 66 | T13: Station Wagon | U13: =L13/$R$15 -> 0.015646259 | V13: =M13/$R$15 -> 0.012244898 | W13: =N13/$R$15 -> 0.0068027211 | X13: =O13/$R$15 -> 0.0013605442 | Y13: =P13/$R$15 -> 0.0047619048 | Z13: =Q13/$R$15 -> 0.0040816327
A14: Minibus | B14: 302 | C14: 164 | D14: 94 | E14: 81 | F14: 86 | G14: 32 | I14: 759 | K14: Truck Trailer | T14: Truck Trailer | U14: =L14/$R$15 -> 0 | V14: =M14/$R$15 -> 0 | W14: =N14/$R$15 -> 0 | X14: =O14/$R$15 -> 0 | Y14: =P14/$R$15 -> 0 | Z14: =Q14/$R$15 -> 0
A15: Pickups | B15: 5 | C15: 5 | D15: 1 | F15: 3 | I15: 14 | R15: =SUM(R5:R14) -> 1470
A16: Station Wagon | B16: 23 | C16: 18 | D16: 10 | E16: 2 | F16: 7 | G16: 6 | I16: 66
A17: (blank)
A18: Grand Total | B18: 605 | C18: 341 | D18: 210 | E18: 142 | F18: 185 | G18: 68 | I18: 1551

Sheet WesternSP-Data
A1: Date | B1: Time (24-h format) | C1: Veh_Reg_No. | D1: Driver or Passenger? D/P | E1: Mode No. | F1: Mode Description | G1: Veh_Type | H1: Veh_Type Desc | I1: Gender (M/F) | J1: Age Bracket No. | K1: Age Bracket Desc. | L1: Or Village | M1: Or District | N1: Or Country | O1: Origin_Purpose | P1: Origin-Purpose Desc | Q1: Dest Village | R1: Dest District | S1: Des Country | T1: Dest_Purpose | U1: Dest_Purpose Desc | V1: Journey_Purpose | W1: Cost of Trip (UGX) | X1: Journey Dist (Km) | Y1: Dist Range | Z1: Journey Time (Hrs) | AA1: Time Range | AB1: Profession No. | AC1: Profession Desc. | AD1: Monthly Income No. | AE1: Monthly Income | AF1: Journey Time | AG1: Cost of Journey | AH1: Comfort | AI1: Safety | AJ1: Reliability | AK1: Would You Use Xpressways? Y/N | AL1: Pay How Much? (UGX) | AM1: Toll Charge
A2: 43762 | B2: 0.73472222 | D2: P | E2: 2 | F2: =VLOOKUP(E2,Key!$A$17:$B$21,2,FALSE) -> Road Vehicle | G2: 1 | H2: =VLOOKUP(G2,Key!$A$2:$B$13,2,FALSE) -> Car | I2: M | J2: 1 | K2: =VLOOKUP(J2,Key!$A$24:$B$29,2,FALSE) -> 20-29 | L2: NANSANA | M2: WAKISO | N2: UG | O2: 1 | P2: =VLOOKUP(O2,Key!$E$2:$F$9,2,FALSE) -> Home | Q2: HIOMA | R2: HIOMA | S2: UG | T2: 4 | U2: =VLOOKUP(T2,Key!$E$2:$F$9,2,FALSE) -> Commercial | V2: =P2&"-"&U2 -> Home-Commercial | W2: 13000 | Y2: =IF(X2<10,"0-10",IF(X2<20,"10-20",IF(X2<40,"20-40",IF(X2<70,"40-70",IF(X2<100,"70-100",IF(X2<200,"100-200","Over 200")))))) -> 0-10 | Z2: 3 | AA2: =IF(Z2<0.5,"0-0.5",IF(Z2<1,"0.5-1.0",IF(Z2<2,"1.0-2.0",IF(Z2<3.5,"2.0-3.5","Over 3.5")))) -> 2.0-3.5 | AB2: 6 | AC2: =VLOOKUP(AB2,Key!$C$20:$D$29,2,FALSE) -> Businessman | AD2: 4 | AE2: =VLOOKUP(AD2,Key!$E$20:$F$24,2,FALSE) -> 750,000-1,000,000 | AF2: 2 | AG2: 3 | AH2: 4 | AI2: 1 | AJ2: 5 | AK2: Y | AL2: 3000 | AM2: =IF(AL2<1000,"0-1000",IF(AL2<2000,"1000-2000",IF(AL2<3000,"2000-3000",IF(AL2<5000,"3000-5000",IF(AL2<10000,"5000-10000","Over 10000"))))) -> 3000-5000
A3: 43763 | B3: 0.69166667 | D3: D | E3: 2 | F3: =VLOOKUP(E3,Key!$A$17:$B$21,2,FALSE) -> Road Vehicle | G3: 1 | H3: =VLOOKUP(G3,Key!$A$2:$B$13,2,FALSE) -> Car | I3: M | J3: 1 | K3: =VLOOKUP(J3,Key!$A$24:$B$29,2,FALSE) -> 20-29 | L3: HIOMA | M3: HIOMA | N3: UG | O3: 1 | P3: =VLOOKUP(O3,Key!$E$2:$F$9,2,FALSE) -> Home | Q3: BUKWIRI | R3: KYANKWENZI | S3: UG | T3: 2 | U3: =VLOOKUP(T3,Key!$E$2:$F$9,2,FALSE) -> Work | V3: =P3&"-"&U3 -> Home-Work | W3: 65000 | X3: 75 | Y3: =IF(X3<10,"0-10",IF(X3<20,"10-20",IF(X3<40,"20-40",IF(X3<70,"40-70",IF(X3<100,"70-100",IF(X3<200,"100-200","Over 200")))))) -> 70-100 | Z3: 1 | AA3: =IF(Z3<0.5,"0-0.5",IF(Z3<1,"0.5-1.0",IF(Z3<2,"1.0-2.0",IF(Z3<3.5,"2.0-3.5","Over 3.5")))) -> 1.0-2.0 | AB3: 5 | AC3: =VLOOKUP(AB3,Key!$C$20:$D$29,2,FALSE) -> Professional | AD3: 3 | AE3: =VLOOKUP(AD3,Key!$E$20:$F$24,2,FALSE) -> 500,000-750,000 | AF3: 2 | AG3: 1 | AH3: 1 | AI3: 1 | AJ3: 2 | AK3: Y | AL3: 2000 | AM3: =IF(AL3<1000,"0-1000",IF(AL3<2000,"1000-2000",IF(AL3<3000,"2000-3000",IF(AL3<5000,"3000-5000",IF(AL3<10000,"5000-10000","Over 10000"))))) -> 2000-3000
A4: 43763 | B4: 0.52916667 | D4: D | E4: 2 | F4: =VLOOKUP(E4,Key!$A$17:$B$21,2,FALSE) -> Road Vehicle | G4: 1 | H4: =VLOOKUP(G4,Key!$A$2:$B$13,2,FALSE) -> Car | I4: M | J4: 1 | K4: =VLOOKUP(J4,Key!$A$24:$B$29,2,FALSE) -> 20-29 | L4: HIOMA | M4: HIOMA | N4: UG | O4: 1 | P4: =VLOOKUP(O4,Key!$E$2:$F$9,2,FALSE) -> Home | Q4: KABAALE | R4: HIOMA | S4: UG | T4: 2 | U4: =VLOOKUP(T4,Key!$E$2:$F$9,2,FALSE) -> Work | V4: =P4&"-"&U4 -> Home-Work | W4: 50000 | Y4: =IF(X4<10,"0-10",IF(X4<20,"10-20",IF(X4<40,"20-40",IF(X4<70,"40-70",IF(X4<100,"70-100",IF(X4<200,"100-200","Over 200")))))) -> 0-10 | Z4: 2 | AA4: =IF(Z4<0.5,"0-0.5",IF(Z4<1,"0.5-1.0",IF(Z4<2,"1.0-2.0",IF(Z4<3.5,"2.0-3.5","Over 3.5")))) -> 2.0-3.5 | AB4: 2 | AC4: =VLOOKUP(AB4,Key!$C$20:$D$29,2,FALSE) -> Manual Labour | AD4: 1 | AE4: =VLOOKUP(AD4,Key!$E$20:$F$24,2,FALSE) -> <300,000 | AF4: 3 | AG4: 4 | AH4: 5 | AI4: 1 | AJ4: 2 | AK4: Y | AL4: 5000 | AM4: =IF(AL4<1000,"0-1000",IF(AL4<2000,"1000-2000",IF(AL4<3000,"2000-3000",IF(AL4<5000,"3000-5000",IF(AL4<10000,"5000-10000","Over 10000"))))) -> 5000-10000
A5: 43763 | B5: 0.57916667 | D5: D | E5: 2 | F5: =VLOOKUP(E5,Key!$A$17:$B$21,2,FALSE) -> Road Vehicle | G5: 1 | H5: =VLOOKUP(G5,Key!$A$2:$B$13,2,FALSE) -> Car | I5: M | J5: 1 | K5: =VLOOKUP(J5,Key!$A$24:$B$29,2,FALSE) -> 20-29 | L5: HIOMA | M5: HIOMA | N5: UG | O5: 1 | P5: =VLOOKUP(O5,Key!$E$2:$F$9,2,FALSE) -> Home | Q5: BULIISA | R5: BULIISA | S5: UG | T5: 2 | U5: =VLOOKUP(T5,Key!$E$2:$F$9,2,FALSE) -> Work | V5: =P5&"-"&U5 -> Home-Work | W5: 80000 | X5: 75 | Y5: =IF(X5<10,"0-10",IF(X5<20,"10-20",IF(X5<40,"20-40",IF(X5<70,"40-70",IF(X5<100,"70-100",IF(X5<200,"100-200","Over 200")))))) -> 70-100 | Z5: 2 | AA5: =IF(Z5<0.5,"0-0.5",IF(Z5<1,"0.5-1.0",IF(Z5<2,"1.0-2.0",IF(Z5<3.5,"2.0-3.5","Over 3.5")))) -> 2.0-3.5 | AB5: 5 | AC5: =VLOOKUP(AB5,Key!$C$20:$D$29,2,FALSE) -> Professional | AD5: 4 | AE5: =VLOOKUP(AD5,Key!$E$20:$F$24,2,FALSE) -> 750,000-1,000,000 | AF5: 1 | AG5: 1 | AH5: 1 | AI5: 1 | AJ5: 1 | AK5: Y | AM5: =IF(AL5<1000,"0-1000",IF(AL5<2000,"1000-2000",IF(AL5<3000,"2000-3000",IF(AL5<5000,"3000-5000",IF(AL5<10000,"5000-10000","Over 10000"))))) -> 0-1000
A6: 43763 | B6: 0.33402778 | D6: D | E6: 2 | F6: =VLOOKUP(E6,Key!$A$17:$B$21,2,FALSE) -> Road Vehicle | G6: 1 | H6: =VLOOKUP(G6,Key!$A$2:$B$13,2,FALSE) -> Car | I6: M | J6: 1 | K6: =VLOOKUP(J6,Key!$A$24:$B$29,2,FALSE) -> 20-29 | L6: HIOMA | M6: HIOMA | N6: UG | O6: 2 | P6: =VLOOKUP(O6,Key!$E$2:$F$9,2,FALSE) -> Work | Q6: KAMPALA | R6: KAMPALA | S6: UG | T6: 2 | U6: =VLOOKUP(T6,Key!$E$2:$F$9,2,FALSE) -> Work | V6: =P6&"-"&U6 -> Work-Work | W6: 100000 | X6: 175 | Y6: =IF(X6<10,"0-10",IF(X6<20,"10-20",IF(X6<40,"20-40",IF(X6<70,"40-70",IF(X6<100,"70-100",IF(X6<200,"100-200","Over 200")))))) -> 100-200 | Z6: 3 | AA6: =IF(Z6<0.5,"0-0.5",IF(Z6<1,"0.5-1.0",IF(Z6<2,"1.0-2.0",IF(Z6<3.5,"2.0-3.5","Over 3.5")))) -> 2.0-3.5 | AB6: 5 | AC6: =VLOOKUP(AB6,Key!$C$20:$D$29,2,FALSE) -> Professional | AD6: 4 | AE6: =VLOOKUP(AD6,Key!$E$20:$F$24,2,FALSE) -> 750,000-1,000,000 | AF6: 1 | AG6: 3 | AH6: 5 | AI6: 4 | AJ6: 2 | AK6: Y | AL6: 5000 | AM6: =IF(AL6<1000,"0-1000",IF(AL6<2000,"1000-2000",IF(AL6<3000,"2000-3000",IF(AL6<5000,"3000-5000",IF(AL6<10000,"5000-10000","Over 10000"))))) -> 5000-10000
A7: 43763 | B7: 0.75347222 | D7: P | E7: 2 | F7: =VLOOKUP(E7,Key!$A$17:$B$21,2,FALSE) -> Road Vehicle | G7: 1 | H7: =VLOOKUP(G7,Key!$A$2:$B$13,2,FALSE) -> Car | I7: M | J7: 1 | K7: =VLOOKUP(J7,Key!$A$24:$B$29,2,FALSE) -> 20-29 | L7: HIOMA | M7: HIOMA | N7: UG | O7: 4 | P7: =VLOOKUP(O7,Key!$E$2:$F$9,2,FALSE) -> Commercial | Q7: ARUA | R7: ARUA | S7: UG | T7: 1 | U7: =VLOOKUP(T7,Key!$E$2:$F$9,2,FALSE) -> Home | V7: =P7&"-"&U7 -> Commercial-Home | W7: 350000 | X7: 390 | Y7: =IF(X7<10,"0-10",IF(X7<20,"10-20",IF(X7<40,"20-40",IF(X7<70,"40-70",IF(X7<100,"70-100",IF(X7<200,"100-200","Over 200")))))) -> Over 200 | Z7: 8 | AA7: =IF(Z7<0.5,"0-0.5",IF(Z7<1,"0.5-1.0",IF(Z7<2,"1.0-2.0",IF(Z7<3.5,"2.0-3.5","Over 3.5")))) -> Over 3.5 | AB7: 5 | AC7: =VLOOKUP(AB7,Key!$C$20:$D$29,2,FALSE) -> Professional | AD7: 3 | AE7: =VLOOKUP(AD7,Key!$E$20:$F$24,2,FALSE) -> 500,000-750,000 | AF7: 3 | AG7: 2 | AH7: 1 | AI7: 5 | AJ7: 4 | AK7: Y | AL7: 7000 | AM7: =IF(AL7<1000,"0-1000",IF(AL7<2000,"1000-2000",IF(AL7<3000,"2000-3000",IF(AL7<5000,"3000-5000",IF(AL7<10000,"5000-10000","Over 10000"))))) -> 5000-10000
A8: 43763 | B8: 0.66180556 | D8: D | E8: 2 | F8: =VLOOKUP(E8,Key!$A$17:$B$21,2,FALSE) -> Road Vehicle | G8: 1 | H8: =VLOOKUP(G8,Key!$A$2:$B$13,2,FALSE) -> Car | I8: M | J8: 1 | K8: =VLOOKUP(J8,Key!$A$24:$B$29,2,FALSE) -> 20-29 | L8: HIOMA | M8: HIOMA | N8: UG | O8: 4 | P8: =VLOOKUP(O8,Key!$E$2:$F$9,2,FALSE) -> Commercial | Q8: KIBOGA | R8: KIBOGA | S8: UG | T8: 1 | U8: =VLOOKUP(T8,Key!$E$2:$F$9,2,FALSE) -> Home | V8: =P8&"-"&U8 -> Commercial-Home | W8: 70000 | X8: 115 | Y8: =IF(X8<10,"0-10",IF(X8<20,"10-20",IF(X8<40,"20-40",IF(X8<70,"40-70",IF(X8<100,"70-100",IF(X8<200,"100-200","Over 200")))))) -> 100-200 | Z8: 1 | AA8: =IF(Z8<0.5,"0-0.5",IF(Z8<1,"0.5-1.0",IF(Z8<2,"1.0-2.0",IF(Z8<3.5,"2.0-3.5","Over 3.5")))) -> 1.0-2.0 | AB8: 5 | AC8: =VLOOKUP(AB8,Key!$C$20:$D$29,2,FALSE) -> Professional | AD8: 3 | AE8: =VLOOKUP(AD8,Key!$E$20:$F$24,2,FALSE) -> 500,000-750,000 | AF8: 1 | AG8: 1 | AH8: 2 | AI8: 1 | AJ8: 1 | AK8: Y | AL8: 2000 | AM8: =IF(AL8<1000,"0-1000",IF(AL8<2000,"1000-2000",IF(AL8<3000,"2000-3000",IF(AL8<5000,"3000-5000",IF(AL8<10000,"5000-10000","Over 10000"))))) -> 2000-3000
A9: 43762 | B9: 0.67083333 | D9: P | E9: 2 | F9: =VLOOKUP(E9,Key!$A$17:$B$21,2,FALSE) -> Road Vehicle | G9: 6 | H9: =VLOOKUP(G9,Key!$A$2:$B$13,2,FALSE) -> Large Bus | I9: F | J9: 1 | K9: =VLOOKUP(J9,Key!$A$24:$B$29,2,FALSE) -> 20-29 | L9: HIOMA | M9: HIOMA | N9: UG | O9: 2 | P9: =VLOOKUP(O9,Key!$E$2:$F$9,2,FALSE) -> Work | Q9: KAMPALA | R9: KAMPALA | S9: UG | T9: 1 | U9: =VLOOKUP(T9,Key!$E$2:$F$9,2,FALSE) -> Home | V9: =P9&"-"&U9 -> Work-Home | W9: 13000 | X9: 200 | Y9: =IF(X9<10,"0-10",IF(X9<20,"10-20",IF(X9<40,"20-40",IF(X9<70,"40-70",IF(X9<100,"70-100",IF(X9<200,"100-200","Over 200")))))) -> Over 200 | Z9: 4 | AA9: =IF(Z9<0.5,"0-0.5",IF(Z9<1,"0.5-1.0",IF(Z9<2,"1.0-2.0",IF(Z9<3.5,"2.0-3.5","Over 3.5")))) -> Over 3.5 | AB9: 4 | AC9: =VLOOKUP(AB9,Key!$C$20:$D$29,2,FALSE) -> Office Worker | AD9: 3 | AE9: =VLOOKUP(AD9,Key!$E$20:$F$24,2,FALSE) -> 500,000-750,000 | AF9: 1 | AG9: 2 | AH9: 3 | AI9: 4 | AJ9: 5 | AK9: Y | AL9: 1000 | AM9: =IF(AL9<1000,"0-1000",IF(AL9<2000,"1000-2000",IF(AL9<3000,"2000-3000",IF(AL9<5000,"3000-5000",IF(AL9<10000,"5000-10000","Over 10000"))))) -> 1000-2000
A10: 43762 | B10: 0.61041667 | D10: P | E10: 2 | F10: =VLOOKUP(E10,Key!$A$17:$B$21,2,FALSE) -> Road Vehicle | G10: 6 | H10: =VLOOKUP(G10,Key!$A$2:$B$13,2,FALSE) -> Large Bus | I10: M | J10: 1 | K10: =VLOOKUP(J10,Key!$A$24:$B$29,2,FALSE) -> 20-29 | L10: HIOMA | M10: HIOMA | N10: UG | O10: 2 | P10: =VLOOKUP(O10,Key!$E$2:$F$9,2,FALSE) -> Work | Q10: KAMPALA | R10: KAMPALA | S10: UG | T10: 2 | U10: =VLOOKUP(T10,Key!$E$2:$F$9,2,FALSE) -> Work | V10: =P10&"-"&U10 -> Work-Work | W10: 13000 | X10: 200 | Y10: =IF(X10<10,"0-10",IF(X10<20,"10-20",IF(X10<40,"20-40",IF(X10<70,"40-70",IF(X10<100,"70-100",IF(X10<200,"100-200","Over 200")))))) -> Over 200 | Z10: 3 | AA10: =IF(Z10<0.5,"0-0.5",IF(Z10<1,"0.5-1.0",IF(Z10<2,"1.0-2.0",IF(Z10<3.5,"2.0-3.5","Over 3.5")))) -> 2.0-3.5 | AB10: 4 | AC10: =VLOOKUP(AB10,Key!$C$20:$D$29,2,FALSE) -> Office Worker | AD10: 4 | AE10: =VLOOKUP(AD10,Key!$E$20:$F$24,2,FALSE) -> 750,000-1,000,000 | AF10: 1 | AG10: 3 | AH10: 5 | AI10: 4 | AJ10: 2 | AK10: Y | AM10: =IF(AL10<1000,"0-1000",IF(AL10<2000,"1000-2000",IF(AL10<3000,"2000-3000",IF(AL10<5000,"3000-5000",IF(AL10<10000,"5000-10000","Over 10000"))))) -> 0-1000
A11: 43762 | B11: 0.6 | D11: P | E11: 2 | F11: =VLOOKUP(E11,Key!$A$17:$B$21,2,FALSE) -> Road Vehicle | G11: 6 | H11: =VLOOKUP(G11,Key!$A$2:$B$13,2,FALSE) -> Large Bus | I11: M | J11: 1 | K11: =VLOOKUP(J11,Key!$A$24:$B$29,2,FALSE) -> 20-29 | L11: HIOMA | M11: HIOMA | N11: UG | O11: 2 | P11: =VLOOKUP(O11,Key!$E$2:$F$9,2,FALSE) -> Work | Q11: KAMPALA | R11: KAMPALA | S11: UG | T11: 6 | U11: =VLOOKUP(T11,Key!$E$2:$F$9,2,FALSE) -> Leisure/Social | V11: =P11&"-"&U11 -> Work-Leisure/Social | W11: 13000 | X11: 195 | Y11: =IF(X11<10,"0-10",IF(X11<20,"10-20",IF(X11<40,"20-40",IF(X11<70,"40-70",IF(X11<100,"70-100",IF(X11<200,"100-200","Over 200")))))) -> 100-200 | Z11: 3 | AA11: =IF(Z11<0.5,"0-0.5",IF(Z11<1,"0.5-1.0",IF(Z11<2,"1.0-2.0",IF(Z11<3.5,"2.0-3.5","Over 3.5")))) -> 2.0-3.5 | AB11: 1 | AC11: =VLOOKUP(AB11,Key!$C$20:$D$29,2,FALSE) -> Unemployed | AD11: 1 | AE11: =VLOOKUP(AD11,Key!$E$20:$F$24,2,FALSE) -> <300,000 | AF11: 2 | AG11: 1 | AH11: 5 | AI11: 4 | AJ11: 3 | AK11: Y | AL11: 3000 | AM11: =IF(AL11<1000,"0-1000",IF(AL11<2000,"1000-2000",IF(AL11<3000,"2000-3000",IF(AL11<5000,"3000-5000",IF(AL11<10000,"5000-10000","Over 10000"))))) -> 3000-5000
A12: 43762 | B12: 0.59027778 | D12: P | E12: 2 | F12: =VLOOKUP(E12,Key!$A$17:$B$21,2,FALSE) -> Road Vehicle | G12: 6 | H12: =VLOOKUP(G12,Key!$A$2:$B$13,2,FALSE) -> Large Bus | I12: M | J12: 1 | K12: =VLOOKUP(J12,Key!$A$24:$B$29,2,FALSE) -> 20-29 | L12: HIOMA | M12: HIOMA | N12: UG | O12: 3 | P12: =VLOOKUP(O12,Key!$E$2:$F$9,2,FALSE) -> Study | Q12: KAMPALA | R12: KAMPALA | S12: UG | T12: 5 | U12: =VLOOKUP(T12,Key!$E$2:$F$9,2,FALSE) -> Tourism | V12: =P12&"-"&U12 -> Study-Tourism | W12: 13000 | X12: 200 | Y12: =IF(X12<10,"0-10",IF(X12<20,"10-20",IF(X12<40,"20-40",IF(X12<70,"40-70",IF(X12<100,"70-100",IF(X12<200,"100-200","Over 200")))))) -> Over 200 | Z12: 4 | AA12: =IF(Z12<0.5,"0-0.5",IF(Z12<1,"0.5-1.0",IF(Z12<2,"1.0-2.0",IF(Z12<3.5,"2.0-3.5","Over 3.5")))) -> Over 3.5 | AB12: 5 | AC12: =VLOOKUP(AB12,Key!$C$20:$D$29,2,FALSE) -> Professional | AD12: 4 | AE12: =VLOOKUP(AD12,Key!$E$20:$F$24,2,FALSE) -> 750,000-1,000,000 | AF12: 2 | AG12: 3 | AH12: 5 | AI12: 4 | AJ12: 7 | AK12: Y | AL12: 2000 | AM12: =IF(AL12<1000,"0-1000",IF(AL12<2000,"1000-2000",IF(AL12<3000,"2000-3000",IF(AL12<5000,"3000-5000",IF(AL12<10000,"5000-10000","Over 10000"))))) -> 2000-3000
A13: 43763 | B13: 0.33611111 | D13: P | E13: 2 | F13: =VLOOKUP(E13,Key!$A$17:$B$21,2,FALSE) -> Road Vehicle | G13: 6 | H13: =VLOOKUP(G13,Key!$A$2:$B$13,2,FALSE) -> Large Bus | I13: M | J13: 1 | K13: =VLOOKUP(J13,Key!$A$24:$B$29,2,FALSE) -> 20-29 | L13: HIOMA | M13: HIOMA | N13: UG | O13: 6 | P13: =VLOOKUP(O13,Key!$E$2:$F$9,2,FALSE) -> Leisure/Social | Q13: KYANKWENZI | R13: KIKUUBE | S13: UG | T13: 6 | U13: =VLOOKUP(T13,Key!$E$2:$F$9,2,FALSE) -> Leisure/Social | V13: =P13&"-"&U13 -> Leisure/Social-Leisure/Social | W13: 10000 | X13: 130 | Y13: =IF(X13<10,"0-10",IF(X13<20,"10-20",IF(X13<40,"20-40",IF(X13<70,"40-70",IF(X13<100,"70-100",IF(X13<200,"100-200","Over 200")))))) -> 100-200 | Z13: 2 | AA13: =IF(Z13<0.5,"0-0.5",IF(Z13<1,"0.5-1.0",IF(Z13<2,"1.0-2.0",IF(Z13<3.5,"2.0-3.5","Over 3.5")))) -> 2.0-3.5 | AB13: 3 | AC13: =VLOOKUP(AB13,Key!$C$20:$D$29,2,FALSE) -> Artisan/Domestic | AD13: 2 | AE13: =VLOOKUP(AD13,Key!$E$20:$F$24,2,FALSE) -> 300,000-500,000 | AF13: 1 | AG13: 1 | AH13: 1 | AI13: 1 | AJ13: 1 | AK13: Y | AM13: =IF(AL13<1000,"0-1000",IF(AL13<2000,"1000-2000",IF(AL13<3000,"2000-3000",IF(AL13<5000,"3000-5000",IF(AL13<10000,"5000-10000","Over 10000"))))) -> 0-1000
A14: 43763 | B14: 0.33611111 | D14: P | E14: 2 | F14: =VLOOKUP(E14,Key!$A$17:$B$21,2,FALSE) -> Road Vehicle | G14: 6 | H14: =VLOOKUP(G14,Key!$A$2:$B$13,2,FALSE) -> Large Bus | I14: M | J14: 1 | K14: =VLOOKUP(J14,Key!$A$24:$B$29,2,FALSE) -> 20-29 | L14: HIOMA | M14: HIOMA | N14: UG | O14: 1 | P14: =VLOOKUP(O14,Key!$E$2:$F$9,2,FALSE) -> Home | Q14: KYANKWENZI | R14: KIKUUBE | S14: UG | T14: 6 | U14: =VLOOKUP(T14,Key!$E$2:$F$9,2,FALSE) -> Leisure/Social | V14: =P14&"-"&U14 -> Home-Leisure/Social | W14: 10000 | X14: 130 | Y14: =IF(X14<10,"0-10",IF(X14<20,"10-20",IF(X14<40,"20-40",IF(X14<70,"40-70",IF(X14<100,"70-100",IF(X14<200,"100-200","Over 200")))))) -> 100-200 | Z14: 2 | AA14: =IF(Z14<0.5,"0-0.5",IF(Z14<1,"0.5-1.0",IF(Z14<2,"1.0-2.0",IF(Z14<3.5,"2.0-3.5","Over 3.5")))) -> 2.0-3.5 | AB14: 3 | AC14: =VLOOKUP(AB14,Key!$C$20:$D$29,2,FALSE) -> Artisan/Domestic | AD14: 2 | AE14: =VLOOKUP(AD14,Key!$E$20:$F$24,2,FALSE) -> 300,000-500,000 | AF14: 1 | AG14: 1 | AH14: 1 | AI14: 1 | AJ14: 1 | AK14: Y | AL14: 1000 | AM14: =IF(AL14<1000,"0-1000",IF(AL14<2000,"1000-2000",IF(AL14<3000,"2000-3000",IF(AL14<5000,"3000-5000",IF(AL14<10000,"5000-10000","Over 10000"))))) -> 1000-2000
A15: 43763 | B15: 0.71875 | D15: D | E15: 2 | F15: =VLOOKUP(E15,Key!$A$17:$B$21,2,FALSE) -> Road Vehicle | G15: 6 | H15: =VLOOKUP(G15,Key!$A$2:$B$13,2,FALSE) -> Large Bus | I15: M | J15: 1 | K15: =VLOOKUP(J15,Key!$A$24:$B$29,2,FALSE) -> 20-29 | L15: HIOMA | M15: HIOMA | N15: UG | O15: 2 | P15: =VLOOKUP(O15,Key!$E$2:$F$9,2,FALSE) -> Work | Q15: KIBUULE | R15: KIBUULE | S15: UG | T15: 1 | U15: =VLOOKUP(T15,Key!$E$2:$F$9,2,FALSE) -> Home | V15: =P15&"-"&U15 -> Work-Home | W15: 600000 | X15: 80 | Y15: =IF(X15<10,"0-10",IF(X15<20,"10-20",IF(X15<40,"20-40",IF(X15<70,"40-70",IF(X15<100,"70-100",IF(X15<200,"100-200","Over 200")))))) -> 70-100 | Z15: 3 | AA15: =IF(Z15<0.5,"0-0.5",IF(Z15<1,"0.5-1.0",IF(Z15<2,"1.0-2.0",IF(Z15<3.5,"2.0-3.5","Over 3.5")))) -> 2.0-3.5 | AB15: 10 | AC15: =VLOOKUP(AB15,Key!$C$20:$D$29,2,FALSE) -> Other | AD15: 4 | AE15: =VLOOKUP(AD15,Key!$E$20:$F$24,2,FALSE) -> 750,000-1,000,000 | AF15: 1 | AG15: 2 | AH15: 3 | AI15: 4 | AJ15: 5 | AK15: Y | AL15: 3000 | AM15: =IF(AL15<1000,"0-1000",IF(AL15<2000,"1000-2000",IF(AL15<3000,"2000-3000",IF(AL15<5000,"3000-5000",IF(AL15<10000,"5000-10000","Over 10000"))))) -> 3000-5000
A16: 43763 | B16: 0.65 | D16: P | E16: 2 | F16: =VLOOKUP(E16,Key!$A$17:$B$21,2,FALSE) -> Road Vehicle | G16: 6 | H16: =VLOOKUP(G16,Key!$A$2:$B$13,2,FALSE) -> Large Bus | I16: M | J16: 1 | K16: =VLOOKUP(J16,Key!$A$24:$B$29,2,FALSE) -> 20-29 | L16: HIOMA | M16: HIOMA | N16: UG | O16: 3 | P16: =VLOOKUP(O16,Key!$E$2:$F$9,2,FALSE) -> Study | Q16: KAMPALA | R16: KAMPALA | S16: UG | T16: 1 | U16: =VLOOKUP(T16,Key!$E$2:$F$9,2,FALSE) -> Home | V16: =P16&"-"&U16 -> Study-Home | W16: 130000 | X16: 190 | Y16: =IF(X16<10,"0-10",IF(X16<20,"10-20",IF(X16<40,"20-40",IF(X16<70,"40-70",IF(X16<100,"70-100",IF(X16<200,"100-200","Over 200")))))) -> 100-200 | Z16: 4 | AA16: =IF(Z16<0.5,"0-0.5",IF(Z16<1,"0.5-1.0",IF(Z16<2,"1.0-2.0",IF(Z16<3.5,"2.0-3.5","Over 3.5")))) -> Over 3.5 | AB16: 4 | AC16: =VLOOKUP(AB16,Key!$C$20:$D$29,2,FALSE) -> Office Worker | AD16: 4 | AE16: =VLOOKUP(AD16,Key!$E$20:$F$24,2,FALSE) -> 750,000-1,000,000 | AF16: 5 | AG16: 4 | AH16: 3 | AI16: 2 | AJ16: 1 | AK16: Y | AM16: =IF(AL16<1000,"0-1000",IF(AL16<2000,"1000-2000",IF(AL16<3000,"2000-3000",IF(AL16<5000,"3000-5000",IF(AL16<10000,"5000-10000","Over 10000"))))) -> 0-1000
A17: 43763 | B17: 0.64930556 | D17: P | E17: 2 | F17: =VLOOKUP(E17,Key!$A$17:$B$21,2,FALSE) -> Road Vehicle | G17: 6 | H17: =VLOOKUP(G17,Key!$A$2:$B$13,2,FALSE) -> Large Bus | I17: M | J17: 1 | K17: =VLOOKUP(J17,Key!$A$24:$B$29,2,FALSE) -> 20-29 | L17: HIOMA | M17: HIOMA | N17: UG | O17: 1 | P17: =VLOOKUP(O17,Key!$E$2:$F$9,2,FALSE) -> Home | Q17: KAMPALA | R17: KAMPALA | S17: UG | T17: 2 | U17: =VLOOKUP(T17,Key!$E$2:$F$9,2,FALSE) -> Work | V17: =P17&"-"&U17 -> Home-Work | W17: 130000 | X17: 190 | Y17: =IF(X17<10,"0-10",IF(X17<20,"10-20",IF(X17<40,"20-40",IF(X17<70,"40-70",IF(X17<100,"70-100",IF(X17<200,"100-200","Over 200")))))) -> 100-200 | Z17: 4 | AA17: =IF(Z17<0.5,"0-0.5",IF(Z17<1,"0.5-1.0",IF(Z17<2,"1.0-2.0",IF(Z17<3.5,"2.0-3.5","Over 3.5")))) -> Over 3.5 | AB17: 10 | AC17: =VLOOKUP(AB17,Key!$C$20:$D$29,2,FALSE) -> Other | AD17: 3 | AE17: =VLOOKUP(AD17,Key!$E$20:$F$24,2,FALSE) -> 500,000-750,000 | AF17: 5 | AG17: 4 | AH17: 3 | AI17: 2 | AJ17: 1 | AK17: Y | AL17: 5000 | AM17: =IF(AL17<1000,"0-1000",IF(AL17<2000,"1000-2000",IF(AL17<3000,"2000-3000",IF(AL17<5000,"3000-5000",IF(AL17<10000,"5000-10000","Over 10000"))))) -> 5000-10000
A18: 43763 | B18: 0.60902778 | D18: P | E18: 2 | F18: =VLOOKUP(E18,Key!$A$17:$B$21,2,FALSE) -> Road Vehicle | G18: 6 | H18: =VLOOKUP(G18,Key!$A$2:$B$13,2,FALSE) -> Large Bus | I18: M | J18: 1 | K18: =VLOOKUP(J18,Key!$A$24:$B$29,2,FALSE) -> 20-29 | L18: HIOMA | M18: HIOMA | N18: UG | O18: 2 | P18: =VLOOKUP(O18,Key!$E$2:$F$9,2,FALSE) -> Work | Q18: KAMPALA | R18: KAMPALA | S18: UG | T18: 1 | U18: =VLOOKUP(T18,Key!$E$2:$F$9,2,FALSE) -> Home | V18: =P18&"-"&U18 -> Work-Home | W18: 130000 | X18: 194 | Y18: =IF(X18<10,"0-10",IF(X18<20,"10-20",IF(X18<40,"20-40",IF(X18<70,"40-70",IF(X18<100,"70-100",IF(X18<200,"100-200","Over 200")))))) -> 100-200 | Z18: 4 | AA18: =IF(Z18<0.5,"0-0.5",IF(Z18<1,"0.5-1.0",IF(Z18<2,"1.0-2.0",IF(Z18<3.5,"2.0-3.5","Over 3.5")))) -> Over 3.5 | AB18: 6 | AC18: =VLOOKUP(AB18,Key!$C$20:$D$29,2,FALSE) -> Businessman | AD18: 3 | AE18: =VLOOKUP(AD18,Key!$E$20:$F$24,2,FALSE) -> 500,000-750,000 | AF18: 5 | AG18: 1 | AH18: 2 | AI18: 4 | AJ18: 3 | AK18: Y | AL18: 1000 | AM18: =IF(AL18<1000,"0-1000",IF(AL18<2000,"1000-2000",IF(AL18<3000,"2000-3000",IF(AL18<5000,"3000-5000",IF(AL18<10000,"5000-10000","Over 10000"))))) -> 1000-2000
A19: 43763 | B19: 0.56111111 | D19: P | E19: 2 | F19: =VLOOKUP(E19,Key!$A$17:$B$21,2,FALSE) -> Road Vehicle | G19: 6 | H19: =VLOOKUP(G19,Key!$A$2:$B$13,2,FALSE) -> Large Bus | I19: M | J19: 1 | K19: =VLOOKUP(J19,Key!$A$24:$B$29,2,FALSE) -> 20-29 | L19: HIOMA | M19: HIOMA | N19: UG | O19: 4 | P19: =VLOOKUP(O19,Key!$E$2:$F$9,2,FALSE) -> Commercial | Q19: KAMPALA | R19: KAMPALA | S19: UG | T19: 1 | U19: =VLOOKUP(T19,Key!$E$2:$F$9,2,FALSE) -> Home | V19: =P19&"-"&U19 -> Commercial-Home | W19: 130000 | X19: 200 | Y19: =IF(X19<10,"0-10",IF(X19<20,"10-20",IF(X19<40,"20-40",IF(X19<70,"40-70",IF(X19<100,"70-100",IF(X19<200,"100-200","Over 200")))))) -> Over 200 | Z19: 4 | AA19: =IF(Z19<0.5,"0-0.5",IF(Z19<1,"0.5-1.0",IF(Z19<2,"1.0-2.0",IF(Z19<3.5,"2.0-3.5","Over 3.5")))) -> Over 3.5 | AB19: 6 | AC19: =VLOOKUP(AB19,Key!$C$20:$D$29,2,FALSE) -> Businessman | AD19: 2 | AE19: =VLOOKUP(AD19,Key!$E$20:$F$24,2,FALSE) -> 300,000-500,000 | AF19: 1 | AG19: 2 | AH19: 5 | AI19: 4 | AJ19: 3 | AK19: Y | AM19: =IF(AL19<1000,"0-1000",IF(AL19<2000,"1000-2000",IF(AL19<3000,"2000-3000",IF(AL19<5000,"3000-5000",IF(AL19<10000,"5000-10000","Over 10000"))))) -> 0-1000
A20: 43763 | B20: 0.53472222 | D20: P | E20: 2 | F20: =VLOOKUP(E20,Key!$A$17:$B$21,2,FALSE) -> Road Vehicle | G20: 6 | H20: =VLOOKUP(G20,Key!$A$2:$B$13,2,FALSE) -> Large Bus | I20: M | J20: 1 | K20: =VLOOKUP(J20,Key!$A$24:$B$29,2,FALSE) -> 20-29 | L20: HIOMA | M20: HIOMA | N20: UG | O20: 6 | P20: =VLOOKUP(O20,Key!$E$2:$F$9,2,FALSE) -> Leisure/Social | Q20: KAMPALA | R20: KAMPALA | S20: UG | T20: 1 | U20: =VLOOKUP(T20,Key!$E$2:$F$9,2,FALSE) -> Home | V20: =P20&"-"&U20 -> Leisure/Social-Home | W20: 130000 | X20: 220 | Y20: =IF(X20<10,"0-10",IF(X20<20,"10-20",IF(X20<40,"20-40",IF(X20<70,"40-70",IF(X20<100,"70-100",IF(X20<200,"100-200","Over 200")))))) -> Over 200 | Z20: 5 | AA20: =IF(Z20<0.5,"0-0.5",IF(Z20<1,"0.5-1.0",IF(Z20<2,"1.0-2.0",IF(Z20<3.5,"2.0-3.5","Over 3.5")))) -> Over 3.5 | AB20: 3 | AC20: =VLOOKUP(AB20,Key!$C$20:$D$29,2,FALSE) -> Artisan/Domestic | AD20: 3 | AE20: =VLOOKUP(AD20,Key!$E$20:$F$24,2,FALSE) -> 500,000-750,000 | AF20: 5 | AG20: 2 | AH20: 1 | AI20: 4 | AJ20: 5 | AK20: Y | AL20: 2000 | AM20: =IF(AL20<1000,"0-1000",IF(AL20<2000,"1000-2000",IF(AL20<3000,"2000-3000",IF(AL20<5000,"3000-5000",IF(AL20<10000,"5000-10000","Over 10000"))))) -> 2000-3000
A21: 43763 | B21: 0.50972222 | D21: P | E21: 2 | F21: =VLOOKUP(E21,Key!$A$17:$B$21,2,FALSE) -> Road Vehicle | G21: 6 | H21: =VLOOKUP(G21,Key!$A$2:$B$13,2,FALSE) -> Large Bus | I21: M | J21: 1 | K21: =VLOOKUP(J21,Key!$A$24:$B$29,2,FALSE) -> 20-29 | L21: HIOMA | M21: HIOMA | N21: UG | O21: 2 | P21: =VLOOKUP(O21,Key!$E$2:$F$9,2,FALSE) -> Work | Q21: BULIISA | R21: BULIISA | S21: UG | T21: 1 | U21: =VLOOKUP(T21,Key!$E$2:$F$9,2,FALSE) -> Home | V21: =P21&"-"&U21 -> Work-Home | W21: 15000 | X21: 200 | Y21: =IF(X21<10,"0-10",IF(X21<20,"10-20",IF(X21<40,"20-40",IF(X21<70,"40-70",IF(X21<100,"70-100",IF(X21<200,"100-200","Over 200")))))) -> Over 200 | Z21: 3 | AA21: =IF(Z21<0.5,"0-0.5",IF(Z21<1,"0.5-1.0",IF(Z21<2,"1.0-2.0",IF(Z21<3.5,"2.0-3.5","Over 3.5")))) -> 2.0-3.5 | AB21: 4 | AC21: =VLOOKUP(AB21,Key!$C$20:$D$29,2,FALSE) -> Office Worker | AD21: 2 | AE21: =VLOOKUP(AD21,Key!$E$20:$F$24,2,FALSE) -> 300,000-500,000 | AF21: 1 | AG21: 2 | AH21: 3 | AI21: 4 | AJ21: 5 | AK21: Y | AM21: =IF(AL21<1000,"0-1000",IF(AL21<2000,"1000-2000",IF(AL21<3000,"2000-3000",IF(AL21<5000,"3000-5000",IF(AL21<10000,"5000-10000","Over 10000"))))) -> 0-1000
A22: 43763 | B22: 0.60486111 | D22: P | E22: 2 | F22: =VLOOKUP(E22,Key!$A$17:$B$21,2,FALSE) -> Road Vehicle | G22: 5 | H22: =VLOOKUP(G22,Key!$A$2:$B$13,2,FALSE) -> Medium bus | I22: M | J22: 1 | K22: =VLOOKUP(J22,Key!$A$24:$B$29,2,FALSE) -> 20-29 | L22: HIOMA | M22: HIOMA | N22: UG | O22: 2 | P22: =VLOOKUP(O22,Key!$E$2:$F$9,2,FALSE) -> Work | Q22: KAMPALA | R22: KAMPALA | S22: UG | T22: 2 | U22: =VLOOKUP(T22,Key!$E$2:$F$9,2,FALSE) -> Work | V22: =P22&"-"&U22 -> Work-Work | W22: 650000 | X22: 200 | Y22: =IF(X22<10,"0-10",IF(X22<20,"10-20",IF(X22<40,"20-40",IF(X22<70,"40-70",IF(X22<100,"70-100",IF(X22<200,"100-200","Over 200")))))) -> Over 200 | Z22: 5 | AA22: =IF(Z22<0.5,"0-0.5",IF(Z22<1,"0.5-1.0",IF(Z22<2,"1.0-2.0",IF(Z22<3.5,"2.0-3.5","Over 3.5")))) -> Over 3.5 | AB22: 10 | AC22: =VLOOKUP(AB22,Key!$C$20:$D$29,2,FALSE) -> Other | AD22: 5 | AE22: =VLOOKUP(AD22,Key!$E$20:$F$24,2,FALSE) -> >1,000,000 | AF22: 1 | AG22: 2 | AH22: 3 | AI22: 5 | AJ22: 4 | AK22: Y | AL22: 1000 | AM22: =IF(AL22<1000,"0-1000",IF(AL22<2000,"1000-2000",IF(AL22<3000,"2000-3000",IF(AL22<5000,"3000-5000",IF(AL22<10000,"5000-10000","Over 10000"))))) -> 1000-2000
A23: 43762 | B23: 0.76666667 | D23: P | E23: 2 | F23: =VLOOKUP(E23,Key!$A$17:$B$21,2,FALSE) -> Road Vehicle | G23: 4 | H23: =VLOOKUP(G23,Key!$A$2:$B$13,2,FALSE) -> Minibus | I23: F | J23: 1 | K23: =VLOOKUP(J23,Key!$A$24:$B$29,2,FALSE) -> 20-29 | L23: HIOMA | M23: HIOMA | N23: UG | O23: 2 | P23: =VLOOKUP(O23,Key!$E$2:$F$9,2,FALSE) -> Work | Q23: KAMPALA | R23: KAMPALA | S23: UG | T23: 1 | U23: =VLOOKUP(T23,Key!$E$2:$F$9,2,FALSE) -> Home | V23: =P23&"-"&U23 -> Work-Home | W23: 15000 | X23: 200 | Y23: =IF(X23<10,"0-10",IF(X23<20,"10-20",IF(X23<40,"20-40",IF(X23<70,"40-70",IF(X23<100,"70-100",IF(X23<200,"100-200","Over 200")))))) -> Over 200 | Z23: 3 | AA23: =IF(Z23<0.5,"0-0.5",IF(Z23<1,"0.5-1.0",IF(Z23<2,"1.0-2.0",IF(Z23<3.5,"2.0-3.5","Over 3.5")))) -> 2.0-3.5 | AB23: 2 | AC23: =VLOOKUP(AB23,Key!$C$20:$D$29,2,FALSE) -> Manual Labour | AD23: 2 | AE23: =VLOOKUP(AD23,Key!$E$20:$F$24,2,FALSE) -> 300,000-500,000 | AF23: 1 | AG23: 3 | AH23: 2 | AI23: 5 | AJ23: 4 | AK23: Y | AL23: 3000 | AM23: =IF(AL23<1000,"0-1000",IF(AL23<2000,"1000-2000",IF(AL23<3000,"2000-3000",IF(AL23<5000,"3000-5000",IF(AL23<10000,"5000-10000","Over 10000"))))) -> 3000-5000
A24: 43762 | B24: 0.725 | D24: P | E24: 2 | F24: =VLOOKUP(E24,Key!$A$17:$B$21,2,FALSE) -> Road Vehicle | G24: 4 | H24: =VLOOKUP(G24,Key!$A$2:$B$13,2,FALSE) -> Minibus | I24: F | J24: 1 | K24: =VLOOKUP(J24,Key!$A$24:$B$29,2,FALSE) -> 20-29 | L24: HIOMA | M24: HIOMA | N24: UG | O24: 1 | P24: =VLOOKUP(O24,Key!$E$2:$F$9,2,FALSE) -> Home | Q24: KABAALE | R24: KABAALE | S24: UG | T24: 2 | U24: =VLOOKUP(T24,Key!$E$2:$F$9,2,FALSE) -> Work | V24: =P24&"-"&U24 -> Home-Work | W24: 5000 | X24: 31 | Y24: =IF(X24<10,"0-10",IF(X24<20,"10-20",IF(X24<40,"20-40",IF(X24<70,"40-70",IF(X24<100,"70-100",IF(X24<200,"100-200","Over 200")))))) -> 20-40 | Z24: 24 | AA24: =IF(Z24<0.5,"0-0.5",IF(Z24<1,"0.5-1.0",IF(Z24<2,"1.0-2.0",IF(Z24<3.5,"2.0-3.5","Over 3.5")))) -> Over 3.5 | AB24: 2 | AC24: =VLOOKUP(AB24,Key!$C$20:$D$29,2,FALSE) -> Manual Labour | AD24: 1 | AE24: =VLOOKUP(AD24,Key!$E$20:$F$24,2,FALSE) -> <300,000 | AF24: 5 | AG24: 3 | AH24: 1 | AI24: 2 | AJ24: 4 | AK24: Y | AM24: =IF(AL24<1000,"0-1000",IF(AL24<2000,"1000-2000",IF(AL24<3000,"2000-3000",IF(AL24<5000,"3000-5000",IF(AL24<10000,"5000-10000","Over 10000"))))) -> 0-1000
A25: 43762 | B25: 0.64722222 | D25: P | E25: 2 | F25: =VLOOKUP(E25,Key!$A$17:$B$21,2,FALSE) -> Road Vehicle | G25: 4 | H25: =VLOOKUP(G25,Key!$A$2:$B$13,2,FALSE) -> Minibus | I25: F | J25: 1 | K25: =VLOOKUP(J25,Key!$A$24:$B$29,2,FALSE) -> 20-29 | L25: HIOMA | M25: HIOMA | N25: UG | O25: 2 | P25: =VLOOKUP(O25,Key!$E$2:$F$9,2,FALSE) -> Work | Q25: BUSUJJU | R25: BUSUJJU | S25: UG | T25: 2 | U25: =VLOOKUP(T25,Key!$E$2:$F$9,2,FALSE) -> Work | V25: =P25&"-"&U25 -> Work-Work | W25: 15000 | X25: 117 | Y25: =IF(X25<10,"0-10",IF(X25<20,"10-20",IF(X25<40,"20-40",IF(X25<70,"40-70",IF(X25<100,"70-100",IF(X25<200,"100-200","Over 200")))))) -> 100-200 | Z25: 2 | AA25: =IF(Z25<0.5,"0-0.5",IF(Z25<1,"0.5-1.0",IF(Z25<2,"1.0-2.0",IF(Z25<3.5,"2.0-3.5","Over 3.5")))) -> 2.0-3.5 | AB25: 4 | AC25: =VLOOKUP(AB25,Key!$C$20:$D$29,2,FALSE) -> Office Worker | AD25: 3 | AE25: =VLOOKUP(AD25,Key!$E$20:$F$24,2,FALSE) -> 500,000-750,000 | AF25: 1 | AG25: 2 | AH25: 3 | AI25: 5 | AJ25: 4 | AK25: Y | AM25: =IF(AL25<1000,"0-1000",IF(AL25<2000,"1000-2000",IF(AL25<3000,"2000-3000",IF(AL25<5000,"3000-5000",IF(AL25<10000,"5000-10000","Over 10000"))))) -> 0-1000
A26: 43762 | B26: 0.66875 | D26: P | E26: 2 | F26: =VLOOKUP(E26,Key!$A$17:$B$21,2,FALSE) -> Road Vehicle | G26: 4 | H26: =VLOOKUP(G26,Key!$A$2:$B$13,2,FALSE) -> Minibus | I26: F | J26: 1 | K26: =VLOOKUP(J26,Key!$A$24:$B$29,2,FALSE) -> 20-29 | L26: HIOMA | M26: HIOMA | N26: UG | O26: 8 | P26: =VLOOKUP(O26,Key!$E$2:$F$9,2,FALSE) -> Others | Q26: KAMPALA | R26: KAMPALA | S26: UG | T26: 3 | U26: =VLOOKUP(T26,Key!$E$2:$F$9,2,FALSE) -> Study | V26: =P26&"-"&U26 -> Others-Study | W26: 15000 | X26: 200 | Y26: =IF(X26<10,"0-10",IF(X26<20,"10-20",IF(X26<40,"20-40",IF(X26<70,"40-70",IF(X26<100,"70-100",IF(X26<200,"100-200","Over 200")))))) -> Over 200 | Z26: 3 | AA26: =IF(Z26<0.5,"0-0.5",IF(Z26<1,"0.5-1.0",IF(Z26<2,"1.0-2.0",IF(Z26<3.5,"2.0-3.5","Over 3.5")))) -> 2.0-3.5 | AB26: 8 | AC26: =VLOOKUP(AB26,Key!$C$20:$D$29,2,FALSE) -> Student | AD26: 2 | AE26: =VLOOKUP(AD26,Key!$E$20:$F$24,2,FALSE) -> 300,000-500,000 | AF26: 4 | AG26: 1 | AH26: 2 | AI26: 3 | AJ26: 5 | AK26: Y | AL26: 1000 | AM26: =IF(AL26<1000,"0-1000",IF(AL26<2000,"1000-2000",IF(AL26<3000,"2000-3000",IF(AL26<5000,"3000-5000",IF(AL26<10000,"5000-10000","Over 10000"))))) -> 1000-2000
A27: 43762 | B27: 0.62361111 | D27: P | E27: 2 | F27: =VLOOKUP(E27,Key!$A$17:$B$21,2,FALSE) -> Road Vehicle | G27: 4 | H27: =VLOOKUP(G27,Key!$A$2:$B$13,2,FALSE) -> Minibus | I27: F | J27: 1 | K27: =VLOOKUP(J27,Key!$A$24:$B$29,2,FALSE) -> 20-29 | L27: HIOMA | M27: HIOMA | N27: UG | O27: 2 | P27: =VLOOKUP(O27,Key!$E$2:$F$9,2,FALSE) -> Work | Q27: HIOMA | R27: HIOMA | S27: UG | T27: 2 | U27: =VLOOKUP(T27,Key!$E$2:$F$9,2,FALSE) -> Work | V27: =P27&"-"&U27 -> Work-Work | W27: 12000 | Y27: =IF(X27<10,"0-10",IF(X27<20,"10-20",IF(X27<40,"20-40",IF(X27<70,"40-70",IF(X27<100,"70-100",IF(X27<200,"100-200","Over 200")))))) -> 0-10 | Z27: 3 | AA27: =IF(Z27<0.5,"0-0.5",IF(Z27<1,"0.5-1.0",IF(Z27<2,"1.0-2.0",IF(Z27<3.5,"2.0-3.5","Over 3.5")))) -> 2.0-3.5 | AB27: 2 | AC27: =VLOOKUP(AB27,Key!$C$20:$D$29,2,FALSE) -> Manual Labour | AD27: 1 | AE27: =VLOOKUP(AD27,Key!$E$20:$F$24,2,FALSE) -> <300,000 | AF27: 1 | AG27: 4 | AH27: 1 | AI27: 2 | AJ27: 3 | AK27: Y | AL27: 3000 | AM27: =IF(AL27<1000,"0-1000",IF(AL27<2000,"1000-2000",IF(AL27<3000,"2000-3000",IF(AL27<5000,"3000-5000",IF(AL27<10000,"5000-10000","Over 10000"))))) -> 3000-5000
A28: 43762 | B28: 0.69375 | D28: P | E28: 2 | F28: =VLOOKUP(E28,Key!$A$17:$B$21,2,FALSE) -> Road Vehicle | G28: 4 | H28: =VLOOKUP(G28,Key!$A$2:$B$13,2,FALSE) -> Minibus | I28: F | J28: 1 | K28: =VLOOKUP(J28,Key!$A$24:$B$29,2,FALSE) -> 20-29 | L28: KIBOGA | M28: KIBOGA | N28: UG | O28: 8 | P28: =VLOOKUP(O28,Key!$E$2:$F$9,2,FALSE) -> Others | Q28: HIOMA | R28: HIOMA | S28: UG | T28: 1 | U28: =VLOOKUP(T28,Key!$E$2:$F$9,2,FALSE) -> Home | V28: =P28&"-"&U28 -> Others-Home | W28: 7000 | Y28: =IF(X28<10,"0-10",IF(X28<20,"10-20",IF(X28<40,"20-40",IF(X28<70,"40-70",IF(X28<100,"70-100",IF(X28<200,"100-200","Over 200")))))) -> 0-10 | Z28: 2 | AA28: =IF(Z28<0.5,"0-0.5",IF(Z28<1,"0.5-1.0",IF(Z28<2,"1.0-2.0",IF(Z28<3.5,"2.0-3.5","Over 3.5")))) -> 2.0-3.5 | AB28: 3 | AC28: =VLOOKUP(AB28,Key!$C$20:$D$29,2,FALSE) -> Artisan/Domestic | AD28: 1 | AE28: =VLOOKUP(AD28,Key!$E$20:$F$24,2,FALSE) -> <300,000 | AF28: 4 | AG28: 1 | AH28: 2 | AI28: 5 | AJ28: 2 | AK28: Y | AM28: =IF(AL28<1000,"0-1000",IF(AL28<2000,"1000-2000",IF(AL28<3000,"2000-3000",IF(AL28<5000,"3000-5000",IF(AL28<10000,"5000-10000","Over 10000"))))) -> 0-1000
A29: 43762 | B29: 0.74097222 | D29: P | E29: 2 | F29: =VLOOKUP(E29,Key!$A$17:$B$21,2,FALSE) -> Road Vehicle | G29: 4 | H29: =VLOOKUP(G29,Key!$A$2:$B$13,2,FALSE) -> Minibus | I29: F | J29: 1 | K29: =VLOOKUP(J29,Key!$A$24:$B$29,2,FALSE) -> 20-29 | L29: KASUBI | M29: KAMPALA | N29: UG | O29: 1 | P29: =VLOOKUP(O29,Key!$E$2:$F$9,2,FALSE) -> Home | Q29: HIOMA | R29: HIOMA | S29: UG | T29: 8 | U29: =VLOOKUP(T29,Key!$E$2:$F$9,2,FALSE) -> Others | V29: =P29&"-"&U29 -> Home-Others | W29: 15000 | Y29: =IF(X29<10,"0-10",IF(X29<20,"10-20",IF(X29<40,"20-40",IF(X29<70,"40-70",IF(X29<100,"70-100",IF(X29<200,"100-200","Over 200")))))) -> 0-10 | Z29: 4 | AA29: =IF(Z29<0.5,"0-0.5",IF(Z29<1,"0.5-1.0",IF(Z29<2,"1.0-2.0",IF(Z29<3.5,"2.0-3.5","Over 3.5")))) -> Over 3.5 | AB29: 8 | AC29: =VLOOKUP(AB29,Key!$C$20:$D$29,2,FALSE) -> Student | AD29: 4 | AE29: =VLOOKUP(AD29,Key!$E$20:$F$24,2,FALSE) -> 750,000-1,000,000 | AF29: 2 | AG29: 1 | AH29: 3 | AI29: 5 | AJ29: 4 | AK29: Y | AL29: 10000 | AM29: =IF(AL29<1000,"0-1000",IF(AL29<2000,"1000-2000",IF(AL29<3000,"2000-3000",IF(AL29<5000,"3000-5000",IF(AL29<10000,"5000-10000","Over 10000"))))) -> Over 10000
A30: 43762 | B30: 0.625 | D30: D | E30: 2 | F30: =VLOOKUP(E30,Key!$A$17:$B$21,2,FALSE) -> Road Vehicle | G30: 4 | H30: =VLOOKUP(G30,Key!$A$2:$B$13,2,FALSE) -> Minibus | I30: M | J30: 1 | K30: =VLOOKUP(J30,Key!$A$24:$B$29,2,FALSE) -> 20-29 | L30: HIOMA | M30: HIOMA | N30: UG | O30: 2 | P30: =VLOOKUP(O30,Key!$E$2:$F$9,2,FALSE) -> Work | Q30: KAMPALA | R30: KAMPALA | S30: UG | T30: 1 | U30: =VLOOKUP(T30,Key!$E$2:$F$9,2,FALSE) -> Home | V30: =P30&"-"&U30 -> Work-Home | W30: 180000 | X30: 198 | Y30: =IF(X30<10,"0-10",IF(X30<20,"10-20",IF(X30<40,"20-40",IF(X30<70,"40-70",IF(X30<100,"70-100",IF(X30<200,"100-200","Over 200")))))) -> 100-200 | Z30: 3 | AA30: =IF(Z30<0.5,"0-0.5",IF(Z30<1,"0.5-1.0",IF(Z30<2,"1.0-2.0",IF(Z30<3.5,"2.0-3.5","Over 3.5")))) -> 2.0-3.5 | AB30: 10 | AC30: =VLOOKUP(AB30,Key!$C$20:$D$29,2,FALSE) -> Other | AD30: 4 | AE30: =VLOOKUP(AD30,Key!$E$20:$F$24,2,FALSE) -> 750,000-1,000,000 | AF30: 4 | AG30: 2 | AH30: 1 | AI30: 3 | AJ30: 5 | AK30: Y | AL30: 3000 | AM30: =IF(AL30<1000,"0-1000",IF(AL30<2000,"1000-2000",IF(AL30<3000,"2000-3000",IF(AL30<5000,"3000-5000",IF(AL30<10000,"5000-10000","Over 10000"))))) -> 3000-5000
A31: 43762 | B31: 0.67291667 | D31: P | E31: 2 | F31: =VLOOKUP(E31,Key!$A$17:$B$21,2,FALSE) -> Road Vehicle | G31: 4 | H31: =VLOOKUP(G31,Key!$A$2:$B$13,2,FALSE) -> Minibus | I31: M | J31: 1 | K31: =VLOOKUP(J31,Key!$A$24:$B$29,2,FALSE) -> 20-29 | L31: HIOMA | M31: HIOMA | N31: UG | O31: 2 | P31: =VLOOKUP(O31,Key!$E$2:$F$9,2,FALSE) -> Work | Q31: HIOMA | R31: BUKIYIRI | S31: UG | T31: 1 | U31: =VLOOKUP(T31,Key!$E$2:$F$9,2,FALSE) -> Home | V31: =P31&"-"&U31 -> Work-Home | W31: 5000 | X31: 160 | Y31: =IF(X31<10,"0-10",IF(X31<20,"10-20",IF(X31<40,"20-40",IF(X31<70,"40-70",IF(X31<100,"70-100",IF(X31<200,"100-200","Over 200")))))) -> 100-200 | Z31: 1 | AA31: =IF(Z31<0.5,"0-0.5",IF(Z31<1,"0.5-1.0",IF(Z31<2,"1.0-2.0",IF(Z31<3.5,"2.0-3.5","Over 3.5")))) -> 1.0-2.0 | AB31: 2 | AC31: =VLOOKUP(AB31,Key!$C$20:$D$29,2,FALSE) -> Manual Labour | AD31: 1 | AE31: =VLOOKUP(AD31,Key!$E$20:$F$24,2,FALSE) -> <300,000 | AF31: 5 | AG31: 4 | AH31: 1 | AI31: 2 | AJ31: 3 | AK31: Y | AL31: 1000 | AM31: =IF(AL31<1000,"0-1000",IF(AL31<2000,"1000-2000",IF(AL31<3000,"2000-3000",IF(AL31<5000,"3000-5000",IF(AL31<10000,"5000-10000","Over 10000"))))) -> 1000-2000
A32: 43762 | B32: 0.66388889 | D32: P | E32: 2 | F32: =VLOOKUP(E32,Key!$A$17:$B$21,2,FALSE) -> Road Vehicle | G32: 4 | H32: =VLOOKUP(G32,Key!$A$2:$B$13,2,FALSE) -> Minibus | I32: M | J32: 1 | K32: =VLOOKUP(J32,Key!$A$24:$B$29,2,FALSE) -> 20-29 | L32: KIBOGA | M32: KIBOGA | N32: UG | O32: 8 | P32: =VLOOKUP(O32,Key!$E$2:$F$9,2,FALSE) -> Others | Q32: HIOMA | R32: HIOMA | S32: UG | T32: 2 | U32: =VLOOKUP(T32,Key!$E$2:$F$9,2,FALSE) -> Work | V32: =P32&"-"&U32 -> Others-Work | W32: 8000 | X32: 87 | Y32: =IF(X32<10,"0-10",IF(X32<20,"10-20",IF(X32<40,"20-40",IF(X32<70,"40-70",IF(X32<100,"70-100",IF(X32<200,"100-200","Over 200")))))) -> 70-100 | Z32: 3 | AA32: =IF(Z32<0.5,"0-0.5",IF(Z32<1,"0.5-1.0",IF(Z32<2,"1.0-2.0",IF(Z32<3.5,"2.0-3.5","Over 3.5")))) -> 2.0-3.5 | AB32: 2 | AC32: =VLOOKUP(AB32,Key!$C$20:$D$29,2,FALSE) -> Manual Labour | AD32: 2 | AE32: =VLOOKUP(AD32,Key!$E$20:$F$24,2,FALSE) -> 300,000-500,000 | AF32: 2 | AG32: 3 | AH32: 4 | AI32: 1 | AJ32: 5 | AK32: Y | AM32: =IF(AL32<1000,"0-1000",IF(AL32<2000,"1000-2000",IF(AL32<3000,"2000-3000",IF(AL32<5000,"3000-5000",IF(AL32<10000,"5000-10000","Over 10000"))))) -> 0-1000
A33: 43762 | B33: 0.65277778 | D33: P | E33: 2 | F33: =VLOOKUP(E33,Key!$A$17:$B$21,2,FALSE) -> Road Vehicle | G33: 4 | H33: =VLOOKUP(G33,Key!$A$2:$B$13,2,FALSE) -> Minibus | I33: M | J33: 1 | K33: =VLOOKUP(J33,Key!$A$24:$B$29,2,FALSE) -> 20-29 | L33: HIOMA | M33: HIOMA | N33: UG | O33: 8 | P33: =VLOOKUP(O33,Key!$E$2:$F$9,2,FALSE) -> Others | Q33: KYANKWENZI | R33: KYANKWENZI | S33: UG | T33: 8 | U33: =VLOOKUP(T33,Key!$E$2:$F$9,2,FALSE) -> Others | V33: =P33&"-"&U33 -> Others-Others | W33: 5000 | Y33: =IF(X33<10,"0-10",IF(X33<20,"10-20",IF(X33<40,"20-40",IF(X33<70,"40-70",IF(X33<100,"70-100",IF(X33<200,"100-200","Over 200")))))) -> 0-10 | Z33: 2 | AA33: =IF(Z33<0.5,"0-0.5",IF(Z33<1,"0.5-1.0",IF(Z33<2,"1.0-2.0",IF(Z33<3.5,"2.0-3.5","Over 3.5")))) -> 2.0-3.5 | AB33: 5 | AC33: =VLOOKUP(AB33,Key!$C$20:$D$29,2,FALSE) -> Professional | AD33: 5 | AE33: =VLOOKUP(AD33,Key!$E$20:$F$24,2,FALSE) -> >1,000,000 | AF33: 3 | AG33: 4 | AH33: 2 | AI33: 1 | AJ33: 5 | AK33: Y | AL33: 1000 | AM33: =IF(AL33<1000,"0-1000",IF(AL33<2000,"1000-2000",IF(AL33<3000,"2000-3000",IF(AL33<5000,"3000-5000",IF(AL33<10000,"5000-10000","Over 10000"))))) -> 1000-2000
A34: 43762 | B34: 0.64236111 | D34: P | E34: 2 | F34: =VLOOKUP(E34,Key!$A$17:$B$21,2,FALSE) -> Road Vehicle | G34: 4 | H34: =VLOOKUP(G34,Key!$A$2:$B$13,2,FALSE) -> Minibus | I34: M | J34: 1 | K34: =VLOOKUP(J34,Key!$A$24:$B$29,2,FALSE) -> 20-29 | L34: HIOMA | M34: HIOMA | N34: UG | O34: 1 | P34: =VLOOKUP(O34,Key!$E$2:$F$9,2,FALSE) -> Home | Q34: WAKISO | R34: WAKISO | S34: UG | T34: 2 | U34: =VLOOKUP(T34,Key!$E$2:$F$9,2,FALSE) -> Work | V34: =P34&"-"&U34 -> Home-Work | W34: 10000 | Y34: =IF(X34<10,"0-10",IF(X34<20,"10-20",IF(X34<40,"20-40",IF(X34<70,"40-70",IF(X34<100,"70-100",IF(X34<200,"100-200","Over 200")))))) -> 0-10 | Z34: 3 | AA34: =IF(Z34<0.5,"0-0.5",IF(Z34<1,"0.5-1.0",IF(Z34<2,"1.0-2.0",IF(Z34<3.5,"2.0-3.5","Over 3.5")))) -> 2.0-3.5 | AB34: 4 | AC34: =VLOOKUP(AB34,Key!$C$20:$D$29,2,FALSE) -> Office Worker | AD34: 2 | AE34: =VLOOKUP(AD34,Key!$E$20:$F$24,2,FALSE) -> 300,000-500,000 | AF34: 4 | AG34: 5 | AH34: 3 | AI34: 2 | AJ34: 1 | AK34: Y | AL34: 3000 | AM34: =IF(AL34<1000,"0-1000",IF(AL34<2000,"1000-2000",IF(AL34<3000,"2000-3000",IF(AL34<5000,"3000-5000",IF(AL34<10000,"5000-10000","Over 10000"))))) -> 3000-5000
A35: 43762 | B35: 0.63958333 | D35: P | E35: 2 | F35: =VLOOKUP(E35,Key!$A$17:$B$21,2,FALSE) -> Road Vehicle | G35: 4 | H35: =VLOOKUP(G35,Key!$A$2:$B$13,2,FALSE) -> Minibus | I35: M | J35: 1 | K35: =VLOOKUP(J35,Key!$A$24:$B$29,2,FALSE) -> 20-29 | L35: NANSANA | M35: WAKISO | N35: UG | O35: 1 | P35: =VLOOKUP(O35,Key!$E$2:$F$9,2,FALSE) -> Home | Q35: BULIISA | R35: HIOMA | S35: UG | T35: 2 | U35: =VLOOKUP(T35,Key!$E$2:$F$9,2,FALSE) -> Work | V35: =P35&"-"&U35 -> Home-Work | W35: 19000 | Y35: =IF(X35<10,"0-10",IF(X35<20,"10-20",IF(X35<40,"20-40",IF(X35<70,"40-70",IF(X35<100,"70-100",IF(X35<200,"100-200","Over 200")))))) -> 0-10 | Z35: 4 | AA35: =IF(Z35<0.5,"0-0.5",IF(Z35<1,"0.5-1.0",IF(Z35<2,"1.0-2.0",IF(Z35<3.5,"2.0-3.5","Over 3.5")))) -> Over 3.5 | AB35: 5 | AC35: =VLOOKUP(AB35,Key!$C$20:$D$29,2,FALSE) -> Professional | AD35: 4 | AE35: =VLOOKUP(AD35,Key!$E$20:$F$24,2,FALSE) -> 750,000-1,000,000 | AF35: 4 | AG35: 1 | AH35: 2 | AI35: 3 | AJ35: 5 | AK35: Y | AL35: 5000 | AM35: =IF(AL35<1000,"0-1000",IF(AL35<2000,"1000-2000",IF(AL35<3000,"2000-3000",IF(AL35<5000,"3000-5000",IF(AL35<10000,"5000-10000","Over 10000"))))) -> 5000-10000
A36: 43762 | B36: 0.72916667 | D36: P | E36: 2 | F36: =VLOOKUP(E36,Key!$A$17:$B$21,2,FALSE) -> Road Vehicle | G36: 4 | H36: =VLOOKUP(G36,Key!$A$2:$B$13,2,FALSE) -> Minibus | I36: M | J36: 1 | K36: =VLOOKUP(J36,Key!$A$24:$B$29,2,FALSE) -> 20-29 | L36: HIOMA | M36: HIOMA | N36: UG | O36: 1 | P36: =VLOOKUP(O36,Key!$E$2:$F$9,2,FALSE) -> Home | Q36: KAKIRI | R36: WAKISO | S36: UG | T36: 1 | U36: =VLOOKUP(T36,Key!$E$2:$F$9,2,FALSE) -> Home | V36: =P36&"-"&U36 -> Home-Home | W36: 13000 | Y36: =IF(X36<10,"0-10",IF(X36<20,"10-20",IF(X36<40,"20-40",IF(X36<70,"40-70",IF(X36<100,"70-100",IF(X36<200,"100-200","Over 200")))))) -> 0-10 | Z36: 3 | AA36: =IF(Z36<0.5,"0-0.5",IF(Z36<1,"0.5-1.0",IF(Z36<2,"1.0-2.0",IF(Z36<3.5,"2.0-3.5","Over 3.5")))) -> 2.0-3.5 | AB36: 4 | AC36: =VLOOKUP(AB36,Key!$C$20:$D$29,2,FALSE) -> Office Worker | AD36: 2 | AE36: =VLOOKUP(AD36,Key!$E$20:$F$24,2,FALSE) -> 300,000-500,000 | AF36: 4 | AG36: 1 | AH36: 2 | AI36: 3 | AJ36: 3 | AK36: Y | AL36: 2000 | AM36: =IF(AL36<1000,"0-1000",IF(AL36<2000,"1000-2000",IF(AL36<3000,"2000-3000",IF(AL36<5000,"3000-5000",IF(AL36<10000,"5000-10000","Over 10000"))))) -> 2000-3000
A37: 43762 | B37: 0.38958333 | D37: P | E37: 2 | F37: =VLOOKUP(E37,Key!$A$17:$B$21,2,FALSE) -> Road Vehicle | G37: 4 | H37: =VLOOKUP(G37,Key!$A$2:$B$13,2,FALSE) -> Minibus | I37: M | J37: 1 | K37: =VLOOKUP(J37,Key!$A$24:$B$29,2,FALSE) -> 20-29 | L37: HIOMA | M37: HIOMA | N37: UG | O37: 1 | P37: =VLOOKUP(O37,Key!$E$2:$F$9,2,FALSE) -> Home | Q37: MUTANZIJO | R37: KAKUMIRO | S37: UG | T37: 4 | U37: =VLOOKUP(T37,Key!$E$2:$F$9,2,FALSE) -> Commercial | V37: =P37&"-"&U37 -> Home-Commercial | W37: 10000 | X37: 140 | Y37: =IF(X37<10,"0-10",IF(X37<20,"10-20",IF(X37<40,"20-40",IF(X37<70,"40-70",IF(X37<100,"70-100",IF(X37<200,"100-200","Over 200")))))) -> 100-200 | Z37: 3 | AA37: =IF(Z37<0.5,"0-0.5",IF(Z37<1,"0.5-1.0",IF(Z37<2,"1.0-2.0",IF(Z37<3.5,"2.0-3.5","Over 3.5")))) -> 2.0-3.5 | AB37: 7 | AC37: =VLOOKUP(AB37,Key!$C$20:$D$29,2,FALSE) -> Farmer | AD37: 2 | AE37: =VLOOKUP(AD37,Key!$E$20:$F$24,2,FALSE) -> 300,000-500,000 | AF37: 1 | AG37: 3 | AH37: 4 | AI37: 5 | AJ37: 2 | AK37: Y | AL37: 1000 | AM37: =IF(AL37<1000,"0-1000",IF(AL37<2000,"1000-2000",IF(AL37<3000,"2000-3000",IF(AL37<5000,"3000-5000",IF(AL37<10000,"5000-10000","Over 10000"))))) -> 1000-2000
A38: 43763 | B38: 0.72083333 | D38: P | E38: 2 | F38: =VLOOKUP(E38,Key!$A$17:$B$21,2,FALSE) -> Road Vehicle | G38: 4 | H38: =VLOOKUP(G38,Key!$A$2:$B$13,2,FALSE) -> Minibus | I38: M | J38: 1 | K38: =VLOOKUP(J38,Key!$A$24:$B$29,2,FALSE) -> 20-29 | L38: HIOMA | M38: HIOMA | N38: UG | O38: 1 | P38: =VLOOKUP(O38,Key!$E$2:$F$9,2,FALSE) -> Home | Q38: BUGEMBE | R38: KIKUUBE | S38: UG | T38: 6 | U38: =VLOOKUP(T38,Key!$E$2:$F$9,2,FALSE) -> Leisure/Social | V38: =P38&"-"&U38 -> Home-Leisure/Social | W38: 7000 | X38: 80 | Y38: =IF(X38<10,"0-10",IF(X38<20,"10-20",IF(X38<40,"20-40",IF(X38<70,"40-70",IF(X38<100,"70-100",IF(X38<200,"100-200","Over 200")))))) -> 70-100 | Z38: 2 | AA38: =IF(Z38<0.5,"0-0.5",IF(Z38<1,"0.5-1.0",IF(Z38<2,"1.0-2.0",IF(Z38<3.5,"2.0-3.5","Over 3.5")))) -> 2.0-3.5 | AB38: 1 | AC38: =VLOOKUP(AB38,Key!$C$20:$D$29,2,FALSE) -> Unemployed | AD38: 1 | AE38: =VLOOKUP(AD38,Key!$E$20:$F$24,2,FALSE) -> <300,000 | AF38: 1 | AG38: 2 | AI38: 2 | AJ38: 2 | AK38: Y | AL38: 3000 | AM38: =IF(AL38<1000,"0-1000",IF(AL38<2000,"1000-2000",IF(AL38<3000,"2000-3000",IF(AL38<5000,"3000-5000",IF(AL38<10000,"5000-10000","Over 10000"))))) -> 3000-5000
A39: 43763 | B39: 0.70625 | D39: D | E39: 2 | F39: =VLOOKUP(E39,Key!$A$17:$B$21,2,FALSE) -> Road Vehicle | G39: 4 | H39: =VLOOKUP(G39,Key!$A$2:$B$13,2,FALSE) -> Minibus | I39: M | J39: 1 | K39: =VLOOKUP(J39,Key!$A$24:$B$29,2,FALSE) -> 20-29 | L39: HIOMA | M39: HIOMA | N39: UG | O39: 1 | P39: =VLOOKUP(O39,Key!$E$2:$F$9,2,FALSE) -> Home | Q39: BUKWIRI | R39: KYANKWENZI | S39: UG | T39: 2 | U39: =VLOOKUP(T39,Key!$E$2:$F$9,2,FALSE) -> Work | V39: =P39&"-"&U39 -> Home-Work | W39: 65000 | X39: 75 | Y39: =IF(X39<10,"0-10",IF(X39<20,"10-20",IF(X39<40,"20-40",IF(X39<70,"40-70",IF(X39<100,"70-100",IF(X39<200,"100-200","Over 200")))))) -> 70-100 | Z39: 2 | AA39: =IF(Z39<0.5,"0-0.5",IF(Z39<1,"0.5-1.0",IF(Z39<2,"1.0-2.0",IF(Z39<3.5,"2.0-3.5","Over 3.5")))) -> 2.0-3.5 | AB39: 5 | AC39: =VLOOKUP(AB39,Key!$C$20:$D$29,2,FALSE) -> Professional | AD39: 3 | AE39: =VLOOKUP(AD39,Key!$E$20:$F$24,2,FALSE) -> 500,000-750,000 | AF39: 2 | AG39: 3 | AH39: 4 | AI39: 1 | AJ39: 5 | AK39: Y | AL39: 2000 | AM39: =IF(AL39<1000,"0-1000",IF(AL39<2000,"1000-2000",IF(AL39<3000,"2000-3000",IF(AL39<5000,"3000-5000",IF(AL39<10000,"5000-10000","Over 10000"))))) -> 2000-3000
A40: 43763 | B40: 0.68333333 | D40: P | E40: 2 | F40: =VLOOKUP(E40,Key!$A$17:$B$21,2,FALSE) -> Road Vehicle | G40: 4 | H40: =VLOOKUP(G40,Key!$A$2:$B$13,2,FALSE) -> Minibus | I40: M | J40: 1 | K40: =VLOOKUP(J40,Key!$A$24:$B$29,2,FALSE) -> 20-29 | L40: HIOMA | M40: HIOMA | N40: UG | O40: 1 | P40: =VLOOKUP(O40,Key!$E$2:$F$9,2,FALSE) -> Home | Q40: BUKWIRI | R40: KYANKWENZI | S40: UG | T40: 2 | U40: =VLOOKUP(T40,Key!$E$2:$F$9,2,FALSE) -> Work | V40: =P40&"-"&U40 -> Home-Work | W40: 8000 | X40: 80 | Y40: =IF(X40<10,"0-10",IF(X40<20,"10-20",IF(X40<40,"20-40",IF(X40<70,"40-70",IF(X40<100,"70-100",IF(X40<200,"100-200","Over 200")))))) -> 70-100 | Z40: 3 | AA40: =IF(Z40<0.5,"0-0.5",IF(Z40<1,"0.5-1.0",IF(Z40<2,"1.0-2.0",IF(Z40<3.5,"2.0-3.5","Over 3.5")))) -> 2.0-3.5 | AB40: 2 | AC40: =VLOOKUP(AB40,Key!$C$20:$D$29,2,FALSE) -> Manual Labour | AD40: 2 | AE40: =VLOOKUP(AD40,Key!$E$20:$F$24,2,FALSE) -> 300,000-500,000 | AF40: 2 | AG40: 3 | AH40: 2 | AI40: 4 | AJ40: 5 | AK40: Y | AL40: 3000 | AM40: =IF(AL40<1000,"0-1000",IF(AL40<2000,"1000-2000",IF(AL40<3000,"2000-3000",IF(AL40<5000,"3000-5000",IF(AL40<10000,"5000-10000","Over 10000"))))) -> 3000-5000
A41: 43763 | B41: 0.37986111 | D41: P | E41: 2 | F41: =VLOOKUP(E41,Key!$A$17:$B$21,2,FALSE) -> Road Vehicle | G41: 4 | H41: =VLOOKUP(G41,Key!$A$2:$B$13,2,FALSE) -> Minibus | I41: M | J41: 1 | K41: =VLOOKUP(J41,Key!$A$24:$B$29,2,FALSE) -> 20-29 | L41: HIOMA | M41: HIOMA | N41: UG | O41: 1 | P41: =VLOOKUP(O41,Key!$E$2:$F$9,2,FALSE) -> Home | Q41: MUTANZIJO | R41: KAKUMIRO | S41: UG | T41: 4 | U41: =VLOOKUP(T41,Key!$E$2:$F$9,2,FALSE) -> Commercial | V41: =P41&"-"&U41 -> Home-Commercial | W41: 1000 | X41: 140 | Y41: =IF(X41<10,"0-10",IF(X41<20,"10-20",IF(X41<40,"20-40",IF(X41<70,"40-70",IF(X41<100,"70-100",IF(X41<200,"100-200","Over 200")))))) -> 100-200 | Z41: 3 | AA41: =IF(Z41<0.5,"0-0.5",IF(Z41<1,"0.5-1.0",IF(Z41<2,"1.0-2.0",IF(Z41<3.5,"2.0-3.5","Over 3.5")))) -> 2.0-3.5 | AB41: 3 | AC41: =VLOOKUP(AB41,Key!$C$20:$D$29,2,FALSE) -> Artisan/Domestic | AD41: 2 | AE41: =VLOOKUP(AD41,Key!$E$20:$F$24,2,FALSE) -> 300,000-500,000 | AF41: 1 | AG41: 3 | AH41: 2 | AI41: 5 | AJ41: 4 | AK41: Y | AM41: =IF(AL41<1000,"0-1000",IF(AL41<2000,"1000-2000",IF(AL41<3000,"2000-3000",IF(AL41<5000,"3000-5000",IF(AL41<10000,"5000-10000","Over 10000"))))) -> 0-1000
A42: 43763 | B42: 0.38541667 | D42: P | E42: 2 | F42: =VLOOKUP(E42,Key!$A$17:$B$21,2,FALSE) -> Road Vehicle | G42: 4 | H42: =VLOOKUP(G42,Key!$A$2:$B$13,2,FALSE) -> Minibus | I42: M | J42: 1 | K42: =VLOOKUP(J42,Key!$A$24:$B$29,2,FALSE) -> 20-29 | L42: HIOMA | M42: HIOMA | N42: UG | O42: 1 | P42: =VLOOKUP(O42,Key!$E$2:$F$9,2,FALSE) -> Home | Q42: KISOLOHYA | R42: HIOMA | S42: UG | T42: 2 | U42: =VLOOKUP(T42,Key!$E$2:$F$9,2,FALSE) -> Work | V42: =P42&"-"&U42 -> Home-Work | W42: 5000 | X42: 30 | Y42: =IF(X42<10,"0-10",IF(X42<20,"10-20",IF(X42<40,"20-40",IF(X42<70,"40-70",IF(X42<100,"70-100",IF(X42<200,"100-200","Over 200")))))) -> 20-40 | Z42: 1 | AA42: =IF(Z42<0.5,"0-0.5",IF(Z42<1,"0.5-1.0",IF(Z42<2,"1.0-2.0",IF(Z42<3.5,"2.0-3.5","Over 3.5")))) -> 1.0-2.0 | AB42: 2 | AC42: =VLOOKUP(AB42,Key!$C$20:$D$29,2,FALSE) -> Manual Labour | AD42: 1 | AE42: =VLOOKUP(AD42,Key!$E$20:$F$24,2,FALSE) -> <300,000 | AF42: 2 | AG42: 3 | AH42: 5 | AI42: 4 | AJ42: 1 | AK42: Y | AL42: 5000 | AM42: =IF(AL42<1000,"0-1000",IF(AL42<2000,"1000-2000",IF(AL42<3000,"2000-3000",IF(AL42<5000,"3000-5000",IF(AL42<10000,"5000-10000","Over 10000"))))) -> 5000-10000
A43: 43763 | B43: 0.34166667 | D43: D | E43: 2 | F43: =VLOOKUP(E43,Key!$A$17:$B$21,2,FALSE) -> Road Vehicle | G43: 4 | H43: =VLOOKUP(G43,Key!$A$2:$B$13,2,FALSE) -> Minibus | I43: M | J43: 1 | K43: =VLOOKUP(J43,Key!$A$24:$B$29,2,FALSE) -> 20-29 | L43: HIOMA | M43: HIOMA | N43: UG | O43: 1 | P43: =VLOOKUP(O43,Key!$E$2:$F$9,2,FALSE) -> Home | Q43: MASINDI | R43: MASINDI | S43: UG | T43: 2 | U43: =VLOOKUP(T43,Key!$E$2:$F$9,2,FALSE) -> Work | V43: =P43&"-"&U43 -> Home-Work | W43: 120000 | X43: 45 | Y43: =IF(X43<10,"0-10",IF(X43<20,"10-20",IF(X43<40,"20-40",IF(X43<70,"40-70",IF(X43<100,"70-100",IF(X43<200,"100-200","Over 200")))))) -> 40-70 | Z43: 2 | AA43: =IF(Z43<0.5,"0-0.5",IF(Z43<1,"0.5-1.0",IF(Z43<2,"1.0-2.0",IF(Z43<3.5,"2.0-3.5","Over 3.5")))) -> 2.0-3.5 | AB43: 2 | AC43: =VLOOKUP(AB43,Key!$C$20:$D$29,2,FALSE) -> Manual Labour | AD43: 1 | AE43: =VLOOKUP(AD43,Key!$E$20:$F$24,2,FALSE) -> <300,000 | AF43: 1 | AG43: 5 | AH43: 3 | AI43: 1 | AJ43: 2 | AK43: Y | AL43: 3000 | AM43: =IF(AL43<1000,"0-1000",IF(AL43<2000,"1000-2000",IF(AL43<3000,"2000-3000",IF(AL43<5000,"3000-5000",IF(AL43<10000,"5000-10000","Over 10000"))))) -> 3000-5000
A44: 43763 | B44: 0.38958333 | D44: D | E44: 2 | F44: =VLOOKUP(E44,Key!$A$17:$B$21,2,FALSE) -> Road Vehicle | G44: 4 | H44: =VLOOKUP(G44,Key!$A$2:$B$13,2,FALSE) -> Minibus | I44: M | J44: 1 | K44: =VLOOKUP(J44,Key!$A$24:$B$29,2,FALSE) -> 20-29 | L44: HIOMA | M44: HIOMA | N44: UG | O44: 1 | P44: =VLOOKUP(O44,Key!$E$2:$F$9,2,FALSE) -> Home | Q44: KIGOLOBYA | R44: HIOMA | S44: UG | T44: 2 | U44: =VLOOKUP(T44,Key!$E$2:$F$9,2,FALSE) -> Work | V44: =P44&"-"&U44 -> Home-Work | W44: 5000 | X44: 15 | Y44: =IF(X44<10,"0-10",IF(X44<20,"10-20",IF(X44<40,"20-40",IF(X44<70,"40-70",IF(X44<100,"70-100",IF(X44<200,"100-200","Over 200")))))) -> 10-20 | Z44: 1 | AA44: =IF(Z44<0.5,"0-0.5",IF(Z44<1,"0.5-1.0",IF(Z44<2,"1.0-2.0",IF(Z44<3.5,"2.0-3.5","Over 3.5")))) -> 1.0-2.0 | AB44: 4 | AC44: =VLOOKUP(AB44,Key!$C$20:$D$29,2,FALSE) -> Office Worker | AD44: 1 | AE44: =VLOOKUP(AD44,Key!$E$20:$F$24,2,FALSE) -> <300,000 | AF44: 1 | AG44: 2 | AH44: 5 | AI44: 4 | AJ44: 2 | AK44: Y | AL44: 1000 | AM44: =IF(AL44<1000,"0-1000",IF(AL44<2000,"1000-2000",IF(AL44<3000,"2000-3000",IF(AL44<5000,"3000-5000",IF(AL44<10000,"5000-10000","Over 10000"))))) -> 1000-2000
A45: 43763 | B45: 0.39722222 | D45: P | E45: 2 | F45: =VLOOKUP(E45,Key!$A$17:$B$21,2,FALSE) -> Road Vehicle | G45: 4 | H45: =VLOOKUP(G45,Key!$A$2:$B$13,2,FALSE) -> Minibus | I45: M | J45: 1 | K45: =VLOOKUP(J45,Key!$A$24:$B$29,2,FALSE) -> 20-29 | L45: HIOMA | M45: HIOMA | N45: UG | O45: 6 | P45: =VLOOKUP(O45,Key!$E$2:$F$9,2,FALSE) -> Leisure/Social | Q45: KIGOLOBYA | R45: HIOMA | S45: UG | T45: 1 | U45: =VLOOKUP(T45,Key!$E$2:$F$9,2,FALSE) -> Home | V45: =P45&"-"&U45 -> Leisure/Social-Home | W45: 5000 | X45: 15 | Y45: =IF(X45<10,"0-10",IF(X45<20,"10-20",IF(X45<40,"20-40",IF(X45<70,"40-70",IF(X45<100,"70-100",IF(X45<200,"100-200","Over 200")))))) -> 10-20 | Z45: 2 | AA45: =IF(Z45<0.5,"0-0.5",IF(Z45<1,"0.5-1.0",IF(Z45<2,"1.0-2.0",IF(Z45<3.5,"2.0-3.5","Over 3.5")))) -> 2.0-3.5 | AB45: 7 | AC45: =VLOOKUP(AB45,Key!$C$20:$D$29,2,FALSE) -> Farmer | AD45: 1 | AE45: =VLOOKUP(AD45,Key!$E$20:$F$24,2,FALSE) -> <300,000 | AF45: 1 | AG45: 2 | AH45: 4 | AI45: 1 | AJ45: 2 | AK45: Y | AM45: =IF(AL45<1000,"0-1000",IF(AL45<2000,"1000-2000",IF(AL45<3000,"2000-3000",IF(AL45<5000,"3000-5000",IF(AL45<10000,"5000-10000","Over 10000"))))) -> 0-1000
A46: 43763 | B46: 0.4 | D46: P | E46: 2 | F46: =VLOOKUP(E46,Key!$A$17:$B$21,2,FALSE) -> Road Vehicle | G46: 4 | H46: =VLOOKUP(G46,Key!$A$2:$B$13,2,FALSE) -> Minibus | I46: M | J46: 1 | K46: =VLOOKUP(J46,Key!$A$24:$B$29,2,FALSE) -> 20-29 | L46: HIOMA | M46: HIOMA | N46: UG | O46: 1 | P46: =VLOOKUP(O46,Key!$E$2:$F$9,2,FALSE) -> Home | Q46: KIGOLOBYA | R46: HIOMA | S46: UG | T46: 6 | U46: =VLOOKUP(T46,Key!$E$2:$F$9,2,FALSE) -> Leisure/Social | V46: =P46&"-"&U46 -> Home-Leisure/Social | W46: 5000 | X46: 8 | Y46: =IF(X46<10,"0-10",IF(X46<20,"10-20",IF(X46<40,"20-40",IF(X46<70,"40-70",IF(X46<100,"70-100",IF(X46<200,"100-200","Over 200")))))) -> 0-10 | Z46: 1 | AA46: =IF(Z46<0.5,"0-0.5",IF(Z46<1,"0.5-1.0",IF(Z46<2,"1.0-2.0",IF(Z46<3.5,"2.0-3.5","Over 3.5")))) -> 1.0-2.0 | AB46: 6 | AC46: =VLOOKUP(AB46,Key!$C$20:$D$29,2,FALSE) -> Businessman | AD46: 2 | AE46: =VLOOKUP(AD46,Key!$E$20:$F$24,2,FALSE) -> 300,000-500,000 | AF46: 3 | AG46: 4 | AH46: 1 | AI46: 2 | AJ46: 5 | AK46: Y | AL46: 3000 | AM46: =IF(AL46<1000,"0-1000",IF(AL46<2000,"1000-2000",IF(AL46<3000,"2000-3000",IF(AL46<5000,"3000-5000",IF(AL46<10000,"5000-10000","Over 10000"))))) -> 3000-5000
A47: 43763 | B47: 0.40347222 | D47: D | E47: 2 | F47: =VLOOKUP(E47,Key!$A$17:$B$21,2,FALSE) -> Road Vehicle | G47: 4 | H47: =VLOOKUP(G47,Key!$A$2:$B$13,2,FALSE) -> Minibus | I47: M | J47: 1 | K47: =VLOOKUP(J47,Key!$A$24:$B$29,2,FALSE) -> 20-29 | L47: HIOMA | M47: HIOMA | N47: UG | O47: 1 | P47: =VLOOKUP(O47,Key!$E$2:$F$9,2,FALSE) -> Home | Q47: KYANKWENZI | R47: KIKUUBE | S47: UG | T47: 2 | U47: =VLOOKUP(T47,Key!$E$2:$F$9,2,FALSE) -> Work | V47: =P47&"-"&U47 -> Home-Work | W47: 70000 | Y47: =IF(X47<10,"0-10",IF(X47<20,"10-20",IF(X47<40,"20-40",IF(X47<70,"40-70",IF(X47<100,"70-100",IF(X47<200,"100-200","Over 200")))))) -> 0-10 | Z47: 4 | AA47: =IF(Z47<0.5,"0-0.5",IF(Z47<1,"0.5-1.0",IF(Z47<2,"1.0-2.0",IF(Z47<3.5,"2.0-3.5","Over 3.5")))) -> Over 3.5 | AB47: 2 | AC47: =VLOOKUP(AB47,Key!$C$20:$D$29,2,FALSE) -> Manual Labour | AD47: 2 | AE47: =VLOOKUP(AD47,Key!$E$20:$F$24,2,FALSE) -> 300,000-500,000 | AF47: 1 | AG47: 1 | AH47: 4 | AI47: 1 | AJ47: 2 | AK47: Y | AL47: 4000 | AM47: =IF(AL47<1000,"0-1000",IF(AL47<2000,"1000-2000",IF(AL47<3000,"2000-3000",IF(AL47<5000,"3000-5000",IF(AL47<10000,"5000-10000","Over 10000"))))) -> 3000-5000
A48: 43763 | B48: 0.40486111 | D48: P | E48: 2 | F48: =VLOOKUP(E48,Key!$A$17:$B$21,2,FALSE) -> Road Vehicle | G48: 4 | H48: =VLOOKUP(G48,Key!$A$2:$B$13,2,FALSE) -> Minibus | I48: M | J48: 1 | K48: =VLOOKUP(J48,Key!$A$24:$B$29,2,FALSE) -> 20-29 | L48: HIOMA | M48: HIOMA | N48: UG | O48: 1 | P48: =VLOOKUP(O48,Key!$E$2:$F$9,2,FALSE) -> Home | Q48: HIOMA | R48: HIOMA | S48: UG | T48: 4 | U48: =VLOOKUP(T48,Key!$E$2:$F$9,2,FALSE) -> Commercial | V48: =P48&"-"&U48 -> Home-Commercial | W48: 10000 | X48: 35 | Y48: =IF(X48<10,"0-10",IF(X48<20,"10-20",IF(X48<40,"20-40",IF(X48<70,"40-70",IF(X48<100,"70-100",IF(X48<200,"100-200","Over 200")))))) -> 20-40 | Z48: 2 | AA48: =IF(Z48<0.5,"0-0.5",IF(Z48<1,"0.5-1.0",IF(Z48<2,"1.0-2.0",IF(Z48<3.5,"2.0-3.5","Over 3.5")))) -> 2.0-3.5 | AB48: 5 | AC48: =VLOOKUP(AB48,Key!$C$20:$D$29,2,FALSE) -> Professional | AD48: 1 | AE48: =VLOOKUP(AD48,Key!$E$20:$F$24,2,FALSE) -> <300,000 | AF48: 2 | AG48: 3 | AH48: 5 | AI48: 1 | AJ48: 4 | AK48: Y | AM48: =IF(AL48<1000,"0-1000",IF(AL48<2000,"1000-2000",IF(AL48<3000,"2000-3000",IF(AL48<5000,"3000-5000",IF(AL48<10000,"5000-10000","Over 10000"))))) -> 0-1000
A49: 43763 | B49: 0.4375 | D49: D | E49: 2 | F49: =VLOOKUP(E49,Key!$A$17:$B$21,2,FALSE) -> Road Vehicle | G49: 4 | H49: =VLOOKUP(G49,Key!$A$2:$B$13,2,FALSE) -> Minibus | I49: M | J49: 1 | K49: =VLOOKUP(J49,Key!$A$24:$B$29,2,FALSE) -> 20-29 | L49: HIOMA | M49: HIOMA | N49: UG | O49: 1 | P49: =VLOOKUP(O49,Key!$E$2:$F$9,2,FALSE) -> Home | Q49: KYANKWENZI | R49: KIKUUBE | S49: UG | T49: 2 | U49: =VLOOKUP(T49,Key!$E$2:$F$9,2,FALSE) -> Work | V49: =P49&"-"&U49 -> Home-Work | W49: 80000 | Y49: =IF(X49<10,"0-10",IF(X49<20,"10-20",IF(X49<40,"20-40",IF(X49<70,"40-70",IF(X49<100,"70-100",IF(X49<200,"100-200","Over 200")))))) -> 0-10 | Z49: 2 | AA49: =IF(Z49<0.5,"0-0.5",IF(Z49<1,"0.5-1.0",IF(Z49<2,"1.0-2.0",IF(Z49<3.5,"2.0-3.5","Over 3.5")))) -> 2.0-3.5 | AB49: 5 | AC49: =VLOOKUP(AB49,Key!$C$20:$D$29,2,FALSE) -> Professional | AD49: 3 | AE49: =VLOOKUP(AD49,Key!$E$20:$F$24,2,FALSE) -> 500,000-750,000 | AF49: 2 | AG49: 1 | AH49: 4 | AI49: 5 | AJ49: 1 | AK49: Y | AL49: 1000 | AM49: =IF(AL49<1000,"0-1000",IF(AL49<2000,"1000-2000",IF(AL49<3000,"2000-3000",IF(AL49<5000,"3000-5000",IF(AL49<10000,"5000-10000","Over 10000"))))) -> 1000-2000
A50: 43763 | B50: 0.45208333 | D50: P | E50: 2 | F50: =VLOOKUP(E50,Key!$A$17:$B$21,2,FALSE) -> Road Vehicle | G50: 4 | H50: =VLOOKUP(G50,Key!$A$2:$B$13,2,FALSE) -> Minibus | I50: M | J50: 1 | K50: =VLOOKUP(J50,Key!$A$24:$B$29,2,FALSE) -> 20-29 | L50: HIOMA | M50: HIOMA | N50: UG | O50: 2 | P50: =VLOOKUP(O50,Key!$E$2:$F$9,2,FALSE) -> Work | Q50: MASINDI | R50: MASINDI | S50: UG | T50: 4 | U50: =VLOOKUP(T50,Key!$E$2:$F$9,2,FALSE) -> Commercial | V50: =P50&"-"&U50 -> Work-Commercial | W50: 10000 | X50: 48 | Y50: =IF(X50<10,"0-10",IF(X50<20,"10-20",IF(X50<40,"20-40",IF(X50<70,"40-70",IF(X50<100,"70-100",IF(X50<200,"100-200","Over 200")))))) -> 40-70 | Z50: 3 | AA50: =IF(Z50<0.5,"0-0.5",IF(Z50<1,"0.5-1.0",IF(Z50<2,"1.0-2.0",IF(Z50<3.5,"2.0-3.5","Over 3.5")))) -> 2.0-3.5 | AB50: 7 | AC50: =VLOOKUP(AB50,Key!$C$20:$D$29,2,FALSE) -> Farmer | AD50: 3 | AE50: =VLOOKUP(AD50,Key!$E$20:$F$24,2,FALSE) -> 500,000-750,000 | AF50: 1 | AG50: 5 | AH50: 4 | AI50: 2 | AJ50: 1 | AK50: Y | AL50: 5000 | AM50: =IF(AL50<1000,"0-1000",IF(AL50<2000,"1000-2000",IF(AL50<3000,"2000-3000",IF(AL50<5000,"3000-5000",IF(AL50<10000,"5000-10000","Over 10000"))))) -> 5000-10000
A51: 43763 | B51: 0.77847222 | D51: D | E51: 2 | F51: =VLOOKUP(E51,Key!$A$17:$B$21,2,FALSE) -> Road Vehicle | G51: 4 | H51: =VLOOKUP(G51,Key!$A$2:$B$13,2,FALSE) -> Minibus | I51: M | J51: 1 | K51: =VLOOKUP(J51,Key!$A$24:$B$29,2,FALSE) -> 20-29 | L51: HIOMA | M51: HIOMA | N51: UG | O51: 2 | P51: =VLOOKUP(O51,Key!$E$2:$F$9,2,FALSE) -> Work | Q51: KAMPALA | R51: KAMPALA | S51: UG | T51: 1 | U51: =VLOOKUP(T51,Key!$E$2:$F$9,2,FALSE) -> Home | V51: =P51&"-"&U51 -> Work-Home | W51: 150000 | X51: 180 | Y51: =IF(X51<10,"0-10",IF(X51<20,"10-20",IF(X51<40,"20-40",IF(X51<70,"40-70",IF(X51<100,"70-100",IF(X51<200,"100-200","Over 200")))))) -> 100-200 | Z51: 3 | AA51: =IF(Z51<0.5,"0-0.5",IF(Z51<1,"0.5-1.0",IF(Z51<2,"1.0-2.0",IF(Z51<3.5,"2.0-3.5","Over 3.5")))) -> 2.0-3.5 | AB51: 10 | AC51: =VLOOKUP(AB51,Key!$C$20:$D$29,2,FALSE) -> Other | AD51: 4 | AE51: =VLOOKUP(AD51,Key!$E$20:$F$24,2,FALSE) -> 750,000-1,000,000 | AF51: 2 | AG51: 3 | AH51: 5 | AI51: 4 | AJ51: 1 | AK51: Y | AL51: 4000 | AM51: =IF(AL51<1000,"0-1000",IF(AL51<2000,"1000-2000",IF(AL51<3000,"2000-3000",IF(AL51<5000,"3000-5000",IF(AL51<10000,"5000-10000","Over 10000"))))) -> 3000-5000
A52: 43763 | B52: 0.77222222 | D52: D | E52: 2 | F52: =VLOOKUP(E52,Key!$A$17:$B$21,2,FALSE) -> Road Vehicle | G52: 4 | H52: =VLOOKUP(G52,Key!$A$2:$B$13,2,FALSE) -> Minibus | I52: M | J52: 1 | K52: =VLOOKUP(J52,Key!$A$24:$B$29,2,FALSE) -> 20-29 | L52: HIOMA | M52: HIOMA | N52: UG | O52: 2 | P52: =VLOOKUP(O52,Key!$E$2:$F$9,2,FALSE) -> Work | Q52: KAMPALA | R52: KAMPALA | S52: UG | T52: 1 | U52: =VLOOKUP(T52,Key!$E$2:$F$9,2,FALSE) -> Home | V52: =P52&"-"&U52 -> Work-Home | W52: 200000 | X52: 300 | Y52: =IF(X52<10,"0-10",IF(X52<20,"10-20",IF(X52<40,"20-40",IF(X52<70,"40-70",IF(X52<100,"70-100",IF(X52<200,"100-200","Over 200")))))) -> Over 200 | Z52: 4 | AA52: =IF(Z52<0.5,"0-0.5",IF(Z52<1,"0.5-1.0",IF(Z52<2,"1.0-2.0",IF(Z52<3.5,"2.0-3.5","Over 3.5")))) -> Over 3.5 | AB52: 10 | AC52: =VLOOKUP(AB52,Key!$C$20:$D$29,2,FALSE) -> Other | AD52: 3 | AE52: =VLOOKUP(AD52,Key!$E$20:$F$24,2,FALSE) -> 500,000-750,000 | AF52: 3 | AG52: 2 | AH52: 4 | AI52: 5 | AJ52: 1 | AK52: Y | AL52: 1000 | AM52: =IF(AL52<1000,"0-1000",IF(AL52<2000,"1000-2000",IF(AL52<3000,"2000-3000",IF(AL52<5000,"3000-5000",IF(AL52<10000,"5000-10000","Over 10000"))))) -> 1000-2000
A53: 43763 | B53: 0.76388889 | D53: D | E53: 2 | F53: =VLOOKUP(E53,Key!$A$17:$B$21,2,FALSE) -> Road Vehicle | G53: 4 | H53: =VLOOKUP(G53,Key!$A$2:$B$13,2,FALSE) -> Minibus | I53: M | J53: 1 | K53: =VLOOKUP(J53,Key!$A$24:$B$29,2,FALSE) -> 20-29 | L53: HIOMA | M53: HIOMA | N53: UG | O53: 2 | P53: =VLOOKUP(O53,Key!$E$2:$F$9,2,FALSE) -> Work | Q53: KAMPALA | R53: KAMPALA | S53: UG | T53: 1 | U53: =VLOOKUP(T53,Key!$E$2:$F$9,2,FALSE) -> Home | V53: =P53&"-"&U53 -> Work-Home | W53: 180000 | X53: 200 | Y53: =IF(X53<10,"0-10",IF(X53<20,"10-20",IF(X53<40,"20-40",IF(X53<70,"40-70",IF(X53<100,"70-100",IF(X53<200,"100-200","Over 200")))))) -> Over 200 | Z53: 3 | AA53: =IF(Z53<0.5,"0-0.5",IF(Z53<1,"0.5-1.0",IF(Z53<2,"1.0-2.0",IF(Z53<3.5,"2.0-3.5","Over 3.5")))) -> 2.0-3.5 | AB53: 10 | AC53: =VLOOKUP(AB53,Key!$C$20:$D$29,2,FALSE) -> Other | AD53: 4 | AE53: =VLOOKUP(AD53,Key!$E$20:$F$24,2,FALSE) -> 750,000-1,000,000 | AF53: 2 | AG53: 3 | AH53: 5 | AI53: 4 | AJ53: 1 | AK53: Y | AM53: =IF(AL53<1000,"0-1000",IF(AL53<2000,"1000-2000",IF(AL53<3000,"2000-3000",IF(AL53<5000,"3000-5000",IF(AL53<10000,"5000-10000","Over 10000"))))) -> 0-1000
A54: 43763 | B54: 0.70277778 | D54: D | E54: 2 | F54: =VLOOKUP(E54,Key!$A$17:$B$21,2,FALSE) -> Road Vehicle | G54: 4 | H54: =VLOOKUP(G54,Key!$A$2:$B$13,2,FALSE) -> Minibus | I54: M | J54: 1 | K54: =VLOOKUP(J54,Key!$A$24:$B$29,2,FALSE) -> 20-29 | L54: HIOMA | M54: HIOMA | N54: UG | O54: 2 | P54: =VLOOKUP(O54,Key!$E$2:$F$9,2,FALSE) -> Work | Q54: BULIISA | R54: BULIISA | S54: UG | T54: 1 | U54: =VLOOKUP(T54,Key!$E$2:$F$9,2,FALSE) -> Home | V54: =P54&"-"&U54 -> Work-Home | W54: 80000 | X54: 75 | Y54: =IF(X54<10,"0-10",IF(X54<20,"10-20",IF(X54<40,"20-40",IF(X54<70,"40-70",IF(X54<100,"70-100",IF(X54<200,"100-200","Over 200")))))) -> 70-100 | Z54: 2 | AA54: =IF(Z54<0.5,"0-0.5",IF(Z54<1,"0.5-1.0",IF(Z54<2,"1.0-2.0",IF(Z54<3.5,"2.0-3.5","Over 3.5")))) -> 2.0-3.5 | AB54: 10 | AC54: =VLOOKUP(AB54,Key!$C$20:$D$29,2,FALSE) -> Other | AD54: 4 | AE54: =VLOOKUP(AD54,Key!$E$20:$F$24,2,FALSE) -> 750,000-1,000,000 | AF54: 4 | AG54: 3 | AI54: 1 | AJ54: 2 | AK54: Y | AM54: =IF(AL54<1000,"0-1000",IF(AL54<2000,"1000-2000",IF(AL54<3000,"2000-3000",IF(AL54<5000,"3000-5000",IF(AL54<10000,"5000-10000","Over 10000"))))) -> 0-1000
A55: 43763 | B55: 0.69583333 | D55: P | E55: 2 | F55: =VLOOKUP(E55,Key!$A$17:$B$21,2,FALSE) -> Road Vehicle | G55: 4 | H55: =VLOOKUP(G55,Key!$A$2:$B$13,2,FALSE) -> Minibus | I55: M | J55: 1 | K55: =VLOOKUP(J55,Key!$A$24:$B$29,2,FALSE) -> 20-29 | L55: HIOMA | M55: HIOMA | N55: UG | O55: 6 | P55: =VLOOKUP(O55,Key!$E$2:$F$9,2,FALSE) -> Leisure/Social | Q55: BULIISA | R55: BULIISA | S55: UG | T55: 1 | U55: =VLOOKUP(T55,Key!$E$2:$F$9,2,FALSE) -> Home | V55: =P55&"-"&U55 -> Leisure/Social-Home | W55: 10000 | X55: 77 | Y55: =IF(X55<10,"0-10",IF(X55<20,"10-20",IF(X55<40,"20-40",IF(X55<70,"40-70",IF(X55<100,"70-100",IF(X55<200,"100-200","Over 200")))))) -> 70-100 | Z55: 2 | AA55: =IF(Z55<0.5,"0-0.5",IF(Z55<1,"0.5-1.0",IF(Z55<2,"1.0-2.0",IF(Z55<3.5,"2.0-3.5","Over 3.5")))) -> 2.0-3.5 | AB55: 5 | AC55: =VLOOKUP(AB55,Key!$C$20:$D$29,2,FALSE) -> Professional | AD55: 5 | AE55: =VLOOKUP(AD55,Key!$E$20:$F$24,2,FALSE) -> >1,000,000 | AF55: 1 | AG55: 2 | AH55: 5 | AI55: 4 | AJ55: 3 | AK55: Y | AL55: 10000 | AM55: =IF(AL55<1000,"0-1000",IF(AL55<2000,"1000-2000",IF(AL55<3000,"2000-3000",IF(AL55<5000,"3000-5000",IF(AL55<10000,"5000-10000","Over 10000"))))) -> Over 10000
A56: 43763 | B56: 0.69027778 | D56: P | E56: 2 | F56: =VLOOKUP(E56,Key!$A$17:$B$21,2,FALSE) -> Road Vehicle | G56: 4 | H56: =VLOOKUP(G56,Key!$A$2:$B$13,2,FALSE) -> Minibus | I56: M | J56: 1 | K56: =VLOOKUP(J56,Key!$A$24:$B$29,2,FALSE) -> 20-29 | L56: HIOMA | M56: HIOMA | N56: UG | O56: 2 | P56: =VLOOKUP(O56,Key!$E$2:$F$9,2,FALSE) -> Work | Q56: KAGADI | R56: KAGADI | S56: UG | T56: 1 | U56: =VLOOKUP(T56,Key!$E$2:$F$9,2,FALSE) -> Home | V56: =P56&"-"&U56 -> Work-Home | W56: 150000 | X56: 70 | Y56: =IF(X56<10,"0-10",IF(X56<20,"10-20",IF(X56<40,"20-40",IF(X56<70,"40-70",IF(X56<100,"70-100",IF(X56<200,"100-200","Over 200")))))) -> 70-100 | Z56: 2 | AA56: =IF(Z56<0.5,"0-0.5",IF(Z56<1,"0.5-1.0",IF(Z56<2,"1.0-2.0",IF(Z56<3.5,"2.0-3.5","Over 3.5")))) -> 2.0-3.5 | AB56: 5 | AC56: =VLOOKUP(AB56,Key!$C$20:$D$29,2,FALSE) -> Professional | AD56: 4 | AE56: =VLOOKUP(AD56,Key!$E$20:$F$24,2,FALSE) -> 750,000-1,000,000 | AF56: 5 | AG56: 1 | AH56: 2 | AI56: 2 | AJ56: 5 | AK56: Y | AL56: 8000 | AM56: =IF(AL56<1000,"0-1000",IF(AL56<2000,"1000-2000",IF(AL56<3000,"2000-3000",IF(AL56<5000,"3000-5000",IF(AL56<10000,"5000-10000","Over 10000"))))) -> 5000-10000
A57: 43763 | B57: 0.67430556 | D57: D | E57: 2 | F57: =VLOOKUP(E57,Key!$A$17:$B$21,2,FALSE) -> Road Vehicle | G57: 4 | H57: =VLOOKUP(G57,Key!$A$2:$B$13,2,FALSE) -> Minibus | I57: M | J57: 1 | K57: =VLOOKUP(J57,Key!$A$24:$B$29,2,FALSE) -> 20-29 | L57: HIOMA | M57: HIOMA | N57: UG | O57: 2 | P57: =VLOOKUP(O57,Key!$E$2:$F$9,2,FALSE) -> Work | Q57: MASINDI | R57: MASINDI | S57: UG | T57: 1 | U57: =VLOOKUP(T57,Key!$E$2:$F$9,2,FALSE) -> Home | V57: =P57&"-"&U57 -> Work-Home | W57: 200000 | X57: 115 | Y57: =IF(X57<10,"0-10",IF(X57<20,"10-20",IF(X57<40,"20-40",IF(X57<70,"40-70",IF(X57<100,"70-100",IF(X57<200,"100-200","Over 200")))))) -> 100-200 | Z57: 3 | AA57: =IF(Z57<0.5,"0-0.5",IF(Z57<1,"0.5-1.0",IF(Z57<2,"1.0-2.0",IF(Z57<3.5,"2.0-3.5","Over 3.5")))) -> 2.0-3.5 | AB57: 10 | AC57: =VLOOKUP(AB57,Key!$C$20:$D$29,2,FALSE) -> Other | AD57: 3 | AE57: =VLOOKUP(AD57,Key!$E$20:$F$24,2,FALSE) -> 500,000-750,000 | AF57: 5 | AG57: 1 | AH57: 3 | AI57: 4 | AJ57: 5 | AK57: Y | AL57: 2000 | AM57: =IF(AL57<1000,"0-1000",IF(AL57<2000,"1000-2000",IF(AL57<3000,"2000-3000",IF(AL57<5000,"3000-5000",IF(AL57<10000,"5000-10000","Over 10000"))))) -> 2000-3000
A58: 43763 | B58: 0.67083333 | D58: D | E58: 2 | F58: =VLOOKUP(E58,Key!$A$17:$B$21,2,FALSE) -> Road Vehicle | G58: 4 | H58: =VLOOKUP(G58,Key!$A$2:$B$13,2,FALSE) -> Minibus | I58: M | J58: 1 | K58: =VLOOKUP(J58,Key!$A$24:$B$29,2,FALSE) -> 20-29 | L58: HIOMA | M58: HIOMA | N58: UG | O58: 2 | P58: =VLOOKUP(O58,Key!$E$2:$F$9,2,FALSE) -> Work | Q58: MASINDI | R58: MASINDI | S58: UG | T58: 1 | U58: =VLOOKUP(T58,Key!$E$2:$F$9,2,FALSE) -> Home | V58: =P58&"-"&U58 -> Work-Home | W58: 180000 | X58: 100 | Y58: =IF(X58<10,"0-10",IF(X58<20,"10-20",IF(X58<40,"20-40",IF(X58<70,"40-70",IF(X58<100,"70-100",IF(X58<200,"100-200","Over 200")))))) -> 100-200 | Z58: 2 | AA58: =IF(Z58<0.5,"0-0.5",IF(Z58<1,"0.5-1.0",IF(Z58<2,"1.0-2.0",IF(Z58<3.5,"2.0-3.5","Over 3.5")))) -> 2.0-3.5 | AB58: 10 | AC58: =VLOOKUP(AB58,Key!$C$20:$D$29,2,FALSE) -> Other | AD58: 2 | AE58: =VLOOKUP(AD58,Key!$E$20:$F$24,2,FALSE) -> 300,000-500,000 | AF58: 2 | AG58: 1 | AH58: 3 | AI58: 5 | AJ58: 4 | AK58: Y | AM58: =IF(AL58<1000,"0-1000",IF(AL58<2000,"1000-2000",IF(AL58<3000,"2000-3000",IF(AL58<5000,"3000-5000",IF(AL58<10000,"5000-10000","Over 10000"))))) -> 0-1000
A59: 43763 | B59: 0.57361111 | D59: P | E59: 2 | F59: =VLOOKUP(E59,Key!$A$17:$B$21,2,FALSE) -> Road Vehicle | G59: 4 | H59: =VLOOKUP(G59,Key!$A$2:$B$13,2,FALSE) -> Minibus | I59: M | J59: 1 | K59: =VLOOKUP(J59,Key!$A$24:$B$29,2,FALSE) -> 20-29 | L59: KAISO | M59: KAISO | N59: UG | O59: 1 | P59: =VLOOKUP(O59,Key!$E$2:$F$9,2,FALSE) -> Home | Q59: HIOMA | R59: HIOMA | S59: UG | T59: 2 | U59: =VLOOKUP(T59,Key!$E$2:$F$9,2,FALSE) -> Work | V59: =P59&"-"&U59 -> Home-Work | W59: 15000 | X59: 100 | Y59: =IF(X59<10,"0-10",IF(X59<20,"10-20",IF(X59<40,"20-40",IF(X59<70,"40-70",IF(X59<100,"70-100",IF(X59<200,"100-200","Over 200")))))) -> 100-200 | Z59: 3 | AA59: =IF(Z59<0.5,"0-0.5",IF(Z59<1,"0.5-1.0",IF(Z59<2,"1.0-2.0",IF(Z59<3.5,"2.0-3.5","Over 3.5")))) -> 2.0-3.5 | AB59: 6 | AC59: =VLOOKUP(AB59,Key!$C$20:$D$29,2,FALSE) -> Businessman | AD59: 4 | AE59: =VLOOKUP(AD59,Key!$E$20:$F$24,2,FALSE) -> 750,000-1,000,000 | AF59: 5 | AG59: 3 | AH59: 4 | AI59: 5 | AJ59: 2 | AK59: Y | AL59: 4000 | AM59: =IF(AL59<1000,"0-1000",IF(AL59<2000,"1000-2000",IF(AL59<3000,"2000-3000",IF(AL59<5000,"3000-5000",IF(AL59<10000,"5000-10000","Over 10000"))))) -> 3000-5000
A60: 43764 | B60: 0.325 | D60: P | E60: 2 | F60: =VLOOKUP(E60,Key!$A$17:$B$21,2,FALSE) -> Road Vehicle | G60: 4 | H60: =VLOOKUP(G60,Key!$A$2:$B$13,2,FALSE) -> Minibus | I60: M | J60: 1 | K60: =VLOOKUP(J60,Key!$A$24:$B$29,2,FALSE) -> 20-29 | L60: HIOMA | M60: HIOMA | N60: UG | O60: 1 | P60: =VLOOKUP(O60,Key!$E$2:$F$9,2,FALSE) -> Home | Q60: KAMPALA | R60: KAMPALA | S60: UG | T60: 2 | U60: =VLOOKUP(T60,Key!$E$2:$F$9,2,FALSE) -> Work | V60: =P60&"-"&U60 -> Home-Work | W60: 13000 | Y60: =IF(X60<10,"0-10",IF(X60<20,"10-20",IF(X60<40,"20-40",IF(X60<70,"40-70",IF(X60<100,"70-100",IF(X60<200,"100-200","Over 200")))))) -> 0-10 | Z60: 3 | AA60: =IF(Z60<0.5,"0-0.5",IF(Z60<1,"0.5-1.0",IF(Z60<2,"1.0-2.0",IF(Z60<3.5,"2.0-3.5","Over 3.5")))) -> 2.0-3.5 | AB60: 3 | AC60: =VLOOKUP(AB60,Key!$C$20:$D$29,2,FALSE) -> Artisan/Domestic | AD60: 1 | AE60: =VLOOKUP(AD60,Key!$E$20:$F$24,2,FALSE) -> <300,000 | AF60: 3 | AG60: 2 | AH60: 5 | AI60: 1 | AJ60: 4 | AK60: Y | AM60: =IF(AL60<1000,"0-1000",IF(AL60<2000,"1000-2000",IF(AL60<3000,"2000-3000",IF(AL60<5000,"3000-5000",IF(AL60<10000,"5000-10000","Over 10000"))))) -> 0-1000
A61: 43764 | B61: 0.6625 | D61: P | E61: 2 | F61: =VLOOKUP(E61,Key!$A$17:$B$21,2,FALSE) -> Road Vehicle | G61: 4 | H61: =VLOOKUP(G61,Key!$A$2:$B$13,2,FALSE) -> Minibus | I61: M | J61: 1 | K61: =VLOOKUP(J61,Key!$A$24:$B$29,2,FALSE) -> 20-29 | L61: HIOMA | M61: HIOMA | N61: UG | O61: 2 | P61: =VLOOKUP(O61,Key!$E$2:$F$9,2,FALSE) -> Work | Q61: BUSUNJJU | R61: WAKISO | S61: UG | T61: 4 | U61: =VLOOKUP(T61,Key!$E$2:$F$9,2,FALSE) -> Commercial | V61: =P61&"-"&U61 -> Work-Commercial | W61: 12000 | Y61: =IF(X61<10,"0-10",IF(X61<20,"10-20",IF(X61<40,"20-40",IF(X61<70,"40-70",IF(X61<100,"70-100",IF(X61<200,"100-200","Over 200")))))) -> 0-10 | Z61: 3 | AA61: =IF(Z61<0.5,"0-0.5",IF(Z61<1,"0.5-1.0",IF(Z61<2,"1.0-2.0",IF(Z61<3.5,"2.0-3.5","Over 3.5")))) -> 2.0-3.5 | AB61: 4 | AC61: =VLOOKUP(AB61,Key!$C$20:$D$29,2,FALSE) -> Office Worker | AD61: 2 | AE61: =VLOOKUP(AD61,Key!$E$20:$F$24,2,FALSE) -> 300,000-500,000 | AF61: 4 | AG61: 2 | AH61: 1 | AI61: 3 | AJ61: 5 | AK61: Y | AM61: =IF(AL61<1000,"0-1000",IF(AL61<2000,"1000-2000",IF(AL61<3000,"2000-3000",IF(AL61<5000,"3000-5000",IF(AL61<10000,"5000-10000","Over 10000"))))) -> 0-1000
A62: 43764 | B62: 0.65625 | D62: P | E62: 2 | F62: =VLOOKUP(E62,Key!$A$17:$B$21,2,FALSE) -> Road Vehicle | G62: 4 | H62: =VLOOKUP(G62,Key!$A$2:$B$13,2,FALSE) -> Minibus | I62: M | J62: 1 | K62: =VLOOKUP(J62,Key!$A$24:$B$29,2,FALSE) -> 20-29 | L62: HIOMA | M62: HIOMA | N62: UG | O62: 1 | P62: =VLOOKUP(O62,Key!$E$2:$F$9,2,FALSE) -> Home | Q62: HIOMA | R62: HIOMA | S62: UG | T62: 4 | U62: =VLOOKUP(T62,Key!$E$2:$F$9,2,FALSE) -> Commercial | V62: =P62&"-"&U62 -> Home-Commercial | W62: 6000 | Y62: =IF(X62<10,"0-10",IF(X62<20,"10-20",IF(X62<40,"20-40",IF(X62<70,"40-70",IF(X62<100,"70-100",IF(X62<200,"100-200","Over 200")))))) -> 0-10 | Z62: 2 | AA62: =IF(Z62<0.5,"0-0.5",IF(Z62<1,"0.5-1.0",IF(Z62<2,"1.0-2.0",IF(Z62<3.5,"2.0-3.5","Over 3.5")))) -> 2.0-3.5 | AB62: 6 | AC62: =VLOOKUP(AB62,Key!$C$20:$D$29,2,FALSE) -> Businessman | AD62: 3 | AE62: =VLOOKUP(AD62,Key!$E$20:$F$24,2,FALSE) -> 500,000-750,000 | AF62: 2 | AG62: 3 | AH62: 1 | AI62: 5 | AJ62: 4 | AK62: Y | AL62: 1000 | AM62: =IF(AL62<1000,"0-1000",IF(AL62<2000,"1000-2000",IF(AL62<3000,"2000-3000",IF(AL62<5000,"3000-5000",IF(AL62<10000,"5000-10000","Over 10000"))))) -> 1000-2000
A63: 43764 | B63: 0.63333333 | D63: P | E63: 2 | F63: =VLOOKUP(E63,Key!$A$17:$B$21,2,FALSE) -> Road Vehicle | G63: 4 | H63: =VLOOKUP(G63,Key!$A$2:$B$13,2,FALSE) -> Minibus | I63: M | J63: 1 | K63: =VLOOKUP(J63,Key!$A$24:$B$29,2,FALSE) -> 20-29 | L63: HIOMA | M63: HIOMA | N63: UG | O63: 1 | P63: =VLOOKUP(O63,Key!$E$2:$F$9,2,FALSE) -> Home | Q63: KABOGA | R63: KIKUUBE | S63: UG | T63: 2 | U63: =VLOOKUP(T63,Key!$E$2:$F$9,2,FALSE) -> Work | V63: =P63&"-"&U63 -> Home-Work | W63: 6000 | Y63: =IF(X63<10,"0-10",IF(X63<20,"10-20",IF(X63<40,"20-40",IF(X63<70,"40-70",IF(X63<100,"70-100",IF(X63<200,"100-200","Over 200")))))) -> 0-10 | Z63: 1 | AA63: =IF(Z63<0.5,"0-0.5",IF(Z63<1,"0.5-1.0",IF(Z63<2,"1.0-2.0",IF(Z63<3.5,"2.0-3.5","Over 3.5")))) -> 1.0-2.0 | AB63: 10 | AC63: =VLOOKUP(AB63,Key!$C$20:$D$29,2,FALSE) -> Other | AD63: 3 | AE63: =VLOOKUP(AD63,Key!$E$20:$F$24,2,FALSE) -> 500,000-750,000 | AF63: 1 | AG63: 1 | AH63: 1 | AI63: 1 | AJ63: 2 | AK63: Y | AM63: =IF(AL63<1000,"0-1000",IF(AL63<2000,"1000-2000",IF(AL63<3000,"2000-3000",IF(AL63<5000,"3000-5000",IF(AL63<10000,"5000-10000","Over 10000"))))) -> 0-1000
A64: 43764 | B64: 0.63333333 | D64: P | E64: 2 | F64: =VLOOKUP(E64,Key!$A$17:$B$21,2,FALSE) -> Road Vehicle | G64: 4 | H64: =VLOOKUP(G64,Key!$A$2:$B$13,2,FALSE) -> Minibus | I64: M | J64: 1 | K64: =VLOOKUP(J64,Key!$A$24:$B$29,2,FALSE) -> 20-29 | L64: HIOMA | M64: HIOMA | N64: UG | O64: 1 | P64: =VLOOKUP(O64,Key!$E$2:$F$9,2,FALSE) -> Home | Q64: KABOGA | R64: KIKUUBE | S64: UG | T64: 2 | U64: =VLOOKUP(T64,Key!$E$2:$F$9,2,FALSE) -> Work | V64: =P64&"-"&U64 -> Home-Work | W64: 6000 | Y64: =IF(X64<10,"0-10",IF(X64<20,"10-20",IF(X64<40,"20-40",IF(X64<70,"40-70",IF(X64<100,"70-100",IF(X64<200,"100-200","Over 200")))))) -> 0-10 | Z64: 1 | AA64: =IF(Z64<0.5,"0-0.5",IF(Z64<1,"0.5-1.0",IF(Z64<2,"1.0-2.0",IF(Z64<3.5,"2.0-3.5","Over 3.5")))) -> 1.0-2.0 | AB64: 10 | AC64: =VLOOKUP(AB64,Key!$C$20:$D$29,2,FALSE) -> Other | AD64: 2 | AE64: =VLOOKUP(AD64,Key!$E$20:$F$24,2,FALSE) -> 300,000-500,000 | AF64: 1 | AG64: 2 | AH64: 1 | AI64: 1 | AJ64: 1 | AK64: Y | AM64: =IF(AL64<1000,"0-1000",IF(AL64<2000,"1000-2000",IF(AL64<3000,"2000-3000",IF(AL64<5000,"3000-5000",IF(AL64<10000,"5000-10000","Over 10000"))))) -> 0-1000
A65: 43764 | B65: 0.60694444 | D65: P | E65: 2 | F65: =VLOOKUP(E65,Key!$A$17:$B$21,2,FALSE) -> Road Vehicle | G65: 4 | H65: =VLOOKUP(G65,Key!$A$2:$B$13,2,FALSE) -> Minibus | I65: M | J65: 1 | K65: =VLOOKUP(J65,Key!$A$24:$B$29,2,FALSE) -> 20-29 | L65: HIOMA | M65: HIOMA | N65: UG | O65: 8 | P65: =VLOOKUP(O65,Key!$E$2:$F$9,2,FALSE) -> Others | Q65: KAMPALA | R65: KAMPALA | S65: UG | T65: 2 | U65: =VLOOKUP(T65,Key!$E$2:$F$9,2,FALSE) -> Work | V65: =P65&"-"&U65 -> Others-Work | W65: 13000 | Y65: =IF(X65<10,"0-10",IF(X65<20,"10-20",IF(X65<40,"20-40",IF(X65<70,"40-70",IF(X65<100,"70-100",IF(X65<200,"100-200","Over 200")))))) -> 0-10 | Z65: 5 | AA65: =IF(Z65<0.5,"0-0.5",IF(Z65<1,"0.5-1.0",IF(Z65<2,"1.0-2.0",IF(Z65<3.5,"2.0-3.5","Over 3.5")))) -> Over 3.5 | AB65: 3 | AC65: =VLOOKUP(AB65,Key!$C$20:$D$29,2,FALSE) -> Artisan/Domestic | AD65: 1 | AE65: =VLOOKUP(AD65,Key!$E$20:$F$24,2,FALSE) -> <300,000 | AF65: 3 | AG65: 4 | AH65: 2 | AI65: 1 | AJ65: 5 | AK65: Y | AM65: =IF(AL65<1000,"0-1000",IF(AL65<2000,"1000-2000",IF(AL65<3000,"2000-3000",IF(AL65<5000,"3000-5000",IF(AL65<10000,"5000-10000","Over 10000"))))) -> 0-1000
A66: 43764 | B66: 0.60833333 | D66: P | E66: 2 | F66: =VLOOKUP(E66,Key!$A$17:$B$21,2,FALSE) -> Road Vehicle | G66: 4 | H66: =VLOOKUP(G66,Key!$A$2:$B$13,2,FALSE) -> Minibus | I66: M | J66: 1 | K66: =VLOOKUP(J66,Key!$A$24:$B$29,2,FALSE) -> 20-29 | L66: HIOMA | M66: HIOMA | N66: UG | O66: 4 | P66: =VLOOKUP(O66,Key!$E$2:$F$9,2,FALSE) -> Commercial | Q66: KAISO | R66: KIKUUBE | S66: UG | T66: 4 | U66: =VLOOKUP(T66,Key!$E$2:$F$9,2,FALSE) -> Commercial | V66: =P66&"-"&U66 -> Commercial-Commercial | W66: 8000 | Y66: =IF(X66<10,"0-10",IF(X66<20,"10-20",IF(X66<40,"20-40",IF(X66<70,"40-70",IF(X66<100,"70-100",IF(X66<200,"100-200","Over 200")))))) -> 0-10 | Z66: 2 | AA66: =IF(Z66<0.5,"0-0.5",IF(Z66<1,"0.5-1.0",IF(Z66<2,"1.0-2.0",IF(Z66<3.5,"2.0-3.5","Over 3.5")))) -> 2.0-3.5 | AB66: 6 | AC66: =VLOOKUP(AB66,Key!$C$20:$D$29,2,FALSE) -> Businessman | AD66: 4 | AE66: =VLOOKUP(AD66,Key!$E$20:$F$24,2,FALSE) -> 750,000-1,000,000 | AF66: 2 | AG66: 3 | AH66: 5 | AI66: 1 | AJ66: 4 | AK66: Y | AM66: =IF(AL66<1000,"0-1000",IF(AL66<2000,"1000-2000",IF(AL66<3000,"2000-3000",IF(AL66<5000,"3000-5000",IF(AL66<10000,"5000-10000","Over 10000"))))) -> 0-1000
A67: 43764 | B67: 0.60347222 | D67: P | E67: 2 | F67: =VLOOKUP(E67,Key!$A$17:$B$21,2,FALSE) -> Road Vehicle | G67: 4 | H67: =VLOOKUP(G67,Key!$A$2:$B$13,2,FALSE) -> Minibus | I67: M | J67: 1 | K67: =VLOOKUP(J67,Key!$A$24:$B$29,2,FALSE) -> 20-29 | L67: HIOMA | M67: HIOMA | N67: UG | O67: 1 | P67: =VLOOKUP(O67,Key!$E$2:$F$9,2,FALSE) -> Home | Q67: KASUBI | R67: KAMPALA | S67: UG | T67: 1 | U67: =VLOOKUP(T67,Key!$E$2:$F$9,2,FALSE) -> Home | V67: =P67&"-"&U67 -> Home-Home | W67: 13000 | Y67: =IF(X67<10,"0-10",IF(X67<20,"10-20",IF(X67<40,"20-40",IF(X67<70,"40-70",IF(X67<100,"70-100",IF(X67<200,"100-200","Over 200")))))) -> 0-10 | Z67: 3 | AA67: =IF(Z67<0.5,"0-0.5",IF(Z67<1,"0.5-1.0",IF(Z67<2,"1.0-2.0",IF(Z67<3.5,"2.0-3.5","Over 3.5")))) -> 2.0-3.5 | AB67: 1 | AC67: =VLOOKUP(AB67,Key!$C$20:$D$29,2,FALSE) -> Unemployed | AD67: 1 | AE67: =VLOOKUP(AD67,Key!$E$20:$F$24,2,FALSE) -> <300,000 | AF67: 1 | AG67: 2 | AH67: 4 | AI67: 3 | AJ67: 2 | AK67: Y | AM67: =IF(AL67<1000,"0-1000",IF(AL67<2000,"1000-2000",IF(AL67<3000,"2000-3000",IF(AL67<5000,"3000-5000",IF(AL67<10000,"5000-10000","Over 10000"))))) -> 0-1000
A68: 43764 | B68: 0.57361111 | D68: P | E68: 2 | F68: =VLOOKUP(E68,Key!$A$17:$B$21,2,FALSE) -> Road Vehicle | G68: 4 | H68: =VLOOKUP(G68,Key!$A$2:$B$13,2,FALSE) -> Minibus | I68: M | J68: 1 | K68: =VLOOKUP(J68,Key!$A$24:$B$29,2,FALSE) -> 20-29 | L68: KAMPALA | M68: KAMPALA | N68: UG | O68: 2 | P68: =VLOOKUP(O68,Key!$E$2:$F$9,2,FALSE) -> Work | Q68: HIOMA | R68: HIOMA | S68: UG | T68: 1 | U68: =VLOOKUP(T68,Key!$E$2:$F$9,2,FALSE) -> Home | V68: =P68&"-"&U68 -> Work-Home | W68: 13000 | Y68: =IF(X68<10,"0-10",IF(X68<20,"10-20",IF(X68<40,"20-40",IF(X68<70,"40-70",IF(X68<100,"70-100",IF(X68<200,"100-200","Over 200")))))) -> 0-10 | Z68: 4 | AA68: =IF(Z68<0.5,"0-0.5",IF(Z68<1,"0.5-1.0",IF(Z68<2,"1.0-2.0",IF(Z68<3.5,"2.0-3.5","Over 3.5")))) -> Over 3.5 | AB68: 4 | AC68: =VLOOKUP(AB68,Key!$C$20:$D$29,2,FALSE) -> Office Worker | AD68: 2 | AE68: =VLOOKUP(AD68,Key!$E$20:$F$24,2,FALSE) -> 300,000-500,000 | AF68: 4 | AG68: 2 | AH68: 3 | AI68: 1 | AJ68: 5 | AK68: Y | AL68: 2000 | AM68: =IF(AL68<1000,"0-1000",IF(AL68<2000,"1000-2000",IF(AL68<3000,"2000-3000",IF(AL68<5000,"3000-5000",IF(AL68<10000,"5000-10000","Over 10000"))))) -> 2000-3000
A69: 43764 | B69: 0.58125 | D69: P | E69: 2 | F69: =VLOOKUP(E69,Key!$A$17:$B$21,2,FALSE) -> Road Vehicle | G69: 4 | H69: =VLOOKUP(G69,Key!$A$2:$B$13,2,FALSE) -> Minibus | I69: M | J69: 1 | K69: =VLOOKUP(J69,Key!$A$24:$B$29,2,FALSE) -> 20-29 | L69: HIOMA | M69: HIOMA | N69: UG | O69: 8 | P69: =VLOOKUP(O69,Key!$E$2:$F$9,2,FALSE) -> Others | Q69: KAMPALA | R69: KAMPALA | S69: UG | T69: 2 | U69: =VLOOKUP(T69,Key!$E$2:$F$9,2,FALSE) -> Work | V69: =P69&"-"&U69 -> Others-Work | W69: 13000 | Y69: =IF(X69<10,"0-10",IF(X69<20,"10-20",IF(X69<40,"20-40",IF(X69<70,"40-70",IF(X69<100,"70-100",IF(X69<200,"100-200","Over 200")))))) -> 0-10 | Z69: 4 | AA69: =IF(Z69<0.5,"0-0.5",IF(Z69<1,"0.5-1.0",IF(Z69<2,"1.0-2.0",IF(Z69<3.5,"2.0-3.5","Over 3.5")))) -> Over 3.5 | AB69: 4 | AC69: =VLOOKUP(AB69,Key!$C$20:$D$29,2,FALSE) -> Office Worker | AD69: 3 | AE69: =VLOOKUP(AD69,Key!$E$20:$F$24,2,FALSE) -> 500,000-750,000 | AF69: 1 | AG69: 2 | AH69: 3 | AI69: 5 | AJ69: 4 | AK69: Y | AM69: =IF(AL69<1000,"0-1000",IF(AL69<2000,"1000-2000",IF(AL69<3000,"2000-3000",IF(AL69<5000,"3000-5000",IF(AL69<10000,"5000-10000","Over 10000"))))) -> 0-1000
A70: 43764 | B70: 0.55694444 | D70: P | E70: 2 | F70: =VLOOKUP(E70,Key!$A$17:$B$21,2,FALSE) -> Road Vehicle | G70: 4 | H70: =VLOOKUP(G70,Key!$A$2:$B$13,2,FALSE) -> Minibus | I70: M | J70: 1 | K70: =VLOOKUP(J70,Key!$A$24:$B$29,2,FALSE) -> 20-29 | L70: HIOMA | M70: HIOMA | N70: UG | O70: 1 | P70: =VLOOKUP(O70,Key!$E$2:$F$9,2,FALSE) -> Home | Q70: KAMPALA | R70: KAMPALA | S70: UG | T70: 2 | U70: =VLOOKUP(T70,Key!$E$2:$F$9,2,FALSE) -> Work | V70: =P70&"-"&U70 -> Home-Work | W70: 13000 | Y70: =IF(X70<10,"0-10",IF(X70<20,"10-20",IF(X70<40,"20-40",IF(X70<70,"40-70",IF(X70<100,"70-100",IF(X70<200,"100-200","Over 200")))))) -> 0-10 | Z70: 5 | AA70: =IF(Z70<0.5,"0-0.5",IF(Z70<1,"0.5-1.0",IF(Z70<2,"1.0-2.0",IF(Z70<3.5,"2.0-3.5","Over 3.5")))) -> Over 3.5 | AB70: 4 | AC70: =VLOOKUP(AB70,Key!$C$20:$D$29,2,FALSE) -> Office Worker | AD70: 3 | AE70: =VLOOKUP(AD70,Key!$E$20:$F$24,2,FALSE) -> 500,000-750,000 | AF70: 2 | AG70: 4 | AH70: 1 | AI70: 5 | AJ70: 0.3 | AK70: Y | AL70: 2000 | AM70: =IF(AL70<1000,"0-1000",IF(AL70<2000,"1000-2000",IF(AL70<3000,"2000-3000",IF(AL70<5000,"3000-5000",IF(AL70<10000,"5000-10000","Over 10000"))))) -> 2000-3000
A71: 43764 | B71: 0.48819444 | D71: P | E71: 2 | F71: =VLOOKUP(E71,Key!$A$17:$B$21,2,FALSE) -> Road Vehicle | G71: 4 | H71: =VLOOKUP(G71,Key!$A$2:$B$13,2,FALSE) -> Minibus | I71: M | J71: 1 | K71: =VLOOKUP(J71,Key!$A$24:$B$29,2,FALSE) -> 20-29 | L71: HIOMA | M71: HIOMA | N71: UG | O71: 1 | P71: =VLOOKUP(O71,Key!$E$2:$F$9,2,FALSE) -> Home | Q71: WAKISO | R71: WAKISO | S71: UG | T71: 2 | U71: =VLOOKUP(T71,Key!$E$2:$F$9,2,FALSE) -> Work | V71: =P71&"-"&U71 -> Home-Work | W71: 13000 | Y71: =IF(X71<10,"0-10",IF(X71<20,"10-20",IF(X71<40,"20-40",IF(X71<70,"40-70",IF(X71<100,"70-100",IF(X71<200,"100-200","Over 200")))))) -> 0-10 | Z71: 3 | AA71: =IF(Z71<0.5,"0-0.5",IF(Z71<1,"0.5-1.0",IF(Z71<2,"1.0-2.0",IF(Z71<3.5,"2.0-3.5","Over 3.5")))) -> 2.0-3.5 | AB71: 2 | AC71: =VLOOKUP(AB71,Key!$C$20:$D$29,2,FALSE) -> Manual Labour | AD71: 3 | AE71: =VLOOKUP(AD71,Key!$E$20:$F$24,2,FALSE) -> 500,000-750,000 | AF71: 2 | AG71: 1 | AH71: 1 | AI71: 5 | AJ71: 2 | AK71: Y | AM71: =IF(AL71<1000,"0-1000",IF(AL71<2000,"1000-2000",IF(AL71<3000,"2000-3000",IF(AL71<5000,"3000-5000",IF(AL71<10000,"5000-10000","Over 10000"))))) -> 0-1000
A72: 43764 | B72: 0.48819444 | D72: P | E72: 2 | F72: =VLOOKUP(E72,Key!$A$17:$B$21,2,FALSE) -> Road Vehicle | G72: 4 | H72: =VLOOKUP(G72,Key!$A$2:$B$13,2,FALSE) -> Minibus | I72: M | J72: 1 | K72: =VLOOKUP(J72,Key!$A$24:$B$29,2,FALSE) -> 20-29 | L72: HIOMA | M72: HIOMA | N72: UG | O72: 8 | P72: =VLOOKUP(O72,Key!$E$2:$F$9,2,FALSE) -> Others | Q72: KAMPALA | R72: KAMPALA | S72: UG | T72: 2 | U72: =VLOOKUP(T72,Key!$E$2:$F$9,2,FALSE) -> Work | V72: =P72&"-"&U72 -> Others-Work | W72: 13000 | Y72: =IF(X72<10,"0-10",IF(X72<20,"10-20",IF(X72<40,"20-40",IF(X72<70,"40-70",IF(X72<100,"70-100",IF(X72<200,"100-200","Over 200")))))) -> 0-10 | Z72: 4 | AA72: =IF(Z72<0.5,"0-0.5",IF(Z72<1,"0.5-1.0",IF(Z72<2,"1.0-2.0",IF(Z72<3.5,"2.0-3.5","Over 3.5")))) -> Over 3.5 | AB72: 4 | AC72: =VLOOKUP(AB72,Key!$C$20:$D$29,2,FALSE) -> Office Worker | AD72: 3 | AE72: =VLOOKUP(AD72,Key!$E$20:$F$24,2,FALSE) -> 500,000-750,000 | AF72: 5 | AG72: 5 | AH72: 4 | AI72: 1 | AJ72: 2 | AK72: Y | AL72: 2000 | AM72: =IF(AL72<1000,"0-1000",IF(AL72<2000,"1000-2000",IF(AL72<3000,"2000-3000",IF(AL72<5000,"3000-5000",IF(AL72<10000,"5000-10000","Over 10000"))))) -> 2000-3000
A73: 43764 | B73: 0.48472222 | D73: P | E73: 2 | F73: =VLOOKUP(E73,Key!$A$17:$B$21,2,FALSE) -> Road Vehicle | G73: 4 | H73: =VLOOKUP(G73,Key!$A$2:$B$13,2,FALSE) -> Minibus | I73: M | J73: 1 | K73: =VLOOKUP(J73,Key!$A$24:$B$29,2,FALSE) -> 20-29 | L73: HIOMA | M73: HIOMA | N73: UG | O73: 1 | P73: =VLOOKUP(O73,Key!$E$2:$F$9,2,FALSE) -> Home | Q73: KAMPALA | R73: KAMPALA | S73: UG | T73: 2 | U73: =VLOOKUP(T73,Key!$E$2:$F$9,2,FALSE) -> Work | V73: =P73&"-"&U73 -> Home-Work | W73: 13000 | Y73: =IF(X73<10,"0-10",IF(X73<20,"10-20",IF(X73<40,"20-40",IF(X73<70,"40-70",IF(X73<100,"70-100",IF(X73<200,"100-200","Over 200")))))) -> 0-10 | Z73: 4 | AA73: =IF(Z73<0.5,"0-0.5",IF(Z73<1,"0.5-1.0",IF(Z73<2,"1.0-2.0",IF(Z73<3.5,"2.0-3.5","Over 3.5")))) -> Over 3.5 | AB73: 2 | AC73: =VLOOKUP(AB73,Key!$C$20:$D$29,2,FALSE) -> Manual Labour | AD73: 1 | AE73: =VLOOKUP(AD73,Key!$E$20:$F$24,2,FALSE) -> <300,000 | AF73: 5 | AG73: 2 | AH73: 1 | AI73: 3 | AJ73: 4 | AK73: Y | AM73: =IF(AL73<1000,"0-1000",IF(AL73<2000,"1000-2000",IF(AL73<3000,"2000-3000",IF(AL73<5000,"3000-5000",IF(AL73<10000,"5000-10000","Over 10000"))))) -> 0-1000
A74: 43764 | B74: 0.46041667 | D74: P | E74: 2 | F74: =VLOOKUP(E74,Key!$A$17:$B$21,2,FALSE) -> Road Vehicle | G74: 4 | H74: =VLOOKUP(G74,Key!$A$2:$B$13,2,FALSE) -> Minibus | I74: M | J74: 1 | K74: =VLOOKUP(J74,Key!$A$24:$B$29,2,FALSE) -> 20-29 | L74: HIOMA | M74: HIOMA | N74: UG | O74: 2 | P74: =VLOOKUP(O74,Key!$E$2:$F$9,2,FALSE) -> Work | Q74: KIKUUBE | R74: KIKUUBE | S74: UG | T74: 8 | U74: =VLOOKUP(T74,Key!$E$2:$F$9,2,FALSE) -> Others | V74: =P74&"-"&U74 -> Work-Others | W74: 5000 | Y74: =IF(X74<10,"0-10",IF(X74<20,"10-20",IF(X74<40,"20-40",IF(X74<70,"40-70",IF(X74<100,"70-100",IF(X74<200,"100-200","Over 200")))))) -> 0-10 | Z74: 1 | AA74: =IF(Z74<0.5,"0-0.5",IF(Z74<1,"0.5-1.0",IF(Z74<2,"1.0-2.0",IF(Z74<3.5,"2.0-3.5","Over 3.5")))) -> 1.0-2.0 | AB74: 2 | AC74: =VLOOKUP(AB74,Key!$C$20:$D$29,2,FALSE) -> Manual Labour | AD74: 1 | AE74: =VLOOKUP(AD74,Key!$E$20:$F$24,2,FALSE) -> <300,000 | AF74: 2 | AG74: 4 | AH74: 5 | AI74: 1 | AJ74: 3 | AK74: Y | AM74: =IF(AL74<1000,"0-1000",IF(AL74<2000,"1000-2000",IF(AL74<3000,"2000-3000",IF(AL74<5000,"3000-5000",IF(AL74<10000,"5000-10000","Over 10000"))))) -> 0-1000
A75: 43764 | B75: 0.45555556 | D75: P | E75: 2 | F75: =VLOOKUP(E75,Key!$A$17:$B$21,2,FALSE) -> Road Vehicle | G75: 4 | H75: =VLOOKUP(G75,Key!$A$2:$B$13,2,FALSE) -> Minibus | I75: M | J75: 1 | K75: =VLOOKUP(J75,Key!$A$24:$B$29,2,FALSE) -> 20-29 | L75: HIOMA | M75: HIOMA | N75: UG | O75: 1 | P75: =VLOOKUP(O75,Key!$E$2:$F$9,2,FALSE) -> Home | Q75: KAMPALA | R75: KAMPALA | S75: UG | T75: 2 | U75: =VLOOKUP(T75,Key!$E$2:$F$9,2,FALSE) -> Work | V75: =P75&"-"&U75 -> Home-Work | W75: 13000 | Y75: =IF(X75<10,"0-10",IF(X75<20,"10-20",IF(X75<40,"20-40",IF(X75<70,"40-70",IF(X75<100,"70-100",IF(X75<200,"100-200","Over 200")))))) -> 0-10 | Z75: 3 | AA75: =IF(Z75<0.5,"0-0.5",IF(Z75<1,"0.5-1.0",IF(Z75<2,"1.0-2.0",IF(Z75<3.5,"2.0-3.5","Over 3.5")))) -> 2.0-3.5 | AB75: 3 | AC75: =VLOOKUP(AB75,Key!$C$20:$D$29,2,FALSE) -> Artisan/Domestic | AD75: 1 | AE75: =VLOOKUP(AD75,Key!$E$20:$F$24,2,FALSE) -> <300,000 | AF75: 2 | AG75: 4 | AH75: 3 | AI75: 1 | AJ75: 5 | AK75: Y | AL75: 1000 | AM75: =IF(AL75<1000,"0-1000",IF(AL75<2000,"1000-2000",IF(AL75<3000,"2000-3000",IF(AL75<5000,"3000-5000",IF(AL75<10000,"5000-10000","Over 10000"))))) -> 1000-2000
A76: 43764 | B76: 0.47569444 | D76: P | E76: 2 | F76: =VLOOKUP(E76,Key!$A$17:$B$21,2,FALSE) -> Road Vehicle | G76: 4 | H76: =VLOOKUP(G76,Key!$A$2:$B$13,2,FALSE) -> Minibus | I76: M | J76: 1 | K76: =VLOOKUP(J76,Key!$A$24:$B$29,2,FALSE) -> 20-29 | L76: HIOMA | M76: HIOMA | N76: UG | O76: 1 | P76: =VLOOKUP(O76,Key!$E$2:$F$9,2,FALSE) -> Home | Q76: KAISO | R76: KIKUUBE | S76: UG | T76: 2 | U76: =VLOOKUP(T76,Key!$E$2:$F$9,2,FALSE) -> Work | V76: =P76&"-"&U76 -> Home-Work | W76: 8000 | Y76: =IF(X76<10,"0-10",IF(X76<20,"10-20",IF(X76<40,"20-40",IF(X76<70,"40-70",IF(X76<100,"70-100",IF(X76<200,"100-200","Over 200")))))) -> 0-10 | Z76: 2 | AA76: =IF(Z76<0.5,"0-0.5",IF(Z76<1,"0.5-1.0",IF(Z76<2,"1.0-2.0",IF(Z76<3.5,"2.0-3.5","Over 3.5")))) -> 2.0-3.5 | AB76: 4 | AC76: =VLOOKUP(AB76,Key!$C$20:$D$29,2,FALSE) -> Office Worker | AD76: 3 | AE76: =VLOOKUP(AD76,Key!$E$20:$F$24,2,FALSE) -> 500,000-750,000 | AF76: 1 | AG76: 2 | AH76: 5 | AI76: 4 | AJ76: 3 | AK76: Y | AL76: 1000 | AM76: =IF(AL76<1000,"0-1000",IF(AL76<2000,"1000-2000",IF(AL76<3000,"2000-3000",IF(AL76<5000,"3000-5000",IF(AL76<10000,"5000-10000","Over 10000"))))) -> 1000-2000
A77: 43764 | B77: 0.63680556 | D77: D | E77: 2 | F77: =VLOOKUP(E77,Key!$A$17:$B$21,2,FALSE) -> Road Vehicle | G77: 4 | H77: =VLOOKUP(G77,Key!$A$2:$B$13,2,FALSE) -> Minibus | I77: M | J77: 1 | K77: =VLOOKUP(J77,Key!$A$24:$B$29,2,FALSE) -> 20-29 | L77: HIOMA | M77: HIOMA | N77: UG | O77: 2 | P77: =VLOOKUP(O77,Key!$E$2:$F$9,2,FALSE) -> Work | Q77: KIGOLOBYA | R77: HIOMA | S77: UG | T77: 1 | U77: =VLOOKUP(T77,Key!$E$2:$F$9,2,FALSE) -> Home | V77: =P77&"-"&U77 -> Work-Home | W77: 5000 | X77: 30 | Y77: =IF(X77<10,"0-10",IF(X77<20,"10-20",IF(X77<40,"20-40",IF(X77<70,"40-70",IF(X77<100,"70-100",IF(X77<200,"100-200","Over 200")))))) -> 20-40 | Z77: 1 | AA77: =IF(Z77<0.5,"0-0.5",IF(Z77<1,"0.5-1.0",IF(Z77<2,"1.0-2.0",IF(Z77<3.5,"2.0-3.5","Over 3.5")))) -> 1.0-2.0 | AB77: 8 | AC77: =VLOOKUP(AB77,Key!$C$20:$D$29,2,FALSE) -> Student | AD77: 1 | AE77: =VLOOKUP(AD77,Key!$E$20:$F$24,2,FALSE) -> <300,000 | AF77: 1 | AG77: 1 | AH77: 1 | AI77: 1 | AJ77: 1 | AK77: Y | AL77: 5000 | AM77: =IF(AL77<1000,"0-1000",IF(AL77<2000,"1000-2000",IF(AL77<3000,"2000-3000",IF(AL77<5000,"3000-5000",IF(AL77<10000,"5000-10000","Over 10000"))))) -> 5000-10000
A78: 43764 | B78: 0.62222222 | D78: D | E78: 2 | F78: =VLOOKUP(E78,Key!$A$17:$B$21,2,FALSE) -> Road Vehicle | G78: 4 | H78: =VLOOKUP(G78,Key!$A$2:$B$13,2,FALSE) -> Minibus | I78: M | J78: 1 | K78: =VLOOKUP(J78,Key!$A$24:$B$29,2,FALSE) -> 20-29 | L78: HIOMA | M78: HIOMA | N78: UG | O78: 1 | P78: =VLOOKUP(O78,Key!$E$2:$F$9,2,FALSE) -> Home | Q78: MUTYABA | R78: KAKUMIRO | S78: UG | T78: 6 | U78: =VLOOKUP(T78,Key!$E$2:$F$9,2,FALSE) -> Leisure/Social | V78: =P78&"-"&U78 -> Home-Leisure/Social | W78: 10000 | X78: 150 | Y78: =IF(X78<10,"0-10",IF(X78<20,"10-20",IF(X78<40,"20-40",IF(X78<70,"40-70",IF(X78<100,"70-100",IF(X78<200,"100-200","Over 200")))))) -> 100-200 | Z78: 4 | AA78: =IF(Z78<0.5,"0-0.5",IF(Z78<1,"0.5-1.0",IF(Z78<2,"1.0-2.0",IF(Z78<3.5,"2.0-3.5","Over 3.5")))) -> Over 3.5 | AB78: 2 | AC78: =VLOOKUP(AB78,Key!$C$20:$D$29,2,FALSE) -> Manual Labour | AD78: 1 | AE78: =VLOOKUP(AD78,Key!$E$20:$F$24,2,FALSE) -> <300,000 | AF78: 4 | AG78: 3 | AH78: 5 | AI78: 1 | AJ78: 4 | AK78: Y | AL78: 7000 | AM78: =IF(AL78<1000,"0-1000",IF(AL78<2000,"1000-2000",IF(AL78<3000,"2000-3000",IF(AL78<5000,"3000-5000",IF(AL78<10000,"5000-10000","Over 10000"))))) -> 5000-10000
A79: 43764 | B79: 0.55486111 | D79: D | E79: 2 | F79: =VLOOKUP(E79,Key!$A$17:$B$21,2,FALSE) -> Road Vehicle | G79: 4 | H79: =VLOOKUP(G79,Key!$A$2:$B$13,2,FALSE) -> Minibus | I79: M | J79: 1 | K79: =VLOOKUP(J79,Key!$A$24:$B$29,2,FALSE) -> 20-29 | L79: HIOMA | M79: HIOMA | N79: UG | O79: 1 | P79: =VLOOKUP(O79,Key!$E$2:$F$9,2,FALSE) -> Home | Q79: BUSIA | R79: BUSIA | S79: UG | T79: 6 | U79: =VLOOKUP(T79,Key!$E$2:$F$9,2,FALSE) -> Leisure/Social | V79: =P79&"-"&U79 -> Home-Leisure/Social | W79: 15000 | X79: 150 | Y79: =IF(X79<10,"0-10",IF(X79<20,"10-20",IF(X79<40,"20-40",IF(X79<70,"40-70",IF(X79<100,"70-100",IF(X79<200,"100-200","Over 200")))))) -> 100-200 | Z79: 3 | AA79: =IF(Z79<0.5,"0-0.5",IF(Z79<1,"0.5-1.0",IF(Z79<2,"1.0-2.0",IF(Z79<3.5,"2.0-3.5","Over 3.5")))) -> 2.0-3.5 | AB79: 2 | AC79: =VLOOKUP(AB79,Key!$C$20:$D$29,2,FALSE) -> Manual Labour | AD79: 2 | AE79: =VLOOKUP(AD79,Key!$E$20:$F$24,2,FALSE) -> 300,000-500,000 | AF79: 3 | AG79: 4 | AH79: 1 | AI79: 2 | AJ79: 1 | AK79: Y | AL79: 1000 | AM79: =IF(AL79<1000,"0-1000",IF(AL79<2000,"1000-2000",IF(AL79<3000,"2000-3000",IF(AL79<5000,"3000-5000",IF(AL79<10000,"5000-10000","Over 10000"))))) -> 1000-2000
A80: 43764 | B80: 0.60833333 | D80: D | E80: 2 | F80: =VLOOKUP(E80,Key!$A$17:$B$21,2,FALSE) -> Road Vehicle | G80: 4 | H80: =VLOOKUP(G80,Key!$A$2:$B$13,2,FALSE) -> Minibus | I80: M | J80: 1 | K80: =VLOOKUP(J80,Key!$A$24:$B$29,2,FALSE) -> 20-29 | L80: HIOMA | M80: HIOMA | N80: UG | O80: 1 | P80: =VLOOKUP(O80,Key!$E$2:$F$9,2,FALSE) -> Home | Q80: MASINDI | R80: MASINDI | S80: UG | T80: 4 | U80: =VLOOKUP(T80,Key!$E$2:$F$9,2,FALSE) -> Commercial | V80: =P80&"-"&U80 -> Home-Commercial | W80: 10000 | X80: 70 | Y80: =IF(X80<10,"0-10",IF(X80<20,"10-20",IF(X80<40,"20-40",IF(X80<70,"40-70",IF(X80<100,"70-100",IF(X80<200,"100-200","Over 200")))))) -> 70-100 | Z80: 2 | AA80: =IF(Z80<0.5,"0-0.5",IF(Z80<1,"0.5-1.0",IF(Z80<2,"1.0-2.0",IF(Z80<3.5,"2.0-3.5","Over 3.5")))) -> 2.0-3.5 | AB80: 2 | AC80: =VLOOKUP(AB80,Key!$C$20:$D$29,2,FALSE) -> Manual Labour | AD80: 2 | AE80: =VLOOKUP(AD80,Key!$E$20:$F$24,2,FALSE) -> 300,000-500,000 | AF80: 1 | AG80: 4 | AH80: 3 | AI80: 2 | AJ80: 5 | AK80: Y | AL80: 1000 | AM80: =IF(AL80<1000,"0-1000",IF(AL80<2000,"1000-2000",IF(AL80<3000,"2000-3000",IF(AL80<5000,"3000-5000",IF(AL80<10000,"5000-10000","Over 10000"))))) -> 1000-2000
A81: 43764 | B81: 0.61805556 | D81: D | E81: 2 | F81: =VLOOKUP(E81,Key!$A$17:$B$21,2,FALSE) -> Road Vehicle | G81: 4 | H81: =VLOOKUP(G81,Key!$A$2:$B$13,2,FALSE) -> Minibus | I81: M | J81: 1 | K81: =VLOOKUP(J81,Key!$A$24:$B$29,2,FALSE) -> 20-29 | L81: HIOMA | M81: HIOMA | N81: UG | O81: 4 | P81: =VLOOKUP(O81,Key!$E$2:$F$9,2,FALSE) -> Commercial | Q81: KIGOLOBYA | R81: HIOMA | S81: UG | T81: 1 | U81: =VLOOKUP(T81,Key!$E$2:$F$9,2,FALSE) -> Home | V81: =P81&"-"&U81 -> Commercial-Home | W81: 5000 | X81: 30 | Y81: =IF(X81<10,"0-10",IF(X81<20,"10-20",IF(X81<40,"20-40",IF(X81<70,"40-70",IF(X81<100,"70-100",IF(X81<200,"100-200","Over 200")))))) -> 20-40 | Z81: 1 | AA81: =IF(Z81<0.5,"0-0.5",IF(Z81<1,"0.5-1.0",IF(Z81<2,"1.0-2.0",IF(Z81<3.5,"2.0-3.5","Over 3.5")))) -> 1.0-2.0 | AB81: 10 | AC81: =VLOOKUP(AB81,Key!$C$20:$D$29,2,FALSE) -> Other | AD81: 2 | AE81: =VLOOKUP(AD81,Key!$E$20:$F$24,2,FALSE) -> 300,000-500,000 | AF81: 3 | AG81: 4 | AH81: 1 | AI81: 5 | AJ81: 2 | AK81: Y | AL81: 1000 | AM81: =IF(AL81<1000,"0-1000",IF(AL81<2000,"1000-2000",IF(AL81<3000,"2000-3000",IF(AL81<5000,"3000-5000",IF(AL81<10000,"5000-10000","Over 10000"))))) -> 1000-2000
A82: 43764 | B82: 0.64652778 | D82: P | E82: 2 | F82: =VLOOKUP(E82,Key!$A$17:$B$21,2,FALSE) -> Road Vehicle | G82: 4 | H82: =VLOOKUP(G82,Key!$A$2:$B$13,2,FALSE) -> Minibus | I82: M | J82: 1 | K82: =VLOOKUP(J82,Key!$A$24:$B$29,2,FALSE) -> 20-29 | L82: HIOMA | M82: HIOMA | N82: UG | O82: 1 | P82: =VLOOKUP(O82,Key!$E$2:$F$9,2,FALSE) -> Home | Q82: BUGAMBE | R82: KIGUBE | S82: UG | T82: 6 | U82: =VLOOKUP(T82,Key!$E$2:$F$9,2,FALSE) -> Leisure/Social | V82: =P82&"-"&U82 -> Home-Leisure/Social | W82: 7000 | X82: 80 | Y82: =IF(X82<10,"0-10",IF(X82<20,"10-20",IF(X82<40,"20-40",IF(X82<70,"40-70",IF(X82<100,"70-100",IF(X82<200,"100-200","Over 200")))))) -> 70-100 | Z82: 2 | AA82: =IF(Z82<0.5,"0-0.5",IF(Z82<1,"0.5-1.0",IF(Z82<2,"1.0-2.0",IF(Z82<3.5,"2.0-3.5","Over 3.5")))) -> 2.0-3.5 | AB82: 3 | AC82: =VLOOKUP(AB82,Key!$C$20:$D$29,2,FALSE) -> Artisan/Domestic | AD82: 2 | AE82: =VLOOKUP(AD82,Key!$E$20:$F$24,2,FALSE) -> 300,000-500,000 | AF82: 3 | AG82: 4 | AH82: 1 | AI82: 5 | AJ82: 2 | AK82: Y | AL82: 5000 | AM82: =IF(AL82<1000,"0-1000",IF(AL82<2000,"1000-2000",IF(AL82<3000,"2000-3000",IF(AL82<5000,"3000-5000",IF(AL82<10000,"5000-10000","Over 10000"))))) -> 5000-10000
A83: 43764 | B83: 0.625 | D83: D | E83: 2 | F83: =VLOOKUP(E83,Key!$A$17:$B$21,2,FALSE) -> Road Vehicle | G83: 4 | H83: =VLOOKUP(G83,Key!$A$2:$B$13,2,FALSE) -> Minibus | I83: M | J83: 1 | K83: =VLOOKUP(J83,Key!$A$24:$B$29,2,FALSE) -> 20-29 | L83: HIOMA | M83: HIOMA | N83: UG | O83: 1 | P83: =VLOOKUP(O83,Key!$E$2:$F$9,2,FALSE) -> Home | Q83: BUKWIRI | R83: KYANKWANZI | S83: UG | T83: 5 | U83: =VLOOKUP(T83,Key!$E$2:$F$9,2,FALSE) -> Tourism | V83: =P83&"-"&U83 -> Home-Tourism | W83: 8000 | X83: 80 | Y83: =IF(X83<10,"0-10",IF(X83<20,"10-20",IF(X83<40,"20-40",IF(X83<70,"40-70",IF(X83<100,"70-100",IF(X83<200,"100-200","Over 200")))))) -> 70-100 | Z83: 3 | AA83: =IF(Z83<0.5,"0-0.5",IF(Z83<1,"0.5-1.0",IF(Z83<2,"1.0-2.0",IF(Z83<3.5,"2.0-3.5","Over 3.5")))) -> 2.0-3.5 | AB83: 3 | AC83: =VLOOKUP(AB83,Key!$C$20:$D$29,2,FALSE) -> Artisan/Domestic | AD83: 2 | AE83: =VLOOKUP(AD83,Key!$E$20:$F$24,2,FALSE) -> 300,000-500,000 | AF83: 3 | AG83: 1 | AH83: 2 | AI83: 5 | AJ83: 4 | AK83: Y | AL83: 3000 | AM83: =IF(AL83<1000,"0-1000",IF(AL83<2000,"1000-2000",IF(AL83<3000,"2000-3000",IF(AL83<5000,"3000-5000",IF(AL83<10000,"5000-10000","Over 10000"))))) -> 3000-5000
A84: 43764 | B84: 0.80833333 | D84: P | E84: 2 | F84: =VLOOKUP(E84,Key!$A$17:$B$21,2,FALSE) -> Road Vehicle | G84: 4 | H84: =VLOOKUP(G84,Key!$A$2:$B$13,2,FALSE) -> Minibus | I84: M | J84: 1 | K84: =VLOOKUP(J84,Key!$A$24:$B$29,2,FALSE) -> 20-29 | L84: HIOMA | M84: HIOMA | N84: UG | O84: 1 | P84: =VLOOKUP(O84,Key!$E$2:$F$9,2,FALSE) -> Home | Q84: BULIISA | R84: BULIISA | S84: UG | T84: 5 | U84: =VLOOKUP(T84,Key!$E$2:$F$9,2,FALSE) -> Tourism | V84: =P84&"-"&U84 -> Home-Tourism | W84: 15000 | X84: 160 | Y84: =IF(X84<10,"0-10",IF(X84<20,"10-20",IF(X84<40,"20-40",IF(X84<70,"40-70",IF(X84<100,"70-100",IF(X84<200,"100-200","Over 200")))))) -> 100-200 | Z84: 3 | AA84: =IF(Z84<0.5,"0-0.5",IF(Z84<1,"0.5-1.0",IF(Z84<2,"1.0-2.0",IF(Z84<3.5,"2.0-3.5","Over 3.5")))) -> 2.0-3.5 | AB84: 2 | AC84: =VLOOKUP(AB84,Key!$C$20:$D$29,2,FALSE) -> Manual Labour | AD84: 2 | AE84: =VLOOKUP(AD84,Key!$E$20:$F$24,2,FALSE) -> 300,000-500,000 | AF84: 1 | AG84: 2 | AH84: 3 | AI84: 5 | AJ84: 4 | AK84: Y | AL84: 5000 | AM84: =IF(AL84<1000,"0-1000",IF(AL84<2000,"1000-2000",IF(AL84<3000,"2000-3000",IF(AL84<5000,"3000-5000",IF(AL84<10000,"5000-10000","Over 10000"))))) -> 5000-10000
A85: 43764 | B85: 0.62152778 | D85: P | E85: 2 | F85: =VLOOKUP(E85,Key!$A$17:$B$21,2,FALSE) -> Road Vehicle | G85: 4 | H85: =VLOOKUP(G85,Key!$A$2:$B$13,2,FALSE) -> Minibus | I85: M | J85: 1 | K85: =VLOOKUP(J85,Key!$A$24:$B$29,2,FALSE) -> 20-29 | L85: HIOMA | M85: HIOMA | N85: UG | O85: 4 | P85: =VLOOKUP(O85,Key!$E$2:$F$9,2,FALSE) -> Commercial | Q85: BULIMA | R85: BULIMA | S85: UG | T85: 1 | U85: =VLOOKUP(T85,Key!$E$2:$F$9,2,FALSE) -> Home | V85: =P85&"-"&U85 -> Commercial-Home | W85: 5000 | X85: 20 | Y85: =IF(X85<10,"0-10",IF(X85<20,"10-20",IF(X85<40,"20-40",IF(X85<70,"40-70",IF(X85<100,"70-100",IF(X85<200,"100-200","Over 200")))))) -> 20-40 | Z85: 1 | AA85: =IF(Z85<0.5,"0-0.5",IF(Z85<1,"0.5-1.0",IF(Z85<2,"1.0-2.0",IF(Z85<3.5,"2.0-3.5","Over 3.5")))) -> 1.0-2.0 | AB85: 4 | AC85: =VLOOKUP(AB85,Key!$C$20:$D$29,2,FALSE) -> Office Worker | AD85: 3 | AE85: =VLOOKUP(AD85,Key!$E$20:$F$24,2,FALSE) -> 500,000-750,000 | AF85: 2 | AG85: 3 | AH85: 4 | AI85: 5 | AJ85: 1 | AK85: Y | AL85: 1000 | AM85: =IF(AL85<1000,"0-1000",IF(AL85<2000,"1000-2000",IF(AL85<3000,"2000-3000",IF(AL85<5000,"3000-5000",IF(AL85<10000,"5000-10000","Over 10000"))))) -> 1000-2000
A86: 43764 | B86: 0.60069444 | D86: D | E86: 2 | F86: =VLOOKUP(E86,Key!$A$17:$B$21,2,FALSE) -> Road Vehicle | G86: 4 | H86: =VLOOKUP(G86,Key!$A$2:$B$13,2,FALSE) -> Minibus | I86: M | J86: 1 | K86: =VLOOKUP(J86,Key!$A$24:$B$29,2,FALSE) -> 20-29 | L86: HIOMA | M86: HIOMA | N86: UG | O86: 2 | P86: =VLOOKUP(O86,Key!$E$2:$F$9,2,FALSE) -> Work | Q86: KAGADI | R86: KAGADI | S86: UG | T86: 1 | U86: =VLOOKUP(T86,Key!$E$2:$F$9,2,FALSE) -> Home | V86: =P86&"-"&U86 -> Work-Home | W86: 180000 | X86: 190 | Y86: =IF(X86<10,"0-10",IF(X86<20,"10-20",IF(X86<40,"20-40",IF(X86<70,"40-70",IF(X86<100,"70-100",IF(X86<200,"100-200","Over 200")))))) -> 100-200 | Z86: 3 | AA86: =IF(Z86<0.5,"0-0.5",IF(Z86<1,"0.5-1.0",IF(Z86<2,"1.0-2.0",IF(Z86<3.5,"2.0-3.5","Over 3.5")))) -> 2.0-3.5 | AB86: 10 | AC86: =VLOOKUP(AB86,Key!$C$20:$D$29,2,FALSE) -> Other | AD86: 3 | AE86: =VLOOKUP(AD86,Key!$E$20:$F$24,2,FALSE) -> 500,000-750,000 | AF86: 1 | AG86: 3 | AH86: 2 | AI86: 4 | AJ86: 5 | AK86: Y | AM86: =IF(AL86<1000,"0-1000",IF(AL86<2000,"1000-2000",IF(AL86<3000,"2000-3000",IF(AL86<5000,"3000-5000",IF(AL86<10000,"5000-10000","Over 10000"))))) -> 0-1000
A87: 43764 | B87: 0.66041667 | D87: P | E87: 2 | F87: =VLOOKUP(E87,Key!$A$17:$B$21,2,FALSE) -> Road Vehicle | G87: 4 | H87: =VLOOKUP(G87,Key!$A$2:$B$13,2,FALSE) -> Minibus | I87: M | J87: 1 | K87: =VLOOKUP(J87,Key!$A$24:$B$29,2,FALSE) -> 20-29 | L87: HIOMA | M87: HIOMA | N87: UG | O87: 2 | P87: =VLOOKUP(O87,Key!$E$2:$F$9,2,FALSE) -> Work | Q87: KAMPALA | R87: KAMPALA | S87: UG | T87: 1 | U87: =VLOOKUP(T87,Key!$E$2:$F$9,2,FALSE) -> Home | V87: =P87&"-"&U87 -> Work-Home | W87: 150000 | X87: 201 | Y87: =IF(X87<10,"0-10",IF(X87<20,"10-20",IF(X87<40,"20-40",IF(X87<70,"40-70",IF(X87<100,"70-100",IF(X87<200,"100-200","Over 200")))))) -> Over 200 | Z87: 4 | AA87: =IF(Z87<0.5,"0-0.5",IF(Z87<1,"0.5-1.0",IF(Z87<2,"1.0-2.0",IF(Z87<3.5,"2.0-3.5","Over 3.5")))) -> Over 3.5 | AB87: 6 | AC87: =VLOOKUP(AB87,Key!$C$20:$D$29,2,FALSE) -> Businessman | AD87: 4 | AE87: =VLOOKUP(AD87,Key!$E$20:$F$24,2,FALSE) -> 750,000-1,000,000 | AF87: 2 | AG87: 1 | AH87: 3 | AI87: 4 | AJ87: 5 | AK87: Y | AL87: 3000 | AM87: =IF(AL87<1000,"0-1000",IF(AL87<2000,"1000-2000",IF(AL87<3000,"2000-3000",IF(AL87<5000,"3000-5000",IF(AL87<10000,"5000-10000","Over 10000"))))) -> 3000-5000
A88: 43764 | B88: 0.53402778 | D88: D | E88: 2 | F88: =VLOOKUP(E88,Key!$A$17:$B$21,2,FALSE) -> Road Vehicle | G88: 4 | H88: =VLOOKUP(G88,Key!$A$2:$B$13,2,FALSE) -> Minibus | I88: M | J88: 1 | K88: =VLOOKUP(J88,Key!$A$24:$B$29,2,FALSE) -> 20-29 | L88: HIOMA | M88: HIOMA | N88: UG | O88: 2 | P88: =VLOOKUP(O88,Key!$E$2:$F$9,2,FALSE) -> Work | Q88: KAISO | R88: KAISO | S88: UG | T88: 4 | U88: =VLOOKUP(T88,Key!$E$2:$F$9,2,FALSE) -> Commercial | V88: =P88&"-"&U88 -> Work-Commercial | W88: 15000 | X88: 190 | Y88: =IF(X88<10,"0-10",IF(X88<20,"10-20",IF(X88<40,"20-40",IF(X88<70,"40-70",IF(X88<100,"70-100",IF(X88<200,"100-200","Over 200")))))) -> 100-200 | Z88: 3 | AA88: =IF(Z88<0.5,"0-0.5",IF(Z88<1,"0.5-1.0",IF(Z88<2,"1.0-2.0",IF(Z88<3.5,"2.0-3.5","Over 3.5")))) -> 2.0-3.5 | AB88: 5 | AC88: =VLOOKUP(AB88,Key!$C$20:$D$29,2,FALSE) -> Professional | AD88: 5 | AE88: =VLOOKUP(AD88,Key!$E$20:$F$24,2,FALSE) -> >1,000,000 | AF88: 2 | AG88: 5 | AH88: 3 | AI88: 1 | AJ88: 4 | AK88: Y | AL88: 2000 | AM88: =IF(AL88<1000,"0-1000",IF(AL88<2000,"1000-2000",IF(AL88<3000,"2000-3000",IF(AL88<5000,"3000-5000",IF(AL88<10000,"5000-10000","Over 10000"))))) -> 2000-3000
A89: 43764 | B89: 0.30138889 | D89: D | E89: 2 | F89: =VLOOKUP(E89,Key!$A$17:$B$21,2,FALSE) -> Road Vehicle | G89: 4 | H89: =VLOOKUP(G89,Key!$A$2:$B$13,2,FALSE) -> Minibus | I89: M | J89: 1 | K89: =VLOOKUP(J89,Key!$A$24:$B$29,2,FALSE) -> 20-29 | L89: HIOMA | M89: HIOMA | N89: UG | O89: 2 | P89: =VLOOKUP(O89,Key!$E$2:$F$9,2,FALSE) -> Work | Q89: MASINDI | R89: MASINDI | S89: UG | T89: 1 | U89: =VLOOKUP(T89,Key!$E$2:$F$9,2,FALSE) -> Home | V89: =P89&"-"&U89 -> Work-Home | W89: 1500 | X89: 190 | Y89: =IF(X89<10,"0-10",IF(X89<20,"10-20",IF(X89<40,"20-40",IF(X89<70,"40-70",IF(X89<100,"70-100",IF(X89<200,"100-200","Over 200")))))) -> 100-200 | Z89: 3 | AA89: =IF(Z89<0.5,"0-0.5",IF(Z89<1,"0.5-1.0",IF(Z89<2,"1.0-2.0",IF(Z89<3.5,"2.0-3.5","Over 3.5")))) -> 2.0-3.5 | AB89: 5 | AC89: =VLOOKUP(AB89,Key!$C$20:$D$29,2,FALSE) -> Professional | AD89: 2 | AE89: =VLOOKUP(AD89,Key!$E$20:$F$24,2,FALSE) -> 300,000-500,000 | AF89: 5 | AG89: 2 | AH89: 3 | AI89: 4 | AJ89: 1 | AK89: Y | AM89: =IF(AL89<1000,"0-1000",IF(AL89<2000,"1000-2000",IF(AL89<3000,"2000-3000",IF(AL89<5000,"3000-5000",IF(AL89<10000,"5000-10000","Over 10000"))))) -> 0-1000
A90: 43764 | B90: 0.38888889 | D90: D | E90: 2 | F90: =VLOOKUP(E90,Key!$A$17:$B$21,2,FALSE) -> Road Vehicle | G90: 4 | H90: =VLOOKUP(G90,Key!$A$2:$B$13,2,FALSE) -> Minibus | I90: M | J90: 1 | K90: =VLOOKUP(J90,Key!$A$24:$B$29,2,FALSE) -> 20-29 | L90: HIOMA | M90: HIOMA | N90: UG | O90: 2 | P90: =VLOOKUP(O90,Key!$E$2:$F$9,2,FALSE) -> Work | Q90: BUSUNJJU | R90: BUSUJJU | S90: UG | T90: 2 | U90: =VLOOKUP(T90,Key!$E$2:$F$9,2,FALSE) -> Work | V90: =P90&"-"&U90 -> Work-Work | W90: 150000 | X90: 190 | Y90: =IF(X90<10,"0-10",IF(X90<20,"10-20",IF(X90<40,"20-40",IF(X90<70,"40-70",IF(X90<100,"70-100",IF(X90<200,"100-200","Over 200")))))) -> 100-200 | Z90: 2 | AA90: =IF(Z90<0.5,"0-0.5",IF(Z90<1,"0.5-1.0",IF(Z90<2,"1.0-2.0",IF(Z90<3.5,"2.0-3.5","Over 3.5")))) -> 2.0-3.5 | AB90: 10 | AC90: =VLOOKUP(AB90,Key!$C$20:$D$29,2,FALSE) -> Other | AD90: 1 | AE90: =VLOOKUP(AD90,Key!$E$20:$F$24,2,FALSE) -> <300,000 | AF90: 4 | AG90: 3 | AH90: 5 | AI90: 2 | AJ90: 1 | AK90: Y | AM90: =IF(AL90<1000,"0-1000",IF(AL90<2000,"1000-2000",IF(AL90<3000,"2000-3000",IF(AL90<5000,"3000-5000",IF(AL90<10000,"5000-10000","Over 10000"))))) -> 0-1000
A91: 43764 | B91: 0.30694444 | D91: D | E91: 2 | F91: =VLOOKUP(E91,Key!$A$17:$B$21,2,FALSE) -> Road Vehicle | G91: 4 | H91: =VLOOKUP(G91,Key!$A$2:$B$13,2,FALSE) -> Minibus | I91: M | J91: 1 | K91: =VLOOKUP(J91,Key!$A$24:$B$29,2,FALSE) -> 20-29 | L91: HIOMA | M91: HIOMA | N91: UG | O91: 2 | P91: =VLOOKUP(O91,Key!$E$2:$F$9,2,FALSE) -> Work | Q91: KAMPALA | R91: KAMPALA | S91: UG | T91: 4 | U91: =VLOOKUP(T91,Key!$E$2:$F$9,2,FALSE) -> Commercial | V91: =P91&"-"&U91 -> Work-Commercial | W91: 15000 | X91: 170 | Y91: =IF(X91<10,"0-10",IF(X91<20,"10-20",IF(X91<40,"20-40",IF(X91<70,"40-70",IF(X91<100,"70-100",IF(X91<200,"100-200","Over 200")))))) -> 100-200 | Z91: 2 | AA91: =IF(Z91<0.5,"0-0.5",IF(Z91<1,"0.5-1.0",IF(Z91<2,"1.0-2.0",IF(Z91<3.5,"2.0-3.5","Over 3.5")))) -> 2.0-3.5 | AB91: 6 | AC91: =VLOOKUP(AB91,Key!$C$20:$D$29,2,FALSE) -> Businessman | AD91: 3 | AE91: =VLOOKUP(AD91,Key!$E$20:$F$24,2,FALSE) -> 500,000-750,000 | AF91: 3 | AG91: 5 | AH91: 4 | AI91: 1 | AJ91: 2 | AK91: Y | AL91: 1000 | AM91: =IF(AL91<1000,"0-1000",IF(AL91<2000,"1000-2000",IF(AL91<3000,"2000-3000",IF(AL91<5000,"3000-5000",IF(AL91<10000,"5000-10000","Over 10000"))))) -> 1000-2000
A92: 43764 | B92: 0.43472222 | D92: D | E92: 2 | F92: =VLOOKUP(E92,Key!$A$17:$B$21,2,FALSE) -> Road Vehicle | G92: 4 | H92: =VLOOKUP(G92,Key!$A$2:$B$13,2,FALSE) -> Minibus | I92: M | J92: 1 | K92: =VLOOKUP(J92,Key!$A$24:$B$29,2,FALSE) -> 20-29 | L92: HIOMA | M92: HIOMA | N92: UG | O92: 4 | P92: =VLOOKUP(O92,Key!$E$2:$F$9,2,FALSE) -> Commercial | Q92: HIOMA | R92: HIOMA | S92: UG | T92: 1 | U92: =VLOOKUP(T92,Key!$E$2:$F$9,2,FALSE) -> Home | V92: =P92&"-"&U92 -> Commercial-Home | W92: 350000 | X92: 400 | Y92: =IF(X92<10,"0-10",IF(X92<20,"10-20",IF(X92<40,"20-40",IF(X92<70,"40-70",IF(X92<100,"70-100",IF(X92<200,"100-200","Over 200")))))) -> Over 200 | Z92: 8 | AA92: =IF(Z92<0.5,"0-0.5",IF(Z92<1,"0.5-1.0",IF(Z92<2,"1.0-2.0",IF(Z92<3.5,"2.0-3.5","Over 3.5")))) -> Over 3.5 | AB92: 8 | AC92: =VLOOKUP(AB92,Key!$C$20:$D$29,2,FALSE) -> Student | AD92: 3 | AE92: =VLOOKUP(AD92,Key!$E$20:$F$24,2,FALSE) -> 500,000-750,000 | AF92: 5 | AG92: 1 | AH92: 3 | AI92: 2 | AJ92: 4 | AK92: Y | AL92: 2000 | AM92: =IF(AL92<1000,"0-1000",IF(AL92<2000,"1000-2000",IF(AL92<3000,"2000-3000",IF(AL92<5000,"3000-5000",IF(AL92<10000,"5000-10000","Over 10000"))))) -> 2000-3000
A93: 43764 | B93: 0.38888889 | D93: P | E93: 2 | F93: =VLOOKUP(E93,Key!$A$17:$B$21,2,FALSE) -> Road Vehicle | G93: 4 | H93: =VLOOKUP(G93,Key!$A$2:$B$13,2,FALSE) -> Minibus | I93: M | J93: 1 | K93: =VLOOKUP(J93,Key!$A$24:$B$29,2,FALSE) -> 20-29 | L93: HIOMA | M93: HIOMA | N93: UG | O93: 1 | P93: =VLOOKUP(O93,Key!$E$2:$F$9,2,FALSE) -> Home | Q93: KAMPALA | R93: KAMPALA | S93: UG | T93: 2 | U93: =VLOOKUP(T93,Key!$E$2:$F$9,2,FALSE) -> Work | V93: =P93&"-"&U93 -> Home-Work | W93: 5000 | X93: 30 | Y93: =IF(X93<10,"0-10",IF(X93<20,"10-20",IF(X93<40,"20-40",IF(X93<70,"40-70",IF(X93<100,"70-100",IF(X93<200,"100-200","Over 200")))))) -> 20-40 | Z93: 1 | AA93: =IF(Z93<0.5,"0-0.5",IF(Z93<1,"0.5-1.0",IF(Z93<2,"1.0-2.0",IF(Z93<3.5,"2.0-3.5","Over 3.5")))) -> 1.0-2.0 | AB93: 4 | AC93: =VLOOKUP(AB93,Key!$C$20:$D$29,2,FALSE) -> Office Worker | AD93: 3 | AE93: =VLOOKUP(AD93,Key!$E$20:$F$24,2,FALSE) -> 500,000-750,000 | AF93: 2 | AG93: 1 | AH93: 4 | AI93: 3 | AJ93: 5 | AK93: Y | AL93: 3000 | AM93: =IF(AL93<1000,"0-1000",IF(AL93<2000,"1000-2000",IF(AL93<3000,"2000-3000",IF(AL93<5000,"3000-5000",IF(AL93<10000,"5000-10000","Over 10000"))))) -> 3000-5000
A94: 43764 | B94: 0.3625 | D94: D | E94: 2 | F94: =VLOOKUP(E94,Key!$A$17:$B$21,2,FALSE) -> Road Vehicle | G94: 4 | H94: =VLOOKUP(G94,Key!$A$2:$B$13,2,FALSE) -> Minibus | I94: M | J94: 1 | K94: =VLOOKUP(J94,Key!$A$24:$B$29,2,FALSE) -> 20-29 | L94: HIOMA | M94: HIOMA | N94: UG | O94: 1 | P94: =VLOOKUP(O94,Key!$E$2:$F$9,2,FALSE) -> Home | Q94: KAMPALA | R94: KAMPALA | S94: UG | T94: 2 | U94: =VLOOKUP(T94,Key!$E$2:$F$9,2,FALSE) -> Work | V94: =P94&"-"&U94 -> Home-Work | W94: 170000 | X94: 192 | Y94: =IF(X94<10,"0-10",IF(X94<20,"10-20",IF(X94<40,"20-40",IF(X94<70,"40-70",IF(X94<100,"70-100",IF(X94<200,"100-200","Over 200")))))) -> 100-200 | Z94: 3 | AA94: =IF(Z94<0.5,"0-0.5",IF(Z94<1,"0.5-1.0",IF(Z94<2,"1.0-2.0",IF(Z94<3.5,"2.0-3.5","Over 3.5")))) -> 2.0-3.5 | AB94: 10 | AC94: =VLOOKUP(AB94,Key!$C$20:$D$29,2,FALSE) -> Other | AD94: 2 | AE94: =VLOOKUP(AD94,Key!$E$20:$F$24,2,FALSE) -> 300,000-500,000 | AF94: 1 | AG94: 2 | AH94: 5 | AI94: 4 | AJ94: 5 | AK94: Y | AM94: =IF(AL94<1000,"0-1000",IF(AL94<2000,"1000-2000",IF(AL94<3000,"2000-3000",IF(AL94<5000,"3000-5000",IF(AL94<10000,"5000-10000","Over 10000"))))) -> 0-1000
A95: 43762 | B95: 0.73819444 | D95: P | E95: 2 | F95: =VLOOKUP(E95,Key!$A$17:$B$21,2,FALSE) -> Road Vehicle | G95: 1 | H95: =VLOOKUP(G95,Key!$A$2:$B$13,2,FALSE) -> Car | I95: M | J95: 2 | K95: =VLOOKUP(J95,Key!$A$24:$B$29,2,FALSE) -> 30-39 | L95: HIOMA | M95: HIOMA | N95: UG | O95: 2 | P95: =VLOOKUP(O95,Key!$E$2:$F$9,2,FALSE) -> Work | Q95: KARANGWALI | R95: KIKUUBE | S95: UG | T95: 8 | U95: =VLOOKUP(T95,Key!$E$2:$F$9,2,FALSE) -> Others | V95: =P95&"-"&U95 -> Work-Others | W95: 15000 | Y95: =IF(X95<10,"0-10",IF(X95<20,"10-20",IF(X95<40,"20-40",IF(X95<70,"40-70",IF(X95<100,"70-100",IF(X95<200,"100-200","Over 200")))))) -> 0-10 | Z95: 2 | AA95: =IF(Z95<0.5,"0-0.5",IF(Z95<1,"0.5-1.0",IF(Z95<2,"1.0-2.0",IF(Z95<3.5,"2.0-3.5","Over 3.5")))) -> 2.0-3.5 | AB95: 4 | AC95: =VLOOKUP(AB95,Key!$C$20:$D$29,2,FALSE) -> Office Worker | AD95: 2 | AE95: =VLOOKUP(AD95,Key!$E$20:$F$24,2,FALSE) -> 300,000-500,000 | AF95: 5 | AG95: 4 | AH95: 1 | AI95: 2 | AJ95: 3 | AK95: Y | AL95: 5000 | AM95: =IF(AL95<1000,"0-1000",IF(AL95<2000,"1000-2000",IF(AL95<3000,"2000-3000",IF(AL95<5000,"3000-5000",IF(AL95<10000,"5000-10000","Over 10000"))))) -> 5000-10000
A96: 43762 | B96: 0.34236111 | D96: D | E96: 2 | F96: =VLOOKUP(E96,Key!$A$17:$B$21,2,FALSE) -> Road Vehicle | G96: 1 | H96: =VLOOKUP(G96,Key!$A$2:$B$13,2,FALSE) -> Car | I96: M | J96: 2 | K96: =VLOOKUP(J96,Key!$A$24:$B$29,2,FALSE) -> 30-39 | L96: HIOMA | M96: HIOMA | N96: UG | O96: 1 | P96: =VLOOKUP(O96,Key!$E$2:$F$9,2,FALSE) -> Home | Q96: BULIISA | R96: BULIISA | S96: UG | T96: 2 | U96: =VLOOKUP(T96,Key!$E$2:$F$9,2,FALSE) -> Work | V96: =P96&"-"&U96 -> Home-Work | W96: 80000 | X96: 76 | Y96: =IF(X96<10,"0-10",IF(X96<20,"10-20",IF(X96<40,"20-40",IF(X96<70,"40-70",IF(X96<100,"70-100",IF(X96<200,"100-200","Over 200")))))) -> 70-100 | Z96: 2 | AA96: =IF(Z96<0.5,"0-0.5",IF(Z96<1,"0.5-1.0",IF(Z96<2,"1.0-2.0",IF(Z96<3.5,"2.0-3.5","Over 3.5")))) -> 2.0-3.5 | AB96: 5 | AC96: =VLOOKUP(AB96,Key!$C$20:$D$29,2,FALSE) -> Professional | AD96: 3 | AE96: =VLOOKUP(AD96,Key!$E$20:$F$24,2,FALSE) -> 500,000-750,000 | AF96: 2 | AG96: 3 | AH96: 5 | AI96: 1 | AJ96: 4 | AK96: Y | AL96: 1000 | AM96: =IF(AL96<1000,"0-1000",IF(AL96<2000,"1000-2000",IF(AL96<3000,"2000-3000",IF(AL96<5000,"3000-5000",IF(AL96<10000,"5000-10000","Over 10000"))))) -> 1000-2000
A97: 43763 | B97: 0.58263889 | D97: D | E97: 2 | F97: =VLOOKUP(E97,Key!$A$17:$B$21,2,FALSE) -> Road Vehicle | G97: 1 | H97: =VLOOKUP(G97,Key!$A$2:$B$13,2,FALSE) -> Car | I97: M | J97: 2 | K97: =VLOOKUP(J97,Key!$A$24:$B$29,2,FALSE) -> 30-39 | L97: HIOMA | M97: HIOMA | N97: UG | O97: 1 | P97: =VLOOKUP(O97,Key!$E$2:$F$9,2,FALSE) -> Home | Q97: BULIISA | R97: BULIISA | S97: UG | T97: 2 | U97: =VLOOKUP(T97,Key!$E$2:$F$9,2,FALSE) -> Work | V97: =P97&"-"&U97 -> Home-Work | W97: 80000 | X97: 79 | Y97: =IF(X97<10,"0-10",IF(X97<20,"10-20",IF(X97<40,"20-40",IF(X97<70,"40-70",IF(X97<100,"70-100",IF(X97<200,"100-200","Over 200")))))) -> 70-100 | Z97: 2 | AA97: =IF(Z97<0.5,"0-0.5",IF(Z97<1,"0.5-1.0",IF(Z97<2,"1.0-2.0",IF(Z97<3.5,"2.0-3.5","Over 3.5")))) -> 2.0-3.5 | AB97: 5 | AC97: =VLOOKUP(AB97,Key!$C$20:$D$29,2,FALSE) -> Professional | AD97: 3 | AE97: =VLOOKUP(AD97,Key!$E$20:$F$24,2,FALSE) -> 500,000-750,000 | AF97: 2 | AG97: 3 | AH97: 1 | AI97: 4 | AJ97: 5 | AK97: Y | AL97: 5000 | AM97: =IF(AL97<1000,"0-1000",IF(AL97<2000,"1000-2000",IF(AL97<3000,"2000-3000",IF(AL97<5000,"3000-5000",IF(AL97<10000,"5000-10000","Over 10000"))))) -> 5000-10000
A98: 43763 | B98: 0.74166667 | D98: D | E98: 2 | F98: =VLOOKUP(E98,Key!$A$17:$B$21,2,FALSE) -> Road Vehicle | G98: 1 | H98: =VLOOKUP(G98,Key!$A$2:$B$13,2,FALSE) -> Car | I98: M | J98: 2 | K98: =VLOOKUP(J98,Key!$A$24:$B$29,2,FALSE) -> 30-39 | L98: HIOMA | M98: HIOMA | N98: UG | O98: 1 | P98: =VLOOKUP(O98,Key!$E$2:$F$9,2,FALSE) -> Home | Q98: KAMPALA | R98: KAMPALA | S98: UG | T98: 2 | U98: =VLOOKUP(T98,Key!$E$2:$F$9,2,FALSE) -> Work | V98: =P98&"-"&U98 -> Home-Work | W98: 90000 | X98: 175 | Y98: =IF(X98<10,"0-10",IF(X98<20,"10-20",IF(X98<40,"20-40",IF(X98<70,"40-70",IF(X98<100,"70-100",IF(X98<200,"100-200","Over 200")))))) -> 100-200 | Z98: 3 | AA98: =IF(Z98<0.5,"0-0.5",IF(Z98<1,"0.5-1.0",IF(Z98<2,"1.0-2.0",IF(Z98<3.5,"2.0-3.5","Over 3.5")))) -> 2.0-3.5 | AB98: 2 | AC98: =VLOOKUP(AB98,Key!$C$20:$D$29,2,FALSE) -> Manual Labour | AD98: 2 | AE98: =VLOOKUP(AD98,Key!$E$20:$F$24,2,FALSE) -> 300,000-500,000 | AF98: 2 | AG98: 4 | AH98: 1 | AI98: 2 | AJ98: 2 | AK98: Y | AL98: 5000 | AM98: =IF(AL98<1000,"0-1000",IF(AL98<2000,"1000-2000",IF(AL98<3000,"2000-3000",IF(AL98<5000,"3000-5000",IF(AL98<10000,"5000-10000","Over 10000"))))) -> 5000-10000
A99: 43763 | B99: 0.36805556 | D99: P | E99: 2 | F99: =VLOOKUP(E99,Key!$A$17:$B$21,2,FALSE) -> Road Vehicle | G99: 1 | H99: =VLOOKUP(G99,Key!$A$2:$B$13,2,FALSE) -> Car | I99: M | J99: 2 | K99: =VLOOKUP(J99,Key!$A$24:$B$29,2,FALSE) -> 30-39 | L99: HIOMA | M99: HIOMA | N99: UG | O99: 1 | P99: =VLOOKUP(O99,Key!$E$2:$F$9,2,FALSE) -> Home | Q99: KABWOGA | R99: KIKUUBE | S99: UG | T99: 2 | U99: =VLOOKUP(T99,Key!$E$2:$F$9,2,FALSE) -> Work | V99: =P99&"-"&U99 -> Home-Work | W99: 7000 | X99: 32 | Y99: =IF(X99<10,"0-10",IF(X99<20,"10-20",IF(X99<40,"20-40",IF(X99<70,"40-70",IF(X99<100,"70-100",IF(X99<200,"100-200","Over 200")))))) -> 20-40 | Z99: 1 | AA99: =IF(Z99<0.5,"0-0.5",IF(Z99<1,"0.5-1.0",IF(Z99<2,"1.0-2.0",IF(Z99<3.5,"2.0-3.5","Over 3.5")))) -> 1.0-2.0 | AB99: 2 | AC99: =VLOOKUP(AB99,Key!$C$20:$D$29,2,FALSE) -> Manual Labour | AD99: 2 | AE99: =VLOOKUP(AD99,Key!$E$20:$F$24,2,FALSE) -> 300,000-500,000 | AF99: 2 | AG99: 3 | AH99: 5 | AI99: 1 | AJ99: 4 | AK99: Y | AL99: 2000 | AM99: =IF(AL99<1000,"0-1000",IF(AL99<2000,"1000-2000",IF(AL99<3000,"2000-3000",IF(AL99<5000,"3000-5000",IF(AL99<10000,"5000-10000","Over 10000"))))) -> 2000-3000
A100: 43763 | B100: 0.34375 | D100: P | E100: 2 | F100: =VLOOKUP(E100,Key!$A$17:$B$21,2,FALSE) -> Road Vehicle | G100: 1 | H100: =VLOOKUP(G100,Key!$A$2:$B$13,2,FALSE) -> Car | I100: M | J100: 2 | K100: =VLOOKUP(J100,Key!$A$24:$B$29,2,FALSE) -> 30-39 | L100: HIOMA | M100: HIOMA | N100: UG | O100: 1 | P100: =VLOOKUP(O100,Key!$E$2:$F$9,2,FALSE) -> Home | Q100: KIBOGA | R100: KIBOGA | S100: UG | T100: 2 | U100: =VLOOKUP(T100,Key!$E$2:$F$9,2,FALSE) -> Work | V100: =P100&"-"&U100 -> Home-Work | W100: 70000 | Y100: =IF(X100<10,"0-10",IF(X100<20,"10-20",IF(X100<40,"20-40",IF(X100<70,"40-70",IF(X100<100,"70-100",IF(X100<200,"100-200","Over 200")))))) -> 0-10 | Z100: 1 | AA100: =IF(Z100<0.5,"0-0.5",IF(Z100<1,"0.5-1.0",IF(Z100<2,"1.0-2.0",IF(Z100<3.5,"2.0-3.5","Over 3.5")))) -> 1.0-2.0 | AB100: 5 | AC100: =VLOOKUP(AB100,Key!$C$20:$D$29,2,FALSE) -> Professional | AD100: 3 | AE100: =VLOOKUP(AD100,Key!$E$20:$F$24,2,FALSE) -> 500,000-750,000 | AF100: 2 | AG100: 2 | AH100: 1 | AI100: 4 | AJ100: 4 | AK100: Y | AL100: 1000 | AM100: =IF(AL100<1000,"0-1000",IF(AL100<2000,"1000-2000",IF(AL100<3000,"2000-3000",IF(AL100<5000,"3000-5000",IF(AL100<10000,"5000-10000","Over 10000"))))) -> 1000-2000
...

Sheet RSI FORM
B1: Feasibility Study and Detailed Design of Kampala - Jinja Highway
B2: Roadside OD Interview Survey
B4: Date: | C4: 40465 | D4: Interviewer: | G4: Survey Station: | H4: Bweyogerere | J4: Direction: | K4: Bweyogerere-Kireka | L4: Coded By: | N4: Chkd By:
B7: Time Period | C7: Veh_Type | D7: Veh_Other | E7: Occupancy | F7: Origin_Address | H7: Origin_Purpose | I7: Origin_other | J7: Destination_Address | L7: Destination_Purpose | M7: Destination_Other | N7: Origin_Zone | O7: Dest_Zone | P7: WTP
F8: Village/Town | G8: City/Country | J8: Village/Town | K8: City/Country
B9: AM | C9: 3 | E9: 2 | F9: Entebbe | G9: Kla, Ug | H9: 1 | J9: Kla | K9: Kla, Ug | L9: 2 | N9: Blank | O9: Blank | P9: Yes | Q9: 3000
B10: AM | C10: 1 | E10: 1 | F10: Kiwanga | G10: Kla, Ug | H10: 1 | J10: Kla | K10: Kla, Ug | L10: 2 | N10: Blank | O10: Blank | P10: Yes | Q10: 2000
B11: AM | E11: 1 | F11: Bukoto | G11: Kla, Ug | H11: 3 | J11: Kla | K11: Kla, Ug | L11: 1 | N11: Blank | O11: Blank
B12: AM
B13: AM
B14: AM
B15: AM
B16: AM
B17: AM
B18: AM
B19: AM
B20: AM
B21: AM
B22: AM
B23: AM
... B53: AM

Sheet Key
B1: Vehicle Type | D1: Establishment Type | F1: Origin / Destination Purpose | H1: Trip Frequency | J1: Goods Type
A2: 1 | B2: Car | C2: 1 | D2: Residential | E2: 1 | F2: Home | G2: 1 | H2: more than 2 times every day | I2: 1 | J2: Food crop (Maize,rice,wheat etc)
A3: 2 | B3: Station Wagon | C3: 2 | D3: Office | E3: 2 | F3: Work | G3: 2 | H3: Daily (Up and Down) | I3: 2 | J3: Cash Crops (coffee,tea etc)
A4: 3 | B4: Pickups | C4: 3 | D4: Factory | E4: 3 | F4: Study | G4: 3 | H4: 2/3 times a week | I4: 3 | J4: Perishable (fish,milk,tea etc)
A5: 4 | B5: Minibus | C5: 4 | D5: Educational Facility | E5: 4 | F5: Commercial | G5: 4 | H5: Once a week | I5: 4 | J5: Construction Material (cement, gravel,stones,gravel,pipes)
A6: 5 | B6: Medium bus | C6: 5 | D6: Hospital | E6: 5 | F6: Tourism | G6: 5 | H6: Once a month | I6: 5 | J6: Metal/machinery
A7: 6 | B7: Large Bus | C7: 6 | D7: Bus / Taxi Park | E7: 6 | F7: Leisure/Social | G7: 6 | H7: Once in a while | I7: 6 | J7: Forestry products (timber & charcoal)
A8: 7 | B8: Light Truck | C8: 7 | D8: Wholesale shopping | E8: 7 | F8: Hospital | I8: 7 | J8: Fuels (any petroleum products)
A9: 8 | B9: Medium Truck | C9: 8 | D9: Boda boda stage | E9: 8 | F9: Others | I9: 8 | J9: Chemical Products (fertilizer,paints)
A10: 9 | B10: Heavy truck | C10: 9 | D10: Farm | I10: 9 | J10: Livestock (cows,goats,camel etc)
A11: 10 | B11: Truck Trailer | C11: 10 | D11: Construction Site | I11: 10 | J11: Household retail products (beverage,oil,sugar,salt,flour)
A12: 11 | B12: Motor cycles | C12: 11 | D12: Retail Shop/Market | I12: 11 | J12: Empty
A13: 12 | B13: Tractors | C13: 12 | D13: Warehouse | I13: 12 | J13: Others (Pl specify)
C14: 13 | D14: Harbour
C15: 14 | D15: Timber Centre
B16: Mode Number | C16: 15 | D16: Quarry
A17: 1 | B17: Walking/Cycling | C17: 16 | D17: Others (to be specified)
A18: 2 | B18: Road Vehicle
A19: 3 | B19: Rail | D19: Profession | F19: Monthly Income
A20: 4 | B20: Water/Ferry | C20: 1 | D20: Unemployed | E20: 1 | F20: <300,000
A21: 5 | B21: Air | C21: 2 | D21: Manual Labour | E21: 2 | F21: 300,000-500,000
C22: 3 | D22: Artisan/Domestic | E22: 3 | F22: 500,000-750,000
B23: Age Bracket No. | C23: 4 | D23: Office Worker | E23: 4 | F23: 750,000-1,000,000
A24: 1 | B24: 20-29 | C24: 5 | D24: Professional | E24: 5 | F24: >1,000,000
A25: 2 | B25: 30-39 | C25: 6 | D25: Businessman
A26: 3 | B26: 40-49 | C26: 7 | D26: Farmer
A27: 4 | B27: 50-59 | C27: 8 | D27: Student
A28: 5 | B28: 60-69 | C28: 9 | D28: Retired
A29: 6 | B29: 70- | C29: 10 | D29: Other
