Workbook
Name Dist: 'ALL DATA'!$S:$S
Name Jtime: 'ALL DATA'!$T:$T
Name Pay: 'ALL DATA'!$Z:$Z
Name TripFreq: 'ALL DATA'!$U:$U
Name Veh: 'ALL DATA'!$D:$D
Name Veh_Type: '12.10 KASANGATTI-MATUGGA'!$D$9:$D$37
Name Veh_Type: '14.10 MATUGGA-KASANGATI'!$D$9:$D$37
Name Veh_Type: '[1]25.07 BUSEGA-NATEETE'!$D:$D
Name Veh_Type: '[1]25.07 BUSEGA-NATEETE'!$D:$D
Name Veh_Type: '14.10 KASANGATI-MATUGGA'!$D$9:$D$37
Name zones: #REF!
Name zones: #REF!
Name zones: #REF!
Name Zones_Ndeke: #REF!
Name Zones_Ndeke: #REF!
Name Zones_Ndeke: #REF!

Sheet RSI FORM
B1: Feasibility Study and Detailed Design of Kampala - Jinja Highway
B2: Roadside OD Interview Survey
B4: Date: | C4: 40465 | D4: Interviewer: | G4: Survey Station: | H4: Bweyogerere | J4: Direction: | K4: Bweyogerere-Kireka | L4: Coded By: | N4: Chkd By:
B7: Time Period | C7: Veh_Type | D7: Veh_Other | E7: Occupancy | F7: Origin_Address | H7: Origin_Purpose | I7: Origin_other | J7: Destination_Address | L7: Destination_Purpose | M7: Destination_Other | N7: Origin_Zone | O7: Dest_Zone | P7: WTP
F8: Village/Town | G8: City/Country | J8: Village/Town | K8: City/Country
B9: AM | C9: 3 | E9: 2 | F9: Entebbe | G9: Kla, Ug | H9: 1 | J9: Kla | K9: Kla, Ug | L9: 2 | N9: Blank | O9: Blank | P9: Yes | Q9: 3000
B10: AM | C10: 1 | E10: 1 | F10: Kiwanga | G10: Kla, Ug | H10: 1 | J10: Kla | K10: Kla, Ug | L10: 2 | N10: Blank | O10: Blank | P10: Yes | Q10: 2000
B11: AM | E11: 1 | F11: Bukoto | G11: Kla, Ug | H11: 3 | J11: Kla | K11: Kla, Ug | L11: 1 | N11: Blank | O11: Blank
B12: AM
B13: AM
B14: AM
B15: AM
B16: AM
B17: AM
B18: AM
B19: AM
B20: AM
B21: AM
B22: AM
B23: AM
... B53: AM

Sheet Analysis
B3: Vehicle OD Sample Proportions | N3: Average Journey Time
B4: Vehicle Types | C4: OD Sample | D4: OD Sample, % | N4: Journey Time Range (Hrs) | O4: Cummu-lative | P4: No of Vehicles | Q4: No. of Vehicles, %
B5: Car | C5: =COUNTIF('ALL DATA'!$D$9:$D$5000,"1") -> 271 | D5: =C5/$C$17 -> 0.55876289 | N5: 0-0.25 | O5: =COUNTIF(Jtime,"<=0.25") -> 128 | P5: =O5 -> 128 | Q5: =P5/$O$15 -> 0.28381375
B6: Station Wagon | C6: =COUNTIF('ALL DATA'!$D$9:$D$5000,"2") -> 64 | D6: =C6/$C$17 -> 0.13195876 | N6: 0.25-0.50 | O6: =COUNTIF(Jtime,"<=0.5") -> 250 | P6: =O6-O5 -> 122 | Q6: =P6/$O$15 -> 0.27050998
B7: Pickups | C7: =COUNTIF('ALL DATA'!$D$9:$D$5000,"3") -> 19 | D7: =C7/$C$17 -> 0.039175258 | N7: 0.50-0.75 | O7: =COUNTIF(Jtime,"<=0.75") -> 303 | P7: =O7-O6 -> 53 | Q7: =P7/$O$15 -> 0.11751663
B8: Minibus, matatu | C8: =COUNTIF('ALL DATA'!$D$9:$D$5000,"4") -> 33 | D8: =C8/$C$17 -> 0.068041237 | N8: 0.75-1.00 | O8: =COUNTIF(Jtime,"<=1.0") -> 384 | P8: =O8-O7 -> 81 | Q8: =P8/$O$15 -> 0.17960089
B9: Medium bus | C9: =COUNTIF('ALL DATA'!$D$9:$D$5000,"5") -> 1 | D9: =C9/$C$17 -> 0.0020618557 | N9: 1.00-1.50 | O9: =COUNTIF(Jtime,"<=1.5") -> 403 | P9: =O9-O8 -> 19 | Q9: =P9/$O$15 -> 0.042128603
B10: Large Bus | C10: =COUNTIF('ALL DATA'!$D$9:$D$5000,"6") -> 1 | D10: =C10/$C$17 -> 0.0020618557 | N10: 1.5-2.0 | O10: =COUNTIF(Jtime,"<=2") -> 425 | P10: =O10-O9 -> 22 | Q10: =P10/$O$15 -> 0.048780488
B11: Light Truck | C11: =COUNTIF('ALL DATA'!$D$9:$D$5000,"7") -> 66 | D11: =C11/$C$17 -> 0.13608247 | N11: 2.0-3.0 | O11: =COUNTIF(Jtime,"<=3") -> 438 | P11: =O11-O10 -> 13 | Q11: =P11/$O$15 -> 0.028824834
B12: Medium Truck | C12: =COUNTIF('ALL DATA'!$D$9:$D$5000,"8") -> 19 | D12: =C12/$C$17 -> 0.039175258 | N12: 3.0-5.0 | O12: =COUNTIF(Jtime,"<=5") -> 444 | P12: =O12-O11 -> 6 | Q12: =P12/$O$15 -> 0.013303769
B13: Heavy truck | C13: =COUNTIF('ALL DATA'!$D$9:$D$5000,"9") -> 5 | D13: =C13/$C$17 -> 0.010309278 | N13: 5.0-7.5 | O13: =COUNTIF(Jtime,"<=7.5") -> 447 | P13: =O13-O12 -> 3 | Q13: =P13/$O$15 -> 0.0066518847
B14: Truck Trailer | C14: =COUNTIF('ALL DATA'!$D$9:$D$5000,"10") -> 2 | D14: =C14/$C$17 -> 0.0041237113 | N14: 7.5-10 | O14: =COUNTIF(Jtime,"<=10") -> 450 | P14: =O14-O13 -> 3 | Q14: =P14/$O$15 -> 0.0066518847
B15: Motor cycles | C15: =COUNTIF('ALL DATA'!$D$9:$D$5000,"11") -> 3 | D15: =C15/$C$17 -> 0.006185567 | N15: Over 10 | O15: =COUNTIF(Jtime,"<=15") -> 451 | P15: =O15-O14 -> 1 | Q15: =P15/$O$15 -> 0.0022172949
B16: Tractors | C16: =COUNTIF('ALL DATA'!$D$9:$D$5000,"12") -> 1 | D16: =C16/$C$17 -> 0.0020618557
C17: =SUM(C5:C16) -> 485
N21: Trip Frequency
B22: Journey Purpose | N22: Trip Frequency | O22: No of Vehicles | P22: No. of Vehicles, %
B23: Purpose | C23: Respondents | D23: Percent | N23: More than 2 times every day | O23: =COUNTIF(TripFreq,"=1") -> 131 | P23: =O23/$O$29 -> 0.27578947
B24: Home-Work | C24: =COUNTIF('ALL DATA'!$R$9:$R$5000,"Home-Work") -> 122 | D24: =C24/$C$29 -> 0.25154639 | N24: Daily (Up and Down) | O24: =COUNTIF(TripFreq,"=2") -> 177 | P24: =O24/$O$29 -> 0.37263158
B25: Home-Study | C25: =COUNTIF('ALL DATA'!$R$9:$R$369,"Home-Study") -> 8 | D25: =C25/$C$29 -> 0.016494845 | N25: 2/3 times a week | O25: =COUNTIF(TripFreq,"=3") -> 54 | P25: =O25/$O$29 -> 0.11368421
B26: Work-Home | C26: =COUNTIF('ALL DATA'!$R$9:$R$369,"Work-Home") -> 35 | D26: =C26/$C$29 -> 0.072164948 | N26: Once a week | O26: =COUNTIF(TripFreq,"=4") -> 26 | P26: =O26/$O$29 -> 0.054736842
B27: Work-Work | C27: =COUNTIF('ALL DATA'!$R$9:$R$369,"Work-Work") -> 39 | D27: =C27/$C$29 -> 0.080412371 | N27: Once a month | O27: =COUNTIF(TripFreq,"=5") -> 10 | P27: =O27/$O$29 -> 0.021052632
B28: Others | C28: =C29-SUM(C24:C27) -> 281 | D28: =C28/$C$29 -> 0.57938144 | N28: Once in a while | O28: =COUNTIF(TripFreq,"=6") -> 77 | P28: =O28/$O$29 -> 0.16210526
B29: Total | C29: =C17 -> 485 | O29: =SUM(O23:O28) -> 475
B40: Expressway Use
B41: Response | C41: Number | D41: Percent
B42: Yes | C42: =COUNTIF('ALL DATA'!$Y$9:$Y$5000,"Y") -> 479 | D42: =C42/$C$44 -> 0.98762887
B43: No | C43: =C44-C42 -> 6 | D43: =C43/$C$44 -> 0.012371134
B44: Total | C44: =C29 -> 485
R47: Home | S47: Work | T47: Study | U47: Commercial | V47: Tourism | W47: Leisure/Social | X47: Hospital | Y47: Others
P48: 1 | Q48: Home | R48: =R59/SUM($R$59:$Y$66) -> 0.063917526 | S48: =S59/SUM($R$59:$Y$66) -> 0.25154639 | T48: =T59/SUM($R$59:$Y$66) -> 0.020618557 | U48: =U59/SUM($R$59:$Y$66) -> 0.065979381 | V48: =V59/SUM($R$59:$Y$66) -> 0.0020618557 | W48: =W59/SUM($R$59:$Y$66) -> 0.028865979 | X48: =X59/SUM($R$59:$Y$66) -> 0.012371134 | Y48: =Y59/SUM($R$59:$Y$66) -> 0.055670103
P49: 2 | Q49: Work | R49: =R60/SUM($R$59:$Y$66) -> 0.084536082 | S49: =S60/SUM($R$59:$Y$66) -> 0.096907216 | T49: =T60/SUM($R$59:$Y$66) -> 0.006185567 | U49: =U60/SUM($R$59:$Y$66) -> 0.012371134 | V49: =V60/SUM($R$59:$Y$66) -> 0 | W49: =W60/SUM($R$59:$Y$66) -> 0.012371134 | X49: =X60/SUM($R$59:$Y$66) -> 0 | Y49: =Y60/SUM($R$59:$Y$66) -> 0.020618557
P50: 3 | Q50: Study | R50: =R61/SUM($R$59:$Y$66) -> 0.01443299 | S50: =S61/SUM($R$59:$Y$66) -> 0 | T50: =T61/SUM($R$59:$Y$66) -> 0.006185567 | U50: =U61/SUM($R$59:$Y$66) -> 0.0020618557 | V50: =V61/SUM($R$59:$Y$66) -> 0 | W50: =W61/SUM($R$59:$Y$66) -> 0 | X50: =X61/SUM($R$59:$Y$66) -> 0 | Y50: =Y61/SUM($R$59:$Y$66) -> 0
P51: 4 | Q51: Commercial | R51: =R62/SUM($R$59:$Y$66) -> 0.039175258 | S51: =S62/SUM($R$59:$Y$66) -> 0.010309278 | T51: =T62/SUM($R$59:$Y$66) -> 0 | U51: =U62/SUM($R$59:$Y$66) -> 0.074226804 | V51: =V62/SUM($R$59:$Y$66) -> 0 | W51: =W62/SUM($R$59:$Y$66) -> 0 | X51: =X62/SUM($R$59:$Y$66) -> 0 | Y51: =Y62/SUM($R$59:$Y$66) -> 0.0041237113
P52: 5 | Q52: Tourism | R52: =R63/SUM($R$59:$Y$66) -> 0.0041237113 | S52: =S63/SUM($R$59:$Y$66) -> 0 | T52: =T63/SUM($R$59:$Y$66) -> 0 | U52: =U63/SUM($R$59:$Y$66) -> 0 | V52: =V63/SUM($R$59:$Y$66) -> 0 | W52: =W63/SUM($R$59:$Y$66) -> 0 | X52: =X63/SUM($R$59:$Y$66) -> 0 | Y52: =Y63/SUM($R$59:$Y$66) -> 0
P53: 6 | Q53: Leisure/Social | R53: =R64/SUM($R$59:$Y$66) -> 0.006185567 | S53: =S64/SUM($R$59:$Y$66) -> 0.0020618557 | T53: =T64/SUM($R$59:$Y$66) -> 0 | U53: =U64/SUM($R$59:$Y$66) -> 0.0041237113 | V53: =V64/SUM($R$59:$Y$66) -> 0 | W53: =W64/SUM($R$59:$Y$66) -> 0.012371134 | X53: =X64/SUM($R$59:$Y$66) -> 0 | Y53: =Y64/SUM($R$59:$Y$66) -> 0
P54: 7 | Q54: Hospital | R54: =R65/SUM($R$59:$Y$66) -> 0.0082474227 | S54: =S65/SUM($R$59:$Y$66) -> 0 | T54: =T65/SUM($R$59:$Y$66) -> 0 | U54: =U65/SUM($R$59:$Y$66) -> 0 | V54: =V65/SUM($R$59:$Y$66) -> 0 | W54: =W65/SUM($R$59:$Y$66) -> 0 | X54: =X65/SUM($R$59:$Y$66) -> 0.0082474227 | Y54: =Y65/SUM($R$59:$Y$66) -> 0
P55: 8 | Q55: Others | R55: =R66/SUM($R$59:$Y$66) -> 0.016494845 | S55: =S66/SUM($R$59:$Y$66) -> 0.022680412 | T55: =T66/SUM($R$59:$Y$66) -> 0.0020618557 | U55: =U66/SUM($R$59:$Y$66) -> 0.006185567 | V55: =V66/SUM($R$59:$Y$66) -> 0 | W55: =W66/SUM($R$59:$Y$66) -> 0 | X55: =X66/SUM($R$59:$Y$66) -> 0.0020618557 | Y55: =Y66/SUM($R$59:$Y$66) -> 0.020618557
R57: 1 | S57: 2 | T57: 3 | U57: 4 | V57: 5 | W57: 6 | X57: 7 | Y57: 8
B58: Willingness to Pay | R58: Home | S58: Work | T58: Study | U58: Commercial | V58: Tourism | W58: Leisure/Social | X58: Hospital | Y58: Others
B59: Vehicle Types | C59: Average Price | P59: 1 | Q59: Home | R59: =COUNTIF('ALL DATA'!$R$9:$R$5000,R69) -> 31 | S59: =COUNTIF('ALL DATA'!$R$9:$R$5000,S69) -> 122 | T59: =COUNTIF('ALL DATA'!$R$9:$R$5000,T69) -> 10 | U59: =COUNTIF('ALL DATA'!$R$9:$R$5000,U69) -> 32 | V59: =COUNTIF('ALL DATA'!$R$9:$R$5000,V69) -> 1 | W59: =COUNTIF('ALL DATA'!$R$9:$R$5000,W69) -> 14 | X59: =COUNTIF('ALL DATA'!$R$9:$R$5000,X69) -> 6 | Y59: =COUNTIF('ALL DATA'!$R$9:$R$5000,Y69) -> 27
B60: Car | C60: =AVERAGEIF(Veh,"=1",'ALL DATA'!$Z$9:$Z$5000) -> 1889.6154 | P60: 2 | Q60: Work | R60: =COUNTIF('ALL DATA'!$R$9:$R$5000,R70) -> 41 | S60: =COUNTIF('ALL DATA'!$R$9:$R$5000,S70) -> 47 | T60: =COUNTIF('ALL DATA'!$R$9:$R$5000,T70) -> 3 | U60: =COUNTIF('ALL DATA'!$R$9:$R$5000,U70) -> 6 | V60: =COUNTIF('ALL DATA'!$R$9:$R$5000,V70) -> 0 | W60: =COUNTIF('ALL DATA'!$R$9:$R$5000,W70) -> 6 | X60: =COUNTIF('ALL DATA'!$R$9:$R$5000,X70) -> 0 | Y60: =COUNTIF('ALL DATA'!$R$9:$R$5000,Y70) -> 10
B61: Station Wagon | C61: =AVERAGEIF(Veh,"=2",'ALL DATA'!$Z$9:$Z$5000) -> 1817.4603 | P61: 3 | Q61: Study | R61: =COUNTIF('ALL DATA'!$R$9:$R$5000,R71) -> 7 | S61: =COUNTIF('ALL DATA'!$R$9:$R$5000,S71) -> 0 | T61: =COUNTIF('ALL DATA'!$R$9:$R$5000,T71) -> 3 | U61: =COUNTIF('ALL DATA'!$R$9:$R$5000,U71) -> 1 | V61: =COUNTIF('ALL DATA'!$R$9:$R$5000,V71) -> 0 | W61: =COUNTIF('ALL DATA'!$R$9:$R$5000,W71) -> 0 | X61: =COUNTIF('ALL DATA'!$R$9:$R$5000,X71) -> 0 | Y61: =COUNTIF('ALL DATA'!$R$9:$R$5000,Y71) -> 0
B62: Pickups | C62: =AVERAGEIF(Veh,"=3",'ALL DATA'!$Z$9:$Z$5000) -> 1176.4706 | P62: 4 | Q62: Commercial | R62: =COUNTIF('ALL DATA'!$R$9:$R$5000,R72) -> 19 | S62: =COUNTIF('ALL DATA'!$R$9:$R$5000,S72) -> 5 | T62: =COUNTIF('ALL DATA'!$R$9:$R$5000,T72) -> 0 | U62: =COUNTIF('ALL DATA'!$R$9:$R$5000,U72) -> 36 | V62: =COUNTIF('ALL DATA'!$R$9:$R$5000,V72) -> 0 | W62: =COUNTIF('ALL DATA'!$R$9:$R$5000,W72) -> 0 | X62: =COUNTIF('ALL DATA'!$R$9:$R$5000,X72) -> 0 | Y62: =COUNTIF('ALL DATA'!$R$9:$R$5000,Y72) -> 2
B63: Minibus, matatu | C63: =AVERAGEIF(Veh,"=4",'ALL DATA'!$Z$9:$Z$5000) -> 1621.2121 | P63: 5 | Q63: Tourism | R63: =COUNTIF('ALL DATA'!$R$9:$R$5000,R73) -> 2 | S63: =COUNTIF('ALL DATA'!$R$9:$R$5000,S73) -> 0 | T63: =COUNTIF('ALL DATA'!$R$9:$R$5000,T73) -> 0 | U63: =COUNTIF('ALL DATA'!$R$9:$R$5000,U73) -> 0 | V63: =COUNTIF('ALL DATA'!$R$9:$R$5000,V73) -> 0 | W63: =COUNTIF('ALL DATA'!$R$9:$R$5000,W73) -> 0 | X63: =COUNTIF('ALL DATA'!$R$9:$R$5000,X73) -> 0 | Y63: =COUNTIF('ALL DATA'!$R$9:$R$5000,Y73) -> 0
B64: Medium bus | C64: =AVERAGEIF(Veh,"=5",'ALL DATA'!$Z$9:$Z$5000) -> 2000 | P64: 6 | Q64: Leisure/Social | R64: =COUNTIF('ALL DATA'!$R$9:$R$5000,R74) -> 3 | S64: =COUNTIF('ALL DATA'!$R$9:$R$5000,S74) -> 1 | T64: =COUNTIF('ALL DATA'!$R$9:$R$5000,T74) -> 0 | U64: =COUNTIF('ALL DATA'!$R$9:$R$5000,U74) -> 2 | V64: =COUNTIF('ALL DATA'!$R$9:$R$5000,V74) -> 0 | W64: =COUNTIF('ALL DATA'!$R$9:$R$5000,W74) -> 6 | X64: =COUNTIF('ALL DATA'!$R$9:$R$5000,X74) -> 0 | Y64: =COUNTIF('ALL DATA'!$R$9:$R$5000,Y74) -> 0
B65: Large Bus | C65: =AVERAGEIF(Veh,"=6",'ALL DATA'!$Z$9:$Z$5000) -> 1000 | P65: 7 | Q65: Hospital | R65: =COUNTIF('ALL DATA'!$R$9:$R$5000,R75) -> 4 | S65: =COUNTIF('ALL DATA'!$R$9:$R$5000,S75) -> 0 | T65: =COUNTIF('ALL DATA'!$R$9:$R$5000,T75) -> 0 | U65: =COUNTIF('ALL DATA'!$R$9:$R$5000,U75) -> 0 | V65: =COUNTIF('ALL DATA'!$R$9:$R$5000,V75) -> 0 | W65: =COUNTIF('ALL DATA'!$R$9:$R$5000,W75) -> 0 | X65: =COUNTIF('ALL DATA'!$R$9:$R$5000,X75) -> 4 | Y65: =COUNTIF('ALL DATA'!$R$9:$R$5000,Y75) -> 0
B66: Light Truck | C66: =AVERAGEIF(Veh,"=7",'ALL DATA'!$Z$9:$Z$5000) -> 2270.7692 | P66: 8 | Q66: Others | R66: =COUNTIF('ALL DATA'!$R$9:$R$5000,R76) -> 8 | S66: =COUNTIF('ALL DATA'!$R$9:$R$5000,S76) -> 11 | T66: =COUNTIF('ALL DATA'!$R$9:$R$5000,T76) -> 1 | U66: =COUNTIF('ALL DATA'!$R$9:$R$5000,U76) -> 3 | V66: =COUNTIF('ALL DATA'!$R$9:$R$5000,V76) -> 0 | W66: =COUNTIF('ALL DATA'!$R$9:$R$5000,W76) -> 0 | X66: =COUNTIF('ALL DATA'!$R$9:$R$5000,X76) -> 1 | Y66: =COUNTIF('ALL DATA'!$R$9:$R$5000,Y76) -> 10
B67: Medium Truck | C67: =AVERAGEIF(Veh,"=8",'ALL DATA'!$Z$9:$Z$5000) -> 1221.0526
B68: Heavy truck | C68: =AVERAGEIF(Veh,"=9",'ALL DATA'!$Z$9:$Z$5000) -> 2000 | R68: Home | S68: Work | T68: Study | U68: Commercial | V68: Tourism | W68: Leisure/Social | X68: Hospital | Y68: Others
B69: Truck Trailer | C69: =AVERAGEIF(Veh,"=10",'ALL DATA'!$Z$9:$Z$5000) -> 3000 | P69: 1 | Q69: Home | R69: =$Q69&"-"&R$68 -> Home-Home | S69: =$Q69&"-"&S$68 -> Home-Work | T69: =$Q69&"-"&T$68 -> Home-Study | U69: =$Q69&"-"&U$68 -> Home-Commercial | V69: =$Q69&"-"&V$68 -> Home-Tourism | W69: =$Q69&"-"&W$68 -> Home-Leisure/Social | X69: =$Q69&"-"&X$68 -> Home-Hospital | Y69: =$Q69&"-"&Y$68 -> Home-Others
B70: Motor cycles | C70: =AVERAGEIF(Veh,"=11",'ALL DATA'!$Z$9:$Z$5000) -> 2666.6667 | P70: 2 | Q70: Work | R70: =$Q70&"-"&R$68 -> Work-Home | S70: =$Q70&"-"&S$68 -> Work-Work | T70: =$Q70&"-"&T$68 -> Work-Study | U70: =$Q70&"-"&U$68 -> Work-Commercial | V70: =$Q70&"-"&V$68 -> Work-Tourism | W70: =$Q70&"-"&W$68 -> Work-Leisure/Social | X70: =$Q70&"-"&X$68 -> Work-Hospital | Y70: =$Q70&"-"&Y$68 -> Work-Others
B71: Tractors | C71: =AVERAGEIF(Veh,"=12",'ALL DATA'!$Z$9:$Z$5000) -> 2000 | P71: 3 | Q71: Study | R71: =$Q71&"-"&R$68 -> Study-Home | S71: =$Q71&"-"&S$68 -> Study-Work | T71: =$Q71&"-"&T$68 -> Study-Study | U71: =$Q71&"-"&U$68 -> Study-Commercial | V71: =$Q71&"-"&V$68 -> Study-Tourism | W71: =$Q71&"-"&W$68 -> Study-Leisure/Social | X71: =$Q71&"-"&X$68 -> Study-Hospital | Y71: =$Q71&"-"&Y$68 -> Study-Others
P72: 4 | Q72: Commercial | R72: =$Q72&"-"&R$68 -> Commercial-Home | S72: =$Q72&"-"&S$68 -> Commercial-Work | T72: =$Q72&"-"&T$68 -> Commercial-Study | U72: =$Q72&"-"&U$68 -> Commercial-Commercial | V72: =$Q72&"-"&V$68 -> Commercial-Tourism | W72: =$Q72&"-"&W$68 -> Commercial-Leisure/Social | X72: =$Q72&"-"&X$68 -> Commercial-Hospital | Y72: =$Q72&"-"&Y$68 -> Commercial-Others
P73: 5 | Q73: Tourism | R73: =$Q73&"-"&R$68 -> Tourism-Home | S73: =$Q73&"-"&S$68 -> Tourism-Work | T73: =$Q73&"-"&T$68 -> Tourism-Study | U73: =$Q73&"-"&U$68 -> Tourism-Commercial | V73: =$Q73&"-"&V$68 -> Tourism-Tourism | W73: =$Q73&"-"&W$68 -> Tourism-Leisure/Social | X73: =$Q73&"-"&X$68 -> Tourism-Hospital | Y73: =$Q73&"-"&Y$68 -> Tourism-Others
P74: 6 | Q74: Leisure/Social | R74: =$Q74&"-"&R$68 -> Leisure/Social-Home | S74: =$Q74&"-"&S$68 -> Leisure/Social-Work | T74: =$Q74&"-"&T$68 -> Leisure/Social-Study | U74: =$Q74&"-"&U$68 -> Leisure/Social-Commercial | V74: =$Q74&"-"&V$68 -> Leisure/Social-Tourism | W74: =$Q74&"-"&W$68 -> Leisure/Social-Leisure/Social | X74: =$Q74&"-"&X$68 -> Leisure/Social-Hospital | Y74: =$Q74&"-"&Y$68 -> Leisure/Social-Others
P75: 7 | Q75: Hospital | R75: =$Q75&"-"&R$68 -> Hospital-Home | S75: =$Q75&"-"&S$68 -> Hospital-Work | T75: =$Q75&"-"&T$68 -> Hospital-Study | U75: =$Q75&"-"&U$68 -> Hospital-Commercial | V75: =$Q75&"-"&V$68 -> Hospital-Tourism | W75: =$Q75&"-"&W$68 -> Hospital-Leisure/Social | X75: =$Q75&"-"&X$68 -> Hospital-Hospital | Y75: =$Q75&"-"&Y$68 -> Hospital-Others
P76: 8 | Q76: Others | R76: =$Q76&"-"&R$68 -> Others-Home | S76: =$Q76&"-"&S$68 -> Others-Work | T76: =$Q76&"-"&T$68 -> Others-Study | U76: =$Q76&"-"&U$68 -> Others-Commercial | V76: =$Q76&"-"&V$68 -> Others-Tourism | W76: =$Q76&"-"&W$68 -> Others-Leisure/Social | X76: =$Q76&"-"&X$68 -> Others-Hospital | Y76: =$Q76&"-"&Y$68 -> Others-Others
B78: Average Trip Length
B79: Trip Length Range | C79: Cumm-ulative | D79: No of Vehicles | E79: Percentage
B80: 0-1 | C80: =COUNTIF(Dist,"<=1") -> 18 | D80: =C80 -> 18 | E80: =D80/$C$88 -> 0.053412463
B81: 1-2.5 | C81: =COUNTIF(Dist,"<=2.5") -> 57 | D81: =C81-C80 -> 39 | E81: =D81/$C$88 -> 0.115727
B82: 2.5-5.0 | C82: =COUNTIF(Dist,"<=5") -> 136 | D82: =C82-C81 -> 79 | E82: =D82/$C$88 -> 0.23442136
B83: 5.0-10.0 | C83: =COUNTIF(Dist,"<=10") -> 203 | D83: =C83-C82 -> 67 | E83: =D83/$C$88 -> 0.19881306
B84: 10.0-20.0 | C84: =COUNTIF(Dist,"<=20") -> 268 | D84: =C84-C83 -> 65 | E84: =D84/$C$88 -> 0.19287834
B85: 20.0-50.0 | C85: =COUNTIF(Dist,"<=50") -> 310 | D85: =C85-C84 -> 42 | E85: =D85/$C$88 -> 0.12462908
B86: 50.0-100.0 | C86: =COUNTIF(Dist,"<=100") -> 322 | D86: =C86-C85 -> 12 | E86: =D86/$C$88 -> 0.035608309
B87: 100.0-250.0 | C87: =COUNTIF(Dist,"<=250") -> 327 | D87: =C87-C86 -> 5 | E87: =D87/$C$88 -> 0.014836795
B88: Over 250 | C88: =COUNTIF(Dist,"<=700") -> 337 | D88: =C88-C87 -> 10 | E88: =D88/$C$88 -> 0.029673591

Sheet ALL DATA
B1: Consultancy services for Preparation of Expressway Develo PMent Master Plan (EDMP) for Uganda
B2: Roadside OD Interview Survey
B4: Date: | C4: 12.10.19 | E4: Road Name: | F4: ='14.10 KASANGATI-MATUGGA'!F4:G4 -> MATUGGA-WAKISO ROAD | I4: Direction From: | L4: MATUGGA | N4: Interviewers: | O4: SHAMIRAH, JULIUS | V4: Supervisor: | W4: STEVEN | Y4: Coded By: | Z4: ='14.10 KASANGATI-MATUGGA'!Z4 -> DAVID | AA4: Chkd By: | AB4: Bakole Deo
I5: Direction To: | L5: KASANGATTI
B7: Time | C7: Veh_Reg_No. | D7: Veh_Type | E7: No. Occupants | F7: Origin_Address | I7: Origin_Establish | J7: Origin_Purpose | K7: Origin-Purpose Desc | L7: Destination_Address | O7: Destination_Establish | P7: Destination_Purpose | Q7: Destination_Purpose Desc | R7: Journey_Purpose | S7: Approx_Distance (Km) | T7: Approx_Journey Time (Hrs) | U7: Trip_Frequency | V7: GOODS VEHICLES ONLY | Y7: Would You Use Xpressways? | Z7: Pay How Much? (UGX) | AA7: Origin_Zone | AB7: Dest_Zone
F8: Village or Town | G8: District | H8: Country | L8: Village or Town | M8: District | N8: Country | V8: Goods_Type | W8: Goods_Quantity (Ton) | X8: Goods_Value (UGXm)
B9: 0.67152778 | C9: UAP 387B | D9: 8 | E9: 1 | F9: KASENGEJJE | G9: WAKISO | H9: UGA | I9: 9 | J9: 1 | K9: =VLOOKUP(J9,Key!$E$2:$F$9,2,FALSE) -> Home | L9: KASANGATTI | M9: WAKISO | N9: UGA | O9: 1 | P9: 1 | Q9: =VLOOKUP(P9,Key!$E$2:$F$9,2,FALSE) -> Home | R9: =K9&"-"&Q9 -> Home-Home | U9: 1 | V9: 11 | Y9: Y | Z9: 3000 | AA9: =VLOOKUP(F9,Zones!$A$2:$F$2186,6,FALSE) -> 1402 | AB9: =VLOOKUP(L9,Zones!$A$2:$F$2186,6,FALSE) -> 1393
B10: 0.67291667 | C10: UAN 185N | D10: 1 | E10: 2 | F10: KABUSU | G10: WAKISO | H10: UGA | I10: 7 | J10: 1 | K10: =VLOOKUP(J10,Key!$E$2:$F$9,2,FALSE) -> Home | L10: BUKOTO | M10: KAMPALA | N10: UGA | O10: 1 | P10: 1 | Q10: =VLOOKUP(P10,Key!$E$2:$F$9,2,FALSE) -> Home | R10: =K10&"-"&Q10 -> Home-Home | S10: 3 | U10: 1 | Y10: Y | Z10: 3500 | AA10: =VLOOKUP(F10,Zones!$A$2:$F$2186,6,FALSE) -> 565 | AB10: =VLOOKUP(L10,Zones!$A$2:$F$2186,6,FALSE) -> 516
B11: 0.62222222 | C11: UAK 338U | D11: 1 | E11: 5 | F11: KITI | G11: WAKISO | H11: UGA | I11: 1 | J11: 3 | K11: =VLOOKUP(J11,Key!$E$2:$F$9,2,FALSE) -> Study | L11: KIIRA | M11: WAKISO | N11: UGA | O11: 4 | P11: 3 | Q11: =VLOOKUP(P11,Key!$E$2:$F$9,2,FALSE) -> Study | R11: =K11&"-"&Q11 -> Study-Study | T11: 0.1 | U11: 1 | Y11: Y | Z11: 3500 | AA11: =VLOOKUP(F11,Zones!$A$2:$F$2186,6,FALSE) -> 1402 | AB11: =VLOOKUP(L11,Zones!$A$2:$F$2186,6,FALSE) -> 1396
B12: 0.625 | C12: UBE 33Q | D12: 1 | E12: 4 | F12: MATUGGA | G12: WAKISO | H12: UGA | I12: 1 | J12: 8 | K12: =VLOOKUP(J12,Key!$E$2:$F$9,2,FALSE) -> Others | L12: MULAGO | M12: KAMPALA | N12: UGA | O12: 4 | P12: 8 | Q12: =VLOOKUP(P12,Key!$E$2:$F$9,2,FALSE) -> Others | R12: =K12&"-"&Q12 -> Others-Others | S12: 7 | T12: 0.2 | U12: 5 | Y12: Y | Z12: 1000 | AA12: =VLOOKUP(F12,Zones!$A$2:$F$2186,6,FALSE) -> 1402 | AB12: =VLOOKUP(L12,Zones!$A$2:$F$2186,6,FALSE) -> 560
B13: 0.62986111 | C13: UAL 290P | D13: 1 | E13: 2 | F13: WAKISO TOWN | G13: WAKISO | H13: UGA | I13: 1 | J13: 2 | K13: =VLOOKUP(J13,Key!$E$2:$F$9,2,FALSE) -> Work | L13: KASANGATTI | M13: WAKISO | N13: UGA | O13: 7 | P13: 4 | Q13: =VLOOKUP(P13,Key!$E$2:$F$9,2,FALSE) -> Commercial | R13: =K13&"-"&Q13 -> Work-Commercial | T13: 0.1 | U13: 1 | Y13: Y | Z13: 400 | AA13: =VLOOKUP(F13,Zones!$A$2:$F$2186,6,FALSE) -> 1408 | AB13: =VLOOKUP(L13,Zones!$A$2:$F$2186,6,FALSE) -> 1393
B14: 0.62777778 | C14: UBB 241W | D14: 1 | E14: 1 | F14: KITI | G14: WAKISO | H14: UGA | I14: 1 | J14: 7 | K14: =VLOOKUP(J14,Key!$E$2:$F$9,2,FALSE) -> Hospital | L14: GAYAZA | M14: WAKISO | N14: UGA | O14: 5 | P14: 7 | Q14: =VLOOKUP(P14,Key!$E$2:$F$9,2,FALSE) -> Hospital | R14: =K14&"-"&Q14 -> Hospital-Hospital | S14: 5 | T14: 0.1 | U14: 1 | Y14: Y | Z14: 5000 | AA14: =VLOOKUP(F14,Zones!$A$2:$F$2186,6,FALSE) -> 1402 | AB14: =VLOOKUP(L14,Zones!$A$2:$F$2186,6,FALSE) -> 811
B15: 0.65833333 | C15: UBE 794R | D15: 1 | E15: 3 | F15: KITI | G15: WAKISO | H15: UGA | I15: 1 | J15: 1 | K15: =VLOOKUP(J15,Key!$E$2:$F$9,2,FALSE) -> Home | L15: KASANGATTI | M15: WAKISO | N15: UGA | O15: 5 | P15: 7 | Q15: =VLOOKUP(P15,Key!$E$2:$F$9,2,FALSE) -> Hospital | R15: =K15&"-"&Q15 -> Home-Hospital | S15: 2 | T15: 0.1 | U15: 6 | Y15: Y | Z15: 500 | AA15: =VLOOKUP(F15,Zones!$A$2:$F$2186,6,FALSE) -> 1402 | AB15: =VLOOKUP(L15,Zones!$A$2:$F$2186,6,FALSE) -> 1393
B16: 0.66319444 | C16: UBA 121B | D16: 3 | E16: 2 | F16: WAKISO TOWN | G16: WAKISO | H16: UGA | I16: 1 | J16: 6 | K16: =VLOOKUP(J16,Key!$E$2:$F$9,2,FALSE) -> Leisure/Social | L16: KASANGATTI | M16: WAKISO | N16: UGA | O16: 7 | P16: 6 | Q16: =VLOOKUP(P16,Key!$E$2:$F$9,2,FALSE) -> Leisure/Social | R16: =K16&"-"&Q16 -> Leisure/Social-Leisure/Social | S16: 0.5 | T16: 0.1 | U16: 1 | Y16: Y | Z16: 1000 | AA16: =VLOOKUP(F16,Zones!$A$2:$F$2186,6,FALSE) -> 1408 | AB16: =VLOOKUP(L16,Zones!$A$2:$F$2186,6,FALSE) -> 1393
B17: 0.61458333 | C17: UAY 217M | D17: 1 | E17: 2 | F17: MATUGGA | G17: WAKISO | H17: UGA | I17: 1 | J17: 6 | K17: =VLOOKUP(J17,Key!$E$2:$F$9,2,FALSE) -> Leisure/Social | L17: GAYAZA | M17: WAKISO | N17: UGA | O17: 1 | P17: 6 | Q17: =VLOOKUP(P17,Key!$E$2:$F$9,2,FALSE) -> Leisure/Social | R17: =K17&"-"&Q17 -> Leisure/Social-Leisure/Social | S17: 7 | T17: 0.1 | U17: 1 | Y17: Y | Z17: 1000 | AA17: =VLOOKUP(F17,Zones!$A$2:$F$2186,6,FALSE) -> 1402 | AB17: =VLOOKUP(L17,Zones!$A$2:$F$2186,6,FALSE) -> 811
B18: 0.61180556 | C18: UAZ 061X | D18: 1 | E18: 6 | F18: WAKISO TOWN | G18: WAKISO | H18: UGA | I18: 1 | J18: 6 | K18: =VLOOKUP(J18,Key!$E$2:$F$9,2,FALSE) -> Leisure/Social | L18: GAYAZA | M18: WAKISO | N18: UGA | O18: 1 | P18: 6 | Q18: =VLOOKUP(P18,Key!$E$2:$F$9,2,FALSE) -> Leisure/Social | R18: =K18&"-"&Q18 -> Leisure/Social-Leisure/Social | S18: 3 | T18: 0.1 | U18: 1 | Y18: Y | Z18: 200 | AA18: =VLOOKUP(F18,Zones!$A$2:$F$2186,6,FALSE) -> 1408 | AB18: =VLOOKUP(L18,Zones!$A$2:$F$2186,6,FALSE) -> 811
B19: 0.64097222 | C19: UBA 239X | D19: 1 | E19: 2 | F19: NANGABO | G19: WAKISO | H19: UGA | I19: 1 | J19: 6 | K19: =VLOOKUP(J19,Key!$E$2:$F$9,2,FALSE) -> Leisure/Social | L19: KASANGATTI | M19: WAKISO | N19: UGA | O19: 7 | P19: 6 | Q19: =VLOOKUP(P19,Key!$E$2:$F$9,2,FALSE) -> Leisure/Social | R19: =K19&"-"&Q19 -> Leisure/Social-Leisure/Social | S19: 0.5 | T19: 0.1 | U19: 6 | Y19: Y | Z19: 2000 | AA19: =VLOOKUP(F19,Zones!$A$2:$F$2186,6,FALSE) -> 1393 | AB19: =VLOOKUP(L19,Zones!$A$2:$F$2186,6,FALSE) -> 1393
B20: 0.6375 | C20: UBE 072G | D20: 1 | E20: 5 | F20: WAKISO TOWN | G20: WAKISO | H20: UGA | I20: 1 | J20: 5 | K20: =VLOOKUP(J20,Key!$E$2:$F$9,2,FALSE) -> Tourism | L20: KASANGATTI | M20: WAKISO | N20: UGA | O20: 1 | P20: 1 | Q20: =VLOOKUP(P20,Key!$E$2:$F$9,2,FALSE) -> Home | R20: =K20&"-"&Q20 -> Tourism-Home | T20: 0.1 | U20: 1 | Y20: Y | Z20: 500 | AA20: =VLOOKUP(F20,Zones!$A$2:$F$2186,6,FALSE) -> 1408 | AB20: =VLOOKUP(L20,Zones!$A$2:$F$2186,6,FALSE) -> 1393
B21: 0.61944444 | C21: UAM 669D | D21: 1 | E21: 4 | F21: NANGABO | G21: WAKISO | H21: UGA | I21: 1 | J21: 1 | K21: =VLOOKUP(J21,Key!$E$2:$F$9,2,FALSE) -> Home | L21: MULAGO | M21: KAMPALA | N21: UGA | O21: 1 | P21: 1 | Q21: =VLOOKUP(P21,Key!$E$2:$F$9,2,FALSE) -> Home | R21: =K21&"-"&Q21 -> Home-Home | S21: 2 | T21: 0.1 | U21: 1 | Y21: Y | Z21: 3000 | AA21: =VLOOKUP(F21,Zones!$A$2:$F$2186,6,FALSE) -> 1393 | AB21: =VLOOKUP(L21,Zones!$A$2:$F$2186,6,FALSE) -> 560
B22: 0.61666667 | C22: UBA 695R | D22: 2 | E22: 2 | F22: NANGABO | G22: WAKISO | H22: UGA | I22: 1 | J22: 2 | K22: =VLOOKUP(J22,Key!$E$2:$F$9,2,FALSE) -> Work | L22: KAMPALA | M22: KAMPALA | N22: UGA | O22: 2 | P22: 2 | Q22: =VLOOKUP(P22,Key!$E$2:$F$9,2,FALSE) -> Work | R22: =K22&"-"&Q22 -> Work-Work | S22: 1.5 | T22: 0.1 | U22: 1 | Y22: Y | Z22: 5000 | AA22: =VLOOKUP(F22,Zones!$A$2:$F$2186,6,FALSE) -> 1393 | AB22: =VLOOKUP(L22,Zones!$A$2:$F$2186,6,FALSE) -> 521
B23: 0.42986111 | C23: UAR 383B | D23: 1 | E23: 2 | F23: WAKISO TOWN | G23: WAKISO | H23: UGA | I23: 1 | J23: 2 | K23: =VLOOKUP(J23,Key!$E$2:$F$9,2,FALSE) -> Work | L23: KASANGATTI | M23: WAKISO | N23: UGA | O23: 3 | P23: 2 | Q23: =VLOOKUP(P23,Key!$E$2:$F$9,2,FALSE) -> Work | R23: =K23&"-"&Q23 -> Work-Work | S23: 1 | T23: 0.1 | U23: 1 | Y23: Y | Z23: 1000 | AA23: =VLOOKUP(F23,Zones!$A$2:$F$2186,6,FALSE) -> 1408 | AB23: =VLOOKUP(L23,Zones!$A$2:$F$2186,6,FALSE) -> 1393
B24: 0.43125 | C24: UAP 465T | D24: 1 | E24: 6 | F24: WAKISO TOWN | G24: WAKISO | H24: UGA | I24: 1 | J24: 6 | K24: =VLOOKUP(J24,Key!$E$2:$F$9,2,FALSE) -> Leisure/Social | L24: NATEETE | M24: KAMPALA | N24: UGA | O24: 1 | P24: 1 | Q24: =VLOOKUP(P24,Key!$E$2:$F$9,2,FALSE) -> Home | R24: =K24&"-"&Q24 -> Leisure/Social-Home | S24: 10 | T24: 0.3 | U24: 1 | Y24: Y | Z24: 1000 | AA24: =VLOOKUP(F24,Zones!$A$2:$F$2186,6,FALSE) -> 1408 | AB24: =VLOOKUP(L24,Zones!$A$2:$F$2186,6,FALSE) -> 572
B25: 0.58333333 | C25: UBE 012B | D25: 2 | E25: 3 | F25: MPERERWE | G25: KAMPALA | H25: UGA | I25: 3 | J25: 4 | K25: =VLOOKUP(J25,Key!$E$2:$F$9,2,FALSE) -> Commercial | L25: GAYAZA | M25: WAKISO | N25: UGA | O25: 4 | P25: 4 | Q25: =VLOOKUP(P25,Key!$E$2:$F$9,2,FALSE) -> Commercial | R25: =K25&"-"&Q25 -> Commercial-Commercial | T25: 0.1 | U25: 1 | V25: 4 | W25: 1.5 | X25: 2 | Y25: Y | Z25: 2500 | AA25: =VLOOKUP(F25,Zones!$A$2:$F$2186,6,FALSE) -> 559 | AB25: =VLOOKUP(L25,Zones!$A$2:$F$2186,6,FALSE) -> 811
B26: 0.83194444 | C26: UAG 516K | D26: 1 | E26: 2 | F26: KITAGOBWA | G26: WAKISO | H26: UGA | I26: 1 | J26: 1 | K26: =VLOOKUP(J26,Key!$E$2:$F$9,2,FALSE) -> Home | L26: KAMPALA | M26: KAMPALA | N26: UGA | O26: 5 | P26: 7 | Q26: =VLOOKUP(P26,Key!$E$2:$F$9,2,FALSE) -> Hospital | R26: =K26&"-"&Q26 -> Home-Hospital | S26: 3 | T26: 0.1 | U26: 1 | Y26: Y | Z26: 3000 | AA26: =VLOOKUP(F26,Zones!$A$2:$F$2186,6,FALSE) -> 1408 | AB26: =VLOOKUP(L26,Zones!$A$2:$F$2186,6,FALSE) -> 521
B27: 0.43402778 | C27: UAW 117W | D27: 1 | E27: 3 | F27: MASOOLI | G27: WAKISO | H27: UGA | I27: 1 | J27: 1 | K27: =VLOOKUP(J27,Key!$E$2:$F$9,2,FALSE) -> Home | L27: KAMPALA | M27: KAMPALA | N27: UGA | O27: 5 | P27: 7 | Q27: =VLOOKUP(P27,Key!$E$2:$F$9,2,FALSE) -> Hospital | R27: =K27&"-"&Q27 -> Home-Hospital | S27: 1.5 | T27: 0.1 | U27: 1 | Y27: Y | Z27: 2000 | AA27: =VLOOKUP(F27,Zones!$A$2:$F$2186,6,FALSE) -> 542 | AB27: =VLOOKUP(L27,Zones!$A$2:$F$2186,6,FALSE) -> 521
B28: 0.44027778 | C28: UAH 787V | D28: 2 | E28: 1 | F28: NANGABO | G28: WAKISO | H28: UGA | I28: 1 | J28: 1 | K28: =VLOOKUP(J28,Key!$E$2:$F$9,2,FALSE) -> Home | L28: GAYAZA | M28: WAKISO | N28: UGA | O28: 7 | P28: 4 | Q28: =VLOOKUP(P28,Key!$E$2:$F$9,2,FALSE) -> Commercial | R28: =K28&"-"&Q28 -> Home-Commercial | S28: 5 | T28: 0.1 | U28: 1 | Y28: Y | Z28: 1000 | AA28: =VLOOKUP(F28,Zones!$A$2:$F$2186,6,FALSE) -> 1393 | AB28: =VLOOKUP(L28,Zones!$A$2:$F$2186,6,FALSE) -> 811
B29: 0.44305556 | C29: UAZ 508R | D29: 1 | E29: 2 | F29: GITTA | G29: WAKISO | H29: UGA | I29: 1 | J29: 4 | K29: =VLOOKUP(J29,Key!$E$2:$F$9,2,FALSE) -> Commercial | L29: KASANGATTI | M29: WAKISO | N29: UGA | O29: 7 | P29: 4 | Q29: =VLOOKUP(P29,Key!$E$2:$F$9,2,FALSE) -> Commercial | R29: =K29&"-"&Q29 -> Commercial-Commercial | T29: 0.3 | U29: 1 | Y29: Y | Z29: 1000 | AA29: =VLOOKUP(F29,Zones!$A$2:$F$2186,6,FALSE) -> 1393 | AB29: =VLOOKUP(L29,Zones!$A$2:$F$2186,6,FALSE) -> 1393
B30: 0.44722222 | C30: UAL 858S | D30: 1 | E30: 2 | F30: KITAGOBWA | G30: WAKISO | H30: UGA | I30: 1 | J30: 4 | K30: =VLOOKUP(J30,Key!$E$2:$F$9,2,FALSE) -> Commercial | L30: KASANGATTI | M30: WAKISO | N30: UGA | O30: 7 | P30: 4 | Q30: =VLOOKUP(P30,Key!$E$2:$F$9,2,FALSE) -> Commercial | R30: =K30&"-"&Q30 -> Commercial-Commercial | S30: 10 | T30: 0.3 | U30: 4 | Y30: Y | Z30: 1000 | AA30: =VLOOKUP(F30,Zones!$A$2:$F$2186,6,FALSE) -> 1408 | AB30: =VLOOKUP(L30,Zones!$A$2:$F$2186,6,FALSE) -> 1393
B31: 0.50763889 | C31: UAM 016T | D31: 1 | E31: 1 | F31: KITI | G31: WAKISO | H31: UGA | I31: 1 | J31: 2 | K31: =VLOOKUP(J31,Key!$E$2:$F$9,2,FALSE) -> Work | L31: KASANGATTI | M31: WAKISO | N31: UGA | O31: 2 | P31: 2 | Q31: =VLOOKUP(P31,Key!$E$2:$F$9,2,FALSE) -> Work | R31: =K31&"-"&Q31 -> Work-Work | S31: 25 | T31: 0.1 | U31: 1 | Y31: Y | Z31: 1000 | AA31: =VLOOKUP(F31,Zones!$A$2:$F$2186,6,FALSE) -> 1402 | AB31: =VLOOKUP(L31,Zones!$A$2:$F$2186,6,FALSE) -> 1393
B32: 0.50416667 | C32: UBB 033X | D32: 1 | E32: 3 | F32: KITI | G32: WAKISO | H32: UGA | I32: 1 | J32: 3 | K32: =VLOOKUP(J32,Key!$E$2:$F$9,2,FALSE) -> Study | L32: NAALYA | M32: KAMPALA | N32: UGA | O32: 4 | P32: 3 | Q32: =VLOOKUP(P32,Key!$E$2:$F$9,2,FALSE) -> Study | R32: =K32&"-"&Q32 -> Study-Study | S32: 3 | T32: 0.1 | U32: 1 | Y32: Y | Z32: 1000 | AA32: =VLOOKUP(F32,Zones!$A$2:$F$2186,6,FALSE) -> 1402 | AB32: =VLOOKUP(L32,Zones!$A$2:$F$2186,6,FALSE) -> 1405
B33: 0.45486111 | C33: UAT 557Z | D33: 1 | E33: 1 | F33: KITAGOBWA | G33: WAKISO | H33: UGA | I33: 1 | J33: 4 | K33: =VLOOKUP(J33,Key!$E$2:$F$9,2,FALSE) -> Commercial | L33: KAMPALA | M33: KAMPALA | N33: UGA | O33: 7 | P33: 4 | Q33: =VLOOKUP(P33,Key!$E$2:$F$9,2,FALSE) -> Commercial | R33: =K33&"-"&Q33 -> Commercial-Commercial | S33: 3 | T33: 0.2 | U33: 1 | Y33: Y | Z33: 1000 | AA33: =VLOOKUP(F33,Zones!$A$2:$F$2186,6,FALSE) -> 1408 | AB33: =VLOOKUP(L33,Zones!$A$2:$F$2186,6,FALSE) -> 521
B34: 0.45347222 | C34: UAZ 646P | D34: 7 | E34: 1 | F34: ZANA | G34: KAMPALA | H34: UGA | I34: 1 | J34: 2 | K34: =VLOOKUP(J34,Key!$E$2:$F$9,2,FALSE) -> Work | L34: NAKASERO | M34: KAMPALA | N34: UGA | O34: 2 | P34: 2 | Q34: =VLOOKUP(P34,Key!$E$2:$F$9,2,FALSE) -> Work | R34: =K34&"-"&Q34 -> Work-Work | S34: 12 | T34: 3 | U34: 6 | V34: 11 | Y34: Y | Z34: 2000 | AA34: =VLOOKUP(F34,Zones!$A$2:$F$2186,6,FALSE) -> 565 | AB34: =VLOOKUP(L34,Zones!$A$2:$F$2186,6,FALSE) -> 566
B35: 0.45972222 | C35: UAP 666J | D35: 1 | E35: 2 | F35: KITAGOBWA | G35: WAKISO | H35: UGA | I35: 1 | J35: 2 | K35: =VLOOKUP(J35,Key!$E$2:$F$9,2,FALSE) -> Work | L35: KAMPALA | M35: KAMPALA | N35: UGA | O35: 2 | P35: 2 | Q35: =VLOOKUP(P35,Key!$E$2:$F$9,2,FALSE) -> Work | R35: =K35&"-"&Q35 -> Work-Work | S35: 4 | T35: 1 | U35: 1 | Y35: Y | Z35: 1000 | AA35: =VLOOKUP(F35,Zones!$A$2:$F$2186,6,FALSE) -> 1408 | AB35: =VLOOKUP(L35,Zones!$A$2:$F$2186,6,FALSE) -> 521
B36: 0.46180556 | C36: UBB 762V | D36: 1 | E36: 1 | F36: NANGABO | G36: WAKISO | H36: UGA | I36: 1 | J36: 2 | K36: =VLOOKUP(J36,Key!$E$2:$F$9,2,FALSE) -> Work | L36: KAMPALA | M36: KAMPALA | N36: UGA | O36: 2 | P36: 2 | Q36: =VLOOKUP(P36,Key!$E$2:$F$9,2,FALSE) -> Work | R36: =K36&"-"&Q36 -> Work-Work | S36: 2 | T36: 0.1 | U36: 1 | Y36: Y | Z36: 1000 | AA36: =VLOOKUP(F36,Zones!$A$2:$F$2186,6,FALSE) -> 1393 | AB36: =VLOOKUP(L36,Zones!$A$2:$F$2186,6,FALSE) -> 521
B37: 0.49652778 | C37: UBB 501B | D37: 1 | E37: 3 | F37: NANGABO | G37: WAKISO | H37: UGA | I37: 1 | J37: 1 | K37: =VLOOKUP(J37,Key!$E$2:$F$9,2,FALSE) -> Home | L37: KAMPALA | M37: KAMPALA | N37: UGA | O37: 2 | P37: 2 | Q37: =VLOOKUP(P37,Key!$E$2:$F$9,2,FALSE) -> Work | R37: =K37&"-"&Q37 -> Home-Work | S37: 2 | T37: 0.2 | U37: 2 | Y37: Y | Z37: 2000 | AA37: =VLOOKUP(F37,Zones!$A$2:$F$2186,6,FALSE) -> 1393 | AB37: =VLOOKUP(L37,Zones!$A$2:$F$2186,6,FALSE) -> 521
B38: 0.49583333 | C38: UAK 084B | D38: 1 | E38: 1 | F38: NANGABO | G38: WAKISO | H38: UGA | I38: 1 | J38: 1 | K38: =VLOOKUP(J38,Key!$E$2:$F$9,2,FALSE) -> Home | L38: MPERRWE | M38: KAMPALA | N38: UGA | O38: 10 | P38: 4 | Q38: =VLOOKUP(P38,Key!$E$2:$F$9,2,FALSE) -> Commercial | R38: =K38&"-"&Q38 -> Home-Commercial | S38: 2 | T38: 0.1 | U38: 1 | Y38: Y | Z38: 1500 | AA38: =VLOOKUP(F38,Zones!$A$2:$F$2186,6,FALSE) -> 1393 | AB38: =VLOOKUP(L38,Zones!$A$2:$F$2186,6,FALSE) -> 559
B39: 0.49930556 | C39: UAG 564B | D39: 4 | E39: 6 | F39: KITI | G39: WAKISO | H39: UGA | I39: 1 | J39: 7 | K39: =VLOOKUP(J39,Key!$E$2:$F$9,2,FALSE) -> Hospital | L39: KASANGATTI | M39: WAKISO | N39: UGA | O39: 5 | P39: 7 | Q39: =VLOOKUP(P39,Key!$E$2:$F$9,2,FALSE) -> Hospital | R39: =K39&"-"&Q39 -> Hospital-Hospital | S39: 5 | T39: 0.1 | U39: 1 | Y39: Y | Z39: 2000 | AA39: =VLOOKUP(F39,Zones!$A$2:$F$2186,6,FALSE) -> 1402 | AB39: =VLOOKUP(L39,Zones!$A$2:$F$2186,6,FALSE) -> 1393
B40: 0.49791667 | C40: UAQ 112T | D40: 1 | E40: 3 | F40: KITAGOBWA | G40: WAKISO | H40: UGA | I40: 1 | J40: 6 | K40: =VLOOKUP(J40,Key!$E$2:$F$9,2,FALSE) -> Leisure/Social | L40: LUTETE | M40: WAKISO | N40: UGA | O40: 1 | P40: 6 | Q40: =VLOOKUP(P40,Key!$E$2:$F$9,2,FALSE) -> Leisure/Social | R40: =K40&"-"&Q40 -> Leisure/Social-Leisure/Social | S40: 2 | T40: 0.1 | U40: 1 | Y40: Y | Z40: 1000 | AA40: =VLOOKUP(F40,Zones!$A$2:$F$2186,6,FALSE) -> 1408 | AB40: =VLOOKUP(L40,Zones!$A$2:$F$2186,6,FALSE) -> 542
B41: 0.46597222 | C41: UAV 218T | D41: 1 | E41: 1 | F41: KITI | G41: WAKISO | H41: UGA | I41: 1 | J41: 7 | K41: =VLOOKUP(J41,Key!$E$2:$F$9,2,FALSE) -> Hospital | L41: SEETA | M41: MUKONO | N41: UGA | O41: 5 | P41: 7 | Q41: =VLOOKUP(P41,Key!$E$2:$F$9,2,FALSE) -> Hospital | R41: =K41&"-"&Q41 -> Hospital-Hospital | S41: 5 | T41: 0.3 | U41: 6 | Y41: Y | Z41: 2000 | AA41: =VLOOKUP(F41,Zones!$A$2:$F$2186,6,FALSE) -> 1402 | AB41: =VLOOKUP(L41,Zones!$A$2:$F$2186,6,FALSE) -> 1071
B42: 0.47291667 | C42: UBF 607T | D42: 8 | E42: 1 | F42: NANGABO | G42: WAKISO | H42: UGA | I42: 1 | J42: 2 | K42: =VLOOKUP(J42,Key!$E$2:$F$9,2,FALSE) -> Work | L42: KASANGATTI | M42: WAKISO | N42: UGA | O42: 3 | P42: 3 | Q42: =VLOOKUP(P42,Key!$E$2:$F$9,2,FALSE) -> Study | R42: =K42&"-"&Q42 -> Work-Study | T42: 2 | U42: 1 | V42: 11 | Y42: Y | Z42: 15000 | AA42: =VLOOKUP(F42,Zones!$A$2:$F$2186,6,FALSE) -> 1393 | AB42: =VLOOKUP(L42,Zones!$A$2:$F$2186,6,FALSE) -> 1393
B43: 0.41875 | C43: UAR 285A | D43: 1 | E43: 2 | F43: KAVULE | G43: WAKISO | H43: UGA | I43: 9 | J43: 2 | K43: =VLOOKUP(J43,Key!$E$2:$F$9,2,FALSE) -> Work | L43: NAKASERO | M43: KAMPALA | N43: UGA | O43: 2 | P43: 2 | Q43: =VLOOKUP(P43,Key!$E$2:$F$9,2,FALSE) -> Work | R43: =K43&"-"&Q43 -> Work-Work | S43: 7 | T43: 0.1 | U43: 1 | Y43: Y | Z43: 1000 | AA43: =VLOOKUP(F43,Zones!$A$2:$F$2186,6,FALSE) -> 583 | AB43: =VLOOKUP(L43,Zones!$A$2:$F$2186,6,FALSE) -> 566
B44: 0.42222222 | C44: UAM 057J | D44: 1 | E44: 1 | F44: GITTA | G44: WAKISO | H44: UGA | I44: 1 | J44: 2 | K44: =VLOOKUP(J44,Key!$E$2:$F$9,2,FALSE) -> Work | L44: NTINDA | M44: KAMPALA | N44: UGA | O44: 2 | P44: 2 | Q44: =VLOOKUP(P44,Key!$E$2:$F$9,2,FALSE) -> Work | R44: =K44&"-"&Q44 -> Work-Work | S44: 2 | T44: 0.1 | U44: 6 | Y44: Y | Z44: 1000 | AA44: =VLOOKUP(F44,Zones!$A$2:$F$2186,6,FALSE) -> 1393 | AB44: =VLOOKUP(L44,Zones!$A$2:$F$2186,6,FALSE) -> 577
B45: 0.46875 | C45: UED 711D | D45: 11 | E45: 2 | F45: KITI | G45: WAKISO | H45: UGA | I45: 1 | J45: 1 | K45: =VLOOKUP(J45,Key!$E$2:$F$9,2,FALSE) -> Home | L45: KASANGATTI | M45: WAKISO | N45: UGA | O45: 2 | P45: 2 | Q45: =VLOOKUP(P45,Key!$E$2:$F$9,2,FALSE) -> Work | R45: =K45&"-"&Q45 -> Home-Work | S45: 12 | T45: 0.1 | U45: 2 | Y45: Y | Z45: 1000 | AA45: =VLOOKUP(F45,Zones!$A$2:$F$2186,6,FALSE) -> 1402 | AB45: =VLOOKUP(L45,Zones!$A$2:$F$2186,6,FALSE) -> 1393
B46: 0.47152778 | C46: UAL 002F | D46: 7 | E46: 1 | F46: SSEMUTO | G46: WAKISO | H46: UGA | I46: 1 | J46: 1 | K46: =VLOOKUP(J46,Key!$E$2:$F$9,2,FALSE) -> Home | L46: MASOLI | M46: WAKISO | N46: UGA | O46: 2 | P46: 2 | Q46: =VLOOKUP(P46,Key!$E$2:$F$9,2,FALSE) -> Work | R46: =K46&"-"&Q46 -> Home-Work | T46: 0.8 | U46: 6 | V46: 11 | Y46: Y | Z46: 2000 | AA46: =VLOOKUP(F46,Zones!$A$2:$F$2186,6,FALSE) -> 1402 | AB46: =VLOOKUP(L46,Zones!$A$2:$F$2186,6,FALSE) -> 542
B47: 0.81388889 | C47: UAR 726J | D47: 1 | E47: 3 | F47: NANGABO | G47: WAKISO | H47: UGA | I47: 1 | J47: 1 | K47: =VLOOKUP(J47,Key!$E$2:$F$9,2,FALSE) -> Home | L47: NTINDA | M47: KAMPALA | N47: UGA | O47: 1 | P47: 6 | Q47: =VLOOKUP(P47,Key!$E$2:$F$9,2,FALSE) -> Leisure/Social | R47: =K47&"-"&Q47 -> Home-Leisure/Social | S47: 2 | T47: 0.1 | U47: 1 | Y47: Y | Z47: 1000 | AA47: =VLOOKUP(F47,Zones!$A$2:$F$2186,6,FALSE) -> 1393 | AB47: =VLOOKUP(L47,Zones!$A$2:$F$2186,6,FALSE) -> 577
B48: 0.8125 | C48: UAW 068P | D48: 8 | E48: 3 | F48: BUSEGA | G48: WAKISO | H48: UGA | I48: 1 | J48: 4 | K48: =VLOOKUP(J48,Key!$E$2:$F$9,2,FALSE) -> Commercial | L48: MUKONO | M48: MUKONO | N48: UGA | O48: 3 | P48: 4 | Q48: =VLOOKUP(P48,Key!$E$2:$F$9,2,FALSE) -> Commercial | R48: =K48&"-"&Q48 -> Commercial-Commercial | T48: 2 | U48: 1 | V48: 1 | W48: 8 | X48: 12 | Y48: Y | Z48: 2000 | AA48: =VLOOKUP(F48,Zones!$A$2:$F$2186,6,FALSE) -> 517 | AB48: =VLOOKUP(L48,Zones!$A$2:$F$2186,6,FALSE) -> 1064
B49: 0.56111111 | C49: UAR 877H | D49: 1 | E49: 4 | F49: NANGABO | G49: WAKISO | H49: UGA | I49: 1 | J49: 7 | K49: =VLOOKUP(J49,Key!$E$2:$F$9,2,FALSE) -> Hospital | L49: MPIGI | M49: MPIGI | N49: UGA | O49: 5 | P49: 7 | Q49: =VLOOKUP(P49,Key!$E$2:$F$9,2,FALSE) -> Hospital | R49: =K49&"-"&Q49 -> Hospital-Hospital | S49: 2 | T49: 0.2 | U49: 1 | Y49: Y | Z49: 1000 | AA49: =VLOOKUP(F49,Zones!$A$2:$F$2186,6,FALSE) -> 1393 | AB49: =VLOOKUP(L49,Zones!$A$2:$F$2186,6,FALSE) -> 1037
B50: 0.55972222 | C50: UBB 648R | D50: 1 | E50: 2 | F50: KITI | G50: WAKISO | H50: UGA | I50: 1 | J50: 1 | K50: =VLOOKUP(J50,Key!$E$2:$F$9,2,FALSE) -> Home | L50: MASOLI | M50: WAKISO | N50: UGA | O50: 4 | P50: 3 | Q50: =VLOOKUP(P50,Key!$E$2:$F$9,2,FALSE) -> Study | R50: =K50&"-"&Q50 -> Home-Study | T50: 0.1 | U50: 1 | Y50: Y | Z50: 2000 | AA50: =VLOOKUP(F50,Zones!$A$2:$F$2186,6,FALSE) -> 1402 | AB50: =VLOOKUP(L50,Zones!$A$2:$F$2186,6,FALSE) -> 542
B51: 0.55763889 | C51: UBE 625H | D51: 1 | E51: 1 | F51: KITAGOBWA | G51: WAKISO | H51: UGA | I51: 1 | J51: 1 | K51: =VLOOKUP(J51,Key!$E$2:$F$9,2,FALSE) -> Home | L51: MUKONO | M51: MUKONO | N51: UGA | O51: 8 | P51: 1 | Q51: =VLOOKUP(P51,Key!$E$2:$F$9,2,FALSE) -> Home | R51: =K51&"-"&Q51 -> Home-Home | S51: 7 | T51: 0.2 | U51: 1 | Y51: Y | Z51: 3000 | AA51: =VLOOKUP(F51,Zones!$A$2:$F$2186,6,FALSE) -> 1408 | AB51: =VLOOKUP(L51,Zones!$A$2:$F$2186,6,FALSE) -> 1064
B52: 0.55555556 | C52: UAZ 476E | D52: 1 | E52: 1 | F52: WAKISO TOWN | G52: LUWERO | H52: UGA | I52: 4 | J52: 3 | K52: =VLOOKUP(J52,Key!$E$2:$F$9,2,FALSE) -> Study | L52: MUKONO | M52: MUKONO | N52: UGA | O52: 1 | P52: 1 | Q52: =VLOOKUP(P52,Key!$E$2:$F$9,2,FALSE) -> Home | R52: =K52&"-"&Q52 -> Study-Home | T52: 0.7 | U52: 4 | Y52: Y | Z52: 1000 | AA52: =VLOOKUP(F52,Zones!$A$2:$F$2186,6,FALSE) -> 1408 | AB52: =VLOOKUP(L52,Zones!$A$2:$F$2186,6,FALSE) -> 1064
B53: 0.76111111 | C53: UBB 963V | D53: 1 | E53: 4 | F53: KAWANDA | G53: WAKISO | H53: UGA | I53: 1 | J53: 1 | K53: =VLOOKUP(J53,Key!$E$2:$F$9,2,FALSE) -> Home | L53: KASANGATTI | M53: WAKISO | N53: UGA | O53: 9 | P53: 2 | Q53: =VLOOKUP(P53,Key!$E$2:$F$9,2,FALSE) -> Work | R53: =K53&"-"&Q53 -> Home-Work | S53: 6 | T53: 0.7 | U53: 1 | Y53: Y | Z53: 3000 | AA53: =VLOOKUP(F53,Zones!$A$2:$F$2186,6,FALSE) -> 1402 | AB53: =VLOOKUP(L53,Zones!$A$2:$F$2186,6,FALSE) -> 1393
B54: 0.75 | C54: UAY 892J | D54: 2 | E54: 2 | F54: MATUGGA | G54: WAKISO | H54: UGA | I54: 9 | J54: 2 | K54: =VLOOKUP(J54,Key!$E$2:$F$9,2,FALSE) -> Work | L54: KASANGATTI | M54: WAKISO | N54: UGA | O54: 1 | P54: 1 | Q54: =VLOOKUP(P54,Key!$E$2:$F$9,2,FALSE) -> Home | R54: =K54&"-"&Q54 -> Work-Home | S54: 2 | T54: 0.7 | U54: 1 | Y54: Y | Z54: 3000 | AA54: =VLOOKUP(F54,Zones!$A$2:$F$2186,6,FALSE) -> 1402 | AB54: =VLOOKUP(L54,Zones!$A$2:$F$2186,6,FALSE) -> 1393
B55: 0.70486111 | C55: UBA 034D | D55: 7 | E55: 2 | F55: MATUGGA | G55: WAKISO | H55: UGA | I55: 11 | J55: 4 | K55: =VLOOKUP(J55,Key!$E$2:$F$9,2,FALSE) -> Commercial | L55: KASANGATTI | M55: WAKISO | N55: UGA | O55: 10 | P55: 4 | Q55: =VLOOKUP(P55,Key!$E$2:$F$9,2,FALSE) -> Commercial | R55: =K55&"-"&Q55 -> Commercial-Commercial | S55: 4 | T55: 0.5 | U55: 1 | V55: 10 | W55: 1 | X55: 0.25 | Y55: Y | Z55: 1000 | AA55: =VLOOKUP(F55,Zones!$A$2:$F$2186,6,FALSE) -> 1402 | AB55: =VLOOKUP(L55,Zones!$A$2:$F$2186,6,FALSE) -> 1393
B56: 0.70277778 | C56: UAB 809Z | D56: 2 | E56: 4 | F56: LUWEROO | G56: LUWERO | H56: UGA | I56: 9 | J56: 2 | K56: =VLOOKUP(J56,Key!$E$2:$F$9,2,FALSE) -> Work | L56: KASANGATTI | M56: WAKISO | N56: UGA | O56: 1 | P56: 1 | Q56: =VLOOKUP(P56,Key!$E$2:$F$9,2,FALSE) -> Home | R56: =K56&"-"&Q56 -> Work-Home | S56: 5 | T56: 3 | U56: 6 | Y56: Y | Z56: 2000 | AA56: =VLOOKUP(F56,Zones!$A$2:$F$2186,6,FALSE) -> 887 | AB56: =VLOOKUP(L56,Zones!$A$2:$F$2186,6,FALSE) -> 1393
B57: 0.7 | C57: UBD 866Y | D57: 1 | E57: 2 | F57: MATUGGA | G57: WAKISO | H57: UGA | I57: 5 | J57: 7 | K57: =VLOOKUP(J57,Key!$E$2:$F$9,2,FALSE) -> Hospital | L57: KASANGATTI | M57: WAKISO | N57: UGA | O57: 1 | P57: 1 | Q57: =VLOOKUP(P57,Key!$E$2:$F$9,2,FALSE) -> Home | R57: =K57&"-"&Q57 -> Hospital-Home | S57: 3 | T57: 0.3 | U57: 1 | Y57: Y | Z57: 500 | AA57: =VLOOKUP(F57,Zones!$A$2:$F$2186,6,FALSE) -> 1402 | AB57: =VLOOKUP(L57,Zones!$A$2:$F$2186,6,FALSE) -> 1393
B58: 0.69722222 | C58: UAQ 128S | D58: 1 | E58: 1 | F58: KAWANDA | G58: WAKISO | H58: UGA | I58: 16 | J58: 6 | K58: =VLOOKUP(J58,Key!$E$2:$F$9,2,FALSE) -> Leisure/Social | L58: KASANGATTI | M58: WAKISO | N58: UGA | O58: 16 | P58: 6 | Q58: =VLOOKUP(P58,Key!$E$2:$F$9,2,FALSE) -> Leisure/Social | R58: =K58&"-"&Q58 -> Leisure/Social-Leisure/Social | T58: 0.5 | U58: 6 | Y58: Y | Z58: 1000 | AA58: =VLOOKUP(F58,Zones!$A$2:$F$2186,6,FALSE) -> 1402 | AB58: =VLOOKUP(L58,Zones!$A$2:$F$2186,6,FALSE) -> 1393
B59: 0.6875 | C59: UBB 683B | D59: 1 | E59: 4 | F59: MATUGGA | G59: WAKISO | H59: UGA | I59: 1 | J59: 1 | K59: =VLOOKUP(J59,Key!$E$2:$F$9,2,FALSE) -> Home | L59: KAMPALA | M59: KAMPALA | N59: UGA | O59: 3 | P59: 2 | Q59: =VLOOKUP(P59,Key!$E$2:$F$9,2,FALSE) -> Work | R59: =K59&"-"&Q59 -> Home-Work | S59: 5 | T59: 0.7 | U59: 1 | Y59: Y | Z59: 1000 | AA59: =VLOOKUP(F59,Zones!$A$2:$F$2186,6,FALSE) -> 1402 | AB59: =VLOOKUP(L59,Zones!$A$2:$F$2186,6,FALSE) -> 521
B60: 0.67569444 | C60: UAH 249U | D60: 1 | E60: 3 | F60: NANGABO | G60: WAKISO | H60: UGA | I60: 9 | J60: 2 | K60: =VLOOKUP(J60,Key!$E$2:$F$9,2,FALSE) -> Work | L60: LUTEETE | M60: WAKISO | N60: UGA | O60: 1 | P60: 1 | Q60: =VLOOKUP(P60,Key!$E$2:$F$9,2,FALSE) -> Home | R60: =K60&"-"&Q60 -> Work-Home | S60: 4 | T60: 0.5 | U60: 1 | Y60: Y | Z60: 2000 | AA60: =VLOOKUP(F60,Zones!$A$2:$F$2186,6,FALSE) -> 1393 | AB60: =VLOOKUP(L60,Zones!$A$2:$F$2186,6,FALSE) -> 542
B61: 0.69513889 | C61: UBF 599F | D61: 1 | E61: 3 | F61: MATUGGA | G61: WAKISO | H61: UGA | I61: 1 | J61: 1 | K61: =VLOOKUP(J61,Key!$E$2:$F$9,2,FALSE) -> Home | L61: KASANGATTI | M61: WAKISO | N61: UGA | O61: 5 | P61: 7 | Q61: =VLOOKUP(P61,Key!$E$2:$F$9,2,FALSE) -> Hospital | R61: =K61&"-"&Q61 -> Home-Hospital | T61: 0.7 | U61: 1 | Y61: Y | Z61: 1000 | AA61: =VLOOKUP(F61,Zones!$A$2:$F$2186,6,FALSE) -> 1402 | AB61: =VLOOKUP(L61,Zones!$A$2:$F$2186,6,FALSE) -> 1393
B62: 0.69305556 | C62: UAN 162M | D62: 1 | E62: 2 | F62: KAWANDA | G62: WAKISO | H62: UGA | I62: 1 | J62: 1 | K62: =VLOOKUP(J62,Key!$E$2:$F$9,2,FALSE) -> Home | L62: KAMPALA | M62: KAMPALA | N62: UGA | O62: 16 | P62: 1 | Q62: =VLOOKUP(P62,Key!$E$2:$F$9,2,FALSE) -> Home | R62: =K62&"-"&Q62 -> Home-Home | S62: 6 | T62: 1 | U62: 1 | Y62: Y | Z62: 2000 | AA62: =VLOOKUP(F62,Zones!$A$2:$F$2186,6,FALSE) -> 1402 | AB62: =VLOOKUP(L62,Zones!$A$2:$F$2186,6,FALSE) -> 521
B63: 0.50486111 | C63: UAW 822A | D63: 1 | E63: 1 | F63: KITEGOMBA | G63: WAKISO | H63: UGA | I63: 1 | J63: 1 | K63: =VLOOKUP(J63,Key!$E$2:$F$9,2,FALSE) -> Home | L63: KAMPALA | M63: KAMPALA | N63: UGA | O63: 2 | P63: 2 | Q63: =VLOOKUP(P63,Key!$E$2:$F$9,2,FALSE) -> Work | R63: =K63&"-"&Q63 -> Home-Work | S63: 5 | T63: 0.5 | U63: 1 | Y63: Y | Z63: 3000 | AA63: =VLOOKUP(F63,Zones!$A$2:$F$2186,6,FALSE) -> 1393 | AB63: =VLOOKUP(L63,Zones!$A$2:$F$2186,6,FALSE) -> 521
B64: 0.50694444 | C64: UBB 954Y | D64: 2 | E64: 1 | F64: KITTI | G64: WAKISO | H64: UGA | I64: 1 | J64: 1 | K64: =VLOOKUP(J64,Key!$E$2:$F$9,2,FALSE) -> Home | L64: KASANGATTI | M64: WAKISO | N64: UGA | O64: 11 | P64: 4 | Q64: =VLOOKUP(P64,Key!$E$2:$F$9,2,FALSE) -> Commercial | R64: =K64&"-"&Q64 -> Home-Commercial | S64: 7 | T64: 0.1 | U64: 1 | Y64: Y | Z64: 0 | AA64: =VLOOKUP(F64,Zones!$A$2:$F$2186,6,FALSE) -> 1402 | AB64: =VLOOKUP(L64,Zones!$A$2:$F$2186,6,FALSE) -> 1393
B65: 0.64444444 | C65: UBE 345F | D65: 1 | E65: 1 | F65: KITTI | G65: WAKISO | H65: UGA | I65: 10 | J65: 2 | K65: =VLOOKUP(J65,Key!$E$2:$F$9,2,FALSE) -> Work | L65: BWEYOGERERE | M65: WAKISO | N65: UGA | O65: 1 | P65: 1 | Q65: =VLOOKUP(P65,Key!$E$2:$F$9,2,FALSE) -> Home | R65: =K65&"-"&Q65 -> Work-Home | S65: 30 | T65: 0.7 | U65: 4 | Y65: Y | Z65: 1000 | AA65: =VLOOKUP(F65,Zones!$A$2:$F$2186,6,FALSE) -> 1402 | AB65: =VLOOKUP(L65,Zones!$A$2:$F$2186,6,FALSE) -> 1386
B66: 0.66111111 | C66: UAL 541F | D66: 1 | E66: 5 | F66: KIWENDA | G66: WAKISO | H66: UGA | I66: 1 | J66: 1 | K66: =VLOOKUP(J66,Key!$E$2:$F$9,2,FALSE) -> Home | L66: KASANGATI | M66: WAKISO | N66: UGA | O66: 7 | P66: 4 | Q66: =VLOOKUP(P66,Key!$E$2:$F$9,2,FALSE) -> Commercial | R66: =K66&"-"&Q66 -> Home-Commercial | S66: 1 | T66: 0.1 | U66: 6 | Y66: Y | Z66: 10000 | AA66: =VLOOKUP(F66,Zones!$A$2:$F$2186,6,FALSE) -> 811 | AB66: =VLOOKUP(L66,Zones!$A$2:$F$2186,6,FALSE) -> 1393
B67: 0.63819444 | C67: UAN 672B | D67: 1 | E67: 2 | F67: KAMPALA | G67: KAMPALA | H67: UGA | I67: 2 | J67: 2 | K67: =VLOOKUP(J67,Key!$E$2:$F$9,2,FALSE) -> Work | L67: KAMPALA | M67: KAMPALA | N67: UGA | O67: 2 | P67: 2 | Q67: =VLOOKUP(P67,Key!$E$2:$F$9,2,FALSE) -> Work | R67: =K67&"-"&Q67 -> Work-Work | S67: 13 | T67: 0.7 | U67: 1 | Y67: Y | Z67: 3000 | AA67: =VLOOKUP(F67,Zones!$A$2:$F$2186,6,FALSE) -> 521 | AB67: =VLOOKUP(L67,Zones!$A$2:$F$2186,6,FALSE) -> 521
B68: 0.65625 | C68: UAQ 736D | D68: 1 | E68: 1 | F68: KITTI | G68: WAKISO | H68: UGA | I68: 10 | J68: 2 | K68: =VLOOKUP(J68,Key!$E$2:$F$9,2,FALSE) -> Work | L68: BUKOTO | M68: KAMPALA | N68: UGA | O68: 1 | P68: 1 | Q68: =VLOOKUP(P68,Key!$E$2:$F$9,2,FALSE) -> Home | R68: =K68&"-"&Q68 -> Work-Home | S68: 20 | T68: 0.2 | U68: 6 | Y68: Y | Z68: 0 | AA68: =VLOOKUP(F68,Zones!$A$2:$F$2186,6,FALSE) -> 1402 | AB68: =VLOOKUP(L68,Zones!$A$2:$F$2186,6,FALSE) -> 516
B69: 0.6625 | C69: UAW 841B | D69: 2 | E69: 2 | F69: MASINDI | G69: MASINDI | H69: UGA | I69: 15 | J69: 5 | K69: =VLOOKUP(J69,Key!$E$2:$F$9,2,FALSE) -> Tourism | L69: KAMPALA | M69: KAMPALA | N69: UGA | O69: 1 | P69: 1 | Q69: =VLOOKUP(P69,Key!$E$2:$F$9,2,FALSE) -> Home | R69: =K69&"-"&Q69 -> Tourism-Home | S69: 400 | T69: 5 | U69: 6 | Y69: Y | Z69: 10000 | AA69: =VLOOKUP(F69,Zones!$A$2:$F$2186,6,FALSE) -> 942 | AB69: =VLOOKUP(L69,Zones!$A$2:$F$2186,6,FALSE) -> 521
B70: 0.66458333 | C70: UAK 186N | D70: 4 | E70: 14 | F70: MATUGGA | G70: WAKISO | H70: UGA | I70: 6 | J70: 2 | K70: =VLOOKUP(J70,Key!$E$2:$F$9,2,FALSE) -> Work | L70: KIIRA | M70: WAKISO | N70: UGA | O70: 6 | P70: 2 | Q70: =VLOOKUP(P70,Key!$E$2:$F$9,2,FALSE) -> Work | R70: =K70&"-"&Q70 -> Work-Work | S70: 5 | T70: 0.5 | U70: 1 | Y70: Y | Z70: 2000 | AA70: =VLOOKUP(F70,Zones!$A$2:$F$2186,6,FALSE) -> 1402 | AB70: =VLOOKUP(L70,Zones!$A$2:$F$2186,6,FALSE) -> 1396
B71: 0.62638889 | C71: UAN 935S | D71: 1 | E71: 2 | F71: MATUGGA | G71: WAKISO | H71: UGA | I71: 3 | J71: 2 | K71: =VLOOKUP(J71,Key!$E$2:$F$9,2,FALSE) -> Work | L71: ENTEBBE | M71: WAKISO | N71: UGA | O71: 16 | P71: 8 | Q71: =VLOOKUP(P71,Key!$E$2:$F$9,2,FALSE) -> Others | R71: =K71&"-"&Q71 -> Work-Others | S71: 55 | T71: 2 | U71: 1 | Y71: Y | Z71: 3000 | AA71: =VLOOKUP(F71,Zones!$A$2:$F$2186,6,FALSE) -> 1402 | AB71: =VLOOKUP(L71,Zones!$A$2:$F$2186,6,FALSE) -> 1387
B72: 0.61944444 | C72: UBE 809J | D72: 1 | E72: 4 | F72: KITEGOMBA | G72: WAKISO | H72: UGA | I72: 1 | J72: 1 | K72: =VLOOKUP(J72,Key!$E$2:$F$9,2,FALSE) -> Home | L72: KAMPALA | M72: KAMPALA | N72: UGA | O72: 16 | P72: 6 | Q72: =VLOOKUP(P72,Key!$E$2:$F$9,2,FALSE) -> Leisure/Social | R72: =K72&"-"&Q72 -> Home-Leisure/Social | S72: 14 | T72: 0.5 | U72: 1 | Y72: Y | Z72: 2000 | AA72: =VLOOKUP(F72,Zones!$A$2:$F$2186,6,FALSE) -> 1393 | AB72: =VLOOKUP(L72,Zones!$A$2:$F$2186,6,FALSE) -> 521
B73: 0.63194444 | C73: UBD 272Y | D73: 7 | E73: 1 | F73: NANGABO | G73: WAKISO | H73: UGA | I73: 1 | J73: 1 | K73: =VLOOKUP(J73,Key!$E$2:$F$9,2,FALSE) -> Home | L73: KALERWE | M73: KAMPALA | N73: UGA | O73: 2 | P73: 2 | Q73: =VLOOKUP(P73,Key!$E$2:$F$9,2,FALSE) -> Work | R73: =K73&"-"&Q73 -> Home-Work | S73: 7 | T73: 0.7 | U73: 1 | V73: 3 | W73: 0.1 | X73: 1 | Y73: Y | Z73: 0 | AA73: =VLOOKUP(F73,Zones!$A$2:$F$2186,6,FALSE) -> 1393 | AB73: =VLOOKUP(L73,Zones!$A$2:$F$2186,6,FALSE) -> 546
B74: 0.63402778 | C74: UBB 626E | D74: 1 | E74: 2 | F74: KITTI | G74: WAKISO | H74: UGA | I74: 1 | J74: 1 | K74: =VLOOKUP(J74,Key!$E$2:$F$9,2,FALSE) -> Home | L74: BUKOTO | M74: KAMPALA | N74: UGA | O74: 16 | P74: 6 | Q74: =VLOOKUP(P74,Key!$E$2:$F$9,2,FALSE) -> Leisure/Social | R74: =K74&"-"&Q74 -> Home-Leisure/Social | S74: 10 | T74: 0.5 | U74: 1 | Y74: Y | Z74: 1000 | AA74: =VLOOKUP(F74,Zones!$A$2:$F$2186,6,FALSE) -> 1402 | AB74: =VLOOKUP(L74,Zones!$A$2:$F$2186,6,FALSE) -> 516
B75: 0.63055556 | C75: UAP 500J | D75: 4 | E75: 13 | F75: MATUGGA | G75: WAKISO | H75: UGA | I75: 6 | J75: 2 | K75: =VLOOKUP(J75,Key!$E$2:$F$9,2,FALSE) -> Work | L75: KASANGATTI | M75: WAKISO | N75: UGA | O75: 6 | P75: 2 | Q75: =VLOOKUP(P75,Key!$E$2:$F$9,2,FALSE) -> Work | R75: =K75&"-"&Q75 -> Work-Work | T75: 0.5 | U75: 1 | Y75: Y | Z75: 500 | AA75: =VLOOKUP(F75,Zones!$A$2:$F$2186,6,FALSE) -> 1402 | AB75: =VLOOKUP(L75,Zones!$A$2:$F$2186,6,FALSE) -> 1393
B76: 0.62777778 | C76: UBA 280B | D76: 1 | E76: 1 | F76: MASOLI | G76: WAKISO | H76: UGA | I76: 1 | J76: 1 | K76: =VLOOKUP(J76,Key!$E$2:$F$9,2,FALSE) -> Home | L76: KAMPALA | M76: KAMPALA | N76: UGA | O76: 2 | P76: 2 | Q76: =VLOOKUP(P76,Key!$E$2:$F$9,2,FALSE) -> Work | R76: =K76&"-"&Q76 -> Home-Work | T76: 0.5 | U76: 1 | Y76: Y | Z76: 500 | AA76: =VLOOKUP(F76,Zones!$A$2:$F$2186,6,FALSE) -> 542 | AB76: =VLOOKUP(L76,Zones!$A$2:$F$2186,6,FALSE) -> 521
B77: 0.61666667 | C77: UAY 348M | D77: 1 | E77: 2 | F77: GAYAZA | G77: WAKISO | H77: UGA | I77: 1 | J77: 1 | K77: =VLOOKUP(J77,Key!$E$2:$F$9,2,FALSE) -> Home | L77: KAMPALA | M77: KAMPALA | N77: UGA | O77: 7 | P77: 4 | Q77: =VLOOKUP(P77,Key!$E$2:$F$9,2,FALSE) -> Commercial | R77: =K77&"-"&Q77 -> Home-Commercial | S77: 18 | T77: 0.5 | U77: 1 | Y77: Y | Z77: 3000 | AA77: =VLOOKUP(F77,Zones!$A$2:$F$2186,6,FALSE) -> 811 | AB77: =VLOOKUP(L77,Zones!$A$2:$F$2186,6,FALSE) -> 521
B78: 0.61180556 | C78: UAN 166B | D78: 1 | E78: 1 | F78: NANGABO | G78: WAKISO | H78: UGA | I78: 1 | J78: 1 | K78: =VLOOKUP(J78,Key!$E$2:$F$9,2,FALSE) -> Home | L78: KASANGATTI | M78: WAKISO | N78: UGA | O78: 16 | P78: 6 | Q78: =VLOOKUP(P78,Key!$E$2:$F$9,2,FALSE) -> Leisure/Social | R78: =K78&"-"&Q78 -> Home-Leisure/Social | S78: 3 | T78: 0.3 | U78: 1 | Y78: Y | Z78: 2000 | AA78: =VLOOKUP(F78,Zones!$A$2:$F$2186,6,FALSE) -> 1393 | AB78: =VLOOKUP(L78,Zones!$A$2:$F$2186,6,FALSE) -> 1393
B79: 0.61388889 | C79: UAU 715G | D79: 2 | E79: 6 | F79: NANGABO | G79: WAKISO | H79: UGA | I79: 16 | J79: 8 | K79: =VLOOKUP(J79,Key!$E$2:$F$9,2,FALSE) -> Others | L79: KIIRA | M79: WAKISO | N79: UGA | O79: 1 | P79: 1 | Q79: =VLOOKUP(P79,Key!$E$2:$F$9,2,FALSE) -> Home | R79: =K79&"-"&Q79 -> Others-Home | S79: 8 | T79: 0.5 | U79: 4 | Y79: Y | Z79: 3000 | AA79: =VLOOKUP(F79,Zones!$A$2:$F$2186,6,FALSE) -> 1393 | AB79: =VLOOKUP(L79,Zones!$A$2:$F$2186,6,FALSE) -> 1396
B80: 0.81180556 | C80: UBB 936Y | D80: 2 | E80: 4 | F80: WAKISO TOWN | G80: WAKISO | H80: UGA | I80: 4 | J80: 2 | K80: =VLOOKUP(J80,Key!$E$2:$F$9,2,FALSE) -> Work | L80: WAKISO | M80: WAKISO | N80: UGA | O80: 1 | P80: 1 | Q80: =VLOOKUP(P80,Key!$E$2:$F$9,2,FALSE) -> Home | R80: =K80&"-"&Q80 -> Work-Home | S80: 30 | T80: 1 | U80: 1 | Y80: Y | Z80: 1000 | AA80: =VLOOKUP(F80,Zones!$A$2:$F$2186,6,FALSE) -> 1408 | AB80: =VLOOKUP(L80,Zones!$A$2:$F$2186,6,FALSE) -> 1408
B81: 0.57569444 | C81: UAV 197T | D81: 1 | E81: 4 | F81: MATUGGA | G81: WAKISO | H81: UGA | I81: 3 | J81: 2 | K81: =VLOOKUP(J81,Key!$E$2:$F$9,2,FALSE) -> Work | L81: GAYAZA | M81: WAKISO | N81: UGA | O81: 1 | P81: 1 | Q81: =VLOOKUP(P81,Key!$E$2:$F$9,2,FALSE) -> Home | R81: =K81&"-"&Q81 -> Work-Home | S81: 10 | T81: 0.1 | U81: 6 | Y81: Y | Z81: 0 | AA81: =VLOOKUP(F81,Zones!$A$2:$F$2186,6,FALSE) -> 1402 | AB81: =VLOOKUP(L81,Zones!$A$2:$F$2186,6,FALSE) -> 811
B82: 0.57777778 | C82: UAS 538M | D82: 1 | E82: 1 | F82: KAVULE | G82: WAKISO | H82: UGA | I82: 2 | J82: 2 | K82: =VLOOKUP(J82,Key!$E$2:$F$9,2,FALSE) -> Work | L82: WAKISO TOWN | M82: WAKISO | N82: UGA | O82: 1 | P82: 1 | Q82: =VLOOKUP(P82,Key!$E$2:$F$9,2,FALSE) -> Home | R82: =K82&"-"&Q82 -> Work-Home | S82: 22 | T82: 0.7 | U82: 3 | Y82: Y | Z82: 0 | AA82: =VLOOKUP(F82,Zones!$A$2:$F$2186,6,FALSE) -> 583 | AB82: =VLOOKUP(L82,Zones!$A$2:$F$2186,6,FALSE) -> 1408
B83: 0.60486111 | C83: UBA 109V | D83: 1 | E83: 1 | F83: NANGABO | G83: WAKISO | H83: UGA | I83: 1 | J83: 1 | K83: =VLOOKUP(J83,Key!$E$2:$F$9,2,FALSE) -> Home | L83: KASANGATI | M83: WAKISO | N83: UGA | O83: 7 | P83: 2 | Q83: =VLOOKUP(P83,Key!$E$2:$F$9,2,FALSE) -> Work | R83: =K83&"-"&Q83 -> Home-Work | S83: 2 | T83: 0.3 | Y83: Y | Z83: 500 | AA83: =VLOOKUP(F83,Zones!$A$2:$F$2186,6,FALSE) -> 1393 | AB83: =VLOOKUP(L83,Zones!$A$2:$F$2186,6,FALSE) -> 1393
B84: 0.57291667 | C84: UAM 695L | D84: 4 | E84: 14 | F84: WAKISO | G84: WAKISO | H84: UGA | I84: 6 | J84: 2 | K84: =VLOOKUP(J84,Key!$E$2:$F$9,2,FALSE) -> Work | L84: KASANGATI | M84: WAKISO | N84: UGA | O84: 6 | P84: 2 | Q84: =VLOOKUP(P84,Key!$E$2:$F$9,2,FALSE) -> Work | R84: =K84&"-"&Q84 -> Work-Work | S84: 20 | T84: 0.7 | U84: 1 | Y84: Y | Z84: 5000 | AA84: =VLOOKUP(F84,Zones!$A$2:$F$2186,6,FALSE) -> 1408 | AB84: =VLOOKUP(L84,Zones!$A$2:$F$2186,6,FALSE) -> 1393
B85: 0.60555556 | C85: UAU 967F | D85: 1 | E85: 4 | F85: NANGABO | G85: WAKISO | H85: UGA | I85: 1 | J85: 1 | K85: =VLOOKUP(J85,Key!$E$2:$F$9,2,FALSE) -> Home | L85: KASANGATI | M85: WAKISO | N85: UGA | O85: 2 | P85: 2 | Q85: =VLOOKUP(P85,Key!$E$2:$F$9,2,FALSE) -> Work | R85: =K85&"-"&Q85 -> Home-Work | S85: 4 | T85: 0.2 | U85: 1 | Y85: Y | Z85: 0 | AA85: =VLOOKUP(F85,Zones!$A$2:$F$2186,6,FALSE) -> 1393 | AB85: =VLOOKUP(L85,Zones!$A$2:$F$2186,6,FALSE) -> 1393
B86: 0.60625 | C86: UAH 249F | D86: 8 | E86: 2 | F86: LUWEROO | G86: WAKISO | H86: UGA | I86: 1 | J86: 1 | K86: =VLOOKUP(J86,Key!$E$2:$F$9,2,FALSE) -> Home | L86: NAMUGONGO | M86: WAKISO | N86: UGA | O86: 1 | P86: 1 | Q86: =VLOOKUP(P86,Key!$E$2:$F$9,2,FALSE) -> Home | R86: =K86&"-"&Q86 -> Home-Home | S86: 78 | T86: 2 | U86: 6 | Y86: Y | Z86: 2000 | AA86: =VLOOKUP(F86,Zones!$A$2:$F$2186,6,FALSE) -> 887 | AB86: =VLOOKUP(L86,Zones!$A$2:$F$2186,6,FALSE) -> 1405
B87: 0.57083333 | C87: UBE 068F | D87: 1 | E87: 2 | F87: KITEGOMBA | G87: WAKISO | H87: UGA | I87: 1 | J87: 1 | K87: =VLOOKUP(J87,Key!$E$2:$F$9,2,FALSE) -> Home | L87: KAMPALA | M87: KAMPALA | N87: UGA | O87: 11 | P87: 4 | Q87: =VLOOKUP(P87,Key!$E$2:$F$9,2,FALSE) -> Commercial | R87: =K87&"-"&Q87 -> Home-Commercial | T87: 0.7 | U87: 1 | Y87: Y | Z87: 2000 | AA87: =VLOOKUP(F87,Zones!$A$2:$F$2186,6,FALSE) -> 1393 | AB87: =VLOOKUP(L87,Zones!$A$2:$F$2186,6,FALSE) -> 521
B88: 0.56527778 | C88: UAZ 845X | D88: 1 | E88: 1 | F88: KASANGATTI | G88: WAKISO | H88: UGA | I88: 1 | J88: 1 | K88: =VLOOKUP(J88,Key!$E$2:$F$9,2,FALSE) -> Home | L88: NAKAWA | M88: KAMPALA | N88: UGA | O88: 2 | P88: 2 | Q88: =VLOOKUP(P88,Key!$E$2:$F$9,2,FALSE) -> Work | R88: =K88&"-"&Q88 -> Home-Work | S88: 23 | T88: 0.7 | U88: 1 | Y88: Y | Z88: 3000 | AA88: =VLOOKUP(F88,Zones!$A$2:$F$2186,6,FALSE) -> 1393 | AB88: =VLOOKUP(L88,Zones!$A$2:$F$2186,6,FALSE) -> 567
B89: 0.54930556 | C89: UAV 492M | D89: 7 | E89: 2 | F89: NANGABO | G89: WAKISO | H89: UGA | I89: 1 | J89: 1 | K89: =VLOOKUP(J89,Key!$E$2:$F$9,2,FALSE) -> Home | L89: KASANGATTI | M89: WAKISO | N89: UGA | O89: 6 | P89: 2 | Q89: =VLOOKUP(P89,Key!$E$2:$F$9,2,FALSE) -> Work | R89: =K89&"-"&Q89 -> Home-Work | S89: 2 | T89: 0.1 | U89: 6 | V89: 5 | W89: 0.1 | Y89: Y | Z89: 300 | AA89: =VLOOKUP(F89,Zones!$A$2:$F$2186,6,FALSE) -> 1393 | AB89: =VLOOKUP(L89,Zones!$A$2:$F$2186,6,FALSE) -> 1393
B90: 0.55 | C90: UAM 704W | D90: 1 | E90: 6 | F90: KITEGOMBA | G90: WAKISO | H90: UGA | I90: 2 | J90: 2 | K90: =VLOOKUP(J90,Key!$E$2:$F$9,2,FALSE) -> Work | L90: KAMPALA | M90: KAMPALA | N90: UGA | O90: 1 | P90: 1 | Q90: =VLOOKUP(P90,Key!$E$2:$F$9,2,FALSE) -> Home | R90: =K90&"-"&Q90 -> Work-Home | S90: 10 | T90: 2 | U90: 1 | Y90: Y | Z90: 0 | AA90: =VLOOKUP(F90,Zones!$A$2:$F$2186,6,FALSE) -> 1393 | AB90: =VLOOKUP(L90,Zones!$A$2:$F$2186,6,FALSE) -> 521
B91: 0.55416667 | C91: UBA 873J | D91: 2 | E91: 1 | F91: NANGABO | G91: WAKISO | H91: UGA | I91: 1 | J91: 1 | K91: =VLOOKUP(J91,Key!$E$2:$F$9,2,FALSE) -> Home | L91: KAMPALA | M91: KAMPALA | N91: UGA | O91: 2 | P91: 2 | Q91: =VLOOKUP(P91,Key!$E$2:$F$9,2,FALSE) -> Work | R91: =K91&"-"&Q91 -> Home-Work | S91: 11 | T91: 1 | U91: 1 | Y91: Y | Z91: 5000 | AA91: =VLOOKUP(F91,Zones!$A$2:$F$2186,6,FALSE) -> 1393 | AB91: =VLOOKUP(L91,Zones!$A$2:$F$2186,6,FALSE) -> 521
B92: 0.55833333 | C92: UAV 890G | D92: 7 | E92: 5 | F92: NANGABO | G92: WAKISO | H92: UGA | I92: 2 | J92: 2 | K92: =VLOOKUP(J92,Key!$E$2:$F$9,2,FALSE) -> Work | L92: GAYAZA | M92: WAKISO | N92: UGA | O92: 6 | P92: 6 | Q92: =VLOOKUP(P92,Key!$E$2:$F$9,2,FALSE) -> Leisure/Social | R92: =K92&"-"&Q92 -> Work-Leisure/Social | S92: 2 | T92: 0.2 | U92: 1 | Y92: Y | Z92: 5000 | AA92: =VLOOKUP(F92,Zones!$A$2:$F$2186,6,FALSE) -> 1393 | AB92: =VLOOKUP(L92,Zones!$A$2:$F$2186,6,FALSE) -> 811
B93: 0.5625 | C93: UBF 096D | D93: 2 | E93: 1 | F93: KITAGOBWA | G93: WAKISO | H93: UGA | I93: 1 | J93: 1 | K93: =VLOOKUP(J93,Key!$E$2:$F$9,2,FALSE) -> Home | L93: KISASI | M93: WAKISO | N93: UGA | O93: 7 | P93: 4 | Q93: =VLOOKUP(P93,Key!$E$2:$F$9,2,FALSE) -> Commercial | R93: =K93&"-"&Q93 -> Home-Commercial | S93: 5 | T93: 0.2 | U93: 1 | Y93: Y | Z93: 3000 | AA93: =VLOOKUP(F93,Zones!$A$2:$F$2186,6,FALSE) -> 1408 | AB93: =VLOOKUP(L93,Zones!$A$2:$F$2186,6,FALSE) -> 577
B94: 0.56666667 | C94: UAS 295U | D94: 2 | E94: 2 | F94: MATUGGA | G94: WAKISO | H94: UGA | I94: 4 | J94: 3 | K94: =VLOOKUP(J94,Key!$E$2:$F$9,2,FALSE) -> Study | L94: KAMPALA | M94: KAMPALA | N94: UGA | O94: 7 | P94: 4 | Q94: =VLOOKUP(P94,Key!$E$2:$F$9,2,FALSE) -> Commercial | R94: =K94&"-"&Q94 -> Study-Commercial | S94: 6 | T94: 0.3 | U94: 6 | Y94: Y | Z94: 0 | AA94: =VLOOKUP(F94,Zones!$A$2:$F$2186,6,FALSE) -> 1402 | AB94: =VLOOKUP(L94,Zones!$A$2:$F$2186,6,FALSE) -> 521
B95: 0.56944444 | C95: UBC 559A | D95: 1 | E95: 2 | F95: WAKISO TOWN | G95: WAKISO | H95: UGA | I95: 1 | J95: 1 | K95: =VLOOKUP(J95,Key!$E$2:$F$9,2,FALSE) -> Home | L95: KAMPALA | M95: KAMPALA | N95: UGA | O95: 7 | P95: 4 | Q95: =VLOOKUP(P95,Key!$E$2:$F$9,2,FALSE) -> Commercial | R95: =K95&"-"&Q95 -> Home-Commercial | S95: 40 | T95: 1 | U95: 1 | Y95: Y | Z95: 0 | AA95: =VLOOKUP(F95,Zones!$A$2:$F$2186,6,FALSE) -> 1408 | AB95: =VLOOKUP(L95,Zones!$A$2:$F$2186,6,FALSE) -> 521
B96: 0.46666667 | C96: UBA 132R | D96: 2 | E96: 2 | F96: WAKISO TOWN | G96: WAKISO | H96: UGA | I96: 1 | J96: 1 | K96: =VLOOKUP(J96,Key!$E$2:$F$9,2,FALSE) -> Home | L96: KAMPALA | M96: KAMPALA | N96: UGA | O96: 2 | P96: 2 | Q96: =VLOOKUP(P96,Key!$E$2:$F$9,2,FALSE) -> Work | R96: =K96&"-"&Q96 -> Home-Work | S96: 15 | T96: 1 | U96: 1 | Y96: Y | Z96: 2000 | AA96: =VLOOKUP(F96,Zones!$A$2:$F$2186,6,FALSE) -> 1408 | AB96: =VLOOKUP(L96,Zones!$A$2:$F$2186,6,FALSE) -> 521
B97: 0.46736111 | C97: UAY 377L | D97: 1 | E97: 2 | F97: NANGABO | G97: WAKISO | H97: UGA | I97: 1 | J97: 1 | K97: =VLOOKUP(J97,Key!$E$2:$F$9,2,FALSE) -> Home | L97: KAMPALA | M97: KAMPALA | N97: UGA | O97: 2 | P97: 2 | Q97: =VLOOKUP(P97,Key!$E$2:$F$9,2,FALSE) -> Work | R97: =K97&"-"&Q97 -> Home-Work | S97: 17 | T97: 0.7 | U97: 2 | Y97: Y | Z97: 3000 | AA97: =VLOOKUP(F97,Zones!$A$2:$F$2186,6,FALSE) -> 1393 | AB97: =VLOOKUP(L97,Zones!$A$2:$F$2186,6,FALSE) -> 521
B98: 0.42083333 | C98: UAY 082J | D98: 11 | E98: 2 | F98: KAWANGA | G98: WAKISO | H98: UGA | I98: 1 | J98: 1 | K98: =VLOOKUP(J98,Key!$E$2:$F$9,2,FALSE) -> Home | L98: GAYAZA | M98: WAKISO | N98: UGA | O98: 4 | P98: 3 | Q98: =VLOOKUP(P98,Key!$E$2:$F$9,2,FALSE) -> Study | R98: =K98&"-"&Q98 -> Home-Study | S98: 16 | T98: 0.7 | U98: 1 | Y98: Y | Z98: 1000 | AA98: =VLOOKUP(F98,Zones!$A$2:$F$2186,6,FALSE) -> 566 | AB98: =VLOOKUP(L98,Zones!$A$2:$F$2186,6,FALSE) -> 811
B99: 0.42361111 | C99: UAQ 530L | D99: 2 | E99: 1 | F99: KITEGOMBA | G99: WAKISO | H99: UGA | I99: 10 | J99: 2 | K99: =VLOOKUP(J99,Key!$E$2:$F$9,2,FALSE) -> Work | L99: LUTEETE | M99: WAKISO | N99: UGA | O99: 16 | P99: 8 | Q99: =VLOOKUP(P99,Key!$E$2:$F$9,2,FALSE) -> Others | R99: =K99&"-"&Q99 -> Work-Others | S99: 5 | T99: 0.5 | U99: 2 | Y99: Y | Z99: 0 | AA99: =VLOOKUP(F99,Zones!$A$2:$F$2186,6,FALSE) -> 1393 | AB99: =VLOOKUP(L99,Zones!$A$2:$F$2186,6,FALSE) -> 542
B100: 0.42916667 | C100: UAN 428E | D100: 1 | E100: 1 | F100: MASOOLI | G100: WAKISO | H100: UGA | I100: 1 | J100: 1 | K100: =VLOOKUP(J100,Key!$E$2:$F$9,2,FALSE) -> Home | L100: GAYAZA | M100: WAKISO | N100: UGA | O100: 2 | P100: 2 | Q100: =VLOOKUP(P100,Key!$E$2:$F$9,2,FALSE) -> Work | R100: =K100&"-"&Q100 -> Home-Work | S100: 2 | T100: 0.1 | U100: 2 | Y100: Y | Z100: 0 | AA100: =VLOOKUP(F100,Zones!$A$2:$F$2186,6,FALSE) -> 542 | AB100: =VLOOKUP(L100,Zones!$A$2:$F$2186,6,FALSE) -> 811
B101: 0.425 | C101: UAG 305H | D101: 1 | E101: 1 | F101: KULAMBIRO | G101: KAMPALA | H101: UGA | I101: 9 | J101: 2 | K101: =VLOOKUP(J101,Key!$E$2:$F$9,2,FALSE) -> Work | L101: KULAMBIRO | M101: KAMPALA | N101: UGA | O101: 1 | P101: 1 | Q101: =VLOOKUP(P101,Key!$E$2:$F$9,2,FALSE) -> Home | R101: =K101&"-"&Q101 -> Work-Home | S101: 4 | T101: 0.2 | U101: 1 | Y101: Y | Z101: 0 | AA101: =VLOOKUP(F101,Zones!$A$2:$F$2186,6,FALSE) -> 577 | AB101: =VLOOKUP(L101,Zones!$A$2:$F$2186,6,FALSE) -> 577
... B113: 0.43472222 | C113: UAY 793P | D113: 2 | E113: 1 | F113: KITTI | G113: WAKISO | H113: UGA | I113: 1 | J113: 1 | K113: =VLOOKUP(J113,Key!$E$2:$F$9,2,FALSE) -> Home | L113: KAMPALA | M113: KAMPALA | N113: UGA | O113: 2 | P113: 2 | Q113: =VLOOKUP(P113,Key!$E$2:$F$9,2,FALSE) -> Work | R113: =K113&"-"&Q113 -> Home-Work | S113: 23 | T113: 1.5 | U113: 2 | Y113: Y | Z113: 10000 | AA113: =VLOOKUP(F113,Zones!$A$2:$F$2186,6,FALSE) -> 1402 | AB113: =VLOOKUP(L113,Zones!$A$2:$F$2186,6,FALSE) -> 521
...

Sheet Zones
A1: ZONE NAME | B1: DISTRICT | C1: COUNTY | D1: SUBCOUNTY | E1: Parish | F1: ZONE No.
A2: Abim | B2: Abim | C2: Labwor | D2: =A2 -> Abim | F2: 1
A3: Abim Town Council | B3: Abim | C3: Labwor | D3: =A3 -> Abim Town Council | F3: 2
A4: Alerek | B4: Abim | C4: Labwor | D4: =A4 -> Alerek | F4: 3
A5: Lotukei | B5: Abim | C5: Labwor | D5: =A5 -> Lotukei | F5: 4
A6: Morulem | B6: Abim | C6: Labwor | D6: =A6 -> Morulem | F6: 5
A7: Nyakwae | B7: Abim | C7: Labwor | D7: =A7 -> Nyakwae | F7: 6
A8: Adjumani Town Council | B8: Adjumani | C8: East Moyo | D8: =A8 -> Adjumani Town Council | F8: 7
A9: Adropi | B9: Adjumani | C9: East Moyo | D9: =A9 -> Adropi | F9: 8
A10: Arinyapi | B10: Adjumani | C10: East Moyo | D10: =A10 -> Arinyapi | F10: 9
A11: Ciforo | B11: Adjumani | C11: East Moyo | D11: =A11 -> Ciforo | F11: 10
A12: Dzaipi | B12: Adjumani | C12: East Moyo | D12: =A12 -> Dzaipi | F12: 11
A13: Itirikwa | B13: Adjumani | C13: East Moyo | D13: =A13 -> Itirikwa | F13: 12
... A75: Amuru Town Council | B75: Amuru | C75: Kilak | D75: =A75 -> Amuru Town Council | F75: 74
A76: Amur town | D76: =A76 -> Amur town | F76: 74
A77: Attiak | B77: Amuru | C77: Kilak | D77: =A77 -> Attiak | F77: 75
A78: Lamogi | B78: Amuru | C78: Kilak | D78: =A78 -> Lamogi | F78: 76
A79: Pabo | B79: Amuru | C79: Kilak | D79: =A79 -> Pabo | F79: 77
A80: Abongomola | B80: Apac | C80: Kwania | D80: =A80 -> Abongomola | F80: 78
A81: Aduku | B81: Apac | C81: Kwania | D81: =A81 -> Aduku | F81: 79
A82: Aduku Town Council | B82: Apac | C82: Kwania | D82: =A82 -> Aduku Town Council | F82: 80
A83: Akokoro | B83: Apac | C83: Maruzi | D83: =A83 -> Akokoro | F83: 81
A84: Apac Muicipality | B84: Apac | C84: Apac Municipality | D84: =A84 -> Apac Muicipality | F84: 82
A85: Chawente | B85: Apac | C85: Kwania | D85: =A85 -> Chawente | F85: 83
A86: Chegere | B86: Apac | C86: Maruzi | D86: =A86 -> Chegere | F86: 84
A87: Ibuje | B87: Apac | C87: Maruzi | D87: =A87 -> Ibuje | F87: 85
A88: Inomo | B88: Apac | C88: Kwania | D88: =A88 -> Inomo | F88: 86
... A96: Arua Municipality | B96: Arua | C96: Arua Municipality | D96: =A96 -> Arua Municipality | F96: 94
A97: Arua | F97: 94
A98: Ayivuni | B98: Arua | C98: Ayivu | D98: =A98 -> Ayivuni | F98: 95
A99: Bileafe | B99: Arua | C99: Terego | D99: =A99 -> Bileafe | F99: 96
A100: Dadamu | B100: Arua | C100: Ayivu | D100: =A100 -> Dadamu | F100: 97
A101: Ewanga | B101: Arua | C101: Madi Okollo | D101: =A101 -> Ewanga | F101: 98
A102: Katrini | B102: Arua | C102: Terego | D102: =A102 -> Katrini | F102: 99
A103: Logiri | B103: Arua | C103: Vurra | D103: =A103 -> Logiri | F103: 100
A104: Manibe | B104: Arua | C104: Ayivu | D104: =A104 -> Manibe | F104: 101
A105: Odupi | B105: Arua | C105: Terego | D105: =A105 -> Odupi | F105: 102
A106: Offaka | B106: Arua | C106: Madi Okollo | D106: =A106 -> Offaka | F106: 103
A107: Ogoko | B107: Arua | C107: Madi Okollo | D107: =A107 -> Ogoko | F107: 104
A108: Okollo | B108: Arua | C108: Madi Okollo | D108: =A108 -> Okollo | F108: 105
A109: Oluko | B109: Arua | C109: Ayivu | D109: =A109 -> Oluko | F109: 106
... A166: Buikwe | B166: Buikwe | C166: Buikwe | D166: =A166 -> Buikwe | F166: 163
A167: Lweru | F167: 163
A168: Buikwe Town Council | B168: Buikwe | C168: Buikwe | D168: =A168 -> Buikwe Town Council | F168: 164
A169: NAJJEMBA | F169: 164
A170: NAJEMBA | F170: 164
A171: Buyikwe | D171: =A171 -> Buyikwe | F171: 164
A172: BUIKWE TOWN | D172: =A172 -> BUIKWE TOWN | F172: 164
A173: Lugazi Municipality | B173: Buikwe | C173: Lugazi Municipality | D173: =A173 -> Lugazi Municipality | F173: 165
A174: LUGAZI | D174: =A174 -> LUGAZI | F174: 165
A175: Namagunga | D175: =A175 -> Namagunga | F175: 165
A176: Najja | B176: Buikwe | C176: Buikwe | D176: =A176 -> Najja | F176: 166
A177: Ngogwe | B177: Buikwe | C177: Buikwe | D177: =A177 -> Ngogwe | F177: 167
A178: Njeru Municipality | B178: Buikwe | C178: Njeru Municipality | D178: =A178 -> Njeru Municipality | F178: 168
A179: Nkokonjeru Town Council | B179: Buikwe | C179: Buikwe | D179: =A179 -> Nkokonjeru Town Council | F179: 169
A180: Ssi-Bukunja | B180: Buikwe | C180: Buikwe | D180: =A180 -> Ssi-Bukunja | F180: 170
A181: Bukedea | B181: Bukedea | C181: Bukedea | D181: =A181 -> Bukedea | F181: 171
A182: Bukedea Town Council | B182: Bukedea | C182: Bukedea | D182: =A182 -> Bukedea Town Council | F182: 172
A183: Kachumbala | B183: Bukedea | C183: Bukedea | D183: =A183 -> Kachumbala | F183: 173
A184: Kidongole | B184: Bukedea | C184: Bukedea | D184: =A184 -> Kidongole | F184: 174
A185: Kolir | B185: Bukedea | C185: Bukedea | D185: =A185 -> Kolir | F185: 175
A186: Malera | B186: Bukedea | C186: Bukedea | D186: =A186 -> Malera | F186: 176
A187: Bigasa | B187: Bukomansimbi | C187: Bukomansimbi | D187: =A187 -> Bigasa | F187: 177
... A263: Bushenyi-Ishaka Municipality | B263: Bushenyi | C263: Bushenyi-Ishaka Municipality | D263: =A263 -> Bushenyi-Ishaka Municipality | F263: 253
A264: BUSHENYI | D264: =A264 -> BUSHENYI | F264: 253
A265: Munyonyi | F265: 253
A266: Ibaare | B266: Bushenyi | C266: Igara | D266: =A266 -> Ibaare | F266: 254
A267: Kakanju | B267: Bushenyi | C267: Igara | D267: =A267 -> Kakanju | F267: 255
A268: Kyabugimbi | B268: Bushenyi | C268: Igara | D268: =A268 -> Kyabugimbi | F268: 256
A269: Kyamuhunga | B269: Bushenyi | C269: Igara | D269: =A269 -> Kyamuhunga | F269: 257
A270: Kyamuhunga Town Council | B270: Bushenyi | C270: Igara | D270: =A270 -> Kyamuhunga Town Council | F270: 258
A271: Kyeizooba | B271: Bushenyi | C271: Igara | D271: =A271 -> Kyeizooba | F271: 259
A272: Nyabubare | B272: Bushenyi | C272: Igara | D272: =A272 -> Nyabubare | F272: 260
A273: Ruhumuro | B273: Bushenyi | C273: Igara | D273: =A273 -> Ruhumuro | F273: 261
A274: Buhehe | B274: Busia | C274: Samia-Bugwe | D274: =A274 -> Buhehe | F274: 262
A275: Bulumbi | B275: Busia | C275: Samia-Bugwe | D275: =A275 -> Bulumbi | F275: 263
A276: Busia Municipality | B276: Busia | C276: Busia Municipality | D276: =A276 -> Busia Municipality | F276: 264
A277: Busia town | D277: =A277 -> Busia town | F277: 264
A278: Busime | B278: Busia | C278: Samia-Bugwe | D278: =A278 -> Busime | F278: 265
A279: Busitema | B279: Busia | C279: Samia-Bugwe | D279: =A279 -> Busitema | F279: 266
A280: Buteba | B280: Busia | C280: Samia-Bugwe | D280: =A280 -> Buteba | F280: 267
A281: Buyanga-Busia | B281: Busia | C281: Samia-Bugwe | D281: =A281 -> Buyanga-Busia | F281: 268
A282: Dabani | B282: Busia | C282: Samia-Bugwe | D282: =A282 -> Dabani | F282: 269
A283: Lumino | B283: Busia | C283: Samia-Bugwe | D283: =A283 -> Lumino | F283: 270
A284: Lunyo | B284: Busia | C284: Samia-Bugwe | D284: =A284 -> Lunyo | F284: 271
A285: Majanji | B285: Busia | C285: Samia-Bugwe | D285: =A285 -> Majanji | F285: 272
A286: Masaba-Busia | B286: Busia | C286: Samia-Bugwe | D286: =A286 -> Masaba-Busia | F286: 273
A287: Masafu | B287: Busia | C287: Samia-Bugwe | D287: =A287 -> Masafu | F287: 274
A288: Masinya | B288: Busia | C288: Samia-Bugwe | D288: =A288 -> Masinya | F288: 275
A289: Sikuda | B289: Busia | C289: Samia-Bugwe | D289: =A289 -> Sikuda | F289: 276
... A312: Kibale | B312: Butebo | C312: Butebo Town Council | D312: =A312 -> Kibale | F312: 299
A313: Kibale town | D313: =A313 -> Kibale town | F313: 299
A314: KIBALE | D314: =A314 -> KIBALE | F314: 299
A315: Opwateta | B315: Butebo | C315: Butebo Town Council | D315: =A315 -> Opwateta | F315: 300
A316: Petete | B316: Butebo | C316: Butebo Town Council | D316: =A316 -> Petete | F316: 301
A317: Bugaya-Buvuma | B317: Buvuma | C317: Buvuma Island | D317: =A317 -> Bugaya-Buvuma | F317: 302
A318: Busamuzi | B318: Buvuma | C318: Buvuma Island | D318: =A318 -> Busamuzi | F318: 303
A319: Buvuma Town Council | B319: Buvuma | C319: Buvuma Island | D319: =A319 -> Buvuma Town Council | F319: 304
A320: Buwooya | B320: Buvuma | C320: Buvuma Island | D320: =A320 -> Buwooya | F320: 305
A321: Bweema | B321: Buvuma | C321: Buvuma Island | D321: =A321 -> Bweema | F321: 306
...

Sheet Zone analysis
A1: Zone | B1: District | C1: County | D1: Subcounty | E1: Parish | F1: DRAFT FINAL ZONE LIST | G1: DISTRICT | H1: Subcounty
A2: 243 | B2: Alebtong | C2: Moroto | D2: Abako | F2: =D2 -> Abako | G2: =B2 -> Alebtong | H2: Abako
A3: 295 | B3: Zombo | C3: Okoro | D3: Abanga | F3: =D3 -> Abanga | G3: =B3 -> Zombo | H3: Abanga
A4: 886 | B4: Amuria | C4: Amuria | D4: Abarilela | F4: =D4 -> Abarilela | G4: =B4 -> Amuria | H4: Abarilela
A5: 215 | B5: Oyam | C5: Oyam | D5: Aber | F5: =D5 -> Aber | G5: =B5 -> Oyam | H5: Aber
A6: 244 | B6: Alebtong | C6: Moroto | D6: Abia | F6: =D6 -> Abia | G6: =B6 -> Alebtong | H6: Abia
A7: 151 | B7: Abim | C7: Labwor | D7: Abim | F7: =D7 -> Abim | G7: =B7 -> Abim | H7: Abim
A8: 152 | B8: Abim | C8: Labwor | D8: Abim Town Council | F8: =D8 -> Abim Town Council | G8: =B8 -> Abim | H8: Abim Town Council
A9: 107 | B9: Nebbi | C9: Nebbi Municipality | D9: Abindu Division | F9: =VLOOKUP(C9,[2]Municipalities!$C$9:$F$1522,4,FALSE) -> Nebbi Municipality | G9: =B9 -> Nebbi | H9: Abindu Division
A10: 216 | B10: Oyam | C10: Oyam | D10: Abok | F10: =D10 -> Abok | G10: =B10 -> Oyam | H10: Abok
A11: 256 | B11: Kole | C11: Kole | D11: Aboke | F11: =D11 -> Aboke | G11: =B11 -> Kole | H11: Aboke
A12: 11 | B12: Apac | C12: Kwania | D12: Abongomola | F12: =D12 -> Abongomola | G12: =B12 -> Apac | H12: Abongomola
A13: 198 | B13: Koboko | C13: Koboko | D13: Abuku | F13: =D13 -> Abuku | G13: =B13 -> Koboko | H13: Abuku
A14: 217 | B14: Oyam | C14: Oyam | D14: Acaba | F14: =D14 -> Acaba | G14: =B14 -> Oyam | H14: Acaba
A15: 126 | B15: Pader | C15: Aruu | D15: Acholibur | F15: =D15 -> Acholibur | G15: =B15 -> Pader | H15: Acholibur
A16: 897 | B16: Amuria | C16: Kapelebyong | D16: Acowa | F16: =D16 -> Acowa | G16: =B16 -> Amuria | H16: Acowa
A17: 173 | B17: Dokolo | C17: Dokolo | D17: Adeknino | F17: =D17 -> Adeknino | G17: =B17 -> Dokolo | H17: Adeknino
A18: 79 | B18: Lira | C18: Erute | D18: Adekokwok | F18: =D18 -> Adekokwok | G18: =B18 -> Lira | H18: Adekokwok
A19: 227 | B19: Agago | C19: Agago | D19: Adilang | F19: =D19 -> Adilang | G19: =B19 -> Agago | H19: Adilang
A20: 1 | B20: Adjumani | C20: East Moyo | D20: Adjumani Town Council | F20: =D20 -> Adjumani Town Council | G20: =B20 -> Adjumani | H20: Adjumani Town Council
A21: 174 | B21: Dokolo | C21: Dokolo | D21: Adok | F21: =D21 -> Adok | G21: =B21 -> Dokolo | H21: Adok
... A26: 287 | B26: Otuke | C26: Otuke | D26: Adwari | F26: =D26 -> Adwari | G26: =B26 -> Otuke | H26: Adwari
A27: 88 | B27: Lira | C27: Lira Municipality | D27: Adyel Division | F27: =VLOOKUP(C27,[2]Municipalities!$C$9:$F$1522,4,FALSE) -> Lira Municipality | G27: =B27 -> Lira | H27: Adyel Division
A28: 228 | B28: Agago | C28: Agago | D28: Agago Town Council | F28: =D28 -> Agago Town Council | G28: =B28 -> Agago | H28: Agago Town Council
A29: 80 | B29: Lira | C29: Erute | D29: Agali | F29: =D29 -> Agali | G29: =B29 -> Lira | H29: Agali
A30: 157 | B30: Amolatar | C30: Kioga | D30: Agikdak | F30: =D30 -> Agikdak | G30: =B30 -> Amolatar | H30: Agikdak
A31: 263 | B31: Lamwo | C31: Lamwo | D31: Agoro | F31: =D31 -> Agoro | G31: =B31 -> Lamwo | H31: Agoro
A32: 802 | B32: Pallisa | C32: Agule | D32: Agule | F32: =D32 -> Agule | G32: =B32 -> Pallisa | H32: Agule
A33: 175 | B33: Dokolo | C33: Dokolo | D33: Agwata | F33: =D33 -> Agwata | G33: =B33 -> Dokolo | H33: Agwata
A34: 81 | B34: Lira | C34: Erute | D34: Agweng | F34: =D34 -> Agweng | G34: =B34 -> Lira | H34: Agweng
A35: 158 | B35: Amolatar | C35: Kioga | D35: Agwingiri | F35: =D35 -> Agwingiri | G35: =B35 -> Amolatar | H35: Agwingiri
A36: 40 | B36: Arua | C36: Terego | D36: Aii-Vu | F36: =D36 -> Aii-Vu | G36: =B36 -> Arua | H36: Aii-Vu
A37: 46 | B37: Arua | C37: Vurra | D37: Ajia | F37: =D37 -> Ajia | G37: =B37 -> Arua | H37: Ajia
A38: 257 | B38: Kole | C38: Kole | D38: Akalo | F38: =D38 -> Akalo | G38: =B38 -> Kole | H38: Akalo
A39: 887 | B39: Amuria | C39: Amuria | D39: Akeriau | F39: =D39 -> Akeriau | G39: =B39 -> Amuria | H39: Akeriau
... A70: 31 | B70: Arua | C70: Madi Okollo | D70: Anyiribu | F70: =D70 -> Anyiribu | G70: =B70 -> Arua | H70: Anyiribu
A71: 20 | B71: Apac | C71: Apac Municipality | D71: Apac | F71: =VLOOKUP(C71,[2]Municipalities!$C$9:$F$1522,4,FALSE) -> Apac Muicipality | G71: =B71 -> Apac | H71: Apac
A72: 21 | B72: Apac | C72: Apac Municipality | D72: Apac Town Council | F72: =VLOOKUP(C72,[2]Municipalities!$C$9:$F$1522,4,FALSE) -> Apac Muicipality | G72: =B72 -> Apac | H72: Apac Town Council
A73: 249 | B73: Alebtong | C73: Moroto | D73: Apala | F73: =D73 -> Apala | G73: =B73 -> Alebtong | H73: Apala
A74: 846 | B74: Kaberamaido | C74: Kalaki | D74: Apapai | F74: =D74 -> Apapai | G74: =B74 -> Kaberamaido | H74: Apapai
A75: 889 | B75: Amuria | C75: Amuria | D75: Apeduru | F75: =D75 -> Apeduru | G75: =B75 -> Amuria | H75: Apeduru
A76: 840 | B76: Kaberamaido | C76: Kaberamaido | D76: Aperkira | F76: =D76 -> Aperkira | G76: =B76 -> Kaberamaido | H76: Aperkira
A77: 138 | B77: Yumbe | C77: Aringa | D77: Apo | F77: =D77 -> Apo | G77: =B77 -> Yumbe | H77: Apo
A78: 804 | B78: Pallisa | C78: Agule | D78: Apopong | F78: =D78 -> Apopong | G78: =B78 -> Pallisa | H78: Apopong
A79: 161 | B79: Amolatar | C79: Kioga | D79: Aputi | F79: =D79 -> Aputi | G79: =B79 -> Amolatar | H79: Aputi
A80: 813 | B80: Soroti | C80: Soroti | D80: Arapai | F80: =D80 -> Arapai | G80: =B80 -> Soroti | H80: Arapai
A81: 3 | B81: Adjumani | C81: East Moyo | D81: Arinyapi | F81: =D81 -> Arinyapi | G81: =B81 -> Adjumani | H81: Arinyapi
A82: 47 | B82: Arua | C82: Vurra | D82: Arivu | F82: =D82 -> Arivu | G82: =B82 -> Arua | H82: Arivu
A83: 139 | B83: Yumbe | C83: Aringa | D83: Ariwa | F83: =D83 -> Ariwa | G83: =B83 -> Yumbe | H83: Ariwa
A84: 25 | B84: Arua | C84: Ayivu | D84: Aroi | F84: =D84 -> Aroi | G84: =B84 -> Arua | H84: Aroi
A85: 83 | B85: Lira | C85: Erute | D85: Aromo | F85: =D85 -> Aromo | G85: =B85 -> Lira | H85: Aromo
A86: 22 | B86: Arua | C86: Arua Municipality | D86: Arua Hill Division | F86: =VLOOKUP(C86,[2]Municipalities!$C$9:$F$1522,4,FALSE) -> Arua Municipality | G86: =B86 -> Arua | H86: Arua Hill Division
A87: 229 | B87: Agago | C87: Agago | D87: Arum | F87: =D87 -> Arum | G87: =B87 -> Agago | H87: Arum
A88: 162 | B88: Amolatar | C88: Kioga | D88: Arwotcek | F88: =D88 -> Arwotcek | G88: =B88 -> Amolatar | H88: Arwotcek
A89: 890 | B89: Amuria | C89: Amuria | D89: Asamuk | F89: =D89 -> Asamuk | G89: =B89 -> Amuria | H89: Asamuk
A90: 810 | B90: Soroti | C90: Soroti | D90: Asuret | F90: =D90 -> Asuret | G90: =B90 -> Soroti | H90: Asuret
A91: 128 | B91: Pader | C91: Aruu | D91: Atanga | F91: =D91 -> Atanga | G91: =B91 -> Pader | H91: Atanga
A92: 111 | B92: Nebbi | C92: Padyere | D92: Atego | F92: =D92 -> Atego | G92: =B92 -> Nebbi | H92: Atego
A93: 1073 | B93: Serere | C93: Serere | D93: Atiira | F93: =D93 -> Atiira | G93: =B93 -> Serere | H93: Atiira
A94: 170 | B94: Amuru | C94: Kilak | D94: Attiak | F94: =D94 -> Attiak | G94: =B94 -> Amuru | H94: Attiak
A95: 763 | B95: Kumi | C95: Kumi | D95: Atutur | F95: =D95 -> Atutur | G95: =B95 -> Kumi | H95: Atutur
A96: 296 | B96: Zombo | C96: Okoro | D96: Atyak | F96: =D96 -> Atyak | G96: =B96 -> Zombo | H96: Atyak
A97: 50 | B97: Gulu | C97: Aswa | D97: Awach | F97: =D97 -> Awach | G97: =B97 -> Gulu | H97: Awach
A98: 250 | B98: Alebtong | C98: Moroto | D98: Awei | F98: =D98 -> Awei | G98: =B98 -> Alebtong | H98: Awei
... A109: 1054 | B109: Namayingo | C109: Bukooli | D109: Banda | F109: =D109 -> Banda | G109: =B109 -> Namayingo | H109: Banda
A110: 54 | B110: Gulu | C110: Gulu Municipality | D110: Bar Dege Division | F110: =VLOOKUP(C110,[2]Municipalities!$C$9:$F$1522,4,FALSE) -> Gulu Municipality | G110: =B110 -> Gulu | H110: Bar Dege Division
A111: 84 | B111: Lira | C111: Erute | D111: Barr | F111: =D111 -> Barr | G111: =B111 -> Lira | H111: Barr
A112: 177 | B112: Dokolo | C112: Dokolo | D112: Batta | F112: =D112 -> Batta | G112: =B112 -> Dokolo | H112: Batta
A113: 523 | B113: Kayunga | C113: Bbaale | D113: Bbaale | F113: =D113 -> Bbaale | G113: =B113 -> Kayunga | H113: Bbaale
A114: 565 | B114: Mityana | C114: Busujju | D114: Bbanda | F114: =D114 -> Bbanda | G114: =B114 -> Mityana | H114: Bbanda
A115: 1034 | B115: Kween | C115: Kween | D115: Benet | F115: =D115 -> Benet | G115: =B115 -> Kween | H115: Benet
A116: 606 | B116: Bukomansimbi | C116: Bukomansimbi | D116: Bigasa | F116: =D116 -> Bigasa | G116: =B116 -> Bukomansimbi | H116: Bigasa
A117: 1297 | B117: Kamwenge | C117: Kibale | D117: Biguli | F117: =D117 -> Biguli | G117: =B117 -> Kamwenge | H117: Biguli
A118: 1304 | B118: Kamwenge | C118: Kibale | D118: Bihanga | F118: =D118&"-"&B118 -> Bihanga-Kamwenge | G118: =B118 -> Kamwenge | H118: Bihanga
A119: 1405 | B119: Buhweju | C119: Buhweju | D119: Bihanga | F119: =D119&"-"&B119 -> Bihanga-Buhweju | G119: =B119 -> Buhweju | H119: Bihanga
A120: 1254 | B120: Mbarara | C120: Mbarara Municipality | D120: Biharwe Division | F120: =VLOOKUP(C120,[2]Municipalities!$C$9:$F$1522,4,FALSE) -> Mbarara Municipality | G120: =B120 -> Mbarara | H120: Biharwe Division
A121: 1346 | B121: Buliisa | C121: Buliisa | D121: Biiso | F121: =D121 -> Biiso | G121: =B121 -> Buliisa | H121: Biiso
A122: 41 | B122: Arua | C122: Terego | D122: Bileafe | F122: =D122 -> Bileafe | G122: =B122 -> Arua | H122: Bileafe
A123: 1035 | B123: Kween | C123: Kween | D123: Binyiny | F123: =D123 -> Binyiny | G123: =B123 -> Kween | H123: Binyiny
A124: 1036 | B124: Kween | C124: Kween | D124: Binyiny Town Council | F124: =D124 -> Binyiny Town Council | G124: =B124 -> Kween | H124: Binyiny Town Council
A125: 1495 | B125: Kakumiro | C125: Bugangaizi | D125: Birembo | F125: =D125 -> Birembo | G125: =B125 -> Kakumiro | H125: Birembo
A126: 1375 | B126: Isingiro | C126: Isingiro | D126: Birere | F126: =D126 -> Birere | G126: =B126 -> Isingiro | H126: Birere
A127: 1363 | B127: Ibanda | C127: Ibanda Municipality | D127: Bisheshe Division | F127: =VLOOKUP(C127,[2]Municipalities!$C$9:$F$1522,4,FALSE) -> Ibanda Municipality | G127: =B127 -> Ibanda | H127: Bisheshe Division
A128: 1430 | B128: Mitooma | C128: Ruhinda | D128: Bitereko | F128: =D128 -> Bitereko | G128: =B128 -> Mitooma | H128: Bitereko
A129: 1125 | B129: Bushenyi | C129: Igara | D129: Bitooma | F129: =D129 -> Bitooma | G129: =B129 -> Bushenyi | H129: Bitooma
A130: 1406 | B130: Buhweju | C130: Buhweju | D130: Bitsya | F130: =D130 -> Bitsya | G130: =B130 -> Buhweju | H130: Bitsya
A131: 305 | B131: Omoro | C131: Omoro | D131: Bobi | F131: =D131 -> Bobi | G131: =B131 -> Omoro | H131: Bobi
A132: 434 | B132: Luwero | C132: Katikamu | D132: Bombo Town Council | F132: =D132 -> Bombo Town Council | G132: =B132 -> Luwero | H132: Bombo Town Council
A133: 1244 | B133: Mbarara | C133: Kashari | D133: Bubaare | F133: =D133&"-"&B133 -> Bubaare-Mbarara | G133: =B133 -> Mbarara | H133: Bubaare
A134: 1506 | B134: Rubanda | C134: Rubanda | D134: Bubaare | F134: =D134&"-"&B134 -> Bubaare-Rubanda | G134: =B134 -> Rubanda | H134: Bubaare
A135: 1112 | B135: Bundibugyo | C135: Bwamba | D135: Bubandi | F135: =D135 -> Bubandi | G135: =B135 -> Bundibugyo | H135: Bubandi
A136: 1208 | B136: Kibaale | C136: Buyanja | D136: Bubango | F136: =D136 -> Bubango | G136: =B136 -> Kibaale | H136: Bubango
A137: 321 | B137: Kalangala | C137: Kyamuswa | D137: Bubeke | F137: =D137 -> Bubeke | G137: =B137 -> Kalangala | H137: Bubeke
A138: 915 | B138: Bududa | C138: Manjiya | D138: Bubiita | F138: =D138 -> Bubiita | G138: =B138 -> Bududa | H138: Bubiita
A139: 1113 | B139: Bundibugyo | C139: Bwamba | D139: Bubukwanga | F139: =D139 -> Bubukwanga | G139: =B139 -> Bundibugyo | H139: Bubukwanga
A140: 1085 | B140: Namisindwa | C140: Namisindwa | D140: Bubutu | F140: =D140 -> Bubutu | G140: =B140 -> Namisindwa | H140: Bubutu
A141: 771 | B141: Mbale | C141: Bungokho | D141: Bubyangu | F141: =D141 -> Bubyangu | G141: =B141 -> Mbale | H141: Bubyangu
A142: 865 | B142: Sironko | C142: Budadiri | D142: Budadiri Town Council | F142: =D142 -> Budadiri Town Council | G142: =B142 -> Sironko | H142: Budadiri Town Council
A143: 902 | B143: Budaka | C143: Budaka | D143: Budaka | F143: =D143 -> Budaka | G143: =B143 -> Budaka | H143: Budaka
A144: 903 | B144: Budaka | C144: Budaka | D144: Budaka Town Council | F144: =D144 -> Budaka Town Council | G144: =B144 -> Budaka | H144: Budaka Town Council
...

Sheet 12.10 MATUGGA-KASANGATTI
B1: Consultancy services for Preparation of Expressway Develo PMent Master Plan (EDMP) for Uganda
B2: Roadside OD Interview Survey
B4: Date: | C4: 12.10.19 | E4: Road Name: | F4: ='14.10 KASANGATI-MATUGGA'!F4:G4 -> MATUGGA-WAKISO ROAD | I4: Direction From: | L4: MATUGGA | N4: Interviewers: | O4: SHAMIRAH, JULIUS | V4: Supervisor: | W4: STEVEN | Y4: Coded By: | Z4: ='14.10 KASANGATI-MATUGGA'!Z4 -> DAVID | AA4: Chkd By: | AB4: Bakole Deo
I5: Direction To: | L5: KASANGATTI
B7: Time | C7: Veh_Reg_No. | D7: Veh_Type | E7: No. Occupants | F7: Origin_Address | I7: Origin_Establish | J7: Origin_Purpose | K7: Origin-Purpose Desc | L7: Destination_Address | O7: Destination_Establish | P7: Destination_Purpose | Q7: Destination_Purpose Desc | R7: Journey_Purpose | S7: Approx_Distance (Km) | T7: Approx_Journey Time (Hrs) | U7: Trip_Frequency | V7: GOODS VEHICLES ONLY | Y7: Would You Use Xpressways? | Z7: Pay How Much? (UGX) | AA7: Origin_Zone | AB7: Dest_Zone
F8: Village or Town | G8: District | H8: Country | L8: Village or Town | M8: District | N8: Country | V8: Goods_Type | W8: Goods_Quantity (Ton) | X8: Goods_Value (UGXm)
B9: 0.67152778 | C9: UAP 387B | D9: 8 | E9: 1 | F9: MAGORA | G9: WAKISO | H9: UGA | I9: 9 | J9: 1 | K9: =VLOOKUP(J9,Key!$E$2:$F$9,2,FALSE) -> Home | L9: KASANGATTI | M9: WAKISO | N9: UGA | O9: 1 | P9: 1 | Q9: =VLOOKUP(P9,Key!$E$2:$F$9,2,FALSE) -> Home | R9: =K9&"-"&Q9 -> Home-Home | U9: 1 | V9: 11 | Y9: Y | Z9: 3000
B10: 0.67291667 | C10: UAN 185N | D10: 1 | E10: 2 | F10: MABUSU | G10: WAKISO | H10: UGA | I10: 7 | J10: 1 | K10: =VLOOKUP(J10,Key!$E$2:$F$9,2,FALSE) -> Home | L10: BUKOTO | M10: KAMPALA | N10: UGA | O10: 1 | P10: 1 | Q10: =VLOOKUP(P10,Key!$E$2:$F$9,2,FALSE) -> Home | R10: =K10&"-"&Q10 -> Home-Home | S10: 3 | U10: 1 | Y10: Y | Z10: 3500
B11: 0.62222222 | C11: UAK 338U | D11: 1 | E11: 5 | F11: KITI | G11: WAKISO | H11: UGA | I11: 1 | J11: 3 | K11: =VLOOKUP(J11,Key!$E$2:$F$9,2,FALSE) -> Study | L11: KIIRA | M11: WAKISO | N11: UGA | O11: 4 | P11: 3 | Q11: =VLOOKUP(P11,Key!$E$2:$F$9,2,FALSE) -> Study | R11: =K11&"-"&Q11 -> Study-Study | T11: 0.1 | U11: 1 | Y11: Y | Z11: 3500
B12: 0.625 | C12: UBE 33Q | D12: 1 | E12: 4 | F12: MATUGGA | G12: WAKISO | H12: UGA | I12: 1 | J12: 8 | K12: =VLOOKUP(J12,Key!$E$2:$F$9,2,FALSE) -> Others | L12: MULAGO | M12: KAMPALA | N12: UGA | O12: 4 | P12: 8 | Q12: =VLOOKUP(P12,Key!$E$2:$F$9,2,FALSE) -> Others | R12: =K12&"-"&Q12 -> Others-Others | S12: 7 | T12: 0.2 | U12: 5 | Y12: Y | Z12: 1000
B13: 0.62986111 | C13: UAL 290P | D13: 1 | E13: 2 | F13: MUGABO | G13: WAKISO | H13: UGA | I13: 1 | J13: 2 | K13: =VLOOKUP(J13,Key!$E$2:$F$9,2,FALSE) -> Work | L13: KASANGATTI | M13: WAKISO | N13: UGA | O13: 7 | P13: 4 | Q13: =VLOOKUP(P13,Key!$E$2:$F$9,2,FALSE) -> Commercial | R13: =K13&"-"&Q13 -> Work-Commercial | T13: 0.1 | U13: 1 | Y13: Y | Z13: 400
B14: 0.62777778 | C14: UBB 241W | D14: 1 | E14: 1 | F14: KITI | G14: WAKISO | H14: UGA | I14: 1 | J14: 7 | K14: =VLOOKUP(J14,Key!$E$2:$F$9,2,FALSE) -> Hospital | L14: GAYAZA | M14: WAKISO | N14: UGA | O14: 5 | P14: 7 | Q14: =VLOOKUP(P14,Key!$E$2:$F$9,2,FALSE) -> Hospital | R14: =K14&"-"&Q14 -> Hospital-Hospital | S14: 5 | T14: 0.1 | U14: 1 | Y14: Y | Z14: 5000
B15: 0.65833333 | C15: UBE 794R | D15: 1 | E15: 3 | F15: KITI | G15: WAKISO | H15: UGA | I15: 1 | J15: 1 | K15: =VLOOKUP(J15,Key!$E$2:$F$9,2,FALSE) -> Home | L15: KASANGATTI | M15: WAKISO | N15: UGA | O15: 5 | P15: 7 | Q15: =VLOOKUP(P15,Key!$E$2:$F$9,2,FALSE) -> Hospital | R15: =K15&"-"&Q15 -> Home-Hospital | S15: 2 | T15: 0.1 | U15: 6 | Y15: Y | Z15: 500
B16: 0.66319444 | C16: UBA 121B | D16: 3 | E16: 2 | F16: WAGABO | G16: WAKISO | H16: UGA | I16: 1 | J16: 6 | K16: =VLOOKUP(J16,Key!$E$2:$F$9,2,FALSE) -> Leisure/Social | L16: KASANGATTI | M16: WAKISO | N16: UGA | O16: 7 | P16: 6 | Q16: =VLOOKUP(P16,Key!$E$2:$F$9,2,FALSE) -> Leisure/Social | R16: =K16&"-"&Q16 -> Leisure/Social-Leisure/Social | S16: 0.5 | T16: 0.1 | U16: 1 | Y16: Y | Z16: 1000
B17: 0.61458333 | C17: UAY 217M | D17: 1 | E17: 2 | F17: MATUGGA | G17: WAKISO | H17: UGA | I17: 1 | J17: 6 | K17: =VLOOKUP(J17,Key!$E$2:$F$9,2,FALSE) -> Leisure/Social | L17: GAYAZA | M17: WAKISO | N17: UGA | O17: 1 | P17: 6 | Q17: =VLOOKUP(P17,Key!$E$2:$F$9,2,FALSE) -> Leisure/Social | R17: =K17&"-"&Q17 -> Leisure/Social-Leisure/Social | S17: 7 | T17: 0.1 | U17: 1 | Y17: Y | Z17: 1000
B18: 0.61180556 | C18: UAZ 061X | D18: 1 | E18: 6 | F18: MAWULAR | G18: WAKISO | H18: UGA | I18: 1 | J18: 6 | K18: =VLOOKUP(J18,Key!$E$2:$F$9,2,FALSE) -> Leisure/Social | L18: STAGAZA | M18: WAKISO | N18: UGA | O18: 1 | P18: 6 | Q18: =VLOOKUP(P18,Key!$E$2:$F$9,2,FALSE) -> Leisure/Social | R18: =K18&"-"&Q18 -> Leisure/Social-Leisure/Social | S18: 3 | T18: 0.1 | U18: 1 | Y18: Y | Z18: 200
B19: 0.64097222 | C19: UBA 239X | D19: 1 | E19: 2 | F19: NANGABO | G19: WAKISO | H19: UGA | I19: 1 | J19: 6 | K19: =VLOOKUP(J19,Key!$E$2:$F$9,2,FALSE) -> Leisure/Social | L19: KASANGATTI | M19: WAKISO | N19: UGA | O19: 7 | P19: 6 | Q19: =VLOOKUP(P19,Key!$E$2:$F$9,2,FALSE) -> Leisure/Social | R19: =K19&"-"&Q19 -> Leisure/Social-Leisure/Social | S19: 0.5 | T19: 0.1 | U19: 6 | Y19: Y | Z19: 2000
B20: 0.6375 | C20: UBE 072G | D20: 1 | E20: 5 | F20: MAKULO | G20: WAKISO | H20: UGA | I20: 1 | J20: 5 | K20: =VLOOKUP(J20,Key!$E$2:$F$9,2,FALSE) -> Tourism | L20: KASANGATTI | M20: WAKISO | N20: UGA | O20: 1 | P20: 1 | Q20: =VLOOKUP(P20,Key!$E$2:$F$9,2,FALSE) -> Home | R20: =K20&"-"&Q20 -> Tourism-Home | T20: 0.1 | U20: 1 | Y20: Y | Z20: 500
B21: 0.61944444 | C21: UAM 669D | D21: 1 | E21: 4 | F21: NANGABO | G21: WAKISO | H21: UGA | I21: 1 | J21: 1 | K21: =VLOOKUP(J21,Key!$E$2:$F$9,2,FALSE) -> Home | L21: MULAGO | M21: KAMPALA | N21: UGA | O21: 1 | P21: 1 | Q21: =VLOOKUP(P21,Key!$E$2:$F$9,2,FALSE) -> Home | R21: =K21&"-"&Q21 -> Home-Home | S21: 2 | T21: 0.1 | U21: 1 | Y21: Y | Z21: 3000
B22: 0.61666667 | C22: UBA 695R | D22: 2 | E22: 2 | F22: NANGABO | G22: WAKISO | H22: UGA | I22: 1 | J22: 2 | K22: =VLOOKUP(J22,Key!$E$2:$F$9,2,FALSE) -> Work | L22: KAMPALA | M22: KAMPALA | N22: UGA | O22: 2 | P22: 2 | Q22: =VLOOKUP(P22,Key!$E$2:$F$9,2,FALSE) -> Work | R22: =K22&"-"&Q22 -> Work-Work | S22: 1.5 | T22: 0.1 | U22: 1 | Y22: Y | Z22: 5000
B23: 0.42986111 | C23: UAR 383B | D23: 1 | E23: 2 | F23: MASAACHI | G23: WAKISO | H23: UGA | I23: 1 | J23: 2 | K23: =VLOOKUP(J23,Key!$E$2:$F$9,2,FALSE) -> Work | L23: KASANGATTI | M23: WAKISO | N23: UGA | O23: 3 | P23: 2 | Q23: =VLOOKUP(P23,Key!$E$2:$F$9,2,FALSE) -> Work | R23: =K23&"-"&Q23 -> Work-Work | S23: 1 | T23: 0.1 | U23: 1 | Y23: Y | Z23: 1000
B24: 0.43125 | C24: UAP 465T | D24: 1 | E24: 6 | F24: NAMALOLO | G24: WAKISO | H24: UGA | I24: 1 | J24: 6 | K24: =VLOOKUP(J24,Key!$E$2:$F$9,2,FALSE) -> Leisure/Social | L24: NATEETE | M24: KAMPALA | N24: UGA | O24: 1 | P24: 1 | Q24: =VLOOKUP(P24,Key!$E$2:$F$9,2,FALSE) -> Home | R24: =K24&"-"&Q24 -> Leisure/Social-Home | S24: 10 | T24: 0.3 | U24: 1 | Y24: Y | Z24: 1000
B25: 0.58333333 | C25: UBE 012B | D25: 2 | E25: 3 | F25: MPERERWE | G25: KAMPALA | H25: UGA | I25: 3 | J25: 4 | K25: =VLOOKUP(J25,Key!$E$2:$F$9,2,FALSE) -> Commercial | L25: GAYAZA | M25: WAKISO | N25: UGA | O25: 4 | P25: 4 | Q25: =VLOOKUP(P25,Key!$E$2:$F$9,2,FALSE) -> Commercial | R25: =K25&"-"&Q25 -> Commercial-Commercial | T25: 0.1 | U25: 1 | V25: 4 | W25: 1.5 | X25: 2 | Y25: Y | Z25: 2500
B26: 0.83194444 | C26: UAG 516K | D26: 1 | E26: 2 | F26: KITAGOBWA | G26: WAKISO | H26: UGA | I26: 1 | J26: 1 | K26: =VLOOKUP(J26,Key!$E$2:$F$9,2,FALSE) -> Home | L26: KAMPALA | M26: KAMPALA | N26: UGA | O26: 5 | P26: 7 | Q26: =VLOOKUP(P26,Key!$E$2:$F$9,2,FALSE) -> Hospital | R26: =K26&"-"&Q26 -> Home-Hospital | S26: 3 | T26: 0.1 | U26: 1 | Y26: Y | Z26: 3000
B27: 0.43402778 | C27: UAW 117W | D27: 1 | E27: 3 | F27: MASOOLI | G27: WAKISO | H27: UGA | I27: 1 | J27: 1 | K27: =VLOOKUP(J27,Key!$E$2:$F$9,2,FALSE) -> Home | L27: KAMPALA | M27: KAMPALA | N27: UGA | O27: 5 | P27: 7 | Q27: =VLOOKUP(P27,Key!$E$2:$F$9,2,FALSE) -> Hospital | R27: =K27&"-"&Q27 -> Home-Hospital | S27: 1.5 | T27: 0.1 | U27: 1 | Y27: Y | Z27: 2000
B28: 0.44027778 | C28: UAH 787V | D28: 2 | E28: 1 | F28: NANGABO | G28: WAKISO | H28: UGA | I28: 1 | J28: 1 | K28: =VLOOKUP(J28,Key!$E$2:$F$9,2,FALSE) -> Home | L28: GAYAZA | M28: WAKISO | N28: UGA | O28: 7 | P28: 4 | Q28: =VLOOKUP(P28,Key!$E$2:$F$9,2,FALSE) -> Commercial | R28: =K28&"-"&Q28 -> Home-Commercial | S28: 5 | T28: 0.1 | U28: 1 | Y28: Y | Z28: 1000
B29: 0.44305556 | C29: UAZ 508R | D29: 1 | E29: 2 | F29: GITTA | G29: WAKISO | H29: UGA | I29: 1 | J29: 4 | K29: =VLOOKUP(J29,Key!$E$2:$F$9,2,FALSE) -> Commercial | L29: KASANGATTI | M29: WAKISO | N29: UGA | O29: 7 | P29: 4 | Q29: =VLOOKUP(P29,Key!$E$2:$F$9,2,FALSE) -> Commercial | R29: =K29&"-"&Q29 -> Commercial-Commercial | T29: 0.3 | U29: 1 | Y29: Y | Z29: 1000
B30: 0.44722222 | C30: UAL 858S | D30: 1 | E30: 2 | F30: KITAGOBWA | G30: WAKISO | H30: UGA | I30: 1 | J30: 4 | K30: =VLOOKUP(J30,Key!$E$2:$F$9,2,FALSE) -> Commercial | L30: KASANGATTI | M30: WAKISO | N30: UGA | O30: 7 | P30: 4 | Q30: =VLOOKUP(P30,Key!$E$2:$F$9,2,FALSE) -> Commercial | R30: =K30&"-"&Q30 -> Commercial-Commercial | S30: 10 | T30: 0.3 | U30: 4 | Y30: Y | Z30: 1000
B31: 0.50763889 | C31: UAM 016T | D31: 1 | E31: 1 | F31: KITI | G31: WAKISO | H31: UGA | I31: 1 | J31: 2 | K31: =VLOOKUP(J31,Key!$E$2:$F$9,2,FALSE) -> Work | L31: KASANGATTI | M31: WAKISO | N31: UGA | O31: 2 | P31: 2 | Q31: =VLOOKUP(P31,Key!$E$2:$F$9,2,FALSE) -> Work | R31: =K31&"-"&Q31 -> Work-Work | S31: 25 | T31: 0.1 | U31: 1 | Y31: Y | Z31: 1000
B32: 0.50416667 | C32: UBB 033X | D32: 1 | E32: 3 | F32: KITI | G32: WAKISO | H32: UGA | I32: 1 | J32: 3 | K32: =VLOOKUP(J32,Key!$E$2:$F$9,2,FALSE) -> Study | L32: NAALYA | M32: KAMPALA | N32: UGA | O32: 4 | P32: 3 | Q32: =VLOOKUP(P32,Key!$E$2:$F$9,2,FALSE) -> Study | R32: =K32&"-"&Q32 -> Study-Study | S32: 3 | T32: 0.1 | U32: 1 | Y32: Y | Z32: 1000
B33: 0.45486111 | C33: UAT 557Z | D33: 1 | E33: 1 | F33: KITAGOBWA | G33: WAKISO | H33: UGA | I33: 1 | J33: 4 | K33: =VLOOKUP(J33,Key!$E$2:$F$9,2,FALSE) -> Commercial | L33: KAMPALA | M33: KAMPALA | N33: UGA | O33: 7 | P33: 4 | Q33: =VLOOKUP(P33,Key!$E$2:$F$9,2,FALSE) -> Commercial | R33: =K33&"-"&Q33 -> Commercial-Commercial | S33: 3 | T33: 0.2 | U33: 1 | Y33: Y | Z33: 1000
B34: 0.45347222 | C34: UAZ 646P | D34: 7 | E34: 1 | F34: ZANA | G34: KAMPALA | H34: UGA | I34: 1 | J34: 2 | K34: =VLOOKUP(J34,Key!$E$2:$F$9,2,FALSE) -> Work | L34: NAKASERO | M34: KAMPALA | N34: UGA | O34: 2 | P34: 2 | Q34: =VLOOKUP(P34,Key!$E$2:$F$9,2,FALSE) -> Work | R34: =K34&"-"&Q34 -> Work-Work | S34: 12 | T34: 3 | U34: 6 | V34: 11 | Y34: Y | Z34: 2000
B35: 0.45972222 | C35: UAP 666J | D35: 1 | E35: 2 | F35: KITAGOBWA | G35: WAKISO | H35: UGA | I35: 1 | J35: 2 | K35: =VLOOKUP(J35,Key!$E$2:$F$9,2,FALSE) -> Work | L35: KAMPALA | M35: KAMPALA | N35: UGA | O35: 2 | P35: 2 | Q35: =VLOOKUP(P35,Key!$E$2:$F$9,2,FALSE) -> Work | R35: =K35&"-"&Q35 -> Work-Work | S35: 4 | T35: 1 | U35: 1 | Y35: Y | Z35: 1000
B36: 0.46180556 | C36: UBB 762V | D36: 1 | E36: 1 | F36: NANGABO | G36: WAKISO | H36: UGA | I36: 1 | J36: 2 | K36: =VLOOKUP(J36,Key!$E$2:$F$9,2,FALSE) -> Work | L36: KAMPALA | M36: KAMPALA | N36: UGA | O36: 2 | P36: 2 | Q36: =VLOOKUP(P36,Key!$E$2:$F$9,2,FALSE) -> Work | R36: =K36&"-"&Q36 -> Work-Work | S36: 2 | T36: 0.1 | U36: 1 | Y36: Y | Z36: 1000
B37: 0.49652778 | C37: UBB 501B | D37: 1 | E37: 3 | F37: NANGABO | G37: WAKISO | H37: UGA | I37: 1 | J37: 1 | K37: =VLOOKUP(J37,Key!$E$2:$F$9,2,FALSE) -> Home | L37: KAMPALA | M37: KAMPALA | N37: UGA | O37: 2 | P37: 2 | Q37: =VLOOKUP(P37,Key!$E$2:$F$9,2,FALSE) -> Work | R37: =K37&"-"&Q37 -> Home-Work | S37: 2 | T37: 0.2 | U37: 2 | Y37: Y | Z37: 2000
B38: 0.49583333 | C38: UAK 084B | D38: 1 | E38: 1 | F38: NANGABO | G38: WAKISO | H38: UGA | I38: 1 | J38: 1 | K38: =VLOOKUP(J38,Key!$E$2:$F$9,2,FALSE) -> Home | L38: MPERRWE | M38: KAMPALA | N38: UGA | O38: 10 | P38: 4 | Q38: =VLOOKUP(P38,Key!$E$2:$F$9,2,FALSE) -> Commercial | R38: =K38&"-"&Q38 -> Home-Commercial | S38: 2 | T38: 0.1 | U38: 1 | Y38: Y | Z38: 1500
B39: 0.49930556 | C39: UAG 564B | D39: 4 | E39: 6 | F39: KITI | G39: WAKISO | H39: UGA | I39: 1 | J39: 7 | K39: =VLOOKUP(J39,Key!$E$2:$F$9,2,FALSE) -> Hospital | L39: KASANGATTI | M39: WAKISO | N39: UGA | O39: 5 | P39: 7 | Q39: =VLOOKUP(P39,Key!$E$2:$F$9,2,FALSE) -> Hospital | R39: =K39&"-"&Q39 -> Hospital-Hospital | S39: 5 | T39: 0.1 | U39: 1 | Y39: Y | Z39: 2000
B40: 0.49791667 | C40: UAQ 112T | D40: 1 | E40: 3 | F40: KITAGOBWA | G40: WAKISO | H40: UGA | I40: 1 | J40: 6 | K40: =VLOOKUP(J40,Key!$E$2:$F$9,2,FALSE) -> Leisure/Social | L40: LUTOOTO | M40: WAKISO | N40: UGA | O40: 1 | P40: 6 | Q40: =VLOOKUP(P40,Key!$E$2:$F$9,2,FALSE) -> Leisure/Social | R40: =K40&"-"&Q40 -> Leisure/Social-Leisure/Social | S40: 2 | T40: 0.1 | U40: 1 | Y40: Y | Z40: 1000
B41: 0.46597222 | C41: UAV 218T | D41: 1 | E41: 1 | F41: KITI | G41: WAKISO | H41: UGA | I41: 1 | J41: 7 | K41: =VLOOKUP(J41,Key!$E$2:$F$9,2,FALSE) -> Hospital | L41: SEETA | M41: MUKONO | N41: UGA | O41: 5 | P41: 7 | Q41: =VLOOKUP(P41,Key!$E$2:$F$9,2,FALSE) -> Hospital | R41: =K41&"-"&Q41 -> Hospital-Hospital | S41: 5 | T41: 0.3 | U41: 6 | Y41: Y | Z41: 2000
B42: 0.47291667 | C42: UBF 607T | D42: 8 | E42: 1 | F42: NANGABO | G42: WAKISO | H42: UGA | I42: 1 | J42: 2 | K42: =VLOOKUP(J42,Key!$E$2:$F$9,2,FALSE) -> Work | L42: KASANGATTI | M42: WAKISO | N42: UGA | O42: 3 | P42: 3 | Q42: =VLOOKUP(P42,Key!$E$2:$F$9,2,FALSE) -> Study | R42: =K42&"-"&Q42 -> Work-Study | T42: 2 | U42: 1 | V42: 11 | Y42: Y | Z42: 15000
B43: 0.41875 | C43: UAR 285A | D43: 1 | E43: 2 | F43: MAVUULE | G43: WAKISO | H43: UGA | I43: 9 | J43: 2 | K43: =VLOOKUP(J43,Key!$E$2:$F$9,2,FALSE) -> Work | L43: NAKASERO | M43: KAMPALA | N43: UGA | O43: 2 | P43: 2 | Q43: =VLOOKUP(P43,Key!$E$2:$F$9,2,FALSE) -> Work | R43: =K43&"-"&Q43 -> Work-Work | S43: 7 | T43: 0.1 | U43: 1 | Y43: Y | Z43: 1000
B44: 0.42222222 | C44: UAM 057J | D44: 1 | E44: 1 | F44: GITTA | G44: WAKISO | H44: UGA | I44: 1 | J44: 2 | K44: =VLOOKUP(J44,Key!$E$2:$F$9,2,FALSE) -> Work | L44: NTINDA | M44: KAMPALA | N44: UGA | O44: 2 | P44: 2 | Q44: =VLOOKUP(P44,Key!$E$2:$F$9,2,FALSE) -> Work | R44: =K44&"-"&Q44 -> Work-Work | S44: 2 | T44: 0.1 | U44: 6 | Y44: Y | Z44: 1000
B45: 0.46875 | C45: UED 711D | D45: 11 | E45: 2 | F45: KITI | G45: WAKISO | H45: UGA | I45: 1 | J45: 1 | K45: =VLOOKUP(J45,Key!$E$2:$F$9,2,FALSE) -> Home | L45: KASANGATTI | M45: WAKISO | N45: UGA | O45: 2 | P45: 2 | Q45: =VLOOKUP(P45,Key!$E$2:$F$9,2,FALSE) -> Work | R45: =K45&"-"&Q45 -> Home-Work | S45: 12 | T45: 0.1 | U45: 2 | Y45: Y | Z45: 1000
B46: 0.47152778 | C46: UAL 002F | D46: 7 | E46: 1 | F46: SSEMUTO | G46: WAKISO | H46: UGA | I46: 1 | J46: 1 | K46: =VLOOKUP(J46,Key!$E$2:$F$9,2,FALSE) -> Home | L46: MASALI | M46: WAKISO | N46: UGA | O46: 2 | P46: 2 | Q46: =VLOOKUP(P46,Key!$E$2:$F$9,2,FALSE) -> Work | R46: =K46&"-"&Q46 -> Home-Work | T46: 0.8 | U46: 6 | V46: 11 | Y46: Y | Z46: 2000
B47: 0.81388889 | C47: UAR 726J | D47: 1 | E47: 3 | F47: NANGABO | G47: WAKISO | H47: UGA | I47: 1 | J47: 1 | K47: =VLOOKUP(J47,Key!$E$2:$F$9,2,FALSE) -> Home | L47: NTINDA | M47: KAMPALA | N47: UGA | O47: 1 | P47: 6 | Q47: =VLOOKUP(P47,Key!$E$2:$F$9,2,FALSE) -> Leisure/Social | R47: =K47&"-"&Q47 -> Home-Leisure/Social | S47: 2 | T47: 0.1 | U47: 1 | Y47: Y | Z47: 1000
B48: 0.8125 | C48: UAW 068P | D48: 8 | E48: 3 | F48: BUSEGA | G48: WAKISO | H48: UGA | I48: 1 | J48: 4 | K48: =VLOOKUP(J48,Key!$E$2:$F$9,2,FALSE) -> Commercial | L48: MUKONO | M48: MUKONO | N48: UGA | O48: 3 | P48: 4 | Q48: =VLOOKUP(P48,Key!$E$2:$F$9,2,FALSE) -> Commercial | R48: =K48&"-"&Q48 -> Commercial-Commercial | T48: 2 | U48: 1 | V48: 1 | W48: 8 | X48: 12 | Y48: Y | Z48: 2000
B49: 0.56111111 | C49: UAR 877H | D49: 1 | E49: 4 | F49: NANGABO | G49: WAKISO | H49: UGA | I49: 1 | J49: 7 | K49: =VLOOKUP(J49,Key!$E$2:$F$9,2,FALSE) -> Hospital | L49: MPIGI | M49: MPIGI | N49: UGA | O49: 5 | P49: 7 | Q49: =VLOOKUP(P49,Key!$E$2:$F$9,2,FALSE) -> Hospital | R49: =K49&"-"&Q49 -> Hospital-Hospital | S49: 2 | T49: 0.2 | U49: 1 | Y49: Y | Z49: 1000
B50: 0.55972222 | C50: UBB 648R | D50: 1 | E50: 2 | F50: KITI | G50: WAKISO | H50: UGA | I50: 1 | J50: 1 | K50: =VLOOKUP(J50,Key!$E$2:$F$9,2,FALSE) -> Home | L50: KISASO | M50: WAKISO | N50: UGA | O50: 4 | P50: 3 | Q50: =VLOOKUP(P50,Key!$E$2:$F$9,2,FALSE) -> Study | R50: =K50&"-"&Q50 -> Home-Study | T50: 0.1 | U50: 1 | Y50: Y | Z50: 2000
B51: 0.55763889 | C51: UBE 625H | D51: 1 | E51: 1 | F51: KITAGOBWA | G51: WAKISO | H51: UGA | I51: 1 | J51: 1 | K51: =VLOOKUP(J51,Key!$E$2:$F$9,2,FALSE) -> Home | L51: MUKONO | M51: MUKONO | N51: UGA | O51: 8 | P51: 1 | Q51: =VLOOKUP(P51,Key!$E$2:$F$9,2,FALSE) -> Home | R51: =K51&"-"&Q51 -> Home-Home | S51: 7 | T51: 0.2 | U51: 1 | Y51: Y | Z51: 3000
B52: 0.55555556 | C52: UAZ 476E | D52: 1 | E52: 1 | F52: NDOOGA | G52: LUWERO | H52: UGA | I52: 4 | J52: 3 | K52: =VLOOKUP(J52,Key!$E$2:$F$9,2,FALSE) -> Study | L52: MUKONO | M52: MUKONO | N52: UGA | O52: 1 | P52: 1 | Q52: =VLOOKUP(P52,Key!$E$2:$F$9,2,FALSE) -> Home | R52: =K52&"-"&Q52 -> Study-Home | T52: 0.7 | U52: 4 | Y52: Y | Z52: 1000
B53: 0.76111111 | C53: UBB 963V | D53: 1 | E53: 4 | F53: KAWANDA | G53: WAKISO | H53: UGA | I53: 1 | J53: 1 | K53: =VLOOKUP(J53,Key!$E$2:$F$9,2,FALSE) -> Home | L53: KASANGATTI | M53: WAKISO | N53: UGA | O53: 9 | P53: 2 | Q53: =VLOOKUP(P53,Key!$E$2:$F$9,2,FALSE) -> Work | R53: =K53&"-"&Q53 -> Home-Work | S53: 6 | T53: 0.7 | U53: 1 | Y53: Y | Z53: 3000
B54: 0.75 | C54: UAY 892J | D54: 2 | E54: 2 | F54: MATUGGA | G54: WAKISO | H54: UGA | I54: 9 | J54: 2 | K54: =VLOOKUP(J54,Key!$E$2:$F$9,2,FALSE) -> Work | L54: KASANGATTI | M54: WAKISO | N54: UGA | O54: 1 | P54: 1 | Q54: =VLOOKUP(P54,Key!$E$2:$F$9,2,FALSE) -> Home | R54: =K54&"-"&Q54 -> Work-Home | S54: 2 | T54: 0.7 | U54: 1 | Y54: Y | Z54: 3000
B55: 0.70486111 | C55: UBA 034D | D55: 7 | E55: 2 | F55: MATUGGA | G55: WAKISO | H55: UGA | I55: 11 | J55: 4 | K55: =VLOOKUP(J55,Key!$E$2:$F$9,2,FALSE) -> Commercial | L55: KASANGATTI | M55: WAKISO | N55: UGA | O55: 10 | P55: 4 | Q55: =VLOOKUP(P55,Key!$E$2:$F$9,2,FALSE) -> Commercial | R55: =K55&"-"&Q55 -> Commercial-Commercial | S55: 4 | T55: 0.5 | U55: 1 | V55: 10 | W55: 1 | X55: 0.25 | Y55: Y | Z55: 1000
B56: 0.70277778 | C56: UAB 809Z | D56: 2 | E56: 4 | F56: LUWEROO | G56: LUWERO | H56: UGA | I56: 9 | J56: 2 | K56: =VLOOKUP(J56,Key!$E$2:$F$9,2,FALSE) -> Work | L56: KASANGATTI | M56: WAKISO | N56: UGA | O56: 1 | P56: 1 | Q56: =VLOOKUP(P56,Key!$E$2:$F$9,2,FALSE) -> Home | R56: =K56&"-"&Q56 -> Work-Home | S56: 5 | T56: 3 | U56: 6 | Y56: Y | Z56: 2000
B57: 0.7 | C57: UBD 866Y | D57: 1 | E57: 2 | F57: MATUGGA | G57: WAKISO | H57: UGA | I57: 5 | J57: 7 | K57: =VLOOKUP(J57,Key!$E$2:$F$9,2,FALSE) -> Hospital | L57: KASANGATTI | M57: WAKISO | N57: UGA | O57: 1 | P57: 1 | Q57: =VLOOKUP(P57,Key!$E$2:$F$9,2,FALSE) -> Home | R57: =K57&"-"&Q57 -> Hospital-Home | S57: 3 | T57: 0.3 | U57: 1 | Y57: Y | Z57: 500
B58: 0.69722222 | C58: UAQ 128S | D58: 1 | E58: 1 | F58: KAWANDA | G58: WAKISO | H58: UGA | I58: 16 | J58: 6 | K58: =VLOOKUP(J58,Key!$E$2:$F$9,2,FALSE) -> Leisure/Social | L58: KASANGATTI | M58: WAKISO | N58: UGA | O58: 16 | P58: 6 | Q58: =VLOOKUP(P58,Key!$E$2:$F$9,2,FALSE) -> Leisure/Social | R58: =K58&"-"&Q58 -> Leisure/Social-Leisure/Social | T58: 0.5 | U58: 6 | Y58: Y | Z58: 1000
B59: 0.6875 | C59: UBB 683B | D59: 1 | E59: 4 | F59: MATUGGA | G59: WAKISO | H59: UGA | I59: 1 | J59: 1 | K59: =VLOOKUP(J59,Key!$E$2:$F$9,2,FALSE) -> Home | L59: KAMPALA | M59: KAMPALA | N59: UGA | O59: 3 | P59: 2 | Q59: =VLOOKUP(P59,Key!$E$2:$F$9,2,FALSE) -> Work | R59: =K59&"-"&Q59 -> Home-Work | S59: 5 | T59: 0.7 | U59: 1 | Y59: Y | Z59: 1000
B60: 0.67569444 | C60: UAH 249U | D60: 1 | E60: 3 | F60: NANGABO | G60: WAKISO | H60: UGA | I60: 9 | J60: 2 | K60: =VLOOKUP(J60,Key!$E$2:$F$9,2,FALSE) -> Work | L60: LUTEETE | M60: WAKISO | N60: UGA | O60: 1 | P60: 1 | Q60: =VLOOKUP(P60,Key!$E$2:$F$9,2,FALSE) -> Home | R60: =K60&"-"&Q60 -> Work-Home | S60: 4 | T60: 0.5 | U60: 1 | Y60: Y | Z60: 2000
B61: 0.69513889 | C61: UBF 599F | D61: 1 | E61: 3 | F61: MATUGGA | G61: WAKISO | H61: UGA | I61: 1 | J61: 1 | K61: =VLOOKUP(J61,Key!$E$2:$F$9,2,FALSE) -> Home | L61: KASANGATTI | M61: WAKISO | N61: UGA | O61: 5 | P61: 7 | Q61: =VLOOKUP(P61,Key!$E$2:$F$9,2,FALSE) -> Hospital | R61: =K61&"-"&Q61 -> Home-Hospital | T61: 0.7 | U61: 1 | Y61: Y | Z61: 1000
B62: 0.69305556 | C62: UAN 162M | D62: 1 | E62: 2 | F62: KAWANDA | G62: WAKISO | H62: UGA | I62: 1 | J62: 1 | K62: =VLOOKUP(J62,Key!$E$2:$F$9,2,FALSE) -> Home | L62: KAMPALA | M62: KAMPALA | N62: UGA | O62: 16 | P62: 1 | Q62: =VLOOKUP(P62,Key!$E$2:$F$9,2,FALSE) -> Home | R62: =K62&"-"&Q62 -> Home-Home | S62: 6 | T62: 1 | U62: 1 | Y62: Y | Z62: 2000
B63: 0.50486111 | C63: UAW 822A | D63: 1 | E63: 1 | F63: KITEGOMBA | G63: WAKISO | H63: UGA | I63: 1 | J63: 1 | K63: =VLOOKUP(J63,Key!$E$2:$F$9,2,FALSE) -> Home | L63: KAMPALA | M63: KAMPALA | N63: UGA | O63: 2 | P63: 2 | Q63: =VLOOKUP(P63,Key!$E$2:$F$9,2,FALSE) -> Work | R63: =K63&"-"&Q63 -> Home-Work | S63: 5 | T63: 0.5 | U63: 1 | Y63: Y | Z63: 3000
B64: 0.50694444 | C64: UBB 954Y | D64: 2 | E64: 1 | F64: KIITA | G64: WAKISO | H64: UGA | I64: 1 | J64: 1 | K64: =VLOOKUP(J64,Key!$E$2:$F$9,2,FALSE) -> Home | L64: KASANGATTI | M64: WAKISO | N64: UGA | O64: 11 | P64: 4 | Q64: =VLOOKUP(P64,Key!$E$2:$F$9,2,FALSE) -> Commercial | R64: =K64&"-"&Q64 -> Home-Commercial | S64: 7 | T64: 0.1 | U64: 1 | Y64: Y | Z64: 0
B65: 0.64444444 | C65: UBE 345F | D65: 1 | E65: 1 | F65: KIITA | G65: WAKISO | H65: UGA | I65: 10 | J65: 2 | K65: =VLOOKUP(J65,Key!$E$2:$F$9,2,FALSE) -> Work | L65: BWEYOGERERE | M65: WAKISO | N65: UGA | O65: 1 | P65: 1 | Q65: =VLOOKUP(P65,Key!$E$2:$F$9,2,FALSE) -> Home | R65: =K65&"-"&Q65 -> Work-Home | S65: 30 | T65: 0.7 | U65: 4 | Y65: Y | Z65: 1000
B66: 0.66111111 | C66: UAL 541F | D66: 1 | E66: 5 | F66: KIWENDA | G66: WAKISO | H66: UGA | I66: 1 | J66: 1 | K66: =VLOOKUP(J66,Key!$E$2:$F$9,2,FALSE) -> Home | L66: KASANGATI | M66: WAKISO | N66: UGA | O66: 7 | P66: 4 | Q66: =VLOOKUP(P66,Key!$E$2:$F$9,2,FALSE) -> Commercial | R66: =K66&"-"&Q66 -> Home-Commercial | S66: 1 | T66: 0.1 | U66: 6 | Y66: Y | Z66: 10000
B67: 0.63819444 | C67: UAN 672B | D67: 1 | E67: 2 | F67: KAMPALA | G67: KAMPALA | H67: UGA | I67: 2 | J67: 2 | K67: =VLOOKUP(J67,Key!$E$2:$F$9,2,FALSE) -> Work | L67: KAMPALA | M67: KAMPALA | N67: UGA | O67: 2 | P67: 2 | Q67: =VLOOKUP(P67,Key!$E$2:$F$9,2,FALSE) -> Work | R67: =K67&"-"&Q67 -> Work-Work | S67: 13 | T67: 0.7 | U67: 1 | Y67: Y | Z67: 3000
B68: 0.65625 | C68: UAQ 736D | D68: 1 | E68: 1 | F68: MUKIITA | G68: WAKISO | H68: UGA | I68: 10 | J68: 2 | K68: =VLOOKUP(J68,Key!$E$2:$F$9,2,FALSE) -> Work | L68: BUKOTO | M68: KAMPALA | N68: UGA | O68: 1 | P68: 1 | Q68: =VLOOKUP(P68,Key!$E$2:$F$9,2,FALSE) -> Home | R68: =K68&"-"&Q68 -> Work-Home | S68: 20 | T68: 0.2 | U68: 6 | Y68: Y | Z68: 0
B69: 0.6625 | C69: UAW 841B | D69: 2 | E69: 2 | F69: MASINDI | G69: MASINDI | H69: UGA | I69: 15 | J69: 5 | K69: =VLOOKUP(J69,Key!$E$2:$F$9,2,FALSE) -> Tourism | L69: KAMPALA | M69: KAMPALA | N69: UGA | O69: 1 | P69: 1 | Q69: =VLOOKUP(P69,Key!$E$2:$F$9,2,FALSE) -> Home | R69: =K69&"-"&Q69 -> Tourism-Home | S69: 400 | T69: 5 | U69: 6 | Y69: Y | Z69: 10000
B70: 0.66458333 | C70: UAK 186N | D70: 4 | E70: 14 | F70: MATUGGA | G70: WAKISO | H70: UGA | I70: 6 | J70: 2 | K70: =VLOOKUP(J70,Key!$E$2:$F$9,2,FALSE) -> Work | L70: KIIRA | M70: WAKISO | N70: UGA | O70: 6 | P70: 2 | Q70: =VLOOKUP(P70,Key!$E$2:$F$9,2,FALSE) -> Work | R70: =K70&"-"&Q70 -> Work-Work | S70: 5 | T70: 0.5 | U70: 1 | Y70: Y | Z70: 2000
B71: 0.62638889 | C71: UAN 935S | D71: 1 | E71: 2 | F71: MATUGGA | G71: WAKISO | H71: UGA | I71: 3 | J71: 2 | K71: =VLOOKUP(J71,Key!$E$2:$F$9,2,FALSE) -> Work | L71: ENTEBBE | M71: WAKISO | N71: UGA | O71: 16 | P71: 8 | Q71: =VLOOKUP(P71,Key!$E$2:$F$9,2,FALSE) -> Others | R71: =K71&"-"&Q71 -> Work-Others | S71: 55 | T71: 2 | U71: 1 | Y71: Y | Z71: 3000
B72: 0.61944444 | C72: UBE 809J | D72: 1 | E72: 4 | F72: KITEGOMBA | G72: WAKISO | H72: UGA | I72: 1 | J72: 1 | K72: =VLOOKUP(J72,Key!$E$2:$F$9,2,FALSE) -> Home | L72: KAMPALA | M72: KAMPALA | N72: UGA | O72: 16 | P72: 6 | Q72: =VLOOKUP(P72,Key!$E$2:$F$9,2,FALSE) -> Leisure/Social | R72: =K72&"-"&Q72 -> Home-Leisure/Social | S72: 14 | T72: 0.5 | U72: 1 | Y72: Y | Z72: 2000
B73: 0.63194444 | C73: UBD 272Y | D73: 7 | E73: 1 | F73: NANGABO | G73: WAKISO | H73: UGA | I73: 1 | J73: 1 | K73: =VLOOKUP(J73,Key!$E$2:$F$9,2,FALSE) -> Home | L73: KALERWE | M73: KAMPALA | N73: UGA | O73: 2 | P73: 2 | Q73: =VLOOKUP(P73,Key!$E$2:$F$9,2,FALSE) -> Work | R73: =K73&"-"&Q73 -> Home-Work | S73: 7 | T73: 0.7 | U73: 1 | V73: 3 | W73: 0.1 | X73: 1 | Y73: Y | Z73: 0
B74: 0.63402778 | C74: UBB 626E | D74: 1 | E74: 2 | F74: MUKIITA | G74: WAKISO | H74: UGA | I74: 1 | J74: 1 | K74: =VLOOKUP(J74,Key!$E$2:$F$9,2,FALSE) -> Home | L74: BUKOTO | M74: KAMPALA | N74: UGA | O74: 16 | P74: 6 | Q74: =VLOOKUP(P74,Key!$E$2:$F$9,2,FALSE) -> Leisure/Social | R74: =K74&"-"&Q74 -> Home-Leisure/Social | S74: 10 | T74: 0.5 | U74: 1 | Y74: Y | Z74: 1000
B75: 0.63055556 | C75: UAP 500J | D75: 4 | E75: 13 | F75: MATUGGA | G75: WAKISO | H75: UGA | I75: 6 | J75: 2 | K75: =VLOOKUP(J75,Key!$E$2:$F$9,2,FALSE) -> Work | L75: KASANGATTI | M75: WAKISO | N75: UGA | O75: 6 | P75: 2 | Q75: =VLOOKUP(P75,Key!$E$2:$F$9,2,FALSE) -> Work | R75: =K75&"-"&Q75 -> Work-Work | T75: 0.5 | U75: 1 | Y75: Y | Z75: 500
B76: 0.62777778 | C76: UBA 280B | D76: 1 | E76: 1 | F76: MASOLI | G76: WAKISO | H76: UGA | I76: 1 | J76: 1 | K76: =VLOOKUP(J76,Key!$E$2:$F$9,2,FALSE) -> Home | L76: KAMPALA | M76: KAMPALA | N76: UGA | O76: 2 | P76: 2 | Q76: =VLOOKUP(P76,Key!$E$2:$F$9,2,FALSE) -> Work | R76: =K76&"-"&Q76 -> Home-Work | T76: 0.5 | U76: 1 | Y76: Y | Z76: 500
B77: 0.61666667 | C77: UAY 348M | D77: 1 | E77: 2 | F77: GAYAZA | G77: WAKISO | H77: UGA | I77: 1 | J77: 1 | K77: =VLOOKUP(J77,Key!$E$2:$F$9,2,FALSE) -> Home | L77: KAMPALA | M77: KAMPALA | N77: UGA | O77: 7 | P77: 4 | Q77: =VLOOKUP(P77,Key!$E$2:$F$9,2,FALSE) -> Commercial | R77: =K77&"-"&Q77 -> Home-Commercial | S77: 18 | T77: 0.5 | U77: 1 | Y77: Y | Z77: 3000
B78: 0.61180556 | C78: UAN 166B | D78: 1 | E78: 1 | F78: NANGABO | G78: WAKISO | H78: UGA | I78: 1 | J78: 1 | K78: =VLOOKUP(J78,Key!$E$2:$F$9,2,FALSE) -> Home | L78: KASANGATTI | M78: WAKISO | N78: UGA | O78: 16 | P78: 6 | Q78: =VLOOKUP(P78,Key!$E$2:$F$9,2,FALSE) -> Leisure/Social | R78: =K78&"-"&Q78 -> Home-Leisure/Social | S78: 3 | T78: 0.3 | U78: 1 | Y78: Y | Z78: 2000
B79: 0.61388889 | C79: UAU 715G | D79: 2 | E79: 6 | F79: NANGABO | G79: WAKISO | H79: UGA | I79: 16 | J79: 8 | K79: =VLOOKUP(J79,Key!$E$2:$F$9,2,FALSE) -> Others | L79: KIIRA | M79: WAKISO | N79: UGA | O79: 1 | P79: 1 | Q79: =VLOOKUP(P79,Key!$E$2:$F$9,2,FALSE) -> Home | R79: =K79&"-"&Q79 -> Others-Home | S79: 8 | T79: 0.5 | U79: 4 | Y79: Y | Z79: 3000
B80: 0.81180556 | C80: UBB 936Y | D80: 2 | E80: 4 | F80: KINAWA | G80: WAKISO | H80: UGA | I80: 4 | J80: 2 | K80: =VLOOKUP(J80,Key!$E$2:$F$9,2,FALSE) -> Work | L80: WAKISO | M80: WAKISO | N80: UGA | O80: 1 | P80: 1 | Q80: =VLOOKUP(P80,Key!$E$2:$F$9,2,FALSE) -> Home | R80: =K80&"-"&Q80 -> Work-Home | S80: 30 | T80: 1 | U80: 1 | Y80: Y | Z80: 1000
B81: 0.57569444 | C81: UAV 197T | D81: 1 | E81: 4 | F81: MATUGGA | G81: WAKISO | H81: UGA | I81: 3 | J81: 2 | K81: =VLOOKUP(J81,Key!$E$2:$F$9,2,FALSE) -> Work | L81: GAYAZA | M81: WAKISO | N81: UGA | O81: 1 | P81: 1 | Q81: =VLOOKUP(P81,Key!$E$2:$F$9,2,FALSE) -> Home | R81: =K81&"-"&Q81 -> Work-Home | S81: 10 | T81: 0.1 | U81: 6 | Y81: Y | Z81: 0
B82: 0.57777778 | C82: UAS 538M | D82: 1 | E82: 1 | F82: KAVULE | G82: WAKISO | H82: UGA | I82: 2 | J82: 2 | K82: =VLOOKUP(J82,Key!$E$2:$F$9,2,FALSE) -> Work | L82: BALUMA | M82: WAKISO | N82: UGA | O82: 1 | P82: 1 | Q82: =VLOOKUP(P82,Key!$E$2:$F$9,2,FALSE) -> Home | R82: =K82&"-"&Q82 -> Work-Home | S82: 22 | T82: 0.7 | U82: 3 | Y82: Y | Z82: 0
B83: 0.60486111 | C83: UBA 109V | D83: 1 | E83: 1 | F83: NANGABO | G83: WAKISO | H83: UGA | I83: 1 | J83: 1 | K83: =VLOOKUP(J83,Key!$E$2:$F$9,2,FALSE) -> Home | L83: KASANSANGA | M83: WAKISO | N83: UGA | O83: 7 | P83: 2 | Q83: =VLOOKUP(P83,Key!$E$2:$F$9,2,FALSE) -> Work | R83: =K83&"-"&Q83 -> Home-Work | S83: 2 | T83: 0.3 | Y83: Y | Z83: 500
B84: 0.57291667 | C84: UAM 695L | D84: 4 | E84: 14 | F84: WAKISO | G84: WAKISO | H84: UGA | I84: 6 | J84: 2 | K84: =VLOOKUP(J84,Key!$E$2:$F$9,2,FALSE) -> Work | L84: KASANGATI | M84: WAKISO | N84: UGA | O84: 6 | P84: 2 | Q84: =VLOOKUP(P84,Key!$E$2:$F$9,2,FALSE) -> Work | R84: =K84&"-"&Q84 -> Work-Work | S84: 20 | T84: 0.7 | U84: 1 | Y84: Y | Z84: 5000
B85: 0.60555556 | C85: UAU 967F | D85: 1 | E85: 4 | F85: NANGABO | G85: WAKISO | H85: UGA | I85: 1 | J85: 1 | K85: =VLOOKUP(J85,Key!$E$2:$F$9,2,FALSE) -> Home | L85: KASANGATI | M85: WAKISO | N85: UGA | O85: 2 | P85: 2 | Q85: =VLOOKUP(P85,Key!$E$2:$F$9,2,FALSE) -> Work | R85: =K85&"-"&Q85 -> Home-Work | S85: 4 | T85: 0.2 | U85: 1 | Y85: Y | Z85: 0
B86: 0.60625 | C86: UAH 249F | D86: 8 | E86: 2 | F86: LUWEROO | G86: WAKISO | H86: UGA | I86: 1 | J86: 1 | K86: =VLOOKUP(J86,Key!$E$2:$F$9,2,FALSE) -> Home | L86: NAMUGONGO | M86: WAKISO | N86: UGA | O86: 1 | P86: 1 | Q86: =VLOOKUP(P86,Key!$E$2:$F$9,2,FALSE) -> Home | R86: =K86&"-"&Q86 -> Home-Home | S86: 78 | T86: 2 | U86: 6 | Y86: Y | Z86: 2000
B87: 0.57083333 | C87: UBE 068F | D87: 1 | E87: 2 | F87: KITEGOMBA | G87: WAKISO | H87: UGA | I87: 1 | J87: 1 | K87: =VLOOKUP(J87,Key!$E$2:$F$9,2,FALSE) -> Home | L87: KAMPALA | M87: KAMPALA | N87: UGA | O87: 11 | P87: 4 | Q87: =VLOOKUP(P87,Key!$E$2:$F$9,2,FALSE) -> Commercial | R87: =K87&"-"&Q87 -> Home-Commercial | T87: 0.7 | U87: 1 | Y87: Y | Z87: 2000
B88: 0.56527778 | C88: UAZ 845X | D88: 1 | E88: 1 | F88: KASANGATTI | G88: WAKISO | H88: UGA | I88: 1 | J88: 1 | K88: =VLOOKUP(J88,Key!$E$2:$F$9,2,FALSE) -> Home | L88: NAKAWA | M88: KAMPALA | N88: UGA | O88: 2 | P88: 2 | Q88: =VLOOKUP(P88,Key!$E$2:$F$9,2,FALSE) -> Work | R88: =K88&"-"&Q88 -> Home-Work | S88: 23 | T88: 0.7 | U88: 1 | Y88: Y | Z88: 3000
B89: 0.54930556 | C89: UAV 492M | D89: 7 | E89: 2 | F89: NANGABO | G89: WAKISO | H89: UGA | I89: 1 | J89: 1 | K89: =VLOOKUP(J89,Key!$E$2:$F$9,2,FALSE) -> Home | L89: KASANGATTI | M89: WAKISO | N89: UGA | O89: 6 | P89: 2 | Q89: =VLOOKUP(P89,Key!$E$2:$F$9,2,FALSE) -> Work | R89: =K89&"-"&Q89 -> Home-Work | S89: 2 | T89: 0.1 | U89: 6 | V89: 5 | W89: 0.1 | Y89: Y | Z89: 300
B90: 0.55 | C90: UAM 704W | D90: 1 | E90: 6 | F90: KITEGOMBA | G90: WAKISO | H90: UGA | I90: 2 | J90: 2 | K90: =VLOOKUP(J90,Key!$E$2:$F$9,2,FALSE) -> Work | L90: KAMPALA | M90: KAMPALA | N90: UGA | O90: 1 | P90: 1 | Q90: =VLOOKUP(P90,Key!$E$2:$F$9,2,FALSE) -> Home | R90: =K90&"-"&Q90 -> Work-Home | S90: 10 | T90: 2 | U90: 1 | Y90: Y | Z90: 0
B91: 0.55416667 | C91: UBA 873J | D91: 2 | E91: 1 | F91: NANGABO | G91: WAKISO | H91: UGA | I91: 1 | J91: 1 | K91: =VLOOKUP(J91,Key!$E$2:$F$9,2,FALSE) -> Home | L91: KAMPALA | M91: KAMPALA | N91: UGA | O91: 2 | P91: 2 | Q91: =VLOOKUP(P91,Key!$E$2:$F$9,2,FALSE) -> Work | R91: =K91&"-"&Q91 -> Home-Work | S91: 11 | T91: 1 | U91: 1 | Y91: Y | Z91: 5000
B92: 0.55833333 | C92: UAV 890G | D92: 7 | E92: 5 | F92: NANGABO | G92: WAKISO | H92: UGA | I92: 2 | J92: 2 | K92: =VLOOKUP(J92,Key!$E$2:$F$9,2,FALSE) -> Work | L92: GAYAZA | M92: WAKISO | N92: UGA | O92: 6 | P92: 6 | Q92: =VLOOKUP(P92,Key!$E$2:$F$9,2,FALSE) -> Leisure/Social | R92: =K92&"-"&Q92 -> Work-Leisure/Social | S92: 2 | T92: 0.2 | U92: 1 | Y92: Y | Z92: 5000
B93: 0.5625 | C93: UBF 096D | D93: 2 | E93: 1 | F93: KITAGOBWA | G93: WAKISO | H93: UGA | I93: 1 | J93: 1 | K93: =VLOOKUP(J93,Key!$E$2:$F$9,2,FALSE) -> Home | L93: KISASI | M93: WAKISO | N93: UGA | O93: 7 | P93: 4 | Q93: =VLOOKUP(P93,Key!$E$2:$F$9,2,FALSE) -> Commercial | R93: =K93&"-"&Q93 -> Home-Commercial | S93: 5 | T93: 0.2 | U93: 1 | Y93: Y | Z93: 3000
B94: 0.56666667 | C94: UAS 295U | D94: 2 | E94: 2 | F94: MATUGGA | G94: WAKISO | H94: UGA | I94: 4 | J94: 3 | K94: =VLOOKUP(J94,Key!$E$2:$F$9,2,FALSE) -> Study | L94: KAMPALA | M94: KAMPALA | N94: UGA | O94: 7 | P94: 4 | Q94: =VLOOKUP(P94,Key!$E$2:$F$9,2,FALSE) -> Commercial | R94: =K94&"-"&Q94 -> Study-Commercial | S94: 6 | T94: 0.3 | U94: 6 | Y94: Y | Z94: 0
B95: 0.56944444 | C95: UBC 559A | D95: 1 | E95: 2 | F95: NAWULE | G95: WAKISO | H95: UGA | I95: 1 | J95: 1 | K95: =VLOOKUP(J95,Key!$E$2:$F$9,2,FALSE) -> Home | L95: KAMPALA | M95: KAMPALA | N95: UGA | O95: 7 | P95: 4 | Q95: =VLOOKUP(P95,Key!$E$2:$F$9,2,FALSE) -> Commercial | R95: =K95&"-"&Q95 -> Home-Commercial | S95: 40 | T95: 1 | U95: 1 | Y95: Y | Z95: 0
B96: 0.46666667 | C96: UBA 132R | D96: 2 | E96: 2 | F96: KANGAYI | G96: WAKISO | H96: UGA | I96: 1 | J96: 1 | K96: =VLOOKUP(J96,Key!$E$2:$F$9,2,FALSE) -> Home | L96: KAMPALA | M96: KAMPALA | N96: UGA | O96: 2 | P96: 2 | Q96: =VLOOKUP(P96,Key!$E$2:$F$9,2,FALSE) -> Work | R96: =K96&"-"&Q96 -> Home-Work | S96: 15 | T96: 1 | U96: 1 | Y96: Y | Z96: 2000
B97: 0.46736111 | C97: UAY 377L | D97: 1 | E97: 2 | F97: NANGABO | G97: WAKISO | H97: UGA | I97: 1 | J97: 1 | K97: =VLOOKUP(J97,Key!$E$2:$F$9,2,FALSE) -> Home | L97: KAMPALA | M97: KAMPALA | N97: UGA | O97: 2 | P97: 2 | Q97: =VLOOKUP(P97,Key!$E$2:$F$9,2,FALSE) -> Work | R97: =K97&"-"&Q97 -> Home-Work | S97: 17 | T97: 0.7 | U97: 2 | Y97: Y | Z97: 3000
B98: 0.42083333 | C98: UAY 082J | D98: 11 | E98: 2 | F98: KAWANGA | G98: WAKISO | H98: UGA | I98: 1 | J98: 1 | K98: =VLOOKUP(J98,Key!$E$2:$F$9,2,FALSE) -> Home | L98: NAMULONGE | M98: WAKISO | N98: UGA | O98: 4 | P98: 3 | Q98: =VLOOKUP(P98,Key!$E$2:$F$9,2,FALSE) -> Study | R98: =K98&"-"&Q98 -> Home-Study | S98: 16 | T98: 0.7 | U98: 1 | Y98: Y | Z98: 1000
B99: 0.42361111 | C99: UAQ 530L | D99: 2 | E99: 1 | F99: KITEGOMBA | G99: WAKISO | H99: UGA | I99: 10 | J99: 2 | K99: =VLOOKUP(J99,Key!$E$2:$F$9,2,FALSE) -> Work | L99: LUTEETE | M99: WAKISO | N99: UGA | O99: 16 | P99: 8 | Q99: =VLOOKUP(P99,Key!$E$2:$F$9,2,FALSE) -> Others | R99: =K99&"-"&Q99 -> Work-Others | S99: 5 | T99: 0.5 | U99: 2 | Y99: Y | Z99: 0
B100: 0.42916667 | C100: UAN 428E | D100: 1 | E100: 1 | F100: MASOOLI | G100: WAKISO | H100: UGA | I100: 1 | J100: 1 | K100: =VLOOKUP(J100,Key!$E$2:$F$9,2,FALSE) -> Home | L100: GAYAZA | M100: WAKISO | N100: UGA | O100: 2 | P100: 2 | Q100: =VLOOKUP(P100,Key!$E$2:$F$9,2,FALSE) -> Work | R100: =K100&"-"&Q100 -> Home-Work | S100: 2 | T100: 0.1 | U100: 2 | Y100: Y | Z100: 0
B101: 0.425 | C101: UAG 305H | D101: 1 | E101: 1 | F101: KULAMBIRO | G101: KAMPALA | H101: UGA | I101: 9 | J101: 2 | K101: =VLOOKUP(J101,Key!$E$2:$F$9,2,FALSE) -> Work | L101: KULAMBIRO | M101: KAMPALA | N101: UGA | O101: 1 | P101: 1 | Q101: =VLOOKUP(P101,Key!$E$2:$F$9,2,FALSE) -> Home | R101: =K101&"-"&Q101 -> Work-Home | S101: 4 | T101: 0.2 | U101: 1 | Y101: Y | Z101: 0
... B113: 0.43472222 | C113: UAY 793P | D113: 2 | E113: 1 | F113: KIITA | G113: WAKISO | H113: UGA | I113: 1 | J113: 1 | K113: =VLOOKUP(J113,Key!$E$2:$F$9,2,FALSE) -> Home | L113: KAMPALA | M113: KAMPALA | N113: UGA | O113: 2 | P113: 2 | Q113: =VLOOKUP(P113,Key!$E$2:$F$9,2,FALSE) -> Work | R113: =K113&"-"&Q113 -> Home-Work | S113: 23 | T113: 1.5 | U113: 2 | Y113: Y | Z113: 10000
...

Sheet 12.10 KASANGATTI-MATUGGA
B1: Consultancy services for Preparation of Expressway Develo PMent Master Plan (EDMP) for Uganda
B2: Roadside OD Interview Survey
B4: Date: | C4: ='12.10 MATUGGA-KASANGATTI'!C4 -> 12.10.19 | E4: Road Name: | F4: ='12.10 MATUGGA-KASANGATTI'!F4:G4 -> MATUGGA-WAKISO ROAD | I4: Direction From: | L4: KASANGATTI | N4: Interviewers: | O4: TUMWINE LINUS, SSEMUKO JUNIOR | V4: Supervisor: | W4: ='12.10 MATUGGA-KASANGATTI'!W4 -> STEVEN | Y4: Coded By: | Z4: ='12.10 MATUGGA-KASANGATTI'!Z4 -> DAVID | AA4: Chkd By: | AB4: ='12.10 MATUGGA-KASANGATTI'!AB4 -> Bakole Deo
I5: Direction To: | L5: MATUGGA
B7: Time | C7: Veh_Reg_No. | D7: Veh_Type | E7: No. Occupants | F7: Origin_Address | I7: Origin_Establish | J7: Origin_Purpose | K7: Origin-Purpose Desc | L7: Destination_Address | O7: Destination_Establish | P7: Destination_Purpose | Q7: Destination_Purpose Desc | R7: Journey_Purpose | S7: Approx_Distance (Km) | T7: Approx_Journey Time (Hrs) | U7: Trip_Frequency | V7: GOODS VEHICLES ONLY | Y7: Would You Use Xpressways? | Z7: Pay How Much? (UGX) | AA7: Origin_Zone | AB7: Dest_Zone
F8: Village or Town | G8: District | H8: Country | L8: Village or Town | M8: District | N8: Country | V8: Goods_Type | W8: Goods_Quantity (Ton) | X8: Goods_Value (UGXm)
B9: 0.57638889 | C9: UAS 950Y | D9: 1 | E9: 4 | F9: MUTUNGO | G9: KAMPALA | H9: UGA | I9: 1 | J9: 2 | K9: =VLOOKUP(J9,Key!$E$2:$F$9,2,FALSE) -> Work | L9: KITEGOBWA | M9: WAKISO | N9: UGA | O9: 16 | P9: 8 | Q9: =VLOOKUP(P9,Key!$E$2:$F$9,2,FALSE) -> Others | R9: =K9&"-"&Q9 -> Work-Others | T9: 1 | U9: 6 | Y9: Y | Z9: 1000
B10: 0.58055556 | C10: UAM 277S | D10: 1 | E10: 1 | F10: KASANGATTI | G10: WAKISO | H10: UGA | I10: 16 | J10: 8 | K10: =VLOOKUP(J10,Key!$E$2:$F$9,2,FALSE) -> Others | L10: KINTI | M10: WAKISO | N10: UGA | O10: 2 | P10: 2 | Q10: =VLOOKUP(P10,Key!$E$2:$F$9,2,FALSE) -> Work | R10: =K10&"-"&Q10 -> Others-Work | S10: 4 | T10: 0.1 | U10: 1 | Y10: Y | Z10: 1000
B11: 0.55902778 | C11: UAR 778L | D11: 2 | E11: 2 | F11: KIIRA | G11: WAKISO | H11: UGA | I11: 2 | J11: 2 | K11: =VLOOKUP(J11,Key!$E$2:$F$9,2,FALSE) -> Work | L11: BUWAMBO | M11: WAKISO | N11: UGA | O11: 1 | P11: 1 | Q11: =VLOOKUP(P11,Key!$E$2:$F$9,2,FALSE) -> Home | R11: =K11&"-"&Q11 -> Work-Home | S11: 20 | T11: 0.6 | U11: 1 | Y11: Y | Z11: 1000
B12: 0.55555556 | C12: UBE 302K | D12: 1 | E12: 3 | F12: GAYAZA | G12: WAKISO | H12: UGA | I12: 5 | J12: 7 | K12: =VLOOKUP(J12,Key!$E$2:$F$9,2,FALSE) -> Hospital | L12: NANGABO | M12: WAKISO | N12: UGA | O12: 1 | P12: 1 | Q12: =VLOOKUP(P12,Key!$E$2:$F$9,2,FALSE) -> Home | R12: =K12&"-"&Q12 -> Hospital-Home | S12: 12 | T12: 0.6 | U12: 1 | Y12: Y | Z12: 0
B13: 0.56736111 | C13: UBD 238A | D13: 2 | E13: 2 | F13: KAYUNGA | G13: KAYUNGA | H13: UGA | I13: 1 | J13: 1 | K13: =VLOOKUP(J13,Key!$E$2:$F$9,2,FALSE) -> Home | L13: MAIZIKIT | M13: WAKISO | N13: UGA | O13: 1 | P13: 1 | Q13: =VLOOKUP(P13,Key!$E$2:$F$9,2,FALSE) -> Home | R13: =K13&"-"&Q13 -> Home-Home | T13: 1.5 | U13: 3 | Y13: Y | Z13: 0
B14: 0.56458333 | C14: UAJ 072Y | D14: 1 | E14: 2 | F14: GWAFU | G14: MUKONO | H14: UGA | I14: 1 | J14: 1 | K14: =VLOOKUP(J14,Key!$E$2:$F$9,2,FALSE) -> Home | L14: BOMBO | M14: WAKISO | N14: UGA | O14: 9 | P14: 2 | Q14: =VLOOKUP(P14,Key!$E$2:$F$9,2,FALSE) -> Work | R14: =K14&"-"&Q14 -> Home-Work | S14: 80 | T14: 1.5 | U14: 3 | Y14: Y | Z14: 5000
B15: 0.50694444 | C15: UAJ 787Y | D15: 2 | E15: 1 | F15: GAYAZA | G15: WAKISO | H15: UGA | I15: 11 | J15: 4 | K15: =VLOOKUP(J15,Key!$E$2:$F$9,2,FALSE) -> Commercial | L15: NANGABO | M15: WAKISO | N15: UGA | O15: 1 | P15: 1 | Q15: =VLOOKUP(P15,Key!$E$2:$F$9,2,FALSE) -> Home | R15: =K15&"-"&Q15 -> Commercial-Home | S15: 2 | T15: 0.5 | U15: 1 | Y15: Y | Z15: 6000
B16: 0.50208333 | C16: UAH 749H | D16: 1 | E16: 2 | F16: MAGANJO | G16: WAKISO | H16: UGA | I16: 1 | J16: 1 | K16: =VLOOKUP(J16,Key!$E$2:$F$9,2,FALSE) -> Home | L16: KASANGATTI | M16: WAKISO | N16: UGA | O16: 16 | P16: 8 | Q16: =VLOOKUP(P16,Key!$E$2:$F$9,2,FALSE) -> Others | R16: =K16&"-"&Q16 -> Home-Others | T16: 0.5 | U16: 6 | Y16: Y | Z16: 2000
B17: 0.49791667 | C17: UAL 718T | D17: 1 | E17: 1 | F17: KASANGATTI | G17: WAKISO | H17: UGA | I17: 16 | J17: 2 | K17: =VLOOKUP(J17,Key!$E$2:$F$9,2,FALSE) -> Work | L17: NANGABO | M17: WAKISO | N17: UGA | O17: 2 | P17: 2 | Q17: =VLOOKUP(P17,Key!$E$2:$F$9,2,FALSE) -> Work | R17: =K17&"-"&Q17 -> Work-Work | S17: 2 | T17: 0.1 | U17: 1 | Y17: Y | Z17: 2000
B18: 0.49444444 | C18: UBA 458Q | D18: 1 | E18: 1 | F18: KOMAMBOGA | G18: WAKISO | H18: UGA | I18: 1 | J18: 1 | K18: =VLOOKUP(J18,Key!$E$2:$F$9,2,FALSE) -> Home | L18: KITI | M18: WAKISO | N18: UGA | O18: 1 | P18: 1 | Q18: =VLOOKUP(P18,Key!$E$2:$F$9,2,FALSE) -> Home | R18: =K18&"-"&Q18 -> Home-Home | S18: 15 | T18: 0.2 | U18: 4 | Y18: Y | Z18: 1000
B19: 0.46666667 | C19: UAG 330P | D19: 1 | E19: 3 | F19: KYAKIMA | G19: WAKISO | H19: UGA | I19: 1 | J19: 1 | K19: =VLOOKUP(J19,Key!$E$2:$F$9,2,FALSE) -> Home | L19: KITEGOBWA | M19: WAKISO | N19: UGA | O19: 3 | P19: 2 | Q19: =VLOOKUP(P19,Key!$E$2:$F$9,2,FALSE) -> Work | R19: =K19&"-"&Q19 -> Home-Work | S19: 2 | T19: 0.3 | U19: 1 | Y19: Y | Z19: 2000
B20: 0.47222222 | C20: UBF 875B | D20: 2 | E20: 2 | F20: KAYIMBA | G20: WAKISO | H20: UGA | I20: 10 | J20: 2 | K20: =VLOOKUP(J20,Key!$E$2:$F$9,2,FALSE) -> Work | L20: NAMGABOBWA | M20: WAKISO | N20: UGA | O20: 2 | P20: 2 | Q20: =VLOOKUP(P20,Key!$E$2:$F$9,2,FALSE) -> Work | R20: =K20&"-"&Q20 -> Work-Work | S20: 3 | T20: 0.1 | U20: 1 | Y20: Y | Z20: 1000
B21: 0.46180556 | C21: UAY 037S | D21: 7 | E21: 1 | F21: KASANGATTI | G21: WAKISO | H21: UGA | I21: 3 | J21: 2 | K21: =VLOOKUP(J21,Key!$E$2:$F$9,2,FALSE) -> Work | L21: KAPEEKA | M21: LUWERO | N21: UGA | O21: 3 | P21: 2 | Q21: =VLOOKUP(P21,Key!$E$2:$F$9,2,FALSE) -> Work | R21: =K21&"-"&Q21 -> Work-Work | S21: 55 | T21: 1.2 | U21: 4 | V21: 11 | Y21: Y | Z21: 1000
B22: 0.45625 | C22: UAV 468T | D22: 8 | E22: 2 | F22: LUTEETE | G22: WAKISO | H22: UGA | I22: 6 | J22: 2 | K22: =VLOOKUP(J22,Key!$E$2:$F$9,2,FALSE) -> Work | L22: NJINTA | M22: WAKISO | N22: UGA | O22: 1 | P22: 1 | Q22: =VLOOKUP(P22,Key!$E$2:$F$9,2,FALSE) -> Home | R22: =K22&"-"&Q22 -> Work-Home | S22: 2 | T22: 0.3 | U22: 6 | Y22: Y | Z22: 2000
B23: 0.45208333 | C23: UAM 431G | D23: 1 | E23: 1 | F23: KASANGATTI | G23: WAKISO | H23: UGA | I23: 1 | J23: 1 | K23: =VLOOKUP(J23,Key!$E$2:$F$9,2,FALSE) -> Home | L23: MAWULE | M23: WAKISO | N23: UGA | O23: 9 | P23: 2 | Q23: =VLOOKUP(P23,Key!$E$2:$F$9,2,FALSE) -> Work | R23: =K23&"-"&Q23 -> Home-Work | S23: 3 | T23: 0.5 | U23: 4 | Y23: Y | Z23: 2000
B24: 0.44513889 | C24: UBB 995G | D24: 4 | E24: 14 | F24: KANSANGA | G24: WAKISO | H24: UGA | I24: 6 | J24: 2 | K24: =VLOOKUP(J24,Key!$E$2:$F$9,2,FALSE) -> Work | L24: MATUGGA | M24: WAKISO | N24: UGA | O24: 6 | P24: 1 | Q24: =VLOOKUP(P24,Key!$E$2:$F$9,2,FALSE) -> Home | R24: =K24&"-"&Q24 -> Work-Home | T24: 0.3 | U24: 2 | Y24: N | Z24: 0
B25: 0.42777778 | C25: UAV 761T | D25: 4 | E25: 13 | F25: KASANGATTI | G25: WAKISO | H25: UGA | I25: 6 | J25: 2 | K25: =VLOOKUP(J25,Key!$E$2:$F$9,2,FALSE) -> Work | L25: MATUGGA | M25: WAKISO | N25: UGA | O25: 6 | P25: 2 | Q25: =VLOOKUP(P25,Key!$E$2:$F$9,2,FALSE) -> Work | R25: =K25&"-"&Q25 -> Work-Work | S25: 9.5 | T25: 0.2 | U25: 1 | Y25: Y | Z25: 10000
B26: 0.42361111 | C26: UAP 484R | D26: 6 | E26: 2 | F26: KIIRA | G26: WAKISO | H26: UGA | I26: 16 | J26: 2 | K26: =VLOOKUP(J26,Key!$E$2:$F$9,2,FALSE) -> Work | L26: KASANA | M26: LUWERO | N26: UGA | O26: 16 | P26: 2 | Q26: =VLOOKUP(P26,Key!$E$2:$F$9,2,FALSE) -> Work | R26: =K26&"-"&Q26 -> Work-Work | T26: 1 | U26: 6 | Y26: Y | Z26: 0
B27: 0.57361111 | C27: UBA 237N | D27: 1 | E27: 2 | F27: KOLOLO | G27: KAMPALA | H27: UGA | I27: 16 | J27: 2 | K27: =VLOOKUP(J27,Key!$E$2:$F$9,2,FALSE) -> Work | L27: KITEGOBWA | M27: WAKISO | N27: UGA | O27: 1 | P27: 1 | Q27: =VLOOKUP(P27,Key!$E$2:$F$9,2,FALSE) -> Home | R27: =K27&"-"&Q27 -> Work-Home | T27: 1 | U27: 3 | Y27: Y | Z27: 0
B28: 0.57083333 | C28: UAU 383G | D28: 7 | E28: 5 | F28: KIIRA | G28: WAKISO | H28: UGA | I28: 3 | J28: 2 | K28: =VLOOKUP(J28,Key!$E$2:$F$9,2,FALSE) -> Work | L28: MATUGGA | M28: WAKISO | N28: UGA | O28: 3 | P28: 2 | Q28: =VLOOKUP(P28,Key!$E$2:$F$9,2,FALSE) -> Work | R28: =K28&"-"&Q28 -> Work-Work | S28: 8 | T28: 0.5 | U28: 3 | V28: 11 | Y28: Y | Z28: 2000
B29: 0.44305556 | C29: UAV 056Q | D29: 7 | E29: 1 | F29: KISAASI | G29: WAKISO | H29: UGA | I29: 3 | J29: 1 | K29: =VLOOKUP(J29,Key!$E$2:$F$9,2,FALSE) -> Home | L29: BUWAMBO | M29: WAKISO | N29: UGA | O29: 11 | P29: 4 | Q29: =VLOOKUP(P29,Key!$E$2:$F$9,2,FALSE) -> Commercial | R29: =K29&"-"&Q29 -> Home-Commercial | S29: 1 | T29: 0.8 | U29: 4 | X29: 1.05 | Y29: Y | Z29: 1000
B30: 0.43819444 | C30: UAL 361D | D30: 4 | E30: 11 | F30: KALERWE | G30: KAMPALA | H30: UGA | I30: 6 | J30: 2 | K30: =VLOOKUP(J30,Key!$E$2:$F$9,2,FALSE) -> Work | L30: KITEGOBWA | M30: WAKISO | N30: UGA | O30: 16 | P30: 8 | Q30: =VLOOKUP(P30,Key!$E$2:$F$9,2,FALSE) -> Others | R30: =K30&"-"&Q30 -> Work-Others | T30: 0.5 | U30: 6 | Y30: N | Z30: 0
B31: 0.43125 | C31: UAZ 841S | D31: 7 | E31: 2 | F31: BWEYOGERERE | G31: WAKISO | H31: UGA | I31: 2 | J31: 2 | K31: =VLOOKUP(J31,Key!$E$2:$F$9,2,FALSE) -> Work | L31: WOBULENZI | M31: LUWERO | N31: UGA | O31: 1 | P31: 1 | Q31: =VLOOKUP(P31,Key!$E$2:$F$9,2,FALSE) -> Home | R31: =K31&"-"&Q31 -> Work-Home | T31: 1 | U31: 3 | Y31: Y | Z31: 1000
B32: 0.43472222 | C32: UAX 474M | D32: 8 | E32: 1 | F32: GAYAZA | G32: WAKISO | H32: UGA | I32: 14 | J32: 2 | K32: =VLOOKUP(J32,Key!$E$2:$F$9,2,FALSE) -> Work | L32: NANGABO | M32: WAKISO | N32: UGA | O32: 16 | P32: 6 | Q32: =VLOOKUP(P32,Key!$E$2:$F$9,2,FALSE) -> Leisure/Social | R32: =K32&"-"&Q32 -> Work-Leisure/Social | S32: 1 | T32: 0.1 | U32: 4 | Y32: Y | Z32: 0
B33: 0.70416667 | C33: UAQ 128A | D33: 1 | E33: 2 | F33: LUZIRA | G33: KAMPALA | H33: UGA | I33: 1 | J33: 1 | K33: =VLOOKUP(J33,Key!$E$2:$F$9,2,FALSE) -> Home | L33: MATUGGA | M33: WAKISO | N33: UGA | O33: 16 | P33: 8 | Q33: =VLOOKUP(P33,Key!$E$2:$F$9,2,FALSE) -> Others | R33: =K33&"-"&Q33 -> Home-Others | S33: 25 | T33: 2 | U33: 4 | Y33: Y | Z33: 2000
B34: 0.70763889 | C34: UBA 585R | D34: 7 | E34: 5 | F34: NAJERA | G34: WAKISO | H34: UGA | I34: 2 | J34: 2 | K34: =VLOOKUP(J34,Key!$E$2:$F$9,2,FALSE) -> Work | L34: MATUGGA | M34: WAKISO | N34: UGA | O34: 1 | P34: 1 | Q34: =VLOOKUP(P34,Key!$E$2:$F$9,2,FALSE) -> Home | R34: =K34&"-"&Q34 -> Work-Home | T34: 3 | U34: 3 | V34: 10 | Y34: Y | Z34: 1000
B35: 0.69930556 | C35: UAX 918A | D35: 1 | E35: 5 | F35: WANDEGEYA | G35: KAMPALA | H35: UGA | I35: 2 | J35: 2 | K35: =VLOOKUP(J35,Key!$E$2:$F$9,2,FALSE) -> Work | L35: KATIKAMU | M35: WAKISO | N35: UGA | O35: 16 | P35: 8 | Q35: =VLOOKUP(P35,Key!$E$2:$F$9,2,FALSE) -> Others | R35: =K35&"-"&Q35 -> Work-Others | S35: 22 | T35: 1 | U35: 3 | Y35: Y | Z35: 0
B36: 0.70138889 | C36: UBB 444N | D36: 7 | E36: 2 | F36: KIIRA | G36: WAKISO | H36: UGA | I36: 14 | J36: 2 | K36: =VLOOKUP(J36,Key!$E$2:$F$9,2,FALSE) -> Work | L36: NANGABO | M36: WAKISO | N36: UGA | O36: 1 | P36: 1 | Q36: =VLOOKUP(P36,Key!$E$2:$F$9,2,FALSE) -> Home | R36: =K36&"-"&Q36 -> Work-Home | S36: 5 | T36: 0.5 | U36: 6 | Y36: Y | Z36: 0
B37: 0.63541667 | C37: UAP 565W | D37: 1 | E37: 2 | F37: GAYAZA | G37: WAKISO | H37: UGA | I37: 10 | J37: 2 | K37: =VLOOKUP(J37,Key!$E$2:$F$9,2,FALSE) -> Work | L37: NAKALOLO | M37: WAKISO | N37: UGA | O37: 16 | P37: 8 | Q37: =VLOOKUP(P37,Key!$E$2:$F$9,2,FALSE) -> Others | R37: =K37&"-"&Q37 -> Work-Others | T37: 0.5 | U37: 2 | Y37: Y | Z37: 0
B38: 0.62916667 | C38: UBA 034G | D38: 7 | E38: 1 | F38: KASANGATTI | G38: WAKISO | H38: UGA | I38: 16 | J38: 2 | K38: =VLOOKUP(J38,Key!$E$2:$F$9,2,FALSE) -> Work | L38: KITEGOBWA | M38: WAKISO | N38: UGA | O38: 1 | P38: 1 | Q38: =VLOOKUP(P38,Key!$E$2:$F$9,2,FALSE) -> Home | R38: =K38&"-"&Q38 -> Work-Home | S38: 2 | T38: 0.1 | U38: 2 | Y38: Y | Z38: 1000
B39: 0.67986111 | C39: UAR 764B | D39: 2 | E39: 2 | F39: NSETA | G39: WAKISO | H39: UGA | I39: 1 | J39: 1 | K39: =VLOOKUP(J39,Key!$E$2:$F$9,2,FALSE) -> Home | L39: NKOWE | M39: WAKISO | N39: UGA | O39: 10 | P39: 2 | Q39: =VLOOKUP(P39,Key!$E$2:$F$9,2,FALSE) -> Work | R39: =K39&"-"&Q39 -> Home-Work | S39: 21 | T39: 0.5 | U39: 6 | Y39: Y | Z39: 1000
B40: 0.69375 | C40: UAW 801S | D40: 7 | E40: 2 | F40: KASANGATTI | G40: WAKISO | H40: UGA | I40: 3 | J40: 2 | K40: =VLOOKUP(J40,Key!$E$2:$F$9,2,FALSE) -> Work | L40: NANGABO | M40: WAKISO | N40: UGA | O40: 11 | P40: 2 | Q40: =VLOOKUP(P40,Key!$E$2:$F$9,2,FALSE) -> Work | R40: =K40&"-"&Q40 -> Work-Work | T40: 0.5 | U40: 3 | Y40: Y | Z40: 1000
B41: 0.62013889 | C41: UAT 892J | D41: 1 | E41: 2 | F41: MUNYONYO | G41: KAMPALA | H41: UGA | I41: 1 | J41: 1 | K41: =VLOOKUP(J41,Key!$E$2:$F$9,2,FALSE) -> Home | L41: KASANGATTI | M41: WAKISO | N41: UGA | O41: 16 | P41: 8 | Q41: =VLOOKUP(P41,Key!$E$2:$F$9,2,FALSE) -> Others | R41: =K41&"-"&Q41 -> Home-Others | T41: 1 | U41: 6 | Y41: Y | Z41: 0
B42: 0.65486111 | C42: UAU 156S | D42: 8 | E42: 2 | F42: KASANGATTI | G42: WAKISO | H42: UGA | I42: 15 | J42: 2 | K42: =VLOOKUP(J42,Key!$E$2:$F$9,2,FALSE) -> Work | L42: NABUTITI | M42: WAKISO | N42: UGA | O42: 10 | P42: 2 | Q42: =VLOOKUP(P42,Key!$E$2:$F$9,2,FALSE) -> Work | R42: =K42&"-"&Q42 -> Work-Work | S42: 15 | T42: 0.5 | U42: 2 | Y42: Y | Z42: 1000
B43: 0.65069444 | C43: UAV 416B | D43: 7 | E43: 1 | F43: KISANGI | G43: WAKISO | H43: UGA | I43: 3 | J43: 1 | K43: =VLOOKUP(J43,Key!$E$2:$F$9,2,FALSE) -> Home | L43: BOMBO | M43: BOMBO | N43: UGA | O43: 11 | P43: 4 | Q43: =VLOOKUP(P43,Key!$E$2:$F$9,2,FALSE) -> Commercial | R43: =K43&"-"&Q43 -> Home-Commercial | T43: 0.5 | U43: 2 | V43: 11 | Y43: Y | Z43: 0
B44: 0.64236111 | C44: UAZ 657D | D44: 1 | E44: 1 | F44: BUGERERE | G44: KAYUNGA | H44: UGA | I44: 16 | J44: 8 | K44: =VLOOKUP(J44,Key!$E$2:$F$9,2,FALSE) -> Others | L44: MAENDE | M44: WAKISO | N44: UGA | O44: 1 | P44: 1 | Q44: =VLOOKUP(P44,Key!$E$2:$F$9,2,FALSE) -> Home | R44: =K44&"-"&Q44 -> Others-Home | S44: 50 | T44: 1.5 | U44: 6 | Y44: Y | Z44: 0
B45: 0.64583333 | C45: UA 993C | D45: 7 | E45: 4 | F45: KILA | G45: WAKISO | H45: UGA | I45: 1 | J45: 1 | K45: =VLOOKUP(J45,Key!$E$2:$F$9,2,FALSE) -> Home | L45: MATUGGA | M45: WAKISO | N45: UGA | O45: 1 | P45: 1 | Q45: =VLOOKUP(P45,Key!$E$2:$F$9,2,FALSE) -> Home | R45: =K45&"-"&Q45 -> Home-Home | S45: 4 | T45: 0.1 | U45: 2 | V45: 11 | Y45: Y | Z45: 2000
B46: 0.64166667 | C46: UEP 783D | D46: 11 | E46: 1 | F46: KASANGATTI | G46: WAKISO | H46: UGA | I46: 11 | J46: 4 | K46: =VLOOKUP(J46,Key!$E$2:$F$9,2,FALSE) -> Commercial | L46: NANGABO | M46: WAKISO | N46: UGA | O46: 11 | P46: 4 | Q46: =VLOOKUP(P46,Key!$E$2:$F$9,2,FALSE) -> Commercial | R46: =K46&"-"&Q46 -> Commercial-Commercial | S46: 1.3 | T46: 0.4 | U46: 2 | Y46: Y | Z46: 5000
B47: 0.62430556 | C47: UAR 152V | D47: 1 | E47: 1 | F47: LUBAGA | G47: KAMPALA | H47: UGA | I47: 1 | J47: 1 | K47: =VLOOKUP(J47,Key!$E$2:$F$9,2,FALSE) -> Home | L47: MASOOLI | M47: WAKISO | N47: UGA | O47: 16 | P47: 8 | Q47: =VLOOKUP(P47,Key!$E$2:$F$9,2,FALSE) -> Others | R47: =K47&"-"&Q47 -> Home-Others | T47: 2 | U47: 6 | Y47: N | Z47: 0
B48: 0.61666667 | C48: UBE 667U | D48: 1 | E48: 2 | F48: KASANGATTI | G48: WAKISO | H48: UGA | I48: 2 | J48: 2 | K48: =VLOOKUP(J48,Key!$E$2:$F$9,2,FALSE) -> Work | L48: NANGABO | M48: WAKISO | N48: UGA | O48: 1 | P48: 1 | Q48: =VLOOKUP(P48,Key!$E$2:$F$9,2,FALSE) -> Home | R48: =K48&"-"&Q48 -> Work-Home | S48: 3 | T48: 0.5 | U48: 2 | Y48: Y | Z48: 0
B49: 0.61111111 | C49: UAR 525Q | D49: 1 | E49: 3 | F49: NANSANA | G49: KAMPALA | H49: UGA | I49: 1 | J49: 1 | K49: =VLOOKUP(J49,Key!$E$2:$F$9,2,FALSE) -> Home | L49: KITEGOBWA | M49: WAKISO | N49: UGA | O49: 16 | P49: 2 | Q49: =VLOOKUP(P49,Key!$E$2:$F$9,2,FALSE) -> Work | R49: =K49&"-"&Q49 -> Home-Work | S49: 20 | T49: 1 | U49: 5 | Y49: Y | Z49: 2000
B50: 0.60486111 | C50: UAU 508E | D50: 1 | E50: 1 | F50: WAMPEWO | G50: WAKISO | H50: UGA | I50: 16 | J50: 2 | K50: =VLOOKUP(J50,Key!$E$2:$F$9,2,FALSE) -> Work | L50: MAWULE | M50: WAKISO | N50: UGA | O50: 1 | P50: 1 | Q50: =VLOOKUP(P50,Key!$E$2:$F$9,2,FALSE) -> Home | R50: =K50&"-"&Q50 -> Work-Home | S50: 5 | T50: 0.5 | U50: 2 | Y50: Y | Z50: 0
B51: 0.71319444 | C51: UAZ 220P | D51: 2 | E51: 2 | F51: SENTA | G51: MBALALA | H51: UGA | I51: 16 | J51: 8 | K51: =VLOOKUP(J51,Key!$E$2:$F$9,2,FALSE) -> Others | L51: NANGABO | M51: WAKISO | N51: UGA | O51: 1 | P51: 1 | Q51: =VLOOKUP(P51,Key!$E$2:$F$9,2,FALSE) -> Home | R51: =K51&"-"&Q51 -> Others-Home | S51: 60 | T51: 0.8 | U51: 2 | Y51: Y | Z51: 2000
B52: 0.4375 | C52: UBD 897R | D52: 1 | E52: 4 | F52: NANGABA | G52: WAKISO | H52: UGA | I52: 1 | J52: 1 | K52: =VLOOKUP(J52,Key!$E$2:$F$9,2,FALSE) -> Home | L52: NANGABO | M52: WAKISO | N52: UGA | O52: 11 | P52: 4 | Q52: =VLOOKUP(P52,Key!$E$2:$F$9,2,FALSE) -> Commercial | R52: =K52&"-"&Q52 -> Home-Commercial | S52: 10 | T52: 0.5 | U52: 2 | Y52: Y | Z52: 1000
B53: 0.50277778 | C53: UBA 884V | D53: 1 | E53: 4 | F53: NAKAWA | G53: KAMPALA | H53: UGA | I53: 1 | J53: 1 | K53: =VLOOKUP(J53,Key!$E$2:$F$9,2,FALSE) -> Home | L53: NANGABO | M53: WAKISO | N53: UGA | O53: 1 | P53: 1 | Q53: =VLOOKUP(P53,Key!$E$2:$F$9,2,FALSE) -> Home | R53: =K53&"-"&Q53 -> Home-Home | T53: 1 | U53: 6 | Y53: Y | Z53: 1000
B54: 0.68194444 | C54: UAU 956L | D54: 8 | E54: 3 | F54: MUKONO | G54: MUKONO | H54: UGA | I54: 1 | J54: 1 | K54: =VLOOKUP(J54,Key!$E$2:$F$9,2,FALSE) -> Home | L54: MATUGGA | M54: WAKISO | N54: UGA | O54: 2 | P54: 2 | Q54: =VLOOKUP(P54,Key!$E$2:$F$9,2,FALSE) -> Work | R54: =K54&"-"&Q54 -> Home-Work | T54: 3 | U54: 3 | V54: 6 | W54: 1 | Y54: Y | Z54: 3000
B55: 0.63541667 | C55: UAR 037N | D55: 1 | E55: 5 | F55: NAKAWA | G55: KAMPALA | H55: UGA | I55: 1 | J55: 1 | K55: =VLOOKUP(J55,Key!$E$2:$F$9,2,FALSE) -> Home | L55: KITI | M55: WAKISO | N55: UGA | O55: 4 | P55: 3 | Q55: =VLOOKUP(P55,Key!$E$2:$F$9,2,FALSE) -> Study | R55: =K55&"-"&Q55 -> Home-Study | S55: 11 | T55: 0.5 | U55: 6 | Y55: Y | Z55: 3000
B56: 0.57013889 | C56: UBA 290Z | D56: 3 | E56: 1 | F56: NAMUGONGO | G56: WAKISO | H56: UGA | I56: 1 | J56: 1 | K56: =VLOOKUP(J56,Key!$E$2:$F$9,2,FALSE) -> Home | L56: MATUGGA | M56: WAKISO | N56: UGA | O56: 16 | P56: 8 | Q56: =VLOOKUP(P56,Key!$E$2:$F$9,2,FALSE) -> Others | R56: =K56&"-"&Q56 -> Home-Others | S56: 15 | T56: 0.8 | U56: 5 | Y56: Y | Z56: 5000
B57: 0.43055556 | C57: UAJ 985W | D57: 1 | E57: 2 | F57: KASANGATTI | G57: WAKISO | H57: UGA | I57: 9 | J57: 4 | K57: =VLOOKUP(J57,Key!$E$2:$F$9,2,FALSE) -> Commercial | L57: MATUGGA | M57: WAKISO | N57: UGA | O57: 9 | P57: 2 | Q57: =VLOOKUP(P57,Key!$E$2:$F$9,2,FALSE) -> Work | R57: =K57&"-"&Q57 -> Commercial-Work | S57: 30 | T57: 0.5 | U57: 2 | Y57: Y | Z57: 1000
B58: 0.44722222 | C58: UAU 642V | D58: 7 | E58: 2 | F58: KASANGATTI | G58: WAKISO | H58: UGA | I58: 16 | J58: 8 | K58: =VLOOKUP(J58,Key!$E$2:$F$9,2,FALSE) -> Others | L58: MATUGGA | M58: WAKISO | N58: UGA | O58: 10 | P58: 2 | Q58: =VLOOKUP(P58,Key!$E$2:$F$9,2,FALSE) -> Work | R58: =K58&"-"&Q58 -> Others-Work | S58: 5 | T58: 0.7 | U58: 2 | V58: 4 | W58: 5 | X58: 3 | Y58: Y | Z58: 2000
B59: 0.4375 | C59: UAX 986Y | D59: 1 | E59: 1 | F59: GAYAZA | G59: WAKISO | H59: UGA | I59: 11 | J59: 4 | K59: =VLOOKUP(J59,Key!$E$2:$F$9,2,FALSE) -> Commercial | L59: NANSANA | M59: WAKISO | N59: UGA | O59: 1 | P59: 1 | Q59: =VLOOKUP(P59,Key!$E$2:$F$9,2,FALSE) -> Home | R59: =K59&"-"&Q59 -> Commercial-Home | S59: 3 | T59: 0.5 | U59: 2 | Y59: Y | Z59: 3500
B60: 0.43333333 | C60: UAR 005Z | D60: 1 | E60: 3 | F60: KASANGATTI | G60: WAKISO | H60: UGA | I60: 11 | J60: 4 | K60: =VLOOKUP(J60,Key!$E$2:$F$9,2,FALSE) -> Commercial | L60: NANGABO | M60: WAKISO | N60: UGA | O60: 1 | P60: 1 | Q60: =VLOOKUP(P60,Key!$E$2:$F$9,2,FALSE) -> Home | R60: =K60&"-"&Q60 -> Commercial-Home | S60: 1.5 | T60: 0.3 | U60: 2 | Y60: Y | Z60: 4000
B61: 0.43194444 | C61: UAU 584U | D61: 1 | E61: 2 | F61: GAYAZA | G61: WAKISO | H61: UGA | I61: 11 | J61: 4 | K61: =VLOOKUP(J61,Key!$E$2:$F$9,2,FALSE) -> Commercial | L61: NANSANA | M61: WAKISO | N61: UGA | O61: 1 | P61: 1 | Q61: =VLOOKUP(P61,Key!$E$2:$F$9,2,FALSE) -> Home | R61: =K61&"-"&Q61 -> Commercial-Home | S61: 5 | T61: 0.3 | U61: 2 | W61: 0.1 | X61: 0.2 | Y61: Y | Z61: 1000
B62: 0.46805556 | C62: UAY 500W | D62: 3 | E62: 1 | F62: KISASI | G62: KAMPALA | H62: UGA | I62: 1 | J62: 1 | K62: =VLOOKUP(J62,Key!$E$2:$F$9,2,FALSE) -> Home | L62: LIRA | M62: LIRA | N62: UGA | O62: 2 | P62: 2 | Q62: =VLOOKUP(P62,Key!$E$2:$F$9,2,FALSE) -> Work | R62: =K62&"-"&Q62 -> Home-Work | S62: 400 | T62: 4 | U62: 6 | W62: 0.1 | Y62: Y | Z62: 200
B63: 0.475 | C63: UAS 754Q | D63: 1 | E63: 2 | F63: GAYAZA | G63: WAKISO | H63: UGA | I63: 11 | J63: 4 | K63: =VLOOKUP(J63,Key!$E$2:$F$9,2,FALSE) -> Commercial | L63: NANGABO | M63: WAKISO | N63: UGA | O63: 1 | P63: 1 | Q63: =VLOOKUP(P63,Key!$E$2:$F$9,2,FALSE) -> Home | R63: =K63&"-"&Q63 -> Commercial-Home | S63: 2 | T63: 0.2 | U63: 2 | Y63: Y | Z63: 1000
B64: 0.46319444 | C64: UAU 972D | D64: 1 | E64: 2 | F64: GAYAZA | G64: WAKISO | H64: UGA | I64: 11 | J64: 4 | K64: =VLOOKUP(J64,Key!$E$2:$F$9,2,FALSE) -> Commercial | L64: NANGABO | M64: WAKISO | N64: UGA | O64: 1 | P64: 1 | Q64: =VLOOKUP(P64,Key!$E$2:$F$9,2,FALSE) -> Home | R64: =K64&"-"&Q64 -> Commercial-Home | S64: 5 | T64: 0.2 | U64: 2 | Y64: Y | Z64: 1000
B65: 0.42638889 | C65: UBD 391L | D65: 9 | E65: 2 | F65: GAYAZA | G65: WAKISO | H65: UGA | I65: 3 | J65: 2 | K65: =VLOOKUP(J65,Key!$E$2:$F$9,2,FALSE) -> Work | L65: SSEMUTO | M65: WAKISO | N65: UGA | O65: 12 | P65: 2 | Q65: =VLOOKUP(P65,Key!$E$2:$F$9,2,FALSE) -> Work | R65: =K65&"-"&Q65 -> Work-Work | S65: 48 | T65: 2 | U65: 2 | V65: 4 | W65: 2 | Y65: Y | Z65: 2000
B66: 0.45833333 | C66: UAK 922L | D66: 7 | E66: 1 | F66: KASANGATTI | G66: WAKISO | H66: UGA | I66: 15 | J66: 2 | K66: =VLOOKUP(J66,Key!$E$2:$F$9,2,FALSE) -> Work | L66: NANGABO | M66: WAKISO | N66: UGA | O66: 10 | P66: 2 | Q66: =VLOOKUP(P66,Key!$E$2:$F$9,2,FALSE) -> Work | R66: =K66&"-"&Q66 -> Work-Work | S66: 1.4 | U66: 2 | V66: 4 | W66: 3 | Y66: Y | Z66: 2000
B67: 0.45972222 | C67: CGO 223AB07 | D67: 2 | E67: 1 | F67: ARUA | G67: ARUA | H67: UGA | I67: 5 | J67: 7 | K67: =VLOOKUP(J67,Key!$E$2:$F$9,2,FALSE) -> Hospital | L67: KAMPALA | M67: KAMPALA | N67: UGA | O67: 1 | P67: 1 | Q67: =VLOOKUP(P67,Key!$E$2:$F$9,2,FALSE) -> Home | R67: =K67&"-"&Q67 -> Hospital-Home | S67: 500 | T67: 8 | U67: 4 | Y67: Y | Z67: 1000
B68: 0.44166667 | C68: UAN 338G | D68: 1 | E68: 2 | F68: KASANGATTI | G68: WAKISO | H68: UGA | I68: 11 | J68: 4 | K68: =VLOOKUP(J68,Key!$E$2:$F$9,2,FALSE) -> Commercial | L68: KITEGOBWA | M68: WAKISO | N68: UGA | O68: 1 | P68: 1 | Q68: =VLOOKUP(P68,Key!$E$2:$F$9,2,FALSE) -> Home | R68: =K68&"-"&Q68 -> Commercial-Home | S68: 3 | T68: 0.2 | U68: 3 | Y68: Y | Z68: 1500
B69: 0.46319444 | C69: UAZ 070G | D69: 7 | E69: 2 | F69: SONDE | G69: MUKONO | H69: UGA | I69: 1 | J69: 1 | K69: =VLOOKUP(J69,Key!$E$2:$F$9,2,FALSE) -> Home | L69: MATUGGA | M69: WAKISO | N69: UGA | O69: 7 | P69: 4 | Q69: =VLOOKUP(P69,Key!$E$2:$F$9,2,FALSE) -> Commercial | R69: =K69&"-"&Q69 -> Home-Commercial | T69: 1 | U69: 4 | V69: 1 | W69: 0.1 | X69: 0.15 | Y69: Y
B70: 0.5 | C70: UAZ 124A | D70: 3 | E70: 2 | F70: KIWATULE | G70: KAMPALA | H70: UGA | I70: 9 | J70: 4 | K70: =VLOOKUP(J70,Key!$E$2:$F$9,2,FALSE) -> Commercial | L70: KITEGOBWA | M70: WAKISO | N70: UGA | O70: 1 | P70: 1 | Q70: =VLOOKUP(P70,Key!$E$2:$F$9,2,FALSE) -> Home | R70: =K70&"-"&Q70 -> Commercial-Home | S70: 20 | T70: 1 | U70: 3 | V70: 11 | Y70: Y | Z70: 1000
B71: 0.55833333 | C71: UAP 214X | D71: 4 | E71: 14 | F71: KASANGATTI | G71: WAKISO | H71: UGA | I71: 6 | J71: 4 | K71: =VLOOKUP(J71,Key!$E$2:$F$9,2,FALSE) -> Commercial | L71: MATUGGA | M71: WAKISO | N71: UGA | O71: 6 | P71: 4 | Q71: =VLOOKUP(P71,Key!$E$2:$F$9,2,FALSE) -> Commercial | R71: =K71&"-"&Q71 -> Commercial-Commercial | S71: 1.5 | T71: 0.5 | U71: 2 | Y71: Y | Z71: 3000
B72: 0.64722222 | C72: UAQ 105Y | D72: 1 | E72: 1 | F72: GAYAZA | G72: WAKISO | H72: UGA | I72: 2 | J72: 2 | K72: =VLOOKUP(J72,Key!$E$2:$F$9,2,FALSE) -> Work | L72: NANGABO | M72: WAKISO | N72: UGA | O72: 1 | P72: 1 | Q72: =VLOOKUP(P72,Key!$E$2:$F$9,2,FALSE) -> Home | R72: =K72&"-"&Q72 -> Work-Home | S72: 1.8 | T72: 0.3 | U72: 2 | Y72: Y | Z72: 2000
B73: 0.64236111 | C73: UAH 249U | D73: 1 | E73: 3 | F73: LUTEETE | G73: WAKISO | H73: UGA | I73: 1 | J73: 1 | K73: =VLOOKUP(J73,Key!$E$2:$F$9,2,FALSE) -> Home | L73: NANGABO | M73: WAKISO | N73: UGA | O73: 9 | P73: 8 | Q73: =VLOOKUP(P73,Key!$E$2:$F$9,2,FALSE) -> Others | R73: =K73&"-"&Q73 -> Home-Others | S73: 2.8 | T73: 0.5 | U73: 2 | Y73: Y | Z73: 2000
B74: 0.60555556 | C74: UAU 849U | D74: 1 | E74: 3 | F74: ENTEBBE | G74: WAKISO | H74: UGA | I74: 1 | J74: 1 | K74: =VLOOKUP(J74,Key!$E$2:$F$9,2,FALSE) -> Home | L74: KIWOKO | M74: NAKASEKE | N74: UGA | O74: 1 | P74: 1 | Q74: =VLOOKUP(P74,Key!$E$2:$F$9,2,FALSE) -> Home | R74: =K74&"-"&Q74 -> Home-Home | S74: 115 | T74: 3 | U74: 4 | Y74: Y | Z74: 5000
B75: 0.56111111 | C75: UAQ 698U | D75: 1 | E75: 4 | F75: KALAGI | G75: MUKONO | H75: UGA | I75: 1 | J75: 1 | K75: =VLOOKUP(J75,Key!$E$2:$F$9,2,FALSE) -> Home | L75: KAKIRI | M75: WAKISO | N75: UGA | O75: 16 | P75: 1 | Q75: =VLOOKUP(P75,Key!$E$2:$F$9,2,FALSE) -> Home | R75: =K75&"-"&Q75 -> Home-Home | T75: 1 | U75: 3 | Y75: Y | Z75: 3000
B76: 0.55694444 | C76: UAH 612P | D76: 7 | E76: 4 | F76: GAYAZA | G76: WAKISO | H76: UGA | I76: 11 | J76: 4 | K76: =VLOOKUP(J76,Key!$E$2:$F$9,2,FALSE) -> Commercial | L76: WAKISO | M76: WAKISO | N76: UGA | O76: 11 | P76: 4 | Q76: =VLOOKUP(P76,Key!$E$2:$F$9,2,FALSE) -> Commercial | R76: =K76&"-"&Q76 -> Commercial-Commercial | T76: 1 | U76: 1 | V76: 1 | W76: 5 | X76: 2 | Y76: Y | Z76: 10000
B77: 0.5625 | C77: UBE 710K | D77: 1 | E77: 1 | F77: KIIRA | G77: WAKISO | H77: UGA | I77: 1 | J77: 1 | K77: =VLOOKUP(J77,Key!$E$2:$F$9,2,FALSE) -> Home | L77: NANGABO | M77: WAKISO | N77: UGA | O77: 1 | P77: 1 | Q77: =VLOOKUP(P77,Key!$E$2:$F$9,2,FALSE) -> Home | R77: =K77&"-"&Q77 -> Home-Home | S77: 5 | T77: 0.3 | U77: 1 | Y77: Y | Z77: 5000
B78: 0.55277778 | C78: UAM 433D | D78: 2 | E78: 6 | F78: ENTEBBE | G78: WAKISO | H78: UGA | I78: 1 | J78: 1 | K78: =VLOOKUP(J78,Key!$E$2:$F$9,2,FALSE) -> Home | L78: NANGABO | M78: WAKISO | N78: UGA | O78: 16 | P78: 8 | Q78: =VLOOKUP(P78,Key!$E$2:$F$9,2,FALSE) -> Others | R78: =K78&"-"&Q78 -> Home-Others | U78: 6 | Y78: Y | Z78: 0
B79: 0.55 | C79: UAY 067X | D79: 1 | E79: 1 | F79: KASANGATTI | G79: WAKISO | H79: UGA | I79: 11 | J79: 4 | K79: =VLOOKUP(J79,Key!$E$2:$F$9,2,FALSE) -> Commercial | L79: KITAGOBWA | M79: WAKISO | N79: UGA | O79: 1 | P79: 1 | Q79: =VLOOKUP(P79,Key!$E$2:$F$9,2,FALSE) -> Home | R79: =K79&"-"&Q79 -> Commercial-Home | S79: 3 | T79: 0.1 | U79: 1 | Y79: Y | Z79: 1000
B80: 0.55763889 | C80: UBF 321S | D80: 1 | E80: 4 | F80: KASANGATTI | G80: WAKISO | H80: UGA | I80: 12 | J80: 4 | K80: =VLOOKUP(J80,Key!$E$2:$F$9,2,FALSE) -> Commercial | L80: NANGABWA | M80: WAKISO | N80: UGA | O80: 10 | P80: 2 | Q80: =VLOOKUP(P80,Key!$E$2:$F$9,2,FALSE) -> Work | R80: =K80&"-"&Q80 -> Commercial-Work | S80: 4 | T80: 0.1 | U80: 2 | V80: 4 | W80: 1 | X80: 2 | Y80: Y | Z80: 10000
B81: 0.43680556 | C81: UBF 416F | D81: 1 | E81: 2 | F81: KASANGATTI | G81: WAKISO | H81: UGA | I81: 11 | J81: 4 | K81: =VLOOKUP(J81,Key!$E$2:$F$9,2,FALSE) -> Commercial | L81: KITAGOBWA | M81: WAKISO | N81: UGA | O81: 1 | P81: 1 | Q81: =VLOOKUP(P81,Key!$E$2:$F$9,2,FALSE) -> Home | R81: =K81&"-"&Q81 -> Commercial-Home | S81: 5 | T81: 0.1 | U81: 1 | Y81: Y | Z81: 1000
B82: 0.60277778 | C82: UAX 703S | D82: 7 | E82: 2 | F82: KASANGATTI | G82: WAKISO | H82: UGA | I82: 12 | J82: 2 | K82: =VLOOKUP(J82,Key!$E$2:$F$9,2,FALSE) -> Work | L82: NAKASEKE | M82: LUWERO | N82: UGA | O82: 12 | P82: 2 | Q82: =VLOOKUP(P82,Key!$E$2:$F$9,2,FALSE) -> Work | R82: =K82&"-"&Q82 -> Work-Work | S82: 60 | T82: 2 | U82: 5 | V82: 1 | W82: 1.5 | X82: 2 | Y82: Y | Z82: 2000
B83: 0.60763889 | C83: UAS 362Z | D83: 1 | E83: 2 | F83: KASANGATTI | G83: WAKISO | H83: UGA | I83: 1 | J83: 1 | K83: =VLOOKUP(J83,Key!$E$2:$F$9,2,FALSE) -> Home | L83: NANGABO | M83: WAKISO | N83: UGA | O83: 2 | P83: 2 | Q83: =VLOOKUP(P83,Key!$E$2:$F$9,2,FALSE) -> Work | R83: =K83&"-"&Q83 -> Home-Work | S83: 3 | T83: 0.1 | U83: 1 | Y83: Y | Z83: 2000
B84: 0.63194444 | C84: UBB 416L | D84: 2 | E84: 2 | F84: KAMPALA | G84: KAMPALA | H84: UGA | I84: 11 | J84: 4 | K84: =VLOOKUP(J84,Key!$E$2:$F$9,2,FALSE) -> Commercial | L84: KASANGATTI | M84: WAKISO | N84: UGA | O84: 1 | P84: 1 | Q84: =VLOOKUP(P84,Key!$E$2:$F$9,2,FALSE) -> Home | R84: =K84&"-"&Q84 -> Commercial-Home | S84: 20 | T84: 1 | U84: 2 | Y84: Y | Z84: 1000
B85: 0.625 | C85: UAM 696H | D85: 1 | E85: 4 | F85: MUKONO | G85: MUKONO | H85: UGA | I85: 1 | J85: 1 | K85: =VLOOKUP(J85,Key!$E$2:$F$9,2,FALSE) -> Home | L85: KASANGATTI | M85: WAKISO | N85: UGA | O85: 1 | P85: 1 | Q85: =VLOOKUP(P85,Key!$E$2:$F$9,2,FALSE) -> Home | R85: =K85&"-"&Q85 -> Home-Home | U85: 6 | Y85: Y | Z85: 5000
B86: 0.59722222 | C86: UAP 761T | D86: 1 | E86: 2 | F86: KAMPALA | G86: KAMPALA | H86: UGA | I86: 2 | J86: 2 | K86: =VLOOKUP(J86,Key!$E$2:$F$9,2,FALSE) -> Work | L86: NANGABO | M86: WAKISO | N86: UGA | O86: 1 | P86: 1 | Q86: =VLOOKUP(P86,Key!$E$2:$F$9,2,FALSE) -> Home | R86: =K86&"-"&Q86 -> Work-Home | S86: 10 | T86: 0.7 | U86: 1 | Y86: Y | Z86: 2000
B87: 0.61666667 | C87: UAZ 693T | D87: 2 | E87: 3 | F87: BULOBA | G87: WAKISO | H87: UGA | I87: 1 | J87: 1 | K87: =VLOOKUP(J87,Key!$E$2:$F$9,2,FALSE) -> Home | L87: ARUA | M87: ARUA | N87: UGA | O87: 1 | P87: 1 | Q87: =VLOOKUP(P87,Key!$E$2:$F$9,2,FALSE) -> Home | R87: =K87&"-"&Q87 -> Home-Home | S87: 550 | T87: 8 | U87: 5 | Y87: Y | Z87: 3000
B88: 0.75138889 | C88: UBE 876Z | D88: 1 | E88: 3 | F88: NATUGG | G88: WAKISO | H88: UGA | I88: 1 | J88: 1 | K88: =VLOOKUP(J88,Key!$E$2:$F$9,2,FALSE) -> Home | L88: NATAGU | M88: WAKISO | N88: UGA | O88: 16 | P88: 6 | Q88: =VLOOKUP(P88,Key!$E$2:$F$9,2,FALSE) -> Leisure/Social | R88: =K88&"-"&Q88 -> Home-Leisure/Social | U88: 4 | Y88: Y | Z88: 1000
B89: 0.1875 | C89: UAH 726K | D89: 3 | E89: 1 | F89: KALIWAJJALA | G89: WAKISO | H89: UGA | I89: 1 | J89: 1 | K89: =VLOOKUP(J89,Key!$E$2:$F$9,2,FALSE) -> Home | L89: MAVULE | M89: WAKISO | N89: UGA | O89: 1 | P89: 1 | Q89: =VLOOKUP(P89,Key!$E$2:$F$9,2,FALSE) -> Home | R89: =K89&"-"&Q89 -> Home-Home | S89: 14 | T89: 0.3 | U89: 0.1 | Y89: Y | Z89: 0
B90: 0.73611111 | C90: UAB 801Y | D90: 1 | E90: 3 | F90: BALAMU | G90: WAKISO | H90: UGA | I90: 1 | J90: 1 | K90: =VLOOKUP(J90,Key!$E$2:$F$9,2,FALSE) -> Home | L90: NANGABO | M90: WAKISO | N90: UGA | O90: 1 | P90: 6 | Q90: =VLOOKUP(P90,Key!$E$2:$F$9,2,FALSE) -> Leisure/Social | R90: =K90&"-"&Q90 -> Home-Leisure/Social | S90: 3 | T90: 0.1 | U90: 2 | Y90: Y | Z90: 3000
B91: 0.48958333 | C91: UAQ 283T | D91: 1 | E91: 3 | F91: KYALIWAJJALA | G91: KAMPALA | H91: UGA | I91: 1 | J91: 1 | K91: =VLOOKUP(J91,Key!$E$2:$F$9,2,FALSE) -> Home | L91: WOBULENZI | M91: WAKISO | N91: UGA | O91: 4 | P91: 1 | Q91: =VLOOKUP(P91,Key!$E$2:$F$9,2,FALSE) -> Home | R91: =K91&"-"&Q91 -> Home-Home | S91: 60 | T91: 1 | U91: 2 | Y91: Y | Z91: 1000
B92: 0.49305556 | C92: UAZ 835C | D92: 7 | E92: 2 | F92: KAMPALA | G92: KAMPALA | H92: UGA | I92: 12 | J92: 4 | K92: =VLOOKUP(J92,Key!$E$2:$F$9,2,FALSE) -> Commercial | L92: KIJUDE | M92: WAKISO | N92: UGA | O92: 1 | P92: 1 | Q92: =VLOOKUP(P92,Key!$E$2:$F$9,2,FALSE) -> Home | R92: =K92&"-"&Q92 -> Commercial-Home | U92: 2 | Y92: Y | Z92: 1000

Sheet 14.10 MATUGGA-KASANGATI
B1: Consultancy services for Preparation of Expressway Develo PMent Master Plan (EDMP) for Uganda
B2: Roadside OD Interview Survey
B4: Date: | C4: ='14.10 KASANGATI-MATUGGA'!C4 -> 14.10.19 | E4: Road Ne: | F4: ='14.10 KASANGATI-MATUGGA'!F4:G4 -> MATUGGA-WAKISO ROAD | I4: Direction From: | L4: MATUGGA | N4: Interviewers: | O4: KASOMA JP, JAL | V4: Supervisor: | W4: ='14.10 KASANGATI-MATUGGA'!W4 -> ANDREW | Y4: Coded By: | Z4: ='14.10 KASANGATI-MATUGGA'!Z4 -> DAVID | AA4: Chkd By: | AB4: Bakole Deo
I5: Direction To: | L5: KASANGATI
B7: Time | C7: Veh_Reg_No. | D7: Veh_Type | E7: No. Occupants | F7: Origin_Address | I7: Origin_Establish | J7: Origin_Purpose | K7: Origin-Purpose Desc | L7: Destination_Address | O7: Destination_Establish | P7: Destination_Purpose | Q7: Destination_Purpose Desc | R7: Journey_Purpose | S7: Approx_Distance (Km) | T7: Approx_Journey Time (Hrs) | U7: Trip_Frequency | V7: GOODS VEHICLES ONLY | Y7: Would You Use Xpressways? | Z7: Pay How Much? (UGX) | AA7: Origin_Zone | AB7: Dest_Zone
F8: Village or Town | G8: District | H8: Country | L8: Village or Town | M8: District | N8: Country | V8: Goods_Type | W8: Goods_Quantity (Ton) | X8: Goods_Value (UGXm)
B9: 0.34444444 | C9: UAY 261Q | D9: 4 | E9: 6 | F9: KITAGOBWA | G9: WAKISO | H9: UGA | I9: 1 | J9: 1 | K9: =VLOOKUP(J9,Key!$E$2:$F$9,2,FALSE) -> Home | L9: KITETIKA | M9: WAKISO | N9: UGA | O9: 2 | P9: 2 | Q9: =VLOOKUP(P9,Key!$E$2:$F$9,2,FALSE) -> Work | R9: =K9&"-"&Q9 -> Home-Work | T9: 0.5 | U9: 2 | Y9: Y | Z9: 3000
B10: 0.34583333 | C10: UAS 784H | D10: 1 | E10: 3 | F10: MASOOLI | G10: WAKISO | H10: UGA | I10: 1 | J10: 1 | K10: =VLOOKUP(J10,Key!$E$2:$F$9,2,FALSE) -> Home | L10: KASANGATI | M10: WAKISO | N10: UGA | O10: 11 | P10: 2 | Q10: =VLOOKUP(P10,Key!$E$2:$F$9,2,FALSE) -> Work | R10: =K10&"-"&Q10 -> Home-Work | T10: 0.3 | U10: 2 | Y10: Y | Z10: 0
B11: 0.34930556 | C11: UBA 898Z | D11: 1 | E11: 1 | F11: MATUGGA | G11: WAKISO | H11: UGA | I11: 1 | J11: 1 | K11: =VLOOKUP(J11,Key!$E$2:$F$9,2,FALSE) -> Home | L11: KIREKA | M11: WAKISO | N11: UGA | O11: 4 | P11: 2 | Q11: =VLOOKUP(P11,Key!$E$2:$F$9,2,FALSE) -> Work | R11: =K11&"-"&Q11 -> Home-Work | T11: 1 | U11: 2 | Y11: Y | Z11: 0
B12: 0.35208333 | C12: UAJ 010W | D12: 1 | E12: 2 | F12: BBA | G12: WAKISO | H12: UGA | I12: 1 | J12: 1 | K12: =VLOOKUP(J12,Key!$E$2:$F$9,2,FALSE) -> Home | L12: NTINDA | M12: KPALA | N12: UGA | O12: 2 | P12: 2 | Q12: =VLOOKUP(P12,Key!$E$2:$F$9,2,FALSE) -> Work | R12: =K12&"-"&Q12 -> Home-Work | T12: 1 | U12: 2 | Y12: Y | Z12: 0
B13: 0.35416667 | C13: UAF 525D | D13: 1 | E13: 2 | F13: KITI | G13: WAKISO | H13: UGA | I13: 1 | J13: 1 | K13: =VLOOKUP(J13,Key!$E$2:$F$9,2,FALSE) -> Home | L13: KPALA | M13: KPALA | N13: UGA | O13: 2 | P13: 2 | Q13: =VLOOKUP(P13,Key!$E$2:$F$9,2,FALSE) -> Work | R13: =K13&"-"&Q13 -> Home-Work | Y13: Y
B14: 0.35833333 | C14: UBB 224F | D14: 1 | E14: 1 | F14: KINAAWA | G14: WAKISO | H14: UGA | I14: 4 | J14: 2 | K14: =VLOOKUP(J14,Key!$E$2:$F$9,2,FALSE) -> Work | L14: KASANGATI | M14: WAKISO | N14: UGA | O14: 11 | P14: 2 | Q14: =VLOOKUP(P14,Key!$E$2:$F$9,2,FALSE) -> Work | R14: =K14&"-"&Q14 -> Work-Work | S14: 1 | T14: 0.1 | U14: 2 | Y14: Y | Z14: 1000
B15: 0.3625 | C15: UAV 442M | D15: 7 | E15: 1 | F15: NANGABO | G15: WAKISO | H15: UGA | I15: 1 | J15: 1 | K15: =VLOOKUP(J15,Key!$E$2:$F$9,2,FALSE) -> Home | L15: KASANGATI | M15: WAKISO | N15: UGA | O15: 6 | P15: 2 | Q15: =VLOOKUP(P15,Key!$E$2:$F$9,2,FALSE) -> Work | R15: =K15&"-"&Q15 -> Home-Work | T15: 0.1 | U15: 6 | Y15: Y | Z15: 300
B16: 0.36458333 | C16: UAG 421Q | D16: 4 | E16: 16 | F16: MATUGGA | G16: WAKISO | H16: UGA | I16: 6 | J16: 2 | K16: =VLOOKUP(J16,Key!$E$2:$F$9,2,FALSE) -> Work | L16: KASANGATI | M16: WAKISO | N16: UGA | O16: 6 | P16: 2 | Q16: =VLOOKUP(P16,Key!$E$2:$F$9,2,FALSE) -> Work | R16: =K16&"-"&Q16 -> Work-Work | T16: 0.1 | U16: 1 | Y16: Y | Z16: 0
B17: 0.36805556 | C17: UAT 402Q | D17: 1 | E17: 2 | F17: MASOOLI | G17: WAKISO | H17: UGA | I17: 1 | J17: 1 | K17: =VLOOKUP(J17,Key!$E$2:$F$9,2,FALSE) -> Home | L17: KASANGATI | M17: WAKISO | N17: UGA | O17: 2 | P17: 4 | Q17: =VLOOKUP(P17,Key!$E$2:$F$9,2,FALSE) -> Commercial | R17: =K17&"-"&Q17 -> Home-Commercial | T17: 0.1 | U17: 2 | Y17: Y | Z17: 0
B18: 0.37291667 | C18: UAK 103A | D18: 2 | E18: 4 | F18: KITEGOMBWA | G18: WAKISO | H18: UGA | I18: 1 | J18: 1 | K18: =VLOOKUP(J18,Key!$E$2:$F$9,2,FALSE) -> Home | L18: NTINDA | M18: KPALA | N18: UGA | O18: 10 | P18: 2 | Q18: =VLOOKUP(P18,Key!$E$2:$F$9,2,FALSE) -> Work | R18: =K18&"-"&Q18 -> Home-Work | T18: 0.7 | U18: 2 | Y18: Y | Z18: 3000
B19: 0.38888889 | C19: UAF 241S | D19: 1 | E19: 1 | F19: KITEGOMBWA | G19: WAKISO | H19: UGA | I19: 1 | J19: 1 | K19: =VLOOKUP(J19,Key!$E$2:$F$9,2,FALSE) -> Home | L19: KISAASI | M19: KPALA | N19: UGA | O19: 11 | P19: 2 | Q19: =VLOOKUP(P19,Key!$E$2:$F$9,2,FALSE) -> Work | R19: =K19&"-"&Q19 -> Home-Work | T19: 0.7 | U19: 2 | Y19: Y | Z19: 1000
B20: 0.38055556 | C20: UAY 391W | D20: 1 | E20: 1 | F20: NANGABO | G20: WAKISO | H20: UGA | I20: 1 | J20: 1 | K20: =VLOOKUP(J20,Key!$E$2:$F$9,2,FALSE) -> Home | L20: KPALA | M20: KPALA | N20: UGA | O20: 2 | P20: 2 | Q20: =VLOOKUP(P20,Key!$E$2:$F$9,2,FALSE) -> Work | R20: =K20&"-"&Q20 -> Home-Work | S20: 16 | T20: 1 | U20: 2 | Y20: Y | Z20: 1000
B21: 0.38263889 | C21: UBD 756A | D21: 7 | E21: 2 | F21: NANGABO | G21: WAKISO | H21: UGA | I21: 11 | J21: 4 | K21: =VLOOKUP(J21,Key!$E$2:$F$9,2,FALSE) -> Commercial | L21: GAYAZA | M21: WAKISO | N21: UGA | O21: 11 | P21: 4 | Q21: =VLOOKUP(P21,Key!$E$2:$F$9,2,FALSE) -> Commercial | R21: =K21&"-"&Q21 -> Commercial-Commercial | T21: 0.1 | Y21: Y | Z21: 0
B22: 0.38472222 | C22: UAS 330Y | D22: 2 | E22: 2 | F22: MASOOLI | G22: WAKISO | H22: UGA | I22: 1 | J22: 1 | K22: =VLOOKUP(J22,Key!$E$2:$F$9,2,FALSE) -> Home | L22: KASANGATI | M22: WAKISO | N22: UGA | O22: 11 | P22: 2 | Q22: =VLOOKUP(P22,Key!$E$2:$F$9,2,FALSE) -> Work | R22: =K22&"-"&Q22 -> Home-Work | T22: 0.1 | Y22: Y | Z22: 0
B23: 0.3875 | C23: UBD 644W | D23: 1 | E23: 2 | F23: NANGABO | G23: WAKISO | H23: UGA | I23: 1 | J23: 1 | K23: =VLOOKUP(J23,Key!$E$2:$F$9,2,FALSE) -> Home | L23: KASANGATI | M23: WAKISO | N23: UGA | O23: 4 | P23: 2 | Q23: =VLOOKUP(P23,Key!$E$2:$F$9,2,FALSE) -> Work | R23: =K23&"-"&Q23 -> Home-Work | T23: 0.1 | U23: 2 | Y23: Y | Z23: 2000
B24: 0.38958333 | C24: UAG 507E | D24: 1 | E24: 2 | F24: NANGABO | G24: WAKISO | H24: UGA | I24: 1 | J24: 1 | K24: =VLOOKUP(J24,Key!$E$2:$F$9,2,FALSE) -> Home | L24: KASANGATI | M24: WAKISO | N24: UGA | O24: 11 | P24: 6 | Q24: =VLOOKUP(P24,Key!$E$2:$F$9,2,FALSE) -> Leisure/Social | R24: =K24&"-"&Q24 -> Home-Leisure/Social | T24: 0.1 | U24: 6 | Y24: Y | Z24: 0
B25: 0.39236111 | C25: UBA 316R | D25: 1 | E25: 1 | F25: KITI | G25: WAKISO | H25: UGA | I25: 1 | J25: 1 | K25: =VLOOKUP(J25,Key!$E$2:$F$9,2,FALSE) -> Home | L25: KPALA | M25: KPALA | N25: UGA | O25: 2 | P25: 2 | Q25: =VLOOKUP(P25,Key!$E$2:$F$9,2,FALSE) -> Work | R25: =K25&"-"&Q25 -> Home-Work | S25: 18 | T25: 1 | U25: 2 | Y25: Y | Z25: 0
B26: 0.39444444 | C26: UAP 324Y | D26: 1 | E26: 1 | F26: NANGABO | G26: WAKISO | H26: UGA | I26: 4 | J26: 6 | K26: =VLOOKUP(J26,Key!$E$2:$F$9,2,FALSE) -> Leisure/Social | L26: BWAISE | M26: KPALA | N26: UGA | O26: 11 | P26: 4 | Q26: =VLOOKUP(P26,Key!$E$2:$F$9,2,FALSE) -> Commercial | R26: =K26&"-"&Q26 -> Leisure/Social-Commercial | T26: 0.5 | U26: 6 | Y26: Y | Z26: 2000
B27: 0.39722222 | C27: UAQ 771G | D27: 1 | E27: 4 | F27: NANGABO | G27: WAKISO | H27: UGA | I27: 1 | J27: 1 | K27: =VLOOKUP(J27,Key!$E$2:$F$9,2,FALSE) -> Home | L27: KPALA | M27: KPALA | N27: UGA | O27: 11 | P27: 2 | Q27: =VLOOKUP(P27,Key!$E$2:$F$9,2,FALSE) -> Work | R27: =K27&"-"&Q27 -> Home-Work | S27: 16 | T27: 1 | U27: 2 | Y27: Y | Z27: 2000
B28: 0.4 | C28: UAW 992Y | D28: 1 | E28: 1 | F28: NANGABO | G28: WAKISO | H28: UGA | I28: 4 | J28: 2 | K28: =VLOOKUP(J28,Key!$E$2:$F$9,2,FALSE) -> Work | L28: KASANGATI | M28: WAKISO | N28: UGA | O28: 11 | P28: 6 | Q28: =VLOOKUP(P28,Key!$E$2:$F$9,2,FALSE) -> Leisure/Social | R28: =K28&"-"&Q28 -> Work-Leisure/Social | T28: 0.1 | U28: 6 | Y28: Y | Z28: 0
B29: 0.40208333 | C29: UBD 811R | D29: 1 | E29: 1 | F29: KITEGOMBWA | G29: WAKISO | H29: UGA | I29: 1 | J29: 1 | K29: =VLOOKUP(J29,Key!$E$2:$F$9,2,FALSE) -> Home | L29: GGABA | M29: KPALA | N29: UGA | O29: 16 | P29: 6 | Q29: =VLOOKUP(P29,Key!$E$2:$F$9,2,FALSE) -> Leisure/Social | R29: =K29&"-"&Q29 -> Home-Leisure/Social | T29: 1 | U29: 6 | Y29: Y | Z29: 5000
B30: 0.40555556 | C30: UBD 916G | D30: 1 | E30: 1 | F30: MAYIRIKITI | G30: WAKISO | H30: UGA | I30: 1 | J30: 1 | K30: =VLOOKUP(J30,Key!$E$2:$F$9,2,FALSE) -> Home | L30: MULAGO | M30: KPALA | N30: UGA | O30: 5 | P30: 2 | Q30: =VLOOKUP(P30,Key!$E$2:$F$9,2,FALSE) -> Work | R30: =K30&"-"&Q30 -> Home-Work | T30: 1 | U30: 2 | Y30: Y | Z30: 2000
B31: 0.41041667 | C31: UAS 966Y | D31: 1 | E31: 3 | F31: NANGABO | G31: WAKISO | H31: UGA | I31: 4 | J31: 2 | K31: =VLOOKUP(J31,Key!$E$2:$F$9,2,FALSE) -> Work | L31: KASANGATI | M31: WAKISO | N31: UGA | O31: 11 | P31: 6 | Q31: =VLOOKUP(P31,Key!$E$2:$F$9,2,FALSE) -> Leisure/Social | R31: =K31&"-"&Q31 -> Work-Leisure/Social | T31: 0.1 | U31: 3 | Y31: Y | Z31: 10000
B32: 0.41319444 | C32: UAE 615F | D32: 3 | E32: 1 | F32: NANGABO | G32: WAKISO | H32: UGA | I32: 9 | J32: 1 | K32: =VLOOKUP(J32,Key!$E$2:$F$9,2,FALSE) -> Home | L32: KASANGATI | M32: WAKISO | N32: UGA | O32: 9 | P32: 4 | Q32: =VLOOKUP(P32,Key!$E$2:$F$9,2,FALSE) -> Commercial | R32: =K32&"-"&Q32 -> Home-Commercial | S32: 1 | T32: 0.5 | U32: 2 | Y32: Y | Z32: 4000
B33: 0.41944444 | C33: UAP 094N | D33: 1 | E33: 2 | F33: MATUGGA | G33: WAKISO | H33: UGA | I33: 1 | J33: 1 | K33: =VLOOKUP(J33,Key!$E$2:$F$9,2,FALSE) -> Home | L33: KASANGATI | M33: WAKISO | N33: UGA | O33: 16 | P33: 3 | Q33: =VLOOKUP(P33,Key!$E$2:$F$9,2,FALSE) -> Study | R33: =K33&"-"&Q33 -> Home-Study | T33: 0.4 | U33: 3 | Y33: Y | Z33: 2000
B34: 0.42291667 | C34: UBA 410K | D34: 1 | E34: 3 | F34: NANGABO | G34: WAKISO | H34: UGA | I34: 1 | J34: 1 | K34: =VLOOKUP(J34,Key!$E$2:$F$9,2,FALSE) -> Home | L34: JINJA | M34: JINJA | N34: UGA | O34: 16 | P34: 6 | Q34: =VLOOKUP(P34,Key!$E$2:$F$9,2,FALSE) -> Leisure/Social | R34: =K34&"-"&Q34 -> Home-Leisure/Social | T34: 3 | U34: 6 | Y34: Y | Z34: 3000
B35: 0.42638889 | C35: UAQ 442J | D35: 1 | E35: 1 | F35: MASOOLI | G35: WAKISO | H35: UGA | I35: 1 | J35: 1 | K35: =VLOOKUP(J35,Key!$E$2:$F$9,2,FALSE) -> Home | L35: MASOOLI | M35: WAKISO | N35: UGA | O35: 2 | P35: 2 | Q35: =VLOOKUP(P35,Key!$E$2:$F$9,2,FALSE) -> Work | R35: =K35&"-"&Q35 -> Home-Work | T35: 0.1 | U35: 2 | Y35: Y | Z35: 3000
B36: 0.42916667 | C36: UAR 390D | D36: 1 | E36: 2 | F36: KITEGOMBWA | G36: WAKISO | H36: UGA | I36: 1 | J36: 1 | K36: =VLOOKUP(J36,Key!$E$2:$F$9,2,FALSE) -> Home | L36: MAKERERE | M36: KPALA | N36: UGA | O36: 4 | P36: 2 | Q36: =VLOOKUP(P36,Key!$E$2:$F$9,2,FALSE) -> Work | R36: =K36&"-"&Q36 -> Home-Work | S36: 25 | T36: 0.7 | U36: 2 | Y36: Y | Z36: 1000
B37: 0.43888889 | C37: UAF 246D | D37: 7 | E37: 1 | F37: KITEGOMBWA | G37: WAKISO | H37: UGA | I37: 9 | J37: 1 | K37: =VLOOKUP(J37,Key!$E$2:$F$9,2,FALSE) -> Home | L37: BULU | M37: WAKISO | N37: UGA | O37: 6 | P37: 2 | Q37: =VLOOKUP(P37,Key!$E$2:$F$9,2,FALSE) -> Work | R37: =K37&"-"&Q37 -> Home-Work | S37: 8 | T37: 0.2 | U37: 6 | Y37: Y | Z37: 3000
B38: 0.43472222 | C38: UAU 196H | D38: 4 | E38: 10 | F38: WAKISO | G38: WAKISO | H38: UGA | I38: 6 | J38: 2 | K38: =VLOOKUP(J38,Key!$E$2:$F$9,2,FALSE) -> Work | L38: KASANGATI | M38: WAKISO | N38: UGA | O38: 6 | P38: 2 | Q38: =VLOOKUP(P38,Key!$E$2:$F$9,2,FALSE) -> Work | R38: =K38&"-"&Q38 -> Work-Work | T38: 0.5 | U38: 1 | Y38: Y | Z38: 0
B39: 0.43263889 | C39: UAF 246D | D39: 7 | E39: 1 | F39: KITEGOMBWA | G39: WAKISO | H39: UGA | I39: 9 | J39: 1 | K39: =VLOOKUP(J39,Key!$E$2:$F$9,2,FALSE) -> Home | L39: BULU | M39: WAKISO | N39: UGA | O39: 6 | P39: 2 | Q39: =VLOOKUP(P39,Key!$E$2:$F$9,2,FALSE) -> Work | R39: =K39&"-"&Q39 -> Home-Work | S39: 8 | T39: 0.2 | U39: 6 | Y39: Y | Z39: 3000
B40: 0.43958333 | C40: UAD 945M | D40: 2 | E40: 1 | F40: MATUGGA | G40: WAKISO | H40: UGA | I40: 1 | J40: 1 | K40: =VLOOKUP(J40,Key!$E$2:$F$9,2,FALSE) -> Home | L40: KALACOL | M40: MUKONO | N40: UGA | O40: 9 | P40: 2 | Q40: =VLOOKUP(P40,Key!$E$2:$F$9,2,FALSE) -> Work | R40: =K40&"-"&Q40 -> Home-Work | T40: 2 | U40: 3 | Y40: Y | Z40: 0
B41: 0.44444444 | C41: UBB 492Z | D41: 7 | E41: 3 | F41: BUWBO | G41: WAKISO | H41: UGA | I41: 11 | J41: 4 | K41: =VLOOKUP(J41,Key!$E$2:$F$9,2,FALSE) -> Commercial | L41: GAYAZA | M41: WAKISO | N41: UGA | O41: 11 | P41: 4 | Q41: =VLOOKUP(P41,Key!$E$2:$F$9,2,FALSE) -> Commercial | R41: =K41&"-"&Q41 -> Commercial-Commercial | T41: 0.5 | U41: 1 | V41: 10 | Y41: Y | Z41: 500
B42: 0.44861111 | C42: UAZ 807C | D42: 7 | E42: 2 | F42: NANGABO | G42: WAKISO | H42: UGA | I42: 1 | J42: 1 | K42: =VLOOKUP(J42,Key!$E$2:$F$9,2,FALSE) -> Home | L42: KASANGATI | M42: WAKISO | N42: UGA | O42: 6 | P42: 2 | Q42: =VLOOKUP(P42,Key!$E$2:$F$9,2,FALSE) -> Work | R42: =K42&"-"&Q42 -> Home-Work | T42: 0.1 | U42: 2 | Y42: Y | Z42: 0
B43: 0.45 | C43: UBD 715R | D43: 1 | E43: 1 | F43: WAKISO | G43: WAKISO | H43: UGA | I43: 16 | J43: 1 | K43: =VLOOKUP(J43,Key!$E$2:$F$9,2,FALSE) -> Home | L43: KIIRA | M43: WAKISO | N43: UGA | O43: 2 | P43: 2 | Q43: =VLOOKUP(P43,Key!$E$2:$F$9,2,FALSE) -> Work | R43: =K43&"-"&Q43 -> Home-Work | T43: 0.5 | U43: 6 | Y43: Y | Z43: 2000]
B44: 0.45486111 | C44: UAY 012M | D44: 3 | E44: 1 | F44: BULOBA | G44: WAKISO | H44: UGA | I44: 1 | J44: 1 | K44: =VLOOKUP(J44,Key!$E$2:$F$9,2,FALSE) -> Home | L44: KASANGATI | M44: WAKISO | N44: UGA | O44: 16 | P44: 6 | Q44: =VLOOKUP(P44,Key!$E$2:$F$9,2,FALSE) -> Leisure/Social | R44: =K44&"-"&Q44 -> Home-Leisure/Social | T44: 0.7 | U44: 6 | Y44: Y | Z44: 1000
B45: 0.45833333 | C45: UAS 218W | D45: 1 | E45: 1 | F45: NANGABO | G45: WAKISO | H45: UGA | I45: 1 | J45: 1 | K45: =VLOOKUP(J45,Key!$E$2:$F$9,2,FALSE) -> Home | L45: KPALA | M45: KPALA | N45: UGA | O45: 11 | P45: 2 | Q45: =VLOOKUP(P45,Key!$E$2:$F$9,2,FALSE) -> Work | R45: =K45&"-"&Q45 -> Home-Work | S45: 17 | T45: 0.5 | U45: 2 | Y45: Y | Z45: 0
B46: 0.46180556 | C46: UBB 085Q | D46: 7 | E46: 2 | F46: NANGABO | G46: WAKISO | H46: UGA | I46: 4 | J46: 2 | K46: =VLOOKUP(J46,Key!$E$2:$F$9,2,FALSE) -> Work | L46: KASANGATI | M46: WAKISO | N46: UGA | O46: 11 | P46: 6 | Q46: =VLOOKUP(P46,Key!$E$2:$F$9,2,FALSE) -> Leisure/Social | R46: =K46&"-"&Q46 -> Work-Leisure/Social | S46: 1 | T46: 0.1 | U46: 2 | Y46: Y | Z46: 3000
B47: 0.46805556 | C47: UBF 806Q | D47: 7 | E47: 1 | F47: WAKISO | G47: WAKISO | H47: UGA | I47: 1 | J47: 1 | K47: =VLOOKUP(J47,Key!$E$2:$F$9,2,FALSE) -> Home | L47: MAGUGYE | M47: WAKISO | N47: UGA | O47: 3 | P47: 2 | Q47: =VLOOKUP(P47,Key!$E$2:$F$9,2,FALSE) -> Work | R47: =K47&"-"&Q47 -> Home-Work | T47: 1 | U47: 6 | Y47: Y | Z47: 0
B48: 0.47361111 | C48: UBD 946P | D48: 1 | E48: 1 | F48: MAVVULE | G48: WAKISO | H48: UGA | I48: 1 | J48: 1 | K48: =VLOOKUP(J48,Key!$E$2:$F$9,2,FALSE) -> Home | L48: KPALA | M48: KPALA | N48: UGA | O48: 11 | P48: 2 | Q48: =VLOOKUP(P48,Key!$E$2:$F$9,2,FALSE) -> Work | R48: =K48&"-"&Q48 -> Home-Work | S48: 20 | T48: 0.7 | U48: 2 | Y48: Y | Z48: 1000
B49: 0.47777778 | C49: UAS 798N | D49: 1 | E49: 1 | F49: NANGABO | G49: WAKISO | H49: UGA | I49: 1 | J49: 1 | K49: =VLOOKUP(J49,Key!$E$2:$F$9,2,FALSE) -> Home | L49: GAYAZA | M49: WAKISO | N49: UGA | O49: 11 | P49: 6 | Q49: =VLOOKUP(P49,Key!$E$2:$F$9,2,FALSE) -> Leisure/Social | R49: =K49&"-"&Q49 -> Home-Leisure/Social | T49: 0.2 | U49: 3 | Y49: Y | Z49: 5000
B50: 0.48263889 | C50: UAY 446Q | D50: 1 | E50: 1 | F50: KITI | G50: WAKISO | H50: UGA | I50: 1 | J50: 1 | K50: =VLOOKUP(J50,Key!$E$2:$F$9,2,FALSE) -> Home | L50: GAYAZA | M50: WAKISO | N50: UGA | O50: 11 | P50: 6 | Q50: =VLOOKUP(P50,Key!$E$2:$F$9,2,FALSE) -> Leisure/Social | R50: =K50&"-"&Q50 -> Home-Leisure/Social | T50: 0.2 | U50: 6 | Y50: Y | Z50: 0
B51: 0.49305556 | C51: UBA 671N | D51: 1 | E51: 1 | F51: NALUSUGA | G51: WAKISO | H51: UGA | I51: 1 | J51: 1 | K51: =VLOOKUP(J51,Key!$E$2:$F$9,2,FALSE) -> Home | L51: KPALA | M51: KPALA | N51: UGA | O51: 11 | P51: 2 | Q51: =VLOOKUP(P51,Key!$E$2:$F$9,2,FALSE) -> Work | R51: =K51&"-"&Q51 -> Home-Work | S51: 20 | T51: 0.3 | U51: 2 | Y51: Y | Z51: 1000
B52: 0.50277778 | C52: UAV 323Y | D52: 7 | E52: 2 | F52: WAKISO | G52: WAKISO | H52: UGA | I52: 14 | J52: 4 | K52: =VLOOKUP(J52,Key!$E$2:$F$9,2,FALSE) -> Commercial | L52: KASANGATI | M52: WAKISO | N52: UGA | O52: 14 | P52: 4 | Q52: =VLOOKUP(P52,Key!$E$2:$F$9,2,FALSE) -> Commercial | R52: =K52&"-"&Q52 -> Commercial-Commercial | T52: 1 | U52: 6 | V52: 6 | W52: 1.5 | Y52: Y | Z52: 0
B53: 0.50972222 | C53: UAK 009K | D53: 1 | E53: 1 | F53: KITI | G53: WAKISO | H53: UGA | I53: 1 | J53: 1 | K53: =VLOOKUP(J53,Key!$E$2:$F$9,2,FALSE) -> Home | L53: KIIRA | M53: WAKISO | N53: UGA | O53: 4 | P53: 2 | Q53: =VLOOKUP(P53,Key!$E$2:$F$9,2,FALSE) -> Work | R53: =K53&"-"&Q53 -> Home-Work | T53: 0.5 | U53: 2 | Y53: Y | Z53: 0
B54: 0.5125 | C54: UAX 408Q | D54: 1 | E54: 2 | F54: NANGABO | G54: WAKISO | H54: UGA | I54: 16 | J54: 6 | K54: =VLOOKUP(J54,Key!$E$2:$F$9,2,FALSE) -> Leisure/Social | L54: KIIRA | M54: WAKISO | N54: UGA | O54: 3 | P54: 2 | Q54: =VLOOKUP(P54,Key!$E$2:$F$9,2,FALSE) -> Work | R54: =K54&"-"&Q54 -> Leisure/Social-Work | S54: 2 | T54: 0.1 | U54: 6 | Y54: Y | Z54: 1000
B55: 0.52638889 | C55: UAT 386D | D55: 1 | E55: 2 | F55: NANGABO | G55: WAKISO | H55: UGA | I55: 1 | J55: 1 | K55: =VLOOKUP(J55,Key!$E$2:$F$9,2,FALSE) -> Home | L55: KPALA | M55: KPALA | N55: UGA | O55: 11 | P55: 2 | Q55: =VLOOKUP(P55,Key!$E$2:$F$9,2,FALSE) -> Work | R55: =K55&"-"&Q55 -> Home-Work | S55: 1 | T55: 0.5 | Y55: Y | Z55: 5000
B56: 0.52777778 | C56: UBE 206J | D56: 7 | E56: 2 | F56: WOBULENZI | G56: WAKISO | H56: UGA | I56: 9 | J56: 4 | K56: =VLOOKUP(J56,Key!$E$2:$F$9,2,FALSE) -> Commercial | L56: KISENYI | M56: KPALA | N56: UGA | O56: 11 | P56: 4 | Q56: =VLOOKUP(P56,Key!$E$2:$F$9,2,FALSE) -> Commercial | R56: =K56&"-"&Q56 -> Commercial-Commercial | T56: 1 | U56: 4 | Y56: Y | Z56: 3000
B57: 0.53819444 | C57: UBF 281K | D57: 7 | E57: 2 | F57: MATUGGA | G57: WAKISO | H57: UGA | I57: 11 | J57: 4 | K57: =VLOOKUP(J57,Key!$E$2:$F$9,2,FALSE) -> Commercial | L57: LUGAZI | M57: BUIKWE | N57: UGA | O57: 3 | P57: 4 | Q57: =VLOOKUP(P57,Key!$E$2:$F$9,2,FALSE) -> Commercial | R57: =K57&"-"&Q57 -> Commercial-Commercial | T57: 1.5 | U57: 4 | V57: 5 | W57: 4 | Y57: Y | Z57: 5000
B58: 0.54722222 | C58: UAW 140X | D58: 3 | E58: 5 | F58: MATUGGA | G58: WAKISO | H58: UGA | I58: 3 | J58: 2 | K58: =VLOOKUP(J58,Key!$E$2:$F$9,2,FALSE) -> Work | L58: KASANGATI | M58: WAKISO | N58: UGA | O58: 4 | P58: 2 | Q58: =VLOOKUP(P58,Key!$E$2:$F$9,2,FALSE) -> Work | R58: =K58&"-"&Q58 -> Work-Work | T58: 0.7 | U58: 6 | V58: 1 | W58: 1 | Y58: Y | Z58: 1000
B59: 0.55555556 | C59: UBF 325M | D59: 1 | E59: 2 | F59: KITI | G59: WAKISO | H59: UGA | I59: 1 | J59: 1 | K59: =VLOOKUP(J59,Key!$E$2:$F$9,2,FALSE) -> Home | L59: KPALA | M59: KPALA | N59: UGA | O59: 2 | P59: 8 | Q59: =VLOOKUP(P59,Key!$E$2:$F$9,2,FALSE) -> Others | R59: =K59&"-"&Q59 -> Home-Others | T59: 1 | U59: 6 | Y59: Y | Z59: 1000
B60: 0.059027778 | C60: UAQ 44A | D60: 1 | E60: 1 | F60: NANGABO | G60: WAKISO | H60: UGA | I60: 2 | J60: 2 | K60: =VLOOKUP(J60,Key!$E$2:$F$9,2,FALSE) -> Work | L60: KASANGATI | M60: WAKISO | N60: UGA | O60: 11 | P60: 6 | Q60: =VLOOKUP(P60,Key!$E$2:$F$9,2,FALSE) -> Leisure/Social | R60: =K60&"-"&Q60 -> Work-Leisure/Social | T60: 0.1 | U60: 2 | Y60: Y | Z60: 0
B61: 0.56388889 | C61: UBD 985R | D61: 1 | E61: 2 | F61: MAWULE | G61: WAKISO | H61: UGA | I61: 16 | J61: 2 | K61: =VLOOKUP(J61,Key!$E$2:$F$9,2,FALSE) -> Work | L61: KASANGATI | M61: WAKISO | N61: UGA | O61: 1 | P61: 1 | Q61: =VLOOKUP(P61,Key!$E$2:$F$9,2,FALSE) -> Home | R61: =K61&"-"&Q61 -> Work-Home | T61: 0.2 | U61: 6 | Y61: Y | Z61: 500
B62: 0.56944444 | C62: UAW 147L | D62: 1 | E62: 1 | F62: NANGABO | G62: WAKISO | H62: UGA | I62: 16 | J62: 6 | K62: =VLOOKUP(J62,Key!$E$2:$F$9,2,FALSE) -> Leisure/Social | L62: KASANGATI | M62: WAKISO | N62: UGA | O62: 11 | P62: 4 | Q62: =VLOOKUP(P62,Key!$E$2:$F$9,2,FALSE) -> Commercial | R62: =K62&"-"&Q62 -> Leisure/Social-Commercial | S62: 1 | T62: 0.1 | U62: 1 | Y62: Y | Z62: 5000
B63: 0.61527778 | C63: UAZ 244P | D63: 1 | E63: 2 | F63: MATUGGA | G63: WAKISO | H63: UGA | I63: 1 | J63: 1 | K63: =VLOOKUP(J63,Key!$E$2:$F$9,2,FALSE) -> Home | L63: KPALA | M63: KPALA | N63: UGA | O63: 11 | P63: 2 | Q63: =VLOOKUP(P63,Key!$E$2:$F$9,2,FALSE) -> Work | R63: =K63&"-"&Q63 -> Home-Work | S63: 30 | T63: 1 | U63: 2 | Y63: Y | Z63: 5000
B64: 0.57638889 | C64: UAZ 001A | D64: 1 | E64: 1 | F64: NAKANAKU | G64: WAKISO | H64: UGA | I64: 1 | J64: 1 | K64: =VLOOKUP(J64,Key!$E$2:$F$9,2,FALSE) -> Home | L64: GAYAZA | M64: WAKISO | N64: UGA | O64: 11 | P64: 2 | Q64: =VLOOKUP(P64,Key!$E$2:$F$9,2,FALSE) -> Work | R64: =K64&"-"&Q64 -> Home-Work | T64: 0.2 | U64: 2 | Y64: Y | Z64: 4000
B65: 0.58333333 | C65: UAY 437N | D65: 7 | E65: 3 | F65: MATUGGA | G65: WAKISO | H65: UGA | I65: 11 | J65: 4 | K65: =VLOOKUP(J65,Key!$E$2:$F$9,2,FALSE) -> Commercial | L65: KASANGATI | M65: WAKISO | N65: UGA | O65: 11 | P65: 4 | Q65: =VLOOKUP(P65,Key!$E$2:$F$9,2,FALSE) -> Commercial | R65: =K65&"-"&Q65 -> Commercial-Commercial | T65: 0.5 | U65: 2 | Y65: Y | Z65: 2000
B66: 0.58611111 | C66: UAW 869Q | D66: 1 | E66: 1 | F66: NANGABO | G66: WAKISO | H66: UGA | I66: 1 | J66: 1 | K66: =VLOOKUP(J66,Key!$E$2:$F$9,2,FALSE) -> Home | L66: KASANGATI | M66: WAKISO | N66: UGA | O66: 11 | P66: 6 | Q66: =VLOOKUP(P66,Key!$E$2:$F$9,2,FALSE) -> Leisure/Social | R66: =K66&"-"&Q66 -> Home-Leisure/Social | U66: 2 | Y66: Y | Z66: 1000
B67: 0.58888889 | C67: UBD 921T | D67: 4 | E67: 2 | F67: BUWBO | G67: WAKISO | H67: UGA | I67: 11 | J67: 4 | K67: =VLOOKUP(J67,Key!$E$2:$F$9,2,FALSE) -> Commercial | L67: KASANGATI | M67: WAKISO | N67: UGA | O67: 11 | P67: 4 | Q67: =VLOOKUP(P67,Key!$E$2:$F$9,2,FALSE) -> Commercial | R67: =K67&"-"&Q67 -> Commercial-Commercial | T67: 0.5 | U67: 3 | Y67: Y | Z67: 1000
B68: 0.59930556 | C68: U 773N | D68: 3 | E68: 2 | F68: NANGABO | G68: WAKISO | H68: UGA | I68: 9 | J68: 2 | K68: =VLOOKUP(J68,Key!$E$2:$F$9,2,FALSE) -> Work | L68: MPERERWE | M68: KPALA | N68: UGA | O68: 11 | P68: 8 | Q68: =VLOOKUP(P68,Key!$E$2:$F$9,2,FALSE) -> Others | R68: =K68&"-"&Q68 -> Work-Others | S68: 8 | T68: 0.3 | U68: 6 | Y68: Y | Z68: 1000
B69: 0.60277778 | C69: UAN 375B | D69: 1 | E69: 1 | F69: KITI | G69: WAKISO | H69: UGA | I69: 1 | J69: 1 | K69: =VLOOKUP(J69,Key!$E$2:$F$9,2,FALSE) -> Home | L69: BUKOTO | M69: KPALA | N69: UGA | O69: 2 | P69: 2 | Q69: =VLOOKUP(P69,Key!$E$2:$F$9,2,FALSE) -> Work | R69: =K69&"-"&Q69 -> Home-Work | T69: 0.5 | U69: 2 | Y69: Y | Z69: 1000
B70: 0.60694444 | C70: UAV 584W | D70: 1 | E70: 3 | F70: KITI | G70: WAKISO | H70: UGA | I70: 1 | J70: 1 | K70: =VLOOKUP(J70,Key!$E$2:$F$9,2,FALSE) -> Home | L70: KPALA | M70: KPALA | N70: UGA | O70: 2 | P70: 2 | Q70: =VLOOKUP(P70,Key!$E$2:$F$9,2,FALSE) -> Work | R70: =K70&"-"&Q70 -> Home-Work | T70: 0.5 | Y70: Y | Z70: 3000
B71: 0.68125 | C71: UAX 675G | D71: 4 | E71: 10 | F71: KASENGEJJE | G71: WAKISO | H71: UGA | I71: 4 | J71: 2 | K71: =VLOOKUP(J71,Key!$E$2:$F$9,2,FALSE) -> Work | L71: GAYAZA | M71: WAKISO | N71: UGA | O71: 16 | P71: 2 | Q71: =VLOOKUP(P71,Key!$E$2:$F$9,2,FALSE) -> Work | R71: =K71&"-"&Q71 -> Work-Work | T71: 0.3 | U71: 2 | Y71: Y | Z71: 2000
B72: 0.68819444 | C72: UAW 392Y | D72: 1 | E72: 1 | F72: NANGABO | G72: WAKISO | H72: UGA | I72: 4 | J72: 6 | K72: =VLOOKUP(J72,Key!$E$2:$F$9,2,FALSE) -> Leisure/Social | L72: BUWAATE | M72: WAKISO | N72: UGA | O72: 1 | P72: 1 | Q72: =VLOOKUP(P72,Key!$E$2:$F$9,2,FALSE) -> Home | R72: =K72&"-"&Q72 -> Leisure/Social-Home | T72: 0.5 | U72: 2 | Y72: Y | Z72: 0
B73: 0.70694444 | C73: UAP 892P | D73: 4 | E73: 2 | F73: NANGABO | G73: WAKISO | H73: UGA | I73: 4 | J73: 6 | K73: =VLOOKUP(J73,Key!$E$2:$F$9,2,FALSE) -> Leisure/Social | L73: KASANGATI | M73: WAKISO | N73: UGA | O73: 1 | P73: 1 | Q73: =VLOOKUP(P73,Key!$E$2:$F$9,2,FALSE) -> Home | R73: =K73&"-"&Q73 -> Leisure/Social-Home | S73: 1 | T73: 0.1 | U73: 2 | Y73: Y | Z73: 1000
B74: 0.71458333 | C74: UAV 108L | D74: 4 | E74: 10 | F74: NANGABO | G74: WAKISO | H74: UGA | I74: 4 | J74: 2 | K74: =VLOOKUP(J74,Key!$E$2:$F$9,2,FALSE) -> Work | L74: KASANGATI | M74: WAKISO | N74: UGA | O74: 1 | P74: 1 | Q74: =VLOOKUP(P74,Key!$E$2:$F$9,2,FALSE) -> Home | R74: =K74&"-"&Q74 -> Work-Home | S74: 1 | T74: 0.3 | U74: 2 | Y74: Y | Z74: 1000
B75: 0.72708333 | C75: UAZ 779P | D75: 7 | E75: 1 | F75: NANGABO | G75: WAKISO | H75: UGA | I75: 2 | J75: 2 | K75: =VLOOKUP(J75,Key!$E$2:$F$9,2,FALSE) -> Work | L75: BWAISE | M75: KPALA | N75: UGA | O75: 1 | P75: 1 | Q75: =VLOOKUP(P75,Key!$E$2:$F$9,2,FALSE) -> Home | R75: =K75&"-"&Q75 -> Work-Home | S75: 10 | T75: 1 | U75: 6 | Y75: Y | Z75: 3000
B76: 0.73958333 | C76: UAN 176Z | D76: 7 | E76: 2 | F76: JOKOLERA | G76: WAKISO | H76: UGA | I76: 1 | J76: 1 | K76: =VLOOKUP(J76,Key!$E$2:$F$9,2,FALSE) -> Home | L76: KASANGATI | M76: WAKISO | N76: UGA | O76: 3 | P76: 2 | Q76: =VLOOKUP(P76,Key!$E$2:$F$9,2,FALSE) -> Work | R76: =K76&"-"&Q76 -> Home-Work | T76: 2 | U76: 3 | Y76: Y | Z76: 1000
B77: 0.74375 | C77: UAY 369K | D77: 1 | E77: 3 | F77: KITALYA | G77: WAKISO | H77: UGA | I77: 15 | J77: 2 | K77: =VLOOKUP(J77,Key!$E$2:$F$9,2,FALSE) -> Work | L77: NTINDA | M77: KPALA | N77: UGA | O77: 10 | P77: 2 | Q77: =VLOOKUP(P77,Key!$E$2:$F$9,2,FALSE) -> Work | R77: =K77&"-"&Q77 -> Work-Work | T77: 0.7 | U77: 6 | V77: 4 | Y77: Y | Z77: 2000
B78: 0.77916667 | C78: UAU 149U | D78: 1 | E78: 1 | F78: NANGABO | G78: WAKISO | H78: UGA | I78: 1 | J78: 1 | K78: =VLOOKUP(J78,Key!$E$2:$F$9,2,FALSE) -> Home | L78: GAYAZA | M78: WAKISO | N78: UGA | O78: 4 | P78: 2 | Q78: =VLOOKUP(P78,Key!$E$2:$F$9,2,FALSE) -> Work | R78: =K78&"-"&Q78 -> Home-Work | T78: 0.2 | U78: 2 | Y78: Y | Z78: 2000
B79: 0.76458333 | C79: UAV 073D | D79: 1 | E79: 1 | F79: NANGABO | G79: WAKISO | H79: UGA | I79: 1 | J79: 1 | K79: =VLOOKUP(J79,Key!$E$2:$F$9,2,FALSE) -> Home | L79: KASANGATI | M79: WAKISO | N79: UGA | O79: 11 | P79: 4 | Q79: =VLOOKUP(P79,Key!$E$2:$F$9,2,FALSE) -> Commercial | R79: =K79&"-"&Q79 -> Home-Commercial | T79: 0.1 | U79: 2 | Y79: Y | Z79: 4000
B80: 0.71527778 | C80: UBE 822E | D80: 4 | E80: 14 | F80: KITI | G80: WAKISO | H80: UGA | I80: 4 | J80: 3 | K80: =VLOOKUP(J80,Key!$E$2:$F$9,2,FALSE) -> Study | L80: GAYAZA | M80: WAKISO | N80: UGA | O80: 3 | P80: 3 | Q80: =VLOOKUP(P80,Key!$E$2:$F$9,2,FALSE) -> Study | R80: =K80&"-"&Q80 -> Study-Study | S80: 6 | T80: 0.7 | U80: 2 | Y80: Y | Z80: 2000
B81: 0.70833333 | C81: UBD 933L | D81: 1 | E81: 1 | F81: MATUGGA | G81: WAKISO | H81: UGA | I81: 1 | J81: 1 | K81: =VLOOKUP(J81,Key!$E$2:$F$9,2,FALSE) -> Home | L81: KPALA | M81: KPALA | N81: UGA | O81: 2 | P81: 2 | Q81: =VLOOKUP(P81,Key!$E$2:$F$9,2,FALSE) -> Work | R81: =K81&"-"&Q81 -> Home-Work | S81: 12 | T81: 1.5 | U81: 2 | Y81: Y | Z81: 1000
B82: 0.73263889 | C82: UAZ 765L | D82: 1 | E82: 3 | F82: WAKISO | G82: WAKISO | H82: UGA | I82: 2 | J82: 2 | K82: =VLOOKUP(J82,Key!$E$2:$F$9,2,FALSE) -> Work | L82: KPALA | M82: KPALA | N82: UGA | O82: 1 | P82: 1 | Q82: =VLOOKUP(P82,Key!$E$2:$F$9,2,FALSE) -> Home | R82: =K82&"-"&Q82 -> Work-Home | S82: 14 | T82: 2 | U82: 2 | Y82: Y | Z82: 1000
B83: 0.76805556 | C83: UAY 797U | D83: 9 | E83: 2 | F83: KAPEEKA | G83: WAKISO | H83: UGA | I83: 10 | J83: 4 | K83: =VLOOKUP(J83,Key!$E$2:$F$9,2,FALSE) -> Commercial | L83: KIREKA | M83: WAKISO | N83: UGA | O83: 10 | P83: 4 | Q83: =VLOOKUP(P83,Key!$E$2:$F$9,2,FALSE) -> Commercial | R83: =K83&"-"&Q83 -> Commercial-Commercial | S83: 60 | T83: 2.5 | V83: 4 | W83: 25 | Y83: Y | Z83: 10000
B84: 0.59861111 | C84: UBB 590B | D84: 1 | E84: 2 | F84: MUKONO | G84: MUKONO | H84: UGA | I84: 1 | J84: 1 | K84: =VLOOKUP(J84,Key!$E$2:$F$9,2,FALSE) -> Home | L84: KIRA | M84: WAKISO | N84: UGA | O84: 2 | P84: 2 | Q84: =VLOOKUP(P84,Key!$E$2:$F$9,2,FALSE) -> Work | R84: =K84&"-"&Q84 -> Home-Work | U84: 2 | Y84: Y | Z84: 1000
B85: 0.59722222 | C85: UAA 270B | D85: 1 | E85: 2 | F85: NANGABO | G85: WAKISO | H85: UGA | I85: 1 | J85: 1 | K85: =VLOOKUP(J85,Key!$E$2:$F$9,2,FALSE) -> Home | L85: KIRA | M85: WAKISO | N85: UGA | O85: 4 | P85: 3 | Q85: =VLOOKUP(P85,Key!$E$2:$F$9,2,FALSE) -> Study | R85: =K85&"-"&Q85 -> Home-Study | U85: 2 | Y85: Y | Z85: 5000
B86: 0.60277778 | C86: UBF 485K | D86: 1 | E86: 3 | F86: MPERERWE | G86: KPALA | H86: UGA | I86: 1 | J86: 1 | K86: =VLOOKUP(J86,Key!$E$2:$F$9,2,FALSE) -> Home | L86: NANGBO | M86: WAKISO | N86: UGA | O86: 16 | P86: 1 | Q86: =VLOOKUP(P86,Key!$E$2:$F$9,2,FALSE) -> Home | R86: =K86&"-"&Q86 -> Home-Home | S86: 25 | T86: 1 | U86: 2 | Y86: Y | Z86: 0
B87: 0.60694444 | C87: UBB 954Y | D87: 2 | E87: 1 | F87: KITI | G87: WAKISO | H87: UGA | I87: 1 | J87: 1 | K87: =VLOOKUP(J87,Key!$E$2:$F$9,2,FALSE) -> Home | L87: KIREKA | M87: WAKISO | N87: UGA | O87: 2 | P87: 2 | Q87: =VLOOKUP(P87,Key!$E$2:$F$9,2,FALSE) -> Work | R87: =K87&"-"&Q87 -> Home-Work | S87: 15 | T87: 0.5 | U87: 3 | Y87: Y | Z87: 3000
B88: 0.59166667 | C88: UBD 781L | D88: 1 | E88: 2 | F88: MATUGGA | G88: WAKISO | H88: UGA | I88: 1 | J88: 1 | K88: =VLOOKUP(J88,Key!$E$2:$F$9,2,FALSE) -> Home | L88: KPALA | M88: KPALA | N88: UGA | O88: 7 | P88: 6 | Q88: =VLOOKUP(P88,Key!$E$2:$F$9,2,FALSE) -> Leisure/Social | R88: =K88&"-"&Q88 -> Home-Leisure/Social | S88: 15 | T88: 1 | U88: 3 | Y88: Y | Z88: 5000
B89: 0.59444444 | C89: UAZ 802L | D89: 3 | E89: 2 | F89: MATUGGA | G89: WAKISO | H89: UGA | I89: 3 | J89: 4 | K89: =VLOOKUP(J89,Key!$E$2:$F$9,2,FALSE) -> Commercial | L89: KPALA | M89: KPALA | N89: UGA | O89: 12 | P89: 4 | Q89: =VLOOKUP(P89,Key!$E$2:$F$9,2,FALSE) -> Commercial | R89: =K89&"-"&Q89 -> Commercial-Commercial | S89: 25 | T89: 1.5 | U89: 1 | Y89: Y | Z89: 1000
B90: 0.57291667 | C90: UAY 882B | D90: 1 | E90: 4 | F90: KPALA | G90: KPALA | H90: UGA | I90: 1 | J90: 1 | K90: =VLOOKUP(J90,Key!$E$2:$F$9,2,FALSE) -> Home | L90: GAYAZA | M90: WAKISO | N90: UGA | O90: 3 | P90: 2 | Q90: =VLOOKUP(P90,Key!$E$2:$F$9,2,FALSE) -> Work | R90: =K90&"-"&Q90 -> Home-Work | S90: 20 | T90: 0.7 | U90: 3 | V90: 9 | W90: 2 | Y90: Y | Z90: 5000
B91: 0.58958333 | C91: UAW 704S | D91: 2 | E91: 3 | F91: KITEGOMBWA | G91: WAKISO | H91: UGA | I91: 1 | J91: 1 | K91: =VLOOKUP(J91,Key!$E$2:$F$9,2,FALSE) -> Home | L91: KASANGATI | M91: WAKISO | N91: UGA | O91: 16 | P91: 8 | Q91: =VLOOKUP(P91,Key!$E$2:$F$9,2,FALSE) -> Others | R91: =K91&"-"&Q91 -> Home-Others | S91: 2 | T91: 0.1 | U91: 2 | Y91: Y | Z91: 3000
B92: 0.55555556 | C92: UBD 532E | D92: 1 | E92: 1 | F92: KITEGOMBWA | G92: WAKISO | H92: UGA | I92: 1 | J92: 1 | K92: =VLOOKUP(J92,Key!$E$2:$F$9,2,FALSE) -> Home | L92: GAYAZA | M92: WAKISO | N92: UGA | O92: 1 | P92: 1 | Q92: =VLOOKUP(P92,Key!$E$2:$F$9,2,FALSE) -> Home | R92: =K92&"-"&Q92 -> Home-Home | S92: 19 | T92: 0.7 | U92: 2 | Y92: Y | Z92: 2000
B93: 0.57013889 | C93: UBE 933U | D93: 3 | E93: 2 | F93: KITEGOMBWA | G93: WAKISO | H93: UGA | I93: 1 | J93: 1 | K93: =VLOOKUP(J93,Key!$E$2:$F$9,2,FALSE) -> Home | L93: KASANGATI | M93: WAKISO | N93: UGA | O93: 2 | P93: 2 | Q93: =VLOOKUP(P93,Key!$E$2:$F$9,2,FALSE) -> Work | R93: =K93&"-"&Q93 -> Home-Work | S93: 2 | U93: 2 | Y93: Y | Z93: 1000
B94: 0.54930556 | C94: UBF 928Q | D94: 1 | E94: 2 | F94: MATUGGA | G94: WAKISO | H94: UGA | I94: 1 | J94: 1 | K94: =VLOOKUP(J94,Key!$E$2:$F$9,2,FALSE) -> Home | L94: NUGONGO | M94: WAKISO | N94: UGA | O94: 16 | P94: 8 | Q94: =VLOOKUP(P94,Key!$E$2:$F$9,2,FALSE) -> Others | R94: =K94&"-"&Q94 -> Home-Others | Y94: Y | Z94: 3000
B95: 0.55277778 | C95: UBD 866F | D95: 2 | E95: 4 | F95: BUWBO | G95: WAKISO | H95: UGA | I95: 6 | J95: 1 | K95: =VLOOKUP(J95,Key!$E$2:$F$9,2,FALSE) -> Home | L95: MUKONO | M95: MUKONO | N95: UGA | O95: 1 | P95: 1 | Q95: =VLOOKUP(P95,Key!$E$2:$F$9,2,FALSE) -> Home | R95: =K95&"-"&Q95 -> Home-Home | S95: 10 | T95: 1 | U95: 2 | Y95: Y | Z95: 2000
B96: 0.52638889 | C96: UAY 216V | D96: 1 | E96: 4 | F96: KITEGOMBWA | G96: WAKISO | H96: UGA | I96: 1 | J96: 1 | K96: =VLOOKUP(J96,Key!$E$2:$F$9,2,FALSE) -> Home | L96: KASANGATI | M96: WAKISO | N96: UGA | O96: 5 | P96: 2 | Q96: =VLOOKUP(P96,Key!$E$2:$F$9,2,FALSE) -> Work | R96: =K96&"-"&Q96 -> Home-Work | S96: 4 | T96: 0.1 | U96: 2 | Y96: Y | Z96: 10000
B97: 0.54375 | C97: UAZ 508M | D97: 1 | E97: 3 | F97: MAWULA | G97: WAKISO | H97: UGA | I97: 1 | J97: 1 | K97: =VLOOKUP(J97,Key!$E$2:$F$9,2,FALSE) -> Home | L97: NTINDA | M97: KPALA | N97: UGA | O97: 16 | P97: 2 | Q97: =VLOOKUP(P97,Key!$E$2:$F$9,2,FALSE) -> Work | R97: =K97&"-"&Q97 -> Home-Work | S97: 19 | T97: 0.5 | U97: 6 | Y97: Y | Z97: 2000
B98: 0.51666667 | C98: UBB 468T | D98: 8 | E98: 3 | F98: GITA | G98: WAKISO | H98: UGA | I98: 11 | J98: 4 | K98: =VLOOKUP(J98,Key!$E$2:$F$9,2,FALSE) -> Commercial | L98: KASANGATI | M98: WAKISO | N98: UGA | O98: 3 | P98: 4 | Q98: =VLOOKUP(P98,Key!$E$2:$F$9,2,FALSE) -> Commercial | R98: =K98&"-"&Q98 -> Commercial-Commercial | S98: 2 | T98: 0.5 | U98: 6 | V98: 6 | W98: 4 | Y98: Y | Z98: 500
B99: 0.52083333 | C99: UAL 779V | D99: 1 | E99: 1 | F99: GULU | G99: GULU | H99: UGA | I99: 16 | J99: 1 | K99: =VLOOKUP(J99,Key!$E$2:$F$9,2,FALSE) -> Home | L99: KASANGATI | M99: WAKISO | N99: UGA | O99: 1 | P99: 8 | Q99: =VLOOKUP(P99,Key!$E$2:$F$9,2,FALSE) -> Others | R99: =K99&"-"&Q99 -> Home-Others | S99: 260 | T99: 6 | U99: 3 | Y99: Y | Z99: 0
B100: 0.50416667 | C100: UAH 425Y | D100: 2 | E100: 3 | F100: MASOOLI | G100: WAKISO | H100: UGA | I100: 16 | J100: 1 | K100: =VLOOKUP(J100,Key!$E$2:$F$9,2,FALSE) -> Home | L100: KASANGATI | M100: WAKISO | N100: UGA | O100: 2 | P100: 2 | Q100: =VLOOKUP(P100,Key!$E$2:$F$9,2,FALSE) -> Work | R100: =K100&"-"&Q100 -> Home-Work | S100: 8 | T100: 0.2 | U100: 3 | Y100: Y | Z100: 0
B101: 0.50763889 | C101: UBG 678K | D101: 1 | E101: 2 | F101: BBU | G101: WAKISO | H101: UGA | I101: 1 | J101: 1 | K101: =VLOOKUP(J101,Key!$E$2:$F$9,2,FALSE) -> Home | L101: GAYAZA | M101: WAKISO | N101: UGA | O101: 1 | P101: 1 | Q101: =VLOOKUP(P101,Key!$E$2:$F$9,2,FALSE) -> Home | R101: =K101&"-"&Q101 -> Home-Home | S101: 6 | T101: 0.3 | U101: 2 | Y101: Y | Z101: 2000
B102: 0.49097222 | C102: UAT 875J | D102: 2 | E102: 2 | F102: MUSOLI | G102: WAKISO | H102: UGA | I102: 1 | J102: 1 | K102: =VLOOKUP(J102,Key!$E$2:$F$9,2,FALSE) -> Home | L102: KPALA | M102: KPALA | N102: UGA | O102: 2 | P102: 2 | Q102: =VLOOKUP(P102,Key!$E$2:$F$9,2,FALSE) -> Work | R102: =K102&"-"&Q102 -> Home-Work | S102: 17 | T102: 1 | U102: 2 | Y102: Y | Z102: 2000
...

Sheet 14.10 KASANGATI-MATUGGA
B1: Consultancy services for Preparation of Expressway Develo PMent Master Plan (EDMP) for Uganda
B2: Roadside OD Interview Survey
B4: Date: | C4: 14.10.19 | E4: Road Name: | F4: MATUGGA-WAKISO ROAD | I4: Direction From: | L4: KASANGATI | N4: Interviewers: | O4: NAKAYO JOAN | V4: Supervisor: | W4: ANDREW | Y4: Coded By: | Z4: DAVID | AA4: Chkd By: | AB4: Bakole Deo
I5: Direction To: | L5: MATUGGA
B7: Time | C7: Veh_Reg_No. | D7: Veh_Type | E7: No. Occupants | F7: Origin_Address | I7: Origin_Establish | J7: Origin_Purpose | K7: Origin-Purpose Desc | L7: Destination_Address | O7: Destination_Establish | P7: Destination_Purpose | Q7: Destination_Purpose Desc | R7: Journey_Purpose | S7: Approx_Distance (Km) | T7: Approx_Journey Time (Hrs) | U7: Trip_Frequency | V7: GOODS VEHICLES ONLY | Y7: Would You Use Xpressways? | Z7: Pay How Much? (UGX) | AA7: Origin_Zone | AB7: Dest_Zone
F8: Village or Town | G8: District | H8: Country | L8: Village or Town | M8: District | N8: Country | V8: Goods_Type | W8: Goods_Quantity (Ton) | X8: Goods_Value (UGXm)
B9: 0.75486111 | C9: UAL 541W | D9: 8 | E9: 1 | F9: KITIKUTWE | G9: WAKISO | H9: UGA | I9: 16 | J9: 8 | K9: =VLOOKUP(J9,Key!$E$2:$F$9,2,FALSE) -> Others | L9: KASANGATI | M9: WAKISO | N9: UGA | O9: 16 | P9: 8 | Q9: =VLOOKUP(P9,Key!$E$2:$F$9,2,FALSE) -> Others | R9: =K9&"-"&Q9 -> Others-Others | U9: 3 | Y9: Y | Z9: 1000
B10: 18:00 | C10: UAQ 983V | D10: 1 | E10: 3 | F10: KAMPALA | G10: KAMPALA | H10: UGA | I10: 4 | J10: 3 | K10: =VLOOKUP(J10,Key!$E$2:$F$9,2,FALSE) -> Study | L10: MAWULE | M10: WAKISO | N10: UGA | O10: 1 | P10: 1 | Q10: =VLOOKUP(P10,Key!$E$2:$F$9,2,FALSE) -> Home | R10: =K10&"-"&Q10 -> Study-Home | T10: 1.5 | U10: 2 | Y10: Y | Z10: 1000
B11: 0.74791667 | C11: UBB 299P | D11: 3 | E11: 3 | F11: BUKERERE | G11: MUKONO | H11: UGA | I11: 16 | J11: 8 | K11: =VLOOKUP(J11,Key!$E$2:$F$9,2,FALSE) -> Others | L11: KASANGATI | M11: WAKISO | N11: UGA | O11: 16 | P11: 8 | Q11: =VLOOKUP(P11,Key!$E$2:$F$9,2,FALSE) -> Others | R11: =K11&"-"&Q11 -> Others-Others | S11: 18 | T11: 1.5 | U11: 2 | Y11: Y | Z11: 500
B12: 0.74583333 | C12: UBE 226X | D12: 1 | E12: 4 | F12: KOLOLO | G12: KAMPALA | H12: UGA | I12: 4 | J12: 3 | K12: =VLOOKUP(J12,Key!$E$2:$F$9,2,FALSE) -> Study | L12: KILEMOZI | M12: WAKISO | N12: UGA | O12: 1 | P12: 1 | Q12: =VLOOKUP(P12,Key!$E$2:$F$9,2,FALSE) -> Home | R12: =K12&"-"&Q12 -> Study-Home | S12: 24 | T12: 1 | U12: 2 | Y12: Y | Z12: 2000
B13: 0.74027778 | C13: UAJ 837U | D13: 2 | E13: 2 | F13: KAMPALA | G13: KAMPALA | H13: UGA | I13: 16 | J13: 2 | K13: =VLOOKUP(J13,Key!$E$2:$F$9,2,FALSE) -> Work | L13: NANGABO | M13: WAKISO | N13: UGA | O13: 9 | P13: 2 | Q13: =VLOOKUP(P13,Key!$E$2:$F$9,2,FALSE) -> Work | R13: =K13&"-"&Q13 -> Work-Work | S13: 8 | T13: 0.7 | U13: 6 | Y13: Y | Z13: 2000
B14: 0.73472222 | C14: UAZ 889Q | D14: 1 | E14: 1 | F14: MBUYA | G14: KAMPALA | H14: UGA | I14: 2 | J14: 2 | K14: =VLOOKUP(J14,Key!$E$2:$F$9,2,FALSE) -> Work | L14: MATUGGA | M14: WAKISO | N14: UGA | O14: 1 | P14: 1 | Q14: =VLOOKUP(P14,Key!$E$2:$F$9,2,FALSE) -> Home | R14: =K14&"-"&Q14 -> Work-Home | S14: 27 | T14: 0.7 | U14: 2 | Y14: Y | Z14: 2000
B15: 0.73958333 | C15: UBA 695R | D15: 1 | E15: 3 | F15: KAMPALA | G15: KAMPALA | H15: UGA | I15: 2 | J15: 2 | K15: =VLOOKUP(J15,Key!$E$2:$F$9,2,FALSE) -> Work | L15: KASANGATI | M15: WAKISO | N15: UGA | O15: 1 | P15: 1 | Q15: =VLOOKUP(P15,Key!$E$2:$F$9,2,FALSE) -> Home | R15: =K15&"-"&Q15 -> Work-Home | S15: 10 | T15: 0.5 | U15: 2 | Y15: Y | Z15: 0
B16: 0.72708333 | C16: UBC 817A | D16: 7 | E16: 3 | F16: KASANGATI | G16: WAKISO | H16: UGA | I16: 16 | J16: 8 | K16: =VLOOKUP(J16,Key!$E$2:$F$9,2,FALSE) -> Others | L16: KITEGOBWA | M16: WAKISO | N16: UGA | O16: 16 | P16: 2 | Q16: =VLOOKUP(P16,Key!$E$2:$F$9,2,FALSE) -> Work | R16: =K16&"-"&Q16 -> Others-Work | S16: 3 | T16: 0.1 | U16: 6 | Y16: Y | Z16: 0
B17: 0.72569444 | C17: UAQ 659M | D17: 1 | E17: 1 | F17: KAMPALA | G17: KAMPALA | H17: UGA | I17: 2 | J17: 2 | K17: =VLOOKUP(J17,Key!$E$2:$F$9,2,FALSE) -> Work | L17: BUWAMBO | M17: WAKISO | N17: UGA | O17: 1 | P17: 1 | Q17: =VLOOKUP(P17,Key!$E$2:$F$9,2,FALSE) -> Home | R17: =K17&"-"&Q17 -> Work-Home | S17: 24 | T17: 1 | U17: 2 | Y17: Y | Z17: 500
B18: 0.72291667 | C18: UAN 330G | D18: 1 | E18: 2 | F18: NAKAWA | G18: KAMPALA | H18: UGA | I18: 2 | J18: 2 | K18: =VLOOKUP(J18,Key!$E$2:$F$9,2,FALSE) -> Work | L18: NANGABO | M18: WAKISO | N18: UGA | O18: 1 | P18: 1 | Q18: =VLOOKUP(P18,Key!$E$2:$F$9,2,FALSE) -> Home | R18: =K18&"-"&Q18 -> Work-Home | U18: 2 | Y18: Y | Z18: 0
B19: 0.58263889 | C19: UAN 671C | D19: 7 | E19: 2 | F19: KASANGATI | G19: WAKISO | H19: UGA | I19: 16 | J19: 8 | K19: =VLOOKUP(J19,Key!$E$2:$F$9,2,FALSE) -> Others | L19: NANGABO | M19: WAKISO | N19: UGA | O19: 14 | P19: 2 | Q19: =VLOOKUP(P19,Key!$E$2:$F$9,2,FALSE) -> Work | R19: =K19&"-"&Q19 -> Others-Work | S19: 2 | T19: 0.3 | U19: 3 | Y19: Y | Z19: 1000
B20: 0.57777778 | C20: UAZ 376A | D20: 1 | E20: 1 | F20: WAMPEWO | G20: WAKISO | H20: UGA | I20: 10 | J20: 2 | K20: =VLOOKUP(J20,Key!$E$2:$F$9,2,FALSE) -> Work | L20: NANGABO | M20: WAKISO | N20: UGA | O20: 1 | P20: 1 | Q20: =VLOOKUP(P20,Key!$E$2:$F$9,2,FALSE) -> Home | R20: =K20&"-"&Q20 -> Work-Home | S20: 3 | T20: 0.1 | U20: 6 | Y20: Y | Z20: 2000
B21: 0.57638889 | C21: UAL 811L | D21: 7 | E21: 1 | F21: KASANGATI | G21: WAKISO | H21: UGA | I21: 1 | J21: 1 | K21: =VLOOKUP(J21,Key!$E$2:$F$9,2,FALSE) -> Home | L21: NANGABO | M21: WAKISO | N21: UGA | O21: 16 | P21: 8 | Q21: =VLOOKUP(P21,Key!$E$2:$F$9,2,FALSE) -> Others | R21: =K21&"-"&Q21 -> Home-Others | U21: 1 | Y21: Y | Z21: 1000
B22: 0.57152778 | C22: UAK 186N | D22: 4 | E22: 15 | F22: KASANGATI | G22: WAKISO | H22: UGA | I22: 6 | J22: 2 | K22: =VLOOKUP(J22,Key!$E$2:$F$9,2,FALSE) -> Work | L22: WAKISO | M22: WAKISO | N22: UGA | O22: 6 | P22: 2 | Q22: =VLOOKUP(P22,Key!$E$2:$F$9,2,FALSE) -> Work | R22: =K22&"-"&Q22 -> Work-Work | S22: 10 | T22: 1 | U22: 2 | Y22: Y | Z22: 1000
B23: 0.56944444 | C23: UAX 474M | D23: 8 | E23: 3 | F23: GAYAZA | G23: WAKISO | H23: UGA | I23: 16 | J23: 8 | K23: =VLOOKUP(J23,Key!$E$2:$F$9,2,FALSE) -> Others | L23: NANGABO | M23: WAKISO | N23: UGA | O23: 16 | P23: 8 | Q23: =VLOOKUP(P23,Key!$E$2:$F$9,2,FALSE) -> Others | R23: =K23&"-"&Q23 -> Others-Others | S23: 1.5 | T23: 0.1 | U23: 3 | Y23: Y | Z23: 0
B24: 0.56666667 | C24: UBF 618X | D24: 1 | E24: 1 | F24: KASANGATI | G24: WAKISO | H24: UGA | I24: 7 | J24: 8 | K24: =VLOOKUP(J24,Key!$E$2:$F$9,2,FALSE) -> Others | L24: NANGABO | M24: WAKISO | N24: UGA | O24: 4 | P24: 3 | Q24: =VLOOKUP(P24,Key!$E$2:$F$9,2,FALSE) -> Study | R24: =K24&"-"&Q24 -> Others-Study | T24: 0.1 | U24: 2 | Y24: Y | Z24: 1000
B25: 0.5625 | C25: UBB 450P | D25: 8 | E25: 3 | F25: NAMANVE | G25: MUKONO | H25: UGA | I25: 16 | J25: 8 | K25: =VLOOKUP(J25,Key!$E$2:$F$9,2,FALSE) -> Others | L25: MATUGGA | M25: WAKISO | N25: UGA | O25: 3 | P25: 4 | Q25: =VLOOKUP(P25,Key!$E$2:$F$9,2,FALSE) -> Commercial | R25: =K25&"-"&Q25 -> Others-Commercial | S25: 20 | T25: 1 | U25: 6 | Y25: Y | Z25: 200
B26: 0.55833333 | C26: UAQ 617X | D26: 1 | E26: 1 | F26: BWEYOGERERE | G26: WAKISO | H26: UGA | I26: 1 | J26: 1 | K26: =VLOOKUP(J26,Key!$E$2:$F$9,2,FALSE) -> Home | L26: KASANGATI | M26: WAKISO | N26: UGA | O26: 2 | P26: 2 | Q26: =VLOOKUP(P26,Key!$E$2:$F$9,2,FALSE) -> Work | R26: =K26&"-"&Q26 -> Home-Work | S26: 15 | T26: 0.3 | U26: 6 | Y26: Y | Z26: 0
B27: 0.55347222 | C27: UBB 132T | D27: 2 | E27: 1 | F27: KASANGATI | G27: WAKISO | H27: UGA | I27: 16 | J27: 8 | K27: =VLOOKUP(J27,Key!$E$2:$F$9,2,FALSE) -> Others | L27: NANGABO | M27: WAKISO | N27: UGA | O27: 1 | P27: 1 | Q27: =VLOOKUP(P27,Key!$E$2:$F$9,2,FALSE) -> Home | R27: =K27&"-"&Q27 -> Others-Home | S27: 3 | T27: 0.1 | U27: 2 | Y27: Y | Z27: 10000
B28: 0.55555556 | C28: UBA 632P | D28: 5 | E28: 30 | F28: GAYAZA | G28: WAKISO | H28: UGA | I28: 1 | J28: 1 | K28: =VLOOKUP(J28,Key!$E$2:$F$9,2,FALSE) -> Home | L28: BOMBO | M28: BOMBO | N28: UGA | O28: 16 | P28: 8 | Q28: =VLOOKUP(P28,Key!$E$2:$F$9,2,FALSE) -> Others | R28: =K28&"-"&Q28 -> Home-Others | S28: 27 | T28: 1 | U28: 3 | Y28: Y | Z28: 1000
B29: 0.55208333 | C29: UBB 623L | D29: 8 | E29: 3 | F29: KYANJA | G29: KAMPALA | H29: UGA | I29: 16 | J29: 8 | K29: =VLOOKUP(J29,Key!$E$2:$F$9,2,FALSE) -> Others | L29: KAKERENGE | M29: WAKISO | N29: UGA | O29: 15 | P29: 2 | Q29: =VLOOKUP(P29,Key!$E$2:$F$9,2,FALSE) -> Work | R29: =K29&"-"&Q29 -> Others-Work | T29: 0.5 | U29: 2 | Y29: Y | Z29: 5000
B30: 0.54930556 | C30: UBF 120P | D30: 1 | E30: 3 | F30: BUGOLOBI | G30: KAMPALA | H30: UGA | I30: 5 | J30: 7 | K30: =VLOOKUP(J30,Key!$E$2:$F$9,2,FALSE) -> Hospital | L30: KASANGATI | M30: WAKISO | N30: UGA | O30: 1 | P30: 1 | Q30: =VLOOKUP(P30,Key!$E$2:$F$9,2,FALSE) -> Home | R30: =K30&"-"&Q30 -> Hospital-Home | S30: 20 | T30: 0.7 | U30: 2 | Y30: Y | Z30: 2000
B31: 0.54375 | C31: UAZ 240A | D31: 1 | E31: 3 | F31: NTINDA | G31: KAMPALA | H31: UGA | I31: 2 | J31: 2 | K31: =VLOOKUP(J31,Key!$E$2:$F$9,2,FALSE) -> Work | L31: KITEGOBWA | M31: WAKISO | N31: UGA | O31: 1 | P31: 1 | Q31: =VLOOKUP(P31,Key!$E$2:$F$9,2,FALSE) -> Home | R31: =K31&"-"&Q31 -> Work-Home | S31: 18 | T31: 0.5 | U31: 2 | Y31: Y | Z31: 0
B32: 0.53263889 | C32: UBB 525N | D32: 2 | E32: 2 | F32: KASANGATI | G32: WAKISO | H32: UGA | I32: 16 | J32: 8 | K32: =VLOOKUP(J32,Key!$E$2:$F$9,2,FALSE) -> Others | L32: SEMUTO | M32: LUWERO | N32: UGA | O32: 16 | P32: 8 | Q32: =VLOOKUP(P32,Key!$E$2:$F$9,2,FALSE) -> Others | R32: =K32&"-"&Q32 -> Others-Others | S32: 60 | T32: 4 | U32: 2 | Y32: Y | Z32: 0
B33: 0.53125 | C33: UAR 484Q | D33: 1 | E33: 1 | F33: KASANGATI | G33: WAKISO | H33: UGA | I33: 16 | J33: 8 | K33: =VLOOKUP(J33,Key!$E$2:$F$9,2,FALSE) -> Others | L33: BUWAMBO | M33: WAKISO | N33: UGA | O33: 16 | P33: 8 | Q33: =VLOOKUP(P33,Key!$E$2:$F$9,2,FALSE) -> Others | R33: =K33&"-"&Q33 -> Others-Others | T33: 0.2 | U33: 2 | Y33: Y | Z33: 1000
B34: 0.52708333 | C34: UP 484I | D34: 2 | E34: 2 | F34: ZIROBWA ROAD | G34: WAKISO | H34: UGA | I34: 16 | J34: 2 | K34: =VLOOKUP(J34,Key!$E$2:$F$9,2,FALSE) -> Work | L34: MATUGGA | M34: WAKISO | N34: UGA | O34: 16 | P34: 2 | Q34: =VLOOKUP(P34,Key!$E$2:$F$9,2,FALSE) -> Work | R34: =K34&"-"&Q34 -> Work-Work | U34: 2 | Y34: Y | Z34: 0
B35: 0.52638889 | C35: UAT 737P | D35: 7 | E35: 3 | F35: NANSANA | G35: WAKISO | H35: UGA | I35: 1 | J35: 1 | K35: =VLOOKUP(J35,Key!$E$2:$F$9,2,FALSE) -> Home | L35: NANGABO | M35: WAKISO | N35: UGA | O35: 16 | P35: 8 | Q35: =VLOOKUP(P35,Key!$E$2:$F$9,2,FALSE) -> Others | R35: =K35&"-"&Q35 -> Home-Others | T35: 0.5 | U35: 6 | Y35: Y | Z35: 1000
B36: 0.52152778 | C36: UAL 448Y | D36: 1 | E36: 2 | F36: KYALIWAJJALA | G36: WAKISO | H36: UGA | I36: 1 | J36: 1 | K36: =VLOOKUP(J36,Key!$E$2:$F$9,2,FALSE) -> Home | L36: NANGABO | M36: WAKISO | N36: UGA | O36: 16 | P36: 8 | Q36: =VLOOKUP(P36,Key!$E$2:$F$9,2,FALSE) -> Others | R36: =K36&"-"&Q36 -> Home-Others | T36: 0.3 | U36: 4 | Y36: Y | Z36: 2000
B37: 0.51597222 | C37: UAR 663C | D37: 4 | E37: 15 | F37: NAKASAJO | G37: WAKISO | H37: UGA | I37: 1 | J37: 1 | K37: =VLOOKUP(J37,Key!$E$2:$F$9,2,FALSE) -> Home | L37: BOMBO | M37: BOMBO | N37: UGA | O37: 16 | P37: 2 | Q37: =VLOOKUP(P37,Key!$E$2:$F$9,2,FALSE) -> Work | R37: =K37&"-"&Q37 -> Home-Work | S37: 40 | T37: 0.7 | U37: 6 | Y37: Y | Z37: 500
B38: 0.5125 | C38: UBB 886B | D38: 2 | E38: 1 | F38: KASANGATI | G38: WAKISO | H38: UGA | I38: 1 | J38: 2 | K38: =VLOOKUP(J38,Key!$E$2:$F$9,2,FALSE) -> Work | L38: KASANGATI | M38: WAKISO | N38: UGA | O38: 16 | P38: 8 | Q38: =VLOOKUP(P38,Key!$E$2:$F$9,2,FALSE) -> Others | R38: =K38&"-"&Q38 -> Work-Others | U38: 6 | Y38: Y | Z38: 0
B39: 0.51388889 | C39: UAN 386N | D39: 8 | E39: 2 | F39: GAYAZA | G39: WAKISO | H39: UGA | I39: 11 | J39: 4 | K39: =VLOOKUP(J39,Key!$E$2:$F$9,2,FALSE) -> Commercial | L39: MATUGGA | M39: WAKISO | N39: UGA | O39: 11 | P39: 4 | Q39: =VLOOKUP(P39,Key!$E$2:$F$9,2,FALSE) -> Commercial | R39: =K39&"-"&Q39 -> Commercial-Commercial | T39: 12 | U39: 0.5 | V39: 2 | Y39: Y | Z39: 300
B40: 0.50555556 | C40: UBB 575T | D40: 2 | E40: 1 | F40: KAMPALA | G40: KAMPALA | H40: UGA | I40: 2 | J40: 2 | K40: =VLOOKUP(J40,Key!$E$2:$F$9,2,FALSE) -> Work | L40: GULU | M40: GULU | N40: UGA | O40: 2 | P40: 2 | Q40: =VLOOKUP(P40,Key!$E$2:$F$9,2,FALSE) -> Work | R40: =K40&"-"&Q40 -> Work-Work | S40: 300 | T40: 6 | U40: 4 | Y40: Y | Z40: 0
B41: 0.50138889 | C41: UAQ 137Z | D41: 2 | E41: 2 | F41: MAKERERE | G41: KAMPALA | H41: UGA | I41: 2 | J41: 2 | K41: =VLOOKUP(J41,Key!$E$2:$F$9,2,FALSE) -> Work | L41: WAKISO | M41: WAKISO | N41: UGA | O41: 2 | P41: 2 | Q41: =VLOOKUP(P41,Key!$E$2:$F$9,2,FALSE) -> Work | R41: =K41&"-"&Q41 -> Work-Work | T41: 0.5 | U41: 3 | Y41: Y | Z41: 500
B42: 0.49791667 | C42: UAF 364C | D42: 2 | E42: 3 | F42: KASANGATI | G42: WAKISO | H42: UGA | I42: 16 | J42: 8 | K42: =VLOOKUP(J42,Key!$E$2:$F$9,2,FALSE) -> Others | L42: KITEGOBWA | M42: WAKISO | N42: UGA | O42: 16 | P42: 2 | Q42: =VLOOKUP(P42,Key!$E$2:$F$9,2,FALSE) -> Work | R42: =K42&"-"&Q42 -> Others-Work | U42: 1 | Y42: Y | Z42: 2000
B43: 0.49027778 | C43: UBB 353M | D43: 1 | E43: 1 | F43: KASANGATI | G43: WAKISO | H43: UGA | I43: 2 | J43: 2 | K43: =VLOOKUP(J43,Key!$E$2:$F$9,2,FALSE) -> Work | L43: KASANGATI | M43: WAKISO | N43: UGA | O43: 2 | P43: 2 | Q43: =VLOOKUP(P43,Key!$E$2:$F$9,2,FALSE) -> Work | R43: =K43&"-"&Q43 -> Work-Work | U43: 1 | Y43: Y | Z43: 0
B44: 0.48819444 | C44: UBB 050R | D44: 1 | E44: 5 | F44: ENTEBBE | G44: WAKISO | H44: UGA | I44: 1 | J44: 1 | K44: =VLOOKUP(J44,Key!$E$2:$F$9,2,FALSE) -> Home | L44: NALUSOGA | M44: WAKISO | N44: UGA | O44: 1 | P44: 1 | Q44: =VLOOKUP(P44,Key!$E$2:$F$9,2,FALSE) -> Home | R44: =K44&"-"&Q44 -> Home-Home | T44: 0.5 | U44: 3 | Y44: Y | Z44: 500
B45: 0.48402778 | C45: UAX 315T | D45: 1 | E45: 2 | F45: KAMPALA | G45: KAMPALA | H45: UGA | I45: 16 | J45: 2 | K45: =VLOOKUP(J45,Key!$E$2:$F$9,2,FALSE) -> Work | L45: NANGABO | M45: WAKISO | N45: UGA | O45: 16 | P45: 2 | Q45: =VLOOKUP(P45,Key!$E$2:$F$9,2,FALSE) -> Work | R45: =K45&"-"&Q45 -> Work-Work | T45: 0.2 | U45: 6 | Y45: Y | Z45: 2000
B46: 0.48263889 | C46: UAU 418F | D46: 4 | E46: 16 | F46: KASANGATI | G46: WAKISO | H46: UGA | I46: 6 | J46: 2 | K46: =VLOOKUP(J46,Key!$E$2:$F$9,2,FALSE) -> Work | L46: MATUGGA | M46: WAKISO | N46: UGA | O46: 6 | P46: 2 | Q46: =VLOOKUP(P46,Key!$E$2:$F$9,2,FALSE) -> Work | R46: =K46&"-"&Q46 -> Work-Work | S46: 4 | U46: 1 | Y46: Y | Z46: 2000
B47: 0.47916667 | C47: UAE 827H | D47: 2 | E47: 1 | F47: NAKWERO | G47: WAKISO | H47: UGA | I47: 1 | J47: 1 | K47: =VLOOKUP(J47,Key!$E$2:$F$9,2,FALSE) -> Home | L47: MASINDI | M47: MASINDI | N47: UGA | O47: 2 | P47: 2 | Q47: =VLOOKUP(P47,Key!$E$2:$F$9,2,FALSE) -> Work | R47: =K47&"-"&Q47 -> Home-Work | S47: 290 | T47: 3 | U47: 4 | Y47: Y | Z47: 0
B48: 0.47291667 | C48: UAK 718G | D48: 7 | E48: 8 | F48: KASANGATI | G48: WAKISO | H48: UGA | I48: 16 | J48: 8 | K48: =VLOOKUP(J48,Key!$E$2:$F$9,2,FALSE) -> Others | L48: NANGABO | M48: WAKISO | N48: UGA | O48: 15 | P48: 2 | Q48: =VLOOKUP(P48,Key!$E$2:$F$9,2,FALSE) -> Work | R48: =K48&"-"&Q48 -> Others-Work | T48: 0.1 | U48: 1 | Y48: Y | Z48: 0
B49: 0.47083333 | C49: UAN 261D | D49: 10 | E49: 1 | F49: NTINDA | G49: KAMPALA | H49: UGA | I49: 11 | J49: 4 | K49: =VLOOKUP(J49,Key!$E$2:$F$9,2,FALSE) -> Commercial | L49: MATUGGA | M49: WAKISO | N49: UGA | O49: 3 | P49: 2 | Q49: =VLOOKUP(P49,Key!$E$2:$F$9,2,FALSE) -> Work | R49: =K49&"-"&Q49 -> Commercial-Work | T49: 0.7 | U49: 3 | Y49: Y | Z49: 3000
B50: 0.46666667 | C50: UAX 769C | D50: 1 | E50: 2 | F50: BWEYOGERERE | G50: WAKISO | H50: UGA | I50: 1 | J50: 1 | K50: =VLOOKUP(J50,Key!$E$2:$F$9,2,FALSE) -> Home | L50: MATUGGA | M50: WAKISO | N50: UGA | O50: 11 | P50: 2 | Q50: =VLOOKUP(P50,Key!$E$2:$F$9,2,FALSE) -> Work | R50: =K50&"-"&Q50 -> Home-Work | T50: 0.7 | U50: 3 | Y50: Y | Z50: 1000
B51: 0.46319444 | C51: UBB 871M | D51: 1 | E51: 1 | F51: KASANGATI | G51: WAKISO | H51: UGA | I51: 1 | J51: 1 | K51: =VLOOKUP(J51,Key!$E$2:$F$9,2,FALSE) -> Home | L51: MATUGGA | M51: WAKISO | N51: UGA | O51: 3 | P51: 2 | Q51: =VLOOKUP(P51,Key!$E$2:$F$9,2,FALSE) -> Work | R51: =K51&"-"&Q51 -> Home-Work | U51: 2 | Y51: Y | Z51: 1000
