Workbook
Name Dist: 'ALL DATA'!$S:$S
Name Jtime: 'ALL DATA'!$T:$T
Name Pay: 'ALL DATA'!$Z:$Z
Name Tripfreq: 'ALL DATA'!$U:$U
Name Veh: 'ALL DATA'!$D:$D
Name Veh_Type: '26.10 ISINGIRO-MBARARA'!$D$9:$D$37
Name Veh_Type: '28.10 ISINGIRO-MBARARA'!$D$9:$D$37
Name Veh_Type: 'ALL DATA'!$D$9:$D$37
Name Veh_Type: '[1]25.07 BUSEGA-NATEETE'!$D:$D
Name Veh_Type: '[1]25.07 BUSEGA-NATEETE'!$D:$D
Name Veh_Type: '28.10 MBARARA-ISINGIRO'!$D$9:$D$37
Name zones: #REF!
Name zones: #REF!
Name zones: #REF!
Name Zones_Ndeke: #REF!
Name Zones_Ndeke: #REF!
Name Zones_Ndeke: #REF!

Sheet Analysis
B3: Vehicle OD Sample Proportions | N3: Average Journey Time
B4: Vehicle Types | C4: OD Sample | D4: OD Sample, % | N4: Journey Time Range (Hrs) | O4: Cummu-lative | P4: No of Vehicles | Q4: No. of Vehicles, %
B5: Car | C5: =COUNTIF('ALL DATA'!$D$9:$D$5000,"1") -> 152 | D5: =C5/$C$17 -> 0.42105263 | N5: 0-0.25 | O5: =COUNTIF(Jtime,"<=0.25") -> 89 | P5: =O5 -> 89 | Q5: =P5/$O$15 -> 0.26176471
B6: Station Wagon | C6: =COUNTIF('ALL DATA'!$D$9:$D$5000,"2") -> 34 | D6: =C6/$C$17 -> 0.094182825 | N6: 0.25-0.50 | O6: =COUNTIF(Jtime,"<=0.5") -> 209 | P6: =O6-O5 -> 120 | Q6: =P6/$O$15 -> 0.35294118
B7: Pickups | C7: =COUNTIF('ALL DATA'!$D$9:$D$5000,"3") -> 23 | D7: =C7/$C$17 -> 0.063711911 | N7: 0.50-0.75 | O7: =COUNTIF(Jtime,"<=0.75") -> 221 | P7: =O7-O6 -> 12 | Q7: =P7/$O$15 -> 0.035294118
B8: Minibus, matatu | C8: =COUNTIF('ALL DATA'!$D$9:$D$5000,"4") -> 13 | D8: =C8/$C$17 -> 0.03601108 | N8: 0.75-1.00 | O8: =COUNTIF(Jtime,"<=1.0") -> 273 | P8: =O8-O7 -> 52 | Q8: =P8/$O$15 -> 0.15294118
B9: Medium bus | C9: =COUNTIF('ALL DATA'!$D$9:$D$5000,"5") -> 1 | D9: =C9/$C$17 -> 0.0027700831 | N9: 1.00-1.50 | O9: =COUNTIF(Jtime,"<=1.5") -> 293 | P9: =O9-O8 -> 20 | Q9: =P9/$O$15 -> 0.058823529
B10: Large Bus | C10: =COUNTIF('ALL DATA'!$D$9:$D$5000,"6") -> 0 | D10: =C10/$C$17 -> 0 | N10: 1.5-2.0 | O10: =COUNTIF(Jtime,"<=2") -> 319 | P10: =O10-O9 -> 26 | Q10: =P10/$O$15 -> 0.076470588
B11: Light Truck | C11: =COUNTIF('ALL DATA'!$D$9:$D$5000,"7") -> 36 | D11: =C11/$C$17 -> 0.099722992 | N11: 2.0-3.0 | O11: =COUNTIF(Jtime,"<=3") -> 325 | P11: =O11-O10 -> 6 | Q11: =P11/$O$15 -> 0.017647059
B12: Medium Truck | C12: =COUNTIF('ALL DATA'!$D$9:$D$5000,"8") -> 35 | D12: =C12/$C$17 -> 0.096952909 | N12: 3.0-5.0 | O12: =COUNTIF(Jtime,"<=5") -> 335 | P12: =O12-O11 -> 10 | Q12: =P12/$O$15 -> 0.029411765
B13: Heavy truck | C13: =COUNTIF('ALL DATA'!$D$9:$D$5000,"9") -> 2 | D13: =C13/$C$17 -> 0.0055401662 | N13: 5.0-7.5 | O13: =COUNTIF(Jtime,"<=7.5") -> 339 | P13: =O13-O12 -> 4 | Q13: =P13/$O$15 -> 0.011764706
B14: Truck Trailer | C14: =COUNTIF('ALL DATA'!$D$9:$D$5000,"10") -> 1 | D14: =C14/$C$17 -> 0.0027700831 | N14: 7.5-10 | O14: =COUNTIF(Jtime,"<=10") -> 339 | P14: =O14-O13 -> 0 | Q14: =P14/$O$15 -> 0
B15: Motor cycles | C15: =COUNTIF('ALL DATA'!$D$9:$D$5000,"11") -> 64 | D15: =C15/$C$17 -> 0.17728532 | N15: Over 10 | O15: =COUNTIF(Jtime,"<=15") -> 340 | P15: =O15-O14 -> 1 | Q15: =P15/$O$15 -> 0.0029411765
B16: Tractors | C16: =COUNTIF('ALL DATA'!$D$9:$D$5000,"12") -> 0 | D16: =C16/$C$17 -> 0
C17: =SUM(C5:C16) -> 361
N21: Trip Frequency
B22: Journey Purpose | N22: Trip Frequency | O22: No of Vehicles | P22: No. of Vehicles, %
B23: Purpose | C23: Respondents | D23: Percent | N23: More than 2 times every day | O23: =COUNTIF(Tripfreq,"=1") -> 74 | P23: =O23/$O$29 -> 0.2084507
B24: Home-Work | C24: =COUNTIF('ALL DATA'!$R$9:$R$5000,"Home-Work") -> 52 | D24: =C24/$C$29 -> 0.14404432 | N24: Daily (Up and Down) | O24: =COUNTIF(Tripfreq,"=2") -> 129 | P24: =O24/$O$29 -> 0.36338028
B25: Home-Study | C25: =COUNTIF('ALL DATA'!$R$9:$R$369,"Home-Study") -> 18 | D25: =C25/$C$29 -> 0.049861496 | N25: 2/3 times a week | O25: =COUNTIF(Tripfreq,"=3") -> 84 | P25: =O25/$O$29 -> 0.23661972
B26: Work-Home | C26: =COUNTIF('ALL DATA'!$R$9:$R$369,"Work-Home") -> 69 | D26: =C26/$C$29 -> 0.19113573 | N26: Once a week | O26: =COUNTIF(Tripfreq,"=4") -> 44 | P26: =O26/$O$29 -> 0.12394366
B27: Work-Work | C27: =COUNTIF('ALL DATA'!$R$9:$R$369,"Work-Work") -> 47 | D27: =C27/$C$29 -> 0.13019391 | N27: Once a month | O27: =COUNTIF(Tripfreq,"=5") -> 9 | P27: =O27/$O$29 -> 0.025352113
B28: Others | C28: =C29-SUM(C24:C27) -> 175 | D28: =C28/$C$29 -> 0.48476454 | N28: Once in a while | O28: =COUNTIF(Tripfreq,"=6") -> 15 | P28: =O28/$O$29 -> 0.042253521
B29: Total | C29: =C17 -> 361 | O29: =SUM(O23:O28) -> 355
B40: Expressway Use
B41: Response | C41: Number | D41: Percent
B42: Yes | C42: =COUNTIF('ALL DATA'!$Y$9:$Y$5000,"Y") -> 361 | D42: =C42/$C$44 -> 1
B43: No | C43: =C44-C42 -> 0 | D43: =C43/$C$44 -> 0
B44: Total | C44: =C29 -> 361
R47: Home | S47: Work | T47: Study | U47: Commercial | V47: Tourism | W47: Leisure/Social | X47: Hospital | Y47: Others
P48: 1 | Q48: Home | R48: =R59/SUM($R$59:$Y$66) -> 0.04735376 | S48: =S59/SUM($R$59:$Y$66) -> 0.1448468 | T48: =T59/SUM($R$59:$Y$66) -> 0.050139276 | U48: =U59/SUM($R$59:$Y$66) -> 0.044568245 | V48: =V59/SUM($R$59:$Y$66) -> 0 | W48: =W59/SUM($R$59:$Y$66) -> 0.008356546 | X48: =X59/SUM($R$59:$Y$66) -> 0.019498607 | Y48: =Y59/SUM($R$59:$Y$66) -> 0.050139276
P49: 2 | Q49: Work | R49: =R60/SUM($R$59:$Y$66) -> 0.19220056 | S49: =S60/SUM($R$59:$Y$66) -> 0.13091922 | T49: =T60/SUM($R$59:$Y$66) -> 0.0055710306 | U49: =U60/SUM($R$59:$Y$66) -> 0.066852368 | V49: =V60/SUM($R$59:$Y$66) -> 0 | W49: =W60/SUM($R$59:$Y$66) -> 0 | X49: =X60/SUM($R$59:$Y$66) -> 0 | Y49: =Y60/SUM($R$59:$Y$66) -> 0.0055710306
P50: 3 | Q50: Study | R50: =R61/SUM($R$59:$Y$66) -> 0.052924791 | S50: =S61/SUM($R$59:$Y$66) -> 0.0027855153 | T50: =T61/SUM($R$59:$Y$66) -> 0.0055710306 | U50: =U61/SUM($R$59:$Y$66) -> 0.0027855153 | V50: =V61/SUM($R$59:$Y$66) -> 0.0027855153 | W50: =W61/SUM($R$59:$Y$66) -> 0 | X50: =X61/SUM($R$59:$Y$66) -> 0 | Y50: =Y61/SUM($R$59:$Y$66) -> 0.0055710306
P51: 4 | Q51: Commercial | R51: =R62/SUM($R$59:$Y$66) -> 0.033426184 | S51: =S62/SUM($R$59:$Y$66) -> 0.025069638 | T51: =T62/SUM($R$59:$Y$66) -> 0.0027855153 | U51: =U62/SUM($R$59:$Y$66) -> 0.033426184 | V51: =V62/SUM($R$59:$Y$66) -> 0 | W51: =W62/SUM($R$59:$Y$66) -> 0 | X51: =X62/SUM($R$59:$Y$66) -> 0 | Y51: =Y62/SUM($R$59:$Y$66) -> 0
P52: 5 | Q52: Tourism | R52: =R63/SUM($R$59:$Y$66) -> 0 | S52: =S63/SUM($R$59:$Y$66) -> 0 | T52: =T63/SUM($R$59:$Y$66) -> 0 | U52: =U63/SUM($R$59:$Y$66) -> 0 | V52: =V63/SUM($R$59:$Y$66) -> 0 | W52: =W63/SUM($R$59:$Y$66) -> 0 | X52: =X63/SUM($R$59:$Y$66) -> 0 | Y52: =Y63/SUM($R$59:$Y$66) -> 0
P53: 6 | Q53: Leisure/Social | R53: =R64/SUM($R$59:$Y$66) -> 0.013927577 | S53: =S64/SUM($R$59:$Y$66) -> 0 | T53: =T64/SUM($R$59:$Y$66) -> 0 | U53: =U64/SUM($R$59:$Y$66) -> 0 | V53: =V64/SUM($R$59:$Y$66) -> 0 | W53: =W64/SUM($R$59:$Y$66) -> 0 | X53: =X64/SUM($R$59:$Y$66) -> 0 | Y53: =Y64/SUM($R$59:$Y$66) -> 0.0027855153
P54: 7 | Q54: Hospital | R54: =R65/SUM($R$59:$Y$66) -> 0.0055710306 | S54: =S65/SUM($R$59:$Y$66) -> 0 | T54: =T65/SUM($R$59:$Y$66) -> 0 | U54: =U65/SUM($R$59:$Y$66) -> 0 | V54: =V65/SUM($R$59:$Y$66) -> 0 | W54: =W65/SUM($R$59:$Y$66) -> 0 | X54: =X65/SUM($R$59:$Y$66) -> 0.008356546 | Y54: =Y65/SUM($R$59:$Y$66) -> 0
P55: 8 | Q55: Others | R55: =R66/SUM($R$59:$Y$66) -> 0.019498607 | S55: =S66/SUM($R$59:$Y$66) -> 0.0027855153 | T55: =T66/SUM($R$59:$Y$66) -> 0 | U55: =U66/SUM($R$59:$Y$66) -> 0.0027855153 | V55: =V66/SUM($R$59:$Y$66) -> 0 | W55: =W66/SUM($R$59:$Y$66) -> 0 | X55: =X66/SUM($R$59:$Y$66) -> 0 | Y55: =Y66/SUM($R$59:$Y$66) -> 0.011142061
R57: 1 | S57: 2 | T57: 3 | U57: 4 | V57: 5 | W57: 6 | X57: 7 | Y57: 8
B58: Willingness to Pay | R58: Home | S58: Work | T58: Study | U58: Commercial | V58: Tourism | W58: Leisure/Social | X58: Hospital | Y58: Others
B59: Vehicle Types | C59: Average Price | P59: 1 | Q59: Home | R59: =COUNTIF('ALL DATA'!$R$9:$R$5000,R69) -> 17 | S59: =COUNTIF('ALL DATA'!$R$9:$R$5000,S69) -> 52 | T59: =COUNTIF('ALL DATA'!$R$9:$R$5000,T69) -> 18 | U59: =COUNTIF('ALL DATA'!$R$9:$R$5000,U69) -> 16 | V59: =COUNTIF('ALL DATA'!$R$9:$R$5000,V69) -> 0 | W59: =COUNTIF('ALL DATA'!$R$9:$R$5000,W69) -> 3 | X59: =COUNTIF('ALL DATA'!$R$9:$R$5000,X69) -> 7 | Y59: =COUNTIF('ALL DATA'!$R$9:$R$5000,Y69) -> 18
B60: Car | C60: 0 | P60: 2 | Q60: Work | R60: =COUNTIF('ALL DATA'!$R$9:$R$5000,R70) -> 69 | S60: =COUNTIF('ALL DATA'!$R$9:$R$5000,S70) -> 47 | T60: =COUNTIF('ALL DATA'!$R$9:$R$5000,T70) -> 2 | U60: =COUNTIF('ALL DATA'!$R$9:$R$5000,U70) -> 24 | V60: =COUNTIF('ALL DATA'!$R$9:$R$5000,V70) -> 0 | W60: =COUNTIF('ALL DATA'!$R$9:$R$5000,W70) -> 0 | X60: =COUNTIF('ALL DATA'!$R$9:$R$5000,X70) -> 0 | Y60: =COUNTIF('ALL DATA'!$R$9:$R$5000,Y70) -> 2
B61: Station Wagon | C61: 0 | P61: 3 | Q61: Study | R61: =COUNTIF('ALL DATA'!$R$9:$R$5000,R71) -> 19 | S61: =COUNTIF('ALL DATA'!$R$9:$R$5000,S71) -> 1 | T61: =COUNTIF('ALL DATA'!$R$9:$R$5000,T71) -> 2 | U61: =COUNTIF('ALL DATA'!$R$9:$R$5000,U71) -> 1 | V61: =COUNTIF('ALL DATA'!$R$9:$R$5000,V71) -> 1 | W61: =COUNTIF('ALL DATA'!$R$9:$R$5000,W71) -> 0 | X61: =COUNTIF('ALL DATA'!$R$9:$R$5000,X71) -> 0 | Y61: =COUNTIF('ALL DATA'!$R$9:$R$5000,Y71) -> 2
B62: Pickups | C62: 0 | P62: 4 | Q62: Commercial | R62: =COUNTIF('ALL DATA'!$R$9:$R$5000,R72) -> 12 | S62: =COUNTIF('ALL DATA'!$R$9:$R$5000,S72) -> 9 | T62: =COUNTIF('ALL DATA'!$R$9:$R$5000,T72) -> 1 | U62: =COUNTIF('ALL DATA'!$R$9:$R$5000,U72) -> 12 | V62: =COUNTIF('ALL DATA'!$R$9:$R$5000,V72) -> 0 | W62: =COUNTIF('ALL DATA'!$R$9:$R$5000,W72) -> 0 | X62: =COUNTIF('ALL DATA'!$R$9:$R$5000,X72) -> 0 | Y62: =COUNTIF('ALL DATA'!$R$9:$R$5000,Y72) -> 0
B63: Minibus, matatu | C63: 0 | P63: 5 | Q63: Tourism | R63: =COUNTIF('ALL DATA'!$R$9:$R$5000,R73) -> 0 | S63: =COUNTIF('ALL DATA'!$R$9:$R$5000,S73) -> 0 | T63: =COUNTIF('ALL DATA'!$R$9:$R$5000,T73) -> 0 | U63: =COUNTIF('ALL DATA'!$R$9:$R$5000,U73) -> 0 | V63: =COUNTIF('ALL DATA'!$R$9:$R$5000,V73) -> 0 | W63: =COUNTIF('ALL DATA'!$R$9:$R$5000,W73) -> 0 | X63: =COUNTIF('ALL DATA'!$R$9:$R$5000,X73) -> 0 | Y63: =COUNTIF('ALL DATA'!$R$9:$R$5000,Y73) -> 0
B64: Medium bus | C64: 0 | P64: 6 | Q64: Leisure/Social | R64: =COUNTIF('ALL DATA'!$R$9:$R$5000,R74) -> 5 | S64: =COUNTIF('ALL DATA'!$R$9:$R$5000,S74) -> 0 | T64: =COUNTIF('ALL DATA'!$R$9:$R$5000,T74) -> 0 | U64: =COUNTIF('ALL DATA'!$R$9:$R$5000,U74) -> 0 | V64: =COUNTIF('ALL DATA'!$R$9:$R$5000,V74) -> 0 | W64: =COUNTIF('ALL DATA'!$R$9:$R$5000,W74) -> 0 | X64: =COUNTIF('ALL DATA'!$R$9:$R$5000,X74) -> 0 | Y64: =COUNTIF('ALL DATA'!$R$9:$R$5000,Y74) -> 1
B65: Large Bus | C65: 0 | P65: 7 | Q65: Hospital | R65: =COUNTIF('ALL DATA'!$R$9:$R$5000,R75) -> 2 | S65: =COUNTIF('ALL DATA'!$R$9:$R$5000,S75) -> 0 | T65: =COUNTIF('ALL DATA'!$R$9:$R$5000,T75) -> 0 | U65: =COUNTIF('ALL DATA'!$R$9:$R$5000,U75) -> 0 | V65: =COUNTIF('ALL DATA'!$R$9:$R$5000,V75) -> 0 | W65: =COUNTIF('ALL DATA'!$R$9:$R$5000,W75) -> 0 | X65: =COUNTIF('ALL DATA'!$R$9:$R$5000,X75) -> 3 | Y65: =COUNTIF('ALL DATA'!$R$9:$R$5000,Y75) -> 0
B66: Light Truck | C66: 0 | P66: 8 | Q66: Others | R66: =COUNTIF('ALL DATA'!$R$9:$R$5000,R76) -> 7 | S66: =COUNTIF('ALL DATA'!$R$9:$R$5000,S76) -> 1 | T66: =COUNTIF('ALL DATA'!$R$9:$R$5000,T76) -> 0 | U66: =COUNTIF('ALL DATA'!$R$9:$R$5000,U76) -> 1 | V66: =COUNTIF('ALL DATA'!$R$9:$R$5000,V76) -> 0 | W66: =COUNTIF('ALL DATA'!$R$9:$R$5000,W76) -> 0 | X66: =COUNTIF('ALL DATA'!$R$9:$R$5000,X76) -> 0 | Y66: =COUNTIF('ALL DATA'!$R$9:$R$5000,Y76) -> 4
B67: Medium Truck | C67: 0
B68: Heavy truck | C68: 0 | R68: Home | S68: Work | T68: Study | U68: Commercial | V68: Tourism | W68: Leisure/Social | X68: Hospital | Y68: Others
B69: Truck Trailer | C69: 0 | P69: 1 | Q69: Home | R69: =$Q69&"-"&R$68 -> Home-Home | S69: =$Q69&"-"&S$68 -> Home-Work | T69: =$Q69&"-"&T$68 -> Home-Study | U69: =$Q69&"-"&U$68 -> Home-Commercial | V69: =$Q69&"-"&V$68 -> Home-Tourism | W69: =$Q69&"-"&W$68 -> Home-Leisure/Social | X69: =$Q69&"-"&X$68 -> Home-Hospital | Y69: =$Q69&"-"&Y$68 -> Home-Others
B70: Motor cycles | C70: 0 | P70: 2 | Q70: Work | R70: =$Q70&"-"&R$68 -> Work-Home | S70: =$Q70&"-"&S$68 -> Work-Work | T70: =$Q70&"-"&T$68 -> Work-Study | U70: =$Q70&"-"&U$68 -> Work-Commercial | V70: =$Q70&"-"&V$68 -> Work-Tourism | W70: =$Q70&"-"&W$68 -> Work-Leisure/Social | X70: =$Q70&"-"&X$68 -> Work-Hospital | Y70: =$Q70&"-"&Y$68 -> Work-Others
B71: Tractors | C71: 0 | P71: 3 | Q71: Study | R71: =$Q71&"-"&R$68 -> Study-Home | S71: =$Q71&"-"&S$68 -> Study-Work | T71: =$Q71&"-"&T$68 -> Study-Study | U71: =$Q71&"-"&U$68 -> Study-Commercial | V71: =$Q71&"-"&V$68 -> Study-Tourism | W71: =$Q71&"-"&W$68 -> Study-Leisure/Social | X71: =$Q71&"-"&X$68 -> Study-Hospital | Y71: =$Q71&"-"&Y$68 -> Study-Others
P72: 4 | Q72: Commercial | R72: =$Q72&"-"&R$68 -> Commercial-Home | S72: =$Q72&"-"&S$68 -> Commercial-Work | T72: =$Q72&"-"&T$68 -> Commercial-Study | U72: =$Q72&"-"&U$68 -> Commercial-Commercial | V72: =$Q72&"-"&V$68 -> Commercial-Tourism | W72: =$Q72&"-"&W$68 -> Commercial-Leisure/Social | X72: =$Q72&"-"&X$68 -> Commercial-Hospital | Y72: =$Q72&"-"&Y$68 -> Commercial-Others
P73: 5 | Q73: Tourism | R73: =$Q73&"-"&R$68 -> Tourism-Home | S73: =$Q73&"-"&S$68 -> Tourism-Work | T73: =$Q73&"-"&T$68 -> Tourism-Study | U73: =$Q73&"-"&U$68 -> Tourism-Commercial | V73: =$Q73&"-"&V$68 -> Tourism-Tourism | W73: =$Q73&"-"&W$68 -> Tourism-Leisure/Social | X73: =$Q73&"-"&X$68 -> Tourism-Hospital | Y73: =$Q73&"-"&Y$68 -> Tourism-Others
P74: 6 | Q74: Leisure/Social | R74: =$Q74&"-"&R$68 -> Leisure/Social-Home | S74: =$Q74&"-"&S$68 -> Leisure/Social-Work | T74: =$Q74&"-"&T$68 -> Leisure/Social-Study | U74: =$Q74&"-"&U$68 -> Leisure/Social-Commercial | V74: =$Q74&"-"&V$68 -> Leisure/Social-Tourism | W74: =$Q74&"-"&W$68 -> Leisure/Social-Leisure/Social | X74: =$Q74&"-"&X$68 -> Leisure/Social-Hospital | Y74: =$Q74&"-"&Y$68 -> Leisure/Social-Others
P75: 7 | Q75: Hospital | R75: =$Q75&"-"&R$68 -> Hospital-Home | S75: =$Q75&"-"&S$68 -> Hospital-Work | T75: =$Q75&"-"&T$68 -> Hospital-Study | U75: =$Q75&"-"&U$68 -> Hospital-Commercial | V75: =$Q75&"-"&V$68 -> Hospital-Tourism | W75: =$Q75&"-"&W$68 -> Hospital-Leisure/Social | X75: =$Q75&"-"&X$68 -> Hospital-Hospital | Y75: =$Q75&"-"&Y$68 -> Hospital-Others
P76: 8 | Q76: Others | R76: =$Q76&"-"&R$68 -> Others-Home | S76: =$Q76&"-"&S$68 -> Others-Work | T76: =$Q76&"-"&T$68 -> Others-Study | U76: =$Q76&"-"&U$68 -> Others-Commercial | V76: =$Q76&"-"&V$68 -> Others-Tourism | W76: =$Q76&"-"&W$68 -> Others-Leisure/Social | X76: =$Q76&"-"&X$68 -> Others-Hospital | Y76: =$Q76&"-"&Y$68 -> Others-Others
B78: Average Trip Length
B79: Trip Length Range | C79: Cumm-ulative | D79: No of Vehicles | E79: Percentage
B80: 0-1 | C80: =COUNTIF(Dist,"<=1") -> 12 | D80: =C80 -> 12 | E80: =D80/$C$88 -> 0.037735849
B81: 1-2.5 | C81: =COUNTIF(Dist,"<=2.5") -> 20 | D81: =C81-C80 -> 8 | E81: =D81/$C$88 -> 0.025157233
B82: 2.5-5.0 | C82: =COUNTIF(Dist,"<=5") -> 83 | D82: =C82-C81 -> 63 | E82: =D82/$C$88 -> 0.19811321
B83: 5.0-10.0 | C83: =COUNTIF(Dist,"<=10") -> 144 | D83: =C83-C82 -> 61 | E83: =D83/$C$88 -> 0.1918239
B84: 10.0-20.0 | C84: =COUNTIF(Dist,"<=20") -> 213 | D84: =C84-C83 -> 69 | E84: =D84/$C$88 -> 0.21698113
B85: 20.0-50.0 | C85: =COUNTIF(Dist,"<=50") -> 281 | D85: =C85-C84 -> 68 | E85: =D85/$C$88 -> 0.21383648
B86: 50.0-100.0 | C86: =COUNTIF(Dist,"<=100") -> 300 | D86: =C86-C85 -> 19 | E86: =D86/$C$88 -> 0.059748428
B87: 100.0-250.0 | C87: =COUNTIF(Dist,"<=250") -> 307 | D87: =C87-C86 -> 7 | E87: =D87/$C$88 -> 0.022012579
B88: Over 250 | C88: =COUNTIF(Dist,"<=700") -> 318 | D88: =C88-C87 -> 11 | E88: =D88/$C$88 -> 0.034591195

Sheet ALL DATA
B1: Consultancy services for Preparation of Expressway Development Master Plan (EDMP) for Uganda
B2: Roadside OD Interview Survey
B4: Date: | C4: 26.10.2019 | E4: Road Name: | F4: ='26.10 MBARARA-ISINGIRO'!F4:G4 -> MBARARA-NTUNGAMO ROAD | I4: Direction From: | L4: ISINGIRO | N4: Interviewers: | O4: AMOS.A, TUMUKUNDE DEVIS | V4: Supervisor: | W4: ='26.10 MBARARA-ISINGIRO'!W4 -> MIREMBE RUTH | Y4: Coded By: | Z4: ='26.10 MBARARA-ISINGIRO'!Z4 -> AJOK EMILY | AA4: Chkd By: | AB4: ='26.10 MBARARA-ISINGIRO'!AB4 -> 0
I5: Direction To: | L5: MBARARA
B7: Time | C7: Veh_Reg_No. | D7: Veh_Type | E7: No. Occupants | F7: Origin_Address | I7: Origin_Establish | J7: Origin_Purpose | K7: Origin-Purpose Desc | L7: Destination_Address | O7: Destination_Establish | P7: Destination_Purpose | Q7: Destination_Purpose Desc | R7: Journey_Purpose | S7: Approx_Distance (Km) | T7: Approx_Journey Time (Hrs) | U7: Trip_Frequency | V7: GOODS VEHICLES ONLY | Y7: Would You Use Xpressways? | Z7: Pay How Much? (UGX) | AA7: Origin_Zone | AB7: Dest_Zone
F8: Village or Town | G8: District | H8: Country | L8: Village or Town | M8: District | N8: Country | V8: Goods_Type | W8: Goods_Quantity (Ton) | X8: Goods_Value (UGXm)
B9: 0.7625 | C9: UAU 995A | D9: 4 | E9: 2 | F9: KABEREBERE | G9: ISINGIRO | H9: UG | I9: 6 | J9: 2 | K9: =VLOOKUP(J9,Key!$E$2:$F$9,2,FALSE) -> Work | L9: MBARARA TOWN | M9: MBARARA | N9: UG | O9: 6 | P9: 2 | Q9: =VLOOKUP(P9,Key!$E$2:$F$9,2,FALSE) -> Work | R9: =K9&"-"&Q9 -> Work-Work | S9: 15 | T9: 0.5 | U9: 4 | Y9: Y | AA9: =VLOOKUP(F9,'Zones (3)'!$A$2:$F$15913,6,FALSE) -> 380 | AB9: =VLOOKUP(L9,'Zones (3)'!$A$1:$F$15616,6,FALSE) -> 987
B10: 0.75902778 | C10: UAY 487N | D10: 2 | E10: 2 | F10: KABALE | G10: KABALE | H10: UG | I10: 1 | J10: 1 | K10: =VLOOKUP(J10,Key!$E$2:$F$9,2,FALSE) -> Home | L10: MBARARA TOWN | M10: MBARARA | N10: UG | O10: 2 | P10: 2 | Q10: =VLOOKUP(P10,Key!$E$2:$F$9,2,FALSE) -> Work | R10: =K10&"-"&Q10 -> Home-Work | S10: 5 | T10: 0.2 | U10: 5 | Y10: Y | AA10: =VLOOKUP(F10,'Zones (3)'!$A$2:$F$15913,6,FALSE) -> 422 | AB10: =VLOOKUP(L10,'Zones (3)'!$A$1:$F$15616,6,FALSE) -> 987
B11: 0.75416667 | C11: UAY 682D | D11: 1 | E11: 2 | F11: RWENZIRINGIRO | G11: ISINGIRO | H11: UG | I11: 4 | J11: 3 | K11: =VLOOKUP(J11,Key!$E$2:$F$9,2,FALSE) -> Study | L11: MBARARA TOWN | M11: MBARARA | N11: UG | O11: 1 | P11: 1 | Q11: =VLOOKUP(P11,Key!$E$2:$F$9,2,FALSE) -> Home | R11: =K11&"-"&Q11 -> Study-Home | T11: 0.3 | U11: 3 | Y11: Y | AA11: =VLOOKUP(F11,'Zones (3)'!$A$2:$F$15913,6,FALSE) -> 1439 | AB11: =VLOOKUP(L11,'Zones (3)'!$A$1:$F$15616,6,FALSE) -> 987
B12: 0.75208333 | C12: UAP 980K | D12: 2 | E12: 1 | F12: KABALE | G12: KABALE | H12: UG | I12: 1 | J12: 1 | K12: =VLOOKUP(J12,Key!$E$2:$F$9,2,FALSE) -> Home | L12: MBARARA TOWN | M12: MBARARA | N12: UG | O12: 2 | P12: 2 | Q12: =VLOOKUP(P12,Key!$E$2:$F$9,2,FALSE) -> Work | R12: =K12&"-"&Q12 -> Home-Work | S12: 4 | T12: 0.2 | U12: 3 | Y12: Y | AA12: =VLOOKUP(F12,'Zones (3)'!$A$2:$F$15913,6,FALSE) -> 422 | AB12: =VLOOKUP(L12,'Zones (3)'!$A$1:$F$15616,6,FALSE) -> 987
B13: 0.74861111 | C13: UAQ 168G | D13: 1 | E13: 1 | F13: KABALE | G13: KABALE | H13: UG | I13: 16 | J13: 8 | K13: =VLOOKUP(J13,Key!$E$2:$F$9,2,FALSE) -> Others | L13: MBARARA TOWN | M13: MBARARA | N13: UG | O13: 16 | P13: 8 | Q13: =VLOOKUP(P13,Key!$E$2:$F$9,2,FALSE) -> Others | R13: =K13&"-"&Q13 -> Others-Others | S13: 10 | T13: 0.2 | U13: 6 | Y13: Y | AA13: =VLOOKUP(F13,'Zones (3)'!$A$2:$F$15913,6,FALSE) -> 422 | AB13: =VLOOKUP(L13,'Zones (3)'!$A$1:$F$15616,6,FALSE) -> 987
B14: 0.74513889 | C14: UAF 911X | D14: 1 | E14: 1 | F14: KABEREBERE | G14: ISINGIRO | H14: UG | I14: 2 | J14: 2 | K14: Work | L14: NYAMITANGA | M14: MBARARA | N14: UG | O14: 1 | P14: 1 | Q14: =VLOOKUP(P14,Key!$E$2:$F$9,2,FALSE) -> Home | R14: =K14&"-"&Q14 -> Work-Home | S14: 13 | T14: 0.3 | U14: 3 | Y14: Y | AA14: =VLOOKUP(F14,'Zones (3)'!$A$2:$F$15913,6,FALSE) -> 380 | AB14: =VLOOKUP(L14,'Zones (3)'!$A$1:$F$15616,6,FALSE) -> 987
B15: 0.74166667 | C15: CD 103 62U | D15: 2 | E15: 2 | F15: ISINGIRO TOWN | G15: ISINGIRO | H15: UG | I15: 2 | J15: 2 | K15: =VLOOKUP(J15,Key!$E$2:$F$9,2,FALSE) -> Work | L15: MBARARA TOWN | M15: MBARARA | N15: UG | O15: 16 | P15: 8 | Q15: =VLOOKUP(P15,Key!$E$2:$F$9,2,FALSE) -> Others | R15: =K15&"-"&Q15 -> Work-Others | S15: 31 | T15: 0.8 | U15: 2 | Y15: Y | AA15: =VLOOKUP(F15,'Zones (3)'!$A$2:$F$15913,6,FALSE) -> 379 | AB15: =VLOOKUP(L15,'Zones (3)'!$A$1:$F$15616,6,FALSE) -> 987
B16: 0.7375 | C16: UAX 388M | D16: 8 | E16: 1 | F16: KABINGO | G16: ISINGIRO | H16: UG | I16: 15 | J16: 4 | K16: =VLOOKUP(J16,Key!$E$2:$F$9,2,FALSE) -> Commercial | L16: MBARARA TOWN | M16: MBARARA | N16: UG | O16: 10 | P16: 2 | Q16: =VLOOKUP(P16,Key!$E$2:$F$9,2,FALSE) -> Work | R16: =K16&"-"&Q16 -> Commercial-Work | S16: 12 | T16: 0.5 | U16: 3 | V16: 4 | W16: 6 | X16: 220000 | Y16: Y | AA16: =VLOOKUP(F16,'Zones (3)'!$A$2:$F$15913,6,FALSE) -> 381 | AB16: =VLOOKUP(L16,'Zones (3)'!$A$1:$F$15616,6,FALSE) -> 987
B17: 0.73333333 | C17: UAS 880K | D17: 1 | E17: 3 | F17: KABALE | G17: ISINGIRO | H17: UG | I17: 4 | J17: 3 | K17: =VLOOKUP(J17,Key!$E$2:$F$9,2,FALSE) -> Study | L17: MBARARA TOWN | M17: MBARARA | N17: UG | O17: 1 | P17: 1 | Q17: =VLOOKUP(P17,Key!$E$2:$F$9,2,FALSE) -> Home | R17: =K17&"-"&Q17 -> Study-Home | S17: 5 | T17: 0.5 | U17: 5 | Y17: Y | AA17: =VLOOKUP(F17,'Zones (3)'!$A$2:$F$15913,6,FALSE) -> 422 | AB17: =VLOOKUP(L17,'Zones (3)'!$A$1:$F$15616,6,FALSE) -> 987
B18: 0.72916667 | C18: UAR 880V | D18: 1 | E18: 1 | F18: KABEREBERE | G18: ISINGIRO | H18: UG | I18: 2 | J18: 2 | K18: =VLOOKUP(J18,Key!$E$2:$F$9,2,FALSE) -> Work | L18: MBARARA TOWN | M18: MBARARA | N18: UG | O18: 2 | P18: 2 | Q18: =VLOOKUP(P18,Key!$E$2:$F$9,2,FALSE) -> Work | R18: =K18&"-"&Q18 -> Work-Work | S18: 35 | T18: 0.4 | U18: 4 | Y18: Y | AA18: =VLOOKUP(F18,'Zones (3)'!$A$2:$F$15913,6,FALSE) -> 380 | AB18: =VLOOKUP(L18,'Zones (3)'!$A$1:$F$15616,6,FALSE) -> 987
B19: 0.725 | C19: UAY 304Y | D19: 8 | E19: 3 | F19: KABEREBERE | G19: ISINGIRO | H19: UG | I19: 3 | J19: 4 | K19: =VLOOKUP(J19,Key!$E$2:$F$9,2,FALSE) -> Commercial | L19: MBARARA TOWN | M19: MBARARA | N19: UG | O19: 4 | P19: 3 | Q19: =VLOOKUP(P19,Key!$E$2:$F$9,2,FALSE) -> Study | R19: =K19&"-"&Q19 -> Commercial-Study | S19: 10 | T19: 0.2 | U19: 2 | V19: 10 | W19: 4 | X19: 4500000 | Y19: Y | AA19: =VLOOKUP(F19,'Zones (3)'!$A$2:$F$15913,6,FALSE) -> 380 | AB19: =VLOOKUP(L19,'Zones (3)'!$A$1:$F$15616,6,FALSE) -> 987
B20: 0.72083333 | C20: UBB 721A | D20: 1 | E20: 2 | F20: KABEREBERE | G20: ISINGIRO | H20: UG | I20: 3 | J20: 4 | K20: =VLOOKUP(J20,Key!$E$2:$F$9,2,FALSE) -> Commercial | L20: MBARARA TOWN | M20: MBARARA | N20: UG | O20: 1 | P20: 1 | Q20: =VLOOKUP(P20,Key!$E$2:$F$9,2,FALSE) -> Home | R20: =K20&"-"&Q20 -> Commercial-Home | S20: 25 | T20: 0.3 | U20: 3 | Y20: Y | AA20: =VLOOKUP(F20,'Zones (3)'!$A$2:$F$15913,6,FALSE) -> 380 | AB20: =VLOOKUP(L20,'Zones (3)'!$A$1:$F$15616,6,FALSE) -> 987
B21: 0.71666667 | C21: UAL 702Y | D21: 1 | E21: 3 | F21: KABEREBERE | G21: ISINGIRO | H21: UG | I21: 1 | J21: 1 | K21: =VLOOKUP(J21,Key!$E$2:$F$9,2,FALSE) -> Home | L21: MBARARA TOWN | M21: MBARARA | N21: UG | O21: 16 | P21: 8 | Q21: =VLOOKUP(P21,Key!$E$2:$F$9,2,FALSE) -> Others | R21: =K21&"-"&Q21 -> Home-Others | S21: 35 | T21: 1 | U21: 4 | V21: 11 | Y21: Y | AA21: =VLOOKUP(F21,'Zones (3)'!$A$2:$F$15913,6,FALSE) -> 380 | AB21: =VLOOKUP(L21,'Zones (3)'!$A$1:$F$15616,6,FALSE) -> 987
B22: 0.71458333 | C22: UAX 390W | D22: 1 | E22: 12 | F22: KABALE | G22: ISINGIRO | H22: UG | I22: 1 | J22: 1 | K22: =VLOOKUP(J22,Key!$E$2:$F$9,2,FALSE) -> Home | L22: MBARARA TOWN | M22: MBARARA | N22: UG | O22: 16 | P22: 8 | Q22: =VLOOKUP(P22,Key!$E$2:$F$9,2,FALSE) -> Others | R22: =K22&"-"&Q22 -> Home-Others | S22: 5 | T22: 0.2 | U22: 2 | Y22: Y | AA22: =VLOOKUP(F22,'Zones (3)'!$A$2:$F$15913,6,FALSE) -> 422 | AB22: =VLOOKUP(L22,'Zones (3)'!$A$1:$F$15616,6,FALSE) -> 987
B23: 0.71111111 | C23: UAY 249B | D23: 1 | E23: 1 | F23: KASENYI | G23: ISINGIRO | H23: UG | I23: 16 | J23: 8 | K23: =VLOOKUP(J23,Key!$E$2:$F$9,2,FALSE) -> Others | L23: MBARARA TOWN | M23: MBARARA | N23: UG | O23: 1 | P23: 1 | Q23: =VLOOKUP(P23,Key!$E$2:$F$9,2,FALSE) -> Home | R23: =K23&"-"&Q23 -> Others-Home | S23: 6 | T23: 0 | U23: 3 | Y23: Y | AA23: =VLOOKUP(F23,'Zones (3)'!$A$2:$F$15913,6,FALSE) -> 538 | AB23: =VLOOKUP(L23,'Zones (3)'!$A$1:$F$15616,6,FALSE) -> 987
B24: 0.70833333 | C24: UAS 808H | D24: 1 | E24: 2 | F24: KASENYI | G24: ISINGIRO | H24: UG | I24: 16 | J24: 8 | K24: =VLOOKUP(J24,Key!$E$2:$F$9,2,FALSE) -> Others | L24: MBARARA TOWN | M24: MBARARA | N24: UG | O24: 1 | P24: 1 | Q24: =VLOOKUP(P24,Key!$E$2:$F$9,2,FALSE) -> Home | R24: =K24&"-"&Q24 -> Others-Home | S24: 5 | T24: 0.3 | U24: 4 | Y24: Y | AA24: =VLOOKUP(F24,'Zones (3)'!$A$2:$F$15913,6,FALSE) -> 538 | AB24: =VLOOKUP(L24,'Zones (3)'!$A$1:$F$15616,6,FALSE) -> 987
B25: 0.70416667 | C25: T487 BFH | D25: 10 | E25: 3 | F25: KABINGO | G25: ISINGIRO | H25: UG | I25: 13 | J25: 4 | K25: =VLOOKUP(J25,Key!$E$2:$F$9,2,FALSE) -> Commercial | L25: MBARARA TOWN | M25: MBARARA | N25: UG | O25: 16 | P25: 8 | Q25: =VLOOKUP(P25,Key!$E$2:$F$9,2,FALSE) -> Others | R25: Work-Others | S25: 32 | T25: 0.7 | U25: 4 | V25: 11 | Y25: Y | AA25: =VLOOKUP(F25,'Zones (3)'!$A$2:$F$15913,6,FALSE) -> 381 | AB25: =VLOOKUP(L25,'Zones (3)'!$A$1:$F$15616,6,FALSE) -> 987
B26: 0.70138889 | C26: UAT 089N | D26: 3 | E26: 4 | F26: KIKAGATI | G26: ISINGIRO | H26: UG | I26: 2 | J26: 2 | K26: =VLOOKUP(J26,Key!$E$2:$F$9,2,FALSE) -> Work | L26: MBARARA TOWN | M26: MBARARA | N26: UG | O26: 1 | P26: 1 | Q26: =VLOOKUP(P26,Key!$E$2:$F$9,2,FALSE) -> Home | R26: =K26&"-"&Q26 -> Work-Home | S26: 40 | T26: 1.5 | U26: 6 | Y26: Y | AA26: =VLOOKUP(F26,'Zones (3)'!$A$2:$F$15913,6,FALSE) -> 379 | AB26: =VLOOKUP(L26,'Zones (3)'!$A$1:$F$15616,6,FALSE) -> 987
B27: 0.69791667 | C27: UAM 124K | D27: 1 | E27: 8 | F27: KABINGO | G27: ISINGIRO | H27: UG | I27: 1 | J27: 1 | K27: =VLOOKUP(J27,Key!$E$2:$F$9,2,FALSE) -> Home | L27: MBARARA TOWN | M27: MBARARA | N27: UG | O27: 1 | P27: 1 | Q27: =VLOOKUP(P27,Key!$E$2:$F$9,2,FALSE) -> Home | R27: =K27&"-"&Q27 -> Home-Home | T27: 0.7 | U27: 3 | Y27: Y | AA27: =VLOOKUP(F27,'Zones (3)'!$A$2:$F$15913,6,FALSE) -> 381 | AB27: =VLOOKUP(L27,'Zones (3)'!$A$1:$F$15616,6,FALSE) -> 987
B28: 0.69444444 | C28: UAQ 705F | D28: 1 | E28: 2 | F28: RWENJELU | G28: ISINGIRO | H28: UG | I28: 4 | J28: 3 | K28: =VLOOKUP(J28,Key!$E$2:$F$9,2,FALSE) -> Study | L28: MBARARA TOWN | M28: MBARARA | N28: UG | O28: 1 | P28: 1 | Q28: =VLOOKUP(P28,Key!$E$2:$F$9,2,FALSE) -> Home | R28: =K28&"-"&Q28 -> Study-Home | S28: 4 | T28: 0.5 | U28: 3 | Y28: Y | AA28: =VLOOKUP(F28,'Zones (3)'!$A$2:$F$15913,6,FALSE) -> 379 | AB28: =VLOOKUP(L28,'Zones (3)'!$A$1:$F$15616,6,FALSE) -> 987
B29: 0.69027778 | C29: UAT 319R | D29: 1 | E29: 1 | F29: KASENYI | G29: ISINGIRO | H29: UG | I29: 4 | J29: 3 | K29: =VLOOKUP(J29,Key!$E$2:$F$9,2,FALSE) -> Study | L29: MBARARA TOWN | M29: MBARARA | N29: UG | O29: 1 | P29: 1 | Q29: =VLOOKUP(P29,Key!$E$2:$F$9,2,FALSE) -> Home | R29: =K29&"-"&Q29 -> Study-Home | S29: 10 | T29: 0.3 | U29: 3 | Y29: Y | AA29: =VLOOKUP(F29,'Zones (3)'!$A$2:$F$15913,6,FALSE) -> 538 | AB29: =VLOOKUP(L29,'Zones (3)'!$A$1:$F$15616,6,FALSE) -> 987
B30: 0.68541667 | C30: UAN 083G | D30: 1 | E30: 2 | F30: NAKIVALA | G30: ISINGIRO | H30: UG | I30: 7 | J30: 2 | K30: =VLOOKUP(J30,Key!$E$2:$F$9,2,FALSE) -> Work | L30: MBARARA TOWN | M30: MBARARA | N30: UG | O30: 1 | P30: 1 | Q30: =VLOOKUP(P30,Key!$E$2:$F$9,2,FALSE) -> Home | R30: =K30&"-"&Q30 -> Work-Home | S30: 30 | T30: 2 | U30: 4 | V30: 10 | Y30: Y | AA30: =VLOOKUP(F30,'Zones (3)'!$A$2:$F$15913,6,FALSE) -> 388 | AB30: =VLOOKUP(L30,'Zones (3)'!$A$1:$F$15616,6,FALSE) -> 987
B31: 0.53472222 | C31: UAZ 098F | D31: 2 | E31: 7 | F31: KIKAGATI | G31: ISINGIRO | H31: UG | I31: 1 | J31: 1 | K31: =VLOOKUP(J31,Key!$E$2:$F$9,2,FALSE) -> Home | L31: MBARARA TOWN | M31: MBARARA | N31: UG | O31: 1 | P31: 1 | Q31: =VLOOKUP(P31,Key!$E$2:$F$9,2,FALSE) -> Home | R31: =K31&"-"&Q31 -> Home-Home | S31: 69 | T31: 1 | U31: 4 | Y31: Y | AA31: =VLOOKUP(F31,'Zones (3)'!$A$2:$F$15913,6,FALSE) -> 379 | AB31: =VLOOKUP(L31,'Zones (3)'!$A$1:$F$15616,6,FALSE) -> 987
B32: 0.53055556 | C32: UAJ 803W | D32: 1 | E32: 1 | F32: KABEREBERE | G32: ISINGIRO | H32: UG | I32: 1 | J32: 1 | K32: =VLOOKUP(J32,Key!$E$2:$F$9,2,FALSE) -> Home | L32: MBARARA TOWN | M32: MBARARA | N32: UG | O32: 2 | P32: 2 | Q32: =VLOOKUP(P32,Key!$E$2:$F$9,2,FALSE) -> Work | R32: =K32&"-"&Q32 -> Home-Work | S32: 9 | T32: 0.5 | U32: 2 | Y32: Y | AA32: =VLOOKUP(F32,'Zones (3)'!$A$2:$F$15913,6,FALSE) -> 380 | AB32: =VLOOKUP(L32,'Zones (3)'!$A$1:$F$15616,6,FALSE) -> 987
B33: 0.52777778 | C33: UBE 386H | D33: 1 | E33: 4 | F33: KABEREBERE | G33: ISINGIRO | H33: UG | I33: 4 | J33: 3 | K33: =VLOOKUP(J33,Key!$E$2:$F$9,2,FALSE) -> Study | L33: MBARARA TOWN | M33: MBARARA | N33: UG | O33: 1 | P33: 1 | Q33: =VLOOKUP(P33,Key!$E$2:$F$9,2,FALSE) -> Home | R33: =K33&"-"&Q33 -> Study-Home | S33: 52 | T33: 1 | U33: 3 | Y33: Y | AA33: =VLOOKUP(F33,'Zones (3)'!$A$2:$F$15913,6,FALSE) -> 380 | AB33: =VLOOKUP(L33,'Zones (3)'!$A$1:$F$15616,6,FALSE) -> 987
B34: 0.525 | C34: UBE 561U | D34: 2 | E34: 1 | F34: KIRUMBA | G34: KYOTERA | H34: UG | I34: 16 | J34: 8 | K34: =VLOOKUP(J34,Key!$E$2:$F$9,2,FALSE) -> Others | L34: KAMPALA CITY | M34: KAMPALA | N34: UG | O34: 1 | P34: 1 | Q34: =VLOOKUP(P34,Key!$E$2:$F$9,2,FALSE) -> Home | R34: =K34&"-"&Q34 -> Others-Home | T34: 3 | U34: 6 | Y34: Y | AA34: =VLOOKUP(F34,'Zones (3)'!$A$2:$F$15913,6,FALSE) -> 850 | AB34: =VLOOKUP(L34,'Zones (3)'!$A$1:$F$15616,6,FALSE) -> 521
B35: 0.52083333 | C35: UBD 114B | D35: 1 | E35: 3 | F35: KASENYI | G35: ISINGIRO | H35: UG | I35: 1 | J35: 1 | K35: =VLOOKUP(J35,Key!$E$2:$F$9,2,FALSE) -> Home | L35: MBARARA TOWN | M35: MBARARA | N35: UG | O35: 2 | P35: 2 | Q35: =VLOOKUP(P35,Key!$E$2:$F$9,2,FALSE) -> Work | R35: =K35&"-"&Q35 -> Home-Work | S35: 4 | T35: 0.3 | U35: 1 | Y35: Y | AA35: =VLOOKUP(F35,'Zones (3)'!$A$2:$F$15913,6,FALSE) -> 538 | AB35: =VLOOKUP(L35,'Zones (3)'!$A$1:$F$15616,6,FALSE) -> 987
B36: 0.51736111 | C36: UAD 009J | D36: 3 | E36: 2 | F36: KABEREBERE | G36: ISINGIRO | H36: UG | I36: 1 | J36: 1 | K36: =VLOOKUP(J36,Key!$E$2:$F$9,2,FALSE) -> Home | L36: MBARARA TOWN | M36: MBARARA | N36: UG | O36: 1 | P36: 1 | Q36: =VLOOKUP(P36,Key!$E$2:$F$9,2,FALSE) -> Home | R36: =K36&"-"&Q36 -> Home-Home | S36: 13 | T36: 0.5 | U36: 4 | V36: 10 | Y36: Y | AA36: =VLOOKUP(F36,'Zones (3)'!$A$2:$F$15913,6,FALSE) -> 380 | AB36: =VLOOKUP(L36,'Zones (3)'!$A$1:$F$15616,6,FALSE) -> 987
B37: 0.51527778 | C37: UAP 660M | D37: 1 | E37: 4 | F37: KABEREBERE | G37: ISINGIRO | H37: UG | I37: 1 | J37: 1 | K37: =VLOOKUP(J37,Key!$E$2:$F$9,2,FALSE) -> Home | L37: MBARARA TOWN | M37: MBARARA | N37: UG | O37: 16 | P37: 8 | Q37: =VLOOKUP(P37,Key!$E$2:$F$9,2,FALSE) -> Others | R37: =K37&"-"&Q37 -> Home-Others | S37: 35 | T37: 2 | U37: 6 | Y37: Y | AA37: =VLOOKUP(F37,'Zones (3)'!$A$2:$F$15913,6,FALSE) -> 380 | AB37: =VLOOKUP(L37,'Zones (3)'!$A$1:$F$15616,6,FALSE) -> 987
B38: 0.51319444 | C38: UAL 863M | D38: 2 | E38: 3 | F38: KABINGO | G38: ISINGIRO | H38: UG | I38: 1 | J38: 1 | K38: =VLOOKUP(J38,Key!$E$2:$F$9,2,FALSE) -> Home | L38: MBARARA TOWN | M38: MBARARA | N38: UG | O38: 5 | P38: 7 | Q38: =VLOOKUP(P38,Key!$E$2:$F$9,2,FALSE) -> Hospital | R38: =K38&"-"&Q38 -> Home-Hospital | S38: 36 | T38: 0.5 | U38: 3 | Y38: Y | AA38: =VLOOKUP(F38,'Zones (3)'!$A$2:$F$15913,6,FALSE) -> 381 | AB38: =VLOOKUP(L38,'Zones (3)'!$A$1:$F$15616,6,FALSE) -> 987
B39: 0.51041667 | C39: UAW 625J | D39: 8 | E39: 2 | F39: KABEREBERE | G39: ISINGIRO | H39: UG | I39: 13 | J39: 4 | K39: =VLOOKUP(J39,Key!$E$2:$F$9,2,FALSE) -> Commercial | L39: MBARARA TOWN | M39: MBARARA | N39: UG | O39: 10 | P39: 2 | Q39: =VLOOKUP(P39,Key!$E$2:$F$9,2,FALSE) -> Work | R39: =K39&"-"&Q39 -> Commercial-Work | S39: 37 | T39: 1.5 | U39: 2 | V39: 4 | W39: 6 | X39: 40000 | Y39: Y | AA39: =VLOOKUP(F39,'Zones (3)'!$A$2:$F$15913,6,FALSE) -> 380 | AB39: =VLOOKUP(L39,'Zones (3)'!$A$1:$F$15616,6,FALSE) -> 987
B40: 0.50763889 | C40: UAE 190G | D40: 1 | E40: 1 | F40: KASENYI | G40: ISINGIRO | H40: UG | I40: 4 | J40: 3 | K40: =VLOOKUP(J40,Key!$E$2:$F$9,2,FALSE) -> Study | L40: MBARARA TOWN | M40: MBARARA | N40: UG | O40: 1 | P40: 1 | Q40: =VLOOKUP(P40,Key!$E$2:$F$9,2,FALSE) -> Home | R40: =K40&"-"&Q40 -> Study-Home | S40: 2 | T40: 0.2 | U40: 2 | Y40: Y | AA40: =VLOOKUP(F40,'Zones (3)'!$A$2:$F$15913,6,FALSE) -> 538 | AB40: =VLOOKUP(L40,'Zones (3)'!$A$1:$F$15616,6,FALSE) -> 987
B41: 0.44097222 | C41: UBA 760C | D41: 2 | E41: 2 | F41: ISINGIRO TOWN | G41: ISINGIRO | H41: UG | I41: 1 | J41: 1 | K41: =VLOOKUP(J41,Key!$E$2:$F$9,2,FALSE) -> Home | L41: MBARARA TOWN | M41: MBARARA | N41: UG | O41: 4 | P41: 3 | Q41: =VLOOKUP(P41,Key!$E$2:$F$9,2,FALSE) -> Study | R41: =K41&"-"&Q41 -> Home-Study | S41: 44 | T41: 1 | U41: 4 | Y41: Y | AA41: =VLOOKUP(F41,'Zones (3)'!$A$2:$F$15913,6,FALSE) -> 379 | AB41: =VLOOKUP(L41,'Zones (3)'!$A$1:$F$15616,6,FALSE) -> 987
B42: 0.4375 | C42: UAQ 147X | D42: 2 | E42: 1 | F42: NGALAMA | G42: ISINGIRO | H42: UG | I42: 1 | J42: 1 | K42: =VLOOKUP(J42,Key!$E$2:$F$9,2,FALSE) -> Home | L42: MBARARA TOWN | M42: MBARARA | N42: UG | O42: 16 | P42: 8 | Q42: =VLOOKUP(P42,Key!$E$2:$F$9,2,FALSE) -> Others | R42: =K42&"-"&Q42 -> Home-Others | S42: 33 | T42: 1 | U42: 4 | Y42: Y | AA42: =VLOOKUP(F42,'Zones (3)'!$A$2:$F$15913,6,FALSE) -> 987 | AB42: =VLOOKUP(L42,'Zones (3)'!$A$1:$F$15616,6,FALSE) -> 987
B43: 0.43472222 | C43: UAW 338V | D43: 2 | E43: 6 | F43: KASHUMBA | G43: ISINGIRO | H43: UG | I43: 1 | J43: 1 | K43: =VLOOKUP(J43,Key!$E$2:$F$9,2,FALSE) -> Home | L43: MBARARA TOWN | M43: MBARARA | N43: UG | O43: 4 | P43: 3 | Q43: =VLOOKUP(P43,Key!$E$2:$F$9,2,FALSE) -> Study | R43: =K43&"-"&Q43 -> Home-Study | T43: 2 | U43: 4 | Y43: Y | AA43: =VLOOKUP(F43,'Zones (3)'!$A$2:$F$15913,6,FALSE) -> 376 | AB43: =VLOOKUP(L43,'Zones (3)'!$A$1:$F$15616,6,FALSE) -> 987
B44: 0.43194444 | C44: UET 296F | D44: 11 | E44: 2 | F44: KATETE | G44: KANUNGU | H44: UG | I44: 8 | J44: 2 | K44: =VLOOKUP(J44,Key!$E$2:$F$9,2,FALSE) -> Work | L44: MBARARA TOWN | M44: MBARARA | N44: UG | O44: 8 | P44: 2 | Q44: =VLOOKUP(P44,Key!$E$2:$F$9,2,FALSE) -> Work | R44: =K44&"-"&Q44 -> Work-Work | S44: 6 | T44: 0.2 | U44: 2 | Y44: Y | AA44: =VLOOKUP(F44,'Zones (3)'!$A$2:$F$15913,6,FALSE) -> 618 | AB44: =VLOOKUP(L44,'Zones (3)'!$A$1:$F$15616,6,FALSE) -> 987
B45: 0.43055556 | C45: UAT 165X | D45: 2 | E45: 1 | F45: RWIZIRINGIRO | G45: ISINGIRO | H45: UG | I45: 1 | J45: 1 | K45: =VLOOKUP(J45,Key!$E$2:$F$9,2,FALSE) -> Home | L45: MBARARA TOWN | M45: MBARARA | N45: UG | O45: 2 | P45: 2 | Q45: =VLOOKUP(P45,Key!$E$2:$F$9,2,FALSE) -> Work | R45: =K45&"-"&Q45 -> Home-Work | S45: 8 | T45: 0.3 | U45: 2 | Y45: Y | AA45: =VLOOKUP(F45,'Zones (3)'!$A$2:$F$15913,6,FALSE) -> 984 | AB45: =VLOOKUP(L45,'Zones (3)'!$A$1:$F$15616,6,FALSE) -> 987
B46: 0.40972222 | C46: UAL 693S | D46: 1 | E46: 2 | F46: KASENYI | G46: ISINGIRO | H46: UG | I46: 1 | J46: 1 | K46: =VLOOKUP(J46,Key!$E$2:$F$9,2,FALSE) -> Home | L46: MBARARA TOWN | M46: MBARARA | N46: UG | O46: 2 | P46: 2 | Q46: =VLOOKUP(P46,Key!$E$2:$F$9,2,FALSE) -> Work | R46: =K46&"-"&Q46 -> Home-Work | S46: 7 | T46: 0.1 | U46: 2 | Y46: Y | AA46: =VLOOKUP(F46,'Zones (3)'!$A$2:$F$15913,6,FALSE) -> 538 | AB46: =VLOOKUP(L46,'Zones (3)'!$A$1:$F$15616,6,FALSE) -> 987
B47: 0.40277778 | C47: UAF 824C | D47: 3 | E47: 3 | F47: KASENYI | G47: ISINGIRO | H47: UG | I47: 9 | J47: 4 | K47: =VLOOKUP(J47,Key!$E$2:$F$9,2,FALSE) -> Commercial | L47: MBARARA TOWN | M47: MBARARA | N47: UG | O47: 9 | P47: 4 | Q47: =VLOOKUP(P47,Key!$E$2:$F$9,2,FALSE) -> Commercial | R47: =K47&"-"&Q47 -> Commercial-Commercial | S47: 10 | T47: 0.3 | U47: 5 | V47: 9 | Y47: Y | AA47: =VLOOKUP(F47,'Zones (3)'!$A$2:$F$15913,6,FALSE) -> 538 | AB47: =VLOOKUP(L47,'Zones (3)'!$A$1:$F$15616,6,FALSE) -> 987
B48: 0.40138889 | C48: UBA 397G | D48: 1 | E48: 2 | F48: KASENYI | G48: ISINGIRO | H48: UG | I48: 1 | J48: 1 | K48: =VLOOKUP(J48,Key!$E$2:$F$9,2,FALSE) -> Home | L48: MBARARA TOWN | M48: MBARARA | N48: UG | O48: 16 | P48: 8 | Q48: =VLOOKUP(P48,Key!$E$2:$F$9,2,FALSE) -> Others | R48: =K48&"-"&Q48 -> Home-Others | S48: 4 | T48: 0.1 | U48: 4 | Y48: Y | AA48: =VLOOKUP(F48,'Zones (3)'!$A$2:$F$15913,6,FALSE) -> 538 | AB48: =VLOOKUP(L48,'Zones (3)'!$A$1:$F$15616,6,FALSE) -> 987
B49: 0.39861111 | C49: UAV 911T | D49: 1 | E49: 3 | F49: KABEREBERE | G49: ISINGIRO | H49: UG | I49: 1 | J49: 1 | K49: M | L49: MBARARA TOWN | M49: MBARARA | N49: UG | O49: 16 | P49: 8 | Q49: =VLOOKUP(P49,Key!$E$2:$F$9,2,FALSE) -> Others | R49: Others-Home | S49: 15 | T49: 0.3 | U49: 2 | Y49: Y | AA49: =VLOOKUP(F49,'Zones (3)'!$A$2:$F$15913,6,FALSE) -> 380 | AB49: =VLOOKUP(L49,'Zones (3)'!$A$1:$F$15616,6,FALSE) -> 987
B50: 0.39583333 | C50: UBB 457M | D50: 1 | E50: 5 | F50: KIKAGATI | G50: ISINGIRO | H50: UG | I50: 1 | J50: 1 | K50: =VLOOKUP(J50,Key!$E$2:$F$9,2,FALSE) -> Home | L50: MBARARA TOWN | M50: MBARARA | N50: UG | O50: 2 | P50: 2 | Q50: =VLOOKUP(P50,Key!$E$2:$F$9,2,FALSE) -> Work | R50: =K50&"-"&Q50 -> Home-Work | S50: 35 | T50: 3 | U50: 2 | Y50: Y | AA50: =VLOOKUP(F50,'Zones (3)'!$A$2:$F$15913,6,FALSE) -> 379 | AB50: =VLOOKUP(L50,'Zones (3)'!$A$1:$F$15616,6,FALSE) -> 987
B51: 0.39444444 | C51: UAH 651L | D51: 1 | E51: 5 | F51: KASENYI | G51: ISINGIRO | H51: UG | I51: 1 | J51: 1 | K51: =VLOOKUP(J51,Key!$E$2:$F$9,2,FALSE) -> Home | L51: MBARARA TOWN | M51: MBARARA | N51: UG | O51: 4 | P51: 3 | Q51: =VLOOKUP(P51,Key!$E$2:$F$9,2,FALSE) -> Study | R51: =K51&"-"&Q51 -> Home-Study | S51: 6 | T51: 0 | U51: 2 | Y51: Y | AA51: =VLOOKUP(F51,'Zones (3)'!$A$2:$F$15913,6,FALSE) -> 538 | AB51: =VLOOKUP(L51,'Zones (3)'!$A$1:$F$15616,6,FALSE) -> 987
B52: 0.39236111 | C52: UAS 400V | D52: 1 | E52: 5 | F52: NAKIVALA | G52: ISINGIRO | H52: UG | I52: 1 | J52: 1 | K52: =VLOOKUP(J52,Key!$E$2:$F$9,2,FALSE) -> Home | L52: MBARARA TOWN | M52: MBARARA | N52: UG | O52: 1 | P52: 1 | Q52: =VLOOKUP(P52,Key!$E$2:$F$9,2,FALSE) -> Home | R52: =K52&"-"&Q52 -> Home-Home | S52: 4 | T52: 0.2 | U52: 4 | Y52: Y | AA52: =VLOOKUP(F52,'Zones (3)'!$A$2:$F$15913,6,FALSE) -> 388 | AB52: =VLOOKUP(L52,'Zones (3)'!$A$1:$F$15616,6,FALSE) -> 987
B53: 0.39027778 | C53: UAK 315M | D53: 1 | E53: 1 | F53: KASENYI | G53: ISINGIRO | H53: UG | I53: 1 | J53: 1 | K53: =VLOOKUP(J53,Key!$E$2:$F$9,2,FALSE) -> Home | L53: KOLANOLYA | M53: MBARARA | N53: UG | O53: 9 | P53: 2 | Q53: =VLOOKUP(P53,Key!$E$2:$F$9,2,FALSE) -> Work | R53: =K53&"-"&Q53 -> Home-Work | T53: 0.3 | U53: 2 | Y53: Y | AA53: =VLOOKUP(F53,'Zones (3)'!$A$2:$F$15913,6,FALSE) -> 538 | AB53: =VLOOKUP(L53,'Zones (3)'!$A$1:$F$15616,6,FALSE) -> 899
B54: 0.38888889 | C54: UAW 583E | D54: 1 | E54: 4 | F54: ISINGIRO TOWN | G54: ISINGIRO | H54: UG | I54: 1 | J54: 1 | K54: =VLOOKUP(J54,Key!$E$2:$F$9,2,FALSE) -> Home | L54: MBARARA TOWN | M54: MBARARA | N54: UG | O54: 4 | P54: 3 | Q54: =VLOOKUP(P54,Key!$E$2:$F$9,2,FALSE) -> Study | R54: =K54&"-"&Q54 -> Home-Study | S54: 35 | T54: 1.5 | U54: 5 | Y54: Y | AA54: =VLOOKUP(F54,'Zones (3)'!$A$2:$F$15913,6,FALSE) -> 379 | AB54: =VLOOKUP(L54,'Zones (3)'!$A$1:$F$15616,6,FALSE) -> 987
B55: 0.38541667 | C55: UAS 038R | D55: 3 | E55: 2 | F55: ISINGIRO TOWN | G55: ISINGIRO | H55: UG | I55: 16 | J55: 8 | K55: =VLOOKUP(J55,Key!$E$2:$F$9,2,FALSE) -> Others | L55: MBARARA TOWN | M55: MBARARA | N55: UG | O55: 16 | P55: 8 | Q55: =VLOOKUP(P55,Key!$E$2:$F$9,2,FALSE) -> Others | R55: =K55&"-"&Q55 -> Others-Others | S55: 32 | T55: 0.7 | U55: 3 | Y55: Y | AA55: =VLOOKUP(F55,'Zones (3)'!$A$2:$F$15913,6,FALSE) -> 379 | AB55: =VLOOKUP(L55,'Zones (3)'!$A$1:$F$15616,6,FALSE) -> 987
B56: 0.38194444 | C56: UAR 829U | D56: 3 | E56: 5 | F56: KABALE | G56: ISINGIRO | H56: UG | I56: 1 | J56: 1 | K56: =VLOOKUP(J56,Key!$E$2:$F$9,2,FALSE) -> Home | L56: MBARARA TOWN | M56: MBARARA | N56: UG | O56: 2 | P56: 2 | Q56: =VLOOKUP(P56,Key!$E$2:$F$9,2,FALSE) -> Work | R56: =K56&"-"&Q56 -> Home-Work | S56: 4 | T56: 0.2 | U56: 2 | Y56: Y | AA56: =VLOOKUP(F56,'Zones (3)'!$A$2:$F$15913,6,FALSE) -> 422 | AB56: =VLOOKUP(L56,'Zones (3)'!$A$1:$F$15616,6,FALSE) -> 987
B57: 0.37152778 | C57: UEV 044V | D57: 11 | E57: 1 | F57: OMUKIHOGO | G57: KAMWENGE | H57: UG | I57: 8 | J57: 2 | K57: =VLOOKUP(J57,Key!$E$2:$F$9,2,FALSE) -> Work | L57: MBARARA TOWN | M57: MBARARA | N57: UG | O57: 8 | P57: 2 | Q57: =VLOOKUP(P57,Key!$E$2:$F$9,2,FALSE) -> Work | R57: =K57&"-"&Q57 -> Work-Work | S57: 4 | T57: 0.2 | U57: 2 | Y57: Y | AA57: =VLOOKUP(F57,'Zones (3)'!$A$2:$F$15913,6,FALSE) -> 608 | AB57: =VLOOKUP(L57,'Zones (3)'!$A$1:$F$15616,6,FALSE) -> 987
B58: 0.36805556 | C58: UAL 402T | D58: 1 | E58: 2 | F58: KABEREBERE | G58: ISINGIRO | H58: UG | I58: 1 | J58: 1 | K58: =VLOOKUP(J58,Key!$E$2:$F$9,2,FALSE) -> Home | L58: MBARARA TOWN | M58: MBARARA | N58: UG | O58: 2 | P58: 2 | Q58: =VLOOKUP(P58,Key!$E$2:$F$9,2,FALSE) -> Work | R58: =K58&"-"&Q58 -> Home-Work | S58: 13 | T58: 0.5 | U58: 2 | Y58: Y | AA58: =VLOOKUP(F58,'Zones (3)'!$A$2:$F$15913,6,FALSE) -> 380 | AB58: =VLOOKUP(L58,'Zones (3)'!$A$1:$F$15616,6,FALSE) -> 987
B59: 0.36666667 | C59: UAK 262K | D59: 1 | E59: 2 | F59: MASHA | G59: ISINGIRO | H59: UG | I59: 1 | J59: 1 | K59: =VLOOKUP(J59,Key!$E$2:$F$9,2,FALSE) -> Home | L59: MBARARA TOWN | M59: MBARARA | N59: UG | O59: 2 | P59: 2 | Q59: =VLOOKUP(P59,Key!$E$2:$F$9,2,FALSE) -> Work | R59: =K59&"-"&Q59 -> Home-Work | S59: 12 | T59: 0.8 | U59: 2 | Y59: Y | AA59: =VLOOKUP(F59,'Zones (3)'!$A$2:$F$15913,6,FALSE) -> 386 | AB59: =VLOOKUP(L59,'Zones (3)'!$A$1:$F$15616,6,FALSE) -> 987
B60: 0.3625 | C60: UEM 875L | D60: 11 | E60: 1 | F60: OMUKIHOGO | G60: KAMWENGE | H60: UG | I60: 8 | J60: 2 | K60: =VLOOKUP(J60,Key!$E$2:$F$9,2,FALSE) -> Work | L60: MBARARA TOWN | M60: MBARARA | N60: UG | O60: 8 | P60: 2 | Q60: =VLOOKUP(P60,Key!$E$2:$F$9,2,FALSE) -> Work | R60: =K60&"-"&Q60 -> Work-Work | S60: 4 | T60: 0.3 | U60: 2 | Y60: Y | AA60: =VLOOKUP(F60,'Zones (3)'!$A$2:$F$15913,6,FALSE) -> 608 | AB60: =VLOOKUP(L60,'Zones (3)'!$A$1:$F$15616,6,FALSE) -> 987
B61: 0.36111111 | C61: UDZ 915T | D61: 11 | E61: 1 | F61: RWENKWELA | G61: ISINGIRO | H61: UG | I61: 8 | J61: 2 | K61: =VLOOKUP(J61,Key!$E$2:$F$9,2,FALSE) -> Work | L61: MBARARA TOWN | M61: MBARARA | N61: UG | O61: 8 | P61: 2 | Q61: =VLOOKUP(P61,Key!$E$2:$F$9,2,FALSE) -> Work | R61: =K61&"-"&Q61 -> Work-Work | T61: 0.5 | U61: 2 | Y61: Y | AA61: =VLOOKUP(F61,'Zones (3)'!$A$2:$F$15913,6,FALSE) -> 379 | AB61: =VLOOKUP(L61,'Zones (3)'!$A$1:$F$15616,6,FALSE) -> 987
B62: 0.35972222 | C62: UAT 352P | D62: 1 | E62: 5 | F62: KASUMBA | G62: ISINGIRO | H62: UG | I62: 1 | J62: 1 | K62: =VLOOKUP(J62,Key!$E$2:$F$9,2,FALSE) -> Home | L62: MBARARA TOWN | M62: MBARARA | N62: UG | O62: 16 | P62: 8 | Q62: =VLOOKUP(P62,Key!$E$2:$F$9,2,FALSE) -> Others | R62: =K62&"-"&Q62 -> Home-Others | S62: 95 | T62: 2 | U62: 3 | Y62: Y | AA62: =VLOOKUP(F62,'Zones (3)'!$A$2:$F$15913,6,FALSE) -> 651 | AB62: =VLOOKUP(L62,'Zones (3)'!$A$1:$F$15616,6,FALSE) -> 987
B63: 0.35763889 | C63: UBC 912D | D63: 7 | E63: 1 | F63: KABEREBERE | G63: ISINGIRO | H63: UG | I63: 11 | J63: 2 | K63: =VLOOKUP(J63,Key!$E$2:$F$9,2,FALSE) -> Work | L63: MBARARA TOWN | M63: MBARARA | N63: UG | O63: 3 | P63: 2 | Q63: =VLOOKUP(P63,Key!$E$2:$F$9,2,FALSE) -> Work | R63: =K63&"-"&Q63 -> Work-Work | S63: 16 | T63: 0.3 | U63: 3 | V63: 11 | Y63: Y | AA63: =VLOOKUP(F63,'Zones (3)'!$A$2:$F$15913,6,FALSE) -> 380 | AB63: =VLOOKUP(L63,'Zones (3)'!$A$1:$F$15616,6,FALSE) -> 987
B64: 0.35416667 | C64: UBB 507R | D64: 1 | E64: 1 | F64: KABALE | G64: ISINGIRO | H64: UG | I64: 1 | J64: 1 | K64: =VLOOKUP(J64,Key!$E$2:$F$9,2,FALSE) -> Home | L64: MBARARA TOWN | M64: MBARARA | N64: UG | O64: 2 | P64: 2 | Q64: =VLOOKUP(P64,Key!$E$2:$F$9,2,FALSE) -> Work | R64: =K64&"-"&Q64 -> Home-Work | S64: 12 | T64: 1 | U64: 2 | Y64: Y | AA64: =VLOOKUP(F64,'Zones (3)'!$A$2:$F$15913,6,FALSE) -> 422 | AB64: =VLOOKUP(L64,'Zones (3)'!$A$1:$F$15616,6,FALSE) -> 987
B65: 0.35069444 | C65: UES 545V | D65: 11 | E65: 1 | F65: KASENYI | G65: ISINGIRO | H65: UG | I65: 8 | J65: 2 | K65: =VLOOKUP(J65,Key!$E$2:$F$9,2,FALSE) -> Work | L65: KASENYI | M65: ISINGIRO | N65: UG | O65: 8 | P65: 2 | Q65: =VLOOKUP(P65,Key!$E$2:$F$9,2,FALSE) -> Work | R65: =K65&"-"&Q65 -> Work-Work | S65: 1 | T65: 0 | U65: 2 | Y65: Y | AA65: =VLOOKUP(F65,'Zones (3)'!$A$2:$F$15913,6,FALSE) -> 538 | AB65: =VLOOKUP(L65,'Zones (3)'!$A$1:$F$15616,6,FALSE) -> 538
B66: 0.34722222 | C66: UAZ 009D | D66: 1 | E66: 2 | F66: BUTENGA | G66: ISINGIRO | H66: UG | I66: 1 | J66: 1 | K66: =VLOOKUP(J66,Key!$E$2:$F$9,2,FALSE) -> Home | L66: MBARARA TOWN | M66: MBARARA | N66: UG | O66: 16 | P66: 8 | Q66: =VLOOKUP(P66,Key!$E$2:$F$9,2,FALSE) -> Others | R66: =K66&"-"&Q66 -> Home-Others | S66: 12 | T66: 0.2 | U66: 3 | Y66: Y | AA66: =VLOOKUP(F66,'Zones (3)'!$A$2:$F$15913,6,FALSE) -> 179 | AB66: =VLOOKUP(L66,'Zones (3)'!$A$1:$F$15616,6,FALSE) -> 987
B67: 0.75833333 | C67: UES 289B | D67: 11 | E67: 1 | F67: KABALE | G67: ISINGIRO | H67: UG | I67: 8 | J67: 2 | K67: =VLOOKUP(J67,Key!$E$2:$F$9,2,FALSE) -> Work | L67: KASENYI | M67: ISINGIRO | N67: UG | O67: 8 | P67: 2 | Q67: =VLOOKUP(P67,Key!$E$2:$F$9,2,FALSE) -> Work | R67: =K67&"-"&Q67 -> Work-Work | S67: 1 | T67: 0.1 | U67: 2 | Y67: Y | AA67: =VLOOKUP(F67,'Zones (3)'!$A$2:$F$15913,6,FALSE) -> 422 | AB67: =VLOOKUP(L67,'Zones (3)'!$A$1:$F$15616,6,FALSE) -> 538
B68: 0.74652778 | C68: UAP 472H | D68: 8 | E68: 1 | F68: KASENYI | G68: ISINGIRO | H68: UG | I68: 10 | J68: 2 | K68: =VLOOKUP(J68,Key!$E$2:$F$9,2,FALSE) -> Work | L68: MBARARA TOWN | M68: MBARARA | N68: UG | O68: 15 | P68: 4 | Q68: =VLOOKUP(P68,Key!$E$2:$F$9,2,FALSE) -> Commercial | R68: =K68&"-"&Q68 -> Work-Commercial | S68: 3 | T68: 0.1 | U68: 2 | V68: 11 | Y68: Y | AA68: =VLOOKUP(F68,'Zones (3)'!$A$2:$F$15913,6,FALSE) -> 538 | AB68: =VLOOKUP(L68,'Zones (3)'!$A$1:$F$15616,6,FALSE) -> 987
B69: 0.74236111 | C69: UBA 631T | D69: 3 | E69: 1 | F69: ISINGIRO TOWN | G69: ISINGIRO | H69: UG | I69: 12 | J69: 4 | K69: =VLOOKUP(J69,Key!$E$2:$F$9,2,FALSE) -> Commercial | L69: MBARARA TOWN | M69: MBARARA | N69: UG | O69: 11 | P69: 4 | Q69: =VLOOKUP(P69,Key!$E$2:$F$9,2,FALSE) -> Commercial | R69: =K69&"-"&Q69 -> Commercial-Commercial | S69: 31 | T69: 2 | U69: 1 | V69: 10 | Y69: Y | AA69: =VLOOKUP(F69,'Zones (3)'!$A$2:$F$15913,6,FALSE) -> 379 | AB69: =VLOOKUP(L69,'Zones (3)'!$A$1:$F$15616,6,FALSE) -> 987
B70: 0.73402778 | C70: UAU 692G | D70: 8 | E70: 2 | F70: MUKIHOGO | G70: KAMWENGE | H70: UG | I70: 15 | J70: 4 | K70: =VLOOKUP(J70,Key!$E$2:$F$9,2,FALSE) -> Commercial | L70: MBARARA TOWN | M70: MBARARA | N70: UG | O70: 10 | P70: 2 | Q70: =VLOOKUP(P70,Key!$E$2:$F$9,2,FALSE) -> Work | R70: =K70&"-"&Q70 -> Commercial-Work | S70: 7 | T70: 0.2 | U70: 3 | V70: 4 | W70: 9 | Y70: Y | AA70: =VLOOKUP(F70,'Zones (3)'!$A$2:$F$15913,6,FALSE) -> 608 | AB70: =VLOOKUP(L70,'Zones (3)'!$A$1:$F$15616,6,FALSE) -> 987
B71: 0.72777778 | C71: UAR 567X | D71: 1 | E71: 1 | F71: NAKIVALA | G71: ISINGIRO | H71: UG | I71: 1 | J71: 1 | K71: =VLOOKUP(J71,Key!$E$2:$F$9,2,FALSE) -> Home | L71: MBARARA TOWN | M71: MBARARA | N71: UG | O71: 2 | P71: 2 | Q71: =VLOOKUP(P71,Key!$E$2:$F$9,2,FALSE) -> Work | R71: =K71&"-"&Q71 -> Home-Work | S71: 5 | T71: 0.2 | U71: 2 | Y71: Y | AA71: =VLOOKUP(F71,'Zones (3)'!$A$2:$F$15913,6,FALSE) -> 388 | AB71: =VLOOKUP(L71,'Zones (3)'!$A$1:$F$15616,6,FALSE) -> 987
B72: 0.72361111 | C72: UBE 908H | D72: 2 | E72: 1 | F72: KIKAGATI | G72: ISINGIRO | H72: UG | I72: 11 | J72: 2 | K72: =VLOOKUP(J72,Key!$E$2:$F$9,2,FALSE) -> Work | L72: MBARARA TOWN | M72: MBARARA | N72: UG | O72: 7 | P72: 2 | Q72: =VLOOKUP(P72,Key!$E$2:$F$9,2,FALSE) -> Work | R72: =K72&"-"&Q72 -> Work-Work | S72: 13 | T72: 0.3 | U72: 4 | Y72: Y | AA72: =VLOOKUP(F72,'Zones (3)'!$A$2:$F$15913,6,FALSE) -> 379 | AB72: =VLOOKUP(L72,'Zones (3)'!$A$1:$F$15616,6,FALSE) -> 987
B73: 0.71527778 | C73: UBE 030F | D73: 1 | E73: 2 | F73: ISINGIRO TOWN | G73: ISINGIRO | H73: UG | I73: 1 | J73: 1 | K73: =VLOOKUP(J73,Key!$E$2:$F$9,2,FALSE) -> Home | L73: MBARARA TOWN | M73: MBARARA | N73: UG | O73: 2 | P73: 2 | Q73: =VLOOKUP(P73,Key!$E$2:$F$9,2,FALSE) -> Work | R73: =K73&"-"&Q73 -> Home-Work | S73: 31 | T73: 2 | U73: 2 | Y73: Y | AA73: =VLOOKUP(F73,'Zones (3)'!$A$2:$F$15913,6,FALSE) -> 379 | AB73: =VLOOKUP(L73,'Zones (3)'!$A$1:$F$15616,6,FALSE) -> 987
B74: 0.70694444 | C74: UAU 481T | D74: 2 | E74: 1 | F74: KABEREBERE | G74: ISINGIRO | H74: UG | I74: 9 | J74: 4 | K74: =VLOOKUP(J74,Key!$E$2:$F$9,2,FALSE) -> Commercial | L74: MBARARA TOWN | M74: MBARARA | N74: UG | O74: 1 | P74: 1 | Q74: =VLOOKUP(P74,Key!$E$2:$F$9,2,FALSE) -> Home | R74: =K74&"-"&Q74 -> Commercial-Home | S74: 10 | T74: 0.3 | U74: 3 | Y74: Y | AA74: =VLOOKUP(F74,'Zones (3)'!$A$2:$F$15913,6,FALSE) -> 380 | AB74: =VLOOKUP(L74,'Zones (3)'!$A$1:$F$15616,6,FALSE) -> 987
B75: 0.69513889 | C75: UBD 149Q | D75: 1 | E75: 1 | F75: KASENYI | G75: ISINGIRO | H75: UG | I75: 4 | J75: 3 | K75: =VLOOKUP(J75,Key!$E$2:$F$9,2,FALSE) -> Study | L75: MBARARA TOWN | M75: MBARARA | N75: UG | O75: 16 | P75: 8 | Q75: =VLOOKUP(P75,Key!$E$2:$F$9,2,FALSE) -> Others | R75: =K75&"-"&Q75 -> Study-Others | S75: 5 | T75: 0.2 | U75: 2 | Y75: Y | AA75: =VLOOKUP(F75,'Zones (3)'!$A$2:$F$15913,6,FALSE) -> 538 | AB75: =VLOOKUP(L75,'Zones (3)'!$A$1:$F$15616,6,FALSE) -> 987
B76: 0.6875 | C76: UAP 123F | D76: 8 | E76: 2 | F76: ISINGIRO TOWN | G76: ISINGIRO | H76: UG | I76: 14 | J76: 4 | K76: =VLOOKUP(J76,Key!$E$2:$F$9,2,FALSE) -> Commercial | L76: NYAMITANGA | M76: MBARARA | N76: UG | O76: 12 | P76: 4 | Q76: =VLOOKUP(P76,Key!$E$2:$F$9,2,FALSE) -> Commercial | R76: =K76&"-"&Q76 -> Commercial-Commercial | S76: 31 | T76: 1 | U76: 4 | V76: 6 | Y76: Y | AA76: =VLOOKUP(F76,'Zones (3)'!$A$2:$F$15913,6,FALSE) -> 379 | AB76: =VLOOKUP(L76,'Zones (3)'!$A$1:$F$15616,6,FALSE) -> 987
B77: 0.53194444 | C77: UAP 129K | D77: 1 | E77: 3 | F77: KASENYI | G77: ISINGIRO | H77: UG | I77: 1 | J77: 1 | K77: =VLOOKUP(J77,Key!$E$2:$F$9,2,FALSE) -> Home | L77: MBARARA TOWN | M77: MBARARA | N77: UG | O77: 5 | P77: 7 | Q77: =VLOOKUP(P77,Key!$E$2:$F$9,2,FALSE) -> Hospital | R77: =K77&"-"&Q77 -> Home-Hospital | S77: 4 | T77: 0.1 | U77: 4 | Y77: Y | AA77: =VLOOKUP(F77,'Zones (3)'!$A$2:$F$15913,6,FALSE) -> 538 | AB77: =VLOOKUP(L77,'Zones (3)'!$A$1:$F$15616,6,FALSE) -> 987
B78: 0.52708333 | C78: UAN 328V | D78: 1 | E78: 1 | F78: KIRUMBA | G78: KYOTERA | H78: UG | I78: 4 | J78: 3 | K78: =VLOOKUP(J78,Key!$E$2:$F$9,2,FALSE) -> Study | L78: MBARARA TOWN | M78: MBARARA | N78: UG | O78: 1 | P78: 1 | Q78: =VLOOKUP(P78,Key!$E$2:$F$9,2,FALSE) -> Home | R78: =K78&"-"&Q78 -> Study-Home | S78: 5 | T78: 0.2 | U78: 2 | Y78: Y | AA78: =VLOOKUP(F78,'Zones (3)'!$A$2:$F$15913,6,FALSE) -> 850 | AB78: =VLOOKUP(L78,'Zones (3)'!$A$1:$F$15616,6,FALSE) -> 987
B79: 0.52083333 | C79: UAX 758T | D79: 3 | E79: 2 | F79: ISINGIRO TOWN | G79: ISINGIRO | H79: UG | I79: 2 | J79: 2 | K79: =VLOOKUP(J79,Key!$E$2:$F$9,2,FALSE) -> Work | L79: MBARARA TOWN | M79: MBARARA | N79: UG | O79: 1 | P79: 1 | Q79: =VLOOKUP(P79,Key!$E$2:$F$9,2,FALSE) -> Home | R79: =K79&"-"&Q79 -> Work-Home | S79: 31 | T79: 1.5 | U79: 2 | Y79: Y | AA79: =VLOOKUP(F79,'Zones (3)'!$A$2:$F$15913,6,FALSE) -> 379 | AB79: =VLOOKUP(L79,'Zones (3)'!$A$1:$F$15616,6,FALSE) -> 987
B80: 0.51041667 | C80: UAZ 158C | D80: 1 | E80: 1 | F80: ISINGIRO TOWN | G80: ISINGIRO | H80: UG | I80: 1 | J80: 1 | K80: =VLOOKUP(J80,Key!$E$2:$F$9,2,FALSE) -> Home | L80: MBARARA TOWN | M80: MBARARA | N80: UG | O80: 16 | P80: 8 | Q80: =VLOOKUP(P80,Key!$E$2:$F$9,2,FALSE) -> Others | R80: =K80&"-"&Q80 -> Home-Others | S80: 32 | T80: 1 | U80: 3 | Y80: Y | AA80: =VLOOKUP(F80,'Zones (3)'!$A$2:$F$15913,6,FALSE) -> 379 | AB80: =VLOOKUP(L80,'Zones (3)'!$A$1:$F$15616,6,FALSE) -> 987
B81: 0.49722222 | C81: UAX 500C | D81: 1 | E81: 1 | F81: MUKIHOGO | G81: KAMWENGE | H81: UG | I81: 1 | J81: 1 | K81: =VLOOKUP(J81,Key!$E$2:$F$9,2,FALSE) -> Home | L81: MBARARA TOWN | M81: MBARARA | N81: UG | O81: 2 | P81: 2 | Q81: =VLOOKUP(P81,Key!$E$2:$F$9,2,FALSE) -> Work | R81: =K81&"-"&Q81 -> Home-Work | S81: 4 | T81: 0.1 | U81: 2 | Y81: Y | AA81: =VLOOKUP(F81,'Zones (3)'!$A$2:$F$15913,6,FALSE) -> 608 | AB81: =VLOOKUP(L81,'Zones (3)'!$A$1:$F$15616,6,FALSE) -> 987
B82: 0.49166667 | C82: UAD 044P | D82: 1 | E82: 3 | F82: KABEREBERE | G82: ISINGIRO | H82: UG | I82: 16 | J82: 8 | K82: =VLOOKUP(J82,Key!$E$2:$F$9,2,FALSE) -> Others | L82: MBARARA TOWN | M82: MBARARA | N82: UG | O82: 16 | P82: 8 | Q82: =VLOOKUP(P82,Key!$E$2:$F$9,2,FALSE) -> Others | R82: =K82&"-"&Q82 -> Others-Others | T82: 1 | U82: 2 | Y82: Y | AA82: =VLOOKUP(F82,'Zones (3)'!$A$2:$F$15913,6,FALSE) -> 380 | AB82: =VLOOKUP(L82,'Zones (3)'!$A$1:$F$15616,6,FALSE) -> 987
B83: 0.48611111 | C83: UAR 466V | D83: 8 | E83: 2 | F83: MBARARA TOWN | G83: MBARARA | H83: UG | I83: 7 | J83: 4 | K83: =VLOOKUP(J83,Key!$E$2:$F$9,2,FALSE) -> Commercial | L83: WAKIRURI | M83: ISINGIRO | N83: UG | O83: 10 | P83: 2 | Q83: =VLOOKUP(P83,Key!$E$2:$F$9,2,FALSE) -> Work | R83: =K83&"-"&Q83 -> Commercial-Work | U83: 1 | Y83: Y | AA83: =VLOOKUP(F83,'Zones (3)'!$A$2:$F$15913,6,FALSE) -> 987 | AB83: =VLOOKUP(L83,'Zones (3)'!$A$2:$F$15616,6,FALSE) -> 376
B84: 0.5 | C84: UEJ 256N | D84: 11 | E84: 2 | F84: KASENYI | G84: ISINGIRO | H84: UG | I84: 8 | J84: 2 | K84: =VLOOKUP(J84,Key!$E$2:$F$9,2,FALSE) -> Work | L84: MUKIWOGA | M84: ISINGIRO | N84: UG | O84: 8 | P84: 4 | Q84: =VLOOKUP(P84,Key!$E$2:$F$9,2,FALSE) -> Commercial | R84: =K84&"-"&Q84 -> Work-Commercial | S84: 2 | T84: 0.2 | U84: 1 | Y84: Y | AA84: =VLOOKUP(F84,'Zones (3)'!$A$2:$F$15913,6,FALSE) -> 538 | AB84: =VLOOKUP(L84,'Zones (3)'!$A$2:$F$15616,6,FALSE) -> 379
B85: 0.50347222 | C85: UBD 241T | D85: 8 | E85: 1 | F85: KASENYI | G85: ISINGIRO | H85: UG | I85: 10 | J85: 2 | K85: =VLOOKUP(J85,Key!$E$2:$F$9,2,FALSE) -> Work | L85: KABALE | M85: ISINGIRO | N85: UG | O85: 15 | P85: 4 | Q85: =VLOOKUP(P85,Key!$E$2:$F$9,2,FALSE) -> Commercial | R85: =K85&"-"&Q85 -> Work-Commercial | S85: 1 | T85: 0 | U85: 1 | V85: 11 | Y85: Y | AA85: =VLOOKUP(F85,'Zones (3)'!$A$2:$F$15913,6,FALSE) -> 538 | AB85: =VLOOKUP(L85,'Zones (3)'!$A$2:$F$15616,6,FALSE) -> 422
B86: 0.50694444 | C86: UAU 338H | D86: 1 | E86: 1 | F86: MBARARA TOWN | G86: MBARARA | H86: UG | I86: 1 | J86: 1 | K86: =VLOOKUP(J86,Key!$E$2:$F$9,2,FALSE) -> Home | L86: ISINGIRO TOWN | M86: ISINGIRO | N86: UG | O86: 1 | P86: 1 | Q86: =VLOOKUP(P86,Key!$E$2:$F$9,2,FALSE) -> Home | R86: =K86&"-"&Q86 -> Home-Home | S86: 31 | T86: 2 | U86: 2 | Y86: Y | AA86: =VLOOKUP(F86,'Zones (3)'!$A$2:$F$15913,6,FALSE) -> 987 | AB86: =VLOOKUP(L86,'Zones (3)'!$A$2:$F$15616,6,FALSE) -> 379
B87: 0.51041667 | C87: UBE 962L | D87: 2 | E87: 2 | F87: MBARARA TOWN | G87: MBARARA | H87: UG | I87: 4 | J87: 3 | K87: =VLOOKUP(J87,Key!$E$2:$F$9,2,FALSE) -> Study | L87: KIRUMBA | M87: ISINGIRO | N87: UG | O87: 1 | P87: 1 | Q87: =VLOOKUP(P87,Key!$E$2:$F$9,2,FALSE) -> Home | R87: =K87&"-"&Q87 -> Study-Home | S87: 15 | T87: 0.3 | U87: 1 | Y87: Y | AA87: =VLOOKUP(F87,'Zones (3)'!$A$2:$F$15913,6,FALSE) -> 987 | AB87: =VLOOKUP(L87,'Zones (3)'!$A$2:$F$15616,6,FALSE) -> 850
B88: 0.51388889 | C88: UAP 691R | D88: 1 | E88: 2 | F88: MBARARA TOWN | G88: MBARARA | H88: UG | I88: 1 | J88: 1 | K88: =VLOOKUP(J88,Key!$E$2:$F$9,2,FALSE) -> Home | L88: KIKAGATI | M88: ISINGIRO | N88: UG | O88: 2 | P88: 2 | Q88: =VLOOKUP(P88,Key!$E$2:$F$9,2,FALSE) -> Work | R88: =K88&"-"&Q88 -> Home-Work | U88: 1 | Y88: Y | AA88: =VLOOKUP(F88,'Zones (3)'!$A$2:$F$15913,6,FALSE) -> 987 | AB88: =VLOOKUP(L88,'Zones (3)'!$A$2:$F$15616,6,FALSE) -> 379
B89: 0.51944444 | C89: UAM 835Z | D89: 2 | E89: 1 | F89: MBARARA TOWN | G89: MBARARA | H89: UG | I89: 1 | J89: 1 | K89: =VLOOKUP(J89,Key!$E$2:$F$9,2,FALSE) -> Home | L89: ISINGIRO TOWN | M89: ISINGIRO | N89: UG | O89: 1 | P89: 1 | Q89: =VLOOKUP(P89,Key!$E$2:$F$9,2,FALSE) -> Home | R89: =K89&"-"&Q89 -> Home-Home | S89: 40 | T89: 0.5 | U89: 1 | Y89: Y | AA89: =VLOOKUP(F89,'Zones (3)'!$A$2:$F$15913,6,FALSE) -> 987 | AB89: =VLOOKUP(L89,'Zones (3)'!$A$2:$F$15616,6,FALSE) -> 379
B90: 0.52430556 | C90: UEQ 325M | D90: 11 | E90: 1 | F90: KASENYI | G90: ISINGIRO | H90: UG | I90: 8 | J90: 2 | K90: =VLOOKUP(J90,Key!$E$2:$F$9,2,FALSE) -> Work | L90: KABEREBERE | M90: ISINGIRO | N90: UG | O90: 8 | P90: 2 | Q90: =VLOOKUP(P90,Key!$E$2:$F$9,2,FALSE) -> Work | R90: =K90&"-"&Q90 -> Work-Work | S90: 10 | T90: 0.5 | U90: 1 | Y90: Y | AA90: =VLOOKUP(F90,'Zones (3)'!$A$2:$F$15913,6,FALSE) -> 538 | AB90: =VLOOKUP(L90,'Zones (3)'!$A$2:$F$15616,6,FALSE) -> 380
B91: 0.68055556 | C91: UDG 462S | D91: 11 | E91: 1 | F91: MBARARA TOWN | G91: MBARARA | H91: UG | I91: 8 | J91: 2 | K91: =VLOOKUP(J91,Key!$E$2:$F$9,2,FALSE) -> Work | L91: ISINGIRO TOWN | M91: ISINGIRO | N91: UG | O91: 8 | P91: 2 | Q91: =VLOOKUP(P91,Key!$E$2:$F$9,2,FALSE) -> Work | R91: =K91&"-"&Q91 -> Work-Work | S91: 40 | T91: 1 | U91: 1 | Y91: Y | AA91: =VLOOKUP(F91,'Zones (3)'!$A$2:$F$15913,6,FALSE) -> 987 | AB91: =VLOOKUP(L91,'Zones (3)'!$A$2:$F$15616,6,FALSE) -> 379
B92: 0.54513889 | C92: UBE 052G | D92: 8 | E92: 2 | F92: IGANGA TOWN | G92: IGANGA | H92: UG | I92: 2 | J92: 2 | K92: =VLOOKUP(J92,Key!$E$2:$F$9,2,FALSE) -> Work | L92: ISINGIRO TOWN | M92: ISINGIRO | N92: UG | O92: 2 | P92: 2 | Q92: =VLOOKUP(P92,Key!$E$2:$F$9,2,FALSE) -> Work | R92: =K92&"-"&Q92 -> Work-Work | S92: 260 | T92: 0.4 | U92: 1 | V92: 11 | Y92: Y | AA92: =VLOOKUP(F92,'Zones (3)'!$A$2:$F$15913,6,FALSE) -> 365 | AB92: =VLOOKUP(L92,'Zones (3)'!$A$2:$F$15616,6,FALSE) -> 379
B93: 0.51388889 | C93: UAN 475M | D93: 1 | E93: 1 | F93: MBARARA TOWN | G93: MBARARA | H93: UG | I93: 4 | J93: 3 | K93: =VLOOKUP(J93,Key!$E$2:$F$9,2,FALSE) -> Study | L93: ISINGIRO TOWN | M93: ISINGIRO | N93: UG | O93: 1 | P93: 1 | Q93: =VLOOKUP(P93,Key!$E$2:$F$9,2,FALSE) -> Home | R93: =K93&"-"&Q93 -> Study-Home | S93: 20 | T93: 2 | U93: 4 | Y93: Y | AA93: =VLOOKUP(F93,'Zones (3)'!$A$2:$F$15913,6,FALSE) -> 987 | AB93: =VLOOKUP(L93,'Zones (3)'!$A$2:$F$15616,6,FALSE) -> 379
B94: 0.50763889 | C94: UPE 240E | D94: 1 | E94: 2 | F94: MBARARA TOWN | G94: MBARARA | H94: UG | I94: 2 | J94: 2 | K94: =VLOOKUP(J94,Key!$E$2:$F$9,2,FALSE) -> Work | L94: NYAMITANGA | M94: ISINGIRO | N94: UG | O94: 1 | P94: 1 | Q94: =VLOOKUP(P94,Key!$E$2:$F$9,2,FALSE) -> Home | R94: =K94&"-"&Q94 -> Work-Home | T94: 2 | U94: 1 | Y94: Y | AA94: =VLOOKUP(F94,'Zones (3)'!$A$2:$F$15913,6,FALSE) -> 987 | AB94: =VLOOKUP(L94,'Zones (3)'!$A$2:$F$15616,6,FALSE) -> 987
B95: 0.52916667 | C95: UAV 143P | D95: 11 | E95: 2 | F95: MBARARA TOWN | G95: MBARARA | H95: UG | I95: 1 | J95: 1 | K95: =VLOOKUP(J95,Key!$E$2:$F$9,2,FALSE) -> Home | L95: KABEREBERE | M95: ISINGIRO | N95: UG | O95: 8 | P95: 2 | Q95: =VLOOKUP(P95,Key!$E$2:$F$9,2,FALSE) -> Work | R95: =K95&"-"&Q95 -> Home-Work | S95: 40 | T95: 2 | U95: 1 | Y95: Y | AA95: =VLOOKUP(F95,'Zones (3)'!$A$2:$F$15913,6,FALSE) -> 987 | AB95: =VLOOKUP(L95,'Zones (3)'!$A$2:$F$15616,6,FALSE) -> 380
B96: 0.52638889 | C96: UET 325G | D96: 1 | E96: 2 | F96: MBARARA TOWN | G96: MBARARA | H96: UG | I96: 2 | J96: 2 | K96: Work | L96: ISINGIRO TOWN | M96: ISINGIRO | N96: UG | O96: 1 | P96: 1 | Q96: Home | R96: =K96&"-"&Q96 -> Work-Home | S96: 12 | T96: 2 | U96: 1 | Y96: Y | AA96: =VLOOKUP(F96,'Zones (3)'!$A$2:$F$15913,6,FALSE) -> 987 | AB96: =VLOOKUP(L96,'Zones (3)'!$A$2:$F$15616,6,FALSE) -> 379
B97: 0.6875 | C97: UAR 049L | D97: 1 | E97: 1 | F97: KATETE | G97: MBARARA | H97: UG | I97: 3 | J97: 4 | K97: =VLOOKUP(J97,Key!$E$2:$F$9,2,FALSE) -> Commercial | L97: KABEREBERE | M97: ISINGIRO | N97: UG | O97: 1 | P97: 1 | Q97: =VLOOKUP(P97,Key!$E$2:$F$9,2,FALSE) -> Home | R97: =K97&"-"&Q97 -> Commercial-Home | S97: 3 | T97: 0.5 | U97: 2 | Y97: Y | AA97: =VLOOKUP(F97,'Zones (3)'!$A$2:$F$15913,6,FALSE) -> 618 | AB97: =VLOOKUP(L97,'Zones (3)'!$A$2:$F$15616,6,FALSE) -> 380
B98: 0.69791667 | C98: UAX 096P | D98: 7 | E98: 3 | F98: MBARARA TOWN | G98: MBARARA | H98: UG | I98: 10 | J98: 4 | K98: =VLOOKUP(J98,Key!$E$2:$F$9,2,FALSE) -> Commercial | L98: KABEREBERE | M98: ISINGIRO | N98: UG | O98: 10 | P98: 4 | Q98: =VLOOKUP(P98,Key!$E$2:$F$9,2,FALSE) -> Commercial | R98: =K98&"-"&Q98 -> Commercial-Commercial | S98: 8 | T98: 0.3 | U98: 2 | V98: 4 | W98: 6 | Y98: Y | AA98: =VLOOKUP(F98,'Zones (3)'!$A$2:$F$15913,6,FALSE) -> 987 | AB98: =VLOOKUP(L98,'Zones (3)'!$A$2:$F$15616,6,FALSE) -> 380
B99: 0.69930556 | C99: UEE 491 | D99: 3 | E99: 2 | F99: MBARARA TOWN | G99: MBARARA | H99: UG | I99: 1 | J99: 1 | K99: =VLOOKUP(J99,Key!$E$2:$F$9,2,FALSE) -> Home | L99: KABEREBERE | M99: ISINGIRO | N99: UG | O99: 2 | P99: 2 | Q99: =VLOOKUP(P99,Key!$E$2:$F$9,2,FALSE) -> Work | R99: =K99&"-"&Q99 -> Home-Work | S99: 4 | T99: 0.2 | U99: 1 | Y99: Y | AA99: =VLOOKUP(F99,'Zones (3)'!$A$2:$F$15913,6,FALSE) -> 987 | AB99: =VLOOKUP(L99,'Zones (3)'!$A$2:$F$15616,6,FALSE) -> 380
B100: 0.70486111 | C100: UAX 589Q | D100: 1 | E100: 2 | F100: BUSHENYI TOWN | G100: BUSHENYI | H100: UG | I100: 4 | J100: 3 | K100: =VLOOKUP(J100,Key!$E$2:$F$9,2,FALSE) -> Study | L100: ISINGIRO TOWN | M100: ISINGIRO | N100: UG | O100: 4 | P100: 2 | Q100: =VLOOKUP(P100,Key!$E$2:$F$9,2,FALSE) -> Work | R100: =K100&"-"&Q100 -> Study-Work | S100: 80 | T100: 1 | U100: 1 | Y100: Y | AA100: =VLOOKUP(F100,'Zones (3)'!$A$2:$F$15913,6,FALSE) -> 253 | AB100: =VLOOKUP(L100,'Zones (3)'!$A$2:$F$15616,6,FALSE) -> 379
B101: 0.71111111 | C101: LG 018,035 | D101: 3 | E101: 1 | F101: JINJA TOWN | G101: JINJA | H101: UG | I101: 2 | J101: 2 | K101: =VLOOKUP(J101,Key!$E$2:$F$9,2,FALSE) -> Work | L101: KABEREBERE | M101: ISINGIRO | N101: UG | O101: 1 | P101: 1 | Q101: =VLOOKUP(P101,Key!$E$2:$F$9,2,FALSE) -> Home | R101: =K101&"-"&Q101 -> Work-Home | S101: 350 | T101: 0.2 | U101: 1 | Y101: Y | AA101: =VLOOKUP(F101,'Zones (3)'!$A$2:$F$15913,6,FALSE) -> 403 | AB101: =VLOOKUP(L101,'Zones (3)'!$A$2:$F$15616,6,FALSE) -> 380
B102: 0.67361111 | C102: UAV 933R | D102: 3 | E102: 1 | F102: MBARARA TOWN | G102: MBARARA | H102: UG | I102: 2 | J102: 2 | K102: =VLOOKUP(J102,Key!$E$2:$F$9,2,FALSE) -> Work | L102: KIKAGATI | M102: ISINGIRO | N102: UG | O102: 1 | P102: 1 | Q102: =VLOOKUP(P102,Key!$E$2:$F$9,2,FALSE) -> Home | R102: =K102&"-"&Q102 -> Work-Home | U102: 1 | Y102: Y | AA102: =VLOOKUP(F102,'Zones (3)'!$A$2:$F$15913,6,FALSE) -> 987 | AB102: =VLOOKUP(L102,'Zones (3)'!$A$2:$F$15616,6,FALSE) -> 379
...

Sheet Zones (3)
A1: ZONE NAME | B1: DISTRICT | C1: COUNTY | D1: SUBCOUNTY | E1: Parish | F1: ZONE No.
A2: Abim | B2: Abim | C2: Labwor | D2: =A2 -> Abim | F2: 1
A3: Abim Town Council | B3: Abim | C3: Labwor | D3: =A3 -> Abim Town Council | F3: 2
A4: Alerek | B4: Abim | C4: Labwor | D4: =A4 -> Alerek | F4: 3
A5: Lotukei | B5: Abim | C5: Labwor | D5: =A5 -> Lotukei | F5: 4
A6: Morulem | B6: Abim | C6: Labwor | D6: =A6 -> Morulem | F6: 5
A7: Nyakwae | B7: Abim | C7: Labwor | D7: =A7 -> Nyakwae | F7: 6
A8: Adjumani Town Council | B8: Adjumani | C8: East Moyo | D8: =A8 -> Adjumani Town Council | F8: 7
A9: Adropi | B9: Adjumani | C9: East Moyo | D9: =A9 -> Adropi | F9: 8
A10: Arinyapi | B10: Adjumani | C10: East Moyo | D10: =A10 -> Arinyapi | F10: 9
A11: Ciforo | B11: Adjumani | C11: East Moyo | D11: =A11 -> Ciforo | F11: 10
A12: Dzaipi | B12: Adjumani | C12: East Moyo | D12: =A12 -> Dzaipi | F12: 11
A13: Itirikwa | B13: Adjumani | C13: East Moyo | D13: =A13 -> Itirikwa | F13: 12
... A75: Amuru Town Council | B75: Amuru | C75: Kilak | D75: =A75 -> Amuru Town Council | F75: 74
A76: Amur town | D76: =A76 -> Amur town | F76: 74
A77: Attiak | B77: Amuru | C77: Kilak | D77: =A77 -> Attiak | F77: 75
A78: Lamogi | B78: Amuru | C78: Kilak | D78: =A78 -> Lamogi | F78: 76
A79: Pabo | B79: Amuru | C79: Kilak | D79: =A79 -> Pabo | F79: 77
A80: Abongomola | B80: Apac | C80: Kwania | D80: =A80 -> Abongomola | F80: 78
A81: Aduku | B81: Apac | C81: Kwania | D81: =A81 -> Aduku | F81: 79
A82: Aduku Town Council | B82: Apac | C82: Kwania | D82: =A82 -> Aduku Town Council | F82: 80
A83: Akokoro | B83: Apac | C83: Maruzi | D83: =A83 -> Akokoro | F83: 81
A84: Apac Muicipality | B84: Apac | C84: Apac Municipality | D84: =A84 -> Apac Muicipality | F84: 82
A85: Apac | D85: =A85 -> Apac | F85: 82
A86: Chawente | B86: Apac | C86: Kwania | D86: =A86 -> Chawente | F86: 83
A87: Chegere | B87: Apac | C87: Maruzi | D87: =A87 -> Chegere | F87: 84
A88: Ibuje | B88: Apac | C88: Maruzi | D88: =A88 -> Ibuje | F88: 85
A89: Inomo | B89: Apac | C89: Kwania | D89: =A89 -> Inomo | F89: 86
A90: Nambieso | B90: Apac | C90: Kwania | D90: =A90 -> Nambieso | F90: 87
A91: Adumi | B91: Arua | C91: Ayivu | D91: =A91 -> Adumi | F91: 88
A92: Aii-Vu | B92: Arua | C92: Terego | D92: =A92 -> Aii-Vu | F92: 89
A93: Ajia | B93: Arua | C93: Vurra | D93: =A93 -> Ajia | F93: 90
A94: Anyiribu | B94: Arua | C94: Madi Okollo | D94: =A94 -> Anyiribu | F94: 91
A95: Arivu | B95: Arua | C95: Vurra | D95: =A95 -> Arivu | F95: 92
A96: Aroi | B96: Arua | C96: Ayivu | D96: =A96 -> Aroi | F96: 93
A97: Arua Municipality | B97: Arua | C97: Arua Municipality | D97: =A97 -> Arua Municipality | F97: 94
A98: Arua | D98: =A98 -> Arua | F98: 94
A99: Ayivuni | B99: Arua | C99: Ayivu | D99: =A99 -> Ayivuni | F99: 95
A100: Bileafe | B100: Arua | C100: Terego | D100: =A100 -> Bileafe | F100: 96
A101: Dadamu | B101: Arua | C101: Ayivu | D101: =A101 -> Dadamu | F101: 97
A102: Ewanga | B102: Arua | C102: Madi Okollo | D102: =A102 -> Ewanga | F102: 98
A103: Katrini | B103: Arua | C103: Terego | D103: =A103 -> Katrini | F103: 99
A104: Logiri | B104: Arua | C104: Vurra | D104: =A104 -> Logiri | F104: 100
A105: Manibe | B105: Arua | C105: Ayivu | D105: =A105 -> Manibe | F105: 101
A106: Odupi | B106: Arua | C106: Terego | D106: =A106 -> Odupi | F106: 102
A107: Offaka | B107: Arua | C107: Madi Okollo | D107: =A107 -> Offaka | F107: 103
A108: Ogoko | B108: Arua | C108: Madi Okollo | D108: =A108 -> Ogoko | F108: 104
A109: Okollo | B109: Arua | C109: Madi Okollo | D109: =A109 -> Okollo | F109: 105
A110: Oluko | B110: Arua | C110: Ayivu | D110: =A110 -> Oluko | F110: 106
... A159: Bihanga-Buhweju | B159: Buhweju | C159: Buhweju | D159: =A159 -> Bihanga-Buhweju | F159: 155
A160: BUHWEJJU | D160: =A160 -> BUHWEJJU | F160: 155
A161: Bitsya | B161: Buhweju | C161: Buhweju | D161: =A161 -> Bitsya | F161: 156
A162: Burere | B162: Buhweju | C162: Buhweju | D162: =A162 -> Burere | F162: 157
A163: Engaju | B163: Buhweju | C163: Buhweju | D163: =A163 -> Engaju | F163: 158
A164: Karungu | B164: Buhweju | C164: Buhweju | D164: =A164 -> Karungu | F164: 159
A165: Nsiika Town Council | B165: Buhweju | C165: Buhweju | D165: =A165 -> Nsiika Town Council | F165: 160
A166: Nyakishana | B166: Buhweju | C166: Buhweju | D166: =A166 -> Nyakishana | F166: 161
A167: Rwengwe | B167: Buhweju | C167: Buhweju | D167: =A167 -> Rwengwe | F167: 162
A168: Buikwe | B168: Buikwe | C168: Buikwe | D168: =A168 -> Buikwe | F168: 163
A169: Namalili | D169: =A169 -> Namalili | F169: 163
A170: Lweru | D170: =A170 -> Lweru | F170: 163
A171: Buikwe Town Council | B171: Buikwe | C171: Buikwe | D171: =A171 -> Buikwe Town Council | F171: 164
A172: NAJJEMBA | D172: =A172 -> NAJJEMBA | F172: 164
A173: NAJEMBA | D173: =A173 -> NAJEMBA | F173: 164
A174: Buyikwe | D174: =A174 -> Buyikwe | F174: 164
A175: BUIKWE TOWN | D175: =A175 -> BUIKWE TOWN | F175: 164
A176: Lugazi Municipality | B176: Buikwe | C176: Lugazi Municipality | D176: =A176 -> Lugazi Municipality | F176: 165
A177: LUGAZI | D177: =A177 -> LUGAZI | F177: 165
A178: Namagunga | D178: =A178 -> Namagunga | F178: 165
A179: Najja | B179: Buikwe | C179: Buikwe | D179: =A179 -> Najja | F179: 166
A180: Ngogwe | B180: Buikwe | C180: Buikwe | D180: =A180 -> Ngogwe | F180: 167
A181: Njeru Municipality | B181: Buikwe | C181: Njeru Municipality | D181: =A181 -> Njeru Municipality | F181: 168
A182: Nkokonjeru Town Council | B182: Buikwe | C182: Buikwe | D182: =A182 -> Nkokonjeru Town Council | F182: 169
A183: Ssi-Bukunja | B183: Buikwe | C183: Buikwe | D183: =A183 -> Ssi-Bukunja | F183: 170
A184: Bukedea | B184: Bukedea | C184: Bukedea | D184: =A184 -> Bukedea | F184: 171
A185: Bukedea Town Council | B185: Bukedea | C185: Bukedea | D185: =A185 -> Bukedea Town Council | F185: 172
A186: Kachumbala | B186: Bukedea | C186: Bukedea | D186: =A186 -> Kachumbala | F186: 173
A187: Kidongole | B187: Bukedea | C187: Bukedea | D187: =A187 -> Kidongole | F187: 174
A188: Kolir | B188: Bukedea | C188: Bukedea | D188: =A188 -> Kolir | F188: 175
A189: Malera | B189: Bukedea | C189: Bukedea | D189: =A189 -> Malera | F189: 176
A190: Bigasa | B190: Bukomansimbi | C190: Bukomansimbi | D190: =A190 -> Bigasa | F190: 177
... A266: Bushenyi-Ishaka Municipality | B266: Bushenyi | C266: Bushenyi-Ishaka Municipality | D266: =A266 -> Bushenyi-Ishaka Municipality | F266: 253
A267: BUSHENYI | D267: =A267 -> BUSHENYI | F267: 253
A268: BUSHENYI TOWN | D268: =A268 -> BUSHENYI TOWN | F268: 253
A269: KYAMUNWUGA | D269: =A269 -> KYAMUNWUGA | F269: 253
A270: ISHAKA | D270: =A270 -> ISHAKA | F270: 253
A271: BWERENYANGI | D271: =A271 -> BWERENYANGI | F271: 253
A272: Munyonyi | D272: =A272 -> Munyonyi | F272: 253
A273: Ibaare | B273: Bushenyi | C273: Igara | D273: =A273 -> Ibaare | F273: 254
A274: Kakanju | B274: Bushenyi | C274: Igara | D274: =A274 -> Kakanju | F274: 255
A275: Kyabugimbi | B275: Bushenyi | C275: Igara | D275: =A275 -> Kyabugimbi | F275: 256
A276: Kyamuhunga | B276: Bushenyi | C276: Igara | D276: =A276 -> Kyamuhunga | F276: 257
A277: Kyamuhunga Town Council | B277: Bushenyi | C277: Igara | D277: =A277 -> Kyamuhunga Town Council | F277: 258
A278: Kyeizooba | B278: Bushenyi | C278: Igara | D278: =A278 -> Kyeizooba | F278: 259
A279: Nyabubare | B279: Bushenyi | C279: Igara | D279: =A279 -> Nyabubare | F279: 260
A280: Ruhumuro | B280: Bushenyi | C280: Igara | D280: =A280 -> Ruhumuro | F280: 261
A281: Buhehe | B281: Busia | C281: Samia-Bugwe | D281: =A281 -> Buhehe | F281: 262
A282: Bulumbi | B282: Busia | C282: Samia-Bugwe | D282: =A282 -> Bulumbi | F282: 263
A283: Busia Municipality | B283: Busia | C283: Busia Municipality | D283: =A283 -> Busia Municipality | F283: 264
A284: Busia town | D284: =A284 -> Busia town | F284: 264
...

Sheet Zone analysis
A1: Zone | B1: District | C1: County | D1: Subcounty | E1: Parish | F1: DRAFT FINAL ZONE LIST | G1: DISTRICT | H1: Subcounty
A2: 243 | B2: Alebtong | C2: Moroto | D2: Abako | F2: =D2 -> Abako | G2: =B2 -> Alebtong | H2: Abako
A3: 295 | B3: Zombo | C3: Okoro | D3: Abanga | F3: =D3 -> Abanga | G3: =B3 -> Zombo | H3: Abanga
A4: 886 | B4: Amuria | C4: Amuria | D4: Abarilela | F4: =D4 -> Abarilela | G4: =B4 -> Amuria | H4: Abarilela
A5: 215 | B5: Oyam | C5: Oyam | D5: Aber | F5: =D5 -> Aber | G5: =B5 -> Oyam | H5: Aber
A6: 244 | B6: Alebtong | C6: Moroto | D6: Abia | F6: =D6 -> Abia | G6: =B6 -> Alebtong | H6: Abia
A7: 151 | B7: Abim | C7: Labwor | D7: Abim | F7: =D7 -> Abim | G7: =B7 -> Abim | H7: Abim
A8: 152 | B8: Abim | C8: Labwor | D8: Abim Town Council | F8: =D8 -> Abim Town Council | G8: =B8 -> Abim | H8: Abim Town Council
A9: 107 | B9: Nebbi | C9: Nebbi Municipality | D9: Abindu Division | F9: =VLOOKUP(C9,[2]Municipalities!$C$9:$F$1522,4,FALSE) -> Nebbi Municipality | G9: =B9 -> Nebbi | H9: Abindu Division
A10: 216 | B10: Oyam | C10: Oyam | D10: Abok | F10: =D10 -> Abok | G10: =B10 -> Oyam | H10: Abok
A11: 256 | B11: Kole | C11: Kole | D11: Aboke | F11: =D11 -> Aboke | G11: =B11 -> Kole | H11: Aboke
A12: 11 | B12: Apac | C12: Kwania | D12: Abongomola | F12: =D12 -> Abongomola | G12: =B12 -> Apac | H12: Abongomola
A13: 198 | B13: Koboko | C13: Koboko | D13: Abuku | F13: =D13 -> Abuku | G13: =B13 -> Koboko | H13: Abuku
A14: 217 | B14: Oyam | C14: Oyam | D14: Acaba | F14: =D14 -> Acaba | G14: =B14 -> Oyam | H14: Acaba
A15: 126 | B15: Pader | C15: Aruu | D15: Acholibur | F15: =D15 -> Acholibur | G15: =B15 -> Pader | H15: Acholibur
A16: 897 | B16: Amuria | C16: Kapelebyong | D16: Acowa | F16: =D16 -> Acowa | G16: =B16 -> Amuria | H16: Acowa
A17: 173 | B17: Dokolo | C17: Dokolo | D17: Adeknino | F17: =D17 -> Adeknino | G17: =B17 -> Dokolo | H17: Adeknino
A18: 79 | B18: Lira | C18: Erute | D18: Adekokwok | F18: =D18 -> Adekokwok | G18: =B18 -> Lira | H18: Adekokwok
A19: 227 | B19: Agago | C19: Agago | D19: Adilang | F19: =D19 -> Adilang | G19: =B19 -> Agago | H19: Adilang
A20: 1 | B20: Adjumani | C20: East Moyo | D20: Adjumani Town Council | F20: =D20 -> Adjumani Town Council | G20: =B20 -> Adjumani | H20: Adjumani Town Council
A21: 174 | B21: Dokolo | C21: Dokolo | D21: Adok | F21: =D21 -> Adok | G21: =B21 -> Dokolo | H21: Adok
... A26: 287 | B26: Otuke | C26: Otuke | D26: Adwari | F26: =D26 -> Adwari | G26: =B26 -> Otuke | H26: Adwari
A27: 88 | B27: Lira | C27: Lira Municipality | D27: Adyel Division | F27: =VLOOKUP(C27,[2]Municipalities!$C$9:$F$1522,4,FALSE) -> Lira Municipality | G27: =B27 -> Lira | H27: Adyel Division
A28: 228 | B28: Agago | C28: Agago | D28: Agago Town Council | F28: =D28 -> Agago Town Council | G28: =B28 -> Agago | H28: Agago Town Council
A29: 80 | B29: Lira | C29: Erute | D29: Agali | F29: =D29 -> Agali | G29: =B29 -> Lira | H29: Agali
A30: 157 | B30: Amolatar | C30: Kioga | D30: Agikdak | F30: =D30 -> Agikdak | G30: =B30 -> Amolatar | H30: Agikdak
A31: 263 | B31: Lamwo | C31: Lamwo | D31: Agoro | F31: =D31 -> Agoro | G31: =B31 -> Lamwo | H31: Agoro
A32: 802 | B32: Pallisa | C32: Agule | D32: Agule | F32: =D32 -> Agule | G32: =B32 -> Pallisa | H32: Agule
A33: 175 | B33: Dokolo | C33: Dokolo | D33: Agwata | F33: =D33 -> Agwata | G33: =B33 -> Dokolo | H33: Agwata
A34: 81 | B34: Lira | C34: Erute | D34: Agweng | F34: =D34 -> Agweng | G34: =B34 -> Lira | H34: Agweng
A35: 158 | B35: Amolatar | C35: Kioga | D35: Agwingiri | F35: =D35 -> Agwingiri | G35: =B35 -> Amolatar | H35: Agwingiri
A36: 40 | B36: Arua | C36: Terego | D36: Aii-Vu | F36: =D36 -> Aii-Vu | G36: =B36 -> Arua | H36: Aii-Vu
A37: 46 | B37: Arua | C37: Vurra | D37: Ajia | F37: =D37 -> Ajia | G37: =B37 -> Arua | H37: Ajia
A38: 257 | B38: Kole | C38: Kole | D38: Akalo | F38: =D38 -> Akalo | G38: =B38 -> Kole | H38: Akalo
A39: 887 | B39: Amuria | C39: Amuria | D39: Akeriau | F39: =D39 -> Akeriau | G39: =B39 -> Amuria | H39: Akeriau
... A70: 31 | B70: Arua | C70: Madi Okollo | D70: Anyiribu | F70: =D70 -> Anyiribu | G70: =B70 -> Arua | H70: Anyiribu
A71: 20 | B71: Apac | C71: Apac Municipality | D71: Apac | F71: =VLOOKUP(C71,[2]Municipalities!$C$9:$F$1522,4,FALSE) -> Apac Muicipality | G71: =B71 -> Apac | H71: Apac
A72: 21 | B72: Apac | C72: Apac Municipality | D72: Apac Town Council | F72: =VLOOKUP(C72,[2]Municipalities!$C$9:$F$1522,4,FALSE) -> Apac Muicipality | G72: =B72 -> Apac | H72: Apac Town Council
A73: 249 | B73: Alebtong | C73: Moroto | D73: Apala | F73: =D73 -> Apala | G73: =B73 -> Alebtong | H73: Apala
A74: 846 | B74: Kaberamaido | C74: Kalaki | D74: Apapai | F74: =D74 -> Apapai | G74: =B74 -> Kaberamaido | H74: Apapai
A75: 889 | B75: Amuria | C75: Amuria | D75: Apeduru | F75: =D75 -> Apeduru | G75: =B75 -> Amuria | H75: Apeduru
A76: 840 | B76: Kaberamaido | C76: Kaberamaido | D76: Aperkira | F76: =D76 -> Aperkira | G76: =B76 -> Kaberamaido | H76: Aperkira
A77: 138 | B77: Yumbe | C77: Aringa | D77: Apo | F77: =D77 -> Apo | G77: =B77 -> Yumbe | H77: Apo
A78: 804 | B78: Pallisa | C78: Agule | D78: Apopong | F78: =D78 -> Apopong | G78: =B78 -> Pallisa | H78: Apopong
A79: 161 | B79: Amolatar | C79: Kioga | D79: Aputi | F79: =D79 -> Aputi | G79: =B79 -> Amolatar | H79: Aputi
A80: 813 | B80: Soroti | C80: Soroti | D80: Arapai | F80: =D80 -> Arapai | G80: =B80 -> Soroti | H80: Arapai
A81: 3 | B81: Adjumani | C81: East Moyo | D81: Arinyapi | F81: =D81 -> Arinyapi | G81: =B81 -> Adjumani | H81: Arinyapi
A82: 47 | B82: Arua | C82: Vurra | D82: Arivu | F82: =D82 -> Arivu | G82: =B82 -> Arua | H82: Arivu
A83: 139 | B83: Yumbe | C83: Aringa | D83: Ariwa | F83: =D83 -> Ariwa | G83: =B83 -> Yumbe | H83: Ariwa
A84: 25 | B84: Arua | C84: Ayivu | D84: Aroi | F84: =D84 -> Aroi | G84: =B84 -> Arua | H84: Aroi
A85: 83 | B85: Lira | C85: Erute | D85: Aromo | F85: =D85 -> Aromo | G85: =B85 -> Lira | H85: Aromo
A86: 22 | B86: Arua | C86: Arua Municipality | D86: Arua Hill Division | F86: =VLOOKUP(C86,[2]Municipalities!$C$9:$F$1522,4,FALSE) -> Arua Municipality | G86: =B86 -> Arua | H86: Arua Hill Division
A87: 229 | B87: Agago | C87: Agago | D87: Arum | F87: =D87 -> Arum | G87: =B87 -> Agago | H87: Arum
A88: 162 | B88: Amolatar | C88: Kioga | D88: Arwotcek | F88: =D88 -> Arwotcek | G88: =B88 -> Amolatar | H88: Arwotcek
A89: 890 | B89: Amuria | C89: Amuria | D89: Asamuk | F89: =D89 -> Asamuk | G89: =B89 -> Amuria | H89: Asamuk
A90: 810 | B90: Soroti | C90: Soroti | D90: Asuret | F90: =D90 -> Asuret | G90: =B90 -> Soroti | H90: Asuret
A91: 128 | B91: Pader | C91: Aruu | D91: Atanga | F91: =D91 -> Atanga | G91: =B91 -> Pader | H91: Atanga
A92: 111 | B92: Nebbi | C92: Padyere | D92: Atego | F92: =D92 -> Atego | G92: =B92 -> Nebbi | H92: Atego
A93: 1073 | B93: Serere | C93: Serere | D93: Atiira | F93: =D93 -> Atiira | G93: =B93 -> Serere | H93: Atiira
A94: 170 | B94: Amuru | C94: Kilak | D94: Attiak | F94: =D94 -> Attiak | G94: =B94 -> Amuru | H94: Attiak
A95: 763 | B95: Kumi | C95: Kumi | D95: Atutur | F95: =D95 -> Atutur | G95: =B95 -> Kumi | H95: Atutur
A96: 296 | B96: Zombo | C96: Okoro | D96: Atyak | F96: =D96 -> Atyak | G96: =B96 -> Zombo | H96: Atyak
A97: 50 | B97: Gulu | C97: Aswa | D97: Awach | F97: =D97 -> Awach | G97: =B97 -> Gulu | H97: Awach
A98: 250 | B98: Alebtong | C98: Moroto | D98: Awei | F98: =D98 -> Awei | G98: =B98 -> Alebtong | H98: Awei
... A109: 1054 | B109: Namayingo | C109: Bukooli | D109: Banda | F109: =D109 -> Banda | G109: =B109 -> Namayingo | H109: Banda
A110: 54 | B110: Gulu | C110: Gulu Municipality | D110: Bar Dege Division | F110: =VLOOKUP(C110,[2]Municipalities!$C$9:$F$1522,4,FALSE) -> Gulu Municipality | G110: =B110 -> Gulu | H110: Bar Dege Division
A111: 84 | B111: Lira | C111: Erute | D111: Barr | F111: =D111 -> Barr | G111: =B111 -> Lira | H111: Barr
A112: 177 | B112: Dokolo | C112: Dokolo | D112: Batta | F112: =D112 -> Batta | G112: =B112 -> Dokolo | H112: Batta
A113: 523 | B113: Kayunga | C113: Bbaale | D113: Bbaale | F113: =D113 -> Bbaale | G113: =B113 -> Kayunga | H113: Bbaale
A114: 565 | B114: Mityana | C114: Busujju | D114: Bbanda | F114: =D114 -> Bbanda | G114: =B114 -> Mityana | H114: Bbanda
A115: 1034 | B115: Kween | C115: Kween | D115: Benet | F115: =D115 -> Benet | G115: =B115 -> Kween | H115: Benet
A116: 606 | B116: Bukomansimbi | C116: Bukomansimbi | D116: Bigasa | F116: =D116 -> Bigasa | G116: =B116 -> Bukomansimbi | H116: Bigasa
A117: 1297 | B117: Kamwenge | C117: Kibale | D117: Biguli | F117: =D117 -> Biguli | G117: =B117 -> Kamwenge | H117: Biguli
A118: 1304 | B118: Kamwenge | C118: Kibale | D118: Bihanga | F118: =D118&"-"&B118 -> Bihanga-Kamwenge | G118: =B118 -> Kamwenge | H118: Bihanga
A119: 1405 | B119: Buhweju | C119: Buhweju | D119: Bihanga | F119: =D119&"-"&B119 -> Bihanga-Buhweju | G119: =B119 -> Buhweju | H119: Bihanga
A120: 1254 | B120: Mbarara | C120: Mbarara Municipality | D120: Biharwe Division | F120: =VLOOKUP(C120,[2]Municipalities!$C$9:$F$1522,4,FALSE) -> Mbarara Municipality | G120: =B120 -> Mbarara | H120: Biharwe Division
A121: 1346 | B121: Buliisa | C121: Buliisa | D121: Biiso | F121: =D121 -> Biiso | G121: =B121 -> Buliisa | H121: Biiso
A122: 41 | B122: Arua | C122: Terego | D122: Bileafe | F122: =D122 -> Bileafe | G122: =B122 -> Arua | H122: Bileafe
A123: 1035 | B123: Kween | C123: Kween | D123: Binyiny | F123: =D123 -> Binyiny | G123: =B123 -> Kween | H123: Binyiny
A124: 1036 | B124: Kween | C124: Kween | D124: Binyiny Town Council | F124: =D124 -> Binyiny Town Council | G124: =B124 -> Kween | H124: Binyiny Town Council
A125: 1495 | B125: Kakumiro | C125: Bugangaizi | D125: Birembo | F125: =D125 -> Birembo | G125: =B125 -> Kakumiro | H125: Birembo
A126: 1375 | B126: Isingiro | C126: Isingiro | D126: Birere | F126: =D126 -> Birere | G126: =B126 -> Isingiro | H126: Birere
A127: 1363 | B127: Ibanda | C127: Ibanda Municipality | D127: Bisheshe Division | F127: =VLOOKUP(C127,[2]Municipalities!$C$9:$F$1522,4,FALSE) -> Ibanda Municipality | G127: =B127 -> Ibanda | H127: Bisheshe Division
A128: 1430 | B128: Mitooma | C128: Ruhinda | D128: Bitereko | F128: =D128 -> Bitereko | G128: =B128 -> Mitooma | H128: Bitereko
A129: 1125 | B129: Bushenyi | C129: Igara | D129: Bitooma | F129: =D129 -> Bitooma | G129: =B129 -> Bushenyi | H129: Bitooma
A130: 1406 | B130: Buhweju | C130: Buhweju | D130: Bitsya | F130: =D130 -> Bitsya | G130: =B130 -> Buhweju | H130: Bitsya
A131: 305 | B131: Omoro | C131: Omoro | D131: Bobi | F131: =D131 -> Bobi | G131: =B131 -> Omoro | H131: Bobi
A132: 434 | B132: Luwero | C132: Katikamu | D132: Bombo Town Council | F132: =D132 -> Bombo Town Council | G132: =B132 -> Luwero | H132: Bombo Town Council
A133: 1244 | B133: Mbarara | C133: Kashari | D133: Bubaare | F133: =D133&"-"&B133 -> Bubaare-Mbarara | G133: =B133 -> Mbarara | H133: Bubaare
A134: 1506 | B134: Rubanda | C134: Rubanda | D134: Bubaare | F134: =D134&"-"&B134 -> Bubaare-Rubanda | G134: =B134 -> Rubanda | H134: Bubaare
A135: 1112 | B135: Bundibugyo | C135: Bwamba | D135: Bubandi | F135: =D135 -> Bubandi | G135: =B135 -> Bundibugyo | H135: Bubandi
A136: 1208 | B136: Kibaale | C136: Buyanja | D136: Bubango | F136: =D136 -> Bubango | G136: =B136 -> Kibaale | H136: Bubango
A137: 321 | B137: Kalangala | C137: Kyamuswa | D137: Bubeke | F137: =D137 -> Bubeke | G137: =B137 -> Kalangala | H137: Bubeke
A138: 915 | B138: Bududa | C138: Manjiya | D138: Bubiita | F138: =D138 -> Bubiita | G138: =B138 -> Bududa | H138: Bubiita
A139: 1113 | B139: Bundibugyo | C139: Bwamba | D139: Bubukwanga | F139: =D139 -> Bubukwanga | G139: =B139 -> Bundibugyo | H139: Bubukwanga
A140: 1085 | B140: Namisindwa | C140: Namisindwa | D140: Bubutu | F140: =D140 -> Bubutu | G140: =B140 -> Namisindwa | H140: Bubutu
A141: 771 | B141: Mbale | C141: Bungokho | D141: Bubyangu | F141: =D141 -> Bubyangu | G141: =B141 -> Mbale | H141: Bubyangu
A142: 865 | B142: Sironko | C142: Budadiri | D142: Budadiri Town Council | F142: =D142 -> Budadiri Town Council | G142: =B142 -> Sironko | H142: Budadiri Town Council
A143: 902 | B143: Budaka | C143: Budaka | D143: Budaka | F143: =D143 -> Budaka | G143: =B143 -> Budaka | H143: Budaka
A144: 903 | B144: Budaka | C144: Budaka | D144: Budaka Town Council | F144: =D144 -> Budaka Town Council | G144: =B144 -> Budaka | H144: Budaka Town Council
...

Sheet 26.10 ISINGIRO-MBARARA
B1: Consultancy services for Preparation of Expressway Development Master Plan (EDMP) for Uganda
B2: Roadside OD Interview Survey
B4: Date: | C4: 26.10.2019 | E4: Road Name: | F4: ='26.10 MBARARA-ISINGIRO'!F4:G4 -> MBARARA-NTUNGAMO ROAD | I4: Direction From: | L4: ISINGIRO | N4: Interviewers: | O4: AMOS.A, TUMUKUNDE DEVIS | V4: Supervisor: | W4: ='26.10 MBARARA-ISINGIRO'!W4 -> MIREMBE RUTH | Y4: Coded By: | Z4: ='26.10 MBARARA-ISINGIRO'!Z4 -> AJOK EMILY | AA4: Chkd By: | AB4: ='26.10 MBARARA-ISINGIRO'!AB4 -> 0
I5: Direction To: | L5: MBARARA
B7: Time | C7: Veh_Reg_No. | D7: Veh_Type | E7: No. Occupants | F7: Origin_Address | I7: Origin_Establish | J7: Origin_Purpose | K7: Origin-Purpose Desc | L7: Destination_Address | O7: Destination_Establish | P7: Destination_Purpose | Q7: Destination_Purpose Desc | R7: Journey_Purpose | S7: Approx_Distance (Km) | T7: Approx_Journey Time (Hrs) | U7: Trip_Frequency | V7: GOODS VEHICLES ONLY | Y7: Would You Use Xpressways? | Z7: Pay How Much? (UGX) | AA7: Origin_Zone | AB7: Dest_Zone
F8: Village or Town | G8: District | H8: Country | L8: Village or Town | M8: District | N8: Country | V8: Goods_Type | W8: Goods_Quantity (Ton) | X8: Goods_Value (UGXm)
B9: 0.7625 | C9: UAU 995A | D9: 4 | E9: 2 | F9: KABEREBERE | G9: ISINGIRO | H9: UG | I9: 6 | J9: 2 | K9: =VLOOKUP(J9,Key!$E$2:$F$9,2,FALSE) -> Work | L9: MBARARA TOWN | M9: MBARARA | N9: UG | O9: 6 | P9: 2 | Q9: =VLOOKUP(P9,Key!$E$2:$F$9,2,FALSE) -> Work | R9: =K9&"-"&Q9 -> Work-Work | S9: 15 | T9: 0.5 | U9: 4 | Y9: Y
B10: 0.75902778 | C10: UAY 487N | D10: 2 | E10: 2 | F10: KABALE | G10: ISINGIRO | H10: UG | I10: 1 | J10: 1 | K10: =VLOOKUP(J10,Key!$E$2:$F$9,2,FALSE) -> Home | L10: MBARARA TOWN | M10: MBARARA | N10: UG | O10: 2 | P10: 2 | Q10: =VLOOKUP(P10,Key!$E$2:$F$9,2,FALSE) -> Work | R10: =K10&"-"&Q10 -> Home-Work | S10: 5 | T10: 0.2 | U10: 5 | Y10: Y
B11: 0.75416667 | C11: UAY 682D | D11: 1 | E11: 2 | F11: RWENZIRINGIRO | G11: ISINGIRO | H11: UG | I11: 4 | J11: 3 | K11: =VLOOKUP(J11,Key!$E$2:$F$9,2,FALSE) -> Study | L11: MBARARA TOWN | M11: MBARARA | N11: UG | O11: 1 | P11: 1 | Q11: =VLOOKUP(P11,Key!$E$2:$F$9,2,FALSE) -> Home | R11: =K11&"-"&Q11 -> Study-Home | T11: 0.3 | U11: 3 | Y11: Y
B12: 0.75208333 | C12: UAP 980K | D12: 2 | E12: 1 | F12: KABALE | G12: ISINGIRO | H12: UG | I12: 1 | J12: 1 | K12: =VLOOKUP(J12,Key!$E$2:$F$9,2,FALSE) -> Home | L12: MBARARA TOWN | M12: MBARARA | N12: UG | O12: 2 | P12: 2 | Q12: =VLOOKUP(P12,Key!$E$2:$F$9,2,FALSE) -> Work | R12: =K12&"-"&Q12 -> Home-Work | S12: 4 | T12: 0.2 | U12: 3 | Y12: Y
B13: 0.74861111 | C13: UAQ 168G | D13: 1 | E13: 1 | F13: KABALE | G13: ISINGIRO | H13: UG | I13: 16 | J13: 8 | K13: =VLOOKUP(J13,Key!$E$2:$F$9,2,FALSE) -> Others | L13: MBARARA TOWN | M13: MBARARA | N13: UG | O13: 16 | P13: 8 | Q13: =VLOOKUP(P13,Key!$E$2:$F$9,2,FALSE) -> Others | R13: =K13&"-"&Q13 -> Others-Others | S13: 10 | T13: 0.2 | U13: 6 | Y13: Y
B14: 0.74513889 | C14: UAF 911X | D14: 1 | E14: 1 | F14: KABEREBERE | G14: ISINGIRO | H14: UG | I14: 2 | J14: 2 | K14: Work | L14: NYAMITANGA | M14: MBARARA | N14: UG | O14: 1 | P14: 1 | Q14: =VLOOKUP(P14,Key!$E$2:$F$9,2,FALSE) -> Home | R14: =K14&"-"&Q14 -> Work-Home | S14: 13 | T14: 0.3 | U14: 3 | Y14: Y
B15: 0.74166667 | C15: CD 103 62U | D15: 2 | E15: 2 | F15: ISINGIRO TOWN | G15: ISINGIRO | H15: UG | I15: 2 | J15: 2 | K15: =VLOOKUP(J15,Key!$E$2:$F$9,2,FALSE) -> Work | L15: MBARARA TOWN | M15: MBARARA | N15: UG | O15: 16 | P15: 8 | Q15: =VLOOKUP(P15,Key!$E$2:$F$9,2,FALSE) -> Others | R15: =K15&"-"&Q15 -> Work-Others | S15: 31 | T15: 0.8 | U15: 2 | Y15: Y
B16: 0.7375 | C16: UAX 388M | D16: 8 | E16: 1 | F16: KABINGO | G16: ISINGIRO | H16: UG | I16: 15 | J16: 4 | K16: =VLOOKUP(J16,Key!$E$2:$F$9,2,FALSE) -> Commercial | L16: MBARARA TOWN | M16: MBARARA | N16: UG | O16: 10 | P16: 2 | Q16: =VLOOKUP(P16,Key!$E$2:$F$9,2,FALSE) -> Work | R16: =K16&"-"&Q16 -> Commercial-Work | S16: 12 | T16: 0.5 | U16: 3 | V16: 4 | W16: 6 | X16: 220000 | Y16: Y
B17: 0.73333333 | C17: UAS 880K | D17: 1 | E17: 3 | F17: KABALE | G17: ISINGIRO | H17: UG | I17: 4 | J17: 3 | K17: =VLOOKUP(J17,Key!$E$2:$F$9,2,FALSE) -> Study | L17: MBARARA TOWN | M17: MBARARA | N17: UG | O17: 1 | P17: 1 | Q17: =VLOOKUP(P17,Key!$E$2:$F$9,2,FALSE) -> Home | R17: =K17&"-"&Q17 -> Study-Home | S17: 5 | T17: 0.5 | U17: 5 | Y17: Y
B18: 0.72916667 | C18: UAR 880V | D18: 1 | E18: 1 | F18: KABEREBERE | G18: ISINGIRO | H18: UG | I18: 2 | J18: 2 | K18: =VLOOKUP(J18,Key!$E$2:$F$9,2,FALSE) -> Work | L18: MBARARA TOWN | M18: MBARARA | N18: UG | O18: 2 | P18: 2 | Q18: =VLOOKUP(P18,Key!$E$2:$F$9,2,FALSE) -> Work | R18: =K18&"-"&Q18 -> Work-Work | S18: 35 | T18: 0.4 | U18: 4 | Y18: Y
B19: 0.725 | C19: UAY 304Y | D19: 8 | E19: 3 | F19: KABEREBERE | G19: ISINGIRO | H19: UG | I19: 3 | J19: 4 | K19: =VLOOKUP(J19,Key!$E$2:$F$9,2,FALSE) -> Commercial | L19: MBARARA TOWN | M19: MBARARA | N19: UG | O19: 4 | P19: 3 | Q19: =VLOOKUP(P19,Key!$E$2:$F$9,2,FALSE) -> Study | R19: =K19&"-"&Q19 -> Commercial-Study | S19: 10 | T19: 0.2 | U19: 2 | V19: 10 | W19: 4 | X19: 4500000 | Y19: Y
B20: 0.72083333 | C20: UBB 721A | D20: 1 | E20: 2 | F20: KABEREBERE | G20: ISINGIRO | H20: UG | I20: 3 | J20: 4 | K20: =VLOOKUP(J20,Key!$E$2:$F$9,2,FALSE) -> Commercial | L20: MBARARA TOWN | M20: MBARARA | N20: UG | O20: 1 | P20: 1 | Q20: =VLOOKUP(P20,Key!$E$2:$F$9,2,FALSE) -> Home | R20: =K20&"-"&Q20 -> Commercial-Home | S20: 25 | T20: 0.3 | U20: 3 | Y20: Y
B21: 0.71666667 | C21: UAL 702Y | D21: 1 | E21: 3 | F21: KABEREBERE | G21: ISINGIRO | H21: UG | I21: 1 | J21: 1 | K21: =VLOOKUP(J21,Key!$E$2:$F$9,2,FALSE) -> Home | L21: MBARARA TOWN | M21: MBARARA | N21: UG | O21: 16 | P21: 8 | Q21: =VLOOKUP(P21,Key!$E$2:$F$9,2,FALSE) -> Others | R21: =K21&"-"&Q21 -> Home-Others | S21: 35 | T21: 1 | U21: 4 | V21: 11 | Y21: Y
B22: 0.71458333 | C22: UAX 390W | D22: 1 | E22: 12 | F22: KABALE | G22: ISINGIRO | H22: UG | I22: 1 | J22: 1 | K22: =VLOOKUP(J22,Key!$E$2:$F$9,2,FALSE) -> Home | L22: MBARARA TOWN | M22: MBARARA | N22: UG | O22: 16 | P22: 8 | Q22: =VLOOKUP(P22,Key!$E$2:$F$9,2,FALSE) -> Others | R22: =K22&"-"&Q22 -> Home-Others | S22: 5 | T22: 0.2 | U22: 2 | Y22: Y
B23: 0.71111111 | C23: UAY 249B | D23: 1 | E23: 1 | F23: KASENYI | G23: ISINGIRO | H23: UG | I23: 16 | J23: 8 | K23: =VLOOKUP(J23,Key!$E$2:$F$9,2,FALSE) -> Others | L23: MBARARA TOWN | M23: MBARARA | N23: UG | O23: 1 | P23: 1 | Q23: =VLOOKUP(P23,Key!$E$2:$F$9,2,FALSE) -> Home | R23: =K23&"-"&Q23 -> Others-Home | S23: 6 | T23: 0 | U23: 3 | Y23: Y
B24: 0.70833333 | C24: UAS 808H | D24: 1 | E24: 2 | F24: KASENYI | G24: ISINGIRO | H24: UG | I24: 16 | J24: 8 | K24: =VLOOKUP(J24,Key!$E$2:$F$9,2,FALSE) -> Others | L24: MBARARA TOWN | M24: MBARARA | N24: UG | O24: 1 | P24: 1 | Q24: =VLOOKUP(P24,Key!$E$2:$F$9,2,FALSE) -> Home | R24: =K24&"-"&Q24 -> Others-Home | S24: 5 | T24: 0.3 | U24: 4 | Y24: Y
B25: 0.70416667 | C25: T487 BFH | D25: 10 | E25: 3 | F25: KABINGO | G25: ISINGIRO | H25: UG | I25: 13 | J25: 4 | K25: =VLOOKUP(J25,Key!$E$2:$F$9,2,FALSE) -> Commercial | L25: MBARARA TOWN | M25: MBARARA | N25: UG | O25: 16 | P25: 8 | Q25: =VLOOKUP(P25,Key!$E$2:$F$9,2,FALSE) -> Others | R25: Work-Others | S25: 32 | T25: 0.7 | U25: 4 | V25: 11 | Y25: Y
B26: 0.70138889 | C26: UAT 089N | D26: 3 | E26: 4 | F26: KIKAGATI | G26: ISINGIRO | H26: UG | I26: 2 | J26: 2 | K26: =VLOOKUP(J26,Key!$E$2:$F$9,2,FALSE) -> Work | L26: MBARARA TOWN | M26: MBARARA | N26: UG | O26: 1 | P26: 1 | Q26: =VLOOKUP(P26,Key!$E$2:$F$9,2,FALSE) -> Home | R26: =K26&"-"&Q26 -> Work-Home | S26: 40 | T26: 1.5 | U26: 6 | Y26: Y
B27: 0.69791667 | C27: UAM 124K | D27: 1 | E27: 8 | F27: KABINGO | G27: ISINGIRO | H27: UG | I27: 1 | J27: 1 | K27: =VLOOKUP(J27,Key!$E$2:$F$9,2,FALSE) -> Home | L27: MBARARA TOWN | M27: MBARARA | N27: UG | O27: 1 | P27: 1 | Q27: =VLOOKUP(P27,Key!$E$2:$F$9,2,FALSE) -> Home | R27: =K27&"-"&Q27 -> Home-Home | T27: 0.7 | U27: 3 | Y27: Y
B28: 0.69444444 | C28: UAQ 705F | D28: 1 | E28: 2 | F28: RWENJELU | G28: ISINGIRO | H28: UG | I28: 4 | J28: 3 | K28: =VLOOKUP(J28,Key!$E$2:$F$9,2,FALSE) -> Study | L28: MBARARA TOWN | M28: MBARARA | N28: UG | O28: 1 | P28: 1 | Q28: =VLOOKUP(P28,Key!$E$2:$F$9,2,FALSE) -> Home | R28: =K28&"-"&Q28 -> Study-Home | S28: 4 | T28: 0.5 | U28: 3 | Y28: Y
B29: 0.69027778 | C29: UAT 319R | D29: 1 | E29: 1 | F29: KASENYI | G29: ISINGIRO | H29: UG | I29: 4 | J29: 3 | K29: =VLOOKUP(J29,Key!$E$2:$F$9,2,FALSE) -> Study | L29: MBARARA TOWN | M29: MBARARA | N29: UG | O29: 1 | P29: 1 | Q29: =VLOOKUP(P29,Key!$E$2:$F$9,2,FALSE) -> Home | R29: =K29&"-"&Q29 -> Study-Home | S29: 10 | T29: 0.3 | U29: 3 | Y29: Y
B30: 0.68541667 | C30: UAN 083G | D30: 1 | E30: 2 | F30: NAKIVALA | G30: ISINGIRO | H30: UG | I30: 7 | J30: 2 | K30: =VLOOKUP(J30,Key!$E$2:$F$9,2,FALSE) -> Work | L30: MBARARA TOWN | M30: MBARARA | N30: UG | O30: 1 | P30: 1 | Q30: =VLOOKUP(P30,Key!$E$2:$F$9,2,FALSE) -> Home | R30: =K30&"-"&Q30 -> Work-Home | S30: 30 | T30: 2 | U30: 4 | V30: 10 | Y30: Y
B31: 0.53472222 | C31: UAZ 098F | D31: 2 | E31: 7 | F31: KIKAGATI | G31: ISINGIRO | H31: UG | I31: 1 | J31: 1 | K31: =VLOOKUP(J31,Key!$E$2:$F$9,2,FALSE) -> Home | L31: MBARARA TOWN | M31: MBARARA | N31: UG | O31: 1 | P31: 1 | Q31: =VLOOKUP(P31,Key!$E$2:$F$9,2,FALSE) -> Home | R31: =K31&"-"&Q31 -> Home-Home | S31: 69 | T31: 1 | U31: 4 | Y31: Y
B32: 0.53055556 | C32: UAJ 803W | D32: 1 | E32: 1 | F32: KABEREBERE | G32: ISINGIRO | H32: UG | I32: 1 | J32: 1 | K32: =VLOOKUP(J32,Key!$E$2:$F$9,2,FALSE) -> Home | L32: MBARARA TOWN | M32: MBARARA | N32: UG | O32: 2 | P32: 2 | Q32: =VLOOKUP(P32,Key!$E$2:$F$9,2,FALSE) -> Work | R32: =K32&"-"&Q32 -> Home-Work | S32: 9 | T32: 0.5 | U32: 2 | Y32: Y
B33: 0.52777778 | C33: UBE 386H | D33: 1 | E33: 4 | F33: KABEREBERE | G33: ISINGIRO | H33: UG | I33: 4 | J33: 3 | K33: =VLOOKUP(J33,Key!$E$2:$F$9,2,FALSE) -> Study | L33: MBARARA TOWN | M33: MBARARA | N33: UG | O33: 1 | P33: 1 | Q33: =VLOOKUP(P33,Key!$E$2:$F$9,2,FALSE) -> Home | R33: =K33&"-"&Q33 -> Study-Home | S33: 52 | T33: 1 | U33: 3 | Y33: Y
B34: 0.525 | C34: UBE 561U | D34: 2 | E34: 1 | F34: KIRUMBA | G34: ISINGIRO | H34: UG | I34: 16 | J34: 8 | K34: =VLOOKUP(J34,Key!$E$2:$F$9,2,FALSE) -> Others | L34: KAMPALA TOWN | M34: KAMPALA | N34: UG | O34: 1 | P34: 1 | Q34: =VLOOKUP(P34,Key!$E$2:$F$9,2,FALSE) -> Home | R34: =K34&"-"&Q34 -> Others-Home | T34: 3 | U34: 6 | Y34: Y
B35: 0.52083333 | C35: UBD 114B | D35: 1 | E35: 3 | F35: KASENYI | G35: ISINGIRO | H35: UG | I35: 1 | J35: 1 | K35: =VLOOKUP(J35,Key!$E$2:$F$9,2,FALSE) -> Home | L35: MBARARA TOWN | M35: MBARARA | N35: UG | O35: 2 | P35: 2 | Q35: =VLOOKUP(P35,Key!$E$2:$F$9,2,FALSE) -> Work | R35: =K35&"-"&Q35 -> Home-Work | S35: 4 | T35: 0.3 | U35: 1 | Y35: Y
B36: 0.51736111 | C36: UAD 009J | D36: 3 | E36: 2 | F36: KABEREBERE | G36: ISINGIRO | H36: UG | I36: 1 | J36: 1 | K36: =VLOOKUP(J36,Key!$E$2:$F$9,2,FALSE) -> Home | L36: MBARARA TOWN | M36: MBARARA | N36: UG | O36: 1 | P36: 1 | Q36: =VLOOKUP(P36,Key!$E$2:$F$9,2,FALSE) -> Home | R36: =K36&"-"&Q36 -> Home-Home | S36: 13 | T36: 0.5 | U36: 4 | V36: 10 | Y36: Y
B37: 0.51527778 | C37: UAP 660M | D37: 1 | E37: 4 | F37: KABEREBERE | G37: ISINGIRO | H37: UG | I37: 1 | J37: 1 | K37: =VLOOKUP(J37,Key!$E$2:$F$9,2,FALSE) -> Home | L37: MBARARA TOWN | M37: MBARARA | N37: UG | O37: 16 | P37: 8 | Q37: =VLOOKUP(P37,Key!$E$2:$F$9,2,FALSE) -> Others | R37: =K37&"-"&Q37 -> Home-Others | S37: 35 | T37: 2 | U37: 6 | Y37: Y
B38: 0.51319444 | C38: UAL 863M | D38: 2 | E38: 3 | F38: KABINGO | G38: ISINGIRO | H38: UG | I38: 1 | J38: 1 | K38: =VLOOKUP(J38,Key!$E$2:$F$9,2,FALSE) -> Home | L38: MBARARA TOWN | M38: MBARARA | N38: UG | O38: 5 | P38: 7 | Q38: =VLOOKUP(P38,Key!$E$2:$F$9,2,FALSE) -> Hospital | R38: =K38&"-"&Q38 -> Home-Hospital | S38: 36 | T38: 0.5 | U38: 3 | Y38: Y
B39: 0.51041667 | C39: UAW 625J | D39: 8 | E39: 2 | F39: KABEREBERE | G39: ISINGIRO | H39: UG | I39: 13 | J39: 4 | K39: =VLOOKUP(J39,Key!$E$2:$F$9,2,FALSE) -> Commercial | L39: MBARARA TOWN | M39: MBARARA | N39: UG | O39: 10 | P39: 2 | Q39: =VLOOKUP(P39,Key!$E$2:$F$9,2,FALSE) -> Work | R39: =K39&"-"&Q39 -> Commercial-Work | S39: 37 | T39: 1.5 | U39: 2 | V39: 4 | W39: 6 | X39: 40000 | Y39: Y
B40: 0.50763889 | C40: UAE 190G | D40: 1 | E40: 1 | F40: KASENYI | G40: ISINGIRO | H40: UG | I40: 4 | J40: 3 | K40: =VLOOKUP(J40,Key!$E$2:$F$9,2,FALSE) -> Study | L40: MBARARA TOWN | M40: MBARARA | N40: UG | O40: 1 | P40: 1 | Q40: =VLOOKUP(P40,Key!$E$2:$F$9,2,FALSE) -> Home | R40: =K40&"-"&Q40 -> Study-Home | S40: 2 | T40: 0.2 | U40: 2 | Y40: Y
B41: 0.44097222 | C41: UBA 760C | D41: 2 | E41: 2 | F41: ISINGIRO TOWN | G41: ISINGIRO | H41: UG | I41: 1 | J41: 1 | K41: =VLOOKUP(J41,Key!$E$2:$F$9,2,FALSE) -> Home | L41: MBARARA TOWN | M41: MBARARA | N41: UG | O41: 4 | P41: 3 | Q41: =VLOOKUP(P41,Key!$E$2:$F$9,2,FALSE) -> Study | R41: =K41&"-"&Q41 -> Home-Study | S41: 44 | T41: 1 | U41: 4 | Y41: Y
B42: 0.4375 | C42: UAQ 147X | D42: 2 | E42: 1 | F42: NGALAMA | G42: ISINGIRO | H42: UG | I42: 1 | J42: 1 | K42: =VLOOKUP(J42,Key!$E$2:$F$9,2,FALSE) -> Home | L42: MBARARA TOWN | M42: MBARARA | N42: UG | O42: 16 | P42: 8 | Q42: =VLOOKUP(P42,Key!$E$2:$F$9,2,FALSE) -> Others | R42: =K42&"-"&Q42 -> Home-Others | S42: 33 | T42: 1 | U42: 4 | Y42: Y
B43: 0.43472222 | C43: UAW 338V | D43: 2 | E43: 6 | F43: KASHUMBA | G43: ISINGIRO | H43: UG | I43: 1 | J43: 1 | K43: =VLOOKUP(J43,Key!$E$2:$F$9,2,FALSE) -> Home | L43: MBARARA TOWN | M43: MBARARA | N43: UG | O43: 4 | P43: 3 | Q43: =VLOOKUP(P43,Key!$E$2:$F$9,2,FALSE) -> Study | R43: =K43&"-"&Q43 -> Home-Study | T43: 2 | U43: 4 | Y43: Y
B44: 0.43194444 | C44: UET 296F | D44: 11 | E44: 2 | F44: KATETE | G44: ISINGIRO | H44: UG | I44: 8 | J44: 2 | K44: =VLOOKUP(J44,Key!$E$2:$F$9,2,FALSE) -> Work | L44: MBARARA TOWN | M44: MBARARA | N44: UG | O44: 8 | P44: 2 | Q44: =VLOOKUP(P44,Key!$E$2:$F$9,2,FALSE) -> Work | R44: =K44&"-"&Q44 -> Work-Work | S44: 6 | T44: 0.2 | U44: 2 | Y44: Y
B45: 0.43055556 | C45: UAT 165X | D45: 2 | E45: 1 | F45: RWIZIRINGIRO | G45: ISINGIRO | H45: UG | I45: 1 | J45: 1 | K45: =VLOOKUP(J45,Key!$E$2:$F$9,2,FALSE) -> Home | L45: MBARARA TOWN | M45: MBARARA | N45: UG | O45: 2 | P45: 2 | Q45: =VLOOKUP(P45,Key!$E$2:$F$9,2,FALSE) -> Work | R45: =K45&"-"&Q45 -> Home-Work | S45: 8 | T45: 0.3 | U45: 2 | Y45: Y
B46: 0.40972222 | C46: UAL 693S | D46: 1 | E46: 2 | F46: KASENYI | G46: ISINGIRO | H46: UG | I46: 1 | J46: 1 | K46: =VLOOKUP(J46,Key!$E$2:$F$9,2,FALSE) -> Home | L46: MBARARA TOWN | M46: MBARARA | N46: UG | O46: 2 | P46: 2 | Q46: =VLOOKUP(P46,Key!$E$2:$F$9,2,FALSE) -> Work | R46: =K46&"-"&Q46 -> Home-Work | S46: 7 | T46: 0.1 | U46: 2 | Y46: Y
B47: 0.40277778 | C47: UAF 824C | D47: 3 | E47: 3 | F47: KASENYI | G47: ISINGIRO | H47: UG | I47: 9 | J47: 4 | K47: =VLOOKUP(J47,Key!$E$2:$F$9,2,FALSE) -> Commercial | L47: MBARARA TOWN | M47: MBARARA | N47: UG | O47: 9 | P47: 4 | Q47: =VLOOKUP(P47,Key!$E$2:$F$9,2,FALSE) -> Commercial | R47: =K47&"-"&Q47 -> Commercial-Commercial | S47: 10 | T47: 0.3 | U47: 5 | V47: 9 | Y47: Y
B48: 0.40138889 | C48: UBA 397G | D48: 1 | E48: 2 | F48: KASENYI | G48: ISINGIRO | H48: UG | I48: 1 | J48: 1 | K48: =VLOOKUP(J48,Key!$E$2:$F$9,2,FALSE) -> Home | L48: MBARARA TOWN | M48: MBARARA | N48: UG | O48: 16 | P48: 8 | Q48: =VLOOKUP(P48,Key!$E$2:$F$9,2,FALSE) -> Others | R48: =K48&"-"&Q48 -> Home-Others | S48: 4 | T48: 0.1 | U48: 4 | Y48: Y
B49: 0.39861111 | C49: UAV 911T | D49: 1 | E49: 3 | F49: KABEREBERE | G49: ISINGIRO | H49: UG | I49: 1 | J49: 1 | K49: M | L49: MBARARA TOWN | M49: MBARARA | N49: UG | O49: 16 | P49: 8 | Q49: =VLOOKUP(P49,Key!$E$2:$F$9,2,FALSE) -> Others | R49: Others-Home | S49: 15 | T49: 0.3 | U49: 2 | Y49: Y
B50: 0.39583333 | C50: UBB 457M | D50: 1 | E50: 5 | F50: KIKAGATI | G50: ISINGIRO | H50: UG | I50: 1 | J50: 1 | K50: =VLOOKUP(J50,Key!$E$2:$F$9,2,FALSE) -> Home | L50: MBARARA TOWN | M50: MBARARA | N50: UG | O50: 2 | P50: 2 | Q50: =VLOOKUP(P50,Key!$E$2:$F$9,2,FALSE) -> Work | R50: =K50&"-"&Q50 -> Home-Work | S50: 35 | T50: 3 | U50: 2 | Y50: Y
B51: 0.39444444 | C51: UAH 651L | D51: 1 | E51: 5 | F51: KASENYI | G51: ISINGIRO | H51: UG | I51: 1 | J51: 1 | K51: =VLOOKUP(J51,Key!$E$2:$F$9,2,FALSE) -> Home | L51: MBARARA TOWN | M51: MBARARA | N51: UG | O51: 4 | P51: 3 | Q51: =VLOOKUP(P51,Key!$E$2:$F$9,2,FALSE) -> Study | R51: =K51&"-"&Q51 -> Home-Study | S51: 6 | T51: 0 | U51: 2 | Y51: Y
B52: 0.39236111 | C52: UAS 400V | D52: 1 | E52: 5 | F52: NAKIVALA | G52: ISINGIRO | H52: UG | I52: 1 | J52: 1 | K52: =VLOOKUP(J52,Key!$E$2:$F$9,2,FALSE) -> Home | L52: MBARARA TOWN | M52: MBARARA | N52: UG | O52: 1 | P52: 1 | Q52: =VLOOKUP(P52,Key!$E$2:$F$9,2,FALSE) -> Home | R52: =K52&"-"&Q52 -> Home-Home | S52: 4 | T52: 0.2 | U52: 4 | Y52: Y
B53: 0.39027778 | C53: UAK 315M | D53: 1 | E53: 1 | F53: KASENYI | G53: ISINGIRO | H53: UG | I53: 1 | J53: 1 | K53: =VLOOKUP(J53,Key!$E$2:$F$9,2,FALSE) -> Home | L53: KOLANOLYA | M53: MBARARA | N53: UG | O53: 9 | P53: 2 | Q53: =VLOOKUP(P53,Key!$E$2:$F$9,2,FALSE) -> Work | R53: =K53&"-"&Q53 -> Home-Work | T53: 0.3 | U53: 2 | Y53: Y
B54: 0.38888889 | C54: UAW 583E | D54: 1 | E54: 4 | F54: ISINGIRO TOWN | G54: ISINGIRO | H54: UG | I54: 1 | J54: 1 | K54: =VLOOKUP(J54,Key!$E$2:$F$9,2,FALSE) -> Home | L54: MBARARA TOWN | M54: MBARARA | N54: UG | O54: 4 | P54: 3 | Q54: =VLOOKUP(P54,Key!$E$2:$F$9,2,FALSE) -> Study | R54: =K54&"-"&Q54 -> Home-Study | S54: 35 | T54: 1.5 | U54: 5 | Y54: Y
B55: 0.38541667 | C55: UAS 038R | D55: 3 | E55: 2 | F55: ISINGIRO TOWN | G55: ISINGIRO | H55: UG | I55: 16 | J55: 8 | K55: =VLOOKUP(J55,Key!$E$2:$F$9,2,FALSE) -> Others | L55: MBARARA TOWN | M55: MBARARA | N55: UG | O55: 16 | P55: 8 | Q55: =VLOOKUP(P55,Key!$E$2:$F$9,2,FALSE) -> Others | R55: =K55&"-"&Q55 -> Others-Others | S55: 32 | T55: 0.7 | U55: 3 | Y55: Y
B56: 0.38194444 | C56: UAR 829U | D56: 3 | E56: 5 | F56: KABALE | G56: ISINGIRO | H56: UG | I56: 1 | J56: 1 | K56: =VLOOKUP(J56,Key!$E$2:$F$9,2,FALSE) -> Home | L56: MBARARA TOWN | M56: MBARARA | N56: UG | O56: 2 | P56: 2 | Q56: =VLOOKUP(P56,Key!$E$2:$F$9,2,FALSE) -> Work | R56: =K56&"-"&Q56 -> Home-Work | S56: 4 | T56: 0.2 | U56: 2 | Y56: Y
B57: 0.37152778 | C57: UEV 044V | D57: 11 | E57: 1 | F57: OMUKIHOGO | G57: ISINGIRO | H57: UG | I57: 8 | J57: 2 | K57: =VLOOKUP(J57,Key!$E$2:$F$9,2,FALSE) -> Work | L57: MBARARA TOWN | M57: MBARARA | N57: UG | O57: 8 | P57: 2 | Q57: =VLOOKUP(P57,Key!$E$2:$F$9,2,FALSE) -> Work | R57: =K57&"-"&Q57 -> Work-Work | S57: 4 | T57: 0.2 | U57: 2 | Y57: Y
B58: 0.36805556 | C58: UAL 402T | D58: 1 | E58: 2 | F58: KABEREBERE | G58: ISINGIRO | H58: UG | I58: 1 | J58: 1 | K58: =VLOOKUP(J58,Key!$E$2:$F$9,2,FALSE) -> Home | L58: MBARARA TOWN | M58: MBARARA | N58: UG | O58: 2 | P58: 2 | Q58: =VLOOKUP(P58,Key!$E$2:$F$9,2,FALSE) -> Work | R58: =K58&"-"&Q58 -> Home-Work | S58: 13 | T58: 0.5 | U58: 2 | Y58: Y
B59: 0.36666667 | C59: UAK 262K | D59: 1 | E59: 2 | F59: MASHA | G59: ISINGIRO | H59: UG | I59: 1 | J59: 1 | K59: =VLOOKUP(J59,Key!$E$2:$F$9,2,FALSE) -> Home | L59: MBARARA TOWN | M59: MBARARA | N59: UG | O59: 2 | P59: 2 | Q59: =VLOOKUP(P59,Key!$E$2:$F$9,2,FALSE) -> Work | R59: =K59&"-"&Q59 -> Home-Work | S59: 12 | T59: 0.8 | U59: 2 | Y59: Y
B60: 0.3625 | C60: UEM 875L | D60: 11 | E60: 1 | F60: OMUKIHOGO | G60: ISINGIRO | H60: UG | I60: 8 | J60: 2 | K60: =VLOOKUP(J60,Key!$E$2:$F$9,2,FALSE) -> Work | L60: MBARARA TOWN | M60: MBARARA | N60: UG | O60: 8 | P60: 2 | Q60: =VLOOKUP(P60,Key!$E$2:$F$9,2,FALSE) -> Work | R60: =K60&"-"&Q60 -> Work-Work | S60: 4 | T60: 0.3 | U60: 2 | Y60: Y
B61: 0.36111111 | C61: UDZ 915T | D61: 11 | E61: 1 | F61: RWENKWELA | G61: ISINGIRO | H61: UG | I61: 8 | J61: 2 | K61: =VLOOKUP(J61,Key!$E$2:$F$9,2,FALSE) -> Work | L61: MBARARA TOWN | M61: MBARARA | N61: UG | O61: 8 | P61: 2 | Q61: =VLOOKUP(P61,Key!$E$2:$F$9,2,FALSE) -> Work | R61: =K61&"-"&Q61 -> Work-Work | T61: 0.5 | U61: 2 | Y61: Y
B62: 0.35972222 | C62: UAT 352P | D62: 1 | E62: 5 | F62: KASUMBA | G62: ISINGIRO | H62: UG | I62: 1 | J62: 1 | K62: =VLOOKUP(J62,Key!$E$2:$F$9,2,FALSE) -> Home | L62: MBARARA TOWN | M62: MBARARA | N62: UG | O62: 16 | P62: 8 | Q62: =VLOOKUP(P62,Key!$E$2:$F$9,2,FALSE) -> Others | R62: =K62&"-"&Q62 -> Home-Others | S62: 95 | T62: 2 | U62: 3 | Y62: Y
B63: 0.35763889 | C63: UBC 912D | D63: 7 | E63: 1 | F63: KABEREBERE | G63: ISINGIRO | H63: UG | I63: 11 | J63: 2 | K63: =VLOOKUP(J63,Key!$E$2:$F$9,2,FALSE) -> Work | L63: MBARARA TOWN | M63: MBARARA | N63: UG | O63: 3 | P63: 2 | Q63: =VLOOKUP(P63,Key!$E$2:$F$9,2,FALSE) -> Work | R63: =K63&"-"&Q63 -> Work-Work | S63: 16 | T63: 0.3 | U63: 3 | V63: 11 | Y63: Y
B64: 0.35416667 | C64: UBB 507R | D64: 1 | E64: 1 | F64: KABALE | G64: ISINGIRO | H64: UG | I64: 1 | J64: 1 | K64: =VLOOKUP(J64,Key!$E$2:$F$9,2,FALSE) -> Home | L64: MBARARA TOWN | M64: MBARARA | N64: UG | O64: 2 | P64: 2 | Q64: =VLOOKUP(P64,Key!$E$2:$F$9,2,FALSE) -> Work | R64: =K64&"-"&Q64 -> Home-Work | S64: 12 | T64: 1 | U64: 2 | Y64: Y
B65: 0.35069444 | C65: UES 545V | D65: 11 | E65: 1 | F65: KASENYI | G65: ISINGIRO | H65: UG | I65: 8 | J65: 2 | K65: =VLOOKUP(J65,Key!$E$2:$F$9,2,FALSE) -> Work | L65: KASENYI | M65: ISINGIRO | N65: UG | O65: 8 | P65: 2 | Q65: =VLOOKUP(P65,Key!$E$2:$F$9,2,FALSE) -> Work | R65: =K65&"-"&Q65 -> Work-Work | S65: 1 | T65: 0 | U65: 2 | Y65: Y
B66: 0.34722222 | C66: UAZ 009D | D66: 1 | E66: 2 | F66: BUTENGA | G66: ISINGIRO | H66: UG | I66: 1 | J66: 1 | K66: =VLOOKUP(J66,Key!$E$2:$F$9,2,FALSE) -> Home | L66: MBARARA TOWN | M66: MBARARA | N66: UG | O66: 16 | P66: 8 | Q66: =VLOOKUP(P66,Key!$E$2:$F$9,2,FALSE) -> Others | R66: =K66&"-"&Q66 -> Home-Others | S66: 12 | T66: 0.2 | U66: 3 | Y66: Y
B67: 0.75833333 | C67: UES 289B | D67: 11 | E67: 1 | F67: KABALE | G67: ISINGIRO | H67: UG | I67: 8 | J67: 2 | K67: =VLOOKUP(J67,Key!$E$2:$F$9,2,FALSE) -> Work | L67: KASENYI | M67: ISINGIRO | N67: UG | O67: 8 | P67: 2 | Q67: =VLOOKUP(P67,Key!$E$2:$F$9,2,FALSE) -> Work | R67: =K67&"-"&Q67 -> Work-Work | S67: 1 | T67: 0.1 | U67: 2 | Y67: Y
B68: 0.74652778 | C68: UAP 472H | D68: 8 | E68: 1 | F68: KASENYI | G68: ISINGIRO | H68: UG | I68: 10 | J68: 2 | K68: =VLOOKUP(J68,Key!$E$2:$F$9,2,FALSE) -> Work | L68: MBARARA TOWN | M68: MBARARA | N68: UG | O68: 15 | P68: 4 | Q68: =VLOOKUP(P68,Key!$E$2:$F$9,2,FALSE) -> Commercial | R68: =K68&"-"&Q68 -> Work-Commercial | S68: 3 | T68: 0.1 | U68: 2 | V68: 11 | Y68: Y
B69: 0.74236111 | C69: UBA 631T | D69: 3 | E69: 1 | F69: ISINGIRO TOWN | G69: ISINGIRO | H69: UG | I69: 12 | J69: 4 | K69: =VLOOKUP(J69,Key!$E$2:$F$9,2,FALSE) -> Commercial | L69: MBARARA TOWN | M69: MBARARA | N69: UG | O69: 11 | P69: 4 | Q69: =VLOOKUP(P69,Key!$E$2:$F$9,2,FALSE) -> Commercial | R69: =K69&"-"&Q69 -> Commercial-Commercial | S69: 31 | T69: 2 | U69: 1 | V69: 10 | Y69: Y
B70: 0.73402778 | C70: UAU 692G | D70: 8 | E70: 2 | F70: MUKIHOGO | G70: ISINGIRO | H70: UG | I70: 15 | J70: 4 | K70: =VLOOKUP(J70,Key!$E$2:$F$9,2,FALSE) -> Commercial | L70: MBARARA TOWN | M70: MBARARA | N70: UG | O70: 10 | P70: 2 | Q70: =VLOOKUP(P70,Key!$E$2:$F$9,2,FALSE) -> Work | R70: =K70&"-"&Q70 -> Commercial-Work | S70: 7 | T70: 0.2 | U70: 3 | V70: 4 | W70: 9 | Y70: Y
B71: 0.72777778 | C71: UAR 567X | D71: 1 | E71: 1 | F71: NAKIVALA | G71: ISINGIRO | H71: UG | I71: 1 | J71: 1 | K71: =VLOOKUP(J71,Key!$E$2:$F$9,2,FALSE) -> Home | L71: MBARARA TOWN | M71: MBARARA | N71: UG | O71: 2 | P71: 2 | Q71: =VLOOKUP(P71,Key!$E$2:$F$9,2,FALSE) -> Work | R71: =K71&"-"&Q71 -> Home-Work | S71: 5 | T71: 0.2 | U71: 2 | Y71: Y
B72: 0.72361111 | C72: UBE 908H | D72: 2 | E72: 1 | F72: KIKAGATI | G72: ISINGIRO | H72: UG | I72: 11 | J72: 2 | K72: =VLOOKUP(J72,Key!$E$2:$F$9,2,FALSE) -> Work | L72: MBARARA TOWN | M72: MBARARA | N72: UG | O72: 7 | P72: 2 | Q72: =VLOOKUP(P72,Key!$E$2:$F$9,2,FALSE) -> Work | R72: =K72&"-"&Q72 -> Work-Work | S72: 13 | T72: 0.3 | U72: 4 | Y72: Y
B73: 0.71527778 | C73: UBE 030F | D73: 1 | E73: 2 | F73: ISINGIRO TOWN | G73: ISINGIRO | H73: UG | I73: 1 | J73: 1 | K73: =VLOOKUP(J73,Key!$E$2:$F$9,2,FALSE) -> Home | L73: MBARARA TOWN | M73: MBARARA | N73: UG | O73: 2 | P73: 2 | Q73: =VLOOKUP(P73,Key!$E$2:$F$9,2,FALSE) -> Work | R73: =K73&"-"&Q73 -> Home-Work | S73: 31 | T73: 2 | U73: 2 | Y73: Y
B74: 0.70694444 | C74: UAU 481T | D74: 2 | E74: 1 | F74: KABEREBERE | G74: ISINGIRO | H74: UG | I74: 9 | J74: 4 | K74: =VLOOKUP(J74,Key!$E$2:$F$9,2,FALSE) -> Commercial | L74: MBARARA TOWN | M74: MBARARA | N74: UG | O74: 1 | P74: 1 | Q74: =VLOOKUP(P74,Key!$E$2:$F$9,2,FALSE) -> Home | R74: =K74&"-"&Q74 -> Commercial-Home | S74: 10 | T74: 0.3 | U74: 3 | Y74: Y
B75: 0.69513889 | C75: UBD 149Q | D75: 1 | E75: 1 | F75: KASENYI | G75: ISINGIRO | H75: UG | I75: 4 | J75: 3 | K75: =VLOOKUP(J75,Key!$E$2:$F$9,2,FALSE) -> Study | L75: MBARARA TOWN | M75: MBARARA | N75: UG | O75: 16 | P75: 8 | Q75: =VLOOKUP(P75,Key!$E$2:$F$9,2,FALSE) -> Others | R75: =K75&"-"&Q75 -> Study-Others | S75: 5 | T75: 0.2 | U75: 2 | Y75: Y
B76: 0.6875 | C76: UAP 123F | D76: 8 | E76: 2 | F76: ISINGIRO TOWN | G76: ISINGIRO | H76: UG | I76: 14 | J76: 4 | K76: =VLOOKUP(J76,Key!$E$2:$F$9,2,FALSE) -> Commercial | L76: NYAMITANGA | M76: MBARARA | N76: UG | O76: 12 | P76: 4 | Q76: =VLOOKUP(P76,Key!$E$2:$F$9,2,FALSE) -> Commercial | R76: =K76&"-"&Q76 -> Commercial-Commercial | S76: 31 | T76: 1 | U76: 4 | V76: 6 | Y76: Y
B77: 0.53194444 | C77: UAP 129K | D77: 1 | E77: 3 | F77: KASENYI | G77: ISINGIRO | H77: UG | I77: 1 | J77: 1 | K77: =VLOOKUP(J77,Key!$E$2:$F$9,2,FALSE) -> Home | L77: MBARARA TOWN | M77: MBARARA | N77: UG | O77: 5 | P77: 7 | Q77: =VLOOKUP(P77,Key!$E$2:$F$9,2,FALSE) -> Hospital | R77: =K77&"-"&Q77 -> Home-Hospital | S77: 4 | T77: 0.1 | U77: 4 | Y77: Y
B78: 0.52708333 | C78: UAN 328V | D78: 1 | E78: 1 | F78: KIRUMBA | G78: ISINGIRO | H78: UG | I78: 4 | J78: 3 | K78: =VLOOKUP(J78,Key!$E$2:$F$9,2,FALSE) -> Study | L78: MBARARA TOWN | M78: MBARARA | N78: UG | O78: 1 | P78: 1 | Q78: =VLOOKUP(P78,Key!$E$2:$F$9,2,FALSE) -> Home | R78: =K78&"-"&Q78 -> Study-Home | S78: 5 | T78: 0.2 | U78: 2 | Y78: Y
B79: 0.52083333 | C79: UAX 758T | D79: 3 | E79: 2 | F79: ISINGIRO TOWN | G79: ISINGIRO | H79: UG | I79: 2 | J79: 2 | K79: =VLOOKUP(J79,Key!$E$2:$F$9,2,FALSE) -> Work | L79: MBARARA TOWN | M79: MBARARA | N79: UG | O79: 1 | P79: 1 | Q79: =VLOOKUP(P79,Key!$E$2:$F$9,2,FALSE) -> Home | R79: =K79&"-"&Q79 -> Work-Home | S79: 31 | T79: 1.5 | U79: 2 | Y79: Y
B80: 0.51041667 | C80: UAZ 158C | D80: 1 | E80: 1 | F80: ISINGIRO TOWN | G80: ISINGIRO | H80: UG | I80: 1 | J80: 1 | K80: =VLOOKUP(J80,Key!$E$2:$F$9,2,FALSE) -> Home | L80: MBARARA TOWN | M80: MBARARA | N80: UG | O80: 16 | P80: 8 | Q80: =VLOOKUP(P80,Key!$E$2:$F$9,2,FALSE) -> Others | R80: =K80&"-"&Q80 -> Home-Others | S80: 32 | T80: 1 | U80: 3 | Y80: Y
B81: 0.49722222 | C81: UAX 500C | D81: 1 | E81: 1 | F81: MUKIHOGO | G81: ISINGIRO | H81: UG | I81: 1 | J81: 1 | K81: =VLOOKUP(J81,Key!$E$2:$F$9,2,FALSE) -> Home | L81: MBARARA TOWN | M81: MBARARA | N81: UG | O81: 2 | P81: 2 | Q81: =VLOOKUP(P81,Key!$E$2:$F$9,2,FALSE) -> Work | R81: =K81&"-"&Q81 -> Home-Work | S81: 4 | T81: 0.1 | U81: 2 | Y81: Y
B82: 0.49166667 | C82: UAD 044P | D82: 1 | E82: 3 | F82: KABEREBERE | G82: ISINGIRO | H82: UG | I82: 16 | J82: 8 | K82: =VLOOKUP(J82,Key!$E$2:$F$9,2,FALSE) -> Others | L82: MBARARA TOWN | M82: MBARARA | N82: UG | O82: 16 | P82: 8 | Q82: =VLOOKUP(P82,Key!$E$2:$F$9,2,FALSE) -> Others | R82: =K82&"-"&Q82 -> Others-Others | T82: 1 | U82: 2 | Y82: Y

Sheet 26.10 MBARARA-ISINGIRO
B1: Consultancy services for Preparation of Expressway Development Master Plan (EDMP) for Uganda
B2: Roadside OD Interview Survey
B4: Date: | C4: 26.10.2019 | E4: Road Name: | F4: ='28.10 MBARARA-ISINGIRO'!F4:G4 -> MBARARA-NTUNGAMO ROAD | I4: Direction From: | L4: MBARARA | N4: Interviewers: | O4: MIREMBE RUTH, NIWAMANYA SAVIOR | V4: Supervisor: | W4: ='28.10 MBARARA-ISINGIRO'!W4 -> MIREMBE RUTH | Y4: Coded By: | Z4: ='28.10 MBARARA-ISINGIRO'!Z4 -> AJOK EMILY | AA4: Chkd By: | AB4: ='28.10 MBARARA-ISINGIRO'!AB4 -> 0
I5: Direction To: | L5: ISINGIRO
B7: Time | C7: Veh_Reg_No. | D7: Veh_Type | E7: No. Occupants | F7: Origin_Address | I7: Origin_Establish | J7: Origin_Purpose | K7: Origin-Purpose Desc | L7: Destination_Address | O7: Destination_Establish | P7: Destination_Purpose | Q7: Destination_Purpose Desc | R7: Journey_Purpose | S7: Approx_Distance (Km) | T7: Approx_Journey Time (Hrs) | U7: Trip_Frequency | V7: GOODS VEHICLES ONLY | Y7: Would You Use Xpressways? | Z7: Pay How Much? (UGX) | AA7: Origin_Zone | AB7: Dest_Zone
F8: Village or Town | G8: District | H8: Country | L8: Village or Town | M8: District | N8: Country | V8: Goods_Type | W8: Goods_Quantity (Ton) | X8: Goods_Value (UGXm)
B9: 0.48611111 | C9: UAR 466V | D9: 8 | E9: 2 | F9: MBARARA TOWN | G9: MBARARA | H9: UG | I9: 7 | J9: 4 | K9: =VLOOKUP(J9,Key!$E$2:$F$9,2,FALSE) -> Commercial | L9: WAKIRURI | M9: ISINGIRO | N9: UG | O9: 10 | P9: 2 | Q9: =VLOOKUP(P9,Key!$E$2:$F$9,2,FALSE) -> Work | R9: =K9&"-"&Q9 -> Commercial-Work | U9: 1 | Y9: Y
B10: 0.5 | C10: UEJ 256N | D10: 11 | E10: 2 | F10: KASENYI | G10: ISINGIRO | H10: UG | I10: 8 | J10: 2 | K10: =VLOOKUP(J10,Key!$E$2:$F$9,2,FALSE) -> Work | L10: MUKIWOGA | M10: ISINGIRO | N10: UG | O10: 8 | P10: 4 | Q10: =VLOOKUP(P10,Key!$E$2:$F$9,2,FALSE) -> Commercial | R10: =K10&"-"&Q10 -> Work-Commercial | S10: 2 | T10: 0.2 | U10: 1 | Y10: Y
B11: 0.50347222 | C11: UBD 241T | D11: 8 | E11: 1 | F11: KASENYI | G11: ISINGIRO | H11: UG | I11: 10 | J11: 2 | K11: =VLOOKUP(J11,Key!$E$2:$F$9,2,FALSE) -> Work | L11: KABALE | M11: ISINGIRO | N11: UG | O11: 15 | P11: 4 | Q11: =VLOOKUP(P11,Key!$E$2:$F$9,2,FALSE) -> Commercial | R11: =K11&"-"&Q11 -> Work-Commercial | S11: 1 | T11: 0 | U11: 1 | V11: 11 | Y11: Y
B12: 0.50694444 | C12: UAU 338H | D12: 1 | E12: 1 | F12: MBARARA TOWN | G12: MBARARA | H12: UG | I12: 1 | J12: 1 | K12: =VLOOKUP(J12,Key!$E$2:$F$9,2,FALSE) -> Home | L12: ISINGIRO TOWN | M12: ISINGIRO | N12: UG | O12: 1 | P12: 1 | Q12: =VLOOKUP(P12,Key!$E$2:$F$9,2,FALSE) -> Home | R12: =K12&"-"&Q12 -> Home-Home | S12: 31 | T12: 2 | U12: 2 | Y12: Y
B13: 0.51041667 | C13: UBE 962L | D13: 2 | E13: 2 | F13: MBARARA TOWN | G13: MBARARA | H13: UG | I13: 4 | J13: 3 | K13: =VLOOKUP(J13,Key!$E$2:$F$9,2,FALSE) -> Study | L13: KIRUMBA | M13: ISINGIRO | N13: UG | O13: 1 | P13: 1 | Q13: =VLOOKUP(P13,Key!$E$2:$F$9,2,FALSE) -> Home | R13: =K13&"-"&Q13 -> Study-Home | S13: 15 | T13: 0.3 | U13: 1 | Y13: Y
B14: 0.51388889 | C14: UAP 691R | D14: 1 | E14: 2 | F14: MBARARA TOWN | G14: MBARARA | H14: UG | I14: 1 | J14: 1 | K14: =VLOOKUP(J14,Key!$E$2:$F$9,2,FALSE) -> Home | L14: KIKAGATI | M14: ISINGIRO | N14: UG | O14: 2 | P14: 2 | Q14: =VLOOKUP(P14,Key!$E$2:$F$9,2,FALSE) -> Work | R14: =K14&"-"&Q14 -> Home-Work | U14: 1 | Y14: Y
B15: 0.51944444 | C15: UAM 835Z | D15: 2 | E15: 1 | F15: MBARARA TOWN | G15: MBARARA | H15: UG | I15: 1 | J15: 1 | K15: =VLOOKUP(J15,Key!$E$2:$F$9,2,FALSE) -> Home | L15: ISINGIRO TOWN | M15: ISINGIRO | N15: UG | O15: 1 | P15: 1 | Q15: =VLOOKUP(P15,Key!$E$2:$F$9,2,FALSE) -> Home | R15: =K15&"-"&Q15 -> Home-Home | S15: 40 | T15: 0.5 | U15: 1 | Y15: Y
B16: 0.52430556 | C16: UEQ 325M | D16: 11 | E16: 1 | F16: KASENYI | G16: ISINGIRO | H16: UG | I16: 8 | J16: 2 | K16: =VLOOKUP(J16,Key!$E$2:$F$9,2,FALSE) -> Work | L16: KABEREBERE | M16: ISINGIRO | N16: UG | O16: 8 | P16: 2 | Q16: =VLOOKUP(P16,Key!$E$2:$F$9,2,FALSE) -> Work | R16: =K16&"-"&Q16 -> Work-Work | S16: 10 | T16: 0.5 | U16: 1 | Y16: Y
B17: 0.68055556 | C17: UDG 462S | D17: 11 | E17: 1 | F17: MBARARA TOWN | G17: MBARARA | H17: UG | I17: 8 | J17: 2 | K17: =VLOOKUP(J17,Key!$E$2:$F$9,2,FALSE) -> Work | L17: ISINGIRO TOWN | M17: ISINGIRO | N17: UG | O17: 8 | P17: 2 | Q17: =VLOOKUP(P17,Key!$E$2:$F$9,2,FALSE) -> Work | R17: =K17&"-"&Q17 -> Work-Work | S17: 40 | T17: 1 | U17: 1 | Y17: Y
B18: 0.54513889 | C18: UBE 052G | D18: 8 | E18: 2 | F18: IGANGA TOWN | G18: IGANGA | H18: UG | I18: 2 | J18: 2 | K18: =VLOOKUP(J18,Key!$E$2:$F$9,2,FALSE) -> Work | L18: ISINGIRO TOWN | M18: ISINGIRO | N18: UG | O18: 2 | P18: 2 | Q18: =VLOOKUP(P18,Key!$E$2:$F$9,2,FALSE) -> Work | R18: =K18&"-"&Q18 -> Work-Work | S18: 260 | T18: 0.4 | U18: 1 | V18: 11 | Y18: Y
B19: 0.51388889 | C19: UAN 475M | D19: 1 | E19: 1 | F19: MBARARA TOWN | G19: MBARARA | H19: UG | I19: 4 | J19: 3 | K19: =VLOOKUP(J19,Key!$E$2:$F$9,2,FALSE) -> Study | L19: ISINGIRO TOWN | M19: ISINGIRO | N19: UG | O19: 1 | P19: 1 | Q19: =VLOOKUP(P19,Key!$E$2:$F$9,2,FALSE) -> Home | R19: =K19&"-"&Q19 -> Study-Home | S19: 20 | T19: 2 | U19: 4 | Y19: Y
B20: 0.50763889 | C20: UPE 240E | D20: 1 | E20: 2 | F20: MBARARA TOWN | G20: MBARARA | H20: UG | I20: 2 | J20: 2 | K20: =VLOOKUP(J20,Key!$E$2:$F$9,2,FALSE) -> Work | L20: NYAMITANGA | M20: ISINGIRO | N20: UG | O20: 1 | P20: 1 | Q20: =VLOOKUP(P20,Key!$E$2:$F$9,2,FALSE) -> Home | R20: =K20&"-"&Q20 -> Work-Home | T20: 2 | U20: 1 | Y20: Y
B21: 0.52916667 | C21: UAV 143P | D21: 11 | E21: 2 | F21: MBARARA TOWN | G21: MBARARA | H21: UG | I21: 1 | J21: 1 | K21: =VLOOKUP(J21,Key!$E$2:$F$9,2,FALSE) -> Home | L21: KABEREBERE | M21: ISINGIRO | N21: UG | O21: 8 | P21: 2 | Q21: =VLOOKUP(P21,Key!$E$2:$F$9,2,FALSE) -> Work | R21: =K21&"-"&Q21 -> Home-Work | S21: 40 | T21: 2 | U21: 1 | Y21: Y
B22: 0.52638889 | C22: UET 325G | D22: 1 | E22: 2 | F22: MBARARA TOWN | G22: MBARARA | H22: UG | I22: 2 | J22: 2 | K22: Work | L22: ISINGIRO TOWN | M22: ISINGIRO | N22: UG | O22: 1 | P22: 1 | Q22: Home | R22: =K22&"-"&Q22 -> Work-Home | S22: 12 | T22: 2 | U22: 1 | Y22: Y
B23: 0.6875 | C23: UAR 049L | D23: 1 | E23: 1 | F23: KATETE | G23: MBARARA | H23: UG | I23: 3 | J23: 4 | K23: =VLOOKUP(J23,Key!$E$2:$F$9,2,FALSE) -> Commercial | L23: KABEREBERE | M23: ISINGIRO | N23: UG | O23: 1 | P23: 1 | Q23: =VLOOKUP(P23,Key!$E$2:$F$9,2,FALSE) -> Home | R23: =K23&"-"&Q23 -> Commercial-Home | S23: 3 | T23: 0.5 | U23: 2 | Y23: Y
B24: 0.69791667 | C24: UAX 096P | D24: 7 | E24: 3 | F24: MBARARA TOWN | G24: MBARARA | H24: UG | I24: 10 | J24: 4 | K24: =VLOOKUP(J24,Key!$E$2:$F$9,2,FALSE) -> Commercial | L24: KABEREBERE | M24: ISINGIRO | N24: UG | O24: 10 | P24: 4 | Q24: =VLOOKUP(P24,Key!$E$2:$F$9,2,FALSE) -> Commercial | R24: =K24&"-"&Q24 -> Commercial-Commercial | S24: 8 | T24: 0.3 | U24: 2 | V24: 4 | W24: 6 | Y24: Y
B25: 0.69930556 | C25: UEE 491 | D25: 3 | E25: 2 | F25: MBARARA TOWN | G25: MBARARA | H25: UG | I25: 1 | J25: 1 | K25: =VLOOKUP(J25,Key!$E$2:$F$9,2,FALSE) -> Home | L25: KABEREBERE | M25: ISINGIRO | N25: UG | O25: 2 | P25: 2 | Q25: =VLOOKUP(P25,Key!$E$2:$F$9,2,FALSE) -> Work | R25: =K25&"-"&Q25 -> Home-Work | S25: 4 | T25: 0.2 | U25: 1 | Y25: Y
B26: 0.70486111 | C26: UAX 589Q | D26: 1 | E26: 2 | F26: BUSHENYI TOWN | G26: BUSHENYI | H26: UG | I26: 4 | J26: 3 | K26: =VLOOKUP(J26,Key!$E$2:$F$9,2,FALSE) -> Study | L26: ISINGIRO TOWN | M26: ISINGIRO | N26: UG | O26: 4 | P26: 2 | Q26: =VLOOKUP(P26,Key!$E$2:$F$9,2,FALSE) -> Work | R26: =K26&"-"&Q26 -> Study-Work | S26: 80 | T26: 1 | U26: 1 | Y26: Y
B27: 0.71111111 | C27: LG 018,035 | D27: 3 | E27: 1 | F27: JINJA TOWN | G27: JINJA | H27: UG | I27: 2 | J27: 2 | K27: =VLOOKUP(J27,Key!$E$2:$F$9,2,FALSE) -> Work | L27: KABEREBERE | M27: ISINGIRO | N27: UG | O27: 1 | P27: 1 | Q27: =VLOOKUP(P27,Key!$E$2:$F$9,2,FALSE) -> Home | R27: =K27&"-"&Q27 -> Work-Home | S27: 350 | T27: 0.2 | U27: 1 | Y27: Y
B28: 0.67361111 | C28: UAV 933R | D28: 3 | E28: 1 | F28: MBARARA TOWN | G28: MBARARA | H28: UG | I28: 2 | J28: 2 | K28: =VLOOKUP(J28,Key!$E$2:$F$9,2,FALSE) -> Work | L28: KIKAGATI | M28: ISINGIRO | N28: UG | O28: 1 | P28: 1 | Q28: =VLOOKUP(P28,Key!$E$2:$F$9,2,FALSE) -> Home | R28: =K28&"-"&Q28 -> Work-Home | U28: 1 | Y28: Y
B29: 0.71875 | C29: T612 DFH | D29: 1 | E29: 4 | F29: MBARARA TOWN | G29: MBARARA | H29: UG | I29: 2 | J29: 2 | K29: =VLOOKUP(J29,Key!$E$2:$F$9,2,FALSE) -> Work | L29: KIGAGATI | M29: ISINGIRO | N29: UG | O29: 1 | P29: 1 | Q29: =VLOOKUP(P29,Key!$E$2:$F$9,2,FALSE) -> Home | R29: =K29&"-"&Q29 -> Work-Home | S29: 58 | T29: 1 | U29: 1 | Y29: Y
B30: 0.73125 | C30: UAP 245X | D30: 7 | E30: 2 | F30: MBARARA TOWN | G30: MBARARA | H30: UG | I30: 10 | J30: 2 | K30: =VLOOKUP(J30,Key!$E$2:$F$9,2,FALSE) -> Work | L30: ISINGIRO TOWN | M30: ISINGIRO | N30: UG | O30: 1 | P30: 1 | Q30: =VLOOKUP(P30,Key!$E$2:$F$9,2,FALSE) -> Home | R30: =K30&"-"&Q30 -> Work-Home | S30: 17 | T30: 0.2 | U30: 1 | V30: 11 | Y30: Y
B31: 0.74583333 | C31: UBA 700H | D31: 1 | E31: 1 | F31: MBARARA TOWN | G31: MBARARA | H31: UG | I31: 2 | J31: 2 | K31: =VLOOKUP(J31,Key!$E$2:$F$9,2,FALSE) -> Work | L31: KABEREBERE | M31: ISINGIRO | N31: UG | O31: 1 | P31: 1 | Q31: =VLOOKUP(P31,Key!$E$2:$F$9,2,FALSE) -> Home | R31: =K31&"-"&Q31 -> Work-Home | S31: 7 | T31: 0.2 | U31: 1 | Y31: Y
B32: 0.75 | C32: UAS 056W | D32: 1 | E32: 3 | F32: KASENYI | G32: ISINGIRO | H32: UG | I32: 1 | J32: 1 | K32: =VLOOKUP(J32,Key!$E$2:$F$9,2,FALSE) -> Home | L32: MASHA | M32: ISINGIRO | N32: UG | O32: 9 | P32: 4 | Q32: =VLOOKUP(P32,Key!$E$2:$F$9,2,FALSE) -> Commercial | R32: =K32&"-"&Q32 -> Home-Commercial | S32: 2 | T32: 0 | U32: 1 | Y32: Y
B33: 0.76527778 | C33: UBB 249C | D33: 2 | E33: 1 | F33: MBARARA TOWN | G33: MBARARA | H33: UG | I33: 2 | J33: 2 | K33: =VLOOKUP(J33,Key!$E$2:$F$9,2,FALSE) -> Work | L33: NTUNGU | M33: ISINGIRO | N33: UG | O33: 1 | P33: 1 | Q33: =VLOOKUP(P33,Key!$E$2:$F$9,2,FALSE) -> Home | R33: =K33&"-"&Q33 -> Work-Home | S33: 25 | T33: 0 | U33: 1 | Y33: Y
B34: 0.76736111 | C34: UAZ 934U | D34: 1 | E34: 1 | F34: MBARARA TOWN | G34: MBARARA | H34: UG | I34: 2 | J34: 2 | K34: =VLOOKUP(J34,Key!$E$2:$F$9,2,FALSE) -> Work | L34: KABALE | M34: ISINGIRO | N34: UG | O34: 1 | P34: 1 | Q34: =VLOOKUP(P34,Key!$E$2:$F$9,2,FALSE) -> Home | R34: =K34&"-"&Q34 -> Work-Home | S34: 6 | T34: 0.2 | U34: 2 | Y34: Y
B35: 0.78125 | C35: UBE 125F | D35: 1 | E35: 3 | F35: NYAMITANGA | G35: MBARARA | H35: UG | I35: 11 | J35: 6 | K35: =VLOOKUP(J35,Key!$E$2:$F$9,2,FALSE) -> Leisure/Social | L35: ISINGIRO TOWN | M35: ISINGIRO | N35: UG | O35: 1 | P35: 1 | Q35: =VLOOKUP(P35,Key!$E$2:$F$9,2,FALSE) -> Home | R35: =K35&"-"&Q35 -> Leisure/Social-Home | S35: 31 | T35: 1.5 | U35: 3 | Y35: Y
B36: 0.77152778 | C36: UBE 359F | D36: 2 | E36: 1 | F36: MBARARA TOWN | G36: MBARARA | H36: UG | I36: 2 | J36: 2 | K36: =VLOOKUP(J36,Key!$E$2:$F$9,2,FALSE) -> Work | L36: KIRUMBA | M36: ISINGIRO | N36: UG | O36: 1 | P36: 1 | Q36: =VLOOKUP(P36,Key!$E$2:$F$9,2,FALSE) -> Home | R36: =K36&"-"&Q36 -> Work-Home | S36: 15 | T36: 0.5 | U36: 1 | Y36: Y
B37: 0.76736111 | C37: UAT 156X | D37: 2 | E37: 4 | F37: MBARARA TOWN | G37: MBARARA | H37: UG | I37: 16 | J37: 6 | K37: =VLOOKUP(J37,Key!$E$2:$F$9,2,FALSE) -> Leisure/Social | L37: NAKIVALE | M37: ISINGIRO | N37: UG | O37: 1 | P37: 1 | Q37: =VLOOKUP(P37,Key!$E$2:$F$9,2,FALSE) -> Home | R37: =K37&"-"&Q37 -> Leisure/Social-Home | S37: 6 | T37: 0.1 | U37: 3 | Y37: Y
B38: 0.76388889 | C38: UAQ 562Q | D38: 3 | E38: 3 | F38: KASENYI | G38: ISINGIRO | H38: UG | I38: 9 | J38: 2 | K38: =VLOOKUP(J38,Key!$E$2:$F$9,2,FALSE) -> Work | L38: KABEREBERE | M38: ISINGIRO | N38: UG | O38: 1 | P38: 1 | Q38: =VLOOKUP(P38,Key!$E$2:$F$9,2,FALSE) -> Home | R38: =K38&"-"&Q38 -> Work-Home | U38: 3 | Y38: Y
B39: 0.75763889 | C39: UAE 227Y | D39: 7 | E39: 3 | F39: MBARARA TOWN | G39: MBARARA | H39: UG | I39: 11 | J39: 4 | K39: =VLOOKUP(J39,Key!$E$2:$F$9,2,FALSE) -> Commercial | L39: KIKAGATI | M39: ISINGIRO | N39: UG | O39: 11 | P39: 4 | Q39: =VLOOKUP(P39,Key!$E$2:$F$9,2,FALSE) -> Commercial | R39: =K39&"-"&Q39 -> Commercial-Commercial | T39: 1.5 | U39: 3 | V39: 4 | W39: 5 | Y39: Y
B40: 0.75 | C40: UAY 513E | D40: 8 | E40: 1 | F40: KASESE TOWN | G40: KASESE | H40: UG | I40: 3 | J40: 2 | K40: =VLOOKUP(J40,Key!$E$2:$F$9,2,FALSE) -> Work | L40: RWEZIRINGIRO | M40: ISINGIRO | N40: UG | O40: 11 | P40: 4 | Q40: =VLOOKUP(P40,Key!$E$2:$F$9,2,FALSE) -> Commercial | R40: =K40&"-"&Q40 -> Work-Commercial | S40: 100 | U40: 3 | V40: 11 | Y40: Y
B41: 0.75138889 | C41: UG 162E | D41: 3 | E41: 1 | F41: KABINGO | G41: MBARARA | H41: UG | I41: 2 | J41: 2 | K41: =VLOOKUP(J41,Key!$E$2:$F$9,2,FALSE) -> Work | L41: MIROTWELVE | M41: ISINGIRO | N41: UG | O41: 1 | P41: 1 | Q41: =VLOOKUP(P41,Key!$E$2:$F$9,2,FALSE) -> Home | R41: =K41&"-"&Q41 -> Work-Home | T41: 0.3 | U41: 1 | Y41: Y
B42: 0.71875 | C42: UAZ 936G | D42: 1 | E42: 4 | F42: MBARARA TOWN | G42: MBARARA | H42: UG | I42: 11 | J42: 6 | K42: =VLOOKUP(J42,Key!$E$2:$F$9,2,FALSE) -> Leisure/Social | L42: KABUYANDA | M42: ISINGIRO | N42: UG | O42: 1 | P42: 1 | Q42: =VLOOKUP(P42,Key!$E$2:$F$9,2,FALSE) -> Home | R42: =K42&"-"&Q42 -> Leisure/Social-Home | T42: 1.5 | U42: 3 | Y42: Y
B43: 0.71458333 | C43: UAG 067H | D43: 1 | E43: 1 | F43: MBARARA TOWN | G43: MBARARA | H43: UG | I43: 2 | J43: 2 | K43: =VLOOKUP(J43,Key!$E$2:$F$9,2,FALSE) -> Work | L43: KABEREBERE | M43: ISINGIRO | N43: UG | O43: 1 | P43: 1 | Q43: =VLOOKUP(P43,Key!$E$2:$F$9,2,FALSE) -> Home | R43: =K43&"-"&Q43 -> Work-Home | S43: 8 | T43: 0.2 | U43: 3 | Y43: Y
B44: 0.70833333 | C44: UBD 075Z | D44: 7 | E44: 1 | F44: KASENYI | G44: ISINGIRO | H44: UG | I44: 11 | J44: 2 | K44: =VLOOKUP(J44,Key!$E$2:$F$9,2,FALSE) -> Work | L44: KABEREBERE | M44: ISINGIRO | N44: UG | O44: 11 | P44: 4 | Q44: =VLOOKUP(P44,Key!$E$2:$F$9,2,FALSE) -> Commercial | R44: =K44&"-"&Q44 -> Work-Commercial | T44: 0.5 | U44: 1 | W44: 3 | Y44: Y
B45: 0.70694444 | C45: UAH 766N | D45: 1 | E45: 2 | F45: MBARARA TOWN | G45: MBARARA | H45: UG | I45: 2 | J45: 2 | K45: =VLOOKUP(J45,Key!$E$2:$F$9,2,FALSE) -> Work | L45: BULERE | M45: ISINGIRO | N45: UG | O45: 1 | P45: 1 | Q45: =VLOOKUP(P45,Key!$E$2:$F$9,2,FALSE) -> Home | R45: =K45&"-"&Q45 -> Work-Home | S45: 8 | T45: 0 | U45: 1 | Y45: Y
B46: 0.70138889 | C46: UBD 148T | D46: 7 | E46: 2 | F46: MBARARA TOWN | G46: MBARARA | H46: UG | I46: 10 | J46: 4 | K46: =VLOOKUP(J46,Key!$E$2:$F$9,2,FALSE) -> Commercial | L46: KABEREBERE | M46: ISINGIRO | N46: UG | O46: 1 | P46: 1 | Q46: =VLOOKUP(P46,Key!$E$2:$F$9,2,FALSE) -> Home | R46: =K46&"-"&Q46 -> Commercial-Home | S46: 14 | T46: 0.5 | U46: 1 | V46: 11 | Y46: Y
B47: 0.69444444 | C47: UAZ 338M | D47: 1 | E47: 4 | F47: MBARARA TOWN | G47: MBARARA | H47: UG | I47: 2 | J47: 2 | K47: =VLOOKUP(J47,Key!$E$2:$F$9,2,FALSE) -> Work | L47: KIBINGO | M47: ISINGIRO | N47: UG | O47: 1 | P47: 1 | Q47: =VLOOKUP(P47,Key!$E$2:$F$9,2,FALSE) -> Home | R47: =K47&"-"&Q47 -> Work-Home | S47: 20 | T47: 0.5 | U47: 3 | Y47: Y
B48: 0.69097222 | C48: 8719 AA 07 | D48: 1 | E48: 2 | F48: KASESE TOWN | G48: KASESE | H48: UG | I48: 2 | J48: 2 | K48: =VLOOKUP(J48,Key!$E$2:$F$9,2,FALSE) -> Work | L48: KIKAGATI | M48: ISINGIRO | N48: UG | O48: 1 | P48: 1 | Q48: =VLOOKUP(P48,Key!$E$2:$F$9,2,FALSE) -> Home | R48: =K48&"-"&Q48 -> Work-Home | U48: 6 | Y48: Y
B49: 0.69027778 | C49: UAP 814F | D49: 8 | E49: 2 | F49: MBARARA TOWN | G49: MBARARA | H49: UG | I49: 9 | J49: 2 | K49: =VLOOKUP(J49,Key!$E$2:$F$9,2,FALSE) -> Work | L49: NYAMISINDO | M49: ISINGIRO | N49: UG | O49: 9 | P49: 4 | Q49: =VLOOKUP(P49,Key!$E$2:$F$9,2,FALSE) -> Commercial | R49: =K49&"-"&Q49 -> Work-Commercial | S49: 20 | T49: 0.8 | U49: 1 | V49: 11 | Y49: Y
B50: 0.68611111 | C50: UAX 070S | D50: 1 | E50: 2 | F50: MBARARA TOWN | G50: MBARARA | H50: UG | I50: 1 | J50: 1 | K50: =VLOOKUP(J50,Key!$E$2:$F$9,2,FALSE) -> Home | L50: KIKAGATI | M50: ISINGIRO | N50: UG | O50: 1 | P50: 1 | Q50: =VLOOKUP(P50,Key!$E$2:$F$9,2,FALSE) -> Home | R50: =K50&"-"&Q50 -> Home-Home | S50: 78 | U50: 1 | Y50: Y
B51: 0.52291667 | C51: UET 202Q | D51: 11 | E51: 1 | F51: MBARARA TOWN | G51: MBARARA | H51: UG | I51: 8 | J51: 4 | K51: =VLOOKUP(J51,Key!$E$2:$F$9,2,FALSE) -> Commercial | L51: MUKIWOGA | M51: ISINGIRO | N51: UG | O51: 1 | P51: 1 | Q51: =VLOOKUP(P51,Key!$E$2:$F$9,2,FALSE) -> Home | R51: =K51&"-"&Q51 -> Commercial-Home | S51: 5 | U51: 3 | Y51: Y
B52: 0.51944444 | C52: UAP 499D | D52: 1 | E52: 1 | F52: MBARARA TOWN | G52: MBARARA | H52: UG | I52: 1 | J52: 1 | K52: =VLOOKUP(J52,Key!$E$2:$F$9,2,FALSE) -> Home | L52: ISINGIRO TOWN | M52: ISINGIRO | N52: UG | O52: 1 | P52: 1 | Q52: =VLOOKUP(P52,Key!$E$2:$F$9,2,FALSE) -> Home | R52: =K52&"-"&Q52 -> Home-Home | S52: 16 | T52: 1 | U52: 3 | Y52: Y
B53: 0.51736111 | C53: UAY 261G | D53: 1 | E53: 1 | F53: MBARARA TOWN | G53: MBARARA | H53: UG | I53: 16 | J53: 2 | K53: =VLOOKUP(J53,Key!$E$2:$F$9,2,FALSE) -> Work | L53: KIRUMBA | M53: ISINGIRO | N53: UG | O53: 16 | P53: 2 | Q53: =VLOOKUP(P53,Key!$E$2:$F$9,2,FALSE) -> Work | R53: =K53&"-"&Q53 -> Work-Work | S53: 15 | T53: 0.3 | U53: 3 | Y53: Y
B54: 0.51388889 | C54: UEP M109R | D54: 11 | E54: 1 | F54: MBARARA TOWN | G54: MBARARA | H54: UG | I54: 8 | J54: 2 | K54: =VLOOKUP(J54,Key!$E$2:$F$9,2,FALSE) -> Work | L54: NYARUBUNGO | M54: ISINGIRO | N54: UG | O54: 1 | P54: 1 | Q54: =VLOOKUP(P54,Key!$E$2:$F$9,2,FALSE) -> Home | R54: =K54&"-"&Q54 -> Work-Home | T54: 0.5 | U54: 1 | Y54: Y
B55: 0.51111111 | C55: UAZ 110H | D55: 1 | E55: 1 | F55: NYAMITANGA | G55: MBARARA | H55: UG | I55: 1 | J55: 1 | K55: =VLOOKUP(J55,Key!$E$2:$F$9,2,FALSE) -> Home | L55: WAKIRURI | M55: ISINGIRO | N55: UG | O55: 4 | P55: 3 | Q55: =VLOOKUP(P55,Key!$E$2:$F$9,2,FALSE) -> Study | R55: =K55&"-"&Q55 -> Home-Study | S55: 2 | T55: 0.2 | U55: 1 | Y55: Y
B56: 0.50833333 | C56: UAZ 840H | D56: 3 | E56: 2 | F56: KASENYI | G56: ISINGIRO | H56: UG | I56: 1 | J56: 1 | K56: =VLOOKUP(J56,Key!$E$2:$F$9,2,FALSE) -> Home | L56: KABINGO | M56: ISINGIRO | N56: UG | O56: 11 | P56: 4 | Q56: =VLOOKUP(P56,Key!$E$2:$F$9,2,FALSE) -> Commercial | R56: =K56&"-"&Q56 -> Home-Commercial | S56: 40 | T56: 0.8 | U56: 4 | V56: 10 | W56: 0.5 | Y56: Y
B57: 1.6979167 | C57: UBB 283D | D57: 7 | E57: 2 | F57: MASAKA TOWN | G57: MASAKA | H57: UG | I57: 1 | J57: 1 | K57: =VLOOKUP(J57,Key!$E$2:$F$9,2,FALSE) -> Home | L57: KIKAGATI | M57: ISINGIRO | N57: UG | O57: 11 | P57: 4 | Q57: =VLOOKUP(P57,Key!$E$2:$F$9,2,FALSE) -> Commercial | R57: =K57&"-"&Q57 -> Home-Commercial | S57: 100 | T57: 5 | U57: 3 | V57: 10 | W57: 0.5 | Y57: Y
B58: 0.44166667 | C58: UAW 979J | D58: 1 | E58: 1 | F58: MAKENKE | G58: MBARARA | H58: UG | I58: 4 | J58: 3 | K58: =VLOOKUP(J58,Key!$E$2:$F$9,2,FALSE) -> Study | L58: RAKAYI | M58: KYOTERA | N58: UG | O58: 1 | P58: 1 | Q58: =VLOOKUP(P58,Key!$E$2:$F$9,2,FALSE) -> Home | R58: =K58&"-"&Q58 -> Study-Home | S58: 90 | T58: 3 | U58: 3 | Y58: Y
B59: 0.4375 | C59: UAP 080M | D59: 1 | E59: 3 | F59: MBARARA TOWN | G59: MBARARA | H59: UG | I59: 16 | J59: 8 | K59: =VLOOKUP(J59,Key!$E$2:$F$9,2,FALSE) -> Others | L59: NYARUBUNGO | M59: ISINGIRO | N59: UG | O59: 1 | P59: 1 | Q59: =VLOOKUP(P59,Key!$E$2:$F$9,2,FALSE) -> Home | R59: =K59&"-"&Q59 -> Others-Home | S59: 15 | T59: 0.3 | U59: 1 | Y59: Y
B60: 10;28 | C60: UEH 508E | D60: 11 | E60: 1 | F60: MBARARA TOWN | G60: MBARARA | H60: UG | I60: 8 | J60: 2 | K60: =VLOOKUP(J60,Key!$E$2:$F$9,2,FALSE) -> Work | L60: MUKIWOGA | M60: ISINGIRO | N60: UG | O60: 8 | P60: 2 | Q60: =VLOOKUP(P60,Key!$E$2:$F$9,2,FALSE) -> Work | R60: =K60&"-"&Q60 -> Work-Work | T60: 0.3 | U60: 2 | Y60: Y
B61: 0.43055556 | C61: UBD 799A | D61: 1 | E61: 1 | F61: NYAMITANGA | G61: MBARARA | H61: UG | I61: 1 | J61: 1 | K61: =VLOOKUP(J61,Key!$E$2:$F$9,2,FALSE) -> Home | L61: KABINGO | M61: ISINGIRO | N61: UG | O61: 16 | P61: 6 | Q61: =VLOOKUP(P61,Key!$E$2:$F$9,2,FALSE) -> Leisure/Social | R61: =K61&"-"&Q61 -> Home-Leisure/Social | S61: 21 | U61: 6 | Y61: Y
B62: 0.425 | C62: UBD 144Q | D62: 1 | E62: 3 | F62: NYAMITANGA | G62: MBARARA | H62: UG | I62: 1 | J62: 1 | K62: =VLOOKUP(J62,Key!$E$2:$F$9,2,FALSE) -> Home | L62: LWAKIRURI | M62: ISINGIRO | N62: UG | O62: 1 | P62: 1 | Q62: =VLOOKUP(P62,Key!$E$2:$F$9,2,FALSE) -> Home | R62: =K62&"-"&Q62 -> Home-Home | T62: 0.5 | U62: 3 | Y62: Y
B63: 0.41666667 | C63: UBE 446C | D63: 7 | E63: 2 | F63: MBARARA TOWN | G63: MBARARA | H63: UG | I63: 15 | J63: 4 | K63: =VLOOKUP(J63,Key!$E$2:$F$9,2,FALSE) -> Commercial | L63: KABALE | M63: ISINGIRO | N63: UG | O63: 10 | P63: 2 | Q63: =VLOOKUP(P63,Key!$E$2:$F$9,2,FALSE) -> Work | R63: =K63&"-"&Q63 -> Commercial-Work | S63: 5 | T63: 0.2 | U63: 1 | V63: 4 | W63: 1 | X63: 150000 | Y63: Y
B64: 0.39375 | C64: UAM 161D | D64: 1 | E64: 1 | F64: MBARARA TOWN | G64: MBARARA | H64: UG | I64: 1 | J64: 1 | K64: =VLOOKUP(J64,Key!$E$2:$F$9,2,FALSE) -> Home | L64: KIKAGATI | M64: ISINGIRO | N64: UG | O64: 11 | P64: 4 | Q64: =VLOOKUP(P64,Key!$E$2:$F$9,2,FALSE) -> Commercial | R64: =K64&"-"&Q64 -> Home-Commercial | S64: 70 | T64: 1 | U64: 4 | Y64: Y
B65: 0.38819444 | C65: UAM 478M | D65: 1 | E65: 1 | F65: KATETE | G65: MBARARA | H65: UG | I65: 1 | J65: 1 | K65: =VLOOKUP(J65,Key!$E$2:$F$9,2,FALSE) -> Home | L65: KABEREBERE | M65: ISINGIRO | N65: UG | O65: 1 | P65: 1 | Q65: =VLOOKUP(P65,Key!$E$2:$F$9,2,FALSE) -> Home | R65: =K65&"-"&Q65 -> Home-Home | S65: 10 | T65: 0.1 | U65: 1 | Y65: Y
B66: 0.38194444 | C66: UAW 090M | D66: 7 | E66: 2 | F66: LUTI | G66: MBARARA | H66: UG | I66: 11 | J66: 3 | K66: =VLOOKUP(J66,Key!$E$2:$F$9,2,FALSE) -> Study | L66: KISHURO | M66: ISINGIRO | N66: UG | O66: 9 | P66: 4 | Q66: =VLOOKUP(P66,Key!$E$2:$F$9,2,FALSE) -> Commercial | R66: =K66&"-"&Q66 -> Study-Commercial | S66: 25 | T66: 1 | U66: 2 | V66: 11 | Y66: Y
B67: 0.38402778 | C67: UAL 342Q | D67: 2 | E67: 1 | F67: MBARARA TOWN | G67: MBARARA | H67: UG | I67: 1 | J67: 1 | K67: =VLOOKUP(J67,Key!$E$2:$F$9,2,FALSE) -> Home | L67: KABEREBERE | M67: ISINGIRO | N67: UG | O67: 16 | P67: 8 | Q67: =VLOOKUP(P67,Key!$E$2:$F$9,2,FALSE) -> Others | R67: =K67&"-"&Q67 -> Home-Others | S67: 12 | T67: 0.3 | U67: 6 | Y67: Y
B68: 0.37847222 | C68: UAP 993L | D68: 1 | E68: 2 | F68: KAKIKA | G68: MBARARA | H68: UG | I68: 1 | J68: 1 | K68: =VLOOKUP(J68,Key!$E$2:$F$9,2,FALSE) -> Home | L68: RWAKIRURI | M68: MBARARA | N68: UG | O68: 1 | P68: 1 | Q68: =VLOOKUP(P68,Key!$E$2:$F$9,2,FALSE) -> Home | R68: =K68&"-"&Q68 -> Home-Home | S68: 10 | T68: 0.3 | U68: 1 | Y68: Y
B69: 0.375 | C69: UAF 158V | D69: 1 | E69: 5 | F69: MBARARA TOWN | G69: MBARARA | H69: UG | I69: 1 | J69: 1 | K69: =VLOOKUP(J69,Key!$E$2:$F$9,2,FALSE) -> Home | L69: KWABIRI | M69: MBARARA | N69: UG | O69: 2 | P69: 2 | Q69: =VLOOKUP(P69,Key!$E$2:$F$9,2,FALSE) -> Work | R69: =K69&"-"&Q69 -> Home-Work | S69: 35 | T69: 0.8 | U69: 1 | Y69: Y
B70: 0.37152778 | C70: UAH 004K | D70: 1 | E70: 3 | F70: MBARARA TOWN | G70: MBARARA | H70: UG | I70: 1 | J70: 1 | K70: =VLOOKUP(J70,Key!$E$2:$F$9,2,FALSE) -> Home | L70: KABEREBERE | M70: ISINGIRO | N70: UG | O70: 16 | P70: 6 | Q70: =VLOOKUP(P70,Key!$E$2:$F$9,2,FALSE) -> Leisure/Social | R70: =K70&"-"&Q70 -> Home-Leisure/Social | S70: 10 | T70: 0.2 | U70: 1 | Y70: Y
B71: 0.36944444 | C71: UED 209R | D71: 11 | E71: 1 | F71: KATETE | G71: MBARARA | H71: UG | I71: 1 | J71: 1 | K71: =VLOOKUP(J71,Key!$E$2:$F$9,2,FALSE) -> Home | L71: MUKIWOGA | M71: MBARARA | N71: UG | O71: 11 | P71: 4 | Q71: =VLOOKUP(P71,Key!$E$2:$F$9,2,FALSE) -> Commercial | R71: =K71&"-"&Q71 -> Home-Commercial | S71: 3 | T71: 0.2 | U71: 1 | Y71: Y
B72: 0.36388889 | C72: UAL 342A | D72: 2 | E72: 1 | F72: MBARARA TOWN | G72: MBARARA | H72: UG | I72: 1 | J72: 1 | K72: =VLOOKUP(J72,Key!$E$2:$F$9,2,FALSE) -> Home | L72: KABEREBERE | M72: ISINGIRO | N72: UG | O72: 4 | P72: 3 | Q72: =VLOOKUP(P72,Key!$E$2:$F$9,2,FALSE) -> Study | R72: =K72&"-"&Q72 -> Home-Study | S72: 11.26 | T72: 0.8 | U72: 5 | Y72: Y
B73: 0.36041667 | C73: UAP 055Y | D73: 2 | E73: 4 | F73: MBARARA TOWN | G73: MBARARA | H73: UG | I73: 1 | J73: 1 | K73: =VLOOKUP(J73,Key!$E$2:$F$9,2,FALSE) -> Home | L73: KABEREBERE | M73: ISINGIRO | N73: UG | O73: 2 | P73: 2 | Q73: =VLOOKUP(P73,Key!$E$2:$F$9,2,FALSE) -> Work | R73: =K73&"-"&Q73 -> Home-Work | S73: 10 | T73: 0.3 | U73: 6 | Y73: Y
B74: 0.35625 | C74: UAS 211N | D74: 1 | E74: 1 | F74: MBARARA TOWN | G74: MBARARA | H74: UG | I74: 1 | J74: 1 | K74: =VLOOKUP(J74,Key!$E$2:$F$9,2,FALSE) -> Home | L74: BUKANGA | M74: ISINGIRO | N74: UG | O74: 9 | P74: 4 | Q74: =VLOOKUP(P74,Key!$E$2:$F$9,2,FALSE) -> Commercial | R74: =K74&"-"&Q74 -> Home-Commercial | S74: 40 | T74: 1.5 | U74: 1 | Y74: Y
B75: 0.35138889 | C75: UAT 889P | D75: 1 | E75: 2 | F75: KASENYI | G75: ISINGIRO | H75: UG | I75: 1 | J75: 1 | K75: =VLOOKUP(J75,Key!$E$2:$F$9,2,FALSE) -> Home | L75: KASENYI | M75: ISINGIRO | N75: UG | O75: 4 | P75: 3 | Q75: =VLOOKUP(P75,Key!$E$2:$F$9,2,FALSE) -> Study | R75: =K75&"-"&Q75 -> Home-Study | S75: 1.5 | T75: 0.1 | U75: 1 | Y75: Y
B76: 0.34722222 | C76: UEP 769Z | D76: 11 | E76: 1 | F76: KASENYI | G76: ISINGIRO | H76: UG | I76: 8 | J76: 1 | K76: =VLOOKUP(J76,Key!$E$2:$F$9,2,FALSE) -> Home | L76: KABEREBERE | M76: ISINGIRO | N76: UG | O76: 8 | P76: 3 | Q76: =VLOOKUP(P76,Key!$E$2:$F$9,2,FALSE) -> Study | R76: =K76&"-"&Q76 -> Home-Study | S76: 4 | T76: 0.2 | U76: 2 | Y76: Y

Sheet 28.10 MBARARA-ISINGIRO
B1: Consultancy services for Preparation of Expressway Development Master Plan (EDMP) for Uganda
B2: Roadside OD Interview Survey
B4: Date: | C4: 28.10.2019 | E4: Road Name: | F4: MBARARA-NTUNGAMO ROAD | I4: Direction From: | L4: MBARARA | N4: Interviewers: | O4: MIREMBE RUTH, NIWAMANYA SAVIOR | V4: Supervisor: | W4: MIREMBE RUTH | Y4: Coded By: | Z4: AJOK EMILY | AA4: Chkd By:
I5: Direction To: | L5: ISINGIRO
B7: Time | C7: Veh_Reg_No. | D7: Veh_Type | E7: No. Occupants | F7: Origin_Address | I7: Origin_Establish | J7: Origin_Purpose | K7: Origin-Purpose Desc | L7: Destination_Address | O7: Destination_Establish | P7: Destination_Purpose | Q7: Destination_Purpose Desc | R7: Journey_Purpose | S7: Approx_Distance (Km) | T7: Approx_Journey Time (Hrs) | U7: Trip_Frequency | V7: GOODS VEHICLES ONLY | Y7: Would You Use Xpressways? | Z7: Pay How Much? (UGX) | AA7: Origin_Zone | AB7: Dest_Zone
F8: Village or Town | G8: District | H8: Country | L8: Village or Town | M8: District | N8: Country | V8: Goods_Type | W8: Goods_Quantity (Ton) | X8: Goods_Value (UGXm)
B9: 0.34722222 | C9: UAS 796Z | D9: 3 | E9: 3 | F9: MBARARA TOWN | G9: MBARARA | H9: UGA | I9: 1 | J9: 1 | K9: =VLOOKUP(J9,Key!$E$2:$F$9,2,FALSE) -> Home | L9: NTANTAMUK | M9: RAKAYI | N9: UGA | O9: 11 | P9: 4 | Q9: =VLOOKUP(P9,Key!$E$2:$F$9,2,FALSE) -> Commercial | R9: =K9&"-"&Q9 -> Home-Commercial | S9: 120 | T9: 4 | U9: 4 | V9: 1 | Y9: Y
B10: 0.35416667 | C10: UAT 802S | D10: 8 | E10: 1 | F10: RWEBIKOONA | G10: MBARARA | H10: UGA | I10: 1 | J10: 1 | K10: =VLOOKUP(J10,Key!$E$2:$F$9,2,FALSE) -> Home | L10: KUUYA | M10: ISINGIRO | N10: UGA | O10: 4 | P10: 3 | Q10: =VLOOKUP(P10,Key!$E$2:$F$9,2,FALSE) -> Study | R10: =K10&"-"&Q10 -> Home-Study | S10: 6 | T10: 0 | U10: 1 | V10: 11 | Y10: Y
B11: 0.35972222 | C11: UAZ 935N | D11: 4 | E11: 7 | F11: MBARARA TOWN | G11: MBARARA | H11: UGA | I11: 6 | J11: 2 | K11: =VLOOKUP(J11,Key!$E$2:$F$9,2,FALSE) -> Work | L11: NAKIVALE | M11: ISINGIRO | N11: UGA | O11: 6 | P11: 2 | Q11: =VLOOKUP(P11,Key!$E$2:$F$9,2,FALSE) -> Work | R11: =K11&"-"&Q11 -> Work-Work | S11: 62 | T11: 1.5 | U11: 1 | Y11: Y
B12: 0.36388889 | C12: UAS 153K | D12: 1 | E12: 2 | F12: KASENYI | G12: ISINGIRO | H12: UGA | I12: 1 | J12: 1 | K12: =VLOOKUP(J12,Key!$E$2:$F$9,2,FALSE) -> Home | L12: LWAKIRURI | M12: ISINGIRO | N12: UGA | O12: 4 | P12: 3 | Q12: =VLOOKUP(P12,Key!$E$2:$F$9,2,FALSE) -> Study | R12: =K12&"-"&Q12 -> Home-Study | S12: 4 | T12: 0 | U12: 1 | Y12: Y
B13: 0.37013889 | C13: UAX 644K | D13: 1 | E13: 3 | F13: KASENYI | G13: ISINGIRO | H13: UGA | I13: 1 | J13: 1 | K13: =VLOOKUP(J13,Key!$E$2:$F$9,2,FALSE) -> Home | L13: RWEZILINGIRO | M13: ISINGIRO | N13: UGA | O13: 9 | P13: 2 | Q13: =VLOOKUP(P13,Key!$E$2:$F$9,2,FALSE) -> Work | R13: =K13&"-"&Q13 -> Home-Work | S13: 11 | U13: 1 | Y13: Y
B14: 0.37291667 | C14: UAB 046H | D14: 1 | E14: 1 | F14: MBARARA TOWN | G14: MBARARA | H14: UGA | I14: 1 | J14: 1 | K14: =VLOOKUP(J14,Key!$E$2:$F$9,2,FALSE) -> Home | L14: KABEREBERE | M14: ISINGIRO | N14: UGA | O14: 2 | P14: 3 | Q14: =VLOOKUP(P14,Key!$E$2:$F$9,2,FALSE) -> Study | R14: =K14&"-"&Q14 -> Home-Study | S14: 12 | T14: 0.3 | U14: 1 | Y14: Y
B15: 0.37638889 | C15: UAP 783G | D15: 1 | E15: 2 | F15: MBARARA TOWN | G15: MBARARA | H15: UGA | I15: 1 | J15: 1 | K15: =VLOOKUP(J15,Key!$E$2:$F$9,2,FALSE) -> Home | L15: ISINGIRO TOWN | M15: ISINGIRO | N15: UGA | O15: 2 | P15: 2 | Q15: =VLOOKUP(P15,Key!$E$2:$F$9,2,FALSE) -> Work | R15: =K15&"-"&Q15 -> Home-Work | S15: 32 | T15: 1 | U15: 2 | Y15: Y
B16: 0.38125 | C16: UAF 900S | D16: 1 | E16: 4 | F16: NYAMITANGA | G16: MBARARA | H16: UGA | I16: 1 | J16: 1 | K16: =VLOOKUP(J16,Key!$E$2:$F$9,2,FALSE) -> Home | L16: KABEREBERE | M16: ISINGIRO | N16: UGA | O16: 2 | P16: 2 | Q16: =VLOOKUP(P16,Key!$E$2:$F$9,2,FALSE) -> Work | R16: =K16&"-"&Q16 -> Home-Work | S16: 4 | T16: 0.1 | U16: 3 | Y16: Y
B17: 0.38333333 | C17: UAU 767J | D17: 8 | E17: 3 | F17: MULUTI | G17: MBARARA | H17: UGA | I17: 11 | J17: 4 | K17: =VLOOKUP(J17,Key!$E$2:$F$9,2,FALSE) -> Commercial | L17: KIJERA | M17: ISINGIRO | N17: UGA | O17: 9 | P17: 4 | Q17: =VLOOKUP(P17,Key!$E$2:$F$9,2,FALSE) -> Commercial | R17: =K17&"-"&Q17 -> Commercial-Commercial | S17: 15 | T17: 1 | U17: 3 | V17: 11 | Y17: Y
B18: 0.38888889 | C18: UBD 703R | D18: 7 | E18: 4 | F18: MBARARA TOWN | G18: MBARARA | H18: UGA | I18: 3 | J18: 2 | K18: =VLOOKUP(J18,Key!$E$2:$F$9,2,FALSE) -> Work | L18: TANZANIA TOWN | M18: TANZANIA | N18: UGA | O18: 3 | P18: 4 | Q18: =VLOOKUP(P18,Key!$E$2:$F$9,2,FALSE) -> Commercial | R18: =K18&"-"&Q18 -> Work-Commercial | S18: 336 | T18: 4 | U18: 2 | V18: 11 | Y18: Y
B19: 0.39861111 | C19: UAM 083W | D19: 1 | E19: 2 | F19: MBARARA TOWN | G19: MBARARA | H19: UGA | I19: 1 | J19: 1 | K19: =VLOOKUP(J19,Key!$E$2:$F$9,2,FALSE) -> Home | L19: ISINGIRO TOWN | M19: ISINGIRO | N19: UGA | O19: 9 | P19: 2 | Q19: =VLOOKUP(P19,Key!$E$2:$F$9,2,FALSE) -> Work | R19: =K19&"-"&Q19 -> Home-Work | T19: 2 | U19: 2 | Y19: Y
B20: 0.40486111 | C20: UBC 487B | D20: 7 | E20: 3 | F20: MBARARA TOWN | G20: MBARARA | H20: UGA | I20: 11 | J20: 2 | K20: =VLOOKUP(J20,Key!$E$2:$F$9,2,FALSE) -> Work | L20: KWABIRI | M20: ISINGIRO | N20: UGA | O20: 11 | P20: 4 | Q20: =VLOOKUP(P20,Key!$E$2:$F$9,2,FALSE) -> Commercial | R20: =K20&"-"&Q20 -> Work-Commercial | S20: 20 | T20: 1 | U20: 3 | V20: 10 | W20: 5 | Y20: Y
B21: 0.44444444 | C21: UAN 954L | D21: 4 | E21: 9 | F21: NYAKAYISHO | G21: MBARARA | H21: UGA | I21: 6 | J21: 2 | K21: =VLOOKUP(J21,Key!$E$2:$F$9,2,FALSE) -> Work | L21: KITYAZA | M21: ISINGIRO | N21: UGA | O21: 6 | P21: 2 | Q21: =VLOOKUP(P21,Key!$E$2:$F$9,2,FALSE) -> Work | R21: =K21&"-"&Q21 -> Work-Work | S21: 40 | T21: 2 | U21: 3 | Y21: Y
B22: 0.45138889 | C22: UEX 927M | D22: 11 | E22: 1 | F22: MBARARA TOWN | G22: MBARARA | H22: UGA | I22: 8 | J22: 2 | K22: =VLOOKUP(J22,Key!$E$2:$F$9,2,FALSE) -> Work | L22: KABEREBERE | M22: ISINGIRO | N22: UGA | O22: 9 | P22: 4 | Q22: =VLOOKUP(P22,Key!$E$2:$F$9,2,FALSE) -> Commercial | R22: =K22&"-"&Q22 -> Work-Commercial | S22: 8 | T22: 0.3 | U22: 2 | Y22: Y
B23: 0.45972222 | C23: UAQ 136M | D23: 4 | E23: 9 | F23: MBARARA TOWN | G23: MBARARA | H23: UGA | I23: 6 | J23: 2 | K23: =VLOOKUP(J23,Key!$E$2:$F$9,2,FALSE) -> Work | L23: ISINGIRO TOWN | M23: ISINGIRO | N23: UGA | O23: 6 | P23: 4 | Q23: =VLOOKUP(P23,Key!$E$2:$F$9,2,FALSE) -> Commercial | R23: =K23&"-"&Q23 -> Work-Commercial | S23: 36 | U23: 4 | Y23: Y
B24: 0.46875 | C24: UEB 435H | D24: 11 | E24: 1 | F24: KUNYA | G24: ISINGIRO | H24: UGA | I24: 6 | J24: 2 | K24: =VLOOKUP(J24,Key!$E$2:$F$9,2,FALSE) -> Work | L24: KABEREBERE | M24: ISINGIRO | N24: UGA | O24: 6 | P24: 2 | Q24: Work | R24: =K24&"-"&Q24 -> Work-Work | T24: 0 | U24: 3 | Y24: Y
B25: 0.475 | C25: UAK 962P | D25: 1 | E25: 1 | F25: MBARARA TOWN | G25: MBARARA | H25: UGA | I25: 2 | J25: 2 | K25: =VLOOKUP(J25,Key!$E$2:$F$9,2,FALSE) -> Work | L25: KABALE | M25: ISINGIRO | N25: UGA | O25: 1 | P25: 1 | Q25: =VLOOKUP(P25,Key!$E$2:$F$9,2,FALSE) -> Home | R25: =K25&"-"&Q25 -> Work-Home | S25: 8 | T25: 0.2 | U25: 2 | Y25: Y
B26: 0.48055556 | C26: UAY 195E | D26: 3 | E26: 4 | F26: MBARARA TOWN | G26: MBARARA | H26: UGA | I26: 7 | J26: 2 | K26: =VLOOKUP(J26,Key!$E$2:$F$9,2,FALSE) -> Work | L26: KABALE | M26: ISINGIRO | N26: UGA | O26: 10 | P26: 4 | Q26: =VLOOKUP(P26,Key!$E$2:$F$9,2,FALSE) -> Commercial | R26: =K26&"-"&Q26 -> Work-Commercial | S26: 6 | T26: 0.5 | U26: 4 | W26: 0.5 | X26: 600000 | Y26: Y
B27: 0.48472222 | C27: UAD 862F | D27: 1 | E27: 2 | F27: MBARARA TOWN | G27: MBARARA | H27: UGA | I27: 1 | J27: 1 | K27: =VLOOKUP(J27,Key!$E$2:$F$9,2,FALSE) -> Home | L27: KABEREBERE | M27: ISINGIRO | N27: UGA | O27: 16 | P27: 6 | Q27: =VLOOKUP(P27,Key!$E$2:$F$9,2,FALSE) -> Leisure/Social | R27: =K27&"-"&Q27 -> Home-Leisure/Social | S27: 8 | T27: 0.4 | U27: 4 | Y27: Y
B28: 0.48958333 | C28: UDP 047C | D28: 11 | E28: 1 | F28: KATETE | G28: MBARARA | H28: UGA | I28: 8 | J28: 2 | K28: =VLOOKUP(J28,Key!$E$2:$F$9,2,FALSE) -> Work | L28: KABALE | M28: ISINGIRO | N28: UGA | O28: 1 | P28: 1 | Q28: =VLOOKUP(P28,Key!$E$2:$F$9,2,FALSE) -> Home | R28: =K28&"-"&Q28 -> Work-Home | S28: 1.5 | T28: 0.1 | U28: 3 | Y28: Y
B29: 0.49305556 | C29: UAD 208W | D29: 1 | E29: 3 | F29: MBARARA TOWN | G29: MBARARA | H29: UGA | I29: 2 | J29: 2 | K29: =VLOOKUP(J29,Key!$E$2:$F$9,2,FALSE) -> Work | L29: KABEREBERE | M29: ISINGIRO | N29: UGA | O29: 9 | P29: 4 | Q29: =VLOOKUP(P29,Key!$E$2:$F$9,2,FALSE) -> Commercial | R29: =K29&"-"&Q29 -> Work-Commercial | S29: 16 | U29: 3 | Y29: Y
B30: 11;55 | C30: UAX 802B | D30: 2 | E30: 4 | F30: LWAMPALA TOWN | G30: LWAMPALA | H30: UGA | I30: 1 | J30: 1 | K30: =VLOOKUP(J30,Key!$E$2:$F$9,2,FALSE) -> Home | L30: MASHA | M30: ISINGIRO | N30: UGA | O30: 9 | P30: 4 | Q30: =VLOOKUP(P30,Key!$E$2:$F$9,2,FALSE) -> Commercial | R30: =K30&"-"&Q30 -> Home-Commercial | S30: 50 | T30: 0.8 | U30: 3 | Y30: Y
B31: 0.50833333 | C31: UAL 413C | D31: 2 | E31: 2 | F31: MBARARA TOWN | G31: MBARARA | H31: UGA | I31: 2 | J31: 2 | K31: Work | L31: KASENYI | M31: ISINGIRO | N31: UGA | O31: 4 | P31: 3 | Q31: =VLOOKUP(P31,Key!$E$2:$F$9,2,FALSE) -> Study | R31: =K31&"-"&Q31 -> Work-Study | S31: 4 | T31: 0.4 | U31: 2 | Y31: Y
B32: 0.51388889 | C32: UAR 047C | D32: 7 | E32: 2 | F32: MBARARA TOWN | G32: MBARARA | H32: UGA | I32: 1 | J32: 1 | K32: =VLOOKUP(J32,Key!$E$2:$F$9,2,FALSE) -> Home | L32: KABEREBERE | M32: ISINGIRO | N32: UGA | O32: 3 | P32: 4 | Q32: =VLOOKUP(P32,Key!$E$2:$F$9,2,FALSE) -> Commercial | R32: =K32&"-"&Q32 -> Home-Commercial | T32: 2 | U32: 3 | V32: 11 | Y32: Y
B33: 0.51666667 | C33: UAH 549A | D33: 1 | E33: 1 | F33: MBARARA TOWN | G33: MBARARA | H33: UGA | I33: 11 | J33: 6 | K33: =VLOOKUP(J33,Key!$E$2:$F$9,2,FALSE) -> Leisure/Social | L33: BUTENGA | M33: ISINGIRO | N33: UGA | O33: 1 | P33: 1 | Q33: =VLOOKUP(P33,Key!$E$2:$F$9,2,FALSE) -> Home | R33: =K33&"-"&Q33 -> Leisure/Social-Home | S33: 12 | T33: 0.3 | U33: 3 | Y33: Y
B34: 0.52777778 | C34: UAP 864B | D34: 7 | E34: 1 | F34: MBARARA TOWN | G34: MBARARA | H34: UGA | I34: 14 | J34: 2 | K34: =VLOOKUP(J34,Key!$E$2:$F$9,2,FALSE) -> Work | L34: KABEREBERE | M34: ISINGIRO | N34: UGA | O34: 10 | P34: 4 | Q34: =VLOOKUP(P34,Key!$E$2:$F$9,2,FALSE) -> Commercial | R34: =K34&"-"&Q34 -> Work-Commercial | S34: 4 | T34: 0.2 | U34: 2 | V34: 6 | Y34: Y
B35: 0.58333333 | C35: UAM 364J | D35: 11 | E35: 1 | F35: NYAMITANGA | G35: MBARARA | H35: UGA | I35: 8 | J35: 2 | K35: =VLOOKUP(J35,Key!$E$2:$F$9,2,FALSE) -> Work | L35: KABEREBERE | M35: ISINGIRO | N35: UGA | O35: 8 | P35: 2 | Q35: =VLOOKUP(P35,Key!$E$2:$F$9,2,FALSE) -> Work | R35: =K35&"-"&Q35 -> Work-Work | T35: 0.2 | U35: 2 | Y35: Y
B36: 0.59375 | C36: UAP 659W | D36: 1 | E36: 3 | F36: MBARARA TOWN | G36: MBARARA | H36: UGA | I36: 4 | J36: 3 | K36: =VLOOKUP(J36,Key!$E$2:$F$9,2,FALSE) -> Study | L36: KIKAGATI | M36: ISINGIRO | N36: UGA | O36: 1 | P36: 1 | Q36: =VLOOKUP(P36,Key!$E$2:$F$9,2,FALSE) -> Home | R36: =K36&"-"&Q36 -> Study-Home | S36: 16 | U36: 2 | Y36: Y
B37: 0.67361111 | C37: UEO 214O | D37: 11 | E37: 1 | F37: MBARARA TOWN | G37: MBARARA | H37: UGA | I37: 8 | J37: 2 | K37: =VLOOKUP(J37,Key!$E$2:$F$9,2,FALSE) -> Work | L37: KYEMPALA | M37: ISINGIRO | N37: UGA | O37: 1 | P37: 1 | Q37: =VLOOKUP(P37,Key!$E$2:$F$9,2,FALSE) -> Home | R37: =K37&"-"&Q37 -> Work-Home | S37: 17 | T37: 0.5 | U37: 3 | Y37: Y
B38: 0.68055556 | C38: UAX 056C | D38: 8 | E38: 3 | F38: MBARARA TOWN | G38: MBARARA | H38: UGA | I38: 10 | J38: 2 | K38: =VLOOKUP(J38,Key!$E$2:$F$9,2,FALSE) -> Work | L38: KABINGO | M38: ISINGIRO | N38: UGA | O38: 15 | P38: 4 | Q38: =VLOOKUP(P38,Key!$E$2:$F$9,2,FALSE) -> Commercial | R38: =K38&"-"&Q38 -> Work-Commercial | T38: 1 | U38: 2 | V38: 11 | Y38: Y
B39: 0.68472222 | C39: UAG 251M | D39: 4 | E39: 6 | F39: MBARARA TOWN | G39: MBARARA | H39: UGA | I39: 6 | J39: 2 | K39: =VLOOKUP(J39,Key!$E$2:$F$9,2,FALSE) -> Work | L39: KIKAGATI | M39: ISINGIRO | N39: UGA | O39: 6 | P39: 2 | Q39: =VLOOKUP(P39,Key!$E$2:$F$9,2,FALSE) -> Work | R39: =K39&"-"&Q39 -> Work-Work | S39: 76 | T39: 1.5 | U39: 3 | Y39: Y
B40: 0.6875 | C40: IAQ 397A | D40: 8 | E40: 3 | F40: MBARARA TOWN | G40: MBARARA | H40: UGA | I40: 11 | J40: 6 | K40: =VLOOKUP(J40,Key!$E$2:$F$9,2,FALSE) -> Leisure/Social | L40: KUMUKAGA | M40: ISINGIRO | N40: UGA | O40: 16 | P40: 8 | Q40: =VLOOKUP(P40,Key!$E$2:$F$9,2,FALSE) -> Others | R40: =K40&"-"&Q40 -> Leisure/Social-Others | S40: 12 | T40: 0.5 | U40: 4 | V40: 11 | Y40: Y
B41: 0.69097222 | C41: UAF 172A | D41: 1 | E41: 2 | F41: MBARARA TOWN | G41: MBARARA | H41: UGA | I41: 4 | J41: 3 | K41: =VLOOKUP(J41,Key!$E$2:$F$9,2,FALSE) -> Study | L41: LWAKIRURI | M41: ISINGIRO | N41: UGA | O41: 1 | P41: 1 | Q41: =VLOOKUP(P41,Key!$E$2:$F$9,2,FALSE) -> Home | R41: =K41&"-"&Q41 -> Study-Home | S41: 4 | T41: 0.2 | U41: 2 | Y41: Y
B42: 0.69652778 | C42: UAZ 281T | D42: 1 | E42: 4 | F42: MBARARA TOWN | G42: MBARARA | H42: UGA | I42: 2 | J42: 2 | K42: =VLOOKUP(J42,Key!$E$2:$F$9,2,FALSE) -> Work | L42: KABEREBERE | M42: ISINGIRO | N42: UGA | O42: 1 | P42: 1 | Q42: =VLOOKUP(P42,Key!$E$2:$F$9,2,FALSE) -> Home | R42: =K42&"-"&Q42 -> Work-Home | S42: 8 | T42: 0.3 | U42: 2 | Y42: Y
B43: 0.70972222 | C43: UAV 279N | D43: 3 | E43: 1 | F43: MBARARA TOWN | G43: MBARARA | H43: UGA | I43: 9 | J43: 2 | K43: =VLOOKUP(J43,Key!$E$2:$F$9,2,FALSE) -> Work | L43: KYAMUSHOKA | M43: ISINGIRO | N43: UGA | O43: 1 | P43: 1 | Q43: =VLOOKUP(P43,Key!$E$2:$F$9,2,FALSE) -> Home | R43: =K43&"-"&Q43 -> Work-Home | T43: 1 | U43: 2 | Y43: Y
B44: 0.71111111 | C44: UEE 743L | D44: 11 | E44: 1 | F44: MBARARA TOWN | G44: MBARARA | H44: UGA | I44: 8 | J44: 2 | K44: =VLOOKUP(J44,Key!$E$2:$F$9,2,FALSE) -> Work | L44: KABEREBERE | M44: ISINGIRO | N44: UGA | O44: 8 | P44: 2 | Q44: =VLOOKUP(P44,Key!$E$2:$F$9,2,FALSE) -> Work | R44: =K44&"-"&Q44 -> Work-Work | T44: 0.5 | U44: 3 | Y44: Y
B45: 0.71527778 | C45: UDY 793U | D45: 11 | E45: 1 | F45: KAKOBA | G45: MBARARA | H45: UGA | I45: 4 | J45: 3 | K45: =VLOOKUP(J45,Key!$E$2:$F$9,2,FALSE) -> Study | L45: KABEREBERE | M45: ISINGIRO | N45: UGA | O45: 1 | P45: 1 | Q45: =VLOOKUP(P45,Key!$E$2:$F$9,2,FALSE) -> Home | R45: =K45&"-"&Q45 -> Study-Home | S45: 12 | T45: 0.5 | U45: 2 | Y45: Y
B46: 0.71875 | C46: UER 018Y | D46: 11 | E46: 1 | F46: MBARARA TOWN | G46: MBARARA | H46: UGA | I46: 8 | J46: 2 | K46: =VLOOKUP(J46,Key!$E$2:$F$9,2,FALSE) -> Work | L46: KISURO | M46: ISINGIRO | N46: UGA | O46: 1 | P46: 1 | Q46: =VLOOKUP(P46,Key!$E$2:$F$9,2,FALSE) -> Home | R46: =K46&"-"&Q46 -> Work-Home | T46: 1 | U46: 4 | Y46: Y
B47: 0.72430556 | C47: UBB 728A | D47: 7 | E47: 2 | F47: MBARARA TOWN | G47: MBARARA | H47: UGA | I47: 14 | J47: 2 | K47: =VLOOKUP(J47,Key!$E$2:$F$9,2,FALSE) -> Work | L47: KABEREBERE | M47: ISINGIRO | N47: UGA | O47: 10 | P47: 4 | Q47: =VLOOKUP(P47,Key!$E$2:$F$9,2,FALSE) -> Commercial | R47: =K47&"-"&Q47 -> Work-Commercial | T47: 0.3 | U47: 2 | V47: 6 | W47: 1.5 | Y47: Y
B48: 0.73888889 | C48: UAN 544P | D48: 3 | E48: 2 | F48: MBARARA TOWN | G48: MBARARA | H48: UGA | I48: 14 | J48: 4 | K48: =VLOOKUP(J48,Key!$E$2:$F$9,2,FALSE) -> Commercial | L48: KABEREBERE | M48: ISINGIRO | N48: UGA | O48: 1 | P48: 1 | Q48: =VLOOKUP(P48,Key!$E$2:$F$9,2,FALSE) -> Home | R48: =K48&"-"&Q48 -> Commercial-Home | S48: 8 | T48: 0.5 | U48: 2 | Y48: Y
B49: 0.29305556 | C49: UBD 094L | D49: 2 | E49: 1 | F49: MBARARA TOWN | G49: MBARARA | H49: UGA | I49: 4 | J49: 3 | K49: =VLOOKUP(J49,Key!$E$2:$F$9,2,FALSE) -> Study | L49: KABEREBERE | M49: ISINGIRO | N49: UGA | O49: 4 | P49: 1 | Q49: =VLOOKUP(P49,Key!$E$2:$F$9,2,FALSE) -> Home | R49: =K49&"-"&Q49 -> Study-Home | S49: 9 | T49: 0.5 | U49: 1 | Y49: Y
B50: 0.29861111 | C50: UAS 514P | D50: 1 | E50: 2 | F50: MILO | G50: ISINGIRO | H50: UGA | I50: 4 | J50: 3 | K50: =VLOOKUP(J50,Key!$E$2:$F$9,2,FALSE) -> Study | L50: KABALE | M50: ISINGIRO | N50: UGA | O50: 1 | P50: 1 | Q50: =VLOOKUP(P50,Key!$E$2:$F$9,2,FALSE) -> Home | R50: =K50&"-"&Q50 -> Study-Home | S50: 4 | T50: 0.5 | U50: 1 | Y50: Y
B51: 0.35347222 | C51: UAW 264E | D51: 1 | E51: 2 | F51: NYAMITANGA | G51: MBARARA | H51: UGA | I51: 1 | J51: 1 | K51: =VLOOKUP(J51,Key!$E$2:$F$9,2,FALSE) -> Home | L51: KWOKIRURI | M51: ISINGIRO | N51: UGA | O51: 9 | P51: 2 | Q51: =VLOOKUP(P51,Key!$E$2:$F$9,2,FALSE) -> Work | R51: =K51&"-"&Q51 -> Home-Work | S51: 4 | T51: 0.8 | U51: 1 | Y51: Y
B52: 0.36319444 | C52: UAP 989E | D52: 1 | E52: 1 | F52: KAMPALA TOWN | G52: KAMPALA | H52: UGA | I52: 1 | J52: 1 | K52: =VLOOKUP(J52,Key!$E$2:$F$9,2,FALSE) -> Home | L52: ISINGIRO TOWN | M52: ISINGIRO | N52: UGA | O52: 2 | P52: 2 | Q52: =VLOOKUP(P52,Key!$E$2:$F$9,2,FALSE) -> Work | R52: =K52&"-"&Q52 -> Home-Work | S52: 300 | T52: 3 | U52: 1 | Y52: Y
B53: 0.36458333 | C53: UAZ 143Q | D53: 7 | E53: 1 | F53: MBARARA TOWN | G53: MBARARA | H53: UGA | I53: 1 | J53: 1 | K53: =VLOOKUP(J53,Key!$E$2:$F$9,2,FALSE) -> Home | L53: KABEREBERE | M53: ISINGIRO | N53: UGA | O53: 16 | P53: 8 | Q53: =VLOOKUP(P53,Key!$E$2:$F$9,2,FALSE) -> Others | R53: =K53&"-"&Q53 -> Home-Others | S53: 6 | T53: 0.3 | U53: 2 | Y53: Y
B54: 0.37083333 | C54: UBF 618V | D54: 7 | E54: 2 | F54: MBARARA TOWN | G54: MBARARA | H54: UGA | I54: 3 | J54: 2 | K54: =VLOOKUP(J54,Key!$E$2:$F$9,2,FALSE) -> Work | L54: KABEREBERE | M54: ISINGIRO | N54: UGA | O54: 9 | P54: 2 | Q54: =VLOOKUP(P54,Key!$E$2:$F$9,2,FALSE) -> Work | R54: =K54&"-"&Q54 -> Work-Work | S54: 15 | T54: 0.3 | U54: 1 | Y54: Y
B55: 0.37986111 | C55: UDA 914B | D55: 11 | E55: 1 | F55: KATETE | G55: MBARARA | H55: UGA | I55: 5 | J55: 7 | K55: =VLOOKUP(J55,Key!$E$2:$F$9,2,FALSE) -> Hospital | L55: KABEREBERE | M55: ISINGIRO | N55: UGA | O55: 1 | P55: 1 | Q55: =VLOOKUP(P55,Key!$E$2:$F$9,2,FALSE) -> Home | R55: =K55&"-"&Q55 -> Hospital-Home | S55: 3 | T55: 1 | U55: 1 | Y55: Y
B56: 0.38125 | C56: UAX 164K | D56: 1 | E56: 1 | F56: MBARARA TOWN | G56: MBARARA | H56: UGA | I56: 2 | J56: 2 | K56: =VLOOKUP(J56,Key!$E$2:$F$9,2,FALSE) -> Work | L56: KABINGO | M56: ISINGIRO | N56: UGA | O56: 1 | P56: 1 | Q56: =VLOOKUP(P56,Key!$E$2:$F$9,2,FALSE) -> Home | R56: =K56&"-"&Q56 -> Work-Home | S56: 3 | T56: 0.3 | U56: 1 | Y56: Y
B57: 0.38194444 | C57: UAZ 202T | D57: 1 | E57: 1 | F57: MBARARA TOWN | G57: MBARARA | H57: UGA | I57: 1 | J57: 1 | K57: =VLOOKUP(J57,Key!$E$2:$F$9,2,FALSE) -> Home | L57: KAMBINGO | M57: ISINGIRO | N57: UGA | O57: 4 | P57: 3 | Q57: =VLOOKUP(P57,Key!$E$2:$F$9,2,FALSE) -> Study | R57: =K57&"-"&Q57 -> Home-Study | S57: 20 | T57: 0.5 | U57: 2 | Y57: Y
B58: 0.39097222 | C58: UBB 783L | D58: 1 | E58: 3 | F58: MBARARA TOWN | G58: MBARARA | H58: UGA | I58: 1 | J58: 1 | K58: =VLOOKUP(J58,Key!$E$2:$F$9,2,FALSE) -> Home | L58: KABEREBERE | M58: ISINGIRO | N58: UGA | O58: 9 | P58: 2 | Q58: =VLOOKUP(P58,Key!$E$2:$F$9,2,FALSE) -> Work | R58: =K58&"-"&Q58 -> Home-Work | S58: 7 | T58: 0.2 | U58: 2 | Y58: Y
B59: 0.39513889 | C59: UAB 876G | D59: 8 | E59: 2 | F59: MBARARA TOWN | G59: MBARARA | H59: UGA | I59: 3 | J59: 2 | K59: =VLOOKUP(J59,Key!$E$2:$F$9,2,FALSE) -> Work | L59: KASHUBA | M59: ISINGIRO | N59: UGA | O59: 11 | P59: 4 | Q59: =VLOOKUP(P59,Key!$E$2:$F$9,2,FALSE) -> Commercial | R59: =K59&"-"&Q59 -> Work-Commercial | S59: 4 | T59: 17 | U59: 3 | V59: 10 | W59: 6 | X59: 80000 | Y59: Y
B60: 0.39930556 | C60: UAL 382F | D60: 7 | E60: 1 | F60: MBARARA TOWN | G60: MBARARA | H60: UGA | I60: 3 | J60: 2 | K60: =VLOOKUP(J60,Key!$E$2:$F$9,2,FALSE) -> Work | L60: OMUKIHONGO | M60: ISINGIRO | N60: UGA | O60: 3 | P60: 4 | Q60: =VLOOKUP(P60,Key!$E$2:$F$9,2,FALSE) -> Commercial | R60: =K60&"-"&Q60 -> Work-Commercial | S60: 4 | T60: 0.2 | U60: 1 | V60: 4 | W60: 0.5 | X60: 100000 | Y60: Y
B61: 0.40208333 | C61: UAY 488M | D61: 2 | E61: 2 | F61: KIBURI | G61: ISINGIRO | H61: UGA | I61: 4 | J61: 3 | K61: =VLOOKUP(J61,Key!$E$2:$F$9,2,FALSE) -> Study | L61: KIBURI | M61: ISINGIRO | N61: UGA | O61: 4 | P61: 3 | Q61: =VLOOKUP(P61,Key!$E$2:$F$9,2,FALSE) -> Study | R61: =K61&"-"&Q61 -> Study-Study | S61: 4 | T61: 1 | U61: 4 | Y61: Y
B62: 0.41666667 | C62: UEE 657S | D62: 11 | E62: 1 | F62: MBARARA TOWN | G62: MBARARA | H62: UGA | I62: 8 | J62: 2 | K62: =VLOOKUP(J62,Key!$E$2:$F$9,2,FALSE) -> Work | L62: KWAKIRURI | M62: ISINGIRO | N62: UGA | O62: 8 | P62: 2 | Q62: =VLOOKUP(P62,Key!$E$2:$F$9,2,FALSE) -> Work | R62: =K62&"-"&Q62 -> Work-Work | S62: 2 | T62: 0.3 | U62: 2 | Y62: Y
B63: 0.44097222 | C63: UAY 294D | D63: 7 | E63: 3 | F63: MBARARA TOWN | G63: MBARARA | H63: UGA | I63: 7 | J63: 2 | K63: =VLOOKUP(J63,Key!$E$2:$F$9,2,FALSE) -> Work | L63: KABINGO | M63: ISINGIRO | N63: UGA | O63: 3 | P63: 2 | Q63: =VLOOKUP(P63,Key!$E$2:$F$9,2,FALSE) -> Work | R63: =K63&"-"&Q63 -> Work-Work | S63: 20 | T63: 1 | U63: 4 | Y63: Y
B64: 0.45069444 | C64: UAG 409V | D64: 1 | E64: 1 | F64: KATETE | G64: MBARARA | H64: UGA | I64: 1 | J64: 1 | K64: =VLOOKUP(J64,Key!$E$2:$F$9,2,FALSE) -> Home | L64: MASHA | M64: ISINGIRO | N64: UGA | O64: 9 | P64: 4 | Q64: =VLOOKUP(P64,Key!$E$2:$F$9,2,FALSE) -> Commercial | R64: =K64&"-"&Q64 -> Home-Commercial | S64: 16 | T64: 0.3 | U64: 3 | Y64: Y
B65: 0.45833333 | C65: UBF 910J | D65: 1 | E65: 3 | F65: MBARARA TOWN | G65: MBARARA | H65: UGA | I65: 2 | J65: 2 | K65: =VLOOKUP(J65,Key!$E$2:$F$9,2,FALSE) -> Work | L65: NAKIVALE | M65: ISINGIRO | N65: UGA | O65: 1 | P65: 1 | Q65: =VLOOKUP(P65,Key!$E$2:$F$9,2,FALSE) -> Home | R65: =K65&"-"&Q65 -> Work-Home | S65: 40 | T65: 2 | U65: 1 | Y65: Y
B66: 0.46388889 | C66: UAT 241H | D66: 7 | E66: 4 | F66: MBARARA TOWN | G66: MBARARA | H66: UGA | I66: 10 | J66: 2 | K66: =VLOOKUP(J66,Key!$E$2:$F$9,2,FALSE) -> Work | L66: KABEREBERE | M66: ISINGIRO | N66: UGA | O66: 3 | P66: 2 | Q66: =VLOOKUP(P66,Key!$E$2:$F$9,2,FALSE) -> Work | R66: =K66&"-"&Q66 -> Work-Work | S66: 9 | T66: 1 | U66: 1 | V66: 11 | Y66: Y
B67: 0.46944444 | C67: UAW 605E | D67: 8 | E67: 2 | F67: MBARARA TOWN | G67: MBARARA | H67: UGA | I67: 3 | J67: 2 | K67: =VLOOKUP(J67,Key!$E$2:$F$9,2,FALSE) -> Work | L67: NYABTUNDA | M67: ISINGIRO | N67: UGA | O67: 11 | P67: 2 | Q67: =VLOOKUP(P67,Key!$E$2:$F$9,2,FALSE) -> Work | R67: =K67&"-"&Q67 -> Work-Work | S67: 40 | T67: 0.3 | U67: 1 | V67: 10 | W67: 3 | X67: 4500000 | Y67: Y
B68: 0.475 | C68: UAG 359Q | D68: 8 | E68: 2 | F68: MBARARA TOWN | G68: MBARARA | H68: UGA | I68: 3 | J68: 2 | K68: =VLOOKUP(J68,Key!$E$2:$F$9,2,FALSE) -> Work | L68: NTUGAMO | M68: ISINGIRO | N68: UGA | O68: 11 | P68: 4 | Q68: =VLOOKUP(P68,Key!$E$2:$F$9,2,FALSE) -> Commercial | R68: =K68&"-"&Q68 -> Work-Commercial | S68: 120 | T68: 6 | U68: 4 | V68: 10 | W68: 3.5 | X68: 2500000 | Y68: Y
B69: 0.47916667 | C69: UAW 483P | D69: 7 | E69: 2 | F69: KASHENYI | G69: ISINGIRO | H69: UGA | I69: 3 | J69: 2 | K69: =VLOOKUP(J69,Key!$E$2:$F$9,2,FALSE) -> Work | L69: KABEREBERE | M69: ISINGIRO | N69: UGA | O69: 3 | P69: 2 | Q69: =VLOOKUP(P69,Key!$E$2:$F$9,2,FALSE) -> Work | R69: =K69&"-"&Q69 -> Work-Work | S69: 3 | T69: 0.2 | U69: 2 | Y69: Y
B70: 0.48194444 | C70: UAH 978E | D70: 1 | E70: 2 | F70: MBARARA TOWN | G70: MBARARA | H70: UGA | I70: 2 | J70: 2 | K70: =VLOOKUP(J70,Key!$E$2:$F$9,2,FALSE) -> Work | L70: KIRUMBA | M70: ISINGIRO | N70: UGA | O70: 9 | P70: 4 | Q70: =VLOOKUP(P70,Key!$E$2:$F$9,2,FALSE) -> Commercial | R70: =K70&"-"&Q70 -> Work-Commercial | S70: 20 | T70: 0.5 | U70: 3 | Y70: Y
B71: 0.48472222 | C71: 020731 LG | D71: 11 | E71: 1 | F71: RWABIKONA | G71: MBARARA | H71: UGA | I71: 2 | J71: 2 | K71: =VLOOKUP(J71,Key!$E$2:$F$9,2,FALSE) -> Work | L71: KABEREBERE | M71: ISINGIRO | N71: UGA | O71: 2 | P71: 2 | Q71: =VLOOKUP(P71,Key!$E$2:$F$9,2,FALSE) -> Work | R71: =K71&"-"&Q71 -> Work-Work | S71: 10 | T71: 0.4 | U71: 3 | Y71: Y
B72: 0.48819444 | C72: UAJ 927Q | D72: 5 | E72: 6 | F72: MBARARA TOWN | G72: MBARARA | H72: UGA | I72: 6 | J72: 2 | K72: =VLOOKUP(J72,Key!$E$2:$F$9,2,FALSE) -> Work | L72: ISINGIRO TOWN | M72: ISINGIRO | N72: UGA | O72: 4 | P72: 3 | Q72: =VLOOKUP(P72,Key!$E$2:$F$9,2,FALSE) -> Study | R72: =K72&"-"&Q72 -> Work-Study | S72: 20 | T72: 0.7 | U72: 3 | Y72: Y
B73: 0.49236111 | C73: UER 066J | D73: 11 | E73: 1 | F73: KATETE | G73: MBARARA | H73: UGA | I73: 8 | J73: 2 | K73: =VLOOKUP(J73,Key!$E$2:$F$9,2,FALSE) -> Work | L73: MUKIHORGO | M73: ISINGIRO | N73: UGA | O73: 1 | P73: 1 | Q73: =VLOOKUP(P73,Key!$E$2:$F$9,2,FALSE) -> Home | R73: =K73&"-"&Q73 -> Work-Home | S73: 5 | T73: 0.1 | U73: 3 | Y73: Y
B74: 0.49513889 | C74: UBD 553T | D74: 7 | E74: 3 | F74: MBARARA TOWN | G74: MBARARA | H74: UGA | I74: 3 | J74: 2 | K74: =VLOOKUP(J74,Key!$E$2:$F$9,2,FALSE) -> Work | L74: NTUGAMO | M74: ISINGIRO | N74: UGA | O74: 11 | P74: 2 | Q74: =VLOOKUP(P74,Key!$E$2:$F$9,2,FALSE) -> Work | R74: =K74&"-"&Q74 -> Work-Work | S74: 120 | T74: 4 | U74: 1 | V74: 10 | W74: 1.5 | X74: 3000000 | Y74: Y
B75: 0.50694444 | C75: UEV 601Z | D75: 11 | E75: 1 | F75: MILO | G75: ISINGIRO | H75: UGA | I75: 8 | J75: 2 | K75: =VLOOKUP(J75,Key!$E$2:$F$9,2,FALSE) -> Work | L75: MILO | M75: ISINGIRO | N75: UGA | O75: 8 | P75: 2 | Q75: =VLOOKUP(P75,Key!$E$2:$F$9,2,FALSE) -> Work | R75: =K75&"-"&Q75 -> Work-Work | S75: 1 | T75: 0 | U75: 2 | Y75: Y
B76: 12;25 | C76: UED 860S | D76: 11 | E76: 1 | F76: MBARARA TOWN | G76: MBARARA | H76: UGA | I76: 1 | J76: 1 | K76: =VLOOKUP(J76,Key!$E$2:$F$9,2,FALSE) -> Home | L76: KABINGO | M76: ISINGIRO | N76: UGA | O76: 16 | P76: 8 | Q76: =VLOOKUP(P76,Key!$E$2:$F$9,2,FALSE) -> Others | R76: =K76&"-"&Q76 -> Home-Others | S76: 24 | T76: 0.7 | U76: 2 | Y76: Y
B77: 0.52777778 | C77: UBD 899R | D77: 8 | E77: 2 | F77: MBARARA TOWN | G77: MBARARA | H77: UGA | I77: 3 | J77: 2 | K77: =VLOOKUP(J77,Key!$E$2:$F$9,2,FALSE) -> Work | L77: TANZANIA TOWN | M77: TANZANIA | N77: UGA | O77: 3 | P77: 2 | Q77: =VLOOKUP(P77,Key!$E$2:$F$9,2,FALSE) -> Work | R77: =K77&"-"&Q77 -> Work-Work | S77: 300 | T77: 6 | U77: 3 | V77: 3 | W77: 3.5 | X77: 1000000 | Y77: Y
B78: 0.53472222 | C78: UAL 941M | D78: 4 | E78: 8 | F78: MBARARA TOWN | G78: MBARARA | H78: UGA | I78: 5 | J78: 7 | K78: =VLOOKUP(J78,Key!$E$2:$F$9,2,FALSE) -> Hospital | L78: KIKAGATI | M78: ISINGIRO | N78: UGA | O78: 5 | P78: 7 | Q78: =VLOOKUP(P78,Key!$E$2:$F$9,2,FALSE) -> Hospital | R78: =K78&"-"&Q78 -> Hospital-Hospital | S78: 40 | T78: 2 | U78: 3 | Y78: Y
B79: 0.67013889 | C79: UAP 916D | D79: 4 | E79: 6 | F79: MBARARA TOWN | G79: MBARARA | H79: UGA | I79: 6 | J79: 2 | K79: =VLOOKUP(J79,Key!$E$2:$F$9,2,FALSE) -> Work | L79: KABINGO | M79: ISINGIRO | N79: UGA | O79: 6 | P79: 2 | Q79: =VLOOKUP(P79,Key!$E$2:$F$9,2,FALSE) -> Work | R79: =K79&"-"&Q79 -> Work-Work | S79: 24 | T79: 1 | Y79: Y
B80: 0.67361111 | C80: UAU 790R | D80: 1 | E80: 4 | F80: MBARARA TOWN | G80: MBARARA | H80: UGA | I80: 1 | J80: 1 | K80: =VLOOKUP(J80,Key!$E$2:$F$9,2,FALSE) -> Home | L80: RUGAGA | M80: ISINGIRO | N80: UGA | O80: 1 | P80: 1 | Q80: =VLOOKUP(P80,Key!$E$2:$F$9,2,FALSE) -> Home | R80: =K80&"-"&Q80 -> Home-Home | S80: 20 | T80: 1 | U80: 3 | Y80: Y
B81: 0.67916667 | C81: UBE 717D | D81: 2 | E81: 4 | F81: NYAMITANGA | G81: MBARARA | H81: UGA | I81: 5 | J81: 7 | K81: =VLOOKUP(J81,Key!$E$2:$F$9,2,FALSE) -> Hospital | L81: MILO | M81: ISINGIRO | N81: UGA | O81: 5 | P81: 7 | Q81: =VLOOKUP(P81,Key!$E$2:$F$9,2,FALSE) -> Hospital | R81: =K81&"-"&Q81 -> Hospital-Hospital | S81: 9 | T81: 0.1 | U81: 4 | Y81: Y
B82: 0.68402778 | C82: UEU 270K | D82: 11 | E82: 2 | F82: MBARARA TOWN | G82: MBARARA | H82: UGA | I82: 8 | J82: 2 | K82: =VLOOKUP(J82,Key!$E$2:$F$9,2,FALSE) -> Work | L82: NYAMINDO | M82: ISINGIRO | N82: UGA | O82: 1 | P82: 1 | Q82: =VLOOKUP(P82,Key!$E$2:$F$9,2,FALSE) -> Home | R82: =K82&"-"&Q82 -> Work-Home | S82: 10 | T82: 0.7 | U82: 3 | Y82: Y
B83: 0.6875 | C83: UAM 860F | D83: 7 | E83: 3 | F83: MBARARA TOWN | G83: MBARARA | H83: UGA | I83: 3 | J83: 2 | K83: =VLOOKUP(J83,Key!$E$2:$F$9,2,FALSE) -> Work | L83: KABEREBERE | M83: ISINGIRO | N83: UGA | O83: 1 | P83: 1 | Q83: =VLOOKUP(P83,Key!$E$2:$F$9,2,FALSE) -> Home | R83: =K83&"-"&Q83 -> Work-Home | S83: 10 | T83: 0.5 | U83: 4 | V83: 4 | W83: 0.5 | X83: 300000 | Y83: Y
B84: 0.70763889 | C84: UAP 692V | D84: 1 | E84: 6 | F84: RUMBIDI | G84: MBARARA | H84: UGA | I84: 5 | J84: 7 | K84: =VLOOKUP(J84,Key!$E$2:$F$9,2,FALSE) -> Hospital | L84: KABINGO | M84: ISINGIRO | N84: UGA | O84: 5 | P84: 7 | Q84: =VLOOKUP(P84,Key!$E$2:$F$9,2,FALSE) -> Hospital | R84: =K84&"-"&Q84 -> Hospital-Hospital | S84: 24 | T84: 0.5 | U84: 1 | Y84: Y
B85: 0.71180556 | C85: UET 903C | D85: 11 | E85: 1 | F85: MBARARA TOWN | G85: MBARARA | H85: UGA | I85: 8 | J85: 2 | K85: =VLOOKUP(J85,Key!$E$2:$F$9,2,FALSE) -> Work | L85: KABEREBERE | M85: ISINGIRO | N85: UGA | O85: 1 | P85: 1 | Q85: =VLOOKUP(P85,Key!$E$2:$F$9,2,FALSE) -> Home | R85: =K85&"-"&Q85 -> Work-Home | S85: 14 | T85: 0.5 | U85: 1 | Y85: Y
B86: 0.71527778 | C86: UDX 414E | D86: 11 | E86: 1 | F86: MBARARA TOWN | G86: MBARARA | H86: UGA | I86: 8 | J86: 2 | K86: =VLOOKUP(J86,Key!$E$2:$F$9,2,FALSE) -> Work | L86: KAHENDA | M86: ISINGIRO | N86: UGA | O86: 1 | P86: 1 | Q86: =VLOOKUP(P86,Key!$E$2:$F$9,2,FALSE) -> Home | R86: =K86&"-"&Q86 -> Work-Home | S86: 24 | T86: 0.5 | U86: 3 | Y86: Y
B87: 0.71875 | C87: UEY 812V | D87: 11 | E87: 1 | F87: KASHENYI | G87: ISINGIRO | H87: UGA | I87: 8 | J87: 2 | K87: =VLOOKUP(J87,Key!$E$2:$F$9,2,FALSE) -> Work | L87: KASHENYI | M87: ISINGIRO | N87: UGA | O87: 8 | P87: 2 | Q87: =VLOOKUP(P87,Key!$E$2:$F$9,2,FALSE) -> Work | R87: =K87&"-"&Q87 -> Work-Work | S87: 1 | T87: 0.2 | U87: 3 | Y87: Y
B88: 0.72152778 | C88: UAY 290P | D88: 7 | E88: 3 | F88: MBARARA TOWN | G88: MBARARA | H88: UGA | I88: 3 | J88: 2 | K88: =VLOOKUP(J88,Key!$E$2:$F$9,2,FALSE) -> Work | L88: KABEREBERE | M88: ISINGIRO | N88: UGA | O88: 10 | P88: 2 | Q88: =VLOOKUP(P88,Key!$E$2:$F$9,2,FALSE) -> Work | R88: =K88&"-"&Q88 -> Work-Work | S88: 30 | T88: 0.5 | U88: 1 | V88: 4 | Y88: Y
B89: 0.72569444 | C89: UED 131B | D89: 11 | E89: 1 | F89: MBARARA TOWN | G89: MBARARA | H89: UGA | I89: 4 | J89: 3 | K89: =VLOOKUP(J89,Key!$E$2:$F$9,2,FALSE) -> Study | L89: KABEREBERE | M89: ISINGIRO | N89: UGA | O89: 4 | P89: 3 | Q89: =VLOOKUP(P89,Key!$E$2:$F$9,2,FALSE) -> Study | R89: =K89&"-"&Q89 -> Study-Study | S89: 20 | U89: 1 | Y89: Y
B90: 0.73611111 | C90: UAP 456R | D90: 7 | E90: 1 | F90: MBARARA TOWN | G90: MBARARA | H90: UGA | I90: 3 | J90: 2 | K90: =VLOOKUP(J90,Key!$E$2:$F$9,2,FALSE) -> Work | L90: MASHA | M90: ISINGIRO | N90: UGA | O90: 1 | P90: 1 | Q90: =VLOOKUP(P90,Key!$E$2:$F$9,2,FALSE) -> Home | R90: =K90&"-"&Q90 -> Work-Home | S90: 3 | T90: 0.5 | U90: 3 | Y90: Y
B91: 0.73958333 | C91: UEW 140Y | D91: 11 | E91: 1 | F91: KASHENYI | G91: ISINGIRO | H91: UGA | I91: 1 | J91: 1 | K91: =VLOOKUP(J91,Key!$E$2:$F$9,2,FALSE) -> Home | L91: KASHENYI | M91: ISINGIRO | N91: UGA | O91: 1 | P91: 1 | Q91: =VLOOKUP(P91,Key!$E$2:$F$9,2,FALSE) -> Home | R91: =K91&"-"&Q91 -> Home-Home | S91: 1 | T91: 0.2 | U91: 3 | Y91: Y
B92: 0.74583333 | C92: UAZ 832M | D92: 7 | E92: 2 | F92: MBARARA TOWN | G92: MBARARA | H92: UGA | I92: 9 | J92: 2 | K92: =VLOOKUP(J92,Key!$E$2:$F$9,2,FALSE) -> Work | L92: KABINGO | M92: ISINGIRO | N92: UGA | O92: 3 | P92: 2 | Q92: =VLOOKUP(P92,Key!$E$2:$F$9,2,FALSE) -> Work | R92: =K92&"-"&Q92 -> Work-Work | S92: 20 | T92: 1 | U92: 3 | V92: 2 | Y92: Y
B93: 0.75555556 | C93: UAH 095G | D93: 1 | E93: 2 | F93: MBARARA TOWN | G93: MBARARA | H93: UGA | I93: 2 | J93: 2 | K93: =VLOOKUP(J93,Key!$E$2:$F$9,2,FALSE) -> Work | L93: KABEREBERE | M93: ISINGIRO | N93: UGA | O93: 1 | P93: 1 | Q93: =VLOOKUP(P93,Key!$E$2:$F$9,2,FALSE) -> Home | R93: =K93&"-"&Q93 -> Work-Home | S93: 8 | T93: 0.3 | U93: 3 | Y93: Y
B94: 0.76041667 | C94: UAG 781V | D94: 1 | E94: 1 | F94: MBARARA TOWN | G94: MBARARA | H94: UGA | I94: 2 | J94: 2 | K94: =VLOOKUP(J94,Key!$E$2:$F$9,2,FALSE) -> Work | L94: MASHA | M94: ISINGIRO | N94: UGA | O94: 9 | P94: 4 | Q94: =VLOOKUP(P94,Key!$E$2:$F$9,2,FALSE) -> Commercial | R94: =K94&"-"&Q94 -> Work-Commercial | S94: 10 | T94: 0.7 | U94: 3 | Y94: Y
B95: 0.76597222 | C95: UAQ 987V | D95: 1 | E95: 3 | F95: MBARARA TOWN | G95: MBARARA | H95: UGA | I95: 4 | J95: 3 | K95: =VLOOKUP(J95,Key!$E$2:$F$9,2,FALSE) -> Study | L95: RWAKIRURI | M95: ISINGIRO | N95: UGA | O95: 1 | P95: 1 | Q95: =VLOOKUP(P95,Key!$E$2:$F$9,2,FALSE) -> Home | R95: =K95&"-"&Q95 -> Study-Home | S95: 5 | T95: 0.5 | U95: 1 | Y95: Y
B96: 0.76944444 | C96: UEQ 286C | D96: 11 | E96: 1 | F96: MBARARA TOWN | G96: MBARARA | H96: UGA | I96: 8 | J96: 2 | K96: =VLOOKUP(J96,Key!$E$2:$F$9,2,FALSE) -> Work | L96: KABEREBERE | M96: ISINGIRO | N96: UGA | O96: 8 | P96: 2 | Q96: =VLOOKUP(P96,Key!$E$2:$F$9,2,FALSE) -> Work | R96: =K96&"-"&Q96 -> Work-Work | S96: 8 | T96: 0.3 | U96: 4 | Y96: Y
B97: 0.77013889 | C97: UBA 386H | D97: 1 | E97: 3 | F97: MBARARA TOWN | G97: MBARARA | H97: UGA | I97: 1 | J97: 1 | K97: =VLOOKUP(J97,Key!$E$2:$F$9,2,FALSE) -> Home | L97: BUTENGA | M97: ISINGIRO | N97: UGA | O97: 1 | P97: 1 | Q97: =VLOOKUP(P97,Key!$E$2:$F$9,2,FALSE) -> Home | R97: =K97&"-"&Q97 -> Home-Home | S97: 50 | T97: 1 | U97: 2 | Y97: Y
B98: 0.77430556 | C98: UAU 906Q | D98: 4 | E98: 6 | F98: MBARARA TOWN | G98: MBARARA | H98: UGA | I98: 6 | J98: 2 | K98: =VLOOKUP(J98,Key!$E$2:$F$9,2,FALSE) -> Work | L98: KABINGO | M98: ISINGIRO | N98: UGA | O98: 6 | P98: 2 | Q98: =VLOOKUP(P98,Key!$E$2:$F$9,2,FALSE) -> Work | R98: =K98&"-"&Q98 -> Work-Work | S98: 20 | T98: 1 | U98: 3 | Y98: Y
B99: 0.77986111 | C99: UAM 736L | D99: 8 | E99: 2 | F99: MBARARA TOWN | G99: MBARARA | H99: UGA | I99: 11 | J99: 2 | K99: =VLOOKUP(J99,Key!$E$2:$F$9,2,FALSE) -> Work | L99: RUGANJA | M99: ISINGIRO | N99: UGA | O99: 2 | P99: 2 | Q99: =VLOOKUP(P99,Key!$E$2:$F$9,2,FALSE) -> Work | R99: =K99&"-"&Q99 -> Work-Work | S99: 40 | T99: 2 | U99: 2 | W99: 4 | X99: 7000000 | Y99: Y
B100: 0.78472222 | C100: UAS 278H | D100: 7 | E100: 1 | F100: MBARARA TOWN | G100: MBARARA | H100: UGA | I100: 3 | J100: 4 | K100: =VLOOKUP(J100,Key!$E$2:$F$9,2,FALSE) -> Commercial | L100: KABINGO | M100: ISINGIRO | N100: UGA | O100: 1 | P100: 1 | Q100: =VLOOKUP(P100,Key!$E$2:$F$9,2,FALSE) -> Home | R100: =K100&"-"&Q100 -> Commercial-Home | S100: 35 | T100: 1 | U100: 2 | V100: 4 | Y100: Y
B101: 0.7875 | C101: UAT 936E | D101: 7 | E101: 2 | F101: MBARARA TOWN | G101: MBARARA | H101: UGA | I101: 3 | J101: 2 | K101: =VLOOKUP(J101,Key!$E$2:$F$9,2,FALSE) -> Work | L101: NYAKITUNDA | M101: ISINGIRO | N101: UGA | O101: 1 | P101: 1 | Q101: =VLOOKUP(P101,Key!$E$2:$F$9,2,FALSE) -> Home | R101: =K101&"-"&Q101 -> Work-Home | S101: 30 | T101: 1 | U101: 3 | V101: 4 | Y101: Y
B102: 0.79166667 | C102: UDV 335J | D102: 11 | E102: 1 | F102: MBARARA TOWN | G102: MBARARA | H102: UGA | I102: 1 | J102: 1 | K102: =VLOOKUP(J102,Key!$E$2:$F$9,2,FALSE) -> Home | L102: MABONA | M102: ISINGIRO | N102: UGA | O102: 1 | P102: 1 | Q102: =VLOOKUP(P102,Key!$E$2:$F$9,2,FALSE) -> Home | R102: =K102&"-"&Q102 -> Home-Home | S102: 25 | U102: 0.8 | V102: 3 | Y102: Y
...

Sheet RSI FORM
B1: Feasibility Study and Detailed Design of Kampala - Jinja Highway
B2: Roadside OD Interview Survey
B4: Date: | C4: 40465 | D4: Interviewer: | G4: Survey Station: | H4: Bweyogerere | J4: Direction: | K4: Bweyogerere-Kireka | L4: Coded By: | N4: Chkd By:
B7: Time Period | C7: Veh_Type | D7: Veh_Other | E7: Occupancy | F7: Origin_Address | H7: Origin_Purpose | I7: Origin_other | J7: Destination_Address | L7: Destination_Purpose | M7: Destination_Other | N7: Origin_Zone | O7: Dest_Zone | P7: WTP
F8: Village/Town | G8: City/Country | J8: Village/Town | K8: City/Country
B9: AM | C9: 3 | E9: 2 | F9: Entebbe | G9: Kla, Ug | H9: 1 | J9: Kla | K9: Kla, Ug | L9: 2 | N9: Blank | O9: Blank | P9: Yes | Q9: 3000
B10: AM | C10: 1 | E10: 1 | F10: Kiwanga | G10: Kla, Ug | H10: 1 | J10: Kla | K10: Kla, Ug | L10: 2 | N10: Blank | O10: Blank | P10: Yes | Q10: 2000
B11: AM | E11: 1 | F11: Bukoto | G11: Kla, Ug | H11: 3 | J11: Kla | K11: Kla, Ug | L11: 1 | N11: Blank | O11: Blank
B12: AM
B13: AM
B14: AM
B15: AM
B16: AM
B17: AM
B18: AM
B19: AM
B20: AM
B21: AM
B22: AM
B23: AM
... B53: AM

Sheet 28.10 ISINGIRO-MBARARA
B1: Consultancy services for Preparation of Expressway Development Master Plan (EDMP) for Uganda
B2: Roadside OD Interview Survey
B4: Date: | C4: ='28.10 MBARARA-ISINGIRO'!C4 -> 28.10.2019 | E4: Road Name: | F4: ='28.10 MBARARA-ISINGIRO'!F4:G4 -> MBARARA-NTUNGAMO ROAD | I4: Direction From: | L4: ISINGIRO | N4: Interviewers: | O4: MUSINGUZI JONNAN, AMOS A | V4: Supervisor: | W4: ='28.10 MBARARA-ISINGIRO'!W4 -> MIREMBE RUTH | Y4: Coded By: | Z4: ='28.10 MBARARA-ISINGIRO'!Z4 -> AJOK EMILY | AA4: Chkd By: | AB4: ='28.10 MBARARA-ISINGIRO'!AB4 -> 0
I5: Direction To: | L5: MBARARA
B7: Time | C7: Veh_Reg_No. | D7: Veh_Type | E7: No. Occupants | F7: Origin_Address | I7: Origin_Establish | J7: Origin_Purpose | K7: Origin-Purpose Desc | L7: Destination_Address | O7: Destination_Establish | P7: Destination_Purpose | Q7: Destination_Purpose Desc | R7: Journey_Purpose | S7: Approx_Distance (Km) | T7: Approx_Journey Time (Hrs) | U7: Trip_Frequency | V7: GOODS VEHICLES ONLY | Y7: Would You Use Xpressways? | Z7: Pay How Much? (UGX) | AA7: Origin_Zone | AB7: Dest_Zone
F8: Village or Town | G8: District | H8: Country | L8: Village or Town | M8: District | N8: Country | V8: Goods_Type | W8: Goods_Quantity (Ton) | X8: Goods_Value (UGXm)
B9: 0.87222222 | C9: UEC 015A | D9: 11 | E9: 1 | F9: KABEREBERE | G9: ISINGIRO | H9: UG | I9: 8 | J9: 2 | K9: =VLOOKUP(J9,Key!$E$2:$F$9,2,FALSE) -> Work | L9: MULUTI | M9: MBARARA | N9: UG | O9: 8 | P9: 2 | Q9: =VLOOKUP(P9,Key!$E$2:$F$9,2,FALSE) -> Work | R9: =K9&"-"&Q9 -> Work-Work | S9: 7 | T9: 0.1 | U9: 2 | Y9: Y
B10: 0.87847222 | C10: UAR 149Q | D10: 1 | E10: 3 | F10: KIKAGATI | G10: ISINGIRO | H10: UG | I10: 2 | J10: 2 | K10: =VLOOKUP(J10,Key!$E$2:$F$9,2,FALSE) -> Work | L10: MBARARA TOWN | M10: MBARARA | N10: UG | O10: 1 | P10: 1 | Q10: =VLOOKUP(P10,Key!$E$2:$F$9,2,FALSE) -> Home | R10: =K10&"-"&Q10 -> Work-Home | S10: 37 | T10: 0.7 | U10: 2 | Y10: Y
B11: 0.88194444 | C11: UBB 896G | D11: 1 | E11: 2 | F11: KASENYI | G11: ISINGIRO | H11: UG | I11: 1 | J11: 1 | K11: =VLOOKUP(J11,Key!$E$2:$F$9,2,FALSE) -> Home | L11: MBARARA TOWN | M11: MBARARA | N11: UG | O11: 11 | P11: 2 | Q11: =VLOOKUP(P11,Key!$E$2:$F$9,2,FALSE) -> Work | R11: =K11&"-"&Q11 -> Home-Work | S11: 3 | T11: 0.2 | U11: 2 | Y11: Y
B12: 0.8875 | C12: UAZ 327Q | D12: 8 | E12: 1 | F12: KABINGO | G12: ISINGIRO | H12: UG | I12: 3 | J12: 2 | K12: =VLOOKUP(J12,Key!$E$2:$F$9,2,FALSE) -> Work | L12: MBARARA TOWN | M12: MBARARA | N12: UG | O12: 1 | P12: 1 | Q12: =VLOOKUP(P12,Key!$E$2:$F$9,2,FALSE) -> Home | R12: =K12&"-"&Q12 -> Work-Home | S12: 68 | T12: 1 | U12: 2 | V12: 11 | Y12: Y
B13: 0.89236111 | C13: UAW 916S | D13: 1 | E13: 2 | F13: KASENYI | G13: ISINGIRO | H13: UG | I13: 1 | J13: 1 | K13: =VLOOKUP(J13,Key!$E$2:$F$9,2,FALSE) -> Home | L13: MBARARA TOWN | M13: MBARARA | N13: UG | O13: 5 | P13: 7 | Q13: =VLOOKUP(P13,Key!$E$2:$F$9,2,FALSE) -> Hospital | R13: =K13&"-"&Q13 -> Home-Hospital | S13: 3 | T13: 0.1 | U13: 3 | Y13: Y
B14: 0.89722222 | C14: UDL 077W | D14: 11 | E14: 2 | F14: KABARE | G14: ISINGIRO | H14: UG | I14: 8 | J14: 2 | K14: =VLOOKUP(J14,Key!$E$2:$F$9,2,FALSE) -> Work | L14: MBARARA TOWN | M14: MBARARA | N14: UG | O14: 8 | P14: 2 | Q14: =VLOOKUP(P14,Key!$E$2:$F$9,2,FALSE) -> Work | R14: =K14&"-"&Q14 -> Work-Work | S14: 5 | T14: 0.2 | U14: 2 | Y14: Y
B15: 0.90138889 | C15: UAW 174K | D15: 1 | E15: 1 | F15: KABEREBERE | G15: ISINGIRO | H15: UG | I15: 2 | J15: 2 | K15: =VLOOKUP(J15,Key!$E$2:$F$9,2,FALSE) -> Work | L15: MBARARA TOWN | M15: MBARARA | N15: UG | O15: 1 | P15: 1 | Q15: =VLOOKUP(P15,Key!$E$2:$F$9,2,FALSE) -> Home | R15: =K15&"-"&Q15 -> Work-Home | S15: 11 | T15: 0.2 | U15: 2 | Y15: Y
B16: 0.90972222 | C16: UAB 105R | D16: 2 | E16: 1 | F16: RWENZIRINGIRO | G16: ISINGIRO | H16: UG | I16: 4 | J16: 3 | K16: =VLOOKUP(J16,Key!$E$2:$F$9,2,FALSE) -> Study | L16: MBARARA TOWN | M16: MBARARA | N16: UG | O16: 1 | P16: 1 | Q16: =VLOOKUP(P16,Key!$E$2:$F$9,2,FALSE) -> Home | R16: =K16&"-"&Q16 -> Study-Home | S16: 4 | T16: 0.3 | U16: 3 | Y16: Y
B17: 0.91875 | C17: UAW 625J | D17: 8 | E17: 3 | F17: KABEREBERE | G17: ISINGIRO | H17: UG | I17: 16 | J17: 8 | K17: =VLOOKUP(J17,Key!$E$2:$F$9,2,FALSE) -> Others | L17: KAMPALA TOWN | M17: KAMPALA | N17: UG | O17: 11 | P17: 4 | Q17: =VLOOKUP(P17,Key!$E$2:$F$9,2,FALSE) -> Commercial | R17: =K17&"-"&Q17 -> Others-Commercial | S17: 423 | T17: 4 | U17: 3 | V17: 1 | X17: 5 | Y17: Y
B18: 0.92847222 | C18: UAX 154K | D18: 2 | E18: 3 | F18: ISINGIRO TOWN | G18: ISINGIRO | H18: UG | I18: 1 | J18: 1 | K18: =VLOOKUP(J18,Key!$E$2:$F$9,2,FALSE) -> Home | L18: MBARARA TOWN | M18: MBARARA | N18: UG | O18: 5 | P18: 7 | Q18: =VLOOKUP(P18,Key!$E$2:$F$9,2,FALSE) -> Hospital | R18: =K18&"-"&Q18 -> Home-Hospital | S18: 31 | T18: 1.5 | U18: 4 | Y18: Y
B19: 0.93333333 | C19: UAD 009J | D19: 3 | E19: 1 | F19: MUKIHOGO | G19: ISINGIRO | H19: UG | I19: 1 | J19: 1 | K19: =VLOOKUP(J19,Key!$E$2:$F$9,2,FALSE) -> Home | L19: NYAMITANGA | M19: MBARARA | N19: UG | O19: 7 | P19: 4 | Q19: =VLOOKUP(P19,Key!$E$2:$F$9,2,FALSE) -> Commercial | R19: =K19&"-"&Q19 -> Home-Commercial | S19: 7 | T19: 0.3 | U19: 3 | V19: 11 | Y19: Y
B20: 0.94444444 | C20: UBE 857V | D20: 8 | E20: 2 | F20: ISINGIRO TOWN | G20: ISINGIRO | H20: UG | I20: 9 | J20: 4 | K20: =VLOOKUP(J20,Key!$E$2:$F$9,2,FALSE) -> Commercial | L20: KAMPALA TOWN | M20: KAMPALA | N20: UG | O20: 11 | P20: 4 | Q20: =VLOOKUP(P20,Key!$E$2:$F$9,2,FALSE) -> Commercial | R20: =K20&"-"&Q20 -> Commercial-Commercial | S20: 31 | T20: 2 | U20: 4 | V20: 1 | Y20: Y
B21: 0.97152778 | C21: UEV 394M | D21: 11 | E21: 23 | F21: KABARE | G21: ISINGIRO | H21: UG | I21: 8 | J21: 2 | K21: =VLOOKUP(J21,Key!$E$2:$F$9,2,FALSE) -> Work | L21: KASENYI | M21: ISINGIRO | N21: UG | O21: 8 | P21: 2 | Q21: =VLOOKUP(P21,Key!$E$2:$F$9,2,FALSE) -> Work | R21: =K21&"-"&Q21 -> Work-Work | S21: 1 | T21: 0.1 | U21: 2 | Y21: Y
B22: 0.98611111 | C22: UAX 281A | D22: 1 | E22: 1 | F22: NAKIVALE | G22: ISINGIRO | H22: UG | I22: 2 | J22: 2 | K22: =VLOOKUP(J22,Key!$E$2:$F$9,2,FALSE) -> Work | L22: MBARARA TOWN | M22: MBARARA | N22: UG | O22: 1 | P22: 1 | Q22: =VLOOKUP(P22,Key!$E$2:$F$9,2,FALSE) -> Home | R22: =K22&"-"&Q22 -> Work-Home | T22: 1 | U22: 2 | Y22: Y
B23: 0.99791667 | C23: UBF 657C | D23: 8 | E23: 1 | F23: ISINGIRO TOWN | G23: ISINGIRO | H23: UG | I23: 16 | J23: 2 | K23: =VLOOKUP(J23,Key!$E$2:$F$9,2,FALSE) -> Work | L23: MBARARA TOWN | M23: MBARARA | N23: UG | O23: 11 | P23: 4 | Q23: =VLOOKUP(P23,Key!$E$2:$F$9,2,FALSE) -> Commercial | R23: =K23&"-"&Q23 -> Work-Commercial | S23: 32 | T23: 1 | U23: 3 | V23: 1 | Y23: Y
B24: 0.50694444 | C24: UAG 088V | D24: 2 | E24: 1 | F24: KITALE | G24: ISINGIRO | H24: UG | I24: 3 | J24: 2 | K24: =VLOOKUP(J24,Key!$E$2:$F$9,2,FALSE) -> Work | L24: MBARARA TOWN | M24: MBARARA | N24: UG | O24: 1 | P24: 1 | Q24: =VLOOKUP(P24,Key!$E$2:$F$9,2,FALSE) -> Home | R24: =K24&"-"&Q24 -> Work-Home | T24: 0.5 | U24: 2 | Y24: Y
B25: 0.52152778 | C25: UEL 270F | D25: 11 | E25: 1 | F25: KASENYI | G25: ISINGIRO | H25: UG | I25: 8 | J25: 2 | K25: =VLOOKUP(J25,Key!$E$2:$F$9,2,FALSE) -> Work | L25: NYAMITANGA | M25: MBARARA | N25: UG | O25: 1 | P25: 1 | Q25: =VLOOKUP(P25,Key!$E$2:$F$9,2,FALSE) -> Home | R25: =K25&"-"&Q25 -> Work-Home | S25: 4 | T25: 0.2 | U25: 1 | Y25: Y
B26: 0.53472222 | C26: UAL 191G | D26: 2 | E26: 1 | F26: RWENZIRINGIRO | G26: ISINGIRO | H26: UG | I26: 9 | J26: 4 | K26: =VLOOKUP(J26,Key!$E$2:$F$9,2,FALSE) -> Commercial | L26: KATETE | M26: MBARARA | N26: UG | O26: 1 | P26: 1 | Q26: =VLOOKUP(P26,Key!$E$2:$F$9,2,FALSE) -> Home | R26: =K26&"-"&Q26 -> Commercial-Home | S26: 10 | T26: 0.6 | U26: 3 | Y26: Y
B27: 0.053472222 | C27: UBA 900T | D27: 8 | E27: 4 | F27: KABEREBERE | G27: ISINGIRO | H27: UG | I27: 9 | J27: 2 | K27: =VLOOKUP(J27,Key!$E$2:$F$9,2,FALSE) -> Work | L27: KAMPALA TOWN | M27: KAMPALA | N27: UG | O27: 11 | P27: 4 | Q27: =VLOOKUP(P27,Key!$E$2:$F$9,2,FALSE) -> Commercial | R27: =K27&"-"&Q27 -> Work-Commercial | S27: 340 | T27: 3.5 | U27: 4 | V27: 11 | W27: 12 | X27: 7 | Y27: Y
B28: 0.059027778 | C28: UAS 525D | D28: 1 | E28: 3 | F28: MASHA | G28: ISINGIRO | H28: UG | I28: 1 | J28: 1 | K28: =VLOOKUP(J28,Key!$E$2:$F$9,2,FALSE) -> Home | L28: MBARARA TOWN | M28: MBARARA | N28: UG | O28: 5 | P28: 7 | Q28: =VLOOKUP(P28,Key!$E$2:$F$9,2,FALSE) -> Hospital | R28: =K28&"-"&Q28 -> Home-Hospital | S28: 15 | T28: 0.5 | U28: 4 | Y28: Y
B29: 0.068055556 | C29: UAW 418D | D29: 8 | E29: 5 | F29: KIRUMBA | G29: ISINGIRO | H29: UG | I29: 15 | J29: 4 | K29: =VLOOKUP(J29,Key!$E$2:$F$9,2,FALSE) -> Commercial | L29: MBARARA TOWN | M29: MBARARA | N29: UG | O29: 10 | P29: 2 | Q29: =VLOOKUP(P29,Key!$E$2:$F$9,2,FALSE) -> Work | R29: =K29&"-"&Q29 -> Commercial-Work | S29: 18 | T29: 0.5 | U29: 1 | V29: 4 | Y29: Y
B30: 0.073611111 | C30: UET 055R | D30: 11 | E30: 1 | F30: KABEREBERE | G30: ISINGIRO | H30: UG | I30: 8 | J30: 2 | K30: =VLOOKUP(J30,Key!$E$2:$F$9,2,FALSE) -> Work | L30: MBARARA TOWN | M30: MBARARA | N30: UG | O30: 1 | P30: 1 | Q30: =VLOOKUP(P30,Key!$E$2:$F$9,2,FALSE) -> Home | R30: =K30&"-"&Q30 -> Work-Home | S30: 13 | T30: 0.8 | U30: 1 | Y30: Y
B31: 0.0875 | C31: UBF 400C | D31: 8 | E31: 1 | F31: KABINGO | G31: ISINGIRO | H31: UG | I31: 3 | J31: 4 | K31: =VLOOKUP(J31,Key!$E$2:$F$9,2,FALSE) -> Commercial | L31: KATETE | M31: MBARARA | N31: UG | O31: 1 | P31: 1 | Q31: =VLOOKUP(P31,Key!$E$2:$F$9,2,FALSE) -> Home | R31: =K31&"-"&Q31 -> Commercial-Home | S31: 20 | T31: 1 | U31: 2 | Y31: Y
B32: 0.10486111 | C32: UAV 904G | D32: 8 | E32: 2 | F32: ISINGIRO TOWN | G32: ISINGIRO | H32: UG | I32: 9 | J32: 4 | K32: =VLOOKUP(J32,Key!$E$2:$F$9,2,FALSE) -> Commercial | L32: NATETE | M32: KAMPALA | N32: UG | O32: 11 | P32: 4 | Q32: =VLOOKUP(P32,Key!$E$2:$F$9,2,FALSE) -> Commercial | R32: =K32&"-"&Q32 -> Commercial-Commercial | S32: 398 | T32: 3 | U32: 3 | V32: 1 | Y32: Y
B33: 0.17291667 | C33: UBE 752Z | D33: 1 | E33: 1 | F33: KABARE | G33: ISINGIRO | H33: UG | I33: 1 | J33: 1 | K33: =VLOOKUP(J33,Key!$E$2:$F$9,2,FALSE) -> Home | L33: MBARARA TOWN | M33: MBARARA | N33: UG | O33: 2 | P33: 2 | Q33: =VLOOKUP(P33,Key!$E$2:$F$9,2,FALSE) -> Work | R33: =K33&"-"&Q33 -> Home-Work | S33: 5 | T33: 0.2 | U33: 2 | Y33: Y
B34: 0.19305556 | C34: UAF 932V | D34: 1 | E34: 2 | F34: NAKIVALE | G34: ISINGIRO | H34: UG | I34: 1 | J34: 1 | K34: =VLOOKUP(J34,Key!$E$2:$F$9,2,FALSE) -> Home | L34: MBARARA TOWN | M34: MBARARA | N34: UG | O34: 2 | P34: 2 | Q34: =VLOOKUP(P34,Key!$E$2:$F$9,2,FALSE) -> Work | R34: Home-Work | S34: 7 | T34: 0.3 | U34: 2 | Y34: Y
B35: 0.19791667 | C35: UAW 751V | D35: 1 | E35: 1 | F35: KASENYI | G35: ISINGIRO | H35: UG | I35: 2 | J35: 2 | K35: =VLOOKUP(J35,Key!$E$2:$F$9,2,FALSE) -> Work | L35: MBARARA TOWN | M35: MBARARA | N35: UG | O35: 1 | P35: 1 | Q35: =VLOOKUP(P35,Key!$E$2:$F$9,2,FALSE) -> Home | R35: =K35&"-"&Q35 -> Work-Home | S35: 4 | T35: 0.2 | U35: 3 | Y35: Y
B36: 0.20277778 | C36: UBB 441U | D36: 7 | E36: 2 | F36: MUKIHOGO | G36: ISINGIRO | H36: UG | I36: 1 | J36: 1 | K36: =VLOOKUP(J36,Key!$E$2:$F$9,2,FALSE) -> Home | L36: NYAMITANGA | M36: MBARARA | N36: UG | O36: 15 | P36: 4 | Q36: =VLOOKUP(P36,Key!$E$2:$F$9,2,FALSE) -> Commercial | R36: =K36&"-"&Q36 -> Home-Commercial | T36: 0.3 | U36: 2 | V36: 11 | Y36: Y
B37: 0.20763889 | C37: UES 799S | D37: 11 | E37: 1 | F37: KASENYI | G37: ISINGIRO | H37: UG | I37: 1 | J37: 1 | K37: =VLOOKUP(J37,Key!$E$2:$F$9,2,FALSE) -> Home | L37: MBARARA TOWN | M37: MBARARA | N37: UG | O37: 8 | P37: 2 | Q37: =VLOOKUP(P37,Key!$E$2:$F$9,2,FALSE) -> Work | R37: =K37&"-"&Q37 -> Home-Work | S37: 3 | T37: 0.1 | U37: 2 | Y37: Y
B38: 0.25555556 | C38: UAV 253M | D38: 1 | E38: 1 | F38: KABEREBERE | G38: ISINGIRO | H38: UG | I38: 1 | J38: 1 | K38: Home | L38: MBARARA TOWN | M38: MBARARA | N38: UG | O38: 2 | P38: 2 | Q38: =VLOOKUP(P38,Key!$E$2:$F$9,2,FALSE) -> Work | R38: =K38&"-"&Q38 -> Home-Work | S38: 13 | T38: 0.5 | U38: 2 | Y38: Y
B39: 0.275 | C39: UAS 580J | D39: 1 | E39: 2 | F39: ISINGIRO TOWN | G39: ISINGIRO | H39: UG | I39: 1 | J39: 1 | K39: =VLOOKUP(J39,Key!$E$2:$F$9,2,FALSE) -> Home | L39: MBARARA TOWN | M39: MBARARA | N39: UG | O39: 2 | P39: 2 | Q39: =VLOOKUP(P39,Key!$E$2:$F$9,2,FALSE) -> Work | R39: =K39&"-"&Q39 -> Home-Work | S39: 31 | T39: 2 | U39: 3 | Y39: Y
B40: 0.27986111 | C40: UAV 323C | D40: 4 | E40: 18 | F40: ISINGIRO TOWN | G40: ISINGIRO | H40: UG | I40: 1 | J40: 1 | K40: =VLOOKUP(J40,Key!$E$2:$F$9,2,FALSE) -> Home | L40: MBARARA TOWN | M40: MBARARA | N40: UG | O40: 4 | P40: 3 | Q40: =VLOOKUP(P40,Key!$E$2:$F$9,2,FALSE) -> Study | R40: =K40&"-"&Q40 -> Home-Study | S40: 31 | T40: 1.5 | U40: 2 | Y40: Y
B41: 0.28611111 | C41: UAW 051P | D41: 1 | E41: 3 | F41: NAKIVALE | G41: ISINGIRO | H41: UG | I41: 1 | J41: 1 | K41: =VLOOKUP(J41,Key!$E$2:$F$9,2,FALSE) -> Home | L41: MBARARA TOWN | M41: MBARARA | N41: UG | O41: 4 | P41: 3 | Q41: =VLOOKUP(P41,Key!$E$2:$F$9,2,FALSE) -> Study | R41: =K41&"-"&Q41 -> Home-Study | S41: 7 | T41: 0.2 | U41: 2 | Y41: Y
B42: 0.31805556 | C42: UAT 889P | D42: 1 | E42: 1 | F42: RWENZIRINGIRO | G42: ISINGIRO | H42: UG | I42: 4 | J42: 2 | K42: =VLOOKUP(J42,Key!$E$2:$F$9,2,FALSE) -> Work | L42: KASENYI | M42: MBARARA | N42: UG | O42: 1 | P42: 1 | Q42: =VLOOKUP(P42,Key!$E$2:$F$9,2,FALSE) -> Home | R42: =K42&"-"&Q42 -> Work-Home | S42: 3 | T42: 0.1 | U42: 2 | Y42: Y
B43: 0.32083333 | C43: UAX 316M | D43: 1 | E43: 2 | F43: ISINGIRO TOWN | G43: ISINGIRO | H43: UG | I43: 4 | J43: 3 | K43: =VLOOKUP(J43,Key!$E$2:$F$9,2,FALSE) -> Study | L43: MBARARA TOWN | M43: MBARARA | N43: UG | O43: 1 | P43: 1 | Q43: =VLOOKUP(P43,Key!$E$2:$F$9,2,FALSE) -> Home | R43: =K43&"-"&Q43 -> Study-Home | S43: 31 | T43: 1 | U43: 3 | Y43: Y
B44: 0.32361111 | C44: UAX 011J | D44: 2 | E44: 4 | F44: ISINGIRO TOWN | G44: ISINGIRO | H44: UG | I44: 16 | J44: 8 | K44: =VLOOKUP(J44,Key!$E$2:$F$9,2,FALSE) -> Others | L44: MBARARA TOWN | M44: MBARARA | N44: UG | O44: 16 | P44: 8 | Q44: =VLOOKUP(P44,Key!$E$2:$F$9,2,FALSE) -> Others | R44: =K44&"-"&Q44 -> Others-Others | S44: 34 | T44: 0.5 | U44: 4 | Y44: Y
B45: 0.32638889 | C45: UAR 016T | D45: 2 | E45: 1 | F45: KABARE | G45: ISINGIRO | H45: UG | I45: 1 | J45: 1 | K45: =VLOOKUP(J45,Key!$E$2:$F$9,2,FALSE) -> Home | L45: MBARARA TOWN | M45: MBARARA | N45: UG | O45: 4 | P45: 3 | Q45: =VLOOKUP(P45,Key!$E$2:$F$9,2,FALSE) -> Study | R45: =K45&"-"&Q45 -> Home-Study | S45: 5 | T45: 0.3 | U45: 2 | Y45: Y
B46: 0.33958333 | C46: UBC 856C | D46: 1 | E46: 1 | F46: ISINGIRO TOWN | G46: ISINGIRO | H46: UG | I46: 16 | J46: 8 | K46: =VLOOKUP(J46,Key!$E$2:$F$9,2,FALSE) -> Others | L46: MBARARA TOWN | M46: MBARARA | N46: UG | O46: 1 | P46: 1 | Q46: =VLOOKUP(P46,Key!$E$2:$F$9,2,FALSE) -> Home | R46: =K46&"-"&Q46 -> Others-Home | S46: 31 | T46: 0.6 | U46: 4 | Y46: Y
B47: 0.34236111 | C47: UAG 706J | D47: 3 | E47: 4 | F47: ISINGIRO TOWN | G47: ISINGIRO | H47: UG | I47: 1 | J47: 1 | K47: =VLOOKUP(J47,Key!$E$2:$F$9,2,FALSE) -> Home | L47: KAMPALA TOWN | M47: KAMPALA | N47: UG | O47: 16 | P47: 8 | Q47: =VLOOKUP(P47,Key!$E$2:$F$9,2,FALSE) -> Others | R47: =K47&"-"&Q47 -> Home-Others | S47: 352 | T47: 6 | U47: 5 | Y47: Y
B48: 0.34861111 | C48: UBD 186Z | D48: 1 | E48: 1 | F48: KABEREBERE | G48: ISINGIRO | H48: UG | I48: 1 | J48: 1 | K48: =VLOOKUP(J48,Key!$E$2:$F$9,2,FALSE) -> Home | L48: MBARARA TOWN | M48: MBARARA | N48: UG | O48: 2 | P48: 2 | Q48: =VLOOKUP(P48,Key!$E$2:$F$9,2,FALSE) -> Work | R48: =K48&"-"&Q48 -> Home-Work | S48: 13 | T48: 0.5 | U48: 2 | Y48: Y
B49: 0.35416667 | C49: UBD 483M | D49: 8 | E49: 2 | F49: ISINGIRO TOWN | G49: ISINGIRO | H49: UG | I49: 1 | J49: 1 | K49: =VLOOKUP(J49,Key!$E$2:$F$9,2,FALSE) -> Home | L49: MBARARA TOWN | M49: MBARARA | N49: UG | O49: 12 | P49: 2 | Q49: =VLOOKUP(P49,Key!$E$2:$F$9,2,FALSE) -> Work | R49: =K49&"-"&Q49 -> Home-Work | S49: 35 | T49: 2 | U49: 2 | V49: 11 | Y49: Y
B50: 0.36527778 | C50: UBA 363L | D50: 7 | E50: 2 | F50: KABEREBERE | G50: ISINGIRO | H50: UG | I50: 1 | J50: 1 | K50: =VLOOKUP(J50,Key!$E$2:$F$9,2,FALSE) -> Home | L50: MBARARA TOWN | M50: MBARARA | N50: UG | O50: 2 | P50: 2 | Q50: =VLOOKUP(P50,Key!$E$2:$F$9,2,FALSE) -> Work | R50: =K50&"-"&Q50 -> Home-Work | S50: 12 | T50: 0.3 | U50: 2 | V50: 11 | Y50: Y
B51: 0.37083333 | C51: T478 DBW | D51: 1 | E51: 2 | F51: KYERWA TOWN | G51: KYERWA | H51: UG | I51: 1 | J51: 1 | K51: =VLOOKUP(J51,Key!$E$2:$F$9,2,FALSE) -> Home | L51: MBARARA TOWN | M51: MBARARA | N51: UG | O51: 16 | P51: 8 | Q51: =VLOOKUP(P51,Key!$E$2:$F$9,2,FALSE) -> Others | R51: =K51&"-"&Q51 -> Home-Others | S51: 98 | T51: 1.5 | U51: 5 | Y51: Y
B52: 0.37916667 | C52: UBE 783N | D52: 4 | E52: 1 | F52: RWENZIRINGIRO | G52: ISINGIRO | H52: UG | I52: 4 | J52: 3 | K52: =VLOOKUP(J52,Key!$E$2:$F$9,2,FALSE) -> Study | L52: KITOMA | M52: MBARARA | N52: UG | O52: 16 | P52: 8 | Q52: =VLOOKUP(P52,Key!$E$2:$F$9,2,FALSE) -> Others | R52: =K52&"-"&Q52 -> Study-Others | S52: 11 | T52: 0.5 | U52: 4 | Y52: Y
B53: 0.38888889 | C53: UAU 409L | D53: 8 | E53: 2 | F53: KABEREBERE | G53: ISINGIRO | H53: UG | I53: 1 | J53: 1 | K53: =VLOOKUP(J53,Key!$E$2:$F$9,2,FALSE) -> Home | L53: MBARARA TOWN | M53: MBARARA | N53: UG | O53: 11 | P53: 2 | Q53: =VLOOKUP(P53,Key!$E$2:$F$9,2,FALSE) -> Work | R53: =K53&"-"&Q53 -> Home-Work | S53: 18 | T53: 0.4 | U53: 4 | V53: 1 | X53: 0.5 | Y53: Y
B54: 0.39583333 | C54: UAT 549N | D54: 7 | E54: 1 | F54: KASENYI | G54: ISINGIRO | H54: UG | I54: 1 | J54: 1 | K54: =VLOOKUP(J54,Key!$E$2:$F$9,2,FALSE) -> Home | L54: KASENYI | M54: ISINGIRO | N54: UG | O54: 15 | P54: 4 | Q54: =VLOOKUP(P54,Key!$E$2:$F$9,2,FALSE) -> Commercial | R54: =K54&"-"&Q54 -> Home-Commercial | S54: 1 | T54: 0 | U54: 2 | V54: 11 | Y54: Y
B55: 0.40416667 | C55: UAY 611P | D55: 7 | E55: 1 | F55: BUTENGA | G55: ISINGIRO | H55: UG | I55: 1 | J55: 1 | K55: =VLOOKUP(J55,Key!$E$2:$F$9,2,FALSE) -> Home | L55: MBARARA TOWN | M55: MBARARA | N55: UG | O55: 11 | P55: 2 | Q55: =VLOOKUP(P55,Key!$E$2:$F$9,2,FALSE) -> Work | R55: =K55&"-"&Q55 -> Home-Work | S55: 12 | T55: 0.8 | U55: 4 | V55: 9 | X55: 2 | Y55: Y
B56: 0.43402778 | C56: UBB 039H | D56: 8 | E56: 3 | F56: KABARE | G56: ISINGIRO | H56: UG | I56: 3 | J56: 4 | K56: =VLOOKUP(J56,Key!$E$2:$F$9,2,FALSE) -> Commercial | L56: MBARARA TOWN | M56: MBARARA | N56: UG | O56: 3 | P56: 4 | Q56: =VLOOKUP(P56,Key!$E$2:$F$9,2,FALSE) -> Commercial | R56: =K56&"-"&Q56 -> Commercial-Commercial | S56: 5 | T56: 0.2 | U56: 3 | V56: 11 | Y56: Y
B57: 0.44097222 | C57: UAX 127C | D57: 1 | E57: 2 | F57: KABEREBERE | G57: ISINGIRO | H57: UG | I57: 16 | J57: 8 | K57: =VLOOKUP(J57,Key!$E$2:$F$9,2,FALSE) -> Others | L57: MBARARA TOWN | M57: MBARARA | N57: UG | O57: 1 | P57: 1 | Q57: =VLOOKUP(P57,Key!$E$2:$F$9,2,FALSE) -> Home | R57: =K57&"-"&Q57 -> Others-Home | S57: 8 | T57: 0.3 | U57: 4 | Y57: Y
B58: 0.44444444 | C58: UBD 634Z | D58: 1 | E58: 2 | F58: ISINGIRO TOWN | G58: ISINGIRO | H58: UG | I58: 1 | J58: 1 | K58: =VLOOKUP(J58,Key!$E$2:$F$9,2,FALSE) -> Home | L58: MBARARA TOWN | M58: MBARARA | N58: UG | O58: 16 | P58: 8 | Q58: =VLOOKUP(P58,Key!$E$2:$F$9,2,FALSE) -> Others | R58: =K58&"-"&Q58 -> Home-Others | S58: 31 | T58: 2 | U58: 4 | Y58: Y
B59: 0.45972222 | C59: UBB 137Y | D59: 7 | E59: 1 | F59: RWENZIRINGIRO | G59: ISINGIRO | H59: UG | I59: 3 | J59: 4 | K59: =VLOOKUP(J59,Key!$E$2:$F$9,2,FALSE) -> Commercial | L59: MBARARA TOWN | M59: MBARARA | N59: UG | O59: 3 | P59: 4 | Q59: =VLOOKUP(P59,Key!$E$2:$F$9,2,FALSE) -> Commercial | R59: =K59&"-"&Q59 -> Commercial-Commercial | S59: 7 | T59: 0.3 | U59: 5 | V59: 11 | Y59: Y
B60: 0.46875 | C60: UAM 162J | D60: 1 | E60: 4 | F60: KIKAGATI | G60: ISINGIRO | H60: UG | I60: 2 | J60: 2 | K60: =VLOOKUP(J60,Key!$E$2:$F$9,2,FALSE) -> Work | L60: MBARARA TOWN | M60: MBARARA | N60: UG | O60: 2 | P60: 2 | Q60: =VLOOKUP(P60,Key!$E$2:$F$9,2,FALSE) -> Work | R60: =K60&"-"&Q60 -> Work-Work | S60: 35 | T60: 2 | U60: 3 | Y60: Y
B61: 0.47916667 | C61: UAX 125X | D61: 2 | E61: 2 | F61: KABARE | G61: ISINGIRO | H61: UG | I61: 1 | J61: 1 | K61: =VLOOKUP(J61,Key!$E$2:$F$9,2,FALSE) -> Home | L61: MBARARA TOWN | M61: MBARARA | N61: UG | O61: 2 | P61: 2 | Q61: =VLOOKUP(P61,Key!$E$2:$F$9,2,FALSE) -> Work | R61: =K61&"-"&Q61 -> Home-Work | S61: 7 | T61: 0.2 | U61: 2 | Y61: Y
B62: 0.50625 | C62: UAL 598E | D62: 1 | E62: 1 | F62: RWENZIRINGIRO | G62: ISINGIRO | H62: UG | I62: 4 | J62: 3 | K62: =VLOOKUP(J62,Key!$E$2:$F$9,2,FALSE) -> Study | L62: MBARARA TOWN | M62: MBARARA | N62: 2 | O62: 2 | P62: 5 | Q62: =VLOOKUP(P62,Key!$E$2:$F$9,2,FALSE) -> Tourism | R62: =K62&"-"&Q62 -> Study-Tourism | S62: 0.2 | T62: 6 | Y62: Y
B63: 0.51388889 | C63: UEH 183T | D63: 11 | E63: 1 | F63: BUTENGA | G63: ISINGIRO | H63: UG | I63: 1 | J63: 1 | K63: =VLOOKUP(J63,Key!$E$2:$F$9,2,FALSE) -> Home | L63: MBARARA TOWN | M63: MBARARA | N63: UG | O63: 16 | P63: 8 | Q63: =VLOOKUP(P63,Key!$E$2:$F$9,2,FALSE) -> Others | R63: =K63&"-"&Q63 -> Home-Others | S63: 12 | T63: 0.5 | U63: 2 | Y63: Y
B64: 0.52430556 | C64: UEL 103M | D64: 11 | E64: 1 | F64: KABEREBERE | G64: ISINGIRO | H64: UG | I64: 8 | J64: 2 | K64: =VLOOKUP(J64,Key!$E$2:$F$9,2,FALSE) -> Work | L64: MBARARA TOWN | M64: MBARARA | N64: UG | O64: 8 | P64: 2 | Q64: =VLOOKUP(P64,Key!$E$2:$F$9,2,FALSE) -> Work | R64: =K64&"-"&Q64 -> Work-Work | S64: 8 | T64: 0.3 | U64: 2 | Y64: Y
B65: 0.52916667 | C65: UAM 628V | D65: 7 | E65: 3 | F65: NYAMIYANZA | G65: ISINGIRO | H65: UG | I65: 7 | J65: 4 | K65: =VLOOKUP(J65,Key!$E$2:$F$9,2,FALSE) -> Commercial | L65: MBARARA TOWN | M65: MBARARA | N65: UG | O65: 11 | P65: 2 | Q65: =VLOOKUP(P65,Key!$E$2:$F$9,2,FALSE) -> Work | R65: =K65&"-"&Q65 -> Commercial-Work | S65: 10 | T65: 0.2 | U65: 10 | Y65: Y
B66: 0.53472222 | C66: UBE 323V | D66: 1 | E66: 1 | F66: BUTENGA | G66: ISINGIRO | H66: UG | I66: 1 | J66: 1 | K66: =VLOOKUP(J66,Key!$E$2:$F$9,2,FALSE) -> Home | L66: MBARARA TOWN | M66: MBARARA | N66: UG | O66: 16 | P66: 8 | Q66: =VLOOKUP(P66,Key!$E$2:$F$9,2,FALSE) -> Others | R66: =K66&"-"&Q66 -> Home-Others | S66: 80 | T66: 2 | U66: 2 | Y66: Y
B67: 0.53819444 | C67: UAZ 014U | D67: 8 | E67: 3 | F67: RWAKIRURI | G67: ISINGIRO | H67: UG | I67: 16 | J67: 8 | K67: =VLOOKUP(J67,Key!$E$2:$F$9,2,FALSE) -> Others | L67: MBARARA TOWN | M67: MBARARA | N67: UG | O67: 10 | P67: 2 | Q67: =VLOOKUP(P67,Key!$E$2:$F$9,2,FALSE) -> Work | R67: Others-Work | S67: 4 | T67: 0.3 | U67: 2 | V67: 12 | W67: 1 | Y67: Y
B68: 0.54166667 | C68: UAM 286F | D68: 3 | E68: 2 | F68: KABINGO | G68: ISINGIRO | H68: UG | I68: 11 | J68: 4 | K68: =VLOOKUP(J68,Key!$E$2:$F$9,2,FALSE) -> Commercial | L68: MBARARA TOWN | M68: MBARARA | N68: UG | O68: 11 | P68: 4 | Q68: =VLOOKUP(P68,Key!$E$2:$F$9,2,FALSE) -> Commercial | R68: =K68&"-"&Q68 -> Commercial-Commercial | T68: 0.3 | U68: 2 | V68: 10 | W68: 0.005 | X68: 2 | Y68: Y
B69: 0.54652778 | C69: UAV 851S | D69: 1 | E69: 1 | F69: KABINGO | G69: ISINGIRO | H69: UG | I69: 1 | J69: 1 | K69: =VLOOKUP(J69,Key!$E$2:$F$9,2,FALSE) -> Home | L69: MBARARA TOWN | M69: MBARARA | N69: UG | O69: 16 | P69: 8 | Q69: =VLOOKUP(P69,Key!$E$2:$F$9,2,FALSE) -> Others | R69: =K69&"-"&Q69 -> Home-Others | S69: 20 | T69: 0.7 | U69: 2 | Y69: Y
B70: 0.57986111 | C70: UBB 087Z | D70: 8 | E70: 2 | F70: KABINGO | G70: ISINGIRO | H70: UG | I70: 13 | J70: 4 | K70: =VLOOKUP(J70,Key!$E$2:$F$9,2,FALSE) -> Commercial | L70: MBARARA TOWN | M70: MBARARA | N70: UG | O70: 13 | P70: 4 | Q70: =VLOOKUP(P70,Key!$E$2:$F$9,2,FALSE) -> Commercial | R70: =K70&"-"&Q70 -> Commercial-Commercial | S70: 8 | T70: 0.3 | U70: 4 | V70: 7 | W70: 0.06 | Y70: Y
B71: 0.59027778 | C71: UAL 955M | D71: 1 | E71: 2 | F71: ISINGIRO TOWN | G71: ISINGIRO | H71: UG | I71: 1 | J71: 1 | K71: =VLOOKUP(J71,Key!$E$2:$F$9,2,FALSE) -> Home | L71: KAMPALA TOWN | M71: KAMPALA | N71: UG | O71: 4 | P71: 3 | Q71: =VLOOKUP(P71,Key!$E$2:$F$9,2,FALSE) -> Study | R71: =K71&"-"&Q71 -> Home-Study | S71: 300 | T71: 4 | U71: 4 | Y71: Y
B72: 0.59583333 | C72: UAU 097F | D72: 3 | E72: 2 | F72: ISINGIRO TOWN | G72: ISINGIRO | H72: UG | I72: 1 | J72: 1 | K72: =VLOOKUP(J72,Key!$E$2:$F$9,2,FALSE) -> Home | L72: MBARARA TOWN | M72: MBARARA | N72: UG | O72: 2 | P72: 2 | Q72: =VLOOKUP(P72,Key!$E$2:$F$9,2,FALSE) -> Work | R72: =K72&"-"&Q72 -> Home-Work | S72: 32 | T72: 2 | U72: 2 | Y72: Y
B73: 0.66666667 | C73: UAH 948D | D73: 3 | E73: 2 | F73: KABEREBERE | G73: ISINGIRO | H73: UG | I73: 1 | J73: 1 | K73: =VLOOKUP(J73,Key!$E$2:$F$9,2,FALSE) -> Home | L73: MBARARA TOWN | M73: MBARARA | N73: UG | O73: 5 | P73: 7 | Q73: =VLOOKUP(P73,Key!$E$2:$F$9,2,FALSE) -> Hospital | R73: =K73&"-"&Q73 -> Home-Hospital | S73: 13 | T73: 0.2 | U73: 3 | Y73: Y
B74: 0.67361111 | C74: UAT 656N | D74: 1 | E74: 2 | F74: KABARE | G74: ISINGIRO | H74: UG | I74: 4 | J74: 3 | K74: =VLOOKUP(J74,Key!$E$2:$F$9,2,FALSE) -> Study | L74: MBARARA TOWN | M74: MBARARA | N74: UG | O74: 1 | P74: 1 | Q74: =VLOOKUP(P74,Key!$E$2:$F$9,2,FALSE) -> Home | R74: =K74&"-"&Q74 -> Study-Home | S74: 3 | T74: 0.1 | U74: 3 | Y74: Y
B75: 0.67847222 | C75: UBF 669U | D75: 1 | E75: 1 | F75: RWENZIRINGIRO | G75: ISINGIRO | H75: UG | I75: 3 | J75: 4 | K75: =VLOOKUP(J75,Key!$E$2:$F$9,2,FALSE) -> Commercial | L75: MBARARA TOWN | M75: MBARARA | N75: UG | O75: 1 | P75: 1 | Q75: =VLOOKUP(P75,Key!$E$2:$F$9,2,FALSE) -> Home | R75: =K75&"-"&Q75 -> Commercial-Home | S75: 10 | T75: 0.1 | U75: 2 | Y75: Y
B76: 0.68263889 | C76: UAV 238K | D76: 7 | E76: 2 | F76: RWENZIRINGIRO | G76: ISINGIRO | H76: UG | I76: 3 | J76: 4 | K76: =VLOOKUP(J76,Key!$E$2:$F$9,2,FALSE) -> Commercial | L76: MBARARA TOWN | M76: MBARARA | N76: UG | O76: 11 | P76: 2 | Q76: =VLOOKUP(P76,Key!$E$2:$F$9,2,FALSE) -> Work | R76: =K76&"-"&Q76 -> Commercial-Work | S76: 7 | T76: 0.3 | U76: 2 | V76: 10 | W76: 0.05 | X76: 1 | Y76: Y
B77: 0.6875 | C77: UDY 391M | D77: 11 | E77: 1 | F77: KABEREBERE | G77: ISINGIRO | H77: UG | I77: 8 | J77: 2 | K77: =VLOOKUP(J77,Key!$E$2:$F$9,2,FALSE) -> Work | L77: MBARARA TOWN | M77: MBARARA | N77: UG | O77: 8 | P77: 2 | Q77: =VLOOKUP(P77,Key!$E$2:$F$9,2,FALSE) -> Work | R77: =K77&"-"&Q77 -> Work-Work | S77: 11 | T77: 0.5 | U77: 2 | Y77: Y
B78: 0.69097222 | C78: UEH 445J | D78: 11 | E78: 1 | F78: KABEREBERE | G78: ISINGIRO | H78: UG | I78: 8 | J78: 2 | K78: =VLOOKUP(J78,Key!$E$2:$F$9,2,FALSE) -> Work | L78: NYAMITANGA | M78: MBARARA | N78: UG | O78: 8 | P78: 2 | Q78: =VLOOKUP(P78,Key!$E$2:$F$9,2,FALSE) -> Work | R78: =K78&"-"&Q78 -> Work-Work | S78: 11 | T78: 0.5 | U78: 2 | Y78: Y
B79: 0.69375 | C79: UET 415W | D79: 11 | E79: 1 | F79: KABINGO | G79: ISINGIRO | H79: UG | I79: 8 | J79: 2 | K79: =VLOOKUP(J79,Key!$E$2:$F$9,2,FALSE) -> Work | L79: MBARARA TOWN | M79: MBARARA | N79: UG | O79: 8 | P79: 2 | Q79: =VLOOKUP(P79,Key!$E$2:$F$9,2,FALSE) -> Work | R79: =K79&"-"&Q79 -> Work-Work | S79: 7 | T79: 0.3 | U79: 2 | Y79: Y
B80: 0.69583333 | C80: UBB 078P | D80: 1 | E80: 2 | F80: BUTENGA | G80: ISINGIRO | H80: UG | I80: 2 | J80: 2 | K80: =VLOOKUP(J80,Key!$E$2:$F$9,2,FALSE) -> Work | L80: MBARARA TOWN | M80: MBARARA | N80: UG | O80: 1 | P80: 1 | Q80: =VLOOKUP(P80,Key!$E$2:$F$9,2,FALSE) -> Home | R80: =K80&"-"&Q80 -> Work-Home | S80: 14 | T80: 0.5 | U80: 2 | Y80: Y
B81: 0.70208333 | C81: UAJ 623R | D81: 9 | E81: 3 | F81: ISINGIRO TOWN | G81: ISINGIRO | H81: UG | I81: 3 | J81: 4 | K81: =VLOOKUP(J81,Key!$E$2:$F$9,2,FALSE) -> Commercial | L81: MBARARA TOWN | M81: MBARARA | N81: UG | O81: 11 | P81: 2 | Q81: =VLOOKUP(P81,Key!$E$2:$F$9,2,FALSE) -> Work | R81: =K81&"-"&Q81 -> Commercial-Work | S81: 31 | T81: 1.5 | U81: 2 | V81: 10 | Y81: Y
B82: 0.70833333 | C82: UBB 142L | D82: 1 | E82: 1 | F82: KABARE | G82: ISINGIRO | H82: UG | I82: 2 | J82: 2 | K82: =VLOOKUP(J82,Key!$E$2:$F$9,2,FALSE) -> Work | L82: MBARARA TOWN | M82: MBARARA | N82: UG | O82: 1 | P82: 1 | Q82: =VLOOKUP(P82,Key!$E$2:$F$9,2,FALSE) -> Home | R82: =K82&"-"&Q82 -> Work-Home | S82: 4 | T82: 0.2 | U82: 2 | Y82: Y
B83: 0.71875 | C83: UAZ 281T | D83: 1 | E83: 1 | F83: KABEREBERE | G83: ISINGIRO | H83: UG | I83: 16 | J83: 2 | K83: =VLOOKUP(J83,Key!$E$2:$F$9,2,FALSE) -> Work | L83: MBARARA TOWN | M83: MBARARA | N83: UG | P83: 1 | Q83: 1 | R83: =K83&"-"&Q83 -> Work-1 | T83: 15 | U83: 0.5 | V83: 6 | Y83: Y
B84: 0.69791667 | C84: UAH 136G | D84: 1 | E84: 1 | F84: KABINGO | G84: ISINGIRO | H84: UG | I84: 1 | J84: 1 | K84: =VLOOKUP(J84,Key!$E$2:$F$9,2,FALSE) -> Home | L84: KABALE TOWN | M84: KABALE | N84: UG | O84: 2 | P84: 2 | Q84: =VLOOKUP(P84,Key!$E$2:$F$9,2,FALSE) -> Work | R84: =K84&"-"&Q84 -> Home-Work | S84: 200 | T84: 3 | U84: 5 | Y84: Y
B85: 0.67152778 | C85: UAK 170D | D85: 1 | E85: 2 | F85: KABEREBERE | G85: ISINGIRO | H85: UG | I85: 9 | J85: 2 | K85: =VLOOKUP(J85,Key!$E$2:$F$9,2,FALSE) -> Work | L85: MBARARA TOWN | M85: MBARARA | N85: UG | O85: 1 | P85: 1 | Q85: =VLOOKUP(P85,Key!$E$2:$F$9,2,FALSE) -> Home | R85: =K85&"-"&Q85 -> Work-Home | S85: 15 | T85: 0.8 | U85: 6 | Y85: Y
B86: 0.58333333 | C86: UEY 122Y | D86: 11 | E86: 1 | F86: KIHOGA | G86: ISINGIRO | H86: UG | I86: 1 | J86: 1 | K86: =VLOOKUP(J86,Key!$E$2:$F$9,2,FALSE) -> Home | L86: KATETE | M86: MBARARA | N86: UG | O86: 8 | P86: 2 | Q86: =VLOOKUP(P86,Key!$E$2:$F$9,2,FALSE) -> Work | R86: =K86&"-"&Q86 -> Home-Work | S86: 5 | T86: 0.2 | U86: 2 | Y86: Y
B87: 0.54166667 | C87: UAU 262A | D87: 1 | E87: 4 | F87: KASHENYI | G87: ISINGIRO | H87: UG | I87: 1 | J87: 1 | K87: Home | L87: MBARARA TOWN | M87: MBARARA | N87: UG | O87: 3 | P87: 2 | Q87: =VLOOKUP(P87,Key!$E$2:$F$9,2,FALSE) -> Work | R87: Work-Home | S87: 15 | T87: 0.5 | U87: 6 | Y87: Y
B88: 0.53958333 | C88: UAY 762V | D88: 2 | E88: 2 | F88: KYALUKUNDA | G88: ISINGIRO | H88: UG | I88: 1 | J88: 1 | K88: =VLOOKUP(J88,Key!$E$2:$F$9,2,FALSE) -> Home | L88: MBARARA TOWN | M88: MBARARA | N88: UG | O88: 4 | P88: 2 | Q88: =VLOOKUP(P88,Key!$E$2:$F$9,2,FALSE) -> Work | R88: =K88&"-"&Q88 -> Home-Work | S88: 25 | T88: 1 | U88: 1 | Y88: Y
B89: 0.53819444 | C89: UAP 461W | D89: 1 | E89: 4 | F89: KAZAHO | G89: ISINGIRO | H89: UG | I89: 1 | J89: 1 | K89: =VLOOKUP(J89,Key!$E$2:$F$9,2,FALSE) -> Home | L89: MBARARA TOWN | M89: MBARARA | N89: UG | O89: 2 | P89: 2 | Q89: =VLOOKUP(P89,Key!$E$2:$F$9,2,FALSE) -> Work | R89: =K89&"-"&Q89 -> Home-Work | S89: 32 | U89: 1 | Y89: Y
B90: 0.52777778 | C90: UEH 508E | D90: 11 | E90: 1 | F90: KIHOGA | G90: ISINGIRO | H90: UG | I90: 1 | J90: 1 | K90: =VLOOKUP(J90,Key!$E$2:$F$9,2,FALSE) -> Home | L90: KATETE | M90: MBARARA | N90: UG | O90: 8 | P90: 2 | Q90: =VLOOKUP(P90,Key!$E$2:$F$9,2,FALSE) -> Work | R90: =K90&"-"&Q90 -> Home-Work | S90: 5 | T90: 0.2 | U90: 2 | Y90: Y
B91: 0.525 | C91: UAZ 679A | D91: 1 | E91: 7 | F91: NAKIVALE | G91: ISINGIRO | H91: UG | I91: 1 | J91: 1 | K91: =VLOOKUP(J91,Key!$E$2:$F$9,2,FALSE) -> Home | L91: MBARARA TOWN | M91: MBARARA | N91: UG | O91: 6 | P91: 2 | Q91: =VLOOKUP(P91,Key!$E$2:$F$9,2,FALSE) -> Work | R91: =K91&"-"&Q91 -> Home-Work | S91: 37 | T91: 1.5 | U91: 1 | Y91: Y
B92: 0.48888889 | C92: UAT 867T | D92: 1 | E92: 1 | F92: RWENZIRINGIRO | G92: ISINGIRO | H92: UG | I92: 1 | J92: 1 | K92: =VLOOKUP(J92,Key!$E$2:$F$9,2,FALSE) -> Home | L92: RUKUNGIRI TOWN | M92: RUKUNGIRI | N92: UG | O92: 5 | P92: 7 | Q92: =VLOOKUP(P92,Key!$E$2:$F$9,2,FALSE) -> Hospital | R92: =K92&"-"&Q92 -> Home-Hospital | S92: 126 | T92: 2 | U92: 6 | Y92: Y
